Workbook

Sheet ACCESS
C3: ACCESSES TO DIFFERENT USERS
C4: ADMIN | D4: ESTABLISHMENT | E4: EMPLOYER | F4: EMPLOYEE | G4: AUDITOR
C5: (PROGRAMMING &EVERY MODIFICATION ) | D5: (FOR REGISTRATION LOG IN DETAILS) | E5: (ENTRIES UPLOAD) | F5: (PARTICULAR EMPLOYEE ONLY) | G5: (FINAL REGISTERS VIEW,PENDING& APRROVAL)
E6: Database sheet upload | F6: EMPLOYMENT CARDS
E7: Attendance sheet upload | F7: SERVICE CERTIFICATE
E8: BANK TRANSFER,EPF,ESI,PT Upload | F8: LEAVE REGISTER
F9: WAGE SLIPS
F10: PAYSLIP
F12: CHECK & SIGN

Sheet Workmen Reg
A1: FORM - XIII REGISTER OF WORKMEN EMPLOYED BY CONTRACTOR
A2: (Vide rule 75 of Contract labour(Regulation and Abolition) Central/A.P.{T.S.} Rules 1971)
A3: Name and address of Contractor: | F3: =Master!F5 -> GROTECH LANDSCAPE DEVELOPERS PVT. LTD.
F4: =Master!F6 -> 290/E, Khanapur Village, Gandipet Mandal, Ranga Reddy, Hyderabad-500075 T.S. | M4: =Master!AK10 -> Name and address of the Principle Employer | N4: =Master!AN10 -> INDIAN SCHOOL OF BUSINESS
A5: Nature and location of work: | F5: =Master!F8 -> GARDENING SERVICES&ISB HYDERABAD | N5: =Master!AN11 -> Opp.Infosys Limited,Gachibowli,Hyderabad
A8: Serial No. | B8: Name and surname of Workman | C8: Date of Birth | D8: Sex | E8: Father's /Husband Name | F8: Nature of Employment/ Designation | G8: Permanent Address-1 (H.No.&Street Name) | H8: Permanent Address-2 (Village Name) | I8: Permanent Address-3 (Mandal&District Name) | J8: Local Address-1 (H.No.&Street Name) | K8: Local Address-2 (Village Name) | L8: Local Address-3 (Mandal&District Name) | M8: Date of Commencement of Employment | N8: Signature or thumb impression of Workman | O8: Date of termination of Employment | P8: Reasons for termination | Q8: Remarks
A10: 1 | B10: 2 | C10: 3 | E10: 4 | F10: 5 | G10: 6 | J10: 7 | M10: 8 | N10: 9 | O10: 10 | P10: 11 | Q10: 12
A11: =[1]Master!A16 -> 1 | B11: VIKAS SHARMA | C11: 32739 | D11: Male | E11: Nandkishor sharma | F11: Horticulture Manager | G11: House No. A-168, Street no. 07, Near power house, | H11: Meet Nagar shahadra, | I11: North East, Delhi - 110094 | J11: Gachibowli Village | K11: Hyderabad | L11: Telangana State | M11: 43850 | O11: 31st May 2020 | P11: Resignation
A12: =[1]Master!A17 -> 2 | B12: ARJUN | C12: 31413 | D12: Male | E12: kallu | F12: Supervisor | G12: Village - Dharai | H12: Amethi | I12: Uttar pradesh - 229127 | J12: Gachibowli Village | K12: Hyderabad | L12: Telangana State | M12: 43850 | O12: 31st May 2020 | P12: Resignation
A13: =[1]Master!A18 -> 3 | B13: GAJAN SINGH | C13: 29587 | D13: Male | E13: Chandrapal singh | F13: Supervisor | G13: Village - Uncha gaon, Pikhani, | H13: Bulandshahr, | I13: Uttar pradesh - 202398 | J13: Gachibowli Village | K13: Hyderabad | L13: Telangana State | M13: 43850
A14: =[1]Master!A19 -> 4 | B14: GUDALA RUSHESHWAR SWAMY | C14: 31345 | D14: Male | E14: GUDALA KRISHANA MURTHY | F14: Supervisor | G14: House no. - 8-153 Kottapeta | H14: Gummaluru, west godavari | I14: Andhra pradesh - 534267 | J14: Gachibowli Village | K14: Hyderabad | L14: Telangana State | M14: 43850
A15: =[1]Master!A20 -> 5 | B15: GOLLA KRISHNAIAH | C15: 28/7/1984 | D15: Male | E15: G BHIMANNA | F15: Organic Waste | G15: House No. 11-106 krishna nagar, Atmakur mandal | H15: Amarchinta, Amerchinta, Mahbubnagar | I15: Andhra pradesh - 509130 | J15: Gachibowli Village | K15: Hyderabad | L15: Telangana State | M15: 43850 | O15: 21-01-2020 | P15: Resignation
A16: =[1]Master!A21 -> 6 | B16: KASALA NARSIMLU | C16: 21919 | D16: Male | E16: KASALA POCHAIAH | F16: Semi Skilled Gardner | G16: =[1]Master!F20 -> Semi Skilled Gardner | H16: Mwdharam,Medhak | I16: =[1]Master!H20 -> Mwdharam,Medhak | J16: Gachibowli Village | K16: Hyderabad | L16: Telangana State | M16: 43850
A17: =[1]Master!A22 -> 7 | B17: PITANI SATHYA NARAYANA | C17: 24473 | D17: Male | E17: P SURYANARAYANA | F17: Semi Skilled Gardner | G17: =[1]Master!F22 -> Semi Skilled Gardner | H17: Near church,serilingampally | I17: =[1]Master!H22 -> Near church,serilingampally | J17: Gachibowli Village | K17: Hyderabad | L17: Telangana State | M17: 43850
A18: =[1]Master!A23 -> 8 | B18: SANGOLLA ASHOK | C18: 21/6/1988 | D18: Male | E18: SANGOLLA ESWARAIAH | F18: Semi Skilled Gardner | G18: =[1]Master!F23 -> Semi Skilled Gardner | H18: Patancheru,Sulthanpur | I18: =[1]Master!H23 -> Patancheru,Sulthanpur | J18: Gachibowli Village | K18: Hyderabad | L18: Telangana State | M18: 43850
A19: =[1]Master!A24 -> 9 | B19: ASHOK LINGURAM GAIKWAD | C19: 29832 | D19: Male | E19: M LINGRAM | F19: Semi Skilled Gardner | G19: =[1]Master!F24 -> Semi Skilled Gardner | H19: Post-sawargaon,Mukhed,Nanded, | I19: =[1]Master!H24 -> Post-sawargaon,Mukhed,Nanded, | J19: Gachibowli Village | K19: Hyderabad | L19: Telangana State | M19: 43850
A20: =[1]Master!A25 -> 10 | B20: MADHUKAR KAMTAM | C20: 26665 | D20: Male | E20: KAMTAM KISHAN | F20: Semi Skilled Gardner | G20: =[1]Master!F25 -> Semi Skilled Gardner | H20: opp Hanuman temple | I20: =[1]Master!H25 -> opp Hanuman temple | J20: Gachibowli Village | K20: Hyderabad | L20: Telangana State | M20: 43850
A21: =[1]Master!A26 -> 11 | B21: BONIGA MARIYA KUMAR | C21: 24838 | D21: Male | E21: BONIGA PRASAD RAO | F21: Semi Skilled Gardner | G21: =[1]Master!F26 -> Semi Skilled Gardner | H21: Bapu nagar,Lingampally | I21: =[1]Master!H26 -> Bapu nagar,Lingampally | J21: Gachibowli Village | K21: Hyderabad | L21: Telangana State | M21: 43850 | O21: 31-01-2020 | P21: Resignation
A22: =[1]Master!A27 -> 12 | B22: Ningolla Raju | C22: 21/5/1975 | D22: Male | E22: ningolla pochaiah | F22: Semi Skilled Gardner | G22: =[1]Master!F27 -> Semi Skilled Gardner | H22: patancherusultanpur,medhak | I22: =[1]Master!H27 -> patancherusultanpur,medhak | J22: Gachibowli Village | K22: Hyderabad | L22: Telangana State | M22: 43850
A23: =[1]Master!A28 -> 13 | B23: Nagani pochaiah | C23: 24108 | D23: Male | E23: Nagani mallaiah | F23: Semi Skilled Gardner | G23: =[1]Master!F28 -> Semi Skilled Gardner | H23: Madaram,Medhak | I23: =[1]Master!H28 -> Madaram,Medhak | J23: Gachibowli Village | K23: Hyderabad | L23: Telangana State | M23: 43850
A24: =[1]Master!A29 -> 14 | B24: Mutholla Mallesh | C24: 36161 | D24: Male | E24: Mutholla balaiah | F24: Semi Skilled Gardner | G24: =[1]Master!F29 -> Semi Skilled Gardner | H24: sulthanpur,Medhak | I24: =[1]Master!H29 -> sulthanpur,Medhak | J24: Gachibowli Village | K24: Hyderabad | L24: Telangana State | M24: 43850
A25: =[1]Master!A30 -> 15 | B25: ALIJANA JAYARAMI REDDY | C25: 36439 | D25: Male | E25: ALIJANA OBULU REDDY | F25: Semi Skilled Gardner | G25: =[1]Master!F30 -> Semi Skilled Gardner | H25: Parnapalle,Cuddaph | I25: =[1]Master!H30 -> Parnapalle,Cuddaph | J25: Gachibowli Village | K25: Hyderabad | L25: Telangana State | M25: 43850
A26: =[1]Master!A31 -> 16 | B26: Kapil | C26: 36162 | D26: Male | E26: Ganesh lal | F26: Semi Skilled Gardner | G26: =[1]Master!F31 -> Semi Skilled Gardner | H26: reabarelli,Khamariya,naiani amethi | I26: =[1]Master!H31 -> reabarelli,Khamariya,naiani amethi | J26: Gachibowli Village | K26: Hyderabad | L26: Telangana State | M26: 43850
A27: =[1]Master!A32 -> 17 | B27: Bablu kumar | C27: 27948 | D27: Male | E27: Harilal | F27: Semi Skilled Gardner | G27: =[1]Master!F32 -> Semi Skilled Gardner | H27: Khamariya pure Kushal,amethi,nini | I27: =[1]Master!H32 -> Khamariya pure Kushal,amethi,nini | J27: Gachibowli Village | K27: Hyderabad | L27: Telangana State | M27: 43850
A28: =[1]Master!A33 -> 18 | B28: Pradeep kumar | C28: 16/9/1977 | D28: Male | E28: Jagdev | F28: Semi Skilled Gardner | G28: =[1]Master!F33 -> Semi Skilled Gardner | H28: Khamariya pure Kushal,amethi,nini | I28: =[1]Master!H33 -> Khamariya pure Kushal,amethi,nini | J28: Gachibowli Village | K28: Hyderabad | L28: Telangana State | M28: 43850
A29: =[1]Master!A34 -> 19 | B29: SHAIK KULSUM BEE | C29: 27762 | D29: Female | E29: SHAIK LALA | F29: Unskilled Gardner | G29: =[1]Master!F34 -> Unskilled Gardner | H29: KONDAPUR,SERILINGAMPALLY | I29: =[1]Master!H34 -> KONDAPUR,SERILINGAMPALLY | J29: Gachibowli Village | K29: Hyderabad | L29: Telangana State | M29: 43850
A30: =[1]Master!A35 -> 20 | B30: S GOWRI | C30: 33239 | D30: Female | E30: S SURYANARAYANA | F30: Unskilled Gardner | G30: =[1]Master!F35 -> Unskilled Gardner | H30: ,Gutkal,Ananthpur | I30: =[1]Master!H35 -> ,Gutkal,Ananthpur | J30: Gachibowli Village | K30: Hyderabad | L30: Telangana State | M30: 43850
A31: =[1]Master!A36 -> 21 | B31: FARZANA BEGUM | C31: 31048 | D31: Female | E31: SHAIK MASTAN WALI | F31: Unskilled Gardner | G31: =[1]Master!F36 -> Unskilled Gardner | H31: HAKEEMPET,THOLICHOUK,GOLUKOND | I31: =[1]Master!H36 -> HAKEEMPET,THOLICHOUK,GOLUKOND | J31: Gachibowli Village | K31: Hyderabad | L31: Telangana State | M31: 43850
A32: =[1]Master!A37 -> 22 | B32: MANAGALI SUHASINI | C32: 29221 | D32: Female | E32: MANGALI RAJU | F32: Unskilled Gardner | G32: =[1]Master!F37 -> Unskilled Gardner | H32: Medharam,medak | I32: =[1]Master!H37 -> Medharam,medak | J32: Gachibowli Village | K32: Hyderabad | L32: Telangana State | M32: 43850
A33: =[1]Master!A38 -> 23 | B33: KONA SUJATHA | C33: 25934 | D33: Female | E33: KONA SURYANARAYANA | F33: Unskilled Gardner | G33: =[1]Master!F38 -> Unskilled Gardner | H33: .guntkal,anthapuram | I33: =[1]Master!H38 -> .guntkal,anthapuram | J33: Gachibowli Village | K33: Hyderabad | L33: Telangana State | M33: 43850
A34: =[1]Master!A39 -> 24 | B34: GOLLA UMA | C34: 30562 | D34: Female | E34: GOLLA ONURU SWAMY | F34: Unskilled Gardner | G34: =[1]Master!F39 -> Unskilled Gardner | H34: GUTAL,ANANTHAPURM | I34: =[1]Master!H39 -> GUTAL,ANANTHAPURM | J34: Gachibowli Village | K34: Hyderabad | L34: Telangana State | M34: 43850
A35: =[1]Master!A40 -> 25 | B35: SINGARAM BHAGYAMMA | C35: 18/5/1964 | D35: Female | E35: SINGARAM NARSIMULU | F35: Unskilled Gardner | G35: =[1]Master!F40 -> Unskilled Gardner | H35: Krishnareddipet,Medak | I35: =[1]Master!H40 -> Krishnareddipet,Medak | J35: Gachibowli Village | K35: Hyderabad | L35: Telangana State | M35: 43850
A36: =[1]Master!A41 -> 26 | B36: BONIGA MARIYAMMA | C36: 32183 | D36: Female | E36: MARIYA KUMAR | F36: Unskilled Gardner | G36: =[1]Master!F41 -> Unskilled Gardner | H36: Bapu nagar,Lingampally, | I36: =[1]Master!H41 -> Bapu nagar,Lingampally, | J36: Gachibowli Village | K36: Hyderabad | L36: Telangana State | M36: 43850 | O36: 43860 | P36: Resignation
A37: =[1]Master!A42 -> 27 | B37: KODICHERLA INDIRAMMA | C37: 32418 | D37: Female | E37: BABAIAH | F37: Unskilled Gardner | G37: =[1]Master!F42 -> Unskilled Gardner | H37: Kondapoor,Serilinampally | I37: =[1]Master!H42 -> Kondapoor,Serilinampally | J37: Gachibowli Village | K37: Hyderabad | L37: Telangana State | M37: 43850
A38: =[1]Master!A43 -> 28 | B38: SANGOLLA LAVANYA | C38: 26299 | D38: Female | E38: SANGOLLA ASHOK | F38: Unskilled Gardner | G38: =[1]Master!F43 -> Unskilled Gardner | H38: Patancheru,Medak | I38: =[1]Master!H43 -> Patancheru,Medak | J38: Gachibowli Village | K38: Hyderabad | L38: Telangana State | M38: 43850
A39: =[1]Master!A44 -> 29 | B39: MANGALI LAVANYA | C39: 14/3/1985 | D39: Female | E39: MANGALI PANDU | F39: Unskilled Gardner | G39: =[1]Master!F44 -> Unskilled Gardner | H39: Madhavaram,madharam,Medhak | I39: =[1]Master!H44 -> Madhavaram,madharam,Medhak | J39: Gachibowli Village | K39: Hyderabad | L39: Telangana State | M39: 43850
A40: =[1]Master!A45 -> 30 | B40: MANGLI CHANDRAMMA | C40: 25/3/1969 | D40: Female | E40: MANGALI VENKATESH | F40: Unskilled Gardner | G40: House no. - 3-33 Madharam, | H40: MADHARAM,MEDHAK | I40: Andhra pradesh - 502319 | J40: Gachibowli Village | K40: Hyderabad | L40: Telangana State | M40: 43850
A41: =[1]Master!A46 -> 31 | B41: DASARI SUVARNA | C41: 32509 | D41: Female | E41: DASARI RAVINDAR | F41: Unskilled Gardner | G41: =[1]Master!F46 -> Unskilled Gardner | H41: NEAR GVT SCHOOL LINGAMPALLI, | I41: =[1]Master!H46 -> NEAR GVT SCHOOL LINGAMPALLI, | J41: Gachibowli Village | K41: Hyderabad | L41: Telangana State | M41: 43850
A42: =[1]Master!A47 -> 32 | B42: MARATHI CHANDRAKALA | C42: 31413 | D42: Female | E42: M ASHOKS | F42: Unskilled Gardner | G42: =[1]Master!F47 -> Unskilled Gardner | H42: patancheru,sultanpur,Medak | I42: =[1]Master!H47 -> patancheru,sultanpur,Medak | J42: Gachibowli Village | K42: Hyderabad | L42: Telangana State | M42: 43850
A43: =[1]Master!A48 -> 33 | B43: ANKAGALLA YADAMMA | C43: 32509 | D43: Female | E43: ANKAGALLA YADAGIRI | F43: Unskilled Gardner | G43: =[1]Master!F48 -> Unskilled Gardner | H43: Sulthanpoor,patancheru,Sulthanpur | I43: =[1]Master!H48 -> Sulthanpoor,patancheru,Sulthanpur | J43: Gachibowli Village | K43: Hyderabad | L43: Telangana State | M43: 43850
A44: =[1]Master!A49 -> 34 | B44: NINGAMMA | C44: 27395 | D44: Female | E44: RAMANNA | F44: Unskilled Gardner | G44: =[1]Master!F49 -> Unskilled Gardner | H44: Janatha colony,Bhalki,Bidar | I44: =[1]Master!H49 -> Janatha colony,Bhalki,Bidar | J44: Gachibowli Village | K44: Hyderabad | L44: Telangana State | M44: 43850
A45: =[1]Master!A50 -> 35 | B45: V AMBAMMA | C45: 20/11/1980 | D45: Female | E45: V YELLAIAH | F45: Unskilled Gardner | G45: =[1]Master!F50 -> Unskilled Gardner | H45: Narra basthi,Patancheru,Medak | I45: =[1]Master!H50 -> Narra basthi,Patancheru,Medak | J45: Gachibowli Village | K45: Hyderabad | L45: Telangana State | M45: 43850
A46: =[1]Master!A51 -> 36 | B46: PALLAPU LAXMI | C46: 21/3/1966 | D46: Female | E46: VENAKAIAH | F46: Unskilled Gardner | G46: =[1]Master!F51 -> Unskilled Gardner | H46: Nagdar,kalher,medak | I46: =[1]Master!H51 -> Nagdar,kalher,medak | J46: Gachibowli Village | K46: Hyderabad | L46: Telangana State | M46: 43850
A47: =[1]Master!A52 -> 37 | B47: Nagani laxmi | C47: 27395 | D47: Female | E47: Nagani pochaiah | F47: Unskilled Gardner | G47: =[1]Master!F52 -> Unskilled Gardner | H47: MADHARAM,MEDHAK | I47: =[1]Master!H52 -> MADHARAM,MEDHAK | J47: Gachibowli Village | K47: Hyderabad | L47: Telangana State | M47: 43850
A48: =[1]Master!A53 -> 38 | B48: Lingola amrutha | C48: 29545 | D48: Female | E48: Ningolla swamy | F48: Unskilled Gardner | G48: =[1]Master!F53 -> Unskilled Gardner | H48: patancheru,Sultanpur,medak | I48: =[1]Master!H53 -> patancheru,Sultanpur,medak | J48: Gachibowli Village | K48: Hyderabad | L48: Telangana State | M48: 43850
A49: =[1]Master!A54 -> 39 | B49: Kuduru satyamma | C49: 24187 | D49: Female | E49: NARAYANA | F49: Unskilled Gardner | G49: =[1]Master!F54 -> Unskilled Gardner | H49: mahabubnagar,dhrmapur-mndl, | I49: =[1]Master!H54 -> mahabubnagar,dhrmapur-mndl, | J49: Gachibowli Village | K49: Hyderabad | L49: Telangana State | M49: 43850
A50: 40 | B50: MANGALI LAXSHMI | C50: 28491 | D50: Female | E50: MANGALI PEDDA | F50: Unskilled Gardner | G50: H NO 2-36 | H50: MADHRAM MEDAK | I50: TS-502319 | J50: Gachibowli Village | K50: Hyderabad | L50: Telangana State | M50: 43862
A51: 41 | B51: NINGOLLA SANTHOSHA | C51: 28491 | D51: Female | E51: NINGOLLA RAJU | F51: Unskilled Gardner | G51: H NO 3-27/1 | H51: SULTANPUR | I51: TS-502319 | J51: Gachibowli Village | K51: Hyderabad | L51: Telangana State | M51: 43862
A52: 42 | B52: MUTHOLLA SUNEETA | C52: 28989 | D52: Female | E52: MUTHOLLA MALLESH | F52: Unskilled Gardner | G52: H NO 3-37 | H52: SULTANPUR | I52: TS-502319 | J52: Gachibowli Village | K52: Hyderabad | L52: Telangana State | M52: 43862
A53: 43 | B53: MUTHOLLA SUSHILA | C53: 26665 | D53: Female | E53: MUTHOLLA CHANDRA | F53: Unskilled Gardner | G53: H NO 3-26JANAKPET | H53: SULTANPUR | I53: TS-502319 | J53: Gachibowli Village | K53: Hyderabad | L53: Telangana State | M53: 43862
A54: 44 | B54: KUMARI KALAVATHI | C54: 27395 | D54: Female | E54: KUMARI KRISHNA | F54: Unskilled Gardner | G54: H NO 2-71\1 | H54: MADHARAM,MEDHAK | I54: TS-502319 | J54: Gachibowli Village | K54: Hyderabad | L54: Telangana State | M54: 43862
A55: 45 | B55: VADLA NAVEENA | C55: 29587 | D55: Female | E55: VADLA BHASHKAR | F55: Unskilled Gardner | G55: H NO 3-10 MADHRAM | H55: MADHRAM MEDAK | I55: TS-502319 | J55: Gachibowli Village | K55: Hyderabad | L55: Telangana State | M55: 43862
A56: 46 | B56: NAGANI SHANTAMA | C56: 25569 | D56: Female | E56: NANGANI VEERAIAH | F56: Unskilled Gardner | G56: H NO 3-44 | H56: MADHARAM,MEDHAK | I56: TS-502319 | J56: Gachibowli Village | K56: Hyderabad | L56: Telangana State | M56: 43864
A57: 47 | B57: GADDMIDI LAKSHMI | C57: 25934 | D57: Female | E57: GADDAMIDI RAGHU | F57: Unskilled Gardner | G57: H N0 3-95/1 | H57: MADHRAM MEDAK | I57: TS-502319 | J57: Gachibowli Village | K57: Hyderabad | L57: Telangana State | M57: 43865
A58: 48 | B58: GADDMIDI PARMEELA | C58: 30319 | D58: Female | E58: GADDAMIDI RAGHU | F58: Unskilled Gardner | G58: H NO 3-84 | H58: MADHRAM MEDAK | I58: TS-502319 | J58: Gachibowli Village | K58: Hyderabad | L58: Telangana State | M58: 43865 | O58: 43863 | P58: Resignation
A59: 49 | B59: GADDMIDI RAGHU | C59: 25934 | D59: Male | E59: GADDAMIDI BALAIAH | F59: Semi Skilled Gardner | G59: H NO 3-95/1 | H59: MADHRAM MEDAK | I59: TS-502319 | J59: Gachibowli Village | K59: Hyderabad | L59: Telangana State | M59: 43865
A60: 50 | B60: LAXMAN | C60: 35065 | D60: Male | E60: IRAPPA | F60: Semi Skilled Gardner | G60: H NO 1/22 KOLLUR | H60: BIDAR | I60: KR-585326 | J60: Gachibowli Village | K60: Hyderabad | L60: Telangana State | M60: 43881
A61: 51 | B61: VADLA JYOTHI | C61: 31413 | D61: Female | E61: VADLA SHANKAR CHARY | F61: Unskilled Gardner | G61: H NO 3-10 MADHRAM | H61: MADHRAM MEDAK | I61: TS-502319 | J61: Gachibowli Village | K61: Hyderabad | L61: Telangana State | M61: 43885
A62: 52 | B62: RUPESH CHANDRA | C62: 32705 | D62: Male | E62: RAJENDRA PRASAD | F62: HORTICULTURIST | G62: KALALGHATI | H62: KOTDWAR | I62: UK 246149 | J62: Gachibowli Village | K62: Hyderabad | L62: Telangana State | M62: 43892
A63: 53 | B63: BAKKANI MALLAIH | C63: 26299 | D63: Male | E63: BAKKANI HANMAIH | F63: Semi Skilled Gardner | G63: H NO1-56 | H63: SOMANGUTHI R.R | I63: TS-502319 | J63: Gachibowli Village | K63: Hyderabad | L63: Telangana State | M63: 43892
A64: 54 | B64: CHAKALI NARAYAN | C64: 29221 | D64: Male | E64: CHAKALI PETAIAH | F64: Semi Skilled Gardner | G64: H NO 3-7/1 | H64: MADHRAM MEDAK | I64: TS-502319 | J64: Gachibowli Village | K64: Hyderabad | L64: Telangana State | M64: 43893
A65: 55 | B65: MUTYALA POSHAVA | C65: 25934 | D65: Female | E65: MUTYALA BABU | F65: Unskilled Gardner | G65: H NO 65/1 | H65: MADHRAM MEDAK | I65: TS-502319 | J65: Gachibowli Village | K65: Hyderabad | L65: Telangana State | M65: 43894 | O65: 43898 | P65: Resignation
A66: 56 | B66: DUMPLA LAXMI | C66: 31048 | D66: Female | E66: DUMPALA DAKAIAH | F66: Unskilled Gardner | G66: H NO 2-11 | H66: NIJAMBAD | I66: TS-502319 | J66: Gachibowli Village | K66: Hyderabad | L66: Telangana State | M66: 43895 | O66: 43898 | P66: Resignation
A67: 57 | B67: KURMA DASHARATHA | C67: 29232 | D67: Male | E67: KURMA SATTAIH | F67: Semi Skilled Gardner | G67: H NO 3-46 | H67: MADHRAM MEDAK | I67: TS-502319 | J67: Gachibowli Village | K67: Hyderabad | L67: Telangana State | M67: 43896

Sheet Master
C3: EMPLOYEE DATABASE
C5: Name and address of Contractor: | F5: GROTECH LANDSCAPE DEVELOPERS PVT. LTD. | AF5: Name and address of Establishemnt in/ under which contract is carried on: | AN5: =F5 -> GROTECH LANDSCAPE DEVELOPERS PVT. LTD.
F6: 290/E, Khanapur Village, Gandipet Mandal, Ranga Reddy, Hyderabad-500075 T.S. | AN6: =F6 -> 290/E, Khanapur Village, Gandipet Mandal, Ranga Reddy, Hyderabad-500075 T.S.
C8: Nature and location of work: | F8: GARDENING SERVICES&ISB HYDERABAD
C10: Wage period: Monthly | F10: 44652 | AK10: Name and address of the Principle Employer | AN10: INDIAN SCHOOL OF BUSINESS
AN11: Opp.Infosys Limited,Gachibowli,Hyderabad
A14: Serial No | B14: Employee ID | C14: Serial No. in the Register of Workmen | D14: Name of Workman | E14: Age | F14: Sex | G14: Father Name | H14: Husband/Wife Name | I14: Department | J14: Designation / Nature of Work Done | K14: Permanent Address-1 (H.No.&Street Name) | L14: Permanent Address-2 (Village Name) | M14: Permanent Address-3 (Mandal&District Name) | N14: Permanent Address-4 (State with PIN code) | O14: Present Address-1 (H.No.&Street Name) | P14: Present Address-2 (Village Name) | Q14: Present Address-3 (Mandal&District Name) | R14: Present Address-4 (State with PIN code) | S14: Date of Joining | T14: Signature or thumb impression of Workman | U14: Date of termination of Employment | V14: Reasons for termination | W14: Remarks | X14: EPF Number | Y14: ESI Number | Z14: Name of Work man | AA14: Payble Days | AB14: Unit of Work done | AC14: Monthly rate of wages | AD14: Basic Wages | AE14: Dearness Allowances | AF14: Overtime | AG14: HRA | AH14: BONUS | AI14: LTA | AJ14: SPECIAL ALLOWNANCES | AK14: Total Amount | AL14: ESI | AM14: PF | AN14: PT | AO14: TDS | AP14: ADV | AQ14: Total Deductions | AR14: Net Salary | AS14: Date of Payment | AT14: Bank Name | AU14: Bank Account Number
A15: 1 | B15: GLDPL/EMP/079 | C15: 2 | D15: ARJUN KUMAR | E15: 31413 | F15: Male | G15: kallu | I15: Nursery | J15: Supervisor | K15: Village - Dharai | L15: Amethi | M15: Uttar pradesh - 229127 | O15: Gachibowli Village | P15: Hyderabad | Q15: Telangana State | S15: 43850 | X15: N/A | Y15: 2016384651 | Z15: =D15 -> ARJUN KUMAR | AA15: 30 | AB15: 0 | AC15: 20000 | AD15: 20000 | AE15: 0 | AF15: 0 | AG15: 0 | AH15: 0 | AI15: 0 | AJ15: 0 | AK15: =AD15+AE15+AF15+AG15+AH15+AI15+AJ15 -> 20000 | AL15: 150 | AM15: 0 | AN15: 150 | AO15: 0 | AP15: 0 | AQ15: =AL15+AM15+AN15+AO15+AP15 -> 300 | AR15: =AK15-AQ15 -> 19700 | AS15: 7th May 2020 | AT15: KKBK0000205 | AU15: 6912137285
A16: 2 | B16: GLDPL/EMP/142 | C16: 3 | D16: GAJAN SINGH | E16: 29587 | F16: Male | G16: Chandrapal singh | I16: Nursery | J16: Supervisor | K16: Village - Uncha gaon, Pikhani, | L16: Bulandshahr, | M16: Uttar pradesh - 202398 | O16: Gachibowli Village | P16: Hyderabad | Q16: Telangana State | S16: 43850 | X16: 101252819921 | Y16: 2017795829 | Z16: =D16 -> GAJAN SINGH | AA16: 30 | AB16: 0 | AC16: 14900 | AD16: 11900 | AE16: 0 | AF16: 0 | AG16: 0 | AH16: 0 | AI16: 0 | AJ16: 3000 | AK16: =AD16+AE16+AF16+AG16+AH16+AI16+AJ16 -> 14900 | AL16: 112 | AM16: 1788 | AN16: 0 | AO16: 0 | AP16: 0 | AQ16: =AL16+AM16+AN16+AO16+AP16 -> 1900 | AR16: =AK16-AQ16 -> 13000 | AS16: 7th May 2020 | AT16: KKBK0000205 | AU16: 7513074030
A17: 3 | B17: GLDPL/EMP/141 | C17: 4 | D17: GUDALA RUSHESHWAR SWAMY | E17: 31345 | F17: Male | G17: GUDALA KRISHANA MURTHY | I17: Nursery | J17: Supervisor | K17: House no. - 8-153 Kottapeta | L17: Gummaluru, west godavari | M17: Andhra pradesh - 534267 | O17: Gachibowli Village | P17: Hyderabad | Q17: Telangana State | S17: 43850 | X17: 100025787555 | Y17: 5216113872 | Z17: =D17 -> GUDALA RUSHESHWAR SWAMY | AA17: 30 | AB17: 0 | AC17: 17918 | AD17: 11802 | AE17: 0 | AF17: 0 | AG17: 4721 | AH17: 0 | AI17: 0 | AJ17: 1395 | AK17: =AD17+AE17+AF17+AG17+AH17+AI17+AJ17 -> 17918 | AL17: 135 | AM17: 1584 | AN17: 150 | AO17: 0 | AP17: 0 | AQ17: =AL17+AM17+AN17+AO17+AP17 -> 1869 | AR17: =AK17-AQ17 -> 16049 | AS17: 7th May 2020 | AT17: KKBK0007476 | AU17: 1912391941
A18: 4 | B18: GLDPL/LB/9002 | C18: 6 | D18: KASALA NARSIMLU | E18: 21919 | F18: Male | G18: KASALA POCHAIAH | I18: Nursery | J18: Semi Skilled Gardner | K18: H.no.3-90, | L18: Mwdharam,Medhak | M18: TS-502319 | O18: Gachibowli Village | P18: Hyderabad | Q18: Telangana State | S18: 43850 | X18: 101335495091 | Y18: 5216248033 | Z18: =D18 -> KASALA NARSIMLU | AA18: 26 | AB18: 0 | AC18: 13753 | AD18: 3844 | AE18: 4931.3333 | AF18: 0 | AG18: 0 | AH18: 730.6 | AI18: 425.53333 | AJ18: 1988.1333 | AK18: =AD18+AE18+AF18+AG18+AH18+AI18+AJ18 -> 11919.6 | AL18: 90 | AM18: 1430 | AN18: 0 | AO18: 0 | AP18: 0 | AQ18: =AL18+AM18+AN18+AO18+AP18 -> 1520 | AR18: =AK18-AQ18 -> 10399.6 | AS18: 7th May 2020 | AT18: ICIC0000202 | AU18: 20201585355
A19: 5 | B19: GLDPL/LB/9003 | C19: 7 | D19: PITANI SATHYA NARAYANA | E19: 24473 | F19: Male | G19: P SURYANARAYANA | I19: Nursery | J19: Semi Skilled Gardner | K19: H.no 12-60/3,Gopinagar colony, | L19: Near church,serilingampally | M19: KV R.R,TS-500019 | O19: Gachibowli Village | P19: Hyderabad | Q19: Telangana State | S19: 43850 | X19: 101423797426 | Y19: 5215982488 | Z19: =D19 -> PITANI SATHYA NARAYANA | AA19: 26 | AB19: 0 | AC19: 11459 | AD19: 3844 | AE19: 4931.3333 | AF19: 0 | AG19: 0 | AH19: 730.6 | AI19: 425.53333 | AJ19: 0 | AK19: =AD19+AE19+AF19+AG19+AH19+AI19+AJ19+1 -> 9932.4667 | AL19: 75 | AM19: 1192 | AN19: 0 | AO19: 0 | AP19: 0 | AQ19: =AL19+AM19+AN19+AO19+AP19 -> 1267 | AR19: =AK19-AQ19 -> 8665.4667 | AS19: 7th May 2020 | AT19: ANDB0001414 | AU19: 141410100131316
A20: 6 | B20: GLDPL/LB/9004 | C20: 8 | D20: SANGOLLA ASHOK | E20: 21/6/1988 | F20: Male | G20: SANGOLLA ESWARAIAH | I20: Nursery | J20: Semi Skilled Gardner | K20: 3-35,Jankampet, | L20: Patancheru,Sulthanpur | M20: TS-502319 | O20: Gachibowli Village | P20: Hyderabad | Q20: Telangana State | S20: 43850 | X20: 100321400080 | Y20: 5210317860 | Z20: =D20 -> SANGOLLA ASHOK | AA20: 26 | AB20: 0 | AC20: 11459 | AD20: 3844 | AE20: 4931.3333 | AF20: 0 | AG20: 0 | AH20: 730.6 | AI20: 425.53333 | AJ20: 0 | AK20: =AD20+AE20+AF20+AG20+AH20+AI20+AJ20+1 -> 9932.4667 | AL20: 75 | AM20: 1192 | AN20: 0 | AO20: 0 | AP20: 0 | AQ20: =AL20+AM20+AN20+AO20+AP20 -> 1267 | AR20: =AK20-AQ20 -> 8665.4667 | AS20: 7th May 2020 | AT20: SBIN0020106 | AU20: 62135175705
A21: 7 | B21: GLDPL/LB/9005 | C21: 9 | D21: ASHOK LINGURAM GAIKWAD | E21: 29832 | F21: Male | G21: M LINGRAM | I21: Nursery | J21: Semi Skilled Gardner | K21: Gaikwada at sangavi bu | L21: Post-sawargaon,Mukhed,Nanded, | M21: Mahrastra-431715 | O21: Gachibowli Village | P21: Hyderabad | Q21: Telangana State | S21: 43850 | X21: 100807941415 | Y21: 5211196939 | Z21: =D21 -> ASHOK LINGURAM GAIKWAD | AA21: 26 | AB21: 0 | AC21: 11459 | AD21: 3844 | AE21: 4931.3333 | AF21: 0 | AG21: 0 | AH21: 730.6 | AI21: 425.53333 | AJ21: 0 | AK21: =AD21+AE21+AF21+AG21+AH21+AI21+AJ21+1 -> 9932.4667 | AL21: 75 | AM21: 1192 | AN21: 0 | AO21: 0 | AP21: 0 | AQ21: =AL21+AM21+AN21+AO21+AP21 -> 1267 | AR21: =AK21-AQ21 -> 8665.4667 | AS21: 7th May 2020 | AT21: SBIN0014234 | AU21: 35398345250
A22: 8 | B22: GLDPL/LB/9006 | C22: 10 | D22: MADHUKAR KAMTAM | E22: 26665 | F22: Male | G22: KAMTAM KISHAN | I22: Nursery | J22: Semi Skilled Gardner | K22: 9-41,Serilingampally,Gopinagar colony, | L22: opp Hanuman temple | M22: R.R-TS,500084 | O22: Gachibowli Village | P22: Hyderabad | Q22: Telangana State | S22: 43850 | X22: 101438575409 | Y22: 5216116351 | Z22: =D22 -> MADHUKAR KAMTAM | AA22: 26 | AB22: 0 | AC22: 11459 | AD22: 3844 | AE22: 4931.3333 | AF22: 0 | AG22: 0 | AH22: 730.6 | AI22: 425.53333 | AJ22: 0 | AK22: =AD22+AE22+AF22+AG22+AH22+AI22+AJ22+1 -> 9932.4667 | AL22: 75 | AM22: 1192 | AN22: 0 | AO22: 0 | AP22: 0 | AQ22: =AL22+AM22+AN22+AO22+AP22 -> 1267 | AR22: =AK22-AQ22 -> 8665.4667 | AS22: 7th May 2020 | AT22: IDIB000N116 | AU22: 923249324
A23: 9 | B23: GLDPL/LB/9009 | C23: 12 | D23: Ningolla Raju | E23: 21/5/1975 | F23: Male | G23: ningolla pochaiah | I23: Nursery | J23: Semi Skilled Gardner | K23: 3-27/1,janakampet, | L23: patancherusultanpur,medhak | M23: TS-502319 | O23: Gachibowli Village | P23: Hyderabad | Q23: Telangana State | S23: 43850 | X23: 100043556888 | Y23: 5216340446 | Z23: =D23 -> Ningolla Raju | AA23: 26 | AB23: 0 | AC23: 11459 | AD23: 3844 | AE23: 4931.3333 | AF23: 0 | AG23: 0 | AH23: 730.6 | AI23: 425.53333 | AJ23: 0 | AK23: =AD23+AE23+AF23+AG23+AH23+AI23+AJ23+1 -> 9932.4667 | AL23: 75 | AM23: 1192 | AN23: 0 | AO23: 0 | AP23: 0 | AQ23: =AL23+AM23+AN23+AO23+AP23 -> 1267 | AR23: =AK23-AQ23 -> 8665.4667 | AS23: 7th May 2020 | AT23: BKID0008614 | AU23: 861410110009223
A24: 10 | B24: GLDPL/LB/9010 | C24: 13 | D24: Nagani pochaiah | E24: 24108 | F24: Male | G24: Nagani mallaiah | I24: Nursery | J24: Semi Skilled Gardner | K24: H.no.3-18, | L24: Madaram,Medhak | M24: TS-502319 | O24: Gachibowli Village | P24: Hyderabad | Q24: Telangana State | S24: 43850 | X24: 100993759408 | Y24: 5212759307 | Z24: =D24 -> Nagani pochaiah | AA24: 26 | AB24: 0 | AC24: 11459 | AD24: 3844 | AE24: 4931.3333 | AF24: 0 | AG24: 0 | AH24: 730.6 | AI24: 425.53333 | AJ24: 0 | AK24: =AD24+AE24+AF24+AG24+AH24+AI24+AJ24+1 -> 9932.4667 | AL24: 75 | AM24: 1192 | AN24: 0 | AO24: 0 | AP24: 0 | AQ24: =AL24+AM24+AN24+AO24+AP24 -> 1267 | AR24: =AK24-AQ24 -> 8665.4667 | AS24: 7th May 2020 | AT24: SBIN0014234 | AU24: 38228069327
A25: 11 | B25: GLDPL/LB/9011 | C25: 14 | D25: Mutholla Mallesh | E25: 36161 | F25: Male | G25: Mutholla balaiah | I25: Nursery | J25: Semi Skilled Gardner | K25: 3-37,Jnakapet, | L25: sulthanpur,Medhak | M25: TS-502319 | O25: Gachibowli Village | P25: Hyderabad | Q25: Telangana State | S25: 43850 | X25: 101196116055 | Y25: 5216340493 | Z25: =D25 -> Mutholla Mallesh | AA25: 26 | AB25: 0 | AC25: 11459 | AD25: 3844 | AE25: 4931.3333 | AF25: 0 | AG25: 0 | AH25: 730.6 | AI25: 425.53333 | AJ25: 0 | AK25: =AD25+AE25+AF25+AG25+AH25+AI25+AJ25+1 -> 9932.4667 | AL25: 75 | AM25: 1192 | AN25: 0 | AO25: 0 | AP25: 0 | AQ25: =AL25+AM25+AN25+AO25+AP25 -> 1267 | AR25: =AK25-AQ25 -> 8665.4667 | AS25: 7th May 2020 | AT25: SBIN0014234 | AU25: 20176301430
A26: 12 | B26: GLDPL/LB/9008 | C26: 15 | D26: ALIJANA JAYARAMI REDDY | E26: 36439 | F26: Male | G26: ALIJANA OBULU REDDY | I26: Nursery | J26: Semi Skilled Gardner | K26: 5/126, | L26: Parnapalle,Cuddaph | M26: AP-516396 | O26: Gachibowli Village | P26: Hyderabad | Q26: Telangana State | S26: 43850 | X26: 100844389108 | Y26: 5211482351 | Z26: =D26 -> ALIJANA JAYARAMI REDDY | AA26: 26 | AB26: 0 | AC26: 11459 | AD26: 3844 | AE26: 4931.3333 | AF26: 0 | AG26: 0 | AH26: 730.6 | AI26: 425.53333 | AJ26: 0 | AK26: =AD26+AE26+AF26+AG26+AH26+AI26+AJ26+1 -> 9932.4667 | AL26: 75 | AM26: 1192 | AN26: 0 | AO26: 0 | AP26: 0 | AQ26: =AL26+AM26+AN26+AO26+AP26 -> 1267 | AR26: =AK26-AQ26 -> 8665.4667 | AS26: 7th May 2020 | AT26: SBIN0008495 | AU26: 33412525880
A27: 13 | B27: GLDPL/LB/9012 | C27: 16 | D27: Kapil | E27: 36162 | F27: Male | G27: Ganesh lal | I27: Nursery | J27: Semi Skilled Gardner | K27: Khamiriya,Puru kusal,Jilla, | L27: reabarelli,Khamariya,naiani amethi | M27: U.P-229127 | O27: Gachibowli Village | P27: Hyderabad | Q27: Telangana State | S27: 43850 | X27: 101554508977 | Y27: 5216340520 | Z27: =D27 -> Kapil | AA27: 0 | AB27: 0 | AC27: 11459 | AD27: 0 | AE27: 0 | AF27: 0 | AG27: 0 | AH27: 0 | AI27: 0 | AJ27: 0 | AK27: =AD27+AE27+AF27+AG27+AH27+AI27+AJ27 -> 0 | AL27: 0 | AM27: 0 | AN27: 0 | AO27: 0 | AP27: 0 | AQ27: =AL27+AM27+AN27+AO27+AP27 -> 0 | AR27: =AK27-AQ27 -> 0 | AS27: 7th May 2020 | AT27: KKBK0007466 | AU27: 8512913818
A28: 14 | B28: GLDPL/LB/9013 | C28: 17 | D28: Bablu kumar | E28: 27948 | F28: Male | G28: Harilal | I28: Nursery | J28: Semi Skilled Gardner | K28: Nayan,Saion, | L28: Khamariya pure Kushal,amethi,nini | M28: U.P-229127 | O28: Gachibowli Village | P28: Hyderabad | Q28: Telangana State | S28: 43850 | X28: 101554509007 | Y28: 5216340547 | Z28: =D28 -> Bablu kumar | AA28: 0 | AB28: 0 | AC28: 11459 | AD28: 0 | AE28: 0 | AF28: 0 | AG28: 0 | AH28: 0 | AI28: 0 | AJ28: 0 | AK28: =AD28+AE28+AF28+AG28+AH28+AI28+AJ28 -> 0 | AL28: 0 | AM28: 0 | AN28: 0 | AO28: 0 | AP28: 0 | AQ28: =AL28+AM28+AN28+AO28+AP28 -> 0 | AR28: =AK28-AQ28 -> 0 | AS28: 7th May 2020 | AT28: KKBK0007466 | AU28: 8512913542
A29: 15 | B29: GLDPL/LB/9014 | C29: 18 | D29: Pradeep kumar | E29: 16/9/1977 | F29: Male | G29: Jagdev | I29: Nursery | J29: Semi Skilled Gardner | K29: Nayan,Saion, | L29: Khamariya pure Kushal,amethi,nini | M29: U.P-229127 | O29: Gachibowli Village | P29: Hyderabad | Q29: Telangana State | S29: 43850 | X29: 101554508996 | Y29: 5216340569 | Z29: =D29 -> Pradeep kumar | AA29: 0 | AB29: 0 | AC29: 11459 | AD29: 0 | AE29: 0 | AF29: 0 | AG29: 0 | AH29: 0 | AI29: 0 | AJ29: 0 | AK29: =AD29+AE29+AF29+AG29+AH29+AI29+AJ29 -> 0 | AL29: 0 | AM29: 0 | AN29: 0 | AO29: 0 | AP29: 0 | AQ29: =AL29+AM29+AN29+AO29+AP29 -> 0 | AR29: =AK29-AQ29 -> 0 | AS29: 7th May 2020 | AT29: KKBK0007466 | AU29: 8512913528
A30: 16 | B30: GLDPL/LB/9015 | C30: 19 | D30: SHAIK KULSUM BEE | E30: 27762 | F30: Female | G30: SHAIK LALA | I30: Nursery | J30: Unskilled Gardner | K30: PLOT.NO.175,MASID BAND, | L30: KONDAPUR,SERILINGAMPALLY | M30: R.R-TS,500084 | O30: Gachibowli Village | P30: Hyderabad | Q30: Telangana State | S30: 43850 | X30: 100201354809 | Y30: 5210209502 | Z30: =D30 -> SHAIK KULSUM BEE | AA30: 26 | AB30: 0 | AC30: 10627 | AD30: 3207 | AE30: 4931.3333 | AF30: 0 | AG30: 0 | AH30: 677.73333 | AI30: 394.33333 | AJ30: 0 | AK30: =AD30+AE30+AF30+AG30+AH30+AI30+AJ30 -> 9210.4 | AL30: 70 | AM30: 1105 | AN30: 0 | AO30: 0 | AP30: 0 | AQ30: =AL30+AM30+AN30+AO30+AP30 -> 1175 | AR30: =AK30-AQ30 -> 8035.4 | AS30: 7th May 2020 | AT30: SBIN0005916 | AU30: 30144397282
A31: 17 | B31: GLDPL/LB/9016 | C31: 20 | D31: S GOWRI | E31: 33239 | F31: Female | G31: S SURYANARAYANA | I31: Nursery | J31: Unskilled Gardner | K31: 2/686,Modinabad | L31: ,Gutkal,Ananthpur | M31: AP-515801 | O31: Gachibowli Village | P31: Hyderabad | Q31: Telangana State | S31: 43850 | X31: 101412580029 | Y31: 5215258577 | Z31: =D31 -> S GOWRI | AA31: 26 | AB31: 0 | AC31: 10627 | AD31: 3207 | AE31: 4931.3333 | AF31: 0 | AG31: 0 | AH31: 677.73333 | AI31: 394.33333 | AJ31: 0 | AK31: =AD31+AE31+AF31+AG31+AH31+AI31+AJ31 -> 9210.4 | AL31: 70 | AM31: 1105 | AN31: 0 | AO31: 0 | AP31: 0 | AQ31: =AL31+AM31+AN31+AO31+AP31 -> 1175 | AR31: =AK31-AQ31 -> 8035.4 | AS31: 7th May 2020 | AT31: SBIN0000957 | AU31: 35855410947
A32: 18 | B32: GLDPL/LB/9017 | C32: 21 | D32: FARZANA BEGUM | E32: 31048 | F32: Female | G32: SHAIK MASTAN WALI | I32: Nursery | J32: Unskilled Gardner | K32: 9-4-57/7/D/10/2/B43, | L32: HAKEEMPET,THOLICHOUK,GOLUKOND | M32: HYDERABAD,TS-500008 | O32: Gachibowli Village | P32: Hyderabad | Q32: Telangana State | S32: 43850 | X32: 100146756163 | Y32: 5206265912 | Z32: =D32 -> FARZANA BEGUM | AA32: 26 | AB32: 0 | AC32: 10627 | AD32: 3207 | AE32: 4931.3333 | AF32: 0 | AG32: 0 | AH32: 677.73333 | AI32: 394.33333 | AJ32: 0 | AK32: =AD32+AE32+AF32+AG32+AH32+AI32+AJ32 -> 9210.4 | AL32: 70 | AM32: 1105 | AN32: 0 | AO32: 0 | AP32: 0 | AQ32: =AL32+AM32+AN32+AO32+AP32 -> 1175 | AR32: =AK32-AQ32 -> 8035.4 | AS32: 7th May 2020 | AT32: ANDB0001306 | AU32: 130610100075445
A33: 19 | B33: GLDPL/LB/9018 | C33: 22 | D33: MANAGALI SUHASINI | E33: 29221 | F33: Female | G33: MANGALI RAJU | I33: Nursery | J33: Unskilled Gardner | K33: H.no.2-36, | L33: Medharam,medak | M33: TS-502319 | O33: Gachibowli Village | P33: Hyderabad | Q33: Telangana State | S33: 43850 | X33: 101257341492 | Y33: 5214635168 | Z33: =D33 -> MANAGALI SUHASINI | AA33: 26 | AB33: 0 | AC33: 10627 | AD33: 3207 | AE33: 4931.3333 | AF33: 0 | AG33: 0 | AH33: 677.73333 | AI33: 394.33333 | AJ33: 0 | AK33: =AD33+AE33+AF33+AG33+AH33+AI33+AJ33 -> 9210.4 | AL33: 70 | AM33: 1105 | AN33: 0 | AO33: 0 | AP33: 0 | AQ33: =AL33+AM33+AN33+AO33+AP33 -> 1175 | AR33: =AK33-AQ33 -> 8035.4 | AS33: 7th May 2020 | AT33: APGV0008110 | AU33: 73138780593
A34: 20 | B34: GLDPL/LB/9019 | C34: 23 | D34: KONA SUJATHA | E34: 25934 | F34: Female | G34: KONA SURYANARAYANA | I34: Nursery | J34: Unskilled Gardner | K34: 2-503/A,modinabad | L34: .guntkal,anthapuram | M34: AP-515801 | O34: Gachibowli Village | P34: Hyderabad | Q34: Telangana State | S34: 43850 | X34: 101421043457 | Y34: 5215374381 | Z34: =D34 -> KONA SUJATHA | AA34: 26 | AB34: 0 | AC34: 10627 | AD34: 3207 | AE34: 4931.3333 | AF34: 0 | AG34: 0 | AH34: 677.73333 | AI34: 394.33333 | AJ34: 0 | AK34: =AD34+AE34+AF34+AG34+AH34+AI34+AJ34 -> 9210.4 | AL34: 70 | AM34: 1105 | AN34: 0 | AO34: 0 | AP34: 0 | AQ34: =AL34+AM34+AN34+AO34+AP34 -> 1175 | AR34: =AK34-AQ34 -> 8035.4 | AS34: 7th May 2020 | AT34: SBIN0000957 | AU34: 30534600258
A35: 21 | B35: GLDPL/LB/9020 | C35: 24 | D35: GOLLA UMA | E35: 30562 | F35: Female | G35: GOLLA ONURU SWAMY | I35: Nursery | J35: Unskilled Gardner | K35: 2-503-B,MODINABAD, | L35: GUTAL,ANANTHAPURM | M35: AP-515801 | O35: Gachibowli Village | P35: Hyderabad | Q35: Telangana State | S35: 43850 | X35: 101412580017 | Y35: 5215258539 | Z35: =D35 -> GOLLA UMA | AA35: 26 | AB35: 0 | AC35: 10627 | AD35: 3207 | AE35: 4931.3333 | AF35: 0 | AG35: 0 | AH35: 677.73333 | AI35: 394.33333 | AJ35: 0 | AK35: =AD35+AE35+AF35+AG35+AH35+AI35+AJ35 -> 9210.4 | AL35: 70 | AM35: 1105 | AN35: 0 | AO35: 0 | AP35: 0 | AQ35: =AL35+AM35+AN35+AO35+AP35 -> 1175 | AR35: =AK35-AQ35 -> 8035.4 | AS35: 7th May 2020 | AT35: SBIN0000957 | AU35: 11107141688
A36: 22 | B36: GLDPL/LB/9021 | C36: 25 | D36: SINGARAM BHAGYAMMA | E36: 18/5/1964 | F36: Female | G36: SINGARAM NARSIMULU | I36: Nursery | J36: Unskilled Gardner | K36: 1-43,patancheru-mndl, | L36: Krishnareddipet,Medak | M36: TS-502319 | O36: Gachibowli Village | P36: Hyderabad | Q36: Telangana State | S36: 43850 | X36: 100118386595 | Y36: 5216279786 | Z36: =D36 -> SINGARAM BHAGYAMMA | AA36: 26 | AB36: 0 | AC36: 10627 | AD36: 3207 | AE36: 4931.3333 | AF36: 0 | AG36: 0 | AH36: 677.73333 | AI36: 394.33333 | AJ36: 0 | AK36: =AD36+AE36+AF36+AG36+AH36+AI36+AJ36 -> 9210.4 | AL36: 70 | AM36: 1105 | AN36: 0 | AO36: 0 | AP36: 0 | AQ36: =AL36+AM36+AN36+AO36+AP36 -> 1175 | AR36: =AK36-AQ36 -> 8035.4 | AS36: 7th May 2020 | AT36: SBIN0014234 | AU36: 36363257786
A37: 23 | B37: GLDPL/LB/9023 | C37: 27 | D37: KODICHERLA INDIRAMMA | E37: 32418 | F37: Female | G37: BABAIAH | I37: Nursery | J37: Unskilled Gardner | K37: 1-92,maseed banda-Vill | L37: Kondapoor,Serilinampally | M37: R.R-TS,500032 | O37: Gachibowli Village | P37: Hyderabad | Q37: Telangana State | S37: 43850 | X37: 100181240855 | Y37: 5209811859 | Z37: =D37 -> KODICHERLA INDIRAMMA | AA37: 26 | AB37: 0 | AC37: 10627 | AD37: 3207 | AE37: 4931.3333 | AF37: 0 | AG37: 0 | AH37: 677.73333 | AI37: 394.33333 | AJ37: 0 | AK37: =AD37+AE37+AF37+AG37+AH37+AI37+AJ37 -> 9210.4 | AL37: 70 | AM37: 1105 | AN37: 0 | AO37: 0 | AP37: 0 | AQ37: =AL37+AM37+AN37+AO37+AP37 -> 1175 | AR37: =AK37-AQ37 -> 8035.4 | AS37: 7th May 2020 | AT37: SBIN0005916 | AU37: 30181587428
A38: 24 | B38: GLDPL/LB/9024 | C38: 28 | D38: SANGOLLA LAVANYA | E38: 26299 | F38: Female | G38: SANGOLLA ASHOK | I38: Nursery | J38: Unskilled Gardner | K38: 3-35,janakapet, | L38: Patancheru,Medak | M38: TS-502319 | O38: Gachibowli Village | P38: Hyderabad | Q38: Telangana State | S38: 43850 | X38: 100993758799 | Y38: 5212759301 | Z38: =D38 -> SANGOLLA LAVANYA | AA38: 26 | AB38: 0 | AC38: 10627 | AD38: 3207 | AE38: 4931.3333 | AF38: 0 | AG38: 0 | AH38: 677.73333 | AI38: 394.33333 | AJ38: 0 | AK38: =AD38+AE38+AF38+AG38+AH38+AI38+AJ38 -> 9210.4 | AL38: 70 | AM38: 1105 | AN38: 0 | AO38: 0 | AP38: 0 | AQ38: =AL38+AM38+AN38+AO38+AP38 -> 1175 | AR38: =AK38-AQ38 -> 8035.4 | AS38: 7th May 2020 | AT38: SBIN0014234 | AU38: 36071152580
A39: 25 | B39: GLDPL/LB/9025 | C39: 29 | D39: MANGALI LAVANYA | E39: 14/3/1985 | F39: Female | G39: MANGALI PANDU | I39: Nursery | J39: Unskilled Gardner | K39: H.no.3-10, | L39: Madhavaram,madharam,Medhak | M39: TS-502319 | O39: Gachibowli Village | P39: Hyderabad | Q39: Telangana State | S39: 43850 | X39: 101269710584 | Y39: 5214535728 | Z39: =D39 -> MANGALI LAVANYA | AA39: 26 | AB39: 0 | AC39: 10627 | AD39: 3207 | AE39: 4931.3333 | AF39: 0 | AG39: 0 | AH39: 677.73333 | AI39: 394.33333 | AJ39: 0 | AK39: =AD39+AE39+AF39+AG39+AH39+AI39+AJ39 -> 9210.4 | AL39: 70 | AM39: 1105 | AN39: 0 | AO39: 0 | AP39: 0 | AQ39: =AL39+AM39+AN39+AO39+AP39 -> 1175 | AR39: =AK39-AQ39 -> 8035.4 | AS39: 7th May 2020 | AT39: SBIN0014234 | AU39: 36071152502
A40: 26 | B40: GLDPL/LB/9026 | C40: 30 | D40: MANGLI CHANDRAMMA | E40: 25/3/1969 | F40: Female | G40: MANGALI VENKATESH | I40: Nursery | J40: Unskilled Gardner | K40: House no. - 3-33 Madharam, | L40: MADHARAM,MEDHAK | M40: Andhra pradesh - 502319 | O40: Gachibowli Village | P40: Hyderabad | Q40: Telangana State | S40: 43850 | X40: 101554508983 | Y40: 5216340615 | Z40: =D40 -> MANGLI CHANDRAMMA | AA40: 26 | AB40: 0 | AC40: 10627 | AD40: 3207 | AE40: 4931.3333 | AF40: 0 | AG40: 0 | AH40: 677.73333 | AI40: 394.33333 | AJ40: 0 | AK40: =AD40+AE40+AF40+AG40+AH40+AI40+AJ40 -> 9210.4 | AL40: 70 | AM40: 1105 | AN40: 0 | AO40: 0 | AP40: 0 | AQ40: =AL40+AM40+AN40+AO40+AP40 -> 1175 | AR40: =AK40-AQ40 -> 8035.4 | AS40: 7th May 2020 | AT40: APGV0008110 | AU40: 73100389136
A41: 27 | B41: GLDPL/LB/9027 | C41: 31 | D41: DASARI SUVARNA | E41: 32509 | F41: Female | G41: DASARI RAVINDAR | I41: Nursery | J41: Unskilled Gardner | K41: H.NO.11-50,GOPINAGAR,SERILINGMPLLI | L41: NEAR GVT SCHOOL LINGAMPALLI, | M41: KV R.R,TS-500019 | O41: Gachibowli Village | P41: Hyderabad | Q41: Telangana State | S41: 43850 | X41: 101521098686 | Y41: 5216116294 | Z41: =D41 -> DASARI SUVARNA | AA41: 0 | AB41: 0 | AC41: 10627 | AD41: 0 | AE41: 0 | AF41: 0 | AG41: 0 | AH41: 0 | AI41: 0 | AJ41: 0 | AK41: =AD41+AE41+AF41+AG41+AH41+AI41+AJ41 -> 0 | AL41: 0 | AM41: 0 | AN41: 0 | AO41: 0 | AP41: 0 | AQ41: =AL41+AM41+AN41+AO41+AP41 -> 0 | AR41: =AK41-AQ41 -> 0 | AS41: 7th May 2020 | AT41: ANDB0001414 | AU41: 141410100016831
A42: 28 | B42: GLDPL/LB/9028 | C42: 32 | D42: MARATHI CHANDRAKALA | E42: 31413 | F42: Female | G42: M ASHOKS | I42: Nursery | J42: Unskilled Gardner | K42: 3/32,janagampet | L42: patancheru,sultanpur,Medak | M42: TS-502319 | O42: Gachibowli Village | P42: Hyderabad | Q42: Telangana State | S42: 43850 | X42: 100127755377 | Y42: 5210266822 | Z42: =D42 -> MARATHI CHANDRAKALA | AA42: 26 | AB42: 0 | AC42: 10627 | AD42: 3207 | AE42: 4931.3333 | AF42: 0 | AG42: 0 | AH42: 677.73333 | AI42: 394.33333 | AJ42: 0 | AK42: =AD42+AE42+AF42+AG42+AH42+AI42+AJ42 -> 9210.4 | AL42: 70 | AM42: 1105 | AN42: 0 | AO42: 0 | AP42: 0 | AQ42: =AL42+AM42+AN42+AO42+AP42 -> 1175 | AR42: =AK42-AQ42 -> 8035.4 | AS42: 7th May 2020 | AT42: SBIN0014234 | AU42: 36363257797
A43: 29 | B43: GLDPL/LB/9029 | C43: 33 | D43: ANKAGALLA YADAMMA | E43: 32509 | F43: Female | G43: ANKAGALLA YADAGIRI | I43: Nursery | J43: Unskilled Gardner | K43: 26330 | L43: Sulthanpoor,patancheru,Sulthanpur | M43: TS-502319 | O43: Gachibowli Village | P43: Hyderabad | Q43: Telangana State | S43: 43850 | X43: 101553811711 | Y43: 5216340696 | Z43: =D43 -> ANKAGALLA YADAMMA | AA43: 26 | AB43: 0 | AC43: 10627 | AD43: 3207 | AE43: 4931.3333 | AF43: 0 | AG43: 0 | AH43: 677.73333 | AI43: 394.33333 | AJ43: 0 | AK43: =AD43+AE43+AF43+AG43+AH43+AI43+AJ43 -> 9210.4 | AL43: 70 | AM43: 1105 | AN43: 0 | AO43: 0 | AP43: 0 | AQ43: =AL43+AM43+AN43+AO43+AP43 -> 1175 | AR43: =AK43-AQ43 -> 8035.4 | AS43: 7th May 2020 | AT43: SBIN0014234 | AU43: 20176302412
A44: 30 | B44: GLDPL/LB/9030 | C44: 34 | D44: NINGAMMA | E44: 27395 | F44: Female | G44: RAMANNA | I44: Nursery | J44: Unskilled Gardner | K44: 5/4/256 | L44: Janatha colony,Bhalki,Bidar | M44: karnataka-585328 | O44: Gachibowli Village | P44: Hyderabad | Q44: Telangana State | S44: 43850 | X44: 101381353296 | Y44: 5215200706 | Z44: =D44 -> NINGAMMA | AA44: 26 | AB44: 0 | AC44: 10627 | AD44: 3207 | AE44: 4931.3333 | AF44: 0 | AG44: 0 | AH44: 677.73333 | AI44: 394.33333 | AJ44: 0 | AK44: =AD44+AE44+AF44+AG44+AH44+AI44+AJ44 -> 9210.4 | AL44: 70 | AM44: 1105 | AN44: 0 | AO44: 0 | AP44: 0 | AQ44: =AL44+AM44+AN44+AO44+AP44 -> 1175 | AR44: =AK44-AQ44 -> 8035.4 | AS44: 7th May 2020 | AT44: FDRL0001605 | AU44: 16050100039723
A45: 31 | B45: GLDPL/LB/9031 | C45: 35 | D45: V AMBAMMA | E45: 20/11/1980 | F45: Female | G45: V YELLAIAH | I45: Nursery | J45: Unskilled Gardner | K45: H.no.6-199/1 | L45: Narra basthi,Patancheru,Medak | M45: TS-502319 | O45: Gachibowli Village | P45: Hyderabad | Q45: Telangana State | S45: 43850 | X45: 101362702317 | Y45: 5216116335 | Z45: =D45 -> V AMBAMMA | AA45: 26 | AB45: 0 | AC45: 10627 | AD45: 3207 | AE45: 4931.3333 | AF45: 0 | AG45: 0 | AH45: 677.73333 | AI45: 394.33333 | AJ45: 0 | AK45: =AD45+AE45+AF45+AG45+AH45+AI45+AJ45 -> 9210.4 | AL45: 70 | AM45: 1105 | AN45: 0 | AO45: 0 | AP45: 0 | AQ45: =AL45+AM45+AN45+AO45+AP45 -> 1175 | AR45: =AK45-AQ45 -> 8035.4 | AS45: 7th May 2020 | AT45: ICIC0001111 | AU45: 111101515392
A46: 32 | B46: GLDPL/LB/9032 | C46: 36 | D46: PALLAPU LAXMI | E46: 21/3/1966 | F46: Female | G46: VENAKAIAH | I46: Nursery | J46: Unskilled Gardner | K46: 21245 | L46: Nagdar,kalher,medak | M46: AP-502371 | O46: Gachibowli Village | P46: Hyderabad | Q46: Telangana State | S46: 43850 | X46: 101362702340 | Y46: 5215200729 | Z46: =D46 -> PALLAPU LAXMI | AA46: 26 | AB46: 0 | AC46: 10627 | AD46: 3207 | AE46: 4931.3333 | AF46: 0 | AG46: 0 | AH46: 677.73333 | AI46: 394.33333 | AJ46: 0 | AK46: =AD46+AE46+AF46+AG46+AH46+AI46+AJ46 -> 9210.4 | AL46: 70 | AM46: 1105 | AN46: 0 | AO46: 0 | AP46: 0 | AQ46: =AL46+AM46+AN46+AO46+AP46 -> 1175 | AR46: =AK46-AQ46 -> 8035.4 | AS46: 7th May 2020 | AT46: APGV0008163 | AU46: 7310404993-5
A47: 33 | B47: GLDPL/LB/9033 | C47: 37 | D47: Nagani laxmi | E47: 27395 | F47: Female | G47: Nagani pochaiah | I47: Nursery | J47: Unskilled Gardner | K47: H.NO.3-18 | L47: MADHARAM,MEDHAK | M47: TS-502319 | O47: Gachibowli Village | P47: Hyderabad | Q47: Telangana State | S47: 43850 | X47: 100245723121 | Y47: 5213565032 | Z47: =D47 -> Nagani laxmi | AA47: 26 | AB47: 0 | AC47: 10627 | AD47: 3207 | AE47: 4931.3333 | AF47: 0 | AG47: 0 | AH47: 677.73333 | AI47: 394.33333 | AJ47: 0 | AK47: =AD47+AE47+AF47+AG47+AH47+AI47+AJ47 -> 9210.4 | AL47: 70 | AM47: 1105 | AN47: 0 | AO47: 0 | AP47: 0 | AQ47: =AL47+AM47+AN47+AO47+AP47 -> 1175 | AR47: =AK47-AQ47 -> 8035.4 | AS47: 7th May 2020 | AT47: SBIN0014234 | AU47: 38228068404
A48: 34 | B48: GLDPL/LB/9034 | C48: 38 | D48: Lingola amrutha | E48: 29545 | F48: Female | G48: Ningolla swamy | I48: Nursery | J48: Unskilled Gardner | K48: 3-31,Janakampet | L48: patancheru,Sultanpur,medak | M48: TS-502319 | O48: Gachibowli Village | P48: Hyderabad | Q48: Telangana State | S48: 43850 | X48: 100201625830 | Y48: 5210209440 | Z48: =D48 -> Lingola amrutha | AA48: 26 | AB48: 0 | AC48: 10627 | AD48: 3207 | AE48: 4931.3333 | AF48: 0 | AG48: 0 | AH48: 677.73333 | AI48: 394.33333 | AJ48: 0 | AK48: =AD48+AE48+AF48+AG48+AH48+AI48+AJ48 -> 9210.4 | AL48: 70 | AM48: 1105 | AN48: 0 | AO48: 0 | AP48: 0 | AQ48: =AL48+AM48+AN48+AO48+AP48 -> 1175 | AR48: =AK48-AQ48 -> 8035.4 | AS48: 7th May 2020 | AT48: SBIN0014234 | AU48: 31891992373
A49: 35 | B49: GLDPL/LB/9035 | C49: 39 | D49: Kuduru satyamma | E49: 24187 | F49: Female | G49: NARAYANA | I49: Nursery | J49: Unskilled Gardner | K49: 5-11 BC colony | L49: mahabubnagar,dhrmapur-mndl, | M49: TS-502319 | O49: Gachibowli Village | P49: Hyderabad | Q49: Telangana State | S49: 43850 | X49: 101440681199 | Y49: 5216116222 | Z49: =D49 -> Kuduru satyamma | AA49: 26 | AB49: 0 | AC49: 10627 | AD49: 3207 | AE49: 4931.3333 | AF49: 0 | AG49: 0 | AH49: 677.73333 | AI49: 394.33333 | AJ49: 0 | AK49: =AD49+AE49+AF49+AG49+AH49+AI49+AJ49 -> 9210.4 | AL49: 70 | AM49: 1105 | AN49: 0 | AO49: 0 | AP49: 0 | AQ49: =AL49+AM49+AN49+AO49+AP49 -> 1175 | AR49: =AK49-AQ49 -> 8035.4 | AS49: 7th May 2020 | AT49: SBIN0016375 | AU49: 62409123202
A50: 36 | B50: GLDPL/LB/9036 | C50: 40 | D50: Mangali Lakshmi | E50: 28491 | F50: Female | G50: MANGALI PEDDA | I50: Nursery | J50: Unskilled Gardner | K50: H NO 2-36 | L50: MADHRAM MEDAK | M50: TS-502319 | O50: Gachibowli Village | P50: Hyderabad | Q50: Telangana State | S50: 43862 | X50: 101556794449 | Y50: 5216385030 | Z50: =D50 -> Mangali Lakshmi | AA50: 26 | AB50: 0 | AC50: 10627 | AD50: 3207 | AE50: 4931.3333 | AF50: 0 | AG50: 0 | AH50: 677.73333 | AI50: 394.33333 | AJ50: 0 | AK50: =AD50+AE50+AF50+AG50+AH50+AI50+AJ50 -> 9210.4 | AL50: 70 | AM50: 1105 | AN50: 0 | AO50: 0 | AP50: 0 | AQ50: =AL50+AM50+AN50+AO50+AP50 -> 1175 | AR50: =AK50-AQ50 -> 8035.4 | AS50: 7th May 2020 | AT50: APGV0008110 | AU50: 73158532002
A51: 37 | B51: GLDPL/LB/9037 | C51: 41 | D51: Ningolla santhosha | E51: 28491 | F51: Female | G51: NINGOLLA RAJU | I51: Nursery | J51: Unskilled Gardner | K51: H NO 3-27/1 | L51: SULTANPUR | M51: TS-502319 | O51: Gachibowli Village | P51: Hyderabad | Q51: Telangana State | S51: 43862 | X51: 101344596547 | Y51: 5216385073 | Z51: =D51 -> Ningolla santhosha | AA51: 26 | AB51: 0 | AC51: 10627 | AD51: 3207 | AE51: 4931.3333 | AF51: 0 | AG51: 0 | AH51: 677.73333 | AI51: 394.33333 | AJ51: 0 | AK51: =AD51+AE51+AF51+AG51+AH51+AI51+AJ51 -> 9210.4 | AL51: 70 | AM51: 1105 | AN51: 0 | AO51: 0 | AP51: 0 | AQ51: =AL51+AM51+AN51+AO51+AP51 -> 1175 | AR51: =AK51-AQ51 -> 8035.4 | AS51: 7th May 2020 | AT51: TSAB0017030 | AU51: 173022010000748
A52: 38 | B52: GLDPL/LB/9038 | C52: 42 | D52: Mutholla Suneeta | E52: 28989 | F52: Female | G52: MUTHOLLA MALLESH | I52: Nursery | J52: Unskilled Gardner | K52: H NO 3-37 | L52: SULTANPUR | M52: TS-502319 | O52: Gachibowli Village | P52: Hyderabad | Q52: Telangana State | S52: 43862 | X52: 101556794454 | Y52: 5216385098 | Z52: =D52 -> Mutholla Suneeta | AA52: 26 | AB52: 0 | AC52: 10627 | AD52: 3207 | AE52: 4931.3333 | AF52: 0 | AG52: 0 | AH52: 677.73333 | AI52: 394.33333 | AJ52: 0 | AK52: =AD52+AE52+AF52+AG52+AH52+AI52+AJ52 -> 9210.4 | AL52: 70 | AM52: 1105 | AN52: 0 | AO52: 0 | AP52: 0 | AQ52: =AL52+AM52+AN52+AO52+AP52 -> 1175 | AR52: =AK52-AQ52 -> 8035.4 | AS52: 7th May 2020 | AT52: SBIN0014234 | AU52: 20163798424
A53: 39 | B53: GLDPL/LB/9039 | C53: 43 | D53: Mutholla sushila | E53: 26665 | F53: Female | G53: MUTHOLLA CHANDRA | I53: Nursery | J53: Unskilled Gardner | K53: H NO 3-26JANAKPET | L53: SULTANPUR | M53: TS-502319 | O53: Gachibowli Village | P53: Hyderabad | Q53: Telangana State | S53: 43862 | X53: 100209063448 | Y53: 5216385125 | Z53: =D53 -> Mutholla sushila | AA53: 26 | AB53: 0 | AC53: 10627 | AD53: 3207 | AE53: 4931.3333 | AF53: 0 | AG53: 0 | AH53: 677.73333 | AI53: 394.33333 | AJ53: 0 | AK53: =AD53+AE53+AF53+AG53+AH53+AI53+AJ53 -> 9210.4 | AL53: 70 | AM53: 1105 | AN53: 0 | AO53: 0 | AP53: 0 | AQ53: =AL53+AM53+AN53+AO53+AP53 -> 1175 | AR53: =AK53-AQ53 -> 8035.4 | AS53: 7th May 2020 | AT53: SBIN0014234 | AU53: 33177853645
A54: 40 | B54: GLDPL/LB/9040 | C54: 44 | D54: Kummari kalavathi | E54: 27395 | F54: Female | G54: KUMARI KRISHNA | I54: Nursery | J54: Unskilled Gardner | K54: H NO 2-71\1 | L54: MADHARAM,MEDHAK | M54: TS-502319 | O54: Gachibowli Village | P54: Hyderabad | Q54: Telangana State | S54: 43862 | X54: 101322441815 | Y54: 5216385155 | Z54: =D54 -> Kummari kalavathi | AA54: 26 | AB54: 0 | AC54: 10627 | AD54: 3207 | AE54: 4931.3333 | AF54: 0 | AG54: 0 | AH54: 677.73333 | AI54: 394.33333 | AJ54: 0 | AK54: =AD54+AE54+AF54+AG54+AH54+AI54+AJ54 -> 9210.4 | AL54: 70 | AM54: 1105 | AN54: 0 | AO54: 0 | AP54: 0 | AQ54: =AL54+AM54+AN54+AO54+AP54 -> 1175 | AR54: =AK54-AQ54 -> 8035.4 | AS54: 7th May 2020 | AT54: SBIN0014234 | AU54: 33415863098
A55: 41 | B55: GLDPL/LB/9041 | C55: 45 | D55: Vadla Naveena | E55: 29587 | F55: Female | G55: VADLA BHASHKAR | I55: Nursery | J55: Unskilled Gardner | K55: H NO 3-10 MADHRAM | L55: MADHRAM MEDAK | M55: TS-502319 | O55: Gachibowli Village | P55: Hyderabad | Q55: Telangana State | S55: 43862 | X55: 101458887492 | Y55: 5216385182 | Z55: =D55 -> Vadla Naveena | AA55: 26 | AB55: 0 | AC55: 10627 | AD55: 3207 | AE55: 4931.3333 | AF55: 0 | AG55: 0 | AH55: 677.73333 | AI55: 394.33333 | AJ55: 0 | AK55: =AD55+AE55+AF55+AG55+AH55+AI55+AJ55 -> 9210.4 | AL55: 70 | AM55: 1105 | AN55: 0 | AO55: 0 | AP55: 0 | AQ55: =AL55+AM55+AN55+AO55+AP55 -> 1175 | AR55: =AK55-AQ55 -> 8035.4 | AS55: 7th May 2020 | AT55: APGV0008110 | AU55: 73097866350
A56: 42 | B56: GLDPL/LB/9042 | C56: 46 | D56: Nagani shantamma | E56: 25569 | F56: Female | G56: NANGANI VEERAIAH | I56: Nursery | J56: Unskilled Gardner | K56: H NO 3-44 | L56: MADHARAM,MEDHAK | M56: TS-502319 | O56: Gachibowli Village | P56: Hyderabad | Q56: Telangana State | S56: 43864 | X56: 100246061839 | Y56: 5209952214 | Z56: =D56 -> Nagani shantamma | AA56: 26 | AB56: 0 | AC56: 10627 | AD56: 3207 | AE56: 4931.3333 | AF56: 0 | AG56: 0 | AH56: 677.73333 | AI56: 394.33333 | AJ56: 0 | AK56: =AD56+AE56+AF56+AG56+AH56+AI56+AJ56 -> 9210.4 | AL56: 70 | AM56: 1105 | AN56: 0 | AO56: 0 | AP56: 0 | AQ56: =AL56+AM56+AN56+AO56+AP56 -> 1175 | AR56: =AK56-AQ56 -> 8035.4 | AS56: 7th May 2020 | AT56: SBIN0014234 | AU56: 33400593738
A57: 43 | B57: GLDPL/LB/9043 | C57: 47 | D57: Gaddmidi lakshmi | E57: 25934 | F57: Female | G57: GADDAMIDI RAGHU | I57: Nursery | J57: Unskilled Gardner | K57: H N0 3-95/1 | L57: MADHRAM MEDAK | M57: TS-502319 | O57: Gachibowli Village | P57: Hyderabad | Q57: Telangana State | S57: 43865 | X57: 101277064828 | Y57: 5214349122 | Z57: =D57 -> Gaddmidi lakshmi | AA57: 26 | AB57: 0 | AC57: 10627 | AD57: 3207 | AE57: 4931.3333 | AF57: 0 | AG57: 0 | AH57: 677.73333 | AI57: 394.33333 | AJ57: 0 | AK57: =AD57+AE57+AF57+AG57+AH57+AI57+AJ57 -> 9210.4 | AL57: 70 | AM57: 1105 | AN57: 0 | AO57: 0 | AP57: 0 | AQ57: =AL57+AM57+AN57+AO57+AP57 -> 1175 | AR57: =AK57-AQ57 -> 8035.4 | AS57: 7th May 2020 | AT57: SBIN0014234 | AU57: 35101295296
A58: 44 | B58: GLDPL/LB/9045 | C58: 49 | D58: Gaddamidi raghu | E58: 25934 | F58: Male | G58: GADDAMIDI BALAIAH | I58: Nursery | J58: Semi Skilled Gardner | K58: H NO 3-95/1 | L58: MADHRAM MEDAK | M58: TS-502319 | O58: Gachibowli Village | P58: Hyderabad | Q58: Telangana State | S58: 43865 | X58: 101170655221 | Y58: 5216385272 | Z58: =D58 -> Gaddamidi raghu | AA58: 26 | AB58: 0 | AC58: 11459 | AD58: 3844 | AE58: 4931.3333 | AF58: 0 | AG58: 0 | AH58: 730.6 | AI58: 425.53333 | AJ58: 0 | AK58: =AD58+AE58+AF58+AG58+AH58+AI58+AJ58+1 -> 9932.4667 | AL58: 75 | AM58: 1192 | AN58: 0 | AO58: 0 | AP58: 0 | AQ58: =AL58+AM58+AN58+AO58+AP58 -> 1267 | AR58: =AK58-AQ58 -> 8665.4667 | AS58: 7th May 2020 | AT58: SBIN0014234 | AU58: 35200839277
A59: 45 | B59: GLDPL/LB/9046 | C59: 50 | D59: Laxman | E59: 35065 | F59: Male | G59: IRAPPA | I59: Nursery | J59: Semi Skilled Gardner | K59: H NO 1/22 KOLLUR | L59: BIDAR | M59: KR-585326 | O59: Gachibowli Village | P59: Hyderabad | Q59: Telangana State | S59: 43881 | X59: 101563813332 | Y59: 5216434433 | Z59: =D59 -> Laxman | AA59: 26 | AB59: 0 | AC59: 11459 | AD59: 3844 | AE59: 4931.3333 | AF59: 0 | AG59: 0 | AH59: 730.6 | AI59: 425.53333 | AJ59: 0 | AK59: =AD59+AE59+AF59+AG59+AH59+AI59+AJ59+1 -> 9932.4667 | AL59: 75 | AM59: 1192 | AN59: 0 | AO59: 0 | AP59: 0 | AQ59: =AL59+AM59+AN59+AO59+AP59 -> 1267 | AR59: =AK59-AQ59 -> 8665.4667 | AS59: 7th May 2020 | AT59: CNRB0003868 | AU59: 3868101008111
A60: 46 | B60: GLDPL/LB/9047 | C60: 51 | D60: VADLA JYOTHI | E60: 31413 | F60: Female | G60: VADLA SHANKAR CHARY | I60: Nursery | J60: Unskilled Gardner | K60: H NO 3-10 MADHRAM | L60: MADHRAM MEDAK | M60: TS-502319 | O60: Gachibowli Village | P60: Hyderabad | Q60: Telangana State | S60: 43885 | X60: 100692721860 | Y60: 5216423961 | Z60: =D60 -> VADLA JYOTHI | AA60: 26 | AB60: 0 | AC60: 10627 | AD60: 3207 | AE60: 4931.3333 | AF60: 0 | AG60: 0 | AH60: 677.73333 | AI60: 394.33333 | AJ60: 0 | AK60: =AD60+AE60+AF60+AG60+AH60+AI60+AJ60 -> 9210.4 | AL60: 70 | AM60: 1105 | AN60: 0 | AO60: 0 | AP60: 0 | AQ60: =AL60+AM60+AN60+AO60+AP60 -> 1175 | AR60: =AK60-AQ60 -> 8035.4 | AS60: 7th May 2020 | AT60: IBKL0000888 | AU60: 0888104000048675'
A61: 47 | B61: GLDPL/EMP/148 | C61: 52 | D61: Rupesh Chandra Jakhmola | E61: 32705 | F61: Male | G61: RAJENDRA PRASAD | I61: Nursery | J61: Manager | K61: KALALGHATI | L61: KOTDWAR | M61: UK 246149 | O61: Gachibowli Village | P61: Hyderabad | Q61: Telangana State | S61: 43892 | X61: 101318416076 | Y61: N/A | Z61: =D61 -> Rupesh Chandra Jakhmola | AA61: 30 | AB61: 0 | AC61: 27800 | AD61: 23000 | AE61: 0 | AF61: 0 | AG61: 0 | AH61: 0 | AI61: 0 | AJ61: 4800 | AK61: =AD61+AE61+AF61+AG61+AH61+AI61+AJ61 -> 27800 | AL61: 0 | AM61: 1800 | AN61: 200 | AO61: 0 | AP61: 0 | AQ61: =AL61+AM61+AN61+AO61+AP61 -> 2000 | AR61: =AK61-AQ61 -> 25800 | AS61: 7th May 2020 | AT61: IDFB0021001 | AU61: 10024839331
A62: 48 | B62: GLDPL/LB/9048 | C62: 53 | D62: Bakkani Mallaiah | E62: 26299 | F62: Male | G62: BAKKANI HANMAIH | I62: Nursery | J62: Semi Skilled Gardner | K62: H NO1-56 | L62: SOMANGUTHI R.R | M62: TS-502319 | O62: Gachibowli Village | P62: Hyderabad | Q62: Telangana State | S62: 43892 | X62: 101567297449 | Y62: 5216113931 | Z62: =D62 -> Bakkani Mallaiah | AA62: 26 | AB62: 0 | AC62: 13753 | AD62: 3844 | AE62: 4931.3333 | AF62: 0 | AG62: 0 | AH62: 730.6 | AI62: 425.53333 | AJ62: 1988.1333 | AK62: =AD62+AE62+AF62+AG62+AH62+AI62+AJ62 -> 11919.6 | AL62: 90 | AM62: 1430 | AN62: 0 | AO62: 0 | AP62: 0 | AQ62: =AL62+AM62+AN62+AO62+AP62 -> 1520 | AR62: =AK62-AQ62 -> 10399.6 | AS62: 7th May 2020 | AT62: SBIN0020092 | AU62: 62325068437
A63: 49 | B63: GLDPL/LB/9049 | C63: 54 | D63: Chakali Narayana | E63: 29221 | F63: Male | G63: CHAKALI PETAIAH | I63: Nursery | J63: Semi Skilled Gardner | K63: H NO 3-7/1 | L63: MADHRAM MEDAK | M63: TS-502319 | O63: Gachibowli Village | P63: Hyderabad | Q63: Telangana State | S63: 43893 | X63: 101567297431 | Y63: 5216452266 | Z63: =D63 -> Chakali Narayana | AA63: 26 | AB63: 0 | AC63: 11459 | AD63: 3844 | AE63: 4931.3333 | AF63: 0 | AG63: 0 | AH63: 730.6 | AI63: 425.53333 | AJ63: 0 | AK63: =AD63+AE63+AF63+AG63+AH63+AI63+AJ63+1 -> 9932.4667 | AL63: 75 | AM63: 1192 | AN63: 0 | AO63: 0 | AP63: 0 | AQ63: =AL63+AM63+AN63+AO63+AP63 -> 1267 | AR63: =AK63-AQ63 -> 8665.4667 | AS63: 7th May 2020 | AT63: SBINORRAPGB | AU63: 73067905502
A64: 50 | B64: GLDPL/LB/9050 | C64: 55 | D64: Mutyala Poshavva | E64: 25934 | F64: Female | G64: MUTYALA BABU | I64: Nursery | J64: Unskilled Gardner | K64: H NO 65/1 | L64: MADHRAM MEDAK | M64: TS-502319 | O64: Gachibowli Village | P64: Hyderabad | Q64: Telangana State | S64: 43894 | X64: 100644249379 | Y64: 5216452300 | Z64: =D64 -> Mutyala Poshavva | AA64: 0 | AB64: 0 | AC64: 10627 | AD64: 0 | AE64: 0 | AF64: 0 | AG64: 0 | AH64: 0 | AI64: 0 | AJ64: 0 | AK64: =AD64+AE64+AF64+AG64+AH64+AI64+AJ64 -> 0 | AL64: 0 | AM64: 0 | AN64: 0 | AO64: 0 | AP64: 0 | AQ64: =AL64+AM64+AN64+AO64+AP64 -> 0 | AR64: =AK64-AQ64 -> 0 | AS64: 7th May 2020 | AT64: Bank Cheque | AU64: Bank Cheque
AA65: =SUM(AA15:AA64) -> 1160 | AB65: =SUM(AB15:AB64) -> 0 | AC65: =SUM(AC15:AC64) -> 587360 | AD65: =SUM(AD15:AD64) -> 206470 | AE65: =SUM(AE15:AE64) -> 202184.67 | AF65: =SUM(AF15:AF64) -> 0 | AG65: =SUM(AG15:AG64) -> 4721 | AH65: =SUM(AH15:AH64) -> 28474.333 | ... AR65: =SUM(AR15:AR64) -> 415659.53
AF69: Signature of the Contractor with Seal

Sheet Employment Cards
B1: FORM XIV
B2: EMPLOYMENT CUM WAGE CARD
B3: (Vide Rule 76 of Contract Labour (R&A) Central & A.P{T.S.} Rules, 1971)
B4: Name and Address of the Contractor | H4: Name and Address of the Establishment in/under which Contract is carried on:
B7: =Master!F5 -> GROTECH LANDSCAPE DEVELOPERS PVT. LTD. | H7: =Master!AN5 -> GROTECH LANDSCAPE DEVELOPERS PVT. LTD.
B9: =Master!F6 -> 290/E, Khanapur Village, Gandipet Mandal, Ranga Reddy, Hyderabad-500075 T.S. | H9: =Master!AN6 -> 290/E, Khanapur Village, Gandipet Mandal, Ranga Reddy, Hyderabad-500075 T.S.
B12: Nature of work and location of work: | H12: Name and address of Principal Employer:
H15: ='Muster Roll'!Z6 -> INDIAN SCHOOL OF BUSINESS
B16: ='Muster Roll'!D4 -> GARDENING SERVICES&ISB HYDERABAD
H17: ='Muster Roll'!Z7 -> Opp.Infosys Limited,Gachibowli,Hyderabad
B19: 1. Name of the Workman and address | H19: =Master!D15 -> ARJUN KUMAR
H20: =Master!K15 -> Village - Dharai
H21: =Master!L15 -> Amethi
H22: =Master!M15 -> Uttar pradesh - 229127
H23: =Master!N15 -> 0
B24: 2. S.No. in the Register of Workmen Employed | H24: =Master!C15 -> 2
B25: 3. Nature of Employment /Designation | H25: =Master!J15 -> Supervisor
B26: 4. Date of entry into service | H26: =Master!S15 -> 43850
B27: 5. ESI No. | H27: =Master!Y15 -> 2016384651
B28: 6.PF No. | H28: =Master!X15 -> N/A
B29: 7. Wage rate (With particulars of unit in case of piece - work) | H29: =Master!AC15 -> 20000
B30: 8. Wage period | H30: =Master!F10 -> 44652
B31: 9. Tenure of Employment | H31: AS PER CONTRACT
B32: 10.No. of days worked in a month | H32: =Master!AA15 -> 30
B33: 11. No. of units worked in case of piece rate workers | H33: N/A
B34: 12. Rate of daily wages / piece rate | H34: 0
B35: 13. Amount of overtime wages | H35: 0
B36: 14. Gross wages payable | J36: =Master!AK15 -> 20000 | L36: ADVANCE
B37: 15. Deductions, if any, | D37: PF | E37: =Master!AM15 -> 0 | F37: ESI | G37: =Master!AL15 -> 150 | H37: PT | I37: =Master!AN15 -> 150 | J37: TDS | K37: =Master!AO15 -> 0 | L37: =Master!AP15 -> 0
B38: 16. Net amount of wages paid | J38: =Master!AR15 -> 19700
B39: Signature of the Representative
B40: of Contractor
B45: FORM XIV
B46: EMPLOYMENT CUM WAGE CARD
B47: (Vide Rule 76 of Contract Labour (R&A) Central & A.P{T.S.} Rules, 1971)
B48: Name and Address of the Contractor | H48: Name and Address of the Establishment in/under which Contract is carried on:
B51: =Master!F5 -> GROTECH LANDSCAPE DEVELOPERS PVT. LTD. | H51: =Master!AN5 -> GROTECH LANDSCAPE DEVELOPERS PVT. LTD.
B53: =Master!F6 -> 290/E, Khanapur Village, Gandipet Mandal, Ranga Reddy, Hyderabad-500075 T.S. | H53: =Master!AN6 -> 290/E, Khanapur Village, Gandipet Mandal, Ranga Reddy, Hyderabad-500075 T.S.
B56: Nature of work and location of work: | H56: Name and address of Principal Employer:
H59: =Master!AN10 -> INDIAN SCHOOL OF BUSINESS
B60: =Master!F8 -> GARDENING SERVICES&ISB HYDERABAD
H61: =Master!AN11 -> Opp.Infosys Limited,Gachibowli,Hyderabad
B63: 1. Name of the Workman and address | H63: =Master!D16 -> GAJAN SINGH
H64: =Master!K16 -> Village - Uncha gaon, Pikhani,
H65: =Master!L16 -> Bulandshahr,
H66: =Master!M16 -> Uttar pradesh - 202398
H67: =Master!N16 -> 0
B68: 2. S.No. in the Register of Workmen Employed | H68: =Master!C16 -> 3
B69: 3. Nature of Employment /Designation | H69: =Master!J16 -> Supervisor
B70: 4. Date of entry into service | H70: =Master!S16 -> 43850
B71: 5. ESI No. | H71: =Master!Y16 -> 2017795829
B72: 6.PF No. | H72: =Master!X16 -> 101252819921
B73: 7. Wage rate (With particulars of unit in case of piece - work) | H73: =Master!AC16 -> 14900
B74: 8. Wage period | H74: =Master!F10 -> 44652
B75: 9. Tenure of Employment | H75: AS PER CONTRACT
B76: 10.No. of days worked in a month | H76: =Master!AA16 -> 30
B77: 11. No. of units worked in case of piece rate workers | H77: N/A
B78: 12. Rate of daily wages / piece rate | H78: 0
B79: 13. Amount of overtime wages | H79: 0
B80: 14. Gross wages payable | J80: =Master!AK16 -> 14900 | L80: ADVANCE
B81: 15. Deductions, if any, | D81: PF | E81: =Master!AM16 -> 1788 | F81: ESI | G81: =Master!AL16 -> 112 | H81: PT | I81: =Master!AN16 -> 0 | J81: TDS | K81: =Master!AO16 -> 0 | L81: =Master!AP16 -> 0
B82: 16. Net amount of wages paid | J82: =Master!AR16 -> 13000
B83: Signature of the Representative
B84: of Contractor
B93: FORM XIV
B94: EMPLOYMENT CUM WAGE CARD
B95: (Vide Rule 76 of Contract Labour (R&A) Central & A.P{T.S.} Rules, 1971)
B96: Name and Address of the Contractor | H96: Name and Address of the Establishment in/under which Contract is carried on:
B99: =Master!F5 -> GROTECH LANDSCAPE DEVELOPERS PVT. LTD. | H99: =Master!AN5 -> GROTECH LANDSCAPE DEVELOPERS PVT. LTD.
B101: =Master!F6 -> 290/E, Khanapur Village, Gandipet Mandal, Ranga Reddy, Hyderabad-500075 T.S. | H101: =Master!AN6 -> 290/E, Khanapur Village, Gandipet Mandal, Ranga Reddy, Hyderabad-500075 T.S.
B104: Nature of work and location of work: | H104: Name and address of Principal Employer:
H107: =Master!AN10 -> INDIAN SCHOOL OF BUSINESS
B108: =Master!F8 -> GARDENING SERVICES&ISB HYDERABAD
H109: =Master!AN11 -> Opp.Infosys Limited,Gachibowli,Hyderabad
B111: 1. Name of the Workman and address | H111: =Master!D17 -> GUDALA RUSHESHWAR SWAMY
H112: =Master!K17 -> House no. - 8-153 Kottapeta
H113: =Master!L17 -> Gummaluru, west godavari
H114: =Master!M17 -> Andhra pradesh - 534267
B115: 2. S.No. in the Register of Workmen Employed | H115: =Master!C17 -> 4
B116: 3. Nature of Employment /Designation | H116: =Master!J17 -> Supervisor
B117: 4. Date of entry into service | H117: =Master!S17 -> 43850
B118: 5. ESI No. | H118: =Master!Y17 -> 5216113872
B119: 6.PF No. | H119: =Master!X17 -> 100025787555
B120: 7. Wage rate (With particulars of unit in case of piece - work) | H120: =Master!AC17 -> 17918
B121: 8. Wage period | H121: =Master!F10 -> 44652
B122: 9. Tenure of Employment | H122: AS PER CONTRACT
B123: 10.No. of days worked in a month | H123: =Master!AA17 -> 30
B124: 11. No. of units worked in case of piece rate workers | H124: N/A
B125: 12. Rate of daily wages / piece rate | H125: 0
B126: 13. Amount of overtime wages | H126: 0
B127: 14. Gross wages payable | J127: =Master!AK17 -> 17918 | L127: ADVANCE
B128: 15. Deductions, if any, | D128: PF | E128: =Master!AM17 -> 1584 | F128: ESI | G128: =Master!AL17 -> 135 | H128: PT | I128: =Master!AN17 -> 150 | J128: TDS | K128: =Master!AO17 -> 0 | L128: =Master!AP17 -> 0
B129: 16. Net amount of wages paid | J129: =Master!AR17 -> 16049
B130: Signature of the Representative
B131: of Contractor
B141: FORM XIV
B142: EMPLOYMENT CUM WAGE CARD
B143: (Vide Rule 76 of Contract Labour (R&A) Central & A.P{T.S.} Rules, 1971)
B144: Name and Address of the Contractor | H144: Name and Address of the Establishment in/under which Contract is carried on:
B147: =Master!F5 -> GROTECH LANDSCAPE DEVELOPERS PVT. LTD. | H147: =Master!AN5 -> GROTECH LANDSCAPE DEVELOPERS PVT. LTD.
...

Sheet Serive Certificate
B2: FORM XV
B3: [Vide rule 77 of Contract Labour (Regul. & Abolition) Central & A.P.{T.S.} Rules, 1971]
B4: SERVICE CERTIFICATE
B6: Name and address of Contractor : | G6: Name and address of establishment in / under which contract is caried on :
B8: =Master!F5 -> GROTECH LANDSCAPE DEVELOPERS PVT. LTD. | G8: =Master!AN5 -> GROTECH LANDSCAPE DEVELOPERS PVT. LTD.
B10: =Master!F6 -> 290/E, Khanapur Village, Gandipet Mandal, Ranga Reddy, Hyderabad-500075 T.S. | G10: =Master!AN6 -> 290/E, Khanapur Village, Gandipet Mandal, Ranga Reddy, Hyderabad-500075 T.S.
B14: Nature and Location of work: | G14: Name and address of Principal Employer :
G16: =Master!AN10 -> INDIAN SCHOOL OF BUSINESS
B18: =Master!F8 -> GARDENING SERVICES&ISB HYDERABAD | G18: =Master!AN11 -> Opp.Infosys Limited,Gachibowli,Hyderabad
B21: Name and address of the workman : | G21: =Master!D15 -> ARJUN KUMAR
G22: =Master!K15 -> Village - Dharai
G23: =Master!L15 -> Amethi
G24: =Master!M15 -> Uttar pradesh - 229127
B25: Age or date of Birth : | G25: =Master!E15 -> 31413
B26: Identification Marks :
B28: Father's / Husband's Name : | G28: =Master!G15 -> kallu
B30: Sl.No. | C30: Total period for which employed | E30: Nature of work done | G30: Rate of wage ( with particulars of units in case of piece work) | J30: Remarks
C32: From | D32: To
B33: 1 | C33: 2 | D33: 3 | E33: 4 | G33: 5 | J33: 6
B34: =Master!C15 -> 2 | C34: =Master!S15 -> 43850 | D34: ='Workmen Reg'!O12 -> 31st May 2020 | E34: =Master!J15 -> Supervisor | G34: =Master!AC15 -> 20000 | J34: =Master!V15 -> 0
H47: Signature of the Employer with Seal

Sheet Muster Roll
A1: FORM - XVI MUSTER ROLL [Vide Rule 78 (1) (a) (i) of Contract Labour (Reg. & Abolition) Central & AP{TS} Rules 1971]
A2: Name and address of Contractor: | D2: =Master!F5 -> GROTECH LANDSCAPE DEVELOPERS PVT. LTD. | J2: Name and address of Establishemnt in/ under which contract is carried on: | Z2: =Master!AN5 -> GROTECH LANDSCAPE DEVELOPERS PVT. LTD.
D3: =Master!F6 -> 290/E, Khanapur Village, Gandipet Mandal, Ranga Reddy, Hyderabad-500075 T.S. | Z3: =Master!AN6 -> 290/E, Khanapur Village, Gandipet Mandal, Ranga Reddy, Hyderabad-500075 T.S.
A4: Nature and location of work: | D4: =Master!F8 -> GARDENING SERVICES&ISB HYDERABAD
A6: Wage period: Monthly | D6: =Master!F10 -> 44652 | J6: Name and address of Principal Employer: | Z6: =Master!AN10 -> INDIAN SCHOOL OF BUSINESS
Z7: =Master!AN11 -> Opp.Infosys Limited,Gachibowli,Hyderabad
A8: S.No | B8: Name of Workman | C8: Father's/ Husband's Name | D8: Sex | AJ8: Remarks
E9: 1 | F9: 2 | G9: 3 | H9: 4 | I9: 5 | J9: 6 | K9: 7 | L9: 8 | M9: 9 | N9: 10 | O9: 11 | P9: 12 | Q9: 13 | R9: 14 | S9: 15 | T9: 16 | U9: 17 | V9: 18 | W9: 19 | X9: 20 | Y9: 21 | Z9: 22 | AA9: 23 | AB9: 24 | AC9: 25 | AD9: 26 | AE9: 27 | AF9: 28 | AG9: 29 | AH9: 30 | AI9: 31
A10: 1 | B10: =Master!D15 -> ARJUN KUMAR | C10: =Master!G15 -> kallu | D10: =Master!F15 -> Male | E10: p | F10: p | G10: p | H10: p | I10: w/o | J10: p | K10: p | L10: p | M10: p | N10: p | O10: p | P10: w/o | Q10: p | R10: p | S10: p | T10: p | U10: p | V10: p | W10: w/o | X10: p | Y10: p | Z10: p | AA10: p | AB10: p | AC10: p | AD10: w/o | AE10: p | AF10: p | AG10: p | AH10: p | AJ10: =Master!AA15 -> 30
A11: 2 | B11: =Master!D16 -> GAJAN SINGH | C11: =Master!G16 -> Chandrapal singh | D11: =Master!F16 -> Male | E11: p | F11: p | G11: p | H11: p | I11: w/o | J11: p | K11: p | L11: p | M11: p | N11: p | O11: p | P11: w/o | Q11: p | R11: p | S11: p | T11: p | U11: p | V11: p | W11: w/o | X11: p | Y11: p | Z11: p | AA11: p | AB11: p | AC11: p | AD11: w/o | AE11: p | AF11: p | AG11: p | AH11: p | AJ11: =Master!AA16 -> 30
A12: 3 | B12: =Master!D17 -> GUDALA RUSHESHWAR SWAMY | C12: =Master!G17 -> GUDALA KRISHANA MURTHY | D12: =Master!F17 -> Male | E12: c | F12: C | G12: c | H12: c | I12: w/o | J12: c | K12: c | L12: c | M12: c | N12: c | O12: c | P12: w/o | Q12: c | R12: c | S12: C | T12: c | U12: c | V12: c | W12: w/o | X12: c | Y12: c | Z12: c | AA12: C | AB12: c | AC12: c | AD12: w/o | AE12: c | AF12: c | AG12: c | AH12: c | AJ12: =Master!AA17 -> 30
A13: 4 | B13: =Master!D18 -> KASALA NARSIMLU | C13: =Master!G18 -> KASALA POCHAIAH | D13: =Master!F18 -> Male | E13: c | F13: C | G13: c | H13: c | I13: w/o | J13: c | K13: c | L13: c | M13: c | N13: c | O13: c | P13: w/o | Q13: c | R13: c | S13: C | T13: c | U13: c | V13: c | W13: w/o | X13: c | Y13: c | Z13: c | AA13: C | AB13: c | AC13: c | AD13: w/o | AE13: c | AF13: c | AG13: C | AH13: c | AJ13: =Master!AA18 -> 26
A14: 5 | B14: =Master!D19 -> PITANI SATHYA NARAYANA | C14: =Master!G19 -> P SURYANARAYANA | D14: =Master!F19 -> Male | E14: c | F14: C | G14: c | H14: c | I14: w/o | J14: c | K14: c | L14: c | M14: c | N14: c | O14: c | P14: w/o | Q14: c | R14: c | S14: C | T14: c | U14: c | V14: c | W14: w/o | X14: c | Y14: c | Z14: c | AA14: C | AB14: c | AC14: c | AD14: w/o | AE14: c | AF14: c | AG14: C | AH14: c | AJ14: =Master!AA19 -> 26
A15: 6 | B15: =Master!D20 -> SANGOLLA ASHOK | C15: =Master!G20 -> SANGOLLA ESWARAIAH | D15: =Master!F20 -> Male | E15: c | F15: C | G15: c | H15: c | I15: w/o | J15: c | K15: c | L15: c | M15: c | N15: c | O15: c | P15: w/o | Q15: c | R15: c | S15: C | T15: c | U15: c | V15: c | W15: w/o | X15: c | Y15: c | Z15: c | AA15: C | AB15: c | AC15: c | AD15: w/o | AE15: c | AF15: c | AG15: C | AH15: c | AJ15: =Master!AA20 -> 26
A16: 7 | B16: =Master!D21 -> ASHOK LINGURAM GAIKWAD | C16: =Master!G21 -> M LINGRAM | D16: =Master!F21 -> Male | E16: c | F16: C | G16: c | H16: c | I16: w/o | J16: c | K16: c | L16: c | M16: c | N16: c | O16: c | P16: w/o | Q16: c | R16: c | S16: C | T16: c | U16: c | V16: c | W16: w/o | X16: c | Y16: c | Z16: c | AA16: C | AB16: c | AC16: c | AD16: w/o | AE16: c | AF16: c | AG16: C | AH16: c | AJ16: =Master!AA21 -> 26
A17: 8 | B17: =Master!D22 -> MADHUKAR KAMTAM | C17: =Master!G22 -> KAMTAM KISHAN | D17: =Master!F22 -> Male | E17: c | F17: C | G17: c | H17: c | I17: w/o | J17: c | K17: c | L17: c | M17: c | N17: c | O17: c | P17: w/o | Q17: c | R17: c | S17: C | T17: c | U17: c | V17: c | W17: w/o | X17: c | Y17: c | Z17: c | AA17: C | AB17: c | AC17: c | AD17: w/o | AE17: c | AF17: c | AG17: C | AH17: c | AJ17: =Master!AA22 -> 26
A18: 9 | B18: =Master!D23 -> Ningolla Raju | C18: =Master!G23 -> ningolla pochaiah | D18: =Master!F23 -> Male | E18: c | F18: C | G18: c | H18: c | I18: w/o | J18: c | K18: c | L18: c | M18: c | N18: c | O18: c | P18: w/o | Q18: c | R18: c | S18: C | T18: c | U18: c | V18: c | W18: w/o | X18: c | Y18: c | Z18: c | AA18: C | AB18: c | AC18: c | AD18: w/o | AE18: c | AF18: c | AG18: C | AH18: c | AJ18: =Master!AA23 -> 26
A19: 10 | B19: =Master!D24 -> Nagani pochaiah | C19: =Master!G24 -> Nagani mallaiah | D19: =Master!F24 -> Male | E19: c | F19: C | G19: c | H19: c | I19: w/o | J19: c | K19: c | L19: c | M19: c | N19: c | O19: c | P19: w/o | Q19: c | R19: c | S19: C | T19: c | U19: c | V19: c | W19: w/o | X19: c | Y19: c | Z19: c | AA19: C | AB19: c | AC19: c | AD19: w/o | AE19: c | AF19: c | AG19: C | AH19: c | AJ19: =Master!AA24 -> 26
A20: 11 | B20: =Master!D25 -> Mutholla Mallesh | C20: =Master!G25 -> Mutholla balaiah | D20: =Master!F25 -> Male | E20: c | F20: C | G20: c | H20: c | I20: w/o | J20: c | K20: c | L20: c | M20: c | N20: c | O20: c | P20: w/o | Q20: c | R20: c | S20: C | T20: c | U20: c | V20: c | W20: w/o | X20: c | Y20: c | Z20: c | AA20: C | AB20: c | AC20: c | AD20: w/o | AE20: c | AF20: c | AG20: C | AH20: c | AJ20: =Master!AA25 -> 26
A21: 12 | B21: =Master!D26 -> ALIJANA JAYARAMI REDDY | C21: =Master!G26 -> ALIJANA OBULU REDDY | D21: =Master!F26 -> Male | E21: c | F21: C | G21: c | H21: c | I21: w/o | J21: c | K21: c | L21: c | M21: c | N21: c | O21: c | P21: w/o | Q21: c | R21: c | S21: C | T21: c | U21: c | V21: c | W21: w/o | X21: c | Y21: c | Z21: c | AA21: C | AB21: c | AC21: c | AD21: w/o | AE21: c | AF21: c | AG21: C | AH21: c | AJ21: =Master!AA26 -> 26
A22: 13 | B22: =Master!D27 -> Kapil | C22: =Master!G27 -> Ganesh lal | D22: =Master!F27 -> Male | AJ22: =Master!AA27 -> 0
A23: 14 | B23: =Master!D28 -> Bablu kumar | C23: =Master!G28 -> Harilal | D23: =Master!F28 -> Male | AJ23: =Master!AA28 -> 0
A24: 15 | B24: =Master!D29 -> Pradeep kumar | C24: =Master!G29 -> Jagdev | D24: =Master!F29 -> Male | AJ24: =Master!AA29 -> 0
A25: 16 | B25: =Master!D30 -> SHAIK KULSUM BEE | C25: =Master!G30 -> SHAIK LALA | D25: =Master!F30 -> Female | E25: c | F25: C | G25: c | H25: c | I25: w/o | J25: c | K25: c | L25: c | M25: c | N25: c | O25: c | P25: w/o | Q25: c | R25: c | S25: C | T25: c | U25: c | V25: c | W25: w/o | X25: c | Y25: c | Z25: c | AA25: C | AB25: c | AC25: c | AD25: w/o | AE25: c | AF25: c | AG25: C | AH25: c | AJ25: =Master!AA30 -> 26
A26: 17 | B26: =Master!D31 -> S GOWRI | C26: =Master!G31 -> S SURYANARAYANA | D26: =Master!F31 -> Female | E26: c | F26: C | G26: c | H26: c | I26: w/o | J26: c | K26: c | L26: c | M26: c | N26: c | O26: c | P26: w/o | Q26: c | R26: c | S26: C | T26: c | U26: c | V26: c | W26: w/o | X26: c | Y26: c | Z26: c | AA26: C | AB26: c | AC26: c | AD26: w/o | AE26: c | AF26: c | AG26: C | AH26: c | AJ26: =Master!AA31 -> 26
A27: 18 | B27: =Master!D32 -> FARZANA BEGUM | C27: =Master!G32 -> SHAIK MASTAN WALI | D27: =Master!F32 -> Female | E27: c | F27: C | G27: c | H27: c | I27: w/o | J27: c | K27: c | L27: c | M27: c | N27: c | O27: c | P27: w/o | Q27: c | R27: c | S27: C | T27: c | U27: c | V27: c | W27: w/o | X27: c | Y27: c | Z27: c | AA27: C | AB27: c | AC27: c | AD27: w/o | AE27: c | AF27: c | AG27: C | AH27: c | AJ27: =Master!AA32 -> 26
A28: 19 | B28: =Master!D33 -> MANAGALI SUHASINI | C28: =Master!G33 -> MANGALI RAJU | D28: =Master!F33 -> Female | E28: c | F28: C | G28: c | H28: c | I28: w/o | J28: c | K28: c | L28: c | M28: c | N28: c | O28: c | P28: w/o | Q28: c | R28: c | S28: C | T28: c | U28: c | V28: c | W28: w/o | X28: c | Y28: c | Z28: c | AA28: C | AB28: c | AC28: c | AD28: w/o | AE28: c | AF28: c | AG28: C | AH28: c | AJ28: =Master!AA33 -> 26
A29: 20 | B29: =Master!D34 -> KONA SUJATHA | C29: =Master!G34 -> KONA SURYANARAYANA | D29: =Master!F34 -> Female | E29: c | F29: C | G29: c | H29: c | I29: w/o | J29: c | K29: c | L29: c | M29: c | N29: c | O29: c | P29: w/o | Q29: c | R29: c | S29: C | T29: c | U29: c | V29: c | W29: w/o | X29: c | Y29: c | Z29: c | AA29: C | AB29: c | AC29: c | AD29: w/o | AE29: c | AF29: c | AG29: C | AH29: c | AJ29: =Master!AA34 -> 26
A30: 21 | B30: =Master!D35 -> GOLLA UMA | C30: =Master!G35 -> GOLLA ONURU SWAMY | D30: =Master!F35 -> Female | E30: c | F30: C | G30: c | H30: c | I30: w/o | J30: c | K30: c | L30: c | M30: c | N30: c | O30: c | P30: w/o | Q30: c | R30: c | S30: C | T30: c | U30: c | V30: c | W30: w/o | X30: c | Y30: c | Z30: c | AA30: C | AB30: c | AC30: c | AD30: w/o | AE30: c | AF30: c | AG30: C | AH30: c | AJ30: =Master!AA35 -> 26
A31: 22 | B31: =Master!D36 -> SINGARAM BHAGYAMMA | C31: =Master!G36 -> SINGARAM NARSIMULU | D31: =Master!F36 -> Female | E31: c | F31: C | G31: c | H31: c | I31: w/o | J31: c | K31: c | L31: c | M31: c | N31: c | O31: c | P31: w/o | Q31: c | R31: c | S31: C | T31: c | U31: c | V31: c | W31: w/o | X31: c | Y31: c | Z31: c | AA31: C | AB31: c | AC31: c | AD31: w/o | AE31: c | AF31: c | AG31: C | AH31: c | AJ31: =Master!AA36 -> 26
A32: 23 | B32: =Master!D37 -> KODICHERLA INDIRAMMA | C32: =Master!G37 -> BABAIAH | D32: =Master!F37 -> Female | E32: c | F32: C | G32: c | H32: c | I32: w/o | J32: c | K32: c | L32: c | M32: c | N32: c | O32: c | P32: w/o | Q32: c | R32: c | S32: C | T32: c | U32: c | V32: c | W32: w/o | X32: c | Y32: c | Z32: c | AA32: C | AB32: c | AC32: c | AD32: w/o | AE32: c | AF32: c | AG32: C | AH32: c | AJ32: =Master!AA37 -> 26
A33: 24 | B33: =Master!D38 -> SANGOLLA LAVANYA | C33: =Master!G38 -> SANGOLLA ASHOK | D33: =Master!F38 -> Female | E33: c | F33: C | G33: c | H33: c | I33: w/o | J33: c | K33: c | L33: c | M33: c | N33: c | O33: c | P33: w/o | Q33: c | R33: c | S33: C | T33: c | U33: c | V33: c | W33: w/o | X33: c | Y33: c | Z33: c | AA33: C | AB33: c | AC33: c | AD33: w/o | AE33: c | AF33: c | AG33: C | AH33: c | AJ33: =Master!AA38 -> 26
A34: 25 | B34: =Master!D39 -> MANGALI LAVANYA | C34: =Master!G39 -> MANGALI PANDU | D34: =Master!F39 -> Female | E34: c | F34: C | G34: c | H34: c | I34: w/o | J34: c | K34: c | L34: c | M34: c | N34: c | O34: c | P34: w/o | Q34: c | R34: c | S34: C | T34: c | U34: c | V34: c | W34: w/o | X34: c | Y34: c | Z34: c | AA34: C | AB34: c | AC34: c | AD34: w/o | AE34: c | AF34: c | AG34: C | AH34: c | AJ34: =Master!AA39 -> 26
A35: 26 | B35: =Master!D40 -> MANGLI CHANDRAMMA | C35: =Master!G40 -> MANGALI VENKATESH | D35: =Master!F40 -> Female | E35: c | F35: C | G35: c | H35: c | I35: w/o | J35: c | K35: c | L35: c | M35: c | N35: c | O35: c | P35: w/o | Q35: c | R35: c | S35: C | T35: c | U35: c | V35: c | W35: w/o | X35: c | Y35: c | Z35: c | AA35: C | AB35: c | AC35: c | AD35: w/o | AE35: c | AF35: c | AG35: C | AH35: c | AJ35: =Master!AA40 -> 26
A36: 27 | B36: =Master!D41 -> DASARI SUVARNA | C36: =Master!G41 -> DASARI RAVINDAR | D36: =Master!F41 -> Female | AJ36: =Master!AA41 -> 0
A37: 28 | B37: =Master!D42 -> MARATHI CHANDRAKALA | C37: =Master!G42 -> M ASHOKS | D37: =Master!F42 -> Female | E37: c | F37: C | G37: c | H37: c | I37: w/o | J37: c | K37: c | L37: c | M37: c | N37: c | O37: c | P37: w/o | Q37: c | R37: c | S37: C | T37: c | U37: c | V37: c | W37: w/o | X37: c | Y37: c | Z37: c | AA37: C | AB37: c | AC37: c | AD37: w/o | AE37: c | AF37: c | AG37: C | AH37: c | AJ37: =Master!AA42 -> 26
A38: 29 | B38: =Master!D43 -> ANKAGALLA YADAMMA | C38: =Master!G43 -> ANKAGALLA YADAGIRI | D38: =Master!F43 -> Female | E38: c | F38: C | G38: c | H38: c | I38: w/o | J38: c | K38: c | L38: c | M38: c | N38: c | O38: c | P38: w/o | Q38: c | R38: c | S38: C | T38: c | U38: c | V38: c | W38: w/o | X38: c | Y38: c | Z38: c | AA38: C | AB38: c | AC38: c | AD38: w/o | AE38: c | AF38: c | AG38: C | AH38: c | AJ38: =Master!AA43 -> 26
A39: 30 | B39: =Master!D44 -> NINGAMMA | C39: =Master!G44 -> RAMANNA | D39: =Master!F44 -> Female | E39: c | F39: C | G39: c | H39: c | I39: w/o | J39: c | K39: c | L39: c | M39: c | N39: c | O39: c | P39: w/o | Q39: c | R39: c | S39: C | T39: c | U39: c | V39: c | W39: w/o | X39: c | Y39: c | Z39: c | AA39: C | AB39: c | AC39: c | AD39: w/o | AE39: c | AF39: c | AG39: C | AH39: c | AJ39: =Master!AA44 -> 26
A40: 31 | B40: =Master!D45 -> V AMBAMMA | C40: =Master!G45 -> V YELLAIAH | D40: =Master!F45 -> Female | E40: c | F40: C | G40: c | H40: c | I40: w/o | J40: c | K40: c | L40: c | M40: c | N40: c | O40: c | P40: w/o | Q40: c | R40: c | S40: C | T40: c | U40: c | V40: c | W40: w/o | X40: c | Y40: c | Z40: c | AA40: C | AB40: c | AC40: c | AD40: w/o | AE40: c | AF40: c | AG40: C | AH40: c | AJ40: =Master!AA45 -> 26
A41: 32 | B41: =Master!D46 -> PALLAPU LAXMI | C41: =Master!G46 -> VENAKAIAH | D41: =Master!F46 -> Female | E41: c | F41: C | G41: c | H41: c | I41: w/o | J41: c | K41: c | L41: c | M41: c | N41: c | O41: c | P41: w/o | Q41: c | R41: c | S41: C | T41: c | U41: c | V41: c | W41: w/o | X41: c | Y41: c | Z41: c | AA41: C | AB41: c | AC41: c | AD41: w/o | AE41: c | AF41: c | AG41: C | AH41: c | AJ41: =Master!AA46 -> 26
A42: 33 | B42: =Master!D47 -> Nagani laxmi | C42: =Master!G47 -> Nagani pochaiah | D42: =Master!F47 -> Female | E42: c | F42: C | G42: c | H42: c | I42: w/o | J42: c | K42: c | L42: c | M42: c | N42: c | O42: c | P42: w/o | Q42: c | R42: c | S42: C | T42: c | U42: c | V42: c | W42: w/o | X42: c | Y42: c | Z42: c | AA42: C | AB42: c | AC42: c | AD42: w/o | AE42: c | AF42: c | AG42: C | AH42: c | AJ42: =Master!AA47 -> 26
A43: 34 | B43: =Master!D48 -> Lingola amrutha | C43: =Master!G48 -> Ningolla swamy | D43: =Master!F48 -> Female | E43: c | F43: C | G43: c | H43: c | I43: w/o | J43: c | K43: c | L43: c | M43: c | N43: c | O43: c | P43: w/o | Q43: c | R43: c | S43: C | T43: c | U43: c | V43: c | W43: w/o | X43: c | Y43: c | Z43: c | AA43: C | AB43: c | AC43: c | AD43: w/o | AE43: c | AF43: c | AG43: C | AH43: c | AJ43: =Master!AA48 -> 26
A44: 35 | B44: =Master!D49 -> Kuduru satyamma | C44: =Master!G49 -> NARAYANA | D44: =Master!F49 -> Female | E44: c | F44: C | G44: c | H44: c | I44: w/o | J44: c | K44: c | L44: c | M44: c | N44: c | O44: c | P44: w/o | Q44: c | R44: c | S44: C | T44: c | U44: c | V44: c | W44: w/o | X44: c | Y44: c | Z44: c | AA44: C | AB44: c | AC44: c | AD44: w/o | AE44: c | AF44: c | AG44: C | AH44: c | AJ44: =Master!AA49 -> 26
A45: 36 | B45: =Master!D50 -> Mangali Lakshmi | C45: =Master!G50 -> MANGALI PEDDA | D45: =Master!F50 -> Female | E45: c | F45: C | G45: c | H45: c | I45: w/o | J45: c | K45: c | L45: c | M45: c | N45: c | O45: c | P45: w/o | Q45: c | R45: c | S45: C | T45: c | U45: c | V45: c | W45: w/o | X45: c | Y45: c | Z45: c | AA45: C | AB45: c | AC45: c | AD45: w/o | AE45: c | AF45: c | AG45: C | AH45: c | AJ45: =Master!AA50 -> 26
A46: 37 | B46: =Master!D51 -> Ningolla santhosha | C46: =Master!G51 -> NINGOLLA RAJU | D46: =Master!F51 -> Female | E46: c | F46: C | G46: c | H46: c | I46: w/o | J46: c | K46: c | L46: c | M46: c | N46: c | O46: c | P46: w/o | Q46: c | R46: c | S46: C | T46: c | U46: c | V46: c | W46: w/o | X46: c | Y46: c | Z46: c | AA46: C | AB46: c | AC46: c | AD46: w/o | AE46: c | AF46: c | AG46: C | AH46: c | AJ46: =Master!AA51 -> 26
A47: 38 | B47: =Master!D52 -> Mutholla Suneeta | C47: =Master!G52 -> MUTHOLLA MALLESH | D47: =Master!F52 -> Female | E47: c | F47: C | G47: c | H47: c | I47: w/o | J47: c | K47: c | L47: c | M47: c | N47: c | O47: c | P47: w/o | Q47: c | R47: c | S47: C | T47: c | U47: c | V47: c | W47: w/o | X47: c | Y47: c | Z47: c | AA47: C | AB47: c | AC47: c | AD47: w/o | AE47: c | AF47: c | AG47: C | AH47: c | AJ47: =Master!AA52 -> 26
A48: 39 | B48: =Master!D53 -> Mutholla sushila | C48: =Master!G53 -> MUTHOLLA CHANDRA | D48: =Master!F53 -> Female | E48: c | F48: C | G48: c | H48: c | I48: w/o | J48: c | K48: c | L48: c | M48: c | N48: c | O48: c | P48: w/o | Q48: c | R48: c | S48: C | T48: c | U48: c | V48: c | W48: w/o | X48: c | Y48: c | Z48: c | AA48: C | AB48: c | AC48: c | AD48: w/o | AE48: c | AF48: c | AG48: C | AH48: c | AJ48: =Master!AA53 -> 26
... A58: 49 | B58: =Master!D63 -> Chakali Narayana | C58: =Master!G63 -> CHAKALI PETAIAH | D58: =Master!F63 -> Male | E58: c | F58: C | G58: c | H58: c | I58: w/o | J58: c | K58: c | L58: c | M58: c | N58: c | O58: c | P58: w/o | Q58: c | R58: c | S58: C | T58: c | U58: c | V58: c | W58: w/o | X58: c | Y58: c | Z58: c | AA58: C | AB58: c | AC58: c | AD58: w/o | AE58: c | AF58: c | AG58: C | AH58: c | AJ58: =Master!AA63 -> 26
A59: 50 | B59: =Master!D64 -> Mutyala Poshavva | C59: =Master!G64 -> MUTYALA BABU | D59: =Master!F64 -> Female | AJ59: =Master!AA64 -> 0
J61: Signature of the Contractor with Seal

Sheet Leave register
B1: FORM XXV- REGISTER OF LEAVE
B3: (Vide Rule 29(6) of A.P.{T.S.} Shops & Establishments Rules,1990)
B4: Name and address of the Establishment/Shop: | F4: =Master!F5 -> GROTECH LANDSCAPE DEVELOPERS PVT. LTD. | I4: Name of the Employee:
C5: =Master!F6 -> 290/E, Khanapur Village, Gandipet Mandal, Ranga Reddy, Hyderabad-500075 T.S. | I5: =Master!D15 -> ARJUN KUMAR
B7: Registration Number:
I8: Father’s / Husband’s Name:
I9: =Master!G15 -> kallu
I10: Date of appointment : | L10: =Master!S15 -> 43850
B11: Date of Application | C11: APPLIED | F11: No. of Days to which the employee is entitled | G11: LEAVE GRANTED | J11: Balance | K11: IF REFUSED IN PART OR FULL | N11: REASONS | O11: SIGNATURE OF
C12: Form(Date) | D12: To(Date) | E12: No. of Days | G12: Form(Date) | H12: To(Date) | I12: No. of Days | K12: Form(Date) | L12: To(Date) | M12: No. of Days | O12: Employee | P12: Employer
B13: 1 | C13: 2 | D13: 3 | E13: 4 | F13: 5 | G13: 6 | H13: 7 | I13: 8 | J13: 9 | K13: 10 | L13: 11 | M13: 12 | N13: 13 | O13: 14 | P13: 15
B14: LEAVE WITH WAGES
B15: JAN'20 | C15: 0 | D15: 0 | E15: 0 | F15: 1 | G15: 0 | H15: 0 | I15: 0 | J15: 1 | K15: NO | L15: N/A | M15: N/A | N15: N/A
B23: SICK LEAVE
B27: CASUAL LEAVE

Sheet wages Reg
A1: FORM - XVII REGISTER OF WAGES [Vide Rule 78 (1) (a) (i) of Contract Labour (Reg. & Abolition) Central & A.P.{T.S.}.Rules 1971]
A3: Name and address of Contractor: | D3: =Master!F5 -> GROTECH LANDSCAPE DEVELOPERS PVT. LTD. | O3: Name and address of Establishemnt in/ under which contract is carried on: | U3: =Master!AN5 -> GROTECH LANDSCAPE DEVELOPERS PVT. LTD.
D4: =Master!F6 -> 290/E, Khanapur Village, Gandipet Mandal, Ranga Reddy, Hyderabad-500075 T.S. | U4: =Master!AN6 -> 290/E, Khanapur Village, Gandipet Mandal, Ranga Reddy, Hyderabad-500075 T.S.
A5: Nature and location of work: | D5: =Master!F8 -> GARDENING SERVICES&ISB HYDERABAD
A7: Wage period: Monthly | D7: =Master!F10 -> 44652 | O7: Name and address of Principal Employer: | U7: =Master!AN10 -> INDIAN SCHOOL OF BUSINESS
U8: =Master!AN11 -> Opp.Infosys Limited,Gachibowli,Hyderabad
A10: S.No | B10: Name of Workman | C10: Serial No. in the Register of Workmen | D10: Designation / Nature of Work Done | E10: No.of Days worked | F10: Unit of work done | G10: Monthly rate of wages/ piece rate | H10: Basic wages | I10: Dearness Allowances | J10: Over time | K10: (Other cash payments(Nature of payments to be indicated) | O10: TOTAL AMOUNT | P10: Deductions, if any, (Indicate nature) | V10: Net Amount paid | W10: Time and Date of Payment | X10: Place of Payment | Y10: Signature/Thumb Impression of workman | Z10: Initial of Contractor or his representative
K11: HRA | L11: BONUS | M11: LTA | N11: SPECIAL ALLOWNANCES | P11: ESI | Q11: PF | R11: PT | S11: TDS | T11: Advance | U11: Total Deductions
A12: 1 | B12: =Master!D15 -> ARJUN KUMAR | C12: =Master!C15 -> 2 | D12: =Master!J15 -> Supervisor | E12: =Master!AA15 -> 30 | F12: N/A | G12: =Master!AC15 -> 20000 | H12: =Master!AD15 -> 20000 | I12: =Master!AE15 -> 0 | J12: =Master!AB15 -> 0 | K12: =Master!AG15 -> 0 | L12: =Master!AH15 -> 0 | M12: =Master!AI15 -> 0 | N12: =Master!AJ15 -> 0 | O12: =H12+I12+J12+K12+L12+M12+N12 -> 20000 | P12: =Master!AL15 -> 150 | Q12: =Master!AM15 -> 0 | R12: =Master!AN15 -> 150 | S12: =Master!AO15 -> 0 | T12: =Master!AP15 -> 0 | U12: =Master!AQ15 -> 300 | V12: =O12-U12 -> 19700 | W12: =Master!AS15 -> 7th May 2020 | X12: =Master!AT15 -> KKBK0000205 | Y12: =Master!AU15 -> 6912137285
A13: 2 | B13: =Master!D16 -> GAJAN SINGH | C13: =Master!C16 -> 3 | D13: =Master!J16 -> Supervisor | E13: =Master!AA16 -> 30 | F13: N/A | G13: =Master!AC16 -> 14900 | H13: =Master!AD16 -> 11900 | I13: =Master!AE16 -> 0 | J13: =Master!AB16 -> 0 | K13: =Master!AG16 -> 0 | L13: =Master!AH16 -> 0 | M13: =Master!AI16 -> 0 | N13: =Master!AJ16 -> 3000 | O13: =H13+I13+J13+K13+L13+M13+N13 -> 14900 | P13: =Master!AL16 -> 112 | Q13: =Master!AM16 -> 1788 | R13: =Master!AN16 -> 0 | S13: =Master!AO16 -> 0 | T13: =Master!AP16 -> 0 | U13: =Master!AQ16 -> 1900 | V13: =O13-U13 -> 13000 | W13: =Master!AS16 -> 7th May 2020 | X13: =Master!AT16 -> KKBK0000205 | Y13: =Master!AU16 -> 7513074030
A14: 3 | B14: =Master!D17 -> GUDALA RUSHESHWAR SWAMY | C14: =Master!C17 -> 4 | D14: =Master!J17 -> Supervisor | E14: =Master!AA17 -> 30 | F14: N/A | G14: =Master!AC17 -> 17918 | H14: =Master!AD17 -> 11802 | I14: =Master!AE17 -> 0 | J14: =Master!AB17 -> 0 | K14: =Master!AG17 -> 4721 | L14: =Master!AH17 -> 0 | M14: =Master!AI17 -> 0 | N14: =Master!AJ17 -> 1395 | O14: =H14+I14+J14+K14+L14+M14+N14 -> 17918 | P14: =Master!AL17 -> 135 | Q14: =Master!AM17 -> 1584 | R14: =Master!AN17 -> 150 | S14: =Master!AO17 -> 0 | T14: =Master!AP17 -> 0 | U14: =Master!AQ17 -> 1869 | V14: =O14-U14 -> 16049 | W14: =Master!AS17 -> 7th May 2020 | X14: =Master!AT17 -> KKBK0007476 | Y14: =Master!AU17 -> 1912391941
A15: 4 | B15: =Master!D18 -> KASALA NARSIMLU | C15: =Master!C18 -> 6 | D15: =Master!J18 -> Semi Skilled Gardner | E15: =Master!AA18 -> 26 | F15: N/A | G15: =Master!AC18 -> 13753 | H15: =Master!AD18 -> 3844 | I15: =Master!AE18 -> 4931.3333 | J15: =Master!AB18 -> 0 | K15: =Master!AG18 -> 0 | L15: =Master!AH18 -> 730.6 | M15: =Master!AI18 -> 425.53333 | N15: =Master!AJ18 -> 1988.1333 | O15: =H15+I15+J15+K15+L15+M15+N15 -> 11919.6 | P15: =Master!AL18 -> 90 | Q15: =Master!AM18 -> 1430 | R15: =Master!AN18 -> 0 | S15: =Master!AO18 -> 0 | T15: =Master!AP18 -> 0 | U15: =Master!AQ18 -> 1520 | V15: =O15-U15 -> 10399.6 | W15: =Master!AS18 -> 7th May 2020 | X15: =Master!AT18 -> ICIC0000202 | Y15: =Master!AU18 -> 20201585355
A16: 5 | B16: =Master!D19 -> PITANI SATHYA NARAYANA | C16: =Master!C19 -> 7 | D16: =Master!J19 -> Semi Skilled Gardner | E16: =Master!AA19 -> 26 | F16: N/A | G16: =Master!AC19 -> 11459 | H16: =Master!AD19 -> 3844 | I16: =Master!AE19 -> 4931.3333 | J16: =Master!AB19 -> 0 | K16: =Master!AG19 -> 0 | L16: =Master!AH19 -> 730.6 | M16: =Master!AI19 -> 425.53333 | N16: =Master!AJ19 -> 0 | O16: =H16+I16+J16+K16+L16+M16+N16 -> 9931.4667 | P16: =Master!AL19 -> 75 | Q16: =Master!AM19 -> 1192 | R16: =Master!AN19 -> 0 | S16: =Master!AO19 -> 0 | T16: =Master!AP19 -> 0 | U16: =Master!AQ19 -> 1267 | V16: =O16-U16 -> 8664.4667 | W16: =Master!AS19 -> 7th May 2020 | X16: =Master!AT19 -> ANDB0001414 | Y16: =Master!AU19 -> 141410100131316
A17: 6 | B17: =Master!D20 -> SANGOLLA ASHOK | C17: =Master!C20 -> 8 | D17: =Master!J20 -> Semi Skilled Gardner | E17: =Master!AA20 -> 26 | F17: N/A | G17: =Master!AC20 -> 11459 | H17: =Master!AD20 -> 3844 | I17: =Master!AE20 -> 4931.3333 | J17: =Master!AB20 -> 0 | K17: =Master!AG20 -> 0 | L17: =Master!AH20 -> 730.6 | M17: =Master!AI20 -> 425.53333 | N17: =Master!AJ20 -> 0 | O17: =H17+I17+J17+K17+L17+M17+N17 -> 9931.4667 | P17: =Master!AL20 -> 75 | Q17: =Master!AM20 -> 1192 | R17: =Master!AN20 -> 0 | S17: =Master!AO20 -> 0 | T17: =Master!AP20 -> 0 | U17: =Master!AQ20 -> 1267 | V17: =O17-U17 -> 8664.4667 | W17: =Master!AS20 -> 7th May 2020 | X17: =Master!AT20 -> SBIN0020106 | Y17: =Master!AU20 -> 62135175705
A18: 7 | B18: =Master!D21 -> ASHOK LINGURAM GAIKWAD | C18: =Master!C21 -> 9 | D18: =Master!J21 -> Semi Skilled Gardner | E18: =Master!AA21 -> 26 | F18: N/A | G18: =Master!AC21 -> 11459 | H18: =Master!AD21 -> 3844 | I18: =Master!AE21 -> 4931.3333 | J18: =Master!AB21 -> 0 | K18: =Master!AG21 -> 0 | L18: =Master!AH21 -> 730.6 | M18: =Master!AI21 -> 425.53333 | N18: =Master!AJ21 -> 0 | O18: =H18+I18+J18+K18+L18+M18+N18 -> 9931.4667 | P18: =Master!AL21 -> 75 | Q18: =Master!AM21 -> 1192 | R18: =Master!AN21 -> 0 | S18: =Master!AO21 -> 0 | T18: =Master!AP21 -> 0 | U18: =Master!AQ21 -> 1267 | V18: =O18-U18 -> 8664.4667 | W18: =Master!AS21 -> 7th May 2020 | X18: =Master!AT21 -> SBIN0014234 | Y18: =Master!AU21 -> 35398345250
A19: 8 | B19: =Master!D22 -> MADHUKAR KAMTAM | C19: =Master!C22 -> 10 | D19: =Master!J22 -> Semi Skilled Gardner | E19: =Master!AA22 -> 26 | F19: N/A | G19: =Master!AC22 -> 11459 | H19: =Master!AD22 -> 3844 | I19: =Master!AE22 -> 4931.3333 | J19: =Master!AB22 -> 0 | K19: =Master!AG22 -> 0 | L19: =Master!AH22 -> 730.6 | M19: =Master!AI22 -> 425.53333 | N19: =Master!AJ22 -> 0 | O19: =H19+I19+J19+K19+L19+M19+N19 -> 9931.4667 | P19: =Master!AL22 -> 75 | Q19: =Master!AM22 -> 1192 | R19: =Master!AN22 -> 0 | S19: =Master!AO22 -> 0 | T19: =Master!AP22 -> 0 | U19: =Master!AQ22 -> 1267 | V19: =O19-U19 -> 8664.4667 | W19: =Master!AS22 -> 7th May 2020 | X19: =Master!AT22 -> IDIB000N116 | Y19: =Master!AU22 -> 923249324
A20: 9 | B20: =Master!D23 -> Ningolla Raju | C20: =Master!C23 -> 12 | D20: =Master!J23 -> Semi Skilled Gardner | E20: =Master!AA23 -> 26 | F20: N/A | G20: =Master!AC23 -> 11459 | H20: =Master!AD23 -> 3844 | I20: =Master!AE23 -> 4931.3333 | J20: =Master!AB23 -> 0 | K20: =Master!AG23 -> 0 | L20: =Master!AH23 -> 730.6 | M20: =Master!AI23 -> 425.53333 | N20: =Master!AJ23 -> 0 | O20: =H20+I20+J20+K20+L20+M20+N20 -> 9931.4667 | P20: =Master!AL23 -> 75 | Q20: =Master!AM23 -> 1192 | R20: =Master!AN23 -> 0 | S20: =Master!AO23 -> 0 | T20: =Master!AP23 -> 0 | U20: =Master!AQ23 -> 1267 | V20: =O20-U20 -> 8664.4667 | W20: =Master!AS23 -> 7th May 2020 | X20: =Master!AT23 -> BKID0008614 | Y20: =Master!AU23 -> 861410110009223
A21: 10 | B21: =Master!D24 -> Nagani pochaiah | C21: =Master!C24 -> 13 | D21: =Master!J24 -> Semi Skilled Gardner | E21: =Master!AA24 -> 26 | F21: N/A | G21: =Master!AC24 -> 11459 | H21: =Master!AD24 -> 3844 | I21: =Master!AE24 -> 4931.3333 | J21: =Master!AB24 -> 0 | K21: =Master!AG24 -> 0 | L21: =Master!AH24 -> 730.6 | M21: =Master!AI24 -> 425.53333 | N21: =Master!AJ24 -> 0 | O21: =H21+I21+J21+K21+L21+M21+N21 -> 9931.4667 | P21: =Master!AL24 -> 75 | Q21: =Master!AM24 -> 1192 | R21: =Master!AN24 -> 0 | S21: =Master!AO24 -> 0 | T21: =Master!AP24 -> 0 | U21: =Master!AQ24 -> 1267 | V21: =O21-U21 -> 8664.4667 | W21: =Master!AS24 -> 7th May 2020 | X21: =Master!AT24 -> SBIN0014234 | Y21: =Master!AU24 -> 38228069327
A22: 11 | B22: =Master!D25 -> Mutholla Mallesh | C22: =Master!C25 -> 14 | D22: =Master!J25 -> Semi Skilled Gardner | E22: =Master!AA25 -> 26 | F22: N/A | G22: =Master!AC25 -> 11459 | H22: =Master!AD25 -> 3844 | I22: =Master!AE25 -> 4931.3333 | J22: =Master!AB25 -> 0 | K22: =Master!AG25 -> 0 | L22: =Master!AH25 -> 730.6 | M22: =Master!AI25 -> 425.53333 | N22: =Master!AJ25 -> 0 | O22: =H22+I22+J22+K22+L22+M22+N22 -> 9931.4667 | P22: =Master!AL25 -> 75 | Q22: =Master!AM25 -> 1192 | R22: =Master!AN25 -> 0 | S22: =Master!AO25 -> 0 | T22: =Master!AP25 -> 0 | U22: =Master!AQ25 -> 1267 | V22: =O22-U22 -> 8664.4667 | W22: =Master!AS25 -> 7th May 2020 | X22: =Master!AT25 -> SBIN0014234 | Y22: =Master!AU25 -> 20176301430
A23: 12 | B23: =Master!D26 -> ALIJANA JAYARAMI REDDY | C23: =Master!C26 -> 15 | D23: =Master!J26 -> Semi Skilled Gardner | E23: =Master!AA26 -> 26 | F23: N/A | G23: =Master!AC26 -> 11459 | H23: =Master!AD26 -> 3844 | I23: =Master!AE26 -> 4931.3333 | J23: =Master!AB26 -> 0 | K23: =Master!AG26 -> 0 | L23: =Master!AH26 -> 730.6 | M23: =Master!AI26 -> 425.53333 | N23: =Master!AJ26 -> 0 | O23: =H23+I23+J23+K23+L23+M23+N23 -> 9931.4667 | P23: =Master!AL26 -> 75 | Q23: =Master!AM26 -> 1192 | R23: =Master!AN26 -> 0 | S23: =Master!AO26 -> 0 | T23: =Master!AP26 -> 0 | U23: =Master!AQ26 -> 1267 | V23: =O23-U23 -> 8664.4667 | W23: =Master!AS26 -> 7th May 2020 | X23: =Master!AT26 -> SBIN0008495 | Y23: =Master!AU26 -> 33412525880
... A61: 50 | B61: =Master!D64 -> Mutyala Poshavva | C61: =Master!C64 -> 55 | D61: =Master!J64 -> Unskilled Gardner | E61: =Master!AA64 -> 0 | F61: N/A | G61: =Master!AC64 -> 10627 | H61: =Master!AD64 -> 0 | I61: =Master!AE64 -> 0 | J61: =Master!AB64 -> 0 | K61: =Master!AG64 -> 0 | L61: =Master!AH64 -> 0 | M61: =Master!AI64 -> 0 | N61: =Master!AJ64 -> 0 | O61: =H61+I61+J61+K61+L61+M61+N61 -> 0 | P61: =Master!AL64 -> 0 | Q61: =Master!AM64 -> 0 | R61: =Master!AN64 -> 0 | S61: =Master!AO64 -> 0 | T61: =Master!AP64 -> 0 | U61: =Master!AQ64 -> 0 | V61: =O61-U61 -> 0 | W61: =Master!AS64 -> 7th May 2020 | X61: =Master!AT64 -> Bank Cheque | Y61: =Master!AU64 -> Bank Cheque
G62: =SUM(G12:G61) -> 587360 | H62: =SUM(H12:H61) -> 206470 | I62: =SUM(I12:I61) -> 202184.67 | J62: =SUM(J12:J61) -> 0 | K62: =SUM(K12:K61) -> 4721 | L62: =SUM(L12:L61) -> 28474.333 | M62: =SUM(M12:M61) -> 16573.267 | N62: =SUM(N12:N61) -> 13171.267 | ... V62: =SUM(V12:V61) -> 415648.53
J64: Signature of the Contractor with Seal

Sheet wage sllips
A2: Form XIX - WAGE SLIP | K2: Form XIX - WAGE SLIP
A3: [Vide rule 78 (1) (b) of the Contract Labour (Regulation and Abolition) Central and A.P.{T.S.}Rules, 1971] | K3: =A3 -> [Vide rule 78 (1) (b) of the Contract Labour (Regulation and Abolition) Central and A.P.{T.S.}Rules, 1971]
A5: Name and address of Contractor | D5: =Master!F5 -> GROTECH LANDSCAPE DEVELOPERS PVT. LTD. | K5: Name and address of Contractor | N5: =D5 -> GROTECH LANDSCAPE DEVELOPERS PVT. LTD.
B6: =Master!F6 -> 290/E, Khanapur Village, Gandipet Mandal, Ranga Reddy, Hyderabad-500075 T.S. | L6: =B6 -> 290/E, Khanapur Village, Gandipet Mandal, Ranga Reddy, Hyderabad-500075 T.S.
A8: Name and Father's / Husband's name of the workman | K8: Name and Father's / Husband's name of the workman
E9: =Master!D15 -> ARJUN KUMAR | H9: =Master!G15 -> kallu | O9: =E9 -> ARJUN KUMAR | R9: =H9 -> kallu
A11: Nature and location of work | E11: =Master!F8 -> GARDENING SERVICES&ISB HYDERABAD | K11: Nature and location of work | O11: =E11 -> GARDENING SERVICES&ISB HYDERABAD
A13: For the Week / Fortnight / Month ending | E13: =Master!F10 -> 44652 | K13: For the Week / Fortnight / Month ending | O13: =E13 -> 44652
A15: 1 | B15: No. of days worked | E15: =Master!AA15 -> 30 | K15: 1 | L15: No. of days worked | O15: =E15 -> 30
A17: 2 | B17: No. of units worked in case of piece rate workers : | K17: 2 | L17: No. of units worked in case of piece rate workers :
E18: N/A | O18: N/A
A20: 3 | B20: Rate of daily wages / piece rate | E20: N/A | K20: 3 | L20: Rate of daily wages / piece rate | O20: =E20 -> N/A
A22: 4 | B22: Amount of overtime wages | E22: Nil | K22: 4 | L22: Amount of overtime wages | O22: Nil
A24: 5 | B24: Gross wages payble | E24: =Master!AK15 -> 20000 | K24: 5 | L24: Gross wages payble | O24: =E24 -> 20000
D25: EPF | E25: ESI | F25: PT | G25: TDS | H25: ADV | I25: Total Ded | N25: EPF | O25: ESI | P25: PT | Q25: TDS | R25: =H25 -> ADV | S25: Total Ded
A26: 6 | B26: Deductions, if any | D26: =Master!AM15 -> 0 | E26: =Master!AL15 -> 150 | F26: =Master!AN15 -> 150 | G26: =Master!AO15 -> 0 | H26: =Master!AP15 -> 0 | I26: =D26+E26+F26+G26+H26 -> 300 | K26: 6 | L26: Deductions, if any | N26: =D26 -> 0 | O26: =E26 -> 150 | P26: =F26 -> 150 | Q26: =G26 -> 0 | R26: =H26 -> 0 | S26: =N26+O26+R26 -> 150
A28: 7 | B28: Net amount of wages paid | E28: =E24-I26 -> 19700 | K28: 7 | L28: Net amount of wages paid | O28: =E28 -> 19700
E32: Initial of the Contractor or his representative | O32: Initial of the Contractor or his representative
A44: Form XIX - WAGE SLIP | K44: Form XIX - WAGE SLIP
A45: [Vide rule 78 (1) (b) of the Contract Labour (Regulation and Abolition) Central and A.P.{T.S.}Rules, 1971] | K45: =A45 -> [Vide rule 78 (1) (b) of the Contract Labour (Regulation and Abolition) Central and A.P.{T.S.}Rules, 1971]
A47: Name and address of Contractor | D47: =Master!F5 -> GROTECH LANDSCAPE DEVELOPERS PVT. LTD. | K47: Name and address of Contractor | N47: =D47 -> GROTECH LANDSCAPE DEVELOPERS PVT. LTD.
B48: =Master!F6 -> 290/E, Khanapur Village, Gandipet Mandal, Ranga Reddy, Hyderabad-500075 T.S. | L48: =B48 -> 290/E, Khanapur Village, Gandipet Mandal, Ranga Reddy, Hyderabad-500075 T.S.
A50: Name and Father's / Husband's name of the workman | K50: Name and Father's / Husband's name of the workman
E51: =Master!D16 -> GAJAN SINGH | H51: =Master!G16 -> Chandrapal singh | O51: =E51 -> GAJAN SINGH | R51: =H51 -> Chandrapal singh
A53: Nature and location of work | E53: =Master!F8 -> GARDENING SERVICES&ISB HYDERABAD | K53: Nature and location of work | O53: =E53 -> GARDENING SERVICES&ISB HYDERABAD
A55: For the Week / Fortnight / Month ending | E55: =Master!F10 -> 44652 | K55: For the Week / Fortnight / Month ending | O55: =E55 -> 44652
A57: 1 | B57: No. of days worked | E57: =Master!AA16 -> 30 | K57: 1 | L57: No. of days worked | O57: =E57 -> 30
A59: 2 | B59: No. of units worked in case of piece rate workers : | K59: 2 | L59: No. of units worked in case of piece rate workers :
E60: N/A | O60: N/A
A62: 3 | B62: Rate of daily wages / piece rate | E62: N/A | K62: 3 | L62: Rate of daily wages / piece rate | O62: =E62 -> N/A
A64: 4 | B64: Amount of overtime wages | E64: Nil | K64: 4 | L64: Amount of overtime wages | O64: Nil
A66: 5 | B66: Gross wages payble | E66: =Master!AK16 -> 14900 | K66: 5 | L66: Gross wages payble | O66: =E66 -> 14900
D67: EPF | E67: ESI | F67: PT | G67: TDS | H67: ADV | I67: Total Ded | N67: EPF | O67: ESI | P67: PT | Q67: TDS | R67: =H67 -> ADV | S67: Total Ded
A68: 6 | B68: Deductions, if any | D68: =Master!AM16 -> 1788 | E68: =Master!AL16 -> 112 | F68: =Master!AN16 -> 0 | G68: =Master!AO16 -> 0 | H68: =Master!AP16 -> 0 | I68: =D68+E68+F68+G68+H68 -> 1900 | K68: 6 | L68: Deductions, if any | N68: =D68 -> 1788 | O68: =E68 -> 112 | P68: =F68 -> 0 | Q68: =G68 -> 0 | R68: =H68 -> 0 | S68: =N68+O68+R68 -> 1900
A70: 7 | B70: Net amount of wages paid | E70: =E66-I68 -> 13000 | K70: 7 | L70: Net amount of wages paid | O70: =E70 -> 13000
E74: Initial of the Contractor or his representative | O74: Initial of the Contractor or his representative
A87: Form XIX - WAGE SLIP | K87: Form XIX - WAGE SLIP
A88: [Vide rule 78 (1) (b) of the Contract Labour (Regulation and Abolition) Central and A.P.{T.S.}Rules, 1971] | K88: =A88 -> [Vide rule 78 (1) (b) of the Contract Labour (Regulation and Abolition) Central and A.P.{T.S.}Rules, 1971]
A90: Name and address of Contractor | D90: =Master!F5 -> GROTECH LANDSCAPE DEVELOPERS PVT. LTD. | K90: Name and address of Contractor | N90: =D90 -> GROTECH LANDSCAPE DEVELOPERS PVT. LTD.
B91: =Master!F6 -> 290/E, Khanapur Village, Gandipet Mandal, Ranga Reddy, Hyderabad-500075 T.S. | L91: =B91 -> 290/E, Khanapur Village, Gandipet Mandal, Ranga Reddy, Hyderabad-500075 T.S.
A93: Name and Father's / Husband's name of the workman | K93: Name and Father's / Husband's name of the workman
E94: =Master!D17 -> GUDALA RUSHESHWAR SWAMY | H94: =Master!G17 -> GUDALA KRISHANA MURTHY | O94: =E94 -> GUDALA RUSHESHWAR SWAMY | R94: =H94 -> GUDALA KRISHANA MURTHY
A96: Nature and location of work | E96: =Master!F8 -> GARDENING SERVICES&ISB HYDERABAD | K96: Nature and location of work | O96: =E96 -> GARDENING SERVICES&ISB HYDERABAD
A98: For the Week / Fortnight / Month ending | E98: =Master!F10 -> 44652 | K98: For the Week / Fortnight / Month ending | O98: =E98 -> 44652
A100: 1 | B100: No. of days worked | E100: =Master!AA17 -> 30 | K100: 1 | L100: No. of days worked | O100: =E100 -> 30
A102: 2 | B102: No. of units worked in case of piece rate workers : | K102: 2 | L102: No. of units worked in case of piece rate workers :
E103: N/A | O103: N/A
A105: 3 | B105: Rate of daily wages / piece rate | E105: N/A | K105: 3 | L105: Rate of daily wages / piece rate | O105: =E105 -> N/A
A107: 4 | B107: Amount of overtime wages | E107: Nil | K107: 4 | L107: Amount of overtime wages | O107: Nil
A109: 5 | B109: Gross wages payble | E109: =Master!AK17 -> 17918 | K109: 5 | L109: Gross wages payble | O109: =E109 -> 17918
D110: EPF | E110: ESI | F110: PT | G110: TDS | H110: ADV | I110: Total Ded | N110: EPF | O110: ESI | P110: PT | Q110: TDS | R110: =H110 -> ADV | S110: Total Ded
A111: 6 | B111: Deductions, if any | D111: =Master!AM17 -> 1584 | E111: =Master!AL17 -> 135 | F111: =Master!AN17 -> 150 | G111: =Master!AO17 -> 0 | H111: =Master!AP17 -> 0 | I111: =D111+E111+F111+G111+H111 -> 1869 | K111: 6 | L111: Deductions, if any | N111: =D111 -> 1584 | O111: =E111 -> 135 | P111: =F111 -> 150 | Q111: =G111 -> 0 | R111: =H111 -> 0 | S111: =N111+O111+R111 -> 1719
A113: 7 | B113: Net amount of wages paid | E113: =E109-I111 -> 16049 | K113: 7 | L113: Net amount of wages paid | O113: =E113 -> 16049
E117: Initial of the Contractor or his representative | O117: Initial of the Contractor or his representative
A130: Form XIX - WAGE SLIP | K130: Form XIX - WAGE SLIP
A131: [Vide rule 78 (1) (b) of the Contract Labour (Regulation and Abolition) Central and A.P.{T.S.}Rules, 1971] | K131: =A131 -> [Vide rule 78 (1) (b) of the Contract Labour (Regulation and Abolition) Central and A.P.{T.S.}Rules, 1971]
A133: Name and address of Contractor | D133: =Master!F5 -> GROTECH LANDSCAPE DEVELOPERS PVT. LTD. | K133: Name and address of Contractor | N133: =D133 -> GROTECH LANDSCAPE DEVELOPERS PVT. LTD.
B134: =Master!F6 -> 290/E, Khanapur Village, Gandipet Mandal, Ranga Reddy, Hyderabad-500075 T.S. | L134: =B134 -> 290/E, Khanapur Village, Gandipet Mandal, Ranga Reddy, Hyderabad-500075 T.S.
A136: Name and Father's / Husband's name of the workman | K136: Name and Father's / Husband's name of the workman
E137: =Master!D18 -> KASALA NARSIMLU | H137: =Master!G18 -> KASALA POCHAIAH | O137: =E137 -> KASALA NARSIMLU | R137: =H137 -> KASALA POCHAIAH
A139: Nature and location of work | E139: =Master!F8 -> GARDENING SERVICES&ISB HYDERABAD | K139: Nature and location of work | O139: =E139 -> GARDENING SERVICES&ISB HYDERABAD
A141: For the Week / Fortnight / Month ending | E141: =Master!F10 -> 44652 | K141: For the Week / Fortnight / Month ending | O141: =E141 -> 44652
A143: 1 | B143: No. of days worked | E143: =Master!AA18 -> 26 | K143: 1 | L143: No. of days worked | O143: =E143 -> 26
A145: 2 | B145: No. of units worked in case of piece rate workers : | K145: 2 | L145: No. of units worked in case of piece rate workers :
E146: N/A | O146: N/A
A148: 3 | B148: Rate of daily wages / piece rate | E148: N/A | K148: 3 | L148: Rate of daily wages / piece rate | O148: =E148 -> N/A
A150: 4 | B150: Amount of overtime wages | E150: Nil | K150: 4 | L150: Amount of overtime wages | O150: Nil
A152: 5 | B152: Gross wages payble | E152: =Master!AK18 -> 11919.6 | K152: 5 | L152: Gross wages payble | O152: =E152 -> 11919.6
D153: EPF | E153: ESI | F153: PT | G153: TDS | H153: ADV | I153: Total Ded | N153: EPF | O153: ESI | P153: PT | Q153: TDS | R153: =H153 -> ADV | S153: Total Ded
A154: 6 | B154: Deductions, if any | D154: =Master!AM18 -> 1430 | E154: =Master!AL18 -> 90 | F154: =Master!AN18 -> 0 | G154: =Master!AO18 -> 0 | H154: =Master!AP18 -> 0 | I154: =D154+E154+F154+G154+H154 -> 1520 | K154: 6 | L154: Deductions, if any | N154: =D154 -> 1430 | O154: =E154 -> 90 | P154: =F154 -> 0 | Q154: =G154 -> 0 | R154: =H154 -> 0 | S154: =N154+O154+R154 -> 1520
A156: 7 | B156: Net amount of wages paid | E156: =E152-I154 -> 10399.6 | K156: 7 | L156: Net amount of wages paid | O156: =E156 -> 10399.6
E160: Initial of the Contractor or his representative | O160: Initial of the Contractor or his representative
A173: Form XIX - WAGE SLIP | K173: Form XIX - WAGE SLIP
A174: [Vide rule 78 (1) (b) of the Contract Labour (Regulation and Abolition) Central and A.P.{T.S.}Rules, 1971] | K174: =A174 -> [Vide rule 78 (1) (b) of the Contract Labour (Regulation and Abolition) Central and A.P.{T.S.}Rules, 1971]
A176: Name and address of Contractor | D176: =Master!F5 -> GROTECH LANDSCAPE DEVELOPERS PVT. LTD. | K176: Name and address of Contractor | N176: =D176 -> GROTECH LANDSCAPE DEVELOPERS PVT. LTD.
B177: =Master!F6 -> 290/E, Khanapur Village, Gandipet Mandal, Ranga Reddy, Hyderabad-500075 T.S. | L177: =B177 -> 290/E, Khanapur Village, Gandipet Mandal, Ranga Reddy, Hyderabad-500075 T.S.
A179: Name and Father's / Husband's name of the workman | K179: Name and Father's / Husband's name of the workman
E180: =Master!D19 -> PITANI SATHYA NARAYANA | H180: =Master!G19 -> P SURYANARAYANA | O180: =E180 -> PITANI SATHYA NARAYANA | R180: =H180 -> P SURYANARAYANA
A182: Nature and location of work | E182: =Master!F8 -> GARDENING SERVICES&ISB HYDERABAD | K182: Nature and location of work | O182: =E182 -> GARDENING SERVICES&ISB HYDERABAD
A184: For the Week / Fortnight / Month ending | E184: =Master!F10 -> 44652 | K184: For the Week / Fortnight / Month ending | O184: =E184 -> 44652
A186: 1 | B186: No. of days worked | E186: =Master!AA19 -> 26 | K186: 1 | L186: No. of days worked | O186: =E186 -> 26
A188: 2 | B188: No. of units worked in case of piece rate workers : | K188: 2 | L188: No. of units worked in case of piece rate workers :
E189: N/A | O189: N/A
A191: 3 | B191: Rate of daily wages / piece rate | E191: N/A | K191: 3 | L191: Rate of daily wages / piece rate | O191: =E191 -> N/A
A193: 4 | B193: Amount of overtime wages | E193: Nil | K193: 4 | L193: Amount of overtime wages | O193: Nil
A195: 5 | B195: Gross wages payble | E195: =Master!AK19 -> 9932.4667 | K195: 5 | L195: Gross wages payble | O195: =E195 -> 9932.4667
D196: EPF | E196: ESI | F196: PT | G196: TDS | H196: ADV | I196: Total Ded | N196: EPF | O196: ESI | P196: PT | Q196: TDS | R196: =H196 -> ADV | S196: Total Ded
A197: 6 | B197: Deductions, if any | D197: =Master!AM19 -> 1192 | E197: =Master!AL19 -> 75 | F197: =Master!AN19 -> 0 | G197: =Master!AO19 -> 0 | H197: =Master!AP19 -> 0 | I197: =D197+E197+F197+G197+H197 -> 1267 | K197: 6 | L197: Deductions, if any | N197: =D197 -> 1192 | O197: =E197 -> 75 | P197: =F197 -> 0 | Q197: =G197 -> 0 | R197: =H197 -> 0 | S197: =N197+O197+R197 -> 1267
A199: 7 | B199: Net amount of wages paid | E199: =E195-I197 -> 8665.4667 | K199: 7 | L199: Net amount of wages paid | O199: =E199 -> 8665.4667
E203: Initial of the Contractor or his representative | O203: Initial of the Contractor or his representative
A216: Form XIX - WAGE SLIP | K216: Form XIX - WAGE SLIP
A217: [Vide rule 78 (1) (b) of the Contract Labour (Regulation and Abolition) Central and A.P.{T.S.}Rules, 1971] | K217: =A217 -> [Vide rule 78 (1) (b) of the Contract Labour (Regulation and Abolition) Central and A.P.{T.S.}Rules, 1971]
A219: Name and address of Contractor | D219: =Master!F5 -> GROTECH LANDSCAPE DEVELOPERS PVT. LTD. | K219: Name and address of Contractor | N219: =D219 -> GROTECH LANDSCAPE DEVELOPERS PVT. LTD.
B220: =Master!F6 -> 290/E, Khanapur Village, Gandipet Mandal, Ranga Reddy, Hyderabad-500075 T.S. | L220: =B220 -> 290/E, Khanapur Village, Gandipet Mandal, Ranga Reddy, Hyderabad-500075 T.S.
A222: Name and Father's / Husband's name of the workman | K222: Name and Father's / Husband's name of the workman
E223: =Master!D20 -> SANGOLLA ASHOK | H223: =Master!G20 -> SANGOLLA ESWARAIAH | O223: =E223 -> SANGOLLA ASHOK | R223: =H223 -> SANGOLLA ESWARAIAH
A225: Nature and location of work | E225: =Master!F8 -> GARDENING SERVICES&ISB HYDERABAD | K225: Nature and location of work | O225: =E225 -> GARDENING SERVICES&ISB HYDERABAD
A227: For the Week / Fortnight / Month ending | E227: =Master!F10 -> 44652 | K227: For the Week / Fortnight / Month ending | O227: =E227 -> 44652
A229: 1 | B229: No. of days worked | E229: =Master!AA20 -> 26 | K229: 1 | L229: No. of days worked | O229: =E229 -> 26
A231: 2 | B231: No. of units worked in case of piece rate workers : | K231: 2 | L231: No. of units worked in case of piece rate workers :
...

Sheet Payslip
D1: Payslip For the Month of | G1: =Master!F10 -> 44652
B2: =Master!F5 -> GROTECH LANDSCAPE DEVELOPERS PVT. LTD.
B3: =Master!F6 -> 290/E, Khanapur Village, Gandipet Mandal, Ranga Reddy, Hyderabad-500075 T.S.
B5: Employee ID | C5: S520 | F5: No. Of Total Days | G5: 30
B6: Employee Name | C6: Sanghamitra Dash | F6: No. Of Paid Days | G6: 30
B7: Designation | C7: Automation Test Engineer | F7: PAN Card No | G7: BZRPM7258K
B8: Department | C8: Software Development | F8: Bank Name | G8: HDFC BANK
B9: Date of Joining | C9: 43720 | F9: Account No. | G9: 50100269606743
B10: UAN No. | C10: =Master!X15 -> N/A | F10: ESI No. | G10: =Master!Y15 -> 2016384651
B12: EARNINGS | D12: Actuals (Rs.) | E12: Amount (Rs.) | F12: DEDUCTIONS | H12: Amount (Rs)
B13: Basic Salary | D13: 40766.67 | E13: 40766.67 | F13: ESI Contribution | H13: 200
B14: HRA | D14: 16306.67 | E14: 16306.67 | F14: EPF Contribution | H14: 1800
B15: Conveyance Allowance | D15: 1600 | E15: 1600 | F15: PT | H15: 200
B16: Medical Allowance Insurance) | D16: 22860 | E16: 22860 | F16: TDS | H16: 0
B17: Special Allowance Insurance) | D17: 0 | E17: 0 | F17: Advance | H17: 0
B18: Other Allowance Insurance) | D18: 0 | E18: 0 | F18: Other Deductions | H18: 0
B19: Gross Salary | D19: 81533.33 | E19: 81533 | F19: Total Deductions | H19: 5500
B21: Net Salary | D21: 76033
B22: Net Salary in Words: | D22: Seventy-Six Thousand Thirty-Three Rupees Only
B23: Note: This is a computer generated document, hence no signature is required.

Sheet Deductions
A1: FORM XX- REGISTER OF DEDUCTIONS FOR DAMAGE OR LOSS
A2: (Vide Rule 78(1) (a) (i) of Contract Labour (Regulation and Abolition) Central /A.P{T.S.}.Rules 1971
A3: Name and address of Contractor: | D3: =Master!F5 -> GROTECH LANDSCAPE DEVELOPERS PVT. LTD. | E3: Name and address of the establishment in / under which contract is carried on:
B4: =Master!F6 -> 290/E, Khanapur Village, Gandipet Mandal, Ranga Reddy, Hyderabad-500075 T.S. | E4: =Master!AN5 -> GROTECH LANDSCAPE DEVELOPERS PVT. LTD.
E5: =Master!AN6 -> 290/E, Khanapur Village, Gandipet Mandal, Ranga Reddy, Hyderabad-500075 T.S.
A6: Nature and Location of Work: | D6: =Master!F8 -> GARDENING SERVICES&ISB HYDERABAD | E6: Name and address of principal employer:
E7: =Master!AN10 -> INDIAN SCHOOL OF BUSINESS
E8: =Master!AN11 -> Opp.Infosys Limited,Gachibowli,Hyderabad
A10: S.No | B10: Name of workman | C10: Father's / Husband's Name | D10: Designation / Nature of employment | E10: Particulars of Damage or loss | F10: Date of Damage or loss | G10: Whether workman showed cause against deduction | H10: Name of person in whose presence employee's explanation was heard | I10: Amount of deduction impossed | J10: Date of recovery | M10: Remarks
J11: No.of Instalments | K11: First Instalment | L11: Last instalment
A12: 1 | B12: 2 | C12: 3 | D12: 4 | E12: 5 | F12: 6 | G12: 7 | H12: 8 | I12: 9 | J12: 10 | K12: 11 | L12: 12 | M12: 13
B15: NO EMPLOYEE WAS IMPOSED DEDUCTIONS FOR DAMAGE OR LOSS FOR THE MONTH OF | H15: =Master!F10 -> 44652
F32: Signature of the Contractor with Seal

Sheet Fines
A1: FORM XXI- REGISTER OF FINES
A2: (Vide Rule 78(1) (a) (i) of Contract Labour (Regulation and Abolition) Central /A.P.{T.S.}Rules 1971
A3: Name and address of Contractor: | D3: =Master!F5 -> GROTECH LANDSCAPE DEVELOPERS PVT. LTD. | E3: Name and address of the establishment in / under which contract is carried on:
B4: =Master!F6 -> 290/E, Khanapur Village, Gandipet Mandal, Ranga Reddy, Hyderabad-500075 T.S. | E4: =Master!AN5 -> GROTECH LANDSCAPE DEVELOPERS PVT. LTD.
E5: =Master!AN6 -> 290/E, Khanapur Village, Gandipet Mandal, Ranga Reddy, Hyderabad-500075 T.S.
A6: Nature and Location of Work: | D6: =Master!F8 -> GARDENING SERVICES&ISB HYDERABAD | E6: Name and address of principal employer:
E7: =Master!AN10 -> INDIAN SCHOOL OF BUSINESS
E8: =Master!AN11 -> Opp.Infosys Limited,Gachibowli,Hyderabad
A10: S.No | B10: Name of workman | C10: Father's / Husband's Name | D10: Designation / Nature of employment | E10: Act/Omission for which fine imposed | F10: Date of offence | G10: Whether workman showed cause against fine | H10: Name of person in whose presence employee's explanation was heard | I10: Wage-period and wge payable | J10: Amount of fine Imposed | K10: Date on which fine realised | L10: Remarks
A12: 1 | B12: 2 | C12: 3 | D12: 4 | E12: 5 | F12: 6 | G12: 7 | H12: 8 | I12: 9 | J12: 10 | K12: 11 | L12: 12
B15: NO EMPLOYEE WAS IMPOSED FINES FOR THE MONTH OF | H15: =Master!F10 -> 44652
F32: Signature of the Contractor with Seal

Sheet Advances
A1: FORM XXII- REGISTER OF ADVANCES
A2: (Vide Rule 78(1) (a) (i) of Contract Labour (Regulation and Abolition) Central /A.P.{T.S.}Rules 1971
A3: Name and address of Contractor: | D3: =Master!F5 -> GROTECH LANDSCAPE DEVELOPERS PVT. LTD. | E3: Name and address of the establishment in / under which contract is carried on:
B4: =Master!F6 -> 290/E, Khanapur Village, Gandipet Mandal, Ranga Reddy, Hyderabad-500075 T.S. | E4: =Master!AN5 -> GROTECH LANDSCAPE DEVELOPERS PVT. LTD.
E5: =Master!AN6 -> 290/E, Khanapur Village, Gandipet Mandal, Ranga Reddy, Hyderabad-500075 T.S.
A6: Nature and Location of Work: | D6: =Master!F8 -> GARDENING SERVICES&ISB HYDERABAD | E6: Name and address of principal employer:
E7: =Master!AN10 -> INDIAN SCHOOL OF BUSINESS
E8: =Master!AN11 -> Opp.Infosys Limited,Gachibowli,Hyderabad
A10: S.No | B10: Name of workman | C10: Father's / Husband's Name | D10: Designation / Nature of employment | E10: Wage period and wages payable | F10: Date and amount of advance given | G10: Purpose(s) for which advance made | H10: Number of instalments by which advance to be repaid | I10: Date and amount of each instalment repaid | J10: Date on which last instalment was repaid | K10: Remarks
A12: 1 | B12: 2 | C12: 3 | D12: 4 | E12: 5 | F12: 6 | G12: 7 | H12: 8 | I12: 9 | J12: 10 | K12: 11
D14: No employee has taken advance for the month of | E14: =Master!F10 -> 44652
G39: Signature of the Contractor with Seal

Sheet Overtime
A1: FORM XXIII- REGISTER OF OVERTIME
A2: (Vide Rule 78(1) (a) (i) of Contract Labour (Regulation and Abolition) Central /A.P.{T.S.}Rules 1971
A3: Name and address of Contractor: | D3: =Master!F5 -> GROTECH LANDSCAPE DEVELOPERS PVT. LTD. | F3: Name and address of the establishment in which under contract is carried on:
B4: =Master!F6 -> 290/E, Khanapur Village, Gandipet Mandal, Ranga Reddy, Hyderabad-500075 T.S. | F4: =Master!AN5 -> GROTECH LANDSCAPE DEVELOPERS PVT. LTD.
F5: =Master!AN6 -> 290/E, Khanapur Village, Gandipet Mandal, Ranga Reddy, Hyderabad-500075 T.S.
A6: Nature and Location of Work: | D6: =Master!F8 -> GARDENING SERVICES&ISB HYDERABAD | F6: Name and address of principal employer:
F7: =Master!AN10 -> INDIAN SCHOOL OF BUSINESS
F8: =Master!AN11 -> Opp.Infosys Limited,Gachibowli,Hyderabad
A10: S.No | B10: Name of workman | C10: Father's / Husband's Name | D10: Sex | E10: Designation / Nature of employment | F10: Date on which overtime worked | G10: Total overtime worked or production in case of piece-rates | H10: Normal rate of wages | I10: Overtime rate of wages | J10: overtime earnings | K10: Date on which overtime wages paid | L10: Remarks
A12: 1 | B12: 2 | C12: 3 | D12: 4 | E12: 5 | F12: 6 | G12: 7 | H12: 8 | I12: 9 | J12: 10 | K12: 11 | L12: 12
B15: NO EMPLOYEE DONE OVERTIME FOR THE MONTH OF | F15: =Master!F10 -> 44652
G29: Signature of the Contractor with Seal

Sheet Bank Upload
A1: BANK UPLOAD DATA OF | B1: =Master!F5 -> GROTECH LANDSCAPE DEVELOPERS PVT. LTD. | D1: FOR THE MONTH OF | E1: =Master!F10 -> 44652
A2: Employee Name | B2: Account Number | C2: IFSC Code | D2: Net Salary | E2: Date of Payment
A3: =Master!Z15 -> ARJUN KUMAR | B3: =Master!AU15 -> 6912137285 | C3: =Master!AT15 -> KKBK0000205 | D3: =Master!AR15 -> 19700 | E3: =Master!AS15 -> 7th May 2020
A4: =Master!Z16 -> GAJAN SINGH | B4: =Master!AU16 -> 7513074030 | C4: =Master!AT16 -> KKBK0000205 | D4: =Master!AR16 -> 13000 | E4: =Master!AS16 -> 7th May 2020
A5: =Master!Z17 -> GUDALA RUSHESHWAR SWAMY | B5: =Master!AU17 -> 1912391941 | C5: =Master!AT17 -> KKBK0007476 | D5: =Master!AR17 -> 16049 | E5: =Master!AS17 -> 7th May 2020
A6: =Master!Z18 -> KASALA NARSIMLU | B6: =Master!AU18 -> 20201585355 | C6: =Master!AT18 -> ICIC0000202 | D6: =Master!AR18 -> 10399.6 | E6: =Master!AS18 -> 7th May 2020
A7: =Master!Z19 -> PITANI SATHYA NARAYANA | B7: =Master!AU19 -> 141410100131316 | C7: =Master!AT19 -> ANDB0001414 | D7: =Master!AR19 -> 8665.4667 | E7: =Master!AS19 -> 7th May 2020
A8: =Master!Z20 -> SANGOLLA ASHOK | B8: =Master!AU20 -> 62135175705 | C8: =Master!AT20 -> SBIN0020106 | D8: =Master!AR20 -> 8665.4667 | E8: =Master!AS20 -> 7th May 2020
A9: =Master!Z21 -> ASHOK LINGURAM GAIKWAD | B9: =Master!AU21 -> 35398345250 | C9: =Master!AT21 -> SBIN0014234 | D9: =Master!AR21 -> 8665.4667 | E9: =Master!AS21 -> 7th May 2020
A10: =Master!Z22 -> MADHUKAR KAMTAM | B10: =Master!AU22 -> 923249324 | C10: =Master!AT22 -> IDIB000N116 | D10: =Master!AR22 -> 8665.4667 | E10: =Master!AS22 -> 7th May 2020
A11: =Master!Z23 -> Ningolla Raju | B11: =Master!AU23 -> 861410110009223 | C11: =Master!AT23 -> BKID0008614 | D11: =Master!AR23 -> 8665.4667 | E11: =Master!AS23 -> 7th May 2020
A12: =Master!Z24 -> Nagani pochaiah | B12: =Master!AU24 -> 38228069327 | C12: =Master!AT24 -> SBIN0014234 | D12: =Master!AR24 -> 8665.4667 | E12: =Master!AS24 -> 7th May 2020
A13: =Master!Z25 -> Mutholla Mallesh | B13: =Master!AU25 -> 20176301430 | C13: =Master!AT25 -> SBIN0014234 | D13: =Master!AR25 -> 8665.4667 | E13: =Master!AS25 -> 7th May 2020
A14: =Master!Z26 -> ALIJANA JAYARAMI REDDY | B14: =Master!AU26 -> 33412525880 | C14: =Master!AT26 -> SBIN0008495 | D14: =Master!AR26 -> 8665.4667 | E14: =Master!AS26 -> 7th May 2020
... A52: =Master!Z64 -> Mutyala Poshavva | B52: =Master!AU64 -> Bank Cheque | C52: =Master!AT64 -> Bank Cheque | D52: =Master!AR64 -> 0 | E52: =Master!AS64 -> 7th May 2020

Sheet ESI-MC Template
A1: IP Number (10 Digits) | B1: IP Name ( Only alphabets and space ) | C1: No of Days for which wages paid/payable during the month | D1: Total Monthly Wages | E1: Reason Code for Zero workings days(numeric only; provide 0 for all other reasons- Click on the link for reference) | F1: Last Working Day ( Format DD/MM/YYYY or DD-MM-YYYY)
A2: =Master!Y15 -> 2016384651 | B2: =Master!Z15 -> ARJUN KUMAR | C2: =Master!AA15 -> 30 | D2: =Master!AK15 -> 20000
A3: =Master!Y16 -> 2017795829 | B3: =Master!Z16 -> GAJAN SINGH | C3: =Master!AA16 -> 30 | D3: =Master!AK16 -> 14900
A4: =Master!Y17 -> 5216113872 | B4: =Master!Z17 -> GUDALA RUSHESHWAR SWAMY | C4: =Master!AA17 -> 30 | D4: =Master!AK17 -> 17918
A5: =Master!Y18 -> 5216248033 | B5: =Master!Z18 -> KASALA NARSIMLU | C5: =Master!AA18 -> 26 | D5: =Master!AK18 -> 11919.6
A6: =Master!Y19 -> 5215982488 | B6: =Master!Z19 -> PITANI SATHYA NARAYANA | C6: =Master!AA19 -> 26 | D6: =Master!AK19 -> 9932.4667
A7: =Master!Y20 -> 5210317860 | B7: =Master!Z20 -> SANGOLLA ASHOK | C7: =Master!AA20 -> 26 | D7: =Master!AK20 -> 9932.4667
A8: =Master!Y21 -> 5211196939 | B8: =Master!Z21 -> ASHOK LINGURAM GAIKWAD | C8: =Master!AA21 -> 26 | D8: =Master!AK21 -> 9932.4667
A9: =Master!Y22 -> 5216116351 | B9: =Master!Z22 -> MADHUKAR KAMTAM | C9: =Master!AA22 -> 26 | D9: =Master!AK22 -> 9932.4667
A10: =Master!Y23 -> 5216340446 | B10: =Master!Z23 -> Ningolla Raju | C10: =Master!AA23 -> 26 | D10: =Master!AK23 -> 9932.4667
A11: =Master!Y24 -> 5212759307 | B11: =Master!Z24 -> Nagani pochaiah | C11: =Master!AA24 -> 26 | D11: =Master!AK24 -> 9932.4667
A12: =Master!Y25 -> 5216340493 | B12: =Master!Z25 -> Mutholla Mallesh | C12: =Master!AA25 -> 26 | D12: =Master!AK25 -> 9932.4667
A13: =Master!Y26 -> 5211482351 | B13: =Master!Z26 -> ALIJANA JAYARAMI REDDY | C13: =Master!AA26 -> 26 | D13: =Master!AK26 -> 9932.4667
... A51: =Master!Y64 -> 5216452300 | B51: =Master!Z64 -> Mutyala Poshavva | C51: =Master!AA64 -> 0 | D51: =Master!AK64 -> 0

Sheet Accident
A1: FORM 11
A2: ACCIDENT BOOK
A3: EMPLOYEE STATE INSURANCE CORPORATION
B4: (Regulation 66)
A6: S.No | B6: Date of Notice | C6: Time of Notice | D6: Name and Address of the Injured Person | E6: Sex | F6: Age | H6: Shift,Department and occupation of employee | I6: Details of Injury | N6: What exactly was the injured person doing at the time of accident | P6: Signature and designation of the person who makes the entry in the accident book | Q6: Name,address and occupation of the two witnesses | R6: Remarks if any
G7: Insurance Number | O7: Name,Occupation,address and signature or the thumb impression of the person(s) giving notice
I8: Cause | J8: Nature | K8: Date | L8: Time | M8: Place
A9: 1 | B9: 2 | C9: 3 | D9: 4 | E9: 5 | F9: 6 | G9: 7 | H9: 8 | I9: 9 | J9: 10 | K9: 11 | L9: 12 | M9: 13 | N9: 14 | O9: 15 | P9: 16 | Q9: 17 | R9: 18
B11: NO ACCIDENT OCCURRED FOR THE MONTH OF | F11: =Master!F10 -> 44652
L19: Signature of the Contractor with Seal

Sheet ESI inspection 
A1: INSPECTION BOOK UNDER E.S.I.ACT
A2: Name of the Inspector:
A3: Date of Inspection | F3: Time
A5: Manager or other officer present at the time of Inspection
F6: =Master!AN10 -> INDIAN SCHOOL OF BUSINESS
F7: =Master!AN11 -> Opp.Infosys Limited,Gachibowli,Hyderabad
A9: Remarks by Inspector

Sheet EPF-ECR
A1: UAN | B1: MEMBER NAME | C1: GROSS WAGES | D1: EPF WAGES | E1: EPS WAGES | F1: EDLI WAGES | G1: EPF CONTRI REMITTED | H1: EPS CONTRI REMITTED | I1: EPF EPS DIFF REMITTED | J1: NCP DAYS | K1: REFUND OF ADVANCES
A2: =Master!X15 -> N/A | B2: =Master!Z15 -> ARJUN KUMAR | C2: =Master!AK15 -> 20000 | D2: =100*Master!AM15/12 -> 0 | E2: =D2 -> 0 | F2: =E2 -> 0 | G2: =ROUND(D2*12/100,0) -> 0 | H2: =ROUND(E2*8.33/100,0) -> 0 | I2: =G2-H2 -> 0 | J2: =30-Master!AA15 -> 0 | K2: 0
A3: =Master!X16 -> 101252819921 | B3: =Master!Z16 -> GAJAN SINGH | C3: =Master!AK16 -> 14900 | D3: =100*Master!AM16/12 -> 14900 | E3: =D3 -> 14900 | F3: =E3 -> 14900 | G3: =ROUND(D3*12/100,0) -> 1788 | H3: =ROUND(E3*8.33/100,0) -> 1241 | I3: =G3-H3 -> 547 | J3: =30-Master!AA16 -> 0 | K3: 0
A4: =Master!X17 -> 100025787555 | B4: =Master!Z17 -> GUDALA RUSHESHWAR SWAMY | C4: =Master!AK17 -> 17918 | D4: =100*Master!AM17/12 -> 13200 | E4: =D4 -> 13200 | F4: =E4 -> 13200 | G4: =ROUND(D4*12/100,0) -> 1584 | H4: =ROUND(E4*8.33/100,0) -> 1100 | I4: =G4-H4 -> 484 | J4: =30-Master!AA17 -> 0 | K4: 0
A5: =Master!X18 -> 101335495091 | B5: =Master!Z18 -> KASALA NARSIMLU | C5: =Master!AK18 -> 11919.6 | D5: =100*Master!AM18/12 -> 11916.667 | E5: =D5 -> 11916.667 | F5: =E5 -> 11916.667 | G5: =ROUND(D5*12/100,0) -> 1430 | H5: =ROUND(E5*8.33/100,0) -> 993 | I5: =G5-H5 -> 437 | J5: =30-Master!AA18 -> 4 | K5: 0
A6: =Master!X19 -> 101423797426 | B6: =Master!Z19 -> PITANI SATHYA NARAYANA | C6: =Master!AK19 -> 9932.4667 | D6: =100*Master!AM19/12 -> 9933.3333 | E6: =D6 -> 9933.3333 | F6: =E6 -> 9933.3333 | G6: =ROUND(D6*12/100,0) -> 1192 | H6: =ROUND(E6*8.33/100,0) -> 827 | I6: =G6-H6 -> 365 | J6: =30-Master!AA19 -> 4 | K6: 0
A7: =Master!X20 -> 100321400080 | B7: =Master!Z20 -> SANGOLLA ASHOK | C7: =Master!AK20 -> 9932.4667 | D7: =100*Master!AM20/12 -> 9933.3333 | E7: =D7 -> 9933.3333 | F7: =E7 -> 9933.3333 | G7: =ROUND(D7*12/100,0) -> 1192 | H7: =ROUND(E7*8.33/100,0) -> 827 | I7: =G7-H7 -> 365 | J7: =30-Master!AA20 -> 4 | K7: 0
A8: =Master!X21 -> 100807941415 | B8: =Master!Z21 -> ASHOK LINGURAM GAIKWAD | C8: =Master!AK21 -> 9932.4667 | D8: =100*Master!AM21/12 -> 9933.3333 | E8: =D8 -> 9933.3333 | F8: =E8 -> 9933.3333 | G8: =ROUND(D8*12/100,0) -> 1192 | H8: =ROUND(E8*8.33/100,0) -> 827 | I8: =G8-H8 -> 365 | J8: =30-Master!AA21 -> 4 | K8: 0
A9: =Master!X22 -> 101438575409 | B9: =Master!Z22 -> MADHUKAR KAMTAM | C9: =Master!AK22 -> 9932.4667 | D9: =100*Master!AM22/12 -> 9933.3333 | E9: =D9 -> 9933.3333 | F9: =E9 -> 9933.3333 | G9: =ROUND(D9*12/100,0) -> 1192 | H9: =ROUND(E9*8.33/100,0) -> 827 | I9: =G9-H9 -> 365 | J9: =30-Master!AA22 -> 4 | K9: 0
A10: =Master!X23 -> 100043556888 | B10: =Master!Z23 -> Ningolla Raju | C10: =Master!AK23 -> 9932.4667 | D10: =100*Master!AM23/12 -> 9933.3333 | E10: =D10 -> 9933.3333 | F10: =E10 -> 9933.3333 | G10: =ROUND(D10*12/100,0) -> 1192 | H10: =ROUND(E10*8.33/100,0) -> 827 | I10: =G10-H10 -> 365 | J10: =30-Master!AA23 -> 4 | K10: 0
A11: =Master!X24 -> 100993759408 | B11: =Master!Z24 -> Nagani pochaiah | C11: =Master!AK24 -> 9932.4667 | D11: =100*Master!AM24/12 -> 9933.3333 | E11: =D11 -> 9933.3333 | F11: =E11 -> 9933.3333 | G11: =ROUND(D11*12/100,0) -> 1192 | H11: =ROUND(E11*8.33/100,0) -> 827 | I11: =G11-H11 -> 365 | J11: =30-Master!AA24 -> 4 | K11: 0
A12: =Master!X25 -> 101196116055 | B12: =Master!Z25 -> Mutholla Mallesh | C12: =Master!AK25 -> 9932.4667 | D12: =100*Master!AM25/12 -> 9933.3333 | E12: =D12 -> 9933.3333 | F12: =E12 -> 9933.3333 | G12: =ROUND(D12*12/100,0) -> 1192 | H12: =ROUND(E12*8.33/100,0) -> 827 | I12: =G12-H12 -> 365 | J12: =30-Master!AA25 -> 4 | K12: 0
A13: =Master!X26 -> 100844389108 | B13: =Master!Z26 -> ALIJANA JAYARAMI REDDY | C13: =Master!AK26 -> 9932.4667 | D13: =100*Master!AM26/12 -> 9933.3333 | E13: =D13 -> 9933.3333 | F13: =E13 -> 9933.3333 | G13: =ROUND(D13*12/100,0) -> 1192 | H13: =ROUND(E13*8.33/100,0) -> 827 | I13: =G13-H13 -> 365 | J13: =30-Master!AA26 -> 4 | K13: 0
... A47: =Master!X60 -> 100692721860 | B47: =Master!Z60 -> VADLA JYOTHI | C47: =Master!AK60 -> 9210.4 | D47: =100*Master!AM60/12 -> 9208.3333 | E47: =D47 -> 9208.3333 | F47: =E47 -> 9208.3333 | G47: =ROUND(D47*12/100,0) -> 1105 | H47: =ROUND(E47*8.33/100,0) -> 767 | I47: =G47-H47 -> 338 | J47: =30-Master!AA60 -> 4 | K47: 0
A48: =Master!X61 -> 101318416076 | B48: =Master!Z61 -> Rupesh Chandra Jakhmola | C48: =Master!AK61 -> 27800 | D48: =100*Master!AM61/12 -> 15000 | E48: =D48 -> 15000 | F48: =E48 -> 15000 | G48: 1800 | H48: =ROUND(E48*8.33/100,0) -> 1250 | I48: =G48-H48 -> 550 | J48: =30-Master!AA61 -> 0 | K48: 0
A49: =Master!X62 -> 101567297449 | B49: =Master!Z62 -> Bakkani Mallaiah | C49: =Master!AK62 -> 11919.6 | D49: =100*Master!AM62/12 -> 11916.667 | E49: =D49 -> 11916.667 | F49: =E49 -> 11916.667 | G49: =ROUND(D49*12/100,0) -> 1430 | H49: =ROUND(E49*8.33/100,0) -> 993 | I49: =G49-H49 -> 437 | J49: =30-Master!AA62 -> 4 | K49: 0
A50: =Master!X63 -> 101567297431 | B50: =Master!Z63 -> Chakali Narayana | C50: =Master!AK63 -> 9932.4667 | D50: =100*Master!AM63/12 -> 9933.3333 | E50: =D50 -> 9933.3333 | F50: =E50 -> 9933.3333 | G50: =ROUND(D50*12/100,0) -> 1192 | H50: =ROUND(E50*8.33/100,0) -> 827 | I50: =G50-H50 -> 365 | J50: =30-Master!AA63 -> 4 | K50: 0
A51: =Master!X64 -> 100644249379 | B51: =Master!Z64 -> Mutyala Poshavva | C51: =Master!AK64 -> 0 | D51: =100*Master!AM64/12 -> 0 | E51: =D51 -> 0 | F51: =E51 -> 0 | G51: =ROUND(D51*12/100,0) -> 0 | H51: =ROUND(E51*8.33/100,0) -> 0 | I51: =G51-H51 -> 0 | J51: =30-Master!AA64 -> 30 | K51: 0

Sheet EPF Inspection
B2: INSPECTION NOTE BOOK
B3: (vide para 36 of the E.P.F.Scheme,1952)
B6: Name of the Establishment : | E6: =Master!AN5 -> GROTECH LANDSCAPE DEVELOPERS PVT. LTD.
C7: &
B8: Address | E8: =Master!AN6 -> 290/E, Khanapur Village, Gandipet Mandal, Ranga Reddy, Hyderabad-500075 T.S.
B13: Code No. AP/ | E13: TYPE
B15: Date of Visit | C15: Period for which accounts checked | E15: Observations of Inspector | H15: Compliance by employer #
B18: 1 | C18: 2 | E18: 3 | H18: 4

Sheet PT-FormV
A1: FORM -V
A2: (See Rule 12)
A3: RETURNS OF TAX PAYABLE BY EMPLOYER
A4: Under sub-section (1) of Section 7 of the A.P.Tax on Professions, Trades, Callings and Employments Act, 1987
A6: Return of tax payable for the month ending on | B6: =Master!F10 -> 44652
A8: Name of the Employer | B8: =Master!F5 -> GROTECH LANDSCAPE DEVELOPERS PVT. LTD.
A10: Address
A11: =Master!F6 -> 290/E, Khanapur Village, Gandipet Mandal, Ranga Reddy, Hyderabad-500075 T.S.
A12: Registration Certificate No. | B12: 36942211242 | C12: TYPE
A14: Number of employees during the month in respect of whoom the tax is payable is as under:
A16: Employees whose monthly salaries or wages or both are | B16: Number of employees | C16: Rate of Tax per month | D16: Amount of tax deducted
A18: Below Rs.15000/- | B18: 49 | C18: 0 | D18: =B18*C18 -> 0
A19: Between Rs.15001/- to Rs.20000/- | B19: 2 | C19: 150 | D19: =B19*C19 -> 300
A20: Above Rs.20000/- | B20: 1 | C20: 200 | D20: =B20*C20 -> 200
A21: Total | D21: =SUM(D18:D20) -> 500
A22: Add: Simple inerest payable (if any) on the above amount at two percent per month or part there of (vide Section 11 of the Act)
A24: Grand Total | D24: =D21 -> 500
A26: Amount paid Rs. | B26: Under Cheque no. | D26: Dated:
A27: I certify that all the employees who are liable to pay the tax in my employ during the period of return have been covered by the foregoing particulars. I also certify that the necessary revision in the amount of tax deductible from the salary or wages of the employees on account of variation in the salary or wages earned by them has been made wherever necessary.
A29: I, Shri. solemnly declare that the above statements are true to the best of my knowledge and belief.
A31: Place: | C31: Signature
A32: Date : | C32: Status
A34: (FOR OFFICIAL USE)
A36: The return is accepted on verification
A38: Tax Assessed | B38: Rs.
A39: Tax Paid | B39: Rs.
A40: Balance | B40: Rs.
C42: Assessing Authority.

Sheet TDS
A2: S.NO | B2: EMPLOYEE NAME | C2: PAN NUMBER | D2: EARNED GROSS WAGES | E2: AMOUNT OF TAX DEDUCTED | F2: DATE OF PAYMENT | G2: PAYMENT MODE | H2: BANK NAME | I2: IFSC CODE | J2: ACCOUNT NUMBER | K2: REMARKS

Sheet Bonus-C
A1: FORM C- Bonus paid to employees for the accounting year ending on the | Q1: 2022-23
A2: FORM "C" ( See rule 4 [c] ) of the Payment of Bonus Rules, 1975)
A4: Name of the Establishment : | C4: =Master!F5 -> GROTECH LANDSCAPE DEVELOPERS PVT. LTD. | J4: Wage Period | L4: =Master!F10 -> 44652
C5: =Master!F6 -> 290/E, Khanapur Village, Gandipet Mandal, Ranga Reddy, Hyderabad-500075 T.S.
A6: Sr. No | B6: Name of the Employee | C6: Father's Name / Husband's Name | D6: Whether he has completed 15 yrs of age at the beginning of the accounting year | E6: Designation | F6: No. of days worked in the year | G6: Total Salary or wages in the year | H6: Amt. of bonus payable under section 10 or section 11 as the case may be Ex gratia | I6: DEDUCTIONS | L6: Total Sum Deducted (Col. 9,10 and 11) | M6: Net Amount payable (Col. 8 minus Col. 12) | N6: Amount Actually paid | O6: Date on which paid | P6: Signature / Thumb impression of the employee
I7: Puja Bonus or other customary bonus paid during the accounting year | J7: Interim Bonus or bonus paid in advance | K7: Deduction on account of financial loss if any caused by misconduct of the employee | Q7: Account Number
A8: 1 | B8: 2 | C8: 3 | D8: 4 | E8: 5 | F8: 6 | G8: 7 | H8: 8 | I8: 9 | J8: 10 | K8: 11 | L8: 12 | M8: 13 | N8: 14 | O8: 15 | P8: 16
A9: 1 | B9: =Master!D15 -> ARJUN KUMAR | C9: =Master!G15 -> kallu | D9: YES | E9: =Master!J15 -> Supervisor | F9: =Master!W15 -> 0 | G9: =Master!AG15 -> 0 | H9: 1442 | I9: N/A | J9: N/A | K9: N/A | L9: N/A | M9: =H9 -> 1442 | N9: =M9 -> 1442 | O9: =Master!AO15 -> 0 | P9: =Master!AP15 -> 0 | Q9: =Master!AU15 -> 6912137285
A10: 2 | B10: =Master!D16 -> GAJAN SINGH | C10: =Master!G16 -> Chandrapal singh | D10: YES | E10: =Master!J16 -> Supervisor | F10: =Master!W16 -> 0 | G10: =Master!AG16 -> 0 | H10: 1442 | I10: N/A | J10: N/A | K10: N/A | L10: N/A | M10: =H10 -> 1442 | N10: =M10 -> 1442 | O10: =Master!AO16 -> 0 | P10: =Master!AP16 -> 0 | Q10: =Master!AU16 -> 7513074030
A11: 3 | B11: =Master!D17 -> GUDALA RUSHESHWAR SWAMY | C11: =Master!G17 -> GUDALA KRISHANA MURTHY | D11: YES | E11: =Master!J17 -> Supervisor | F11: =Master!W17 -> 0 | G11: =Master!AG17 -> 4721 | H11: 1442 | I11: N/A | J11: N/A | K11: N/A | L11: N/A | M11: =H11 -> 1442 | N11: =M11 -> 1442 | O11: =Master!AO17 -> 0 | P11: =Master!AP17 -> 0 | Q11: =Master!AU17 -> 1912391941
A12: 4 | B12: =Master!D18 -> KASALA NARSIMLU | C12: =Master!G18 -> KASALA POCHAIAH | D12: YES | E12: =Master!J18 -> Semi Skilled Gardner | F12: =Master!W18 -> 0 | G12: =Master!AG18 -> 0 | H12: 1442 | I12: N/A | J12: N/A | K12: N/A | L12: N/A | M12: =H12 -> 1442 | N12: =M12 -> 1442 | O12: =Master!AO18 -> 0 | P12: =Master!AP18 -> 0 | Q12: =Master!AU18 -> 20201585355
A13: 5 | B13: =Master!D19 -> PITANI SATHYA NARAYANA | C13: =Master!G19 -> P SURYANARAYANA | D13: YES | E13: =Master!J19 -> Semi Skilled Gardner | F13: =Master!W19 -> 0 | G13: =Master!AG19 -> 0 | H13: 1442 | I13: N/A | J13: N/A | K13: N/A | L13: N/A | M13: =H13 -> 1442 | N13: =M13 -> 1442 | O13: =Master!AO19 -> 0 | P13: =Master!AP19 -> 0 | Q13: =Master!AU19 -> 141410100131316
A14: 6 | B14: =Master!D20 -> SANGOLLA ASHOK | C14: =Master!G20 -> SANGOLLA ESWARAIAH | D14: YES | E14: =Master!J20 -> Semi Skilled Gardner | F14: =Master!W20 -> 0 | G14: =Master!AG20 -> 0 | H14: 1442 | I14: N/A | J14: N/A | K14: N/A | L14: N/A | M14: =H14 -> 1442 | N14: =M14 -> 1442 | O14: =Master!AO20 -> 0 | P14: =Master!AP20 -> 0 | Q14: =Master!AU20 -> 62135175705
A15: 7 | B15: =Master!D21 -> ASHOK LINGURAM GAIKWAD | C15: =Master!G21 -> M LINGRAM | D15: YES | E15: =Master!J21 -> Semi Skilled Gardner | F15: =Master!W21 -> 0 | G15: =Master!AG21 -> 0 | H15: 1442 | I15: N/A | J15: N/A | K15: N/A | L15: N/A | M15: =H15 -> 1442 | N15: =M15 -> 1442 | O15: =Master!AO21 -> 0 | P15: =Master!AP21 -> 0 | Q15: =Master!AU21 -> 35398345250
A16: 8 | B16: =Master!D22 -> MADHUKAR KAMTAM | C16: =Master!G22 -> KAMTAM KISHAN | D16: YES | E16: =Master!J22 -> Semi Skilled Gardner | F16: =Master!W22 -> 0 | G16: =Master!AG22 -> 0 | H16: 1442 | I16: N/A | J16: N/A | K16: N/A | L16: N/A | M16: =H16 -> 1442 | N16: =M16 -> 1442 | O16: =Master!AO22 -> 0 | P16: =Master!AP22 -> 0 | Q16: =Master!AU22 -> 923249324
A17: 9 | B17: =Master!D23 -> Ningolla Raju | C17: =Master!G23 -> ningolla pochaiah | D17: YES | E17: =Master!J23 -> Semi Skilled Gardner | F17: =Master!W23 -> 0 | G17: =Master!AG23 -> 0 | H17: 1442 | I17: N/A | J17: N/A | K17: N/A | L17: N/A | M17: =H17 -> 1442 | N17: =M17 -> 1442 | O17: =Master!AO23 -> 0 | P17: =Master!AP23 -> 0 | Q17: =Master!AU23 -> 861410110009223
A18: 10 | B18: =Master!D24 -> Nagani pochaiah | C18: =Master!G24 -> Nagani mallaiah | D18: YES | E18: =Master!J24 -> Semi Skilled Gardner | F18: =Master!W24 -> 0 | G18: =Master!AG24 -> 0 | H18: 1442 | I18: N/A | J18: N/A | K18: N/A | L18: N/A | M18: =H18 -> 1442 | N18: =M18 -> 1442 | O18: =Master!AO24 -> 0 | P18: =Master!AP24 -> 0 | Q18: =Master!AU24 -> 38228069327
A19: 11 | B19: =Master!D25 -> Mutholla Mallesh | C19: =Master!G25 -> Mutholla balaiah | D19: YES | E19: =Master!J25 -> Semi Skilled Gardner | F19: =Master!W25 -> 0 | G19: =Master!AG25 -> 0 | H19: 1442 | I19: N/A | J19: N/A | K19: N/A | L19: N/A | M19: =H19 -> 1442 | N19: =M19 -> 1442 | O19: =Master!AO25 -> 0 | P19: =Master!AP25 -> 0 | Q19: =Master!AU25 -> 20176301430
A20: 12 | B20: =Master!D26 -> ALIJANA JAYARAMI REDDY | C20: =Master!G26 -> ALIJANA OBULU REDDY | D20: YES | E20: =Master!J26 -> Semi Skilled Gardner | F20: =Master!W26 -> 0 | G20: =Master!AG26 -> 0 | H20: 1442 | I20: N/A | J20: N/A | K20: N/A | L20: N/A | M20: =H20 -> 1442 | N20: =M20 -> 1442 | O20: =Master!AO26 -> 0 | P20: =Master!AP26 -> 0 | Q20: =Master!AU26 -> 33412525880
... A58: 50 | B58: =Master!D64 -> Mutyala Poshavva | C58: =Master!G64 -> MUTYALA BABU | D58: YES | E58: =Master!J64 -> Unskilled Gardner | F58: =Master!W64 -> 0 | G58: =Master!AG64 -> 0 | H58: 1442 | I58: N/A | J58: N/A | K58: N/A | L58: N/A | M58: =H58 -> 1442 | N58: =M58 -> 1442 | O58: =Master!AO64 -> 0 | P58: =Master!AP64 -> 0 | Q58: =Master!AU64 -> Bank Cheque
F59: =SUM(F9:F58) -> 0 | G59: =SUM(G9:G58) -> 4721 | H59: =SUM(H9:H58) -> 72100 | M59: =SUM(M9:M58) -> 72100 | N59: =SUM(N9:N58) -> 72100
L62: Signature of the Contractor with Seal

Sheet Equal remuneration
A1: FORM-D
A2: (See rule 6)
A3: Register to be maintained by the employer under rule 6 of the Equal Remuneration Rules, 1976
D5: =Master!F10 -> 44652
A7: Name and address of Contractor : | F7: =Master!F5 -> GROTECH LANDSCAPE DEVELOPERS PVT. LTD.
F8: =Master!AN6 -> 290/E, Khanapur Village, Gandipet Mandal, Ranga Reddy, Hyderabad-500075 T.S.
A9: Name and address of establishment in/under which contract is carried on :
A11: Name and address of Principal Employer : | F11: =Master!AN10 -> INDIAN SCHOOL OF BUSINESS
F12: =Master!AN11 -> Opp.Infosys Limited,Gachibowli,Hyderabad
A13: Total number of men workers employed | C13: =D21 -> 2
A15: Total number of women workers employed | C15: =C21 -> 0
C17: Components of remuneration
A18: Category of workers | B18: Brief Description of work | C18: No of women employed | D18: No. of men employed | E18: Rate or remuneration paid | F18: Basic wage & Dearness Allowance | G18: House Rent allowance | H18: Other allowances | I18: Cash value of concessional supply of essential commodities | J18: Name of the Client | K18: Primary Work Place/ Location
A19: =Master!J15 -> Supervisor | B19: IT SUPPORTIVE SERVICES | C19: 0 | D19: 1 | E19: =Master!AK15 -> 20000 | F19: =Master!AD15 -> 20000 | G19: =Master!AG15 -> 0 | H19: =E19-(F19+G19) -> 0 | I19: 0 | J19: Infosys Limited | K19: HYDERABAD
A20: =Master!J16 -> Supervisor | B20: IT SUPPORTIVE SERVICES | C20: 0 | D20: 1 | E20: =Master!AK16 -> 14900 | F20: =Master!AD16 -> 11900 | G20: =Master!AG16 -> 0 | H20: =E20-(F20+G20) -> 3000 | I20: 0 | K20: SEZ
C21: =C19+C22 -> 0 | D21: =SUM(D19:D20) -> 2
E25: Signature of the Contractor with Seal

Sheet FORM-A
B1: FORM A
B2: [See Rule 3 of Maternity Act Rules, 1965]
B3: MUSTER ROLL
B4: Name of [mine or circus]: | D4: =Master!F5 -> GROTECH LANDSCAPE DEVELOPERS PVT. LTD. | E4: =Master!F6 -> 290/E, Khanapur Village, Gandipet Mandal, Ranga Reddy, Hyderabad-500075 T.S.
B5: 1 | C5: Serial Number.
B6: 2 | C6: Name of woman and her father's (or, if married, husband's) name.
B7: 3 | C7: Date of appointment.
B8: 4 | C8: Nature of work.
B9: 5 | C9: Dates with month and year in which she is employed, laid off and not employed.
C10: Month | D10: No.of days employed | E10: No.of days laid off | F10: No.of days not employed | G10: Remarks
B17: 6 | C17: Date on which the woman gives notice under section 6.
B18: 7 | C18: Date of discharge/dismissal, if any.
B19: 8 | C19: Date of production of proof of pregnancy under section 6.
B20: 9 | C20: Date of birth of child.
B21: 10 | C21: Date of production of proof of delivery/miscarriage/ 1[Medical Termination of pregnancy/ tubectomy operation/death.]
B22: 11 | C22: Date of production of proof of illness referred to in section 10.
B23: 12 | C23: Date with the amount of maternity benefit paid in advance of expected delivery.
B24: 13 | C24: Date with the amount of subsequent payment of maternity benefit.
B25: 14 | C25: Date with the amount of bonus, if paid, under section 8.
B26: 15 | C26: Date with the amount of wages paid on account of leave under section 9.
B27: 15A | C27: Date with the amount of wages paid on account of leave under section 9A
B28: 16 | C28: Date with the amount of wages paid on account of leave under section 10 and period of leave granted
B29: 17 | C29: Name of the person nominated by the woman under section 6.
B30: 18 | C30: If the woman dies, the date of her death, the name of the person to whom maternity benefit and/or other amount was paid, the amount thereof, and the date of payment.
B31: 19 | C31: If the woman dies and the child survives, the name of the person to whom the amount of maternity benefit was paid on behalf of the child and the period for which it was paid.
B32: 20 | C32: Signature of the employer of 3[the mine or circus] authenticating the entries in the muster-roll.
B33: 21 | C33: Remarks column for the use of the Inspector.
B34: Certifited that no pregnant employee worked for the month of | G34: =Master!F10 -> 44652
E36: For | F36: =Master!F5 -> GROTECH LANDSCAPE DEVELOPERS PVT. LTD.
F38: Authorized Signatory

Sheet FORM-B
B1: FORM B
B2: [See Rule 4(1) of Maternity Act Rules, 1965]
B3: Name of [mine or circus]: | D3: =Master!F5 -> GROTECH LANDSCAPE DEVELOPERS PVT. LTD. | E3: =Master!F6 -> 290/E, Khanapur Village, Gandipet Mandal, Ranga Reddy, Hyderabad-500075 T.S.
B6: This is to certify that I examined…. wife /daughter of ….. a woman employee in name of Mine or Circus on (Date)
D7: and found/ cannot discover that she is pregnant and is expected to be delivered of a child within (month/days) from the above
B8: mentioned date date/has undergone miscarriage/[Medical termination of pregnancy or tubectomy operation]/has been delivered
B9: of a child on….. (date) or is suffering from…..(date) from illness arising out of pregnancy/delivery/premature birth of a child or miscarriage/
B10: [Medical termination of pregnancy or tubectomy operation ].
D12: Signature, qualifications and designation of Medical Officer/Medical Practitioner.
B15: Date…..
B16: Definitions of "child" and "miscarriage" as in the Maternity Benefit Act, 1961.-
B17: 1. "Child" includes a still-born child.
B18: 2. "Miscarriage" means expulsion of the contents of a pregnant uterus at any period prior to or during the twenty-sixth week of pregnancy
B19: but does not include any miscarriage,the causing of which is punishable under the Indian Penal Code.
B20: Ins. by G.S.R. 70(E), dated 31st January, 1996 (w.e.f. 31-1-1996).
B22: Certifited that no pregnant employee worked for the month of | G22: =Master!F10 -> 44652
E25: For | F25: =Master!F5 -> GROTECH LANDSCAPE DEVELOPERS PVT. LTD.
F27: Authorized Signatory

Sheet FORM-C
B1: FORM C
B2: [See Rule 4(4) of Maternity Act Rules, 1965]
B4: Name of [mine or circus]: | D4: =Master!F5 -> GROTECH LANDSCAPE DEVELOPERS PVT. LTD. | E4: =Master!F6 -> 290/E, Khanapur Village, Gandipet Mandal, Ranga Reddy, Hyderabad-500075 T.S.
B7: This is to certify that
B8: Smt……………………………….wife/daughter of ……………………….employed in ……………….(name of [Mine or Circus]
B9: expired on ……………………..before/during/after confinement. The child died on …./survives her.
D13: Signature, qualifications and designation of Medical Officer/Medical Practitioner.
C15: Ins. by G.S.R. 70(E), dated 31st January, 1996 (w.e.f. 31-1-1996).
B17: Certifited that no pregnant employee worked for the month of | G17: =Master!F10 -> 44652
E20: For | F20: =Master!F5 -> GROTECH LANDSCAPE DEVELOPERS PVT. LTD.
F22: Authorized Signatory

Sheet FORM-D
B1: FORM D
B2: [See Rule 4(5) of Maternity Act Rules, 1965]
B4: Name of [mine or circus]: | D4: =Master!F5 -> GROTECH LANDSCAPE DEVELOPERS PVT. LTD. | E4: =Master!F6 -> 290/E, Khanapur Village, Gandipet Mandal, Ranga Reddy, Hyderabad-500075 T.S.
B7: This is to certify that I examined……………..wife/daughter of ……….a woman employed in ………..(name of [Mine or Circus ]
B8: and found that she has been delivered of a child/has undergone miscarriage on ….(date)
E11: Signature of registered Midwife
C13: Date….
C14: Definitions of "child" and "miscarriage" as in the Maternity Benefit Act, 1961-
C15: 1. "Child" includes a still-born child.
C16: 2. "Miscarriage" means expulsion of the contents of a pregnant uterus at any period prior to or during the twenty-sixth
C17: week of pregnancy but does not include any miscarriage, the causing of which is punishable under the Indian Penal Code.
C20: Subs. by G.S.R. 59(E), dated 27th February, 1975 (w.e.f. 1-3-1975).
B22: Certifited that no pregnant employee worked for the month of | G22: =Master!F10 -> 44652
E25: For | F25: =Master!F5 -> GROTECH LANDSCAPE DEVELOPERS PVT. LTD.
F27: Authorized Signatory

Sheet FORM-E
C2: FORM E
C3: [See sub-rule (2) of Rule 4]
D4: Register of Fines Realised and unpaid accumulations for the year 2022
C6: Sl. No. | E6: During
E7: Quarter ending 31st March | F7: Quarter ending 30th June | G7: Quarter ending 30th September | H7: Quarter ending 31st December
C8: 1 | D8: 2 | E8: 3 | F8: 4 | G8: 5 | H8: 6
C9: 1 | D9: Total realisation under fines | E9: NIL | F9: NIL | G9: NIL | H9: NIL
C10: 2 | D10: Total amount becoming unpaid accumulations* of
D11: (i) Basic Wage | E11: NIL | F11: NIL | G11: NIL | H11: NIL
D12: (ii) Overtime | E12: NIL | F12: NIL | G12: NIL | H12: NIL
D13: (iii) Dearness Allowance and other allowances | E13: NIL | F13: NIL | G13: NIL | H13: NIL
D16: Total of (1) and (2) ………….
C17: *See definition of “unpaid Accumulation” under sub-section (11) of Section 2 of the Act.
D19: =Master!F5 -> GROTECH LANDSCAPE DEVELOPERS PVT. LTD. | F19: Signature of the Employer with Seal
D20: =Master!F6 -> 290/E, Khanapur Village, Gandipet Mandal, Ranga Reddy, Hyderabad-500075 T.S.

Sheet MIS
B1: =Master!F5 -> GROTECH LANDSCAPE DEVELOPERS PVT. LTD.
B2: MANAGEMENT INFORMATION SYSTEM
A3: S.NO | B3: MONTHLY REPORT | E3: SELECT | I3: =Master!F10 -> 44652
A4: 1 | B4: Employee Attendance in days | D4: =Master!AA65 -> 1160
A5: 2 | B5: Employee Total Earned Salaries | D5: =Master!AK65 -> 471605.53
A6: 3 | B6: ESI Employee Contribution | D6: =Master!AL65 -> 3362
A7: 4 | B7: ESI Employer Contribution | D7: =3.25*D6/0.75 -> 14568.667
A8: 5 | B8: EPF Employee Contribution | D8: =Master!AM65 -> 52084
A9: 6 | B9: EPF Employer Contribution | D9: =13*D8/12 -> 56424.333
A10: 7 | B10: Workmen Compensation/Insurance contribution | D10: NIL
A11: 8 | B11: Maternity benefit contribution | D11: NIL
A12: 9 | B12: PT contribution | D12: ='PT-FormV'!D24 -> 500
A13: 10 | B13: TDS Contribution | D13: =Master!AO65 -> 0
A14: 11 | B14: Employee Total Net Salaries | D14: =Master!AR65 -> 415659.53
A15: 12 | B15: Bonus Contribution | D15: ='Bonus-C'!H59 -> 72100
A16: 13 | B16: Gratuity Contribution | D16: NIL

Sheet Integrate Annual returns
A2: Form- I
A3: Annual Return for the Financial Year……….. | J3: select
A4: (to be filed before 30th April to the inspector concerned)
A5: 1 | B5: Details of Establishment:
A6: (a) | B6: Name of the Establishment: | G6: =Master!F5 -> GROTECH LANDSCAPE DEVELOPERS PVT. LTD.
G7: =Master!F6 -> 290/E, Khanapur Village, Gandipet Mandal, Ranga Reddy, Hyderabad-500075 T.S.
A9: (b) | B9: Address of the Establishment:
A10: (c) | B10: Establishment registered under which Act? (ticket the correct option)
B11: (i) The Telangana Shops and Establishments Act, 1988
B12: (ii) The Factories Act, 1948
B13: (iii) The Motor Transport Workers Act, 1961
B14: (iv) Other (Specify) | G14: Contract Labour Act 1970
A15: (d) | B15: Name of Employer
A16: (e) | B16: Address of Employer
A17: (f) | B17: Email of employer
A18: (g) | B18: Telephone Number of employer (Office )
E19: (Residency)
A20: (h) | B20: Mobile Number
A21: (i) | B21: Name and address of the Manager or person responsible for supervision and control of the establishment:
A22: (j) | B22: Brief description of business/work/product:
A23: 2 | B23: Details of Registration under Applicable Acts:
B24: Enter details only for the Acts which are applicable:
A25: Sl. No. | B25: Name of Act (tick at appropriate Acts) | F25: Registration / License No. | J25: Date of issue /last renewal
A26: 1 | B26: 2 | F26: 3 | J26: 4
A27: i. | B27: Telangana Shops & Establishments Act, 1988 / Factories Act, 1948 / Moto Transport Workers Act, 1961
A28: ii. | B28: Contract Labour (R&A) Act, 1970 (if applicable)
A29: iii. | B29: Inter-state Migrant Workmen (Regulation of Employment and Condition of Service), Act, 1979 (if applicable)
A30: 3 | B30: Details of workers directly employed the establishment (excluding contract workers) during the financial year
A31: (a) | B31: Average number of workers employed daily:
A32: (b) | B32: Average number of hours worked in a day (including overtime):
A33: (c) | B33: Number of man-days during the year:
B34: (i) Male
B35: (ii) Female
B36: (iii) Adolescent
B37: (iv) Children
B38: TOTAL
A39: (d) | B39: Day of weekly holiday (Tick ):
B40: (Monday/Tuesday/Wednesday/Thursday/Friday/Saturday/Sunday).
A41: (e) | B41: Timings of shift working:
B42: General Shift | F42: Time from___________Hrs | J42: To……………..Hrs
B43: First Shift: | F43: Time from___________Hrs | J43: To……………..Hrs
B44: Second Shift: | F44: Time from___________Hrs | J44: To……………..Hrs
B45: (if applicable)
B46: Third Shift: | F46: Time from___________Hrs | J46: To……………..Hrs
B47: (if applicable)
A48: (f) | B48: Number of working days during the financial year:
A49: 4 | B49: Details of Contract Labour (if employed):
B50: No of Contractors engaged | D50: No. of Contract Labour Employed | L50: Total Mandays during g the year
D51: Males | E51: Females | F51: Adolescents(bet ween the age of 14 to 18 years) | H51: Children(bel ow 14 years of age) | J51: Total | K51: No. of days worked
B52: 1 | D52: 2 | L52: 3
A56: 5 | B56: Maximum number of persons employed in any day during the financial year
B57: Males | D57: Females | F57: Adolescents (between the age of 14 to 18 years) | J57: Children (below 14 years of age) | L57: Total
B58: 1 | D58: 2 | F58: 3 | J58: 4 | L58: 5
A62: 6 | B62: Details of workers retired, retrenched, discharged etc. during the Financial year:
B63: No. of workers | K63: Amount of benefits paid (benefit wise) Rs.
B64: Retired on superannuation | D64: Retrenched/ Discharged / Terminated | G64: Dismissed | I64: Terminal Benefit Paid Rs.
B66: 1 | K66: 2
A68: 7 | B68: Man-days lost during the Financial year on account of
A69: Sl. No. | B69: Reasons | E69: No. of workers involved | H69: No. of man-days lost | K69: Loss in terms of money
A70: 1 | B70: 2 | E70: 3 | H70: 4 | K70: 5
A71: (a) | B71: Strike
A72: (b) | B72: Lockout
A73: (c) | B73: Lay - off
A74: (d) | B74: Retrenchment
A75: (e) | B75: Fatal accidents
A76: (f) | B76: Non-fatal but serious accidents
A77: (g) | B77: Any other
B78: TOTAL
A79: 8 | B79: Wages paid during the Financial year
B80: Category | C80: Rates of Wages | D80: No. of Workers
D81: Male | E81: Female | F81: Children | G81: Adolescent | H81: Total | I81: Male | J81: Female | K81: Children | L81: Adolescent | M81: Total
B82: 1 | C82: 2 | D82: 3
B83: Highly Skilled
B84: Skilled
B85: Semi Skilled
B86: Un Skilled
B87: Total
A88: a) | B88: Whether Minimum wages GO is applicable to the establishment and if so mention the G.O. No. and Date
A89: b) | B89: Whether Minimum wages paid to all the workers
A90: c) | B90: Whether equal wages paid to male and female workers
A91: d) | B91: Whether claim applications under Minimum Wages Act are pending before the Authority
A92: e) | B92: If so, the amount claimed in the application
B93: i) No. of workers filled claim application
B94: ii) Period of claim
A95: 9 | B95: Details of Wage Payments
B96: Gross wages paid | E96: Deductions | J96: Net Wages paid
B97: 1 | E97: 2 | J97: 3
B98: In cash | C98: In kind | E98: Fines | F98: Deductions for damage or loss | H98: Others (Welfare contribution etc) | J98: In cash | L98: In kind
A101: 10 | B101: Details of various welfare amenities provided to workers
B102: 1 Total number of workers in the establishment:
B103: 2 No. of workers granted Casual Leave: / Sick leave / Leave with Wages / Earned Leave
B104: 3 No. of workers granted Leave with wages or paid wages in lieu of leave:
B105: 4 No. of workers who were provided ambulance facility:
B106: 5 No. of workers who availed facility of canteen:
B107: 6 No. of rest rooms:
A108: 11 | B108: Payment of Bonus Act, 1965
B109: Number of employees benefited by bonus payments during the Financial Year
A110: Total no. of workers in the Estt | B110: Total No. of worker entitled to bonus | C110: Total amount payable as bonus | D110: Settlement, if any, reached | F110: Percentage of bonus declared or Minimum Bonus @ 8.33% Paid | H110: Total amount of bonus actually paid | I110: Date on which payment made | J110: Whether bonus has been paid to all the employees (Yes/No) | L110: Reasons for nonpayment of bonus to any employee (if applicable)
A111: 1 | B111: 2 | C111: 3 | D111: 4 | F111: 5 | H111: 6 | I111: 7 | J111: 8 | L111: 9
A117: 12 | B117: Payment of Gratuity Act, 1972 Details of Gratuity paid to workers during the Financial Year
...

Sheet POSH return
E1: on letter head
D8: Annual report for the Year ending year | F8: 2021
D9: Under section 21 of The Sexual Harassment of women at workplace(PRSH Act,2013)
E10: TO | F10: The District Officer
D11: Name and address of the POSH Authority | F11: And Deputy Collector
F12: Hyderabad District Collectorate
F13: Hyderabad
F14: Telangana
D16: Sl. No. | E16: Description of the Complaint | F16: Action taken
D17: 1 | E17: 2 | F17: 3
D18: 1 | E18: No.of Complaints received during the year : | F18: NIL
D19: 2 | E19: No.of Complaints disposed off during the year : | F19: NIL
D20: 3 | E20: No.of Cased pending for more than 90 days : | F20: NIL
D21: 4 | E21: No. of Workshops or Awareness programs against Sexual Harassment Carried out : | F21: TWO
E22: (Kindly mention static data or Number of total workshop/Training Program conducted during the year)
D23: 5 | E23: Nature of action taken by the Employer : | F23: NO ACTION TAKEN AS NO COMPLAINTS
E24: ANNEXURE
E25: The following action was taken by the Employer in respect of the complaints received
E26: during the year | F26: NIL
E27: No.of Complaints during the year : | F27: NIL
E28: Investigated and completed by the Committee: | F28: NIL
E29: Action taken | F29: NO ACTION TAKEN AS NO COMPLAINTS
E30: Written Apology : | F30: N/A
E31: Warning : | F31: N/A
E32: Reprimand or Censure : | F32: N/A
E33: Withholding of Promotion : | F33: N/A
E34: Withholding of Pay rise/Increment : | F34: N/A
E35: Termination : | F35: N/A
E36: Transfer : | F36: N/A
E37: Undergo Counselling : | F37: N/A
E38: Carrying out Community Service : | F38: N/A
E39: (Officer name : )
E40: Sign/-
E41: Presiding Officer-Internal Committee
F44: Signature of the Employer
