Workbook

Sheet Employee Database
A1: EMPLOYEE DATABASE
A3: Name and address of Employer: | J3: =[1]Master!F5 -> Spruce IT Private Limited
J4: =[1]Master!F6 -> #Shop No.7,II Floor,Sy.No. 30/Part,Street No.8,Habsiguda,Hyderabad-07
A5: Nature and location of work: | J5: =[1]Master!F8 -> IT Support Services & Hyderabad
A7: Wage period: Monthly | J7: 45383
A9: Serial No. in the Register of Workmen | B9: Service Status (In Service/Resigned) | C9: Name of the Principal Employer | D9: Address-1 (H.No.&Street Name) | E9: Address-2 (Village Name) | F9: Address-3 (Mandal&District Name) | G9: Address-4 (State with PIN code) | H9: Work Location | I9: Employee ID | J9: Name of the Employee as Per Aadhar Card | K9: Date of Birth | L9: Gender | M9: Father Name | N9: Marital Status | O9: Husband/Wife Name | P9: Mobile | Q9: Emergency Contact Number(Family) | R9: Mail ID | S9: Nationality | T9: Educational Qualification | U9: Department | V9: Designation / Nature of Work Done | W9: Date of Joining | X9: EPF UAN Number (If already have) | Y9: ESI Number (If already have) | Z9: EPF required | AA9: ESI required | AB9: Aadhar Card No | AC9: PAN No | AD9: Bank Name | AE9: Bank Account No | AF9: Bank IFSC Code | AG9: Permanent Address-1 (H.No.&Street Name) | AH9: Permanent Address-2 (Village Name) | AI9: Permanent Address-3 (Mandal&District Name) | AJ9: Permanent Address-4 (State with PIN code) | AK9: Present Address-1 (H.No.&Street Name) | AL9: Present Address-2 (Village Name) | AM9: Present Address-3 (Mandal&District Name) | AN9: Present Address-4 (State with PIN code) | AO9: Specimen Signature or thumb impression of Workman | AP9: Performance Remarks | AQ9: Date of termination of Employment | AR9: Reasons for termination | AS9: Photo | AT9: Actuals Salary Details
A10: 1 | B10: 2 | C10: 3 | D10: 4 | E10: 5 | F10: 6 | G10: 7 | H10: 8 | I10: 9 | J10: 10 | K10: 11 | L10: 12 | M10: 13 | N10: 14 | O10: 15 | P10: 16 | Q10: 17 | R10: 18 | S10: 19 | T10: 20 | U10: 21 | V10: 22 | W10: 23 | X10: 24 | Y10: 25 | Z10: 26 | AA10: 27 | AB10: 28 | AC10: 29 | AD10: 30 | AE10: 31 | AF10: 32 | AG10: 33 | AH10: 34 | AI10: 35 | AJ10: 36 | AK10: 37 | AL10: 38 | AM10: 39 | AN10: 40 | AO10: 41 | AP10: 42 | AQ10: 43 | AR10: 44 | AS10: 45 | AT10: Monthly CTC | AU10: Monthly rate of wages | AV10: Basic | AW10: Dearness Allowances | AX10: HRA | AY10: CONVEYANCE | AZ10: Medical Allowance | BA10: Bonus | BB10: Special Allowance
A11: 1 | B11: In Service | C11: Infosys Limited | D11: Sy No 43 | E11: Pocharam | F11: Ghatkesar Mandal,RR | G11: Telangana-500087 | H11: Telangana_Hyderabad_SEZ | I11: GR001 | J11: GOLLAMANDA SUDEEP KUMAR | K11: 01.01.1978 | L11: Male | M11: GOLLAMANDA PAUL RAJU | N11: Un Married | S11: INDIAN | AP11: Excellent | AT11: 120000 | AU11: 10000 | AV11: =AU11*60% -> 6000 | AW11: 0 | AX11: =(AU11-AV11) -> 4000 | AY11: 0 | AZ11: 0 | BA11: 0 | BB11: 0
A12: 2 | B12: Resigned | C12: Infosys Limited | D12: Electronic city | E12: Bangalore | F12: Srinagar Colony Mandal, | G12: Karnataka-600087 | H12: Karnataka_Bangalore-STP | I12: GR002 | J12: GOLLAMANDA PRAVEEN KUMAR | K12: 01.01.1980 | L12: Male | M12: GOLLAMANDA PRABHAKAR | N12: Un Married | S12: INDIAN | AP12: Excellent | AR12: Resignation | AT12: 28000 | AU12: 25000 | AV12: =AU12*60% -> 15000 | AW12: 0 | AX12: =(AU12-AV12) -> 10000 | AY12: 0 | AZ12: 0 | BA12: 0 | BB12: 0
A13: 3
A14: 4
A15: 5
A16: 6
A17: 7
A18: 8
A19: 9
A20: 10
A21: 11
A22: 12
A23: 13
A24: 14
... A60: 50

Sheet Wage Data
A1: WAGES STATEMENT
A3: Name and address of Employer: | Q3: Spruce IT Private Limited
Q4: #Shop No.7,II Floor,Sy.No. 30/Part,Street No.8,Habsiguda,Hyderabad-07
A5: Nature and location of work: | Q5: IT Support Services & Hyderabad
A7: Wage period: Monthly | Q7: 45383
A9: S.No | B9: Employee ID | C9: Name of Workman | D9: Period Details | G9: Actuals Details | O9: Earnings Details | Z9: Deductions Details (Indicate nature) | AG9: Payment Details | AJ9: Overtime Details | AM9: Advance Details
D10: Total No.of Days in the month | E10: Total No.of Days Payble | F10: Monthly CTC | G10: Monthly rate of wages/ piece rate | H10: Basic | I10: D.A. | J10: HRA | K10: CONVEYANCE | L10: Medical Allowance | M10: Bonus | N10: Special Allowance | O10: Basic | P10: D.A. | Q10: HRA | R10: CONVEYANCE | S10: Medical Allowance | T10: Bonus | U10: Special Allowance | V10: Earned Gross | W10: Overtime Amount | X10: TOTAL AMOUNT | Y10: EPF Basic Wages | Z10: ESI | AA10: EPF | AB10: PT | AC10: TDS | AD10: ADV | AE10: MED | AF10: TOTAL DED | AG10: Net Amount paid | AH10: Time and Date of Payment | AI10: Place of Payment | AJ10: Overtime Dates | AK10: Overtime Hours | AL10: Total Overtime Hours | AM10: Total Advance | AN10: Advance Date | AO10: No.of EMI | AP10: Amouunt of EMI | AQ10: Start | AR10: End | AS10: Status
A11: 1 | B11: ='Employee Database'!I11 -> GR001 | C11: ='Employee Database'!J11 -> GOLLAMANDA SUDEEP KUMAR | D11: 30 | E11: ='Attendance Data'!AN11 -> 30 | G11: 10000 | H11: =G11*60% -> 6000 | I11: 0 | J11: =(G11-H11) -> 4000 | K11: 0 | L11: 0 | M11: 0 | N11: 0 | O11: =H11/D11*E11 -> 6000 | P11: =I11/D11*E11 -> 0 | Q11: =J11/D11*E11 -> 4000 | R11: =K11/D11*E11 -> 0 | S11: =L11/D11*E11 -> 0 | T11: =M11/D11*E11 -> 0 | U11: =N11/D11*E11 -> 0 | V11: =O11+P11+Q11+R11+S11+U11 -> 10000 | W11: =G11/240*AL11*2 -> 1166.6667 | X11: =V11+W11 -> 11166.667 | Y11: =MIN((V11-Q11),15000) -> 6000 | Z11: =IF(G11<=21000,0.75%*X11,0) -> 83.75 | AA11: =MIN(Y11,15000)*12% -> 720 | AB11: =IF(X11>20000,200,IF(X11>15000,150,0)) -> 0 | AC11: 1500 | AD11: =AP11 -> 2000 | AE11: 500 | AF11: =Z11+AA11+AB11+AC11+AD11+AE11 -> 4803.75 | AG11: =X11-AF11 -> 6362.9167 | AH11: 07.05.2024 | AI11: ONLINE | AJ11: 2,5,10,27 | AK11: 4,2,3,5 | AL11: =4+2+3+5 -> 14 | AM11: 10000 | AN11: 01.09.2020 | AO11: 5 | AP11: =AM11/AO11 -> 2000 | AQ11: 44075 | AR11: 44197 | AS11: Pending
A12: 2 | B12: ='Employee Database'!I12 -> GR002 | C12: ='Employee Database'!J12 -> GOLLAMANDA PRAVEEN KUMAR | D12: 30 | E12: ='Attendance Data'!AN12 -> 30 | G12: 25000 | H12: =G12*60% -> 15000 | I12: 0 | J12: =(G12-H12) -> 10000 | K12: 0 | L12: 0 | M12: 0 | N12: 0 | O12: =H12/D12*E12 -> 15000 | P12: =I12/D12*E12 -> 0 | Q12: =J12/D12*E12 -> 10000 | R12: =K12/D12*E12 -> 0 | S12: =L12/D12*E12 -> 0 | T12: =M12/D12*E12 -> 0 | U12: =N12/D12*E12 -> 0 | V12: =O12+P12+Q12+R12+S12+U12 -> 25000 | W12: =G12/240*AL12*2 -> 2916.6667 | X12: =V12+W12 -> 27916.667 | Y12: =MIN((V12-Q12),15000) -> 15000 | Z12: =IF(G12<=21000,0.75%*X12,0) -> 0 | AA12: =MIN(Y12,15000)*12% -> 1800 | AB12: =IF(X12>20000,200,IF(X12>15000,150,0)) -> 200 | AC12: 1500 | AD12: =AP12 -> 5000 | AE12: 500 | AF12: =Z12+AA12+AB12+AC12+AD12+AE12 -> 9000 | AG12: =X12-AF12 -> 18916.667 | AH12: 07.05.2024 | AI12: ONLINE | AJ12: 2,5,10,27 | AK12: 4,2,3,5 | AL12: =4+2+3+5 -> 14 | AM12: 25000 | AN12: 01.09.2020 | AO12: 5 | AP12: =AM12/AO12 -> 5000 | AQ12: 44075 | AR12: 44197 | AS12: Pending
A13: 3
A14: 4
A15: 5
A16: 6
A17: 7
A18: 8
A19: 9
A20: 10
A21: 11
A22: 12
A23: 13
A24: 14
... A30: 20

Sheet Attendance Data
A1: MUSTER ROLL STATEMENT
A3: Name and address of Employer: | P3: Spruce IT Private Limited
P4: #Shop No.7,II Floor,Sy.No. 30/Part,Street No.8,Habsiguda,Hyderabad-07
A5: Nature and location of work: | P5: IT Support Services & Hyderabad
A7: Wage period: Monthly | P7: 45383
A9: S.No | B9: Employee ID | C9: Name of Workman | D9: ATTENDANCE | AO9: Leave details
D10: 1 | E10: 2 | F10: 3 | G10: 4 | H10: 5 | I10: 6 | J10: 7 | K10: 8 | L10: 9 | M10: 10 | N10: 11 | O10: 12 | P10: 13 | Q10: 14 | R10: 15 | S10: 16 | T10: 17 | U10: 18 | V10: 19 | W10: 20 | X10: 21 | Y10: 22 | Z10: 23 | AA10: 24 | AB10: 25 | AC10: 26 | AD10: 27 | AE10: 28 | AF10: 29 | AG10: 30 | AH10: 31 | AI10: W.D. | AJ10: W.O. | AK10: H | AL10: C.O. | AM10: EL | AN10: Remarks | AO10: Opening Leave Balance | AP10: No.Eligible Leaves added in the month | AQ10: Leaves taken in the month | AR10: Closing Leave Balance
A11: 1 | B11: ='Employee Database'!I11 -> GR001 | C11: ='Employee Database'!J11 -> GOLLAMANDA SUDEEP KUMAR | D11: P | E11: P | F11: P | G11: WO | H11: WO | I11: P | J11: P | K11: P | L11: P | M11: P | N11: WO | O11: WO | P11: P | Q11: P | R11: H | S11: P | T11: P | U11: WO | V11: WO | W11: P | X11: P | Y11: P | Z11: P | AA11: P | AB11: WO | AC11: WO | AD11: P | AE11: P | AF11: P | AG11: P | AI11: =COUNTIF(D11:AH11,"P") -> 21 | AJ11: =COUNTIF(E11:AI11,"WO") -> 8 | AK11: =COUNTIF(F11:AJ11,"H") -> 1 | AL11: =COUNTIF(G11:AK11,"CO") -> 0 | AM11: =COUNTIF(H11:AL11,"EL") -> 0 | AN11: =AI11+AJ11+AK11+AL11+AM11 -> 30 | AO11: 0 | AP11: 1.5 | AQ11: 0 | AR11: =(AO11+AP11)-AQ11 -> 1.5
A12: 2 | B12: ='Employee Database'!I12 -> GR002 | C12: ='Employee Database'!J12 -> GOLLAMANDA PRAVEEN KUMAR | D12: P | E12: P | F12: P | G12: WO | H12: WO | I12: P | J12: P | K12: P | L12: P | M12: P | N12: WO | O12: WO | P12: P | Q12: P | R12: H | S12: P | T12: P | U12: WO | V12: WO | W12: P | X12: P | Y12: P | Z12: P | AA12: P | AB12: WO | AC12: WO | AD12: P | AE12: P | AF12: P | AG12: P | AI12: =COUNTIF(D12:AH12,"P") -> 21 | AJ12: =COUNTIF(E12:AI12,"WO") -> 8 | AK12: =COUNTIF(F12:AJ12,"H") -> 1 | AL12: =COUNTIF(G12:AK12,"CO") -> 0 | AM12: =COUNTIF(H12:AL12,"EL") -> 0 | AN12: =AI12+AJ12+AK12+AL12+AM12 -> 30 | AO12: 0 | AP12: 1.5 | AQ12: =AM12 -> 0 | AR12: =(AO12+AP12)-AQ12 -> 1.5
A13: 3
A14: 4
A15: 5
A16: 6
A17: 7
A18: 8
A19: 9
A20: 10
A21: 11
A22: 12
A23: 13
A24: 14
... A30: 20
