Workbook

Sheet HYD SEZ-APRIL -22WM Reg
A1: FORM - XIII REGISTER OF WORKMEN EMPLOYED BY CONTRACTOR
A2: (Vide Rule 75 of Contract Labour (Regulation and Abolition) Central/Telangana/A.P. Rules 1971)
A3: Name and address of Contractor: | F3: Burgeon IT Services Pvt.Ltd. | J3: Name and address of Establishemnt in/under which contract is carried on: | K3: Burgeon IT Services Pvt.Ltd.
F4: Siri Mansion LIGB 436 Dr.A S Rao Nagar,Hyderabad | K4: Siri Mansion LIGB 436 Dr.A S Rao Nagar,Hyderabad
A5: Nature and location of work: | F5: IT SUPPORTIVE SERVICES & HYDERABAD SEZ
A7: Wage period: Monthly | J7: Name and address of Principal Employer: | K7: INFOSYS LTD.HYDERABAD-STP
K8: Sy.No 210,Manikonda Village,Serilingampally Mandal,RR District,TS
A11: Serial No. in the Register of Workmen | B11: Name of Workman | C11: Age | D11: Sex | E11: Father's /Husband Name | F11: Designation / Nature of Work Done | G11: Permanent Address | H11: Local Address | I11: Date of Commencement of Employment | J11: Signature or thumb impression of Workman | K11: Date of termination of Employment | L11: Reasons for termination | M11: Remarks
A13: 13 | B13: Sameer Sheikh | C13: 02.10.1986 | D13: Male | E13: Mahaboob Shaikh | F13: TECHNICAL CONSULTATNT | G13: Room No.4,Kalbhor nagar,Opp: Ansari White ,Chinchwada , | H13: Pocharam,Ghatkesaer,Hyderabad,TS | I13: 16.04.2018 | K13: 43205 | L13: Resigned
A14: 14 | B14: Satish Makena | C14: 05.08.1979 | D14: Male | E14: M N Parthrudu | F14: TECHNICAL CONSULTATNT | G14: Door No.58-18-28/1, Near Ravindra Bharat School,N A D Kotla Road,Vizag 530027 | H14: S R T# 573,3rd Floor,Sanath nagar,Hyderabad,TS | I14: 01.06.2018 | K14: 43676 | L14: Resigned
A15: 15 | B15: SANDEEP CHARY BANALA | C15: 04.03.1991 | D15: Male | E15: RAMACHARI | F15: TECHNICAL CONSULTATNT | G15: #12-1-105/46, Sreenivasa nagar colony,bandlaguda,hyderabad,TS | H15: #12-1-105/46, Sreenivasa nagar colony,Bandlaguda,HYD,TS | I15: 25.06.2018 | K15: 30.6.2019 | L15: Resigned
A16: 16 | B16: Venkatarami reddy Naga | C16: 19.01.1986 | D16: Male | E16: Ramana Reddy | F16: TECHNICAL CONSULTATNT | G16: 10-31, Chemuduru Street, Badvel, Caddapah, Ap 516227 | H16: 8-3-136, Pallebalayya Nilayam, Yousufguda, Hyderabad 500045 | I16: 43276 | K16: 43371 | L16: Resigned
A17: 17 | B17: Burra Rajkumar vishal kumar | C17: 19.01.1986 | D17: Male | E17: B RAJKUMAR | F17: TECHNICAL CONSULTATNT | G17: Plot No 13, Kasthuri Cooperative Housing Society,Secunderabad | H17: Plot No 13, Kasthuri Cooperative Housing Society,Old Bowenpally,Secunderabad,TS | I17: 43290 | K17: 43734 | L17: Resigned
A18: 18 | B18: Benjamine Lee | C18: 19.10.1980 | D18: Male | E18: RICHARD LEE | F18: TECHNICAL CONSULTATNT | G18: #509, Tower G,PBEL City,Old Bowenpally,Peeramchervu,Rajendra nagar Mandal,Hyderabad | H18: #509, Tower G,PBEL City,Peeramchervu,Rajendra nagar Mandal, | I18: 43291 | K18: 43602 | L18: Resigned
A19: 19 | B19: DHARANIPARAGADA KEERTHI KIRIT | C19: 27.04.1987 | D19: Male | E19: SESHAGIRI RAO | F19: TECHNICAL CONSULTATNT | G19: #8-3-1020/1, Plot No 25,Srinagar Colony,Yella reddy guda,hyderabad | H19: #8-3-1020/1, Plot No 25,Srinagar Colony,Yella reddy guda,Hyderabad ,TS | I19: 43292 | K19: 43738 | L19: Resigned
A20: 20 | B20: Sreejith Nair | C20: 02.06.1991 | D20: Male | E20: SREEDHARAN | F20: TECHNICAL CONSULTATNT | G20: B-803,Raheja vistas,Road No.12,IDA nacharam,hyderabad | H20: B-803,Raheja vistas,Road No.12,IDA Nacharam,Hyderabad | I20: 43313 | K20: 43738 | L20: Resigned
A21: 21 | B21: S BHARADWAJ KOLLURU | C21: 01.08.1985 | D21: Male | E21: KAMESHWARA SHARMA | F21: TECHNICAL CONSULTATNT | G21: #4-110/24,Plot No.6 BNR Enclave,Nagaram,RR | H21: #4-110/24,Plot No.6 BNR Enclave,Nagaram,HYDEARAD,TS | I21: 43313 | K21: 43637 | L21: Resigned
A22: 22 | B22: Mamidala Rakesh Reddy | C22: 25.02.1987 | D22: Male | E22: RAVINDRA REDDY | F22: TECHNICAL CONSULTATNT | G22: #10-4-183, Road No.3 Dharmapuri Colony,SAROOR NAGAR,HYDERABAD | H22: Plot No.130, H.No 12-1-256/133,Road No.5,Krushinagar Colony,Bandlaguda,HYDEARAD,TS | I22: 43319 | K22: 43665 | L22: Resigned
A23: 23 | B23: Allwyn Bangera | C23: 7.9.1987 | D23: Male | E23: Prabhakar | F23: TECHNICAL CONSULTATNT | G23: Flat No 32077, Janapriya Apts, Attapur, Hyderabad | H23: A-403, Jigar Apartments, Yogidham, Kalyan | I23: 43321 | K23: 43434 | L23: Resigned
A24: 24 | B24: Nandan Sujati | C24: 08.11.1985 | D24: Male | E24: ASHWANI SUJATI | F24: TECHNICAL CONSULTATNT | G24: 37,Suncity I ,ROPAR,PUNJAB,1400001 | H24: GE-Block -A Jain Shrikar Auroville,Near N-Convention centre,HYDEARAAD,TS | I24: 43326 | K24: 43665 | L24: Resigned
A25: 25 | B25: AMIT MOHAN | C25: 09.09.1985 | D25: Male | E25: BIJAY KUMAR MALLIK | F25: TECHNICAL CONSULTATNT | G25: L N Nagar,Mujafar pur,BIHAR,843116 | H25: #407, Gerbera Bhanu Township,Miyapur,Hyderabad,TS | I25: 43271 | K25: 43677 | L25: Resigned
A26: 26 | B26: Bharath Dommaraju | C26: 01.07.1978 | D26: Male | E26: CHENCHURAJU DOMMARAJU | F26: TECHNICAL CONSULTATNT | G26: H No 505, 2nd Floor 1st Main,5th east,NGEF kasthuri nagar,bangalore | H26: Flat no 201,Sri nilayam appartments,Street No.7 Patrikanagar Madhapur,HYD,TS | I26: 43362 | K26: 43494 | L26: Resigned
A27: 27 | B27: Ritesh Solomon | C27: 10.09.1985 | D27: Male | E27: NADHAN SOLOMON | F27: TECHNICAL CONSULTATNT | G27: 134/67, Chaklal Mohammad,NAINI,ALAHABAD | H27: Room 402,H No 1-57/93, Rajiv nagar,Gachibowli,HYD,TS | I27: 43346 | K27: 43738 | L27: Resigned
... A32: 33 | B32: Prakruthi K Murthy | C32: 28.05.1994 | D32: Female | E32: KRISHNA MURTHY | F32: TECHNICAL CONSULTATNT | G32: #24/6, Sree rama Mandir road,Basavanna gudi,bongalore,karnataka560004 | H32: #1204, Raheja vistas Road no.12 ,IDA Nacharam,HYD,TS | I32: 43416 | K32: 43714 | L32: Resigned
A33: 34 | B33: Arun Kohli8 | C33: 22.4.1984 | D33: Male | E33: Kewal Kohli | F33: TECHNICAL CONSULTATNT | G33: Gk pride Apts, Flat No 304, Block 6, Balaji Nagar road, Yapral, Secunderabad -87 | H33: Flat nO 505,5th Floor, khanamet village, GHMC serilingampally, Rangareddy, Hyderabad | I33: 7.1-2019 | K33: 43714 | L33: Resigned
A34: 35 | B34: Sravan Kumar Mupparaju | C34: 10.05.1991 | D34: Male | E34: RAMBABU | F34: TECHNICAL CONSULTATNT | G34: #8-5 Vishnalayam Street | H34: HIG-27, Krishna Nilayam,KPHB Colony,HYD,TS | I34: 43493 | K34: 43646 | L34: Resigned
A35: 36 | B35: Vidyasagar Rao Annamaneni | C35: 13.08.1984 | D35: Male | E35: SUDHAKAR RAO | F35: TECHNICAL CONSULTATNT | G35: #2-35,Narayanapur | H35: Plot No. 1064&1065, Flat No.203,Sai Kuteer Appts.,Pragathinagar,Kukatpally,Hyderabad | I35: 43503 | K35: 43553 | L35: Resigned
A36: 37 | B36: Nagarjuna Sriramoju | C36: 19.12.1990 | D36: Male | E36: Sathyanarayana Sriramoju | F36: TECHNICAL CONSULTATNT | G36: 9-4-582,Sapthagiri Colony,Karimnagar,5050001 | H36: EWS, 767&768, Road No : 3,KPHB Colony, Hyderabad,TS | I36: 43619 | J36: STP Branch | K36: 44035 | L36: Resigned
A37: 38 | B37: Gopi Bollu | C37: 13.06.1982 | D37: Male | E37: YADAIAH YADHAV | F37: SERVICE DELIEVARY SPECIALIST | G37: #10-3-365/5 Michael Mansion 1st Phase,edan colony,bidar ,,karnataka | H37: #1-9-318,Shakuntha nivas Flat No 402,Vidyanagar,HYDERABAD,TS | I37: 43647 | L37: Resigned
A38: 39 | B38: Bharath Varma P | C38: 15.07.1994 | D38: Male | E38: Trinath Raju | F38: Technical consultant | G38: D No 3-141, Elampod,anakoderu post West godavari 534208 | H38: plot no 432, Road No 14/6, Vasanth Nagar, KPHB, Hyderabad, Telangana | I38: 43801
A39: 40 | B39: Prashanth Inti | C39: 11-06-1990 | D39: Male | E39: TVS suryanarayana | F39: SALESFORCE DEVOLOPERS | G39: 18-175/1, road number: 4, Hanmanupet, Malkajagiri,Hyderabad-500047 | H39: 18-175/1, road number: 4, Hanmanupet, Malkajagiri,Hyderabad-500047 | I39: 10-12-2019
A40: 41 | B40: kaja Venkat Ragavendra | C40: 26-05-1990 | D40: Male | E40: Kaja Suresh Babu | F40: SR.Application Consultant | G40: Kidambi Residency, Flat no 6, Agraharam, Guntur, 522003 | H40: Reddy's Avenue, Road no 28, HNO 59, Nizampet, Hyderabad 500090 | I40: 03-02-2020 | Q40: 1
A41: 42 | B41: Ramu Yetukuri | C41: 05-10-1992 | D41: Male | E41: Yetukuri Ravi | F41: SALESFORCE CONSULTANT | G41: H.NO : 2-19,Kotapadu Village,Raghunadhapalem(M), Khammam,507182 | H41: SaiBaba Hostel, roomno: 501, Near :Infosys, Pocharam ,Hyderabad, 500088 | I41: 24-02-2020 | K41: 27-01-2020 | L41: Resigned
A42: 43 | B42: Srinivas Marukurthi | C42: 06-07-1980 | D42: Male | E42: VEERRAJU | F42: Technical conusltant | G42: DOOR-NO: 2-226,RICE MILL STREET ,DUPPALAPUDI VILLAGE, ANPARTHI MANDAL,EAST GODAVARI DISTRICT,AP | H42: FLAT-NO: 102,SHRIKA & SRIDHA TERA ENCLAVE,SRI RAM NAGAR COLONY,BESIDE GOWTHAMI MODEL SCHOOL,MANIKONDA,HYD,TS | I42: 24-02-2020 | K42: 30-4-2020 | L42: Resigned
A43: 44 | B43: Devanand Jorige | C43: 27/12/1995 | D43: Male | E43: Chinnamurthi | F43: Mainframe Scheduler | G43: #24-222 AVR COLONY VELPUR,THANUKU.MND,WEST GODHAVARI,AP | H43: MIG-II 253,3RD FLOUR,KPHP 9TH PHASE,HYD | I43: 02-03-2020 | K43: 15-1-2020 | L43: Resigned
A44: 45 | B44: Fareeda Tarannum | C44: 23/05/1979 | D44: Female | E44: shaidd noor ahmed | F44: Qlikviev Devoloper | G44: Flot no.501,AR rahim opportment,taramount colony.tollychouk hyderabad | H44: flot no.501,AR rahim opportment,taramount colony.tollychouk hyderabad | I44: 08-04-2020 | K44: 30-2-2021 | L44: Resigned
A45: 46 | B45: Pulipati Kaushik | C45: 08-05-1994 | D45: Male | E45: Venkataramana | F45: Dynamic CRM Devoloper | G45: #3-29-10/A,krishnanagar 3rd lane,guntur.AP | H45: 303,3rd flour,vamshireddy recidancy,youshafguda checkposr hyderabad | I45: 22-04-2020 | K45: 08-04-2020 | L45: Resigned
A46: 47 | B46: JAHNVI SINGH | C46: 13/03/1993 | D46: Female | E46: Jitendra Bahadur singh | F46: Team Lead | G46: HNo. 177, Shanti Nagar, Bharuhana, Mirzapur, 231001, UP | H46: 1372, Arun Vihar,Sector 37, Noida,201301 | I46: 06-05-2020 | K46: 31-5-2020 | L46: Resigned
A47: 48 | B47: Saikumar Ramisetty | C47: 03-12-1994 | D47: Male | E47: Anjaneyulu R | F47: BI Developer | G47: D.NO: 2-250-A-3-1-15, Raja Nagar, N G Palle, Madanapalle, Chittoor(Dist), ANDHRA PRADESH-517325 | H47: Flat# 319, MVV Ozone, Midhilapuri Vuda Colony, P.M Palem, Visakhapatnam, ANDHRA PRADESH-530041. | I47: 11-05-2020 | K47: 11-9-2020 | L47: Resigned
A48: 49 | B48: Gurram Gayathri | C48: 15-06-1992 | D48: Female | E48: Gurrram Naga Prasad | F48: Software Developer | G48: Plot no-307,2nd floor,201,Roadno-3,Gokul plots,Near vasanth nagar,KPHB Colony 9th phase,Telangana,500085 | H48: Plot no-307,2nd floor,201,Roadno-3,Gokul plots,Near vasanth nagar,KPHB Colony 9th phase,Telangana,500085 | I48: 13-05-2020 | K48: 30-6-2020 | L48: Resigned
A49: 50 | B49: Rachamallla sravankumar | C49: 26-03-1991 | D49: Male | E49: Bhaskar Rao | F49: DataStage Admin | G49: 25/7/451, vengalraonagar c-block dargamitta nellore, pin-524004 | H49: fifth floor, A block road number 8, Parvath Nagar, thulasi Nagar, Borabanda, Hyderabad, Telangana,500018 | I49: 29-06-2020 | K49: 28-10-2020 | L49: Resigned
A50: 51 | B50: Ayyappa Kopparapu | C50: 13/09/1993 | D50: Male | E50: Srinivasarao Kopparapu | F50: Senior Software Engineer | G50: 11-14-7/5, Old samithi office rd,near sannidhi function hall,Ramireddypet,Narasaraopet -522601 | H50: 1-114/4, sri Karthik Nilayam,prashant nagar, police battalion rd, kondapur, Hyderabad | I50: 22-07-2020 | K50: 10-02-2022 | L50: Resigned
A51: 52 | B51: Gunjan Suthar | C51: 01-08-1992 | D51: Female | E51: Sanjaykumar Dinkarray Suthar | F51: Technical consultant | G51: 2, Panchvati Society, Nr Bus stand, B/H Prasutigruh, Halol-389350 | H51: 2, Panchvati Society, Nr Bus stand, B/H Prasutigruh, Halol-390350 | I51: 29-07-2020 | K51: 31-12-2020 | L51: Resigned
A52: 53 | B52: Anji Babu Yedla | C52: 08-02-1990 | D52: Male | E52: Ananda Raju | F52: SENIOR DATABASE ADMIN | G52: 401, HIG 136, Sheshadri towers, 5th phase, KPHB colony | H52: 401, HIG 136, Sheshadri towers, 5th phase, KPHB colony | I52: 10-08-2020 | K52: 29/07/2020 | L52: Resigned
A53: 54 | B53: Susmitha Arepalli | C53: 16/09/1992 | D53: Male | E53: Prasanta panda | F53: Application Consultant | G53: Ananya womens hostel, H.NO 1-9-98/60,Plot No.60,Jaihind Enclave OPP Dena Bank Lane, Madhpur, Hyerabad | H53: Bhabinipur, gobinda bihar 6th lane,Ganjam,Odisha,761001 | I53: 19-08-2020 | K53: 31-3-2021 | L53: Resigned
A54: 55 | B54: KAMINI RAGHUNATH REDDY | C54: 05.02.1992 | D54: Male | E54: Kamini Venkatarami Reddy | G54: 1/93 , Sanagala Guduru, Putluru (M), Anantapur (D), Andhra pradesh, 515411 | H54: 1/93 , Sanagala Guduru, Putluru (M), Anantapur (D), Andhra pradesh, 515411 | I54: 07-09-2020 | K54: 30-3-2021 | L54: Resigned
A55: 56 | B55: NAGUBANDI SAITEJA | C55: 29-04-1991 | D55: Male | E55: N.srinivasa Rao | F55: Software engineer | G55: H.No-6-133/1,V.M.Banzara,Penuballi(M),Khammam(d)PIN-507302,Telangana | H55: H.No-6-133/1,V.M.Banzara,Penuballi(M),Khammam(d)PIN-507302,Telangana | I55: 25-09-2020 | K55: 31-3-2021 | L55: Resigned
A56: 57 | B56: NAKKA NAGARAJ GOUD | C56: 01-08-1984 | D56: Male | E56: Amarender Goud | F56: Technical Lead | G56: h .no 1-69,village vendikole,mandal pulkal dist:sangareddy pin:502273 | H56: flot no 403,narra raguramaiah towers, opp:saibaba temple,RingRoad,padmanagar phase-2,quthbullapur chintal 500054 | I56: 01-10-2020 | K56: 8-1-2021 | L56: Resigned
A57: 58 | B57: Veerapandi V | C57: 08-09-1981 | D57: Male | E57: Veerakalai | F57: Senior Unix administrator | G57: 290, vallalar Cross street, BB Kulam, Madhurai North, Madurai, Tamil nadu, 625002 | H57: 290, vallalar Cross street, BB Kulam, Madhurai North, Madurai, Tamil nadu, 625002 | I57: 19-10-2020 | K57: 11-12-2020 | L57: Resigned
A58: 59 | B58: POSUBABU GUDLA | C58: 13/06/1990 | D58: Male | E58: Subbarao Gudla | F58: Senior Administrator | G58: s/o subbarao,gudimula post ,sakhinetipalli mandal ,East godavari dist pin 533251 | H58: c/o hanumantha rao,NSL colony phase no 2 ,Ashok nagar,near BHEL Hyderabad | I58: 28-10-2020 | K58: 12-5-2021 | L58: Resigned
A59: 60 | B59: KasiViswanath Paliru | C59: 25-06-1988 | D59: Male | E59: Paliru Karunakar | F59: Senior Consultant | G59: F10, B Block, Mana callista, Bellandur Main Road, Bellandur, Bangalore, Karnataka -560103 | H59: F10, B Block, Mana callista, Bellandur Main Road, Bellandur, Bangalore, Karnataka -560103 | I59: 12-11-2020 | K59: 8-1-2021 | L59: Resigned
A60: 61 | B60: Veeran Matmari | C60: 31-08-1980 | D60: Male | E60: Laxman Goud | F60: AD & SME Lead | G60: 10-3, Plot No 6 and 6/1, flat no 301, Brighton Residency, Tukaram Gate Main road, East Maredpally, Hyderabad, Telangana 500026 | H60: 10-3, Plot No 6 and 6/1, flat no 301, Brighton Residency, Tukaram Gate Main road, East Maredpally, Hyderabad, Telangana 500026 | I60: 12-11-2020 | K60: 30-7-2021 | L60: Resigned
A61: 62 | B61: GAUTAM NAGARAJAN | C61: 06-06-1981 | D61: Male | E61: A. P. Nagarajan | F61: Technical SME | G61: 44/B, State Bank Nagar North, Chinna Chettipalayam, Lakkapuram Pudur, Erode - 638002 | H61: 44/B, State Bank Nagar North, Chinna Chettipalayam, Lakkapuram Pudur, Erode - 638002 | I61: 23-11-2020 | K61: 3-2-2021 | L61: Resigned
A62: 63 | B62: Chaitanya Lakshmikanth .M | C62: 08-08-1987 | D62: Male | E62: M. NAGESWARA RAO | F62: Oracle apps DBA consultant | G62: 24-34-850, Rambageecha, ramangar, prakasam, ap-523001 | H62: 24-34-850, Rambageecha, ramangar, prakasam, ap-523001 | I62: 01-02-2021
A63: 64 | B63: Ajay Reddy | C63: 28/9/1989 | D63: Male | E63: VASUDEVAREDDY GARLAPATI | F63: SAP Senior BODS analyst | G63: Lingala village, Penpahad Mandal, Suryapet District, Pin:508201 | H63: Lingala village, Penpahad Mandal, Suryapet District, Pin:508201 | I63: 22-02-2021
A64: 65 | B64: Rajesh Kumar Kurra | C64: 29-11-1983 | D64: Male | E64: Kurra Lavanya | F64: Azure Consultant | G64: 5-5-33/25B,Vignanpuri Colony,kukatpally,Balanagar,500072 | H64: 4-28,Jammulapalem,Guntur Dist,Bapatla Post,522113 | I64: 04-03-2021 | K64: 04-03-2021 | L64: Resigned
A65: 66 | B65: Reenulatha Chevuri | C65: 20.02.1992 | D65: Female | E65: Jonnalagadda Victor Paul | F65: MSBI | G65: Flat no: 302, 3rd floor, Srinivasa Nilayam, Silicon Town, Doddanagamangala, Electronic city phase 2, Bangalore- 100 | H65: #202, 10th cross, manjunatha nagar, marathalli, bangalore- 37 | I65: 08-03-2021 | K65: 8th March 2021 | L65: Resigned
A66: 67 | B66: MIRZA IRSHAD BEGUM | C66: 25-10-1990 | D66: Female | E66: Mirza Ghouse Baig | F66: ServiceNow Developer | G66: H no 1-6-212/65/15 M.C.H COLONY west parsigutta | H66: H no 1-6-212/65/15 M.C.H COLONY west parsigutta | I66: 18-03-2021 | K66: 30-6-2021 | L66: Resigned
A67: 68 | B67: VeerendraBabu Galam | C67: 15-02-1992 | D67: Male | E67: Gopal Rao | F67: Senior Test Engineer | G67: 1-66, Lakshmipuram Village, Kallur mandal, Khammam Dist, Telangana 507209 | H67: 1-66, Lakshmipuram Village, Kallur mandal, Khammam Dist, Telangana 507209 | I67: 18-03-2021 | Q67: 2
A68: 69 | B68: Tammineni VenuGopal Naidu | C68: 12-10-1994 | D68: Male | E68: Tammineni VenkataRamana | F68: SQL DBA | G68: N.kotthapalli(v), Yadiki(M),Anantapur(D),Ao,515408 | H68: N.kotthapalli(v), Yadiki(M),Anantapur(D),Ao,515408 | I68: 30-03-2021 | K68: 30-4-2021 | L68: Resigned
A69: 70 | B69: Sreenivas Gampa | C69: 05.05.1985 | D69: Male | E69: G Venkataramana | F69: backup administrator | G69: Dno. 2/105, veerappagaripalli, kurly reddyvapalli post, talupula mandal, anantapuram district, ap-515581 | H69: Dno. 2/105, veerappagaripalli, kurly reddyvapalli post, talupula mandal, anantapuram district, ap-515581 | I69: 22-03-2021 | K69: 26-8-2021 | L69: Resigned
A70: 71 | B70: Ramesh Baira | C70: 18-06-1989 | D70: Male | E70: Myaka Lavanya | F70: Google Cloud Engineer | G70: 1-8-518/242/9.NBT Nagar, Patigadda, Secunderbad,500016 | H70: 1-8-518/242/9.NBT Nagar, Patigadda, Secunderbad,500016 | I70: 27-04-2021 | K70: 28-02-2022 | L70: Resigned
A71: 72 | B71: Arunkumar Sikharam | C71: 22-06-1995 | D71: Male | E71: Sikharam Venkateswara Rao | F71: GCP Consultant | G71: 1/54 , Sopirala , Chinnaganjam , Prakasam Dist , Andhra Pradesh | H71: 1/54 , Sopirala , Chinnaganjam , Prakasam Dist , Andhra Pradesh | I71: 29-04-2021 | K71: 31-5-2021 | L71: Resigned
A72: 73 | B72: Ramakrishna Bandari | C72: 11-09-1992 | D72: MALE | E72: NARSIMHA BANDARU | F72: DevOps Developer | G72: Satyadev Gents Pg, 3rd cross, Kamadenu Layout,B.Narayanapura, | H72: Satyadev Gents Pg, 3rd cross, Kamadenu Layout,B.Narayanapura, | I72: 03-05-2021 | K72: 5-8-2021 | L72: Resigned
A73: 74 | B73: RAMALAKSHMAIAH | C73: 04-05-1988 | D73: MALE | E73: SUBBAIAH | F73: Technical Lead | G73: Mahadevpura,560048. | H73: Mahadevpura,560048. | I73: 03-05-2021 | L73: Resigned
A74: 75 | B74: RUKNUDEEN S | C74: 30-01-1988 | D74: MALE | E74: SIRBUDIN T | F74: Technology Consultant | G74: 5 - 2 -46/7, P T R Colony, Uthamapalayam, Theni District , Tamilnadu - 625533. | H74: 5 - 2 -46/7, P T R Colony, Uthamapalayam, Theni District , Tamilnadu - 625533. | I74: 14-05-2021 | Q74: 3
A75: 76 | B75: Ravindra bathoji | C75: 01-01-1985 | D75: MALE | E75: BUCHAIAH | F75: MSSQL DBA | G75: H.No:18-8-306/7/A,Maruthi Nagar,Lalithabagh, HUPPUGUDA:500053. | H75: H.No:18-8-306/7/A,Maruthi Nagar,Lalithabagh, HUPPUGUDA:500053. | I75: 24-05-2021
A76: 77 | B76: SrikanthReddy ChinthiReddy | C76: 14-02-1989 | D76: MALE | E76: THIRUPATHI REDDY CHINTHIREDDY | F76: Technology Analyst | G76: H:No:1-29/14/6/1, pochampally (vill),manakondur(mdl),Karimnagar(Dist).-505505.. | H76: H:No:1-29/14/6/1, pochampally (vill),manakondur(mdl),Karimnagar(Dist).-505505.. | I76: 28-05-2021
A77: 78 | B77: SATHISH AKULA | C77: 21-06-2021 | D77: MALE | E77: Yadiah | F77: SQL DATABASE ADMINISTRATOR | G77: 6-76, Devaruppula mandal, jangaon, Telangana 500013 | H77: 6-76, Devaruppula mandal, jangaon, Telangana 500013 | I77: 21-06-2021 | K77: 31-8-2021 | L77: Resigned
A78: 79 | B78: Vikram Sunchu | C78: 22-06-2021 | D78: MALE | E78: Chandramouli | F78: CyberArk Consultant | G78: 3-117/31/a, Srinivas nagar, Mulkanorr, Bheemadevarapally, Karimnagar Dist 505471 Telangana | H78: 3-117/31/a, Srinivas nagar, Mulkanorr, Bheemadevarapally, Karimnagar Dist 505471 Telangana | I78: 22-06-2021
A79: 80 | B79: Srikanth Thota | C79: 17-12-1981 | D79: MALE | E79: Vasudha thota | F79: PMO Manager | G79: Plot No 779,Defence colony Sainikpuri Secunderabad 500094 | H79: Plot No 779,Defence colony Sainikpuri Secunderabad 500094 | I79: 01-07-2021 | Q79: 4
A80: 81 | B80: Shekhar Panchal | C80: 02-12-1993 | D80: MALE | E80: Naresh Kumar Panchal | F80: Sr. Network Security Engineer | G80: V.P.O. ANANDPURI, DIST- BANSWARA, RAJASTHAN-327021 | H80: V.P.O. ANANDPURI, DIST- BANSWARA, RAJASTHAN-327021 | I80: 11-07-2021 | Q80: 5
A81: 82 | B81: Saibabu Mandapuri | C81: 07-08-1985 | D81: MALE | E81: Venkateswarlu | F81: Splunk Admin | G81: H.N0:1-129, Kachanapally P/V, Gundala Mandal, Bhadradri kothagudem Dist | H81: H.N0:1-129, Kachanapally P/V, Gundala Mandal, Bhadradri kothagudem Dist | I81: 12-07-2021
A82: 83 | B82: Gangadhar Yarabham | C82: 07-01-1982 | D82: MALE | E82: Yarabham Savaraiah | F82: Senior Specialist | G82: Flat.No:P1, MVGK Vaishnavy Residency, Kondapur-500084 | H82: Flat.No:P1, MVGK Vaishnavy Residency, Kondapur-500084 | I82: 23-08-2021 | Q82: 6
A83: 84 | B83: Suresh Babu Putta Lakshmi | C83: 16-01-1978 | D83: Male | E83: Narayana Putta | F83: SYSTEM ADMINISTRATOR | G83: No 1 E,2nd street,2nd floor,satiya nagar,vivek nagar main road,chennai,Tiruvallur,Tamilnadu 600099 | H83: No 1 E,2nd street,2nd floor,satiya nagar,vivek nagar main road,chennai,Tiruvallur,Tamilnadu 600099 | I83: 05-10-2021
A84: 85 | B84: Sandeep Kumar Gupta | C84: 01-06-1991 | D84: Male | E84: Laxman gupta | F84: Senior Infrastructure Support Engineer | G84: E 111, Ace City Police Chowki, Sector-1, Bishrak, Greater Noida West, Yatharth Hospital, Noida, 201306 | H84: E 111, Ace City Police Chowki, Sector-1, Bishrak, Greater Noida West, Yatharth Hospital, Noida, 201306 | I84: 25-10-2021
A85: 86 | B85: Sasidhar reddy Nagired | C85: 15-07-1984 | D85: Male | E85: Venkata Radhava Reddy | F85: SR. CONSULTANT | G85: Sri kolanu,A.S Pet,Nellor District,Andhra Pradesh | H85: Sri kolanu,A.S Pet,Nellor District,Andhra Pradesh | I85: 08-11-2021
A86: 87 | B86: Praveen Kumar Beesabat | C86: 01-06-1992 | D86: Male | E86: Swamulu | F86: SENIOR STORAGE ADMINISTRATOR | G86: Nagayalanka,Krishna District,Andhra pradesh 521120 | H86: Nagayalanka,Krishna District,Andhra pradesh 521120 | I86: 16-11-2021
A87: 88 | B87: Veeran Matmari | C87: 31-08-1980 | D87: Male | E87: Laxman Goud | F87: AD SME & Lead | G87: 10-3, Plot No 6 and 6/1, flat no 301, Brighton Residency, Tukaram Gate Main road, East Maredpally, Hyderabad, Telangana 500026 | H87: 10-3, Plot No 6 and 6/1, flat no 301, Brighton Residency, Tukaram Gate Main road, East Maredpally, Hyderabad, Telangana 500026 | I87: 12-11-2020
A88: 89 | B88: Nikhila Kaveri | C88: 09/10/1994 | D88: FEMALE | E88: Sreehari | F88: TECHNICAL SOLUTION CONSULTANT | G88: 5-6-98/37, Sriharivasam, Behind Dal Factory, Lakshmipuram, Hindupur, AP 515201 | H88: 5-6-98/37, Sriharivasam, Behind Dal Factory, Lakshmipuram, Hindupur, AP 515201 | I88: 29/11/2021 | Q88: 7
A89: 90 | B89: Thaposh Ghosh | C89: 12/05/1987 | D89: Male | E89: CH Divya Vani | F89: Incident Governance Manager | G89: Mayflower Grande, Block-D,D003, Mallapur,Hyderabad | H89: Mayflower Grande, Block-D,D003, Mallapur,Hyderabad | I89: 03/01/2022 | Q89: 8
A90: 91 | B90: Nagashree Narayan | C90: 05/05/1981 | D90: Male | E90: KANTHA KAMBAIAH LAKSHMI | F90: Technical Lead | G90: Flat Number: 1302, Building: I-2 (Manchester), Puranik City, Ghodbunder Road, Thane West, Thane, Maharastra Pin Code: 400615 | H90: 2nd Floor, Number 24, 1st Cross, 1st Main, Behind Fortune Central Park Apartment, Anand Layout, Kodigehalli, Bangalore North, PO: Chikkabettahalli. District: Bangaluru, Pin Code: 560097 | I90: 10/01/2022 | Q90: 9
A91: 92 | B91: ROOPINI CHIYYARAPU | C91: 08-07-1996 | D91: FEMALE | E91: C.ChandraReddy | F91: Service Now Developer | G91: Abbinaidi palli(v),L.G palli(p),Settigunta,Rly Kodur(m),Kadapa(dist),516101. | H91: plot:31,H.no:12-2-54/1,j.p nagar,moosapet,Bharat Nagar,Hyderabad,500018. | I91: 18/02/2022 | Q91: 10
A92: 93 | B92: D.Santhoshi | C92: 19-05-1995 | D92: FEMALE | E92: Srinivasu | F92: SAP Basis Consultant | G92: 6-56, Nekkantivari street, alamuru East godavari Dist | H92: 6-56, Nekkantivari street, alamuru East godavari Dist | I92: 23/02/2022 | Q92: 11
A93: 94 | B93: Bharath | C93: 30-10-1996 | D93: Male | E93: Mani ram | F93: SAP Basis Consultant | G93: village - Bagpur, post. office. - Mohna, Teh & Distt. Palwal, (Haryana) pin code - 121004 | H93: village - Bagpur, post. office. - Mohna, Teh & Distt. Palwal, (Haryana) pin code - 121004 | I93: 23/02/2022 | Q93: 12
A94: 95 | B94: NEERUDU SAI KUMAR | C94: 04-08-1993 | D94: Male | E94: UMA | F94: SAP Basis Consultant | G94: H NO 5-4-46, Seetharam Street, Maripeda bangla, Maripeda, Mahabubabad 506315 | H94: H NO 5-4-46, Seetharam Street, Maripeda bangla, Maripeda, Mahabubabad 506315 | I94: 23/02/2022 | Q94: 13
A95: 96 | B95: Ramineni Abhilash | C95: 28-08-1997 | D95: Male | E95: Bhulokarao | F95: SAP Basis Consultant | G95: H No 18-626, Flat no 206, Raghavendra Towers, Ashok Nagar, Miryalaguda, | H95: H NO 3-12-92/12, Flat No 202, Saimaruthi Residency, Rock town colony,near Gare function hall, Hyderabad | I95: 23/02/2022 | Q95: 14
A96: 97 | B96: SRILATHA | C96: 03-01-1992 | D96: FEMALE | E96: Anjaneya Reddy | F96: Data Engineer | G96: 2-177,Main road,Ramavaram post,Nuzendla mandal,Guntur 522660 | H96: 2-177,Main road,Ramavaram post,Nuzendla mandal,Guntur 522660 | I96: 01-03-2022 | Q96: 15
A97: 98 | B97: SURESH Kumar KOLA | C97: 08-09-1989 | D97: Male | E97: BHAVANI KOLA | F97: SOFTWARE ENGINEER | G97: H No 2-4-123/1/5/F/3,Street No1,seven hills colony,Uppal,Hyderabad 500039 | H97: H No 2-4-123/1/5/F/3,Street No1,seven hills colony,Uppal,Hyderabad 500039 | I97: 17-03-2022 | Q97: 16
A98: 99 | B98: ANILKUMAR MUMMANA | C98: 02-08-1985 | D98: Male | E98: MUMMANA VENKATESWARLU | F98: Sr Developer technical lead | G98: G2,subhashini manson,road no 20, alkapur township,manikonda,Hyderabad 500089 | H98: G2,subhashini manson,road no 20, alkapur township,manikonda,Hyderabad 500089 | I98: 28-03-2022 | Q98: 17
A99: 100 | B99: Ravi Gande | C99: 01-06-1982 | D99: Male | E99: Narsimhulu | F99: JAVA DEVELOPER | G99: 14-1-90/434,60ft road,Gayatri nagar,Telangana,Hyderabad 500018 | H99: 14-1-90/434,60ft road,Gayatri nagar,Telangana,Hyderabad 500018 | I99: 28-03-2022 | Q99: 18
... A102: 103 | B102: SADHAM HUSSAIN | C102: 16-04-1991 | D102: Male | E102: Shahul Hameed | F102: Security Administrator | G102: 10/8,Amman pagoda lane,7 Hills,Chennai,Tamilnadu 600001 | H102: 10/8,Amman pagoda lane,7 Hills,Chennai,Tamilnadu 600001 | I102: 25-04-2022 | Q102: 21

Sheet 04-22-Master
A3: FORM - XIII REGISTER OF WORKMEN EMPLOYED BY CONTRACTOR
B4: (Vide Rule 75 of Contract Labour (Regulation and Abolition) Central/Telangana/A.P. Rules 1971)
A5: Name and address of Contractor: | F5: Burgeon IT Services Pvt.Ltd. | V5: Name and address of Establishemnt in/ under which contract is carried on: | AJ5: =F5 -> Burgeon IT Services Pvt.Ltd.
F6: Siri Mansion LIGB 436 Dr.A S Rao Nagar,Hyderabad | AJ6: =F6 -> Siri Mansion LIGB 436 Dr.A S Rao Nagar,Hyderabad
A8: Nature and location of work: | F8: IT SUPPORTIVE SERVICES & HYDERABAD SEZ
A10: Wage period: Monthly | D10: 44652 | AE10: Name and address of Principal Employer: | AJ10: INFOSYS LTD.IL Hyderabad SEZ
AJ11: Sy.No 42,Pocharam Village,Gatkesar Mandal
B13: 1 | C13: 2 | D13: 3 | E13: 4 | F13: 5 | G13: 6 | H13: 7 | I13: 8 | J13: 9 | K13: 10 | L13: 11 | M13: 12 | N13: 13 | O13: 14 | P13: 15 | Q13: 16 | R13: 17 | S13: 18 | T13: 19 | U13: 20 | V13: 21 | W13: 22 | X13: 23 | Y13: 24 | Z13: 25 | AA13: 26 | AB13: 27 | AC13: 28 | AD13: 29 | AE13: 30 | AF13: 31 | AG13: 32 | AH13: 33 | AI13: 34 | AJ13: 35 | AK13: 36 | AL13: 37 | AM13: 38 | AN13: 39 | AO13: 40 | AP13: 41 | AQ13: 42 | AR13: 43 | AS13: 44 | AT13: 45 | AU13: 46
B14: Name of Workman | C14: Age | D14: Sex | E14: Father's /Husband Name | F14: Designation / Nature of Work Done | G14: Permanent Address | H14: Local Address | I14: Date of Commencement of Employment | J14: Signature or thumb impression of Workman | K14: Date of termination of Employment | L14: Reasons for termination | M14: Remarks | N14: EPF Number | O14: ESI Number | P14: Name of Workman | Q14: No.of Days worked | R14: Unit of work done | S14: Monthly rate of wages/ piece rate | T14: Basic wages | U14: Dearness Allowances | V14: Over time | W14: Other cash payments (Nature of payments to be indicated) | X14: HRA | Y14: CONVEYANCE | Z14: MEDICAL ALLOWANCES | AA14: SPECIAL ALLOWNANCES | AB14: Total | AC14: BONUS | AD14: GRATUITY | AE14: LTA/L.E | AF14: ARREAR AMOUNT | AG14: TOTAL AMOUNT | AH14: Deductions, if any, (Indicate nature) | AO14: Net Amount paid | AP14: Time and Date of Payment | AQ14: Place of Payment | AR14: Signature/Thumb Impression of workman | AS14: Initial of Contractor or his representative | AT14: Serial No. in the Register of Workmen
AH15: ESI | AI15: PF | AJ15: PT | AK15: TDS | AL15: MED | AM15: OTHERS | AN15: Total Deductions
A16: BITS-432 | B16: kaja Venkat Ragavendra | C16: 33019 | D16: Male | E16: Kaja Suresh Babu | F16: SR.Application Consultant | G16: Kidambi Residency, Flat no 6, Agraharam, Guntur, 522003 | H16: Reddy's Avenue, Road no 28, HNO 59, Nizampet, Hyderabad 500090 | I16: 43864 | N16: 101308550178 | O16: N/A | P16: =B16 -> kaja Venkat Ragavendra | Q16: =VLOOKUP(A16,'[1]Pay sheet-APRIL- 2022'!$C$4:$AF$140,10,0) -> 30 | R16: N/A | S16: 84913 | T16: =VLOOKUP(A16,'[1]Pay sheet-APRIL- 2022'!$C$4:$AF$140,11,0) -> 50947.8 | U16: 0 | V16: 0 | W16: 0 | X16: =VLOOKUP(A16,'[1]Pay sheet-APRIL- 2022'!$C$4:$AF$140,12,0) -> 20379.12 | Y16: =VLOOKUP(A16,'[1]Pay sheet-APRIL- 2022'!$C$4:$AF$140,13,0) -> 2083 | Z16: =VLOOKUP(A16,'[1]Pay sheet-APRIL- 2022'!$C$4:$AF$140,14,0) -> 2083 | AA16: =VLOOKUP(A16,'[1]Pay sheet-APRIL- 2022'!$C$4:$AF$140,15,0) -> 9533.08 | AB16: =SUM(T16:AA16) -> 85026 | AC16: =VLOOKUP(A16,'[1]Pay sheet-APRIL- 2022'!$C$4:$AF$140,18,0) -> 1554.609 | AD16: =VLOOKUP(A16,'[1]Pay sheet-APRIL- 2022'!$C$4:$AF$140,19,0) -> 2450.5892 | AE16: =VLOOKUP(A16,'[1]Pay sheet-APRIL- 2022'!$C$4:$AF$140,20,0) -> 4245.65 | AF16: 0 | AG16: =AB16+AC16+AD16+AE16+AF16 -> 93276.848 | AH16: 0 | AI16: =VLOOKUP(A16,'[1]Pay sheet-APRIL- 2022'!$C$4:$AF$140,26,0) -> 1800 | AJ16: =VLOOKUP(A16,'[1]Pay sheet-APRIL- 2022'!$C$4:$AF$140,25,0) -> 200 | AK16: =VLOOKUP(A16,'[1]Pay sheet-APRIL- 2022'!$C$4:$AF$140,24,0) -> 0 | AL16: =VLOOKUP(A16,'[1]Pay sheet-APRIL- 2022'!$C$4:$AF$140,27,0) -> 391.78785 | AN16: =AH16+AI16+AJ16+AK16+AL16+AM16 -> 2391.7878 | AO16: =AG16-AN16 -> 90885.06 | AP16: 44686 | AQ16: KMB | AR16: A/C'6812236194 | AT16: 41 | AU16: 1
A17: BITS-528 | B17: VeerendraBabu Galam | C17: 15-02-1992 | D17: Male | E17: Gopal Rao | F17: Senior Test Engineer | G17: 1-66, Lakshmipuram Village, Kallur mandal, Khammam Dist, Telangana 507209 | H17: 1-66, Lakshmipuram Village, Kallur mandal, Khammam Dist, Telangana 507209 | I17: 18-03-2021 | N17: 100916499521 | O17: N/A | P17: =B17 -> VeerendraBabu Galam | Q17: =VLOOKUP(A17,'[1]Pay sheet-APRIL- 2022'!$C$4:$AF$140,10,0) -> 30 | R17: N/A | S17: 66374 | T17: =VLOOKUP(A17,'[1]Pay sheet-APRIL- 2022'!$C$4:$AF$140,11,0) -> 39824.4 | U17: 0 | V17: 0 | W17: 0 | X17: =VLOOKUP(A17,'[1]Pay sheet-APRIL- 2022'!$C$4:$AF$140,12,0) -> 15929.76 | Y17: =VLOOKUP(A17,'[1]Pay sheet-APRIL- 2022'!$C$4:$AF$140,13,0) -> 2083 | Z17: =VLOOKUP(A17,'[1]Pay sheet-APRIL- 2022'!$C$4:$AF$140,14,0) -> 2083 | AA17: =VLOOKUP(A17,'[1]Pay sheet-APRIL- 2022'!$C$4:$AF$140,15,0) -> 6566.84 | AB17: =SUM(T17:AA17) -> 66487 | AC17: =VLOOKUP(A17,'[1]Pay sheet-APRIL- 2022'!$C$4:$AF$140,18,0) -> 1554.609 | AD17: =VLOOKUP(A17,'[1]Pay sheet-APRIL- 2022'!$C$4:$AF$140,19,0) -> 1915.5536 | AE17: =VLOOKUP(A17,'[1]Pay sheet-APRIL- 2022'!$C$4:$AF$140,20,0) -> 3318.7 | AF17: =VLOOKUP(A17,'[2]Pay sheet-MARCH- 2022'!$C$4:$AF$150,22,0) -> 0 | AG17: =AB17+AC17+AD17+AE17+AF17 -> 73275.863 | AH17: 0 | AI17: =VLOOKUP(A17,'[1]Pay sheet-APRIL- 2022'!$C$4:$AF$140,26,0) -> 1800 | AJ17: =VLOOKUP(A17,'[1]Pay sheet-APRIL- 2022'!$C$4:$AF$140,25,0) -> 200 | AK17: =VLOOKUP(A17,'[1]Pay sheet-APRIL- 2022'!$C$4:$AF$140,24,0) -> 0 | AL17: =VLOOKUP(A17,'[1]Pay sheet-APRIL- 2022'!$C$4:$AF$140,27,0) -> 391.78785 | AN17: =AH17+AI17+AJ17+AK17+AL17+AM17 -> 2391.7878 | AO17: =AG17-AN17 -> 70884.075 | AP17: 44686 | AQ17: Standard chartered Bank | AR17: A/C'44511140919 | AT17: 68 | AU17: 2
A18: BITS-568 | B18: RUKNUDEEN S | C18: 32172 | D18: Male | E18: SIRBUDIN.T | F18: Technical consultant | G18: WARD 5-2-46/7,PTR COLONY ,UTHAMAPALAYAM,THENI,TAMILNADU-625533 | H18: WARD 5-2-46/7,PTR COLONY ,UTHAMAPALAYAM,THENI,TAMILNADU-625533 | I18: 44330 | N18: 101695261761 | O18: N/A | P18: =B18 -> RUKNUDEEN S | Q18: =VLOOKUP(A18,'[1]Pay sheet-APRIL- 2022'!$C$4:$AF$140,10,0) -> 30 | R18: N/A | S18: 89547 | T18: =VLOOKUP(A18,'[1]Pay sheet-APRIL- 2022'!$C$4:$AF$140,11,0) -> 53728.2 | U18: 0 | V18: 0 | W18: 0 | X18: =VLOOKUP(A18,'[1]Pay sheet-APRIL- 2022'!$C$4:$AF$140,12,0) -> 21491.28 | Y18: =VLOOKUP(A18,'[1]Pay sheet-APRIL- 2022'!$C$4:$AF$140,13,0) -> 2083 | Z18: =VLOOKUP(A18,'[1]Pay sheet-APRIL- 2022'!$C$4:$AF$140,14,0) -> 2083 | AA18: =VLOOKUP(A18,'[1]Pay sheet-APRIL- 2022'!$C$4:$AF$140,15,0) -> 10274.52 | AB18: =SUM(T18:AA18) -> 89660 | AC18: =VLOOKUP(A18,'[1]Pay sheet-APRIL- 2022'!$C$4:$AF$140,18,0) -> 1554.609 | AD18: =VLOOKUP(A18,'[1]Pay sheet-APRIL- 2022'!$C$4:$AF$140,19,0) -> 2584.3264 | AE18: =VLOOKUP(A18,'[1]Pay sheet-APRIL- 2022'!$C$4:$AF$140,20,0) -> 4477.35 | AF18: =VLOOKUP(A18,'[2]Pay sheet-MARCH- 2022'!$C$4:$AF$150,22,0) -> 0 | AG18: =AB18+AC18+AD18+AE18+AF18 -> 98276.285 | AH18: 0 | AI18: =VLOOKUP(A18,'[1]Pay sheet-APRIL- 2022'!$C$4:$AF$140,26,0) -> 1800 | AJ18: =VLOOKUP(A18,'[1]Pay sheet-APRIL- 2022'!$C$4:$AF$140,25,0) -> 200 | AK18: =VLOOKUP(A18,'[1]Pay sheet-APRIL- 2022'!$C$4:$AF$140,24,0) -> 0 | AL18: =VLOOKUP(A18,'[1]Pay sheet-APRIL- 2022'!$C$4:$AF$140,27,0) -> 391.78785 | AN18: =AH18+AI18+AJ18+AK18+AL18+AM18 -> 2391.7878 | AO18: =AG18-AN18 -> 95884.498 | AP18: 44686 | AQ18: SBI | AR18: 39203094887 | AT18: 75 | AU18: 3
A19: BITS-597 | B19: Srikanth Thota | C19: 29937 | D19: Male | E19: Vasudha thota | F19: PMO Manager | G19: Plot No 779,Defence colony Sainikpuri Secunderabad 500094 | H19: Plot No 779,Defence colony Sainikpuri Secunderabad 500094 | I19: 44378 | J19: OOOO | N19: 100362420499 | O19: N/A | P19: =B19 -> Srikanth Thota | Q19: =VLOOKUP(A19,'[1]Pay sheet-APRIL- 2022'!$C$4:$AF$140,10,0) -> 30 | R19: N/A | S19: 103451 | T19: =VLOOKUP(A19,'[1]Pay sheet-APRIL- 2022'!$C$4:$AF$140,11,0) -> 62070.6 | U19: 0 | V19: 0 | W19: 0 | X19: =VLOOKUP(A19,'[1]Pay sheet-APRIL- 2022'!$C$4:$AF$140,12,0) -> 24828.24 | Y19: =VLOOKUP(A19,'[1]Pay sheet-APRIL- 2022'!$C$4:$AF$140,13,0) -> 2083 | Z19: =VLOOKUP(A19,'[1]Pay sheet-APRIL- 2022'!$C$4:$AF$140,14,0) -> 2083 | AA19: =VLOOKUP(A19,'[1]Pay sheet-APRIL- 2022'!$C$4:$AF$140,15,0) -> 12499.16 | AB19: =SUM(T19:AA19) -> 103564 | AC19: =VLOOKUP(A19,'[1]Pay sheet-APRIL- 2022'!$C$4:$AF$140,18,0) -> 1554.609 | AD19: =VLOOKUP(A19,'[1]Pay sheet-APRIL- 2022'!$C$4:$AF$140,19,0) -> 2985.5959 | AE19: =VLOOKUP(A19,'[1]Pay sheet-APRIL- 2022'!$C$4:$AF$140,20,0) -> 5172.55 | AF19: =VLOOKUP(A19,'[2]Pay sheet-MARCH- 2022'!$C$4:$AF$150,22,0) -> 0 | AG19: =AB19+AC19+AD19+AE19+AF19 -> 113276.75 | AH19: 0 | AI19: =VLOOKUP(A19,'[1]Pay sheet-APRIL- 2022'!$C$4:$AF$140,26,0) -> 1800 | AJ19: =VLOOKUP(A19,'[1]Pay sheet-APRIL- 2022'!$C$4:$AF$140,25,0) -> 200 | AK19: =VLOOKUP(A19,'[1]Pay sheet-APRIL- 2022'!$C$4:$AF$140,24,0) -> 0 | AL19: =VLOOKUP(A19,'[1]Pay sheet-APRIL- 2022'!$C$4:$AF$140,27,0) -> 377 | AN19: =AH19+AI19+AJ19+AK19+AL19+AM19 -> 2377 | AO19: =AG19-AN19 -> 110899.75 | AP19: 44686 | AQ19: ICICI BANK | AR19: 020201513961 | AT19: 80 | AU19: 4
A20: BITS-600 | B20: Shekhar Panchal | C20: 34305 | D20: Male | E20: Naresh Kumar Panchal | F20: Sr. Network Security Engineer | G20: V.P.O. ANANDPURI, DIST- BANSWARA, RAJASTHAN-327021 | H20: V.P.O. ANANDPURI, DIST- BANSWARA, RAJASTHAN-327021 | I20: 44388 | J20: OOOO | N20: 101185605036 | O20: N/A | P20: =B20 -> Shekhar Panchal | Q20: =VLOOKUP(A20,'[1]Pay sheet-APRIL- 2022'!$C$4:$AF$140,10,0) -> 30 | R20: N/A | S20: 66374 | T20: =VLOOKUP(A20,'[1]Pay sheet-APRIL- 2022'!$C$4:$AF$140,11,0) -> 39824.4 | U20: 0 | V20: 0 | W20: 0 | X20: =VLOOKUP(A20,'[1]Pay sheet-APRIL- 2022'!$C$4:$AF$140,12,0) -> 15929.76 | Y20: =VLOOKUP(A20,'[1]Pay sheet-APRIL- 2022'!$C$4:$AF$140,13,0) -> 2083 | Z20: =VLOOKUP(A20,'[1]Pay sheet-APRIL- 2022'!$C$4:$AF$140,14,0) -> 2083 | AA20: =VLOOKUP(A20,'[1]Pay sheet-APRIL- 2022'!$C$4:$AF$140,15,0) -> 6566.84 | AB20: =SUM(T20:AA20) -> 66487 | AC20: =VLOOKUP(A20,'[1]Pay sheet-APRIL- 2022'!$C$4:$AF$140,18,0) -> 1554.609 | AD20: =VLOOKUP(A20,'[1]Pay sheet-APRIL- 2022'!$C$4:$AF$140,19,0) -> 1915.5536 | AE20: =VLOOKUP(A20,'[1]Pay sheet-APRIL- 2022'!$C$4:$AF$140,20,0) -> 3318.7 | AF20: =VLOOKUP(A20,'[2]Pay sheet-MARCH- 2022'!$C$4:$AF$150,22,0) -> 0 | AG20: =AB20+AC20+AD20+AE20+AF20 -> 73275.863 | AH20: 0 | AI20: =VLOOKUP(A20,'[1]Pay sheet-APRIL- 2022'!$C$4:$AF$140,26,0) -> 1800 | AJ20: =VLOOKUP(A20,'[1]Pay sheet-APRIL- 2022'!$C$4:$AF$140,25,0) -> 200 | AK20: =VLOOKUP(A20,'[1]Pay sheet-APRIL- 2022'!$C$4:$AF$140,24,0) -> 0 | AL20: =VLOOKUP(A20,'[1]Pay sheet-APRIL- 2022'!$C$4:$AF$140,27,0) -> 336 | AN20: =AH20+AI20+AJ20+AK20+AL20+AM20 -> 2336 | AO20: =AG20-AN20 -> 70939.863 | AP20: 44686 | AQ20: ICICI BANK | AR20: 346801502975 | AT20: 81 | AU20: 5
A21: BITS-630 | B21: Gangadhar Yarabham | C21: 29958 | D21: Male | E21: Yarabham Savaraiah | F21: Senior Specialist | G21: Flat.No:P1, MVGK Vaishnavy Residency, Kondapur-500084 | H21: H.No:1-112, Thummalur post, Pamulapadu mandal, Kurnool-518401 | I21: 44431 | J21: OOOO | N21: 101348551716 | O21: N/A | P21: =B21 -> Gangadhar Yarabham | Q21: =VLOOKUP(A21,'[1]Pay sheet-APRIL- 2022'!$C$4:$AF$140,10,0) -> 30 | R21: N/A | S21: 84912 | T21: =VLOOKUP(A21,'[1]Pay sheet-APRIL- 2022'!$C$4:$AF$140,11,0) -> 50947.2 | U21: 0 | V21: 0 | W21: 0 | X21: =VLOOKUP(A21,'[1]Pay sheet-APRIL- 2022'!$C$4:$AF$140,12,0) -> 20378.88 | Y21: =VLOOKUP(A21,'[1]Pay sheet-APRIL- 2022'!$C$4:$AF$140,13,0) -> 2083 | Z21: =VLOOKUP(A21,'[1]Pay sheet-APRIL- 2022'!$C$4:$AF$140,14,0) -> 2083 | AA21: =VLOOKUP(A21,'[1]Pay sheet-APRIL- 2022'!$C$4:$AF$140,15,0) -> 9532.92 | AB21: =SUM(T21:AA21) -> 85025 | AC21: =VLOOKUP(A21,'[1]Pay sheet-APRIL- 2022'!$C$4:$AF$140,18,0) -> 1554.609 | AD21: =VLOOKUP(A21,'[1]Pay sheet-APRIL- 2022'!$C$4:$AF$140,19,0) -> 2450.5603 | AE21: =VLOOKUP(A21,'[1]Pay sheet-APRIL- 2022'!$C$4:$AF$140,20,0) -> 4245.6 | AF21: =VLOOKUP(A21,'[2]Pay sheet-MARCH- 2022'!$C$4:$AF$150,22,0) -> 0 | AG21: =AB21+AC21+AD21+AE21+AF21 -> 93275.769 | AH21: 0 | AI21: =VLOOKUP(A21,'[1]Pay sheet-APRIL- 2022'!$C$4:$AF$140,26,0) -> 1800 | AJ21: =VLOOKUP(A21,'[1]Pay sheet-APRIL- 2022'!$C$4:$AF$140,25,0) -> 200 | AK21: =VLOOKUP(A21,'[1]Pay sheet-APRIL- 2022'!$C$4:$AF$140,24,0) -> 0 | AL21: =VLOOKUP(A21,'[1]Pay sheet-APRIL- 2022'!$C$4:$AF$140,27,0) -> 377 | AM21: 0 | AN21: =AH21+AI21+AJ21+AK21+AL21+AM21 -> 2377 | AO21: =AG21-AN21 -> 90898.769 | AP21: 44686 | AQ21: KOTAK BANK | AR21: A/C NUM:0745780762 | AT21: 83 | AU21: 6
A22: BITS-675 | B22: Nikhila Kaveri | C22: 09/10/1994 | D22: FEMALE | E22: Sreehari | F22: TECHNICAL SOLUTION CONSULTANT | G22: 5-6-98/37, Sriharivasam, Behind Dal Factory, Lakshmipuram, Hindupur, AP 515201 | H22: 5-6-98/37, Sriharivasam, Behind Dal Factory, Lakshmipuram, Hindupur, AP 515201 | I22: 44529 | J22: OOOO | N22: 100929123434 | O22: N/A | P22: Nikhila Kaveri | Q22: =VLOOKUP(A22,'[1]Pay sheet-APRIL- 2022'!$C$4:$AF$140,10,0) -> 30 | R22: N/A | S22: 108085 | T22: =VLOOKUP(A22,'[1]Pay sheet-APRIL- 2022'!$C$4:$AF$140,11,0) -> 64851 | U22: 0 | V22: 0 | W22: 0 | X22: =VLOOKUP(A22,'[1]Pay sheet-APRIL- 2022'!$C$4:$AF$140,12,0) -> 25940.4 | Y22: =VLOOKUP(A22,'[1]Pay sheet-APRIL- 2022'!$C$4:$AF$140,13,0) -> 2083 | Z22: =VLOOKUP(A22,'[1]Pay sheet-APRIL- 2022'!$C$4:$AF$140,14,0) -> 2083 | AA22: =VLOOKUP(A22,'[1]Pay sheet-APRIL- 2022'!$C$4:$AF$140,15,0) -> 13240.6 | AB22: =SUM(T22:AA22) -> 108198 | AC22: =VLOOKUP(A22,'[1]Pay sheet-APRIL- 2022'!$C$4:$AF$140,18,0) -> 1554.609 | AD22: =VLOOKUP(A22,'[1]Pay sheet-APRIL- 2022'!$C$4:$AF$140,19,0) -> 3119.3331 | AE22: =VLOOKUP(A22,'[1]Pay sheet-APRIL- 2022'!$C$4:$AF$140,20,0) -> 5404.25 | AF22: =VLOOKUP(A22,'[2]Pay sheet-MARCH- 2022'!$C$4:$AF$150,22,0) -> 0 | AG22: =AB22+AC22+AD22+AE22+AF22 -> 118276.19 | AH22: 0 | AI22: =VLOOKUP(A22,'[1]Pay sheet-APRIL- 2022'!$C$4:$AF$140,26,0) -> 1800 | AJ22: =VLOOKUP(A22,'[1]Pay sheet-APRIL- 2022'!$C$4:$AF$140,25,0) -> 200 | AK22: =VLOOKUP(A22,'[1]Pay sheet-APRIL- 2022'!$C$4:$AF$140,24,0) -> 0 | AL22: =VLOOKUP(A22,'[1]Pay sheet-APRIL- 2022'!$C$4:$AF$140,27,0) -> 252 | AN22: =AH22+AI22+AJ22+AK22+AL22+AM22 -> 2252 | AO22: =AG22-AN22 -> 116024.19 | AP22: 44686 | AQ22: HDFC BANK | AR22: HDFC0002770 | AT22: 89 | AU22: 7
A23: BITS-690 | B23: Thaposh Ghosh | C23: 12/05/1987 | D23: MALE | E23: CH Divya Vani | F23: Incident Governance Manager | G23: Mayflower Grande, Block-D,D003, Mallapur,Hyderabad | H23: Mayflower Grande, Block-D,D003, Mallapur,Hyderabad | I23: 44564 | J23: OOOO | N23: 100605733434 | O23: N/A | P23: Thaposh Ghosh | Q23: =VLOOKUP(A23,'[1]Pay sheet-APRIL- 2022'!$C$4:$AF$140,10,0) -> 30 | R23: N/A | S23: 140526 | T23: =VLOOKUP(A23,'[1]Pay sheet-APRIL- 2022'!$C$4:$AF$140,11,0) -> 84315.6 | U23: 0 | V23: 0 | W23: 0 | X23: =VLOOKUP(A23,'[1]Pay sheet-APRIL- 2022'!$C$4:$AF$140,12,0) -> 33726.24 | Y23: =VLOOKUP(A23,'[1]Pay sheet-APRIL- 2022'!$C$4:$AF$140,13,0) -> 2083 | Z23: =VLOOKUP(A23,'[1]Pay sheet-APRIL- 2022'!$C$4:$AF$140,14,0) -> 2083 | AA23: =VLOOKUP(A23,'[1]Pay sheet-APRIL- 2022'!$C$4:$AF$140,15,0) -> 18431.16 | AB23: =SUM(T23:AA23) -> 140639 | AC23: =VLOOKUP(A23,'[1]Pay sheet-APRIL- 2022'!$C$4:$AF$140,18,0) -> 1554.609 | AD23: =VLOOKUP(A23,'[1]Pay sheet-APRIL- 2022'!$C$4:$AF$140,19,0) -> 4055.5804 | AE23: =VLOOKUP(A23,'[1]Pay sheet-APRIL- 2022'!$C$4:$AF$140,20,0) -> 7026.3 | AF23: =VLOOKUP(A23,'[2]Pay sheet-MARCH- 2022'!$C$4:$AF$150,22,0) -> 0 | AG23: =AB23+AC23+AD23+AE23+AF23 -> 153275.49 | AH23: 0 | AI23: =VLOOKUP(A23,'[1]Pay sheet-APRIL- 2022'!$C$4:$AF$140,26,0) -> 1800 | AJ23: =VLOOKUP(A23,'[1]Pay sheet-APRIL- 2022'!$C$4:$AF$140,25,0) -> 200 | AK23: =VLOOKUP(A23,'[1]Pay sheet-APRIL- 2022'!$C$4:$AF$140,24,0) -> 0 | AL23: =VLOOKUP(A23,'[1]Pay sheet-APRIL- 2022'!$C$4:$AF$140,27,0) -> 283 | AN23: =AH23+AI23+AJ23+AK23+AL23+AM23 -> 2283 | AO23: =AG23-AN23 -> 150992.49 | AP23: 44686 | AQ23: AXIS BANK | AR23: 914010012727732 | AT23: 90 | AU23: 8
A24: BITS-695 | B24: Nagashree Narayan | C24: 05/05/1981 | D24: FEMALE | E24: KANTHA KAMBAIAH LAKSHMI | F24: Technical Lead | G24: Flat Number: 1302, Building: I-2 (Manchester), Puranik City, Ghodbunder Road, Thane West, Thane, Maharastra Pin Code: 400615 | H24: 2nd Floor, Number 24, 1st Cross, 1st Main, Behind Fortune Central Park Apartment, Anand Layout, Kodigehalli, Bangalore North, PO: Chikkabettahalli. District: Bangaluru, Pin Code: 560097 | I24: 44571 | J24: OOOO | N24: 101780502399 | O24: N/A | P24: Nagashree Narayan | Q24: =VLOOKUP(A24,'[1]Pay sheet-APRIL- 2022'!$C$4:$AF$140,10,0) -> 29 | R24: N/A | S24: 98816 | T24: =VLOOKUP(A24,'[1]Pay sheet-APRIL- 2022'!$C$4:$AF$140,11,0) -> 57313.28 | U24: 0 | V24: 0 | W24: 0 | X24: =VLOOKUP(A24,'[1]Pay sheet-APRIL- 2022'!$C$4:$AF$140,12,0) -> 22925.312 | Y24: =VLOOKUP(A24,'[1]Pay sheet-APRIL- 2022'!$C$4:$AF$140,13,0) -> 2014 | Z24: =VLOOKUP(A24,'[1]Pay sheet-APRIL- 2022'!$C$4:$AF$140,14,0) -> 2014 | AA24: =VLOOKUP(A24,'[1]Pay sheet-APRIL- 2022'!$C$4:$AF$140,15,0) -> 11368.541 | AB24: =SUM(T24:AA24) -> 95635.133 | AC24: =VLOOKUP(A24,'[1]Pay sheet-APRIL- 2022'!$C$4:$AF$140,18,0) -> 1554.609 | AD24: =VLOOKUP(A24,'[1]Pay sheet-APRIL- 2022'!$C$4:$AF$140,19,0) -> 2756.7688 | AE24: =VLOOKUP(A24,'[1]Pay sheet-APRIL- 2022'!$C$4:$AF$140,20,0) -> 4776.1067 | AF24: =VLOOKUP(A24,'[2]Pay sheet-MARCH- 2022'!$C$4:$AF$150,22,0) -> 0 | AG24: =AB24+AC24+AD24+AE24+AF24 -> 104722.62 | AH24: 0 | AI24: =VLOOKUP(A24,'[1]Pay sheet-APRIL- 2022'!$C$4:$AF$140,26,0) -> 1800 | AJ24: =VLOOKUP(A24,'[1]Pay sheet-APRIL- 2022'!$C$4:$AF$140,25,0) -> 200 | AK24: =VLOOKUP(A24,'[1]Pay sheet-APRIL- 2022'!$C$4:$AF$140,24,0) -> 0 | AL24: =VLOOKUP(A24,'[1]Pay sheet-APRIL- 2022'!$C$4:$AF$140,27,0) -> 283 | AN24: =AH24+AI24+AJ24+AK24+AL24+AM24 -> 2283 | AO24: =AG24-AN24 -> 102439.62 | AP24: 44686 | AQ24: ICICI BANK | AR24: 098601510169 | AT24: 91 | AU24: 9
A25: BITS-719 | B25: ROOPINI CHIYYARAPU | C25: 35254 | D25: FEMALE | E25: C.ChandraReddy | F25: Service Now Developer | G25: Abbinaidi palli(v),L.G palli(p),Settigunta,Rly Kodur(m),Kadapa(dist),516101. | H25: plot:31,H.no:12-2-54/1,j.p nagar,moosapet,Bharat Nagar,Hyderabad,500018. | I25: 44610 | J25: OOOO | N25: 101792969219 | O25: N/A | P25: ROOPINI CHIYYARAPU | Q25: =VLOOKUP(A25,'[1]Pay sheet-APRIL- 2022'!$C$4:$AF$140,10,0) -> 30 | R25: N/A | S25: 75643 | T25: =VLOOKUP(A25,'[1]Pay sheet-APRIL- 2022'!$C$4:$AF$140,11,0) -> 45385.8 | U25: 0 | V25: 0 | W25: 0 | X25: =VLOOKUP(A25,'[1]Pay sheet-APRIL- 2022'!$C$4:$AF$140,12,0) -> 18154.32 | Y25: =VLOOKUP(A25,'[1]Pay sheet-APRIL- 2022'!$C$4:$AF$140,13,0) -> 2083 | Z25: =VLOOKUP(A25,'[1]Pay sheet-APRIL- 2022'!$C$4:$AF$140,14,0) -> 2083 | AA25: =VLOOKUP(A25,'[1]Pay sheet-APRIL- 2022'!$C$4:$AF$140,15,0) -> 8049.88 | AB25: =SUM(T25:AA25) -> 75756 | AC25: =VLOOKUP(A25,'[1]Pay sheet-APRIL- 2022'!$C$4:$AF$140,18,0) -> 1554.609 | AD25: =VLOOKUP(A25,'[1]Pay sheet-APRIL- 2022'!$C$4:$AF$140,19,0) -> 2183.057 | AE25: =VLOOKUP(A25,'[1]Pay sheet-APRIL- 2022'!$C$4:$AF$140,20,0) -> 3782.15 | AF25: =VLOOKUP(A25,'[2]Pay sheet-MARCH- 2022'!$C$4:$AF$150,22,0) -> 0 | AG25: =AB25+AC25+AD25+AE25+AF25 -> 83275.816 | AH25: 0 | AI25: =VLOOKUP(A25,'[1]Pay sheet-APRIL- 2022'!$C$4:$AF$140,26,0) -> 1800 | AJ25: =VLOOKUP(A25,'[1]Pay sheet-APRIL- 2022'!$C$4:$AF$140,25,0) -> 200 | AK25: =VLOOKUP(A25,'[1]Pay sheet-APRIL- 2022'!$C$4:$AF$140,24,0) -> 0 | AL25: =VLOOKUP(A25,'[1]Pay sheet-APRIL- 2022'!$C$4:$AF$140,27,0) -> 283 | AN25: =AH25+AI25+AJ25+AK25+AL25+AM25 -> 2283 | AO25: =AG25-AN25 -> 80992.816 | AP25: 44686 | AQ25: SBI | AR25: 39504382024 | AT25: 92 | AU25: 10
A26: BITS-723 | B26: D.Santhoshi | C26: 34838 | D26: FEMALE | E26: Srinivasu | F26: SAP Basis Consultant | G26: 6-56, Nekkantivari street, alamuru East godavari Dist | H26: 6-56, Nekkantivari street, alamuru East godavari Dist | I26: 44615 | J26: OOOO | N26: 101284342568 | O26: N/A | P26: D.Santhoshi | Q26: =VLOOKUP(A26,'[1]Pay sheet-APRIL- 2022'!$C$4:$AF$140,10,0) -> 30 | R26: N/A | S26: 38567 | T26: =VLOOKUP(A26,'[1]Pay sheet-APRIL- 2022'!$C$4:$AF$140,11,0) -> 23140.2 | U26: 0 | V26: 0 | W26: 0 | X26: =VLOOKUP(A26,'[1]Pay sheet-APRIL- 2022'!$C$4:$AF$140,12,0) -> 9256.08 | Y26: =VLOOKUP(A26,'[1]Pay sheet-APRIL- 2022'!$C$4:$AF$140,13,0) -> 2083 | Z26: =VLOOKUP(A26,'[1]Pay sheet-APRIL- 2022'!$C$4:$AF$140,14,0) -> 2083 | AA26: =VLOOKUP(A26,'[1]Pay sheet-APRIL- 2022'!$C$4:$AF$140,15,0) -> 2117.72 | AB26: =SUM(T26:AA26) -> 38680 | AC26: =VLOOKUP(A26,'[1]Pay sheet-APRIL- 2022'!$C$4:$AF$140,18,0) -> 1554.609 | AD26: =VLOOKUP(A26,'[1]Pay sheet-APRIL- 2022'!$C$4:$AF$140,19,0) -> 1113.0436 | AE26: =VLOOKUP(A26,'[1]Pay sheet-APRIL- 2022'!$C$4:$AF$140,20,0) -> 1928.35 | AF26: =VLOOKUP(A26,'[2]Pay sheet-MARCH- 2022'!$C$4:$AF$150,22,0) -> 0 | AG26: =AB26+AC26+AD26+AE26+AF26 -> 43276.003 | AH26: 0 | AI26: =VLOOKUP(A26,'[1]Pay sheet-APRIL- 2022'!$C$4:$AF$140,26,0) -> 1800 | AJ26: =VLOOKUP(A26,'[1]Pay sheet-APRIL- 2022'!$C$4:$AF$140,25,0) -> 200 | AK26: =VLOOKUP(A26,'[1]Pay sheet-APRIL- 2022'!$C$4:$AF$140,24,0) -> 0 | AL26: =VLOOKUP(A26,'[1]Pay sheet-APRIL- 2022'!$C$4:$AF$140,27,0) -> 283 | AN26: =AH26+AI26+AJ26+AK26+AL26+AM26 -> 2283 | AO26: =AG26-AN26 -> 40993.003 | AP26: 44686 | AQ26: INDIAN BANK | AR26: 6108665097 | AT26: 93 | AU26: 11
A27: BITS-724 | B27: Bharath Pal | C27: 35368 | D27: Male | E27: Mani ram | F27: SAP Basis Consultant | G27: village - Bagpur, post. office. - Mohna, Teh & Distt. Palwal, (Haryana) pin code - 121004 | H27: village - Bagpur, post. office. - Mohna, Teh & Distt. Palwal, (Haryana) pin code - 121004 | I27: 44615 | J27: OOOO | N27: 101711677279 | O27: N/A | P27: Bharath | Q27: =VLOOKUP(A27,'[1]Pay sheet-APRIL- 2022'!$C$4:$AF$140,10,0) -> 30 | R27: N/A | S27: 24636 | T27: =VLOOKUP(A27,'[1]Pay sheet-APRIL- 2022'!$C$4:$AF$140,11,0) -> 14781.6 | U27: 0 | V27: 0 | W27: 0 | X27: =VLOOKUP(A27,'[1]Pay sheet-APRIL- 2022'!$C$4:$AF$140,12,0) -> 5912.64 | Y27: =VLOOKUP(A27,'[1]Pay sheet-APRIL- 2022'!$C$4:$AF$140,13,0) -> 1500 | Z27: =VLOOKUP(A27,'[1]Pay sheet-APRIL- 2022'!$C$4:$AF$140,14,0) -> 1500 | AA27: =VLOOKUP(A27,'[1]Pay sheet-APRIL- 2022'!$C$4:$AF$140,15,0) -> 1054.76 | AB27: =SUM(T27:AA27) -> 24749 | AC27: =VLOOKUP(A27,'[1]Pay sheet-APRIL- 2022'!$C$4:$AF$140,18,0) -> 1554.609 | AD27: =VLOOKUP(A27,'[1]Pay sheet-APRIL- 2022'!$C$4:$AF$140,19,0) -> 710.99496 | AE27: =VLOOKUP(A27,'[1]Pay sheet-APRIL- 2022'!$C$4:$AF$140,20,0) -> 1231.8 | AF27: =VLOOKUP(A27,'[2]Pay sheet-MARCH- 2022'!$C$4:$AF$150,22,0) -> 0 | AG27: =AB27+AC27+AD27+AE27+AF27 -> 28246.404 | AH27: 0 | AI27: =VLOOKUP(A27,'[1]Pay sheet-APRIL- 2022'!$C$4:$AF$140,26,0) -> 1774 | AJ27: =VLOOKUP(A27,'[1]Pay sheet-APRIL- 2022'!$C$4:$AF$140,25,0) -> 200 | AK27: =VLOOKUP(A27,'[1]Pay sheet-APRIL- 2022'!$C$4:$AF$140,24,0) -> 0 | AL27: =VLOOKUP(A27,'[1]Pay sheet-APRIL- 2022'!$C$4:$AF$140,27,0) -> 283 | AN27: =AH27+AI27+AJ27+AK27+AL27+AM27 -> 2257 | AO27: =AG27-AN27 -> 25989.404 | AP27: 44686 | AQ27: SBI | AR27: 34997967265 | AT27: 94 | AU27: 12
A28: BITS-725 | B28: NEERUDU SAI KUMAR | C28: 34185 | D28: Male | E28: UMA | F28: SAP Basis Consultant | G28: H NO 5-4-46, Seetharam Street, Maripeda bangla, Maripeda, Mahabubabad 506315 | H28: H NO 5-4-46, Seetharam Street, Maripeda bangla, Maripeda, Mahabubabad 506315 | I28: 44615 | J28: OOOO | N28: 101792969242 | O28: N/A | P28: NEERUDU SAI KUMAR | Q28: =VLOOKUP(A28,'[1]Pay sheet-APRIL- 2022'!$C$4:$AF$140,10,0) -> 30 | R28: N/A | S28: 38567 | T28: =VLOOKUP(A28,'[1]Pay sheet-APRIL- 2022'!$C$4:$AF$140,11,0) -> 23140.2 | U28: 0 | V28: 0 | W28: 0 | X28: =VLOOKUP(A28,'[1]Pay sheet-APRIL- 2022'!$C$4:$AF$140,12,0) -> 9256.08 | Y28: =VLOOKUP(A28,'[1]Pay sheet-APRIL- 2022'!$C$4:$AF$140,13,0) -> 2083 | Z28: =VLOOKUP(A28,'[1]Pay sheet-APRIL- 2022'!$C$4:$AF$140,14,0) -> 2083 | AA28: =VLOOKUP(A28,'[1]Pay sheet-APRIL- 2022'!$C$4:$AF$140,15,0) -> 2117.72 | AB28: =SUM(T28:AA28) -> 38680 | AC28: =VLOOKUP(A28,'[1]Pay sheet-APRIL- 2022'!$C$4:$AF$140,18,0) -> 1554.609 | AD28: =VLOOKUP(A28,'[1]Pay sheet-APRIL- 2022'!$C$4:$AF$140,19,0) -> 1113.0436 | AE28: =VLOOKUP(A28,'[1]Pay sheet-APRIL- 2022'!$C$4:$AF$140,20,0) -> 1928.35 | AF28: =VLOOKUP(A28,'[2]Pay sheet-MARCH- 2022'!$C$4:$AF$150,22,0) -> 0 | AG28: =AB28+AC28+AD28+AE28+AF28 -> 43276.003 | AH28: 0 | AI28: =VLOOKUP(A28,'[1]Pay sheet-APRIL- 2022'!$C$4:$AF$140,26,0) -> 1800 | AJ28: =VLOOKUP(A28,'[1]Pay sheet-APRIL- 2022'!$C$4:$AF$140,25,0) -> 200 | AK28: =VLOOKUP(A28,'[1]Pay sheet-APRIL- 2022'!$C$4:$AF$140,24,0) -> 0 | AL28: =VLOOKUP(A28,'[1]Pay sheet-APRIL- 2022'!$C$4:$AF$140,27,0) -> 283 | AN28: =AH28+AI28+AJ28+AK28+AL28+AM28 -> 2283 | AO28: =AG28-AN28 -> 40993.003 | AP28: 44686 | AQ28: HDFC | AR28: 50100450339212 | AT28: 95 | AU28: 13
A29: BITS-726 | B29: Ramineni Abhilash | C29: 35670 | D29: Male | E29: Bhulokarao | F29: SAP Basis Consultant | G29: H No 18-626, Flat no 206, Raghavendra Towers, Ashok Nagar, Miryalaguda, | H29: H NO 3-12-92/12, Flat No 202, Saimaruthi Residency, Rock town colony,near Gare function hall, Hyderabad | I29: 44615 | J29: OOOO | N29: 101793033177 | O29: N/A | P29: Ramineni Abhilash | Q29: =VLOOKUP(A29,'[1]Pay sheet-APRIL- 2022'!$C$4:$AF$140,10,0) -> 30 | R29: N/A | S29: 38567 | T29: =VLOOKUP(A29,'[1]Pay sheet-APRIL- 2022'!$C$4:$AF$140,11,0) -> 23140.2 | U29: 0 | V29: 0 | W29: 0 | X29: =VLOOKUP(A29,'[1]Pay sheet-APRIL- 2022'!$C$4:$AF$140,12,0) -> 9256.08 | Y29: =VLOOKUP(A29,'[1]Pay sheet-APRIL- 2022'!$C$4:$AF$140,13,0) -> 2083 | Z29: =VLOOKUP(A29,'[1]Pay sheet-APRIL- 2022'!$C$4:$AF$140,14,0) -> 2083 | AA29: =VLOOKUP(A29,'[1]Pay sheet-APRIL- 2022'!$C$4:$AF$140,15,0) -> 2117.72 | AB29: =SUM(T29:AA29) -> 38680 | AC29: =VLOOKUP(A29,'[1]Pay sheet-APRIL- 2022'!$C$4:$AF$140,18,0) -> 1554.609 | AD29: =VLOOKUP(A29,'[1]Pay sheet-APRIL- 2022'!$C$4:$AF$140,19,0) -> 1113.0436 | AE29: =VLOOKUP(A29,'[1]Pay sheet-APRIL- 2022'!$C$4:$AF$140,20,0) -> 1928.35 | AF29: =VLOOKUP(A29,'[2]Pay sheet-MARCH- 2022'!$C$4:$AF$150,22,0) -> 0 | AG29: =AB29+AC29+AD29+AE29+AF29 -> 43276.003 | AH29: 0 | AI29: =VLOOKUP(A29,'[1]Pay sheet-APRIL- 2022'!$C$4:$AF$140,26,0) -> 1800 | AJ29: =VLOOKUP(A29,'[1]Pay sheet-APRIL- 2022'!$C$4:$AF$140,25,0) -> 200 | AK29: =VLOOKUP(A29,'[1]Pay sheet-APRIL- 2022'!$C$4:$AF$140,24,0) -> 0 | AL29: =VLOOKUP(A29,'[1]Pay sheet-APRIL- 2022'!$C$4:$AF$140,27,0) -> 283 | AN29: =AH29+AI29+AJ29+AK29+AL29+AM29 -> 2283 | AO29: =AG29-AN29 -> 40993.003 | AP29: 44686 | AQ29: IDBI | AR29: 1169104000110723 | AT29: 96 | AU29: 14
A30: BITS-727 | B30: B SRILATHA | C30: 33606 | D30: FEMALE | E30: Anjaneya Reddy | F30: Data Engineer | G30: 2-177,Main road,Ramavaram post,Nuzendla mandal,Guntur 522660 | H30: 2-177,Main road,Ramavaram post,Nuzendla mandal,Guntur 522660 | I30: 44621 | J30: OOOO | N30: 101194018795 | O30: N/A | P30: B SRILATHA | Q30: =VLOOKUP(A30,'[1]Pay sheet-APRIL- 2022'!$C$4:$AF$140,10,0) -> 30 | R30: N/A | S30: 103450 | T30: =VLOOKUP(A30,'[1]Pay sheet-APRIL- 2022'!$C$4:$AF$140,11,0) -> 62070 | U30: 0 | V30: 0 | W30: 0 | X30: =VLOOKUP(A30,'[1]Pay sheet-APRIL- 2022'!$C$4:$AF$140,12,0) -> 24828 | Y30: =VLOOKUP(A30,'[1]Pay sheet-APRIL- 2022'!$C$4:$AF$140,13,0) -> 2083 | Z30: =VLOOKUP(A30,'[1]Pay sheet-APRIL- 2022'!$C$4:$AF$140,14,0) -> 2083 | AA30: =VLOOKUP(A30,'[1]Pay sheet-APRIL- 2022'!$C$4:$AF$140,15,0) -> 12499 | AB30: =SUM(T30:AA30) -> 103563 | AC30: =VLOOKUP(A30,'[1]Pay sheet-APRIL- 2022'!$C$4:$AF$140,18,0) -> 1554.609 | AD30: =VLOOKUP(A30,'[1]Pay sheet-APRIL- 2022'!$C$4:$AF$140,19,0) -> 2985.567 | AE30: =VLOOKUP(A30,'[1]Pay sheet-APRIL- 2022'!$C$4:$AF$140,20,0) -> 5172.5 | AF30: =VLOOKUP(A30,'[2]Pay sheet-MARCH- 2022'!$C$4:$AF$150,22,0) -> 0 | AG30: =AB30+AC30+AD30+AE30+AF30 -> 113275.68 | AH30: 0 | AI30: =VLOOKUP(A30,'[1]Pay sheet-APRIL- 2022'!$C$4:$AF$140,26,0) -> 1800 | AJ30: =VLOOKUP(A30,'[1]Pay sheet-APRIL- 2022'!$C$4:$AF$140,25,0) -> 200 | AK30: =VLOOKUP(A30,'[1]Pay sheet-APRIL- 2022'!$C$4:$AF$140,24,0) -> 0 | AL30: =VLOOKUP(A30,'[1]Pay sheet-APRIL- 2022'!$C$4:$AF$140,27,0) -> 283 | AN30: =AH30+AI30+AJ30+AK30+AL30+AM30 -> 2283 | AO30: =AG30-AN30 -> 110992.68 | AP30: 44686 | AQ30: SBI | AR30: 33161877369 | AT30: 97 | AU30: 15
A31: BITS-735 | B31: SURESH Kumar KOLA | C31: 08-09-1989 | D31: Male | E31: BHAVANI KOLA | F31: SOFTWARE ENGINEER | G31: H No 2-4-123/1/5/F/3,Street No1,seven hills colony,Uppal,Hyderabad 500039 | H31: H No 2-4-123/1/5/F/3,Street No1,seven hills colony,Uppal,Hyderabad 500039 | I31: 44637 | J31: OOOO | N31: 101739029576 | O31: N/A | P31: SURESH Kumar KOLA | Q31: =VLOOKUP(A31,'[1]Pay sheet-APRIL- 2022'!$C$4:$AF$140,10,0) -> 30 | R31: N/A | S31: 80278 | T31: =VLOOKUP(A31,'[1]Pay sheet-APRIL- 2022'!$C$4:$AF$140,11,0) -> 48166.8 | U31: 0 | V31: 0 | W31: 0 | X31: =VLOOKUP(A31,'[1]Pay sheet-APRIL- 2022'!$C$4:$AF$140,12,0) -> 19266.72 | Y31: =VLOOKUP(A31,'[1]Pay sheet-APRIL- 2022'!$C$4:$AF$140,13,0) -> 2083 | Z31: =VLOOKUP(A31,'[1]Pay sheet-APRIL- 2022'!$C$4:$AF$140,14,0) -> 2083 | AA31: =VLOOKUP(A31,'[1]Pay sheet-APRIL- 2022'!$C$4:$AF$140,15,0) -> 8791.48 | AB31: =SUM(T31:AA31) -> 80391 | AC31: =VLOOKUP(A31,'[1]Pay sheet-APRIL- 2022'!$C$4:$AF$140,18,0) -> 1554.609 | AD31: =VLOOKUP(A31,'[1]Pay sheet-APRIL- 2022'!$C$4:$AF$140,19,0) -> 2316.8231 | AE31: =VLOOKUP(A31,'[1]Pay sheet-APRIL- 2022'!$C$4:$AF$140,20,0) -> 4013.9 | AF31: =VLOOKUP(A31,'[2]Pay sheet-MARCH- 2022'!$C$4:$AF$150,22,0) -> 0 | AG31: =AB31+AC31+AD31+AE31+AF31 -> 88276.332 | AH31: 0 | AI31: =VLOOKUP(A31,'[1]Pay sheet-APRIL- 2022'!$C$4:$AF$140,26,0) -> 1800 | AJ31: =VLOOKUP(A31,'[1]Pay sheet-APRIL- 2022'!$C$4:$AF$140,25,0) -> 200 | AK31: =VLOOKUP(A31,'[1]Pay sheet-APRIL- 2022'!$C$4:$AF$140,24,0) -> 0 | AL31: =VLOOKUP(A31,'[1]Pay sheet-APRIL- 2022'!$C$4:$AF$140,27,0) -> 283 | AN31: =AH31+AI31+AJ31+AK31+AL31+AM31 -> 2283 | AO31: =AG31-AN31 -> 85993.332 | AP31: 44686 | AQ31: BANK OF BARODA | AR31: 83270100000529 | AT31: 98 | AU31: 16
A32: BITS-740 | B32: MUMMANA ANILKUMAR | C32: 31261 | D32: Male | E32: MUMMANA VENKATESWARLU | F32: Sr Developer technical lead | G32: G2,subhashini manson,road no 20, alkapur township,manikonda,Hyderabad 500089 | H32: G2,subhashini manson,road no 20, alkapur township,manikonda,Hyderabad 500089 | I32: 44648 | J32: OOOO | N32: 100084289127 | O32: N/A | P32: ANILKUMAR MUMMANA | Q32: =VLOOKUP(A32,'[1]Pay sheet-APRIL- 2022'!$C$4:$AF$140,10,0) -> 30 | R32: N/A | S32: 131257 | T32: =VLOOKUP(A32,'[1]Pay sheet-APRIL- 2022'!$C$4:$AF$140,11,0) -> 78754.2 | U32: 0 | V32: 0 | W32: 0 | X32: =VLOOKUP(A32,'[1]Pay sheet-APRIL- 2022'!$C$4:$AF$140,12,0) -> 31501.68 | Y32: =VLOOKUP(A32,'[1]Pay sheet-APRIL- 2022'!$C$4:$AF$140,13,0) -> 2083 | Z32: =VLOOKUP(A32,'[1]Pay sheet-APRIL- 2022'!$C$4:$AF$140,14,0) -> 2083 | AA32: =VLOOKUP(A32,'[1]Pay sheet-APRIL- 2022'!$C$4:$AF$140,15,0) -> 16948.12 | AB32: =SUM(T32:AA32) -> 131370 | AC32: =VLOOKUP(A32,'[1]Pay sheet-APRIL- 2022'!$C$4:$AF$140,18,0) -> 1554.609 | AD32: =VLOOKUP(A32,'[1]Pay sheet-APRIL- 2022'!$C$4:$AF$140,19,0) -> 3788.077 | AE32: =VLOOKUP(A32,'[1]Pay sheet-APRIL- 2022'!$C$4:$AF$140,20,0) -> 6562.85 | AF32: =VLOOKUP(A32,'[2]Pay sheet-MARCH- 2022'!$C$4:$AF$150,22,0) -> 0 | AG32: =AB32+AC32+AD32+AE32+AF32 -> 143275.54 | AH32: 0 | AI32: =VLOOKUP(A32,'[1]Pay sheet-APRIL- 2022'!$C$4:$AF$140,26,0) -> 1800 | AJ32: =VLOOKUP(A32,'[1]Pay sheet-APRIL- 2022'!$C$4:$AF$140,25,0) -> 200 | AK32: =VLOOKUP(A32,'[1]Pay sheet-APRIL- 2022'!$C$4:$AF$140,24,0) -> 0 | AL32: =VLOOKUP(A32,'[1]Pay sheet-APRIL- 2022'!$C$4:$AF$140,27,0) -> 283 | AN32: =AH32+AI32+AJ32+AK32+AL32+AM32 -> 2283 | AO32: =AG32-AN32 -> 140992.54 | AP32: 44686 | AQ32: HDFC | AR32: 50100480501513 | AT32: 99 | AU32: 17
A33: BITS-742 | B33: Ravi Gande | C33: 30103 | D33: Male | E33: Narsimhulu | F33: JAVA DEVELOPER | G33: 14-1-90/434,60ft road,Gayatri nagar,Telangana,Hyderabad 500018 | H33: 14-1-90/434,60ft road,Gayatri nagar,Telangana,Hyderabad 500018 | I33: 44648 | J33: OOOO | N33: 100310765422 | O33: N/A | P33: Ravi Gande | Q33: =VLOOKUP(A33,'[1]Pay sheet-APRIL- 2022'!$C$4:$AF$140,10,0) -> 30 | R33: N/A | S33: 68182 | T33: =VLOOKUP(A33,'[1]Pay sheet-APRIL- 2022'!$C$4:$AF$140,11,0) -> 40909.2 | U33: 0 | V33: 0 | W33: 0 | X33: =VLOOKUP(A33,'[1]Pay sheet-APRIL- 2022'!$C$4:$AF$140,12,0) -> 16363.68 | Y33: =VLOOKUP(A33,'[1]Pay sheet-APRIL- 2022'!$C$4:$AF$140,13,0) -> 2083 | Z33: =VLOOKUP(A33,'[1]Pay sheet-APRIL- 2022'!$C$4:$AF$140,14,0) -> 2083 | AA33: =VLOOKUP(A33,'[1]Pay sheet-APRIL- 2022'!$C$4:$AF$140,15,0) -> 6856.12 | AB33: =SUM(T33:AA33) -> 68295 | AC33: =VLOOKUP(A33,'[1]Pay sheet-APRIL- 2022'!$C$4:$AF$140,18,0) -> 1441.609 | AD33: =VLOOKUP(A33,'[1]Pay sheet-APRIL- 2022'!$C$4:$AF$140,19,0) -> 1967.7325 | AE33: =VLOOKUP(A33,'[1]Pay sheet-APRIL- 2022'!$C$4:$AF$140,20,0) -> 3409.1 | AF33: =VLOOKUP(A33,'[2]Pay sheet-MARCH- 2022'!$C$4:$AF$150,22,0) -> 0 | AG33: =AB33+AC33+AD33+AE33+AF33 -> 75113.442 | AH33: 0 | AI33: =VLOOKUP(A33,'[1]Pay sheet-APRIL- 2022'!$C$4:$AF$140,26,0) -> 0 | AJ33: =VLOOKUP(A33,'[1]Pay sheet-APRIL- 2022'!$C$4:$AF$140,25,0) -> 200 | AK33: =VLOOKUP(A33,'[1]Pay sheet-APRIL- 2022'!$C$4:$AF$140,24,0) -> 0 | AL33: =VLOOKUP(A33,'[1]Pay sheet-APRIL- 2022'!$C$4:$AF$140,27,0) -> 0 | AN33: =AH33+AI33+AJ33+AK33+AL33+AM33 -> 200 | AO33: =AG33-AN33 -> 74913.442 | AP33: 44686 | AQ33: ICICI BANK | AR33: 038201510552 | AT33: 100 | AU33: 18
A34: BITS-745 | B34: NarsiReddy Venna | C34: 25-07-1986 | D34: Male | E34: Krishna Reddy | F34: Senior Administrator | G34: Flat No 26B,Street No.1,HUDA colony,Saroor nagar,Near Kothapet signal,Hyderabda TS | H34: Flat No 26B,Street No.1,HUDA colony,Saroor nagar,Near Kothapet signal,Hyderabda TS | I34: 44655 | J34: OOOO | N34: 101322850601 | O34: N/A | P34: NarsiReddy Venna | Q34: =VLOOKUP(A34,'[1]Pay sheet-APRIL- 2022'!$C$4:$AF$140,10,0) -> 27 | S34: 112719 | T34: =VLOOKUP(A34,'[1]Pay sheet-APRIL- 2022'!$C$4:$AF$140,11,0) -> 60868.26 | U34: 0 | V34: 0 | W34: 0 | X34: =VLOOKUP(A34,'[1]Pay sheet-APRIL- 2022'!$C$4:$AF$140,12,0) -> 24347.304 | Y34: =VLOOKUP(A34,'[1]Pay sheet-APRIL- 2022'!$C$4:$AF$140,13,0) -> 1875 | Z34: =VLOOKUP(A34,'[1]Pay sheet-APRIL- 2022'!$C$4:$AF$140,14,0) -> 1875 | AA34: =VLOOKUP(A34,'[1]Pay sheet-APRIL- 2022'!$C$4:$AF$140,15,0) -> 12594.536 | AB34: =SUM(T34:AA34) -> 101560.1 | AC34: =VLOOKUP(A34,'[1]Pay sheet-APRIL- 2022'!$C$4:$AF$140,18,0) -> 1554.609 | AD34: =VLOOKUP(A34,'[1]Pay sheet-APRIL- 2022'!$C$4:$AF$140,19,0) -> 2927.7633 | AE34: =VLOOKUP(A34,'[1]Pay sheet-APRIL- 2022'!$C$4:$AF$140,20,0) -> 5072.355 | AF34: 0 | AG34: =AB34+AC34+AD34+AE34+AF34 -> 111114.83 | AH34: 0 | AI34: =VLOOKUP(A34,'[1]Pay sheet-APRIL- 2022'!$C$4:$AF$140,26,0) -> 1800 | AJ34: =VLOOKUP(A34,'[1]Pay sheet-APRIL- 2022'!$C$4:$AF$140,25,0) -> 200 | AK34: =VLOOKUP(A34,'[1]Pay sheet-APRIL- 2022'!$C$4:$AF$140,24,0) -> 0 | AL34: =VLOOKUP(A34,'[1]Pay sheet-APRIL- 2022'!$C$4:$AF$140,27,0) -> 0 | AN34: =AH34+AI34+AJ34+AK34+AL34+AM34 -> 2000 | AO34: =AG34-AN34 -> 109114.83 | AP34: 44686 | AQ34: CITI Bank | AR34: 5708925554 | AT34: 101 | AU34: 19
A35: BITS-750 | B35: AbdulSaleem Sunkesula | C35: 10-05-1993 | D35: Male | E35: Sunkesula Sowdayya | F35: Technical Consultant | G35: 19/76,Papireddygari palle,Ramapuram,Hasanapuram,Kadapa,AP 516504 | H35: 19/76,Papireddygari palle,Ramapuram,Hasanapuram,Kadapa,AP 516504 | I35: 44671 | J35: OOOO | N35: 101814583013 | O35: N/A | P35: AbdulSaleem Sunkesula | Q35: =VLOOKUP(A35,'[1]Pay sheet-APRIL- 2022'!$C$4:$AF$140,10,0) -> 11 | S35: 75643 | T35: =VLOOKUP(A35,'[1]Pay sheet-APRIL- 2022'!$C$4:$AF$140,11,0) -> 16641.46 | U35: 0 | V35: 0 | W35: 0 | X35: =VLOOKUP(A35,'[1]Pay sheet-APRIL- 2022'!$C$4:$AF$140,12,0) -> 6656.584 | Y35: =VLOOKUP(A35,'[1]Pay sheet-APRIL- 2022'!$C$4:$AF$140,13,0) -> 764 | Z35: =VLOOKUP(A35,'[1]Pay sheet-APRIL- 2022'!$C$4:$AF$140,14,0) -> 764 | AA35: =VLOOKUP(A35,'[1]Pay sheet-APRIL- 2022'!$C$4:$AF$140,15,0) -> 3022.7227 | AB35: =SUM(T35:AA35) -> 27848.767 | AC35: =VLOOKUP(A35,'[1]Pay sheet-APRIL- 2022'!$C$4:$AF$140,18,0) -> 1554.609 | AD35: =VLOOKUP(A35,'[1]Pay sheet-APRIL- 2022'!$C$4:$AF$140,19,0) -> 800.45423 | AE35: =VLOOKUP(A35,'[1]Pay sheet-APRIL- 2022'!$C$4:$AF$140,20,0) -> 1386.7883 | AF35: 0 | AG35: =AB35+AC35+AD35+AE35+AF35 -> 31590.618 | AH35: 0 | AI35: =VLOOKUP(A35,'[1]Pay sheet-APRIL- 2022'!$C$4:$AF$140,26,0) -> 1800 | AJ35: =VLOOKUP(A35,'[1]Pay sheet-APRIL- 2022'!$C$4:$AF$140,25,0) -> 200 | AK35: =VLOOKUP(A35,'[1]Pay sheet-APRIL- 2022'!$C$4:$AF$140,24,0) -> 0 | AL35: =VLOOKUP(A35,'[1]Pay sheet-APRIL- 2022'!$C$4:$AF$140,27,0) -> 0 | AN35: =AH35+AI35+AJ35+AK35+AL35+AM35 -> 2000 | AO35: =AG35-AN35 -> 29590.618 | AP35: 44686 | AQ35: SBI | AR35: 20029285687 | AT35: 102 | AU35: 20
A36: BITS-752 | B36: SADHAM HUSSAIN | C36: 16-04-1991 | D36: Male | E36: Shahul Hameed | F36: Security Administrator | G36: 10/8,Amman pagoda lane,7 Hills,Chennai,Tamilnadu 600001 | H36: 10/8,Amman pagoda lane,7 Hills,Chennai,Tamilnadu 600001 | I36: 44676 | J36: OOOO | N36: 100554328630 | O36: N/A | P36: SADHAMHUSSAIN | Q36: =VLOOKUP(A36,'[1]Pay sheet-APRIL- 2022'!$C$4:$AF$140,10,0) -> 6 | S36: 135892 | T36: =VLOOKUP(A36,'[1]Pay sheet-APRIL- 2022'!$C$4:$AF$140,11,0) -> 16307.04 | U36: 0 | V36: 0 | W36: 0 | X36: =VLOOKUP(A36,'[1]Pay sheet-APRIL- 2022'!$C$4:$AF$140,12,0) -> 6522.816 | Y36: =VLOOKUP(A36,'[1]Pay sheet-APRIL- 2022'!$C$4:$AF$140,13,0) -> 417 | Z36: =VLOOKUP(A36,'[1]Pay sheet-APRIL- 2022'!$C$4:$AF$140,14,0) -> 417 | AA36: =VLOOKUP(A36,'[1]Pay sheet-APRIL- 2022'!$C$4:$AF$140,15,0) -> 3627.544 | AB36: =SUM(T36:AA36) -> 27291.4 | AC36: =VLOOKUP(A36,'[1]Pay sheet-APRIL- 2022'!$C$4:$AF$140,18,0) -> 1554.609 | AD36: =VLOOKUP(A36,'[1]Pay sheet-APRIL- 2022'!$C$4:$AF$140,19,0) -> 784.36862 | AE36: =VLOOKUP(A36,'[1]Pay sheet-APRIL- 2022'!$C$4:$AF$140,20,0) -> 1358.92 | AF36: 0 | AG36: =AB36+AC36+AD36+AE36+AF36 -> 30989.298 | AH36: 0 | AI36: =VLOOKUP(A36,'[1]Pay sheet-APRIL- 2022'!$C$4:$AF$140,26,0) -> 1800 | AJ36: =VLOOKUP(A36,'[1]Pay sheet-APRIL- 2022'!$C$4:$AF$140,25,0) -> 200 | AK36: =VLOOKUP(A36,'[1]Pay sheet-APRIL- 2022'!$C$4:$AF$140,24,0) -> 0 | AL36: =VLOOKUP(A36,'[1]Pay sheet-APRIL- 2022'!$C$4:$AF$140,27,0) -> 0 | AN36: =AH36+AI36+AJ36+AK36+AL36+AM36 -> 2000 | AO36: =AG36-AN36 -> 28989.298 | AP36: 44686 | AQ36: HDFC BANK | AR36: 50100271012409 | AT36: 103 | AU36: 21
X37: =SUM(X16:X36) -> 382850.98 | Y37: =SUM(Y16:Y36) -> 39898 | Z37: =SUM(Z16:Z36) -> 39898 | AA37: =SUM(AA16:AA36) -> 177810.98 | AB37: =SUM(AB16:AB36) -> 1597585.4 | AC37: =SUM(AC16:AC36) -> 32533.789 | AD37: =SUM(AD16:AD36) -> 46037.83 | AE37: =SUM(AE16:AE36) -> 79760.62 | AG37: =SUM(AG16:AG36) -> 1755917.6 | AI37: =SUM(AI16:AI36) -> 35974 | AJ37: =SUM(AJ16:AJ36) -> 4200 | AK37: =SUM(AK16:AK36) -> 0 | AL37: =SUM(AL16:AL36) -> 5347.3635 | AN37: =SUM(AN16:AN36) -> 45521.364 | AO37: =SUM(AO16:AO36) -> 1710396.3
Q38: =SUM(Q16:Q37) -> 583 | T38: =SUM(T16:T37) -> 957127.44
H667: ='04-22-Master'!I259 -> 0

Sheet Eql remon
A1: Form D
A2: (See rule 6)
A4: Register to be maintained by the employer under rule 6 of the Equal Remuneration Rules, 1976
D6: ='04-22-Master'!D10 -> 44652
A8: Name and address of Contractor : | F8: ='04-22-Master'!F5 -> Burgeon IT Services Pvt.Ltd.
A10: Name and address of establishment in/under which contract is carried on : | F10: ='04-22-Master'!AJ5 -> Burgeon IT Services Pvt.Ltd.
F11: ='04-22-Master'!AJ6 -> Siri Mansion LIGB 436 Dr.A S Rao Nagar,Hyderabad
A12: Name and address of Principal Employer : | F12: ='04-22-Master'!AJ10 -> INFOSYS LTD.IL Hyderabad SEZ
F13: ='04-22-Master'!AJ11 -> Sy.No 42,Pocharam Village,Gatkesar Mandal
A14: Total number of men workers employed | C14: =D41 -> 16
A16: Total number of women workers employed | C16: =C41 -> 5
C18: Components of remuneration
A19: Category of workers | B19: Brief Description of work | C19: No of women employed | D19: No. of men employed | E19: Rate or remuneration paid | F19: Basic wage & Dearness Allowance | G19: House Rent allowance | H19: Other allowances | I19: Cash value of concessional supply of essential commodities | J19: Name of the Client | K19: Primary Work Place/ Location
A20: ='04-22-Master'!F16 -> SR.Application Consultant | B20: IT SUPPORTIVE SERVICES | C20: 0 | D20: 1 | E20: ='04-22-Master'!S16 -> 84913 | F20: ='04-22-Master'!T16 -> 50947.8 | G20: ='04-22-Master'!X16 -> 20379.12 | H20: =E20-(F20+G20) -> 13586.08 | I20: 0 | J20: INFOSYS LTD | K20: HYDERABAD
A21: ='04-22-Master'!F17 -> Senior Test Engineer | B21: IT SUPPORTIVE SERVICES | C21: 0 | D21: 1 | E21: ='04-22-Master'!S17 -> 66374 | F21: ='04-22-Master'!T17 -> 39824.4 | G21: ='04-22-Master'!X17 -> 15929.76 | H21: =E21-(F21+G21) -> 10619.84 | I21: 0 | K21: SEZ
A22: ='04-22-Master'!F18 -> Technical consultant | B22: IT SUPPORTIVE SERVICES | C22: 0 | D22: 1 | E22: ='04-22-Master'!S18 -> 89547 | F22: ='04-22-Master'!T18 -> 53728.2 | G22: ='04-22-Master'!X18 -> 21491.28 | H22: =E22-(F22+G22) -> 14327.52 | I22: 0
A23: ='04-22-Master'!F19 -> PMO Manager | B23: IT SUPPORTIVE SERVICES | C23: 0 | D23: 1 | E23: ='04-22-Master'!S19 -> 103451 | F23: ='04-22-Master'!T19 -> 62070.6 | G23: ='04-22-Master'!X19 -> 24828.24 | H23: =E23-(F23+G23) -> 16552.16 | I23: 0
A24: ='04-22-Master'!F20 -> Sr. Network Security Engineer | B24: IT SUPPORTIVE SERVICES | C24: 0 | D24: 1 | E24: ='04-22-Master'!S20 -> 66374 | F24: ='04-22-Master'!T20 -> 39824.4 | G24: ='04-22-Master'!X20 -> 15929.76 | H24: =E24-(F24+G24) -> 10619.84 | I24: 0
A25: ='04-22-Master'!F21 -> Senior Specialist | B25: IT SUPPORTIVE SERVICES | C25: 0 | D25: 1 | E25: ='04-22-Master'!S21 -> 84912 | F25: ='04-22-Master'!T21 -> 50947.2 | G25: ='04-22-Master'!X21 -> 20378.88 | H25: =E25-(F25+G25) -> 13585.92 | I25: 0
A26: ='04-22-Master'!F22 -> TECHNICAL SOLUTION CONSULTANT | B26: IT SUPPORTIVE SERVICES | C26: 1 | D26: 0 | E26: ='04-22-Master'!S22 -> 108085 | F26: ='04-22-Master'!T22 -> 64851 | G26: ='04-22-Master'!X22 -> 25940.4 | H26: =E26-(F26+G26) -> 17293.6 | I26: 0
A27: ='04-22-Master'!F23 -> Incident Governance Manager | B27: IT SUPPORTIVE SERVICES | C27: 0 | D27: 1 | E27: ='04-22-Master'!S23 -> 140526 | F27: ='04-22-Master'!T23 -> 84315.6 | G27: ='04-22-Master'!X23 -> 33726.24 | H27: =E27-(F27+G27) -> 22484.16 | I27: 0
A28: ='04-22-Master'!F24 -> Technical Lead | B28: IT SUPPORTIVE SERVICES | C28: 1 | D28: 0 | E28: ='04-22-Master'!S24 -> 98816 | F28: ='04-22-Master'!T24 -> 57313.28 | G28: ='04-22-Master'!X24 -> 22925.312 | H28: =E28-(F28+G28) -> 18577.408 | I28: 0
A29: ='04-22-Master'!F25 -> Service Now Developer | B29: IT SUPPORTIVE SERVICES | C29: 1 | D29: 0 | E29: ='04-22-Master'!S25 -> 75643 | F29: ='04-22-Master'!T25 -> 45385.8 | G29: ='04-22-Master'!X25 -> 18154.32 | H29: =E29-(F29+G29) -> 12102.88 | I29: 0
A30: ='04-22-Master'!F26 -> SAP Basis Consultant | B30: IT SUPPORTIVE SERVICES | C30: 1 | D30: 0 | E30: ='04-22-Master'!S26 -> 38567 | F30: ='04-22-Master'!T26 -> 23140.2 | G30: ='04-22-Master'!X26 -> 9256.08 | H30: =E30-(F30+G30) -> 6170.72 | I30: 0
A31: ='04-22-Master'!F27 -> SAP Basis Consultant | B31: IT SUPPORTIVE SERVICES | C31: 0 | D31: 1 | E31: ='04-22-Master'!S27 -> 24636 | F31: ='04-22-Master'!T27 -> 14781.6 | G31: ='04-22-Master'!X27 -> 5912.64 | H31: =E31-(F31+G31) -> 3941.76 | I31: 0
A32: ='04-22-Master'!F28 -> SAP Basis Consultant | B32: IT SUPPORTIVE SERVICES | C32: 0 | D32: 1 | E32: ='04-22-Master'!S28 -> 38567 | F32: ='04-22-Master'!T28 -> 23140.2 | G32: ='04-22-Master'!X28 -> 9256.08 | H32: =E32-(F32+G32) -> 6170.72 | I32: 0
A33: ='04-22-Master'!F29 -> SAP Basis Consultant | B33: IT SUPPORTIVE SERVICES | C33: 0 | D33: 1 | E33: ='04-22-Master'!S29 -> 38567 | F33: ='04-22-Master'!T29 -> 23140.2 | G33: ='04-22-Master'!X29 -> 9256.08 | H33: =E33-(F33+G33) -> 6170.72 | I33: 0
... A40: ='04-22-Master'!F36 -> Security Administrator | B40: IT SUPPORTIVE SERVICES | C40: 0 | D40: 1 | E40: ='04-22-Master'!S36 -> 135892 | F40: ='04-22-Master'!T36 -> 16307.04 | G40: ='04-22-Master'!X36 -> 6522.816 | H40: =E40-(F40+G40) -> 113062.14 | I40: 0
C41: =SUM(C20:C40) -> 5 | D41: =SUM(D20:D40) -> 16
I47: Signature of the Contractor with Seal

Sheet 04-22-TMur Roll
A1: FORM - XVI MUSTER ROLL [Vide Rule 78 (1) (P) (i) of ContrPct LPbour (Reg. & Pbolition) CentrPl & TPPngPnP Rules 1971]
A3: NPme Pnd Pddress of ContrPctor: | D3: ='04-22-Master'!F5 -> Burgeon IT Services Pvt.Ltd. | J3: Name and address of Establishemnt in/ under which contract is carried on: | Z3: ='04-22-Master'!AJ5 -> Burgeon IT Services Pvt.Ltd.
D4: ='04-22-Master'!F6 -> Siri Mansion LIGB 436 Dr.A S Rao Nagar,Hyderabad | Z4: ='04-22-Master'!AJ6 -> Siri Mansion LIGB 436 Dr.A S Rao Nagar,Hyderabad
A5: Nature and location of work: | D5: ='[3]HYD-Master-JULY21'!F8 -> IT Support Services & Hyderabad
A6: Wage period: Monthly | D6: ='04-22-Master'!D10 -> 44652 | J6: Name and address of Principal Employer: | Z6: ='04-22-Master'!AJ10 -> INFOSYS LTD.IL Hyderabad SEZ
Z7: ='04-22-Master'!AJ11 -> Sy.No 42,Pocharam Village,Gatkesar Mandal
A10: S.No | B10: Name of Workman | C10: Father's/ Husband's Name | D10: Sex
E11: 1 | F11: 2 | G11: 3 | H11: 4 | I11: 5 | J11: 6 | K11: 7 | L11: 8 | M11: 9 | N11: 10 | O11: 11 | P11: 12 | Q11: 13 | R11: 14 | S11: 15 | T11: 16 | U11: 17 | V11: 18 | W11: 19 | X11: 20 | Y11: 21 | Z11: 22 | AA11: 23 | AB11: 24 | AC11: 25 | AD11: 26 | AE11: 27 | AF11: 28 | AG11: 29 | AH11: 30 | AI11: P Days | AJ11: Remarks
A12: 1 | B12: ='04-22-Master'!B16 -> kaja Venkat Ragavendra | C12: ='04-22-Master'!E16 -> Kaja Suresh Babu | D12: ='04-22-Master'!D16 -> Male | E12: P | F12: WO | G12: WO | H12: P | I12: P | J12: P | K12: P | L12: EL | M12: WO | N12: WO | O12: P | P12: P | Q12: P | R12: P | S12: H | T12: WO | U12: WO | V12: P | W12: P | X12: P | Y12: P | Z12: P | AA12: WO | AB12: WO | AC12: P | AD12: P | AE12: P | AF12: P | AG12: P | AH12: WO | AI12: ='04-22-Master'!Q16 -> 30
A13: 2 | B13: ='04-22-Master'!B17 -> VeerendraBabu Galam | C13: ='04-22-Master'!E17 -> Gopal Rao | D13: ='04-22-Master'!D17 -> Male | E13: P | F13: WO | G13: WO | H13: P | I13: P | J13: P | K13: P | L13: P | M13: WO | N13: WO | O13: EL | P13: P | Q13: P | R13: P | S13: H | T13: WO | U13: WO | V13: P | W13: P | X13: P | Y13: P | Z13: P | AA13: WO | AB13: WO | AC13: P | AD13: P | AE13: P | AF13: P | AG13: P | AH13: WO | AI13: ='04-22-Master'!Q17 -> 30
A14: 3 | B14: ='04-22-Master'!B18 -> RUKNUDEEN S | C14: ='04-22-Master'!E18 -> SIRBUDIN.T | D14: ='04-22-Master'!D18 -> Male | E14: P | F14: WO | G14: WO | H14: P | I14: P | J14: P | K14: P | L14: P | M14: WO | N14: WO | O14: P | P14: P | Q14: P | R14: EL | S14: H | T14: WO | U14: WO | V14: P | W14: P | X14: P | Y14: P | Z14: P | AA14: WO | AB14: WO | AC14: P | AD14: P | AE14: P | AF14: P | AG14: P | AH14: WO | AI14: ='04-22-Master'!Q18 -> 30
A15: 4 | B15: ='04-22-Master'!B19 -> Srikanth Thota | C15: ='04-22-Master'!E19 -> Vasudha thota | D15: ='04-22-Master'!D19 -> Male | E15: P | F15: WO | G15: WO | H15: P | I15: P | J15: P | K15: P | L15: P | M15: WO | N15: WO | O15: P | P15: P | Q15: P | R15: P | S15: H | T15: WO | U15: WO | V15: P | W15: P | X15: P | Y15: P | Z15: P | AA15: WO | AB15: WO | AC15: P | AD15: P | AE15: P | AF15: P | AG15: EL | AH15: WO | AI15: ='04-22-Master'!Q19 -> 30
A16: 5 | B16: ='04-22-Master'!B20 -> Shekhar Panchal | C16: ='04-22-Master'!E20 -> Naresh Kumar Panchal | D16: ='04-22-Master'!D20 -> Male | E16: P | F16: WO | G16: WO | H16: P | I16: P | J16: P | K16: P | L16: P | M16: WO | N16: WO | O16: P | P16: P | Q16: P | R16: P | S16: H | T16: WO | U16: WO | V16: P | W16: P | X16: P | Y16: P | Z16: P | AA16: WO | AB16: WO | AC16: P | AD16: P | AE16: P | AF16: P | AG16: P | AH16: WO | AI16: ='04-22-Master'!Q20 -> 30
A17: 6 | B17: ='04-22-Master'!B21 -> Gangadhar Yarabham | C17: ='04-22-Master'!E21 -> Yarabham Savaraiah | D17: ='04-22-Master'!D21 -> Male | E17: P | F17: WO | G17: WO | H17: P | I17: P | J17: P | K17: P | L17: P | M17: WO | N17: WO | O17: P | P17: P | Q17: P | R17: P | S17: H | T17: WO | U17: WO | V17: P | W17: P | X17: P | Y17: P | Z17: P | AA17: WO | AB17: WO | AC17: P | AD17: P | AE17: P | AF17: P | AG17: P | AH17: WO | AI17: ='04-22-Master'!Q21 -> 30
A18: 7 | B18: ='04-22-Master'!B22 -> Nikhila Kaveri | C18: ='04-22-Master'!E22 -> Sreehari | D18: ='04-22-Master'!D22 -> FEMALE | E18: P | F18: WO | G18: WO | H18: P | I18: P | J18: P | K18: P | L18: P | M18: WO | N18: WO | O18: P | P18: P | Q18: P | R18: P | S18: H | T18: WO | U18: WO | V18: P | W18: P | X18: P | Y18: P | Z18: P | AA18: WO | AB18: WO | AC18: P | AD18: P | AE18: P | AF18: P | AG18: P | AH18: WO | AI18: ='04-22-Master'!Q22 -> 30
A19: 8 | B19: ='04-22-Master'!B23 -> Thaposh Ghosh | C19: ='04-22-Master'!E23 -> CH Divya Vani | D19: ='04-22-Master'!D23 -> MALE | E19: P | F19: WO | G19: WO | H19: P | I19: P | J19: P | K19: P | L19: P | M19: WO | N19: WO | O19: P | P19: P | Q19: P | R19: P | S19: H | T19: WO | U19: WO | V19: P | W19: P | X19: P | Y19: P | Z19: P | AA19: WO | AB19: WO | AC19: P | AD19: P | AE19: P | AF19: P | AG19: P | AH19: WO | AI19: ='04-22-Master'!Q23 -> 30
A20: 9 | B20: ='04-22-Master'!B24 -> Nagashree Narayan | C20: ='04-22-Master'!E24 -> KANTHA KAMBAIAH LAKSHMI | D20: ='04-22-Master'!D24 -> FEMALE | E20: P | F20: WO | G20: WO | H20: P | I20: P | J20: P | K20: P | L20: P | M20: WO | N20: WO | O20: EL | P20: A | Q20: P | R20: P | S20: H | T20: WO | U20: WO | V20: P | W20: P | X20: P | Y20: P | Z20: P | AA20: WO | AB20: WO | AC20: P | AD20: P | AE20: P | AF20: P | AG20: P | AH20: WO | AI20: ='04-22-Master'!Q24 -> 29
A21: 10 | B21: ='04-22-Master'!B25 -> ROOPINI CHIYYARAPU | C21: ='04-22-Master'!E25 -> C.ChandraReddy | D21: ='04-22-Master'!D25 -> FEMALE | E21: P | F21: WO | G21: WO | H21: P | I21: P | J21: P | K21: P | L21: P | M21: WO | N21: WO | O21: P | P21: P | Q21: P | R21: P | S21: H | T21: WO | U21: WO | V21: P | W21: P | X21: P | Y21: P | Z21: P | AA21: WO | AB21: WO | AC21: EL | AD21: P | AE21: P | AF21: P | AG21: P | AH21: WO | AI21: ='04-22-Master'!Q25 -> 30
A22: 11 | B22: ='04-22-Master'!B26 -> D.Santhoshi | C22: ='04-22-Master'!E26 -> Srinivasu | D22: ='04-22-Master'!D26 -> FEMALE | E22: P | F22: WO | G22: WO | H22: P | I22: P | J22: P | K22: P | L22: P | M22: WO | N22: WO | O22: P | P22: P | Q22: P | R22: P | S22: H | T22: WO | U22: WO | V22: P | W22: P | X22: P | Y22: P | Z22: P | AA22: WO | AB22: WO | AC22: P | AD22: P | AE22: P | AF22: P | AG22: P | AH22: WO | AI22: ='04-22-Master'!Q26 -> 30
A23: 12 | B23: ='04-22-Master'!B27 -> Bharath Pal | C23: ='04-22-Master'!E27 -> Mani ram | D23: ='04-22-Master'!D27 -> Male | E23: P | F23: WO | G23: WO | H23: P | I23: P | J23: P | K23: P | L23: P | M23: WO | N23: WO | O23: P | P23: P | Q23: P | R23: P | S23: H | T23: WO | U23: WO | V23: P | W23: P | X23: P | Y23: P | Z23: P | AA23: WO | AB23: WO | AC23: P | AD23: P | AE23: P | AF23: P | AG23: P | AH23: WO | AI23: ='04-22-Master'!Q27 -> 30
... A29: 18 | B29: ='04-22-Master'!B33 -> Ravi Gande | C29: ='04-22-Master'!E33 -> Narsimhulu | D29: ='04-22-Master'!D33 -> Male | E29: P | F29: WO | G29: WO | H29: P | I29: P | J29: P | K29: P | L29: P | M29: WO | N29: WO | O29: P | P29: P | Q29: P | R29: P | S29: H | T29: WO | U29: WO | V29: P | W29: P | X29: P | Y29: P | Z29: P | AA29: WO | AB29: WO | AC29: P | AD29: P | AE29: P | AF29: P | AG29: P | AH29: WO | AI29: ='04-22-Master'!Q33 -> 30
A30: 19 | B30: ='04-22-Master'!B34 -> NarsiReddy Venna | C30: ='04-22-Master'!E34 -> Krishna Reddy | D30: ='04-22-Master'!D34 -> Male | H30: P | I30: P | J30: P | K30: P | L30: P | M30: WO | N30: WO | O30: P | P30: P | Q30: P | R30: P | S30: H | T30: WO | U30: WO | V30: P | W30: P | X30: P | Y30: P | Z30: P | AA30: WO | AB30: WO | AC30: P | AD30: P | AE30: P | AF30: P | AG30: P | AH30: WO | AI30: ='04-22-Master'!Q34 -> 27
A31: 20 | B31: ='04-22-Master'!B35 -> AbdulSaleem Sunkesula | C31: ='04-22-Master'!E35 -> Sunkesula Sowdayya | D31: ='04-22-Master'!D35 -> Male | X31: P | Y31: P | Z31: P | AA31: WO | AB31: WO | AC31: P | AD31: P | AE31: P | AF31: P | AG31: P | AH31: WO | AI31: ='04-22-Master'!Q35 -> 11
A32: 21 | B32: ='04-22-Master'!B36 -> SADHAM HUSSAIN | C32: ='04-22-Master'!E36 -> Shahul Hameed | D32: ='04-22-Master'!D36 -> Male | AC32: P | AD32: P | AE32: P | AF32: P | AG32: P | AH32: WO | AI32: ='04-22-Master'!Q36 -> 6
AI33: =SUM(AI12:AI32) -> 583
J39: Signature of the Contractor with Seal

Sheet Leave Reg
B1: FORM XXV- REGISTER OF LEAVE
B3: [See Rule 29(6)]A.P. Shops & Establishments Rules, 1990
C4: ='04-22-Master'!B16 -> kaja Venkat Ragavendra | I4: ='04-22-Master'!B16 -> kaja Venkat Ragavendra
B6: Registration Number:
I7: Father’s / Husband’s Name:
I8: ='04-22-Master'!E16 -> Kaja Suresh Babu
I9: Date of appointment : | L9: ='04-22-Master'!I16 -> 43864
B10: S.No | C10: Accumalation of Leave | E10: Leave allowed | G10: Balance of Leave Carried Over | H10: Payment of Leave made on | J10: Refusal of Leave | M10: Payment of Leave on Discharge of an employee quitting employment if a admissible | P10: Signature or the Thumb impression of employee on Receipt of Leave Book in Form N
B12: 1 | G12: 6 | J12: 9 | M12: 9 | P12: Impression of
C13: Leave due on | D13: No of Days | E13: From | F13: To | H13: 1st month | I13: 2nd month | J13: Date of Application | K13: Date of Refusal | L13: Amount of Leave refused | M13: Date of Discharge | N13: Date of Amount Paid | O13: Signature or Left hand thumb impression of employee
B15: JAN'22 | C15: 1.5 | D15: 1 | E15: 44575 | F15: 44575 | G15: 18.5 | J15: NO | K15: NO | L15: NO
B16: FEB'22 | C16: 1.5 | D16: 0 | E16: 0 | F16: 0 | G16: =G15+C16-D16 -> 20 | J16: NO | K16: NO | L16: NO
B17: MAR'22 | C17: 1.5 | D17: 0 | E17: 0 | F17: 0 | G17: =G16+C17-D17 -> 21.5 | J17: NO | K17: NO | L17: NO
B18: APRIL'22 | C18: 1.5 | D18: 1 | E18: 44659 | F18: 44659 | G18: =G17+C18-D18 -> 22 | J18: NO | K18: NO | L18: NO | Q18: 1
J46: Signature of the Contractor with Seal
B47: FORM XXV- REGISTER OF LEAVE
B49: [See Rule 29(6)]A.P. Shops & Establishments Rules, 1990
B50: Name of the Establishment: | D50: ='04-22-Master'!F5 -> Burgeon IT Services Pvt.Ltd. | I50: Name of the Employee:
C51: ='04-22-Master'!F6 -> Siri Mansion LIGB 436 Dr.A S Rao Nagar,Hyderabad | I51: ='04-22-Master'!B17 -> VeerendraBabu Galam
B53: Registration Number:
I54: Father’s / Husband’s Name:
I55: ='04-22-Master'!E17 -> Gopal Rao
I56: Date of appointment : | L56: ='04-22-Master'!I17 -> 18-03-2021
B57: S.No | C57: Accumalation of Leave | E57: Leave allowed | G57: Balance of Leave Carried Over | H57: Payment of Leave made on | J57: Refusal of Leave | M57: Payment of Leave on Discharge of an employee quitting employment if a admissible | P57: Signature or the Thumb impression of employee on Receipt of Leave Book in Form N
B59: 1 | G59: 6 | J59: 9 | M59: 9 | P59: Impression of
C60: Leave due on | D60: No of Days | E60: From | F60: To | H60: 1st month | I60: 2nd month | J60: Date of Application | K60: Date of Refusal | L60: Amount of Leave refused | M60: Date of Discharge | N60: Date of Amount Paid | O60: Signature or Left hand thumb impression of employee
B61: JAN'22 | C61: 1.5 | D61: 1 | E61: 44575 | F61: 44575 | G61: 8 | J61: NO | K61: NO | L61: NO
B62: FEB'22 | C62: 1.5 | D62: 1 | E62: 44603 | F62: 44603 | G62: =G61+C62-D62 -> 8.5 | J62: NO | K62: NO | L62: NO
B63: MAR'22 | C63: 1.5 | D63: 1 | E63: 44624 | F63: 44624 | G63: =G62+C63-D63 -> 9 | J63: NO | K63: NO | L63: NO
B64: APRIL'22 | C64: 1.5 | D64: 1 | E64: 44662 | F64: 44662 | G64: =G63+C64-D64 -> 9.5 | J64: NO | K64: NO | L64: NO | Q64: 2
J84: Signature of the Contractor with Seal
B88: FORM XXV- REGISTER OF LEAVE
B90: [See Rule 29(6)]A.P. Shops & Establishments Rules, 1990
B91: Name of the Establishment: | D91: ='04-22-Master'!F5 -> Burgeon IT Services Pvt.Ltd. | I91: Name of the Employee:
C92: ='04-22-Master'!F6 -> Siri Mansion LIGB 436 Dr.A S Rao Nagar,Hyderabad | I92: ='04-22-Master'!B18 -> RUKNUDEEN S
B94: Registration Number:
I95: Father’s / Husband’s Name:
I96: ='04-22-Master'!E18 -> SIRBUDIN.T
I97: Date of appointment : | L97: ='04-22-Master'!I18 -> 44330
B98: S.No | C98: Accumalation of Leave | E98: Leave allowed | G98: Balance of Leave Carried Over | H98: Payment of Leave made on | J98: Refusal of Leave | M98: Payment of Leave on Discharge of an employee quitting employment if a admissible | P98: Signature or the Thumb impression of employee on Receipt of Leave Book in Form N
B100: 1 | G100: 6 | J100: 9 | M100: 9 | P100: Impression of
C101: Leave due on | D101: No of Days | E101: From | F101: To | H101: 1st month | I101: 2nd month | J101: Date of Application | K101: Date of Refusal | L101: Amount of Leave refused | M101: Date of Discharge | N101: Date of Amount Paid | O101: Signature or Left hand thumb impression of employee
B103: JAN'22 | C103: 1.5 | G103: 12 | J103: NO | K103: NO | L103: NO
B104: FEB'22 | C104: 1.5 | D104: 0 | E104: 0 | F104: 0 | G104: =G103+C104-D104 -> 13.5 | J104: NO | K104: NO | L104: NO
B105: MAR'22 | C105: 1.5 | D105: 0 | E105: 0 | F105: 0 | G105: =G104+C105-D105 -> 15 | J105: NO | K105: NO | L105: NO
B106: APRIL'22 | C106: 1.5 | D106: 1 | E106: 44665 | F106: 44665 | G106: =G105+C106-D106 -> 15.5 | J106: NO | K106: NO | L106: NO | Q106: 3
J124: Signature of the Contractor with Seal
B129: FORM XXV- REGISTER OF LEAVE
B131: [See Rule 29(6)]A.P. Shops & Establishments Rules, 1990
B132: Name of the Establishment: | D132: ='04-22-Master'!F5 -> Burgeon IT Services Pvt.Ltd. | I132: Name of the Employee:
C133: ='04-22-Master'!F6 -> Siri Mansion LIGB 436 Dr.A S Rao Nagar,Hyderabad | I133: ='04-22-Master'!B19 -> Srikanth Thota
B135: Registration Number:
I136: Father’s / Husband’s Name:
I137: ='04-22-Master'!E19 -> Vasudha thota
I138: Date of appointment : | L138: ='04-22-Master'!I19 -> 44378
B139: S.No | C139: Accumalation of Leave | E139: Leave allowed | G139: Balance of Leave Carried Over | H139: Payment of Leave made on | J139: Refusal of Leave | M139: Payment of Leave on Discharge of an employee quitting employment if a admissible | P139: Signature or the Thumb impression of employee on Receipt of Leave Book in Form N
B141: 1 | G141: 6 | J141: 9 | M141: 9 | P141: Impression of
C142: Leave due on | D142: No of Days | E142: From | F142: To | H142: 1st month | I142: 2nd month | J142: Date of Application | K142: Date of Refusal | L142: Amount of Leave refused | M142: Date of Discharge | N142: Date of Amount Paid | O142: Signature or Left hand thumb impression of employee
B144: JAN'22 | C144: 1.5 | G144: 3.5 | J144: NO | K144: NO | L144: NO
B145: FEB'22 | C145: 1.5 | D145: 1 | E145: 44596 | F145: 44596 | G145: =G144+C145-D145 -> 4 | J145: NO | K145: NO | L145: NO
B146: MAR'22 | C146: 1.5 | D146: 0 | E146: 0 | F146: 0 | G146: =G145+C146-D146 -> 5.5 | J146: NO | K146: NO | L146: NO
A147: 4 | B147: APRIL'22 | C147: 1.5 | D147: 1 | E147: 44680 | F147: 44680 | G147: =G146+C147-D147 -> 6 | J147: NO | K147: NO | L147: NO | Q147: 4
J165: Signature of the Contractor with Seal
B170: FORM XXV- REGISTER OF LEAVE
B172: [See Rule 29(6)]A.P. Shops & Establishments Rules, 1990
B173: Name of the Establishment: | D173: ='04-22-Master'!F5 -> Burgeon IT Services Pvt.Ltd. | I173: Name of the Employee:
C174: ='04-22-Master'!F6 -> Siri Mansion LIGB 436 Dr.A S Rao Nagar,Hyderabad | I174: ='04-22-Master'!B20 -> Shekhar Panchal
B176: Registration Number:
I177: Father’s / Husband’s Name:
I178: ='04-22-Master'!E20 -> Naresh Kumar Panchal
I179: Date of appointment : | L179: ='04-22-Master'!I20 -> 44388
B180: S.No | C180: Accumalation of Leave | E180: Leave allowed | G180: Balance of Leave Carried Over | H180: Payment of Leave made on | J180: Refusal of Leave | M180: Payment of Leave on Discharge of an employee quitting employment if a admissible | P180: Signature or the Thumb impression of employee on Receipt of Leave Book in Form N
B182: 1 | G182: 6 | J182: 9 | M182: 9 | P182: Impression of
C183: Leave due on | D183: No of Days | E183: From | F183: To | H183: 1st month | I183: 2nd month | J183: Date of Application | K183: Date of Refusal | L183: Amount of Leave refused | M183: Date of Discharge | N183: Date of Amount Paid | O183: Signature or Left hand thumb impression of employee
B185: JAN'22 | C185: 1.5 | G185: 6 | J185: NO | K185: NO | L185: NO
B186: FEB'22 | C186: 1.5 | D186: 1 | E186: 44610 | F186: 44610 | G186: =G185+C186-D186 -> 6.5 | J186: NO | K186: NO | L186: NO
B187: MAR'22 | C187: 1.5 | D187: 0 | E187: 0 | F187: 0 | G187: =G186+C187-D187 -> 8 | J187: NO | K187: NO | L187: NO
A188: 4 | B188: APRIL'22 | C188: 1.5 | D188: 0 | E188: 0 | F188: 0 | G188: =G187+C188-D188 -> 9.5 | J188: NO | K188: NO | L188: NO | Q188: 5
J206: Signature of the Contractor with Seal
B211: FORM XXV- REGISTER OF LEAVE
B213: [See Rule 29(6)]A.P. Shops & Establishments Rules, 1990
B214: Name of the Establishment: | D214: ='04-22-Master'!F5 -> Burgeon IT Services Pvt.Ltd. | I214: Name of the Employee:
C215: ='04-22-Master'!F6 -> Siri Mansion LIGB 436 Dr.A S Rao Nagar,Hyderabad | I215: ='04-22-Master'!B21 -> Gangadhar Yarabham
I218: Father’s / Husband’s Name:
I219: ='04-22-Master'!E21 -> Yarabham Savaraiah
I220: Date of appointment : | L220: ='04-22-Master'!I21 -> 44431
B221: =I1 -> 0 | C221: Accumalation of Leave | E221: Leave allowed | G221: Balance of Leave Carried Over | H221: Payment of Leave made on | J221: Refusal of Leave | M221: Payment of Leave on Discharge of an employee quitting employment if a admissible | P221: Signature or the Thumb impression of employee on Receipt of Leave Book in Form N
B223: 1 | G223: 6 | J223: 9 | M223: 9 | P223: Impression of
C224: Leave due on | D224: No of Days | E224: From | F224: To | H224: 1st month | I224: 2nd month | J224: Date of Application | K224: Date of Refusal | L224: Amount of Leave refused | M224: Date of Discharge | N224: Date of Amount Paid | O224: Signature or Left hand thumb impression of employee
B226: JAN'22 | C226: 1.5 | G226: 7.5 | J226: NO | K226: NO | L226: NO
B227: FEB'22 | C227: 1.5 | D227: 0 | E227: 0 | F227: 0 | G227: =G226+C227-D227 -> 9 | J227: NO | K227: NO | L227: NO
B228: MAR'22 | C228: 1.5 | D228: 0 | E228: 0 | F228: 0 | G228: =G227+C228-D228 -> 10.5 | J228: NO | K228: NO | L228: NO
B229: APRIL'22 | C229: 1.5 | D229: 0 | E229: 0 | F229: 0 | G229: =G228+C229-D229 -> 12 | J229: NO | K229: NO | L229: NO | Q229: 6
J247: Signature of the Contractor with Seal
B252: FORM XXV- REGISTER OF LEAVE
B254: [See Rule 29(6)]A.P. Shops & Establishments Rules, 1990
B255: Name of the Establishment: | D255: Burgeon IT Services Pvt.Ltd. | I255: Name of the Employee:
C256: Siri Mansion LIGB 436 Dr.A S Rao Nagar,Hyderabad | I256: ='04-22-Master'!B22 -> Nikhila Kaveri
I259: Father’s / Husband’s Name:
I260: ='04-22-Master'!E170 -> 0
...

Sheet wages Reg
A1: FORM - XVII REGISTER OF WAGES [Vide Rule 78 (1) (a) (i) of Contract Labour (Reg. & Abolition) Central & Telangana/A.P.Rules 1971]
A2: Name and address of Contractor: | D2: ='04-22-Master'!F5 -> Burgeon IT Services Pvt.Ltd. | U2: Name and address of Establishemnt in/ under which contract is carried on: | AB2: ='04-22-Master'!AJ5 -> Burgeon IT Services Pvt.Ltd.
D3: ='04-22-Master'!F6 -> Siri Mansion LIGB 436 Dr.A S Rao Nagar,Hyderabad | AB3: ='04-22-Master'!AJ6 -> Siri Mansion LIGB 436 Dr.A S Rao Nagar,Hyderabad
A4: Nature and location of work: | D4: ='04-22-Master'!F8 -> IT SUPPORTIVE SERVICES & HYDERABAD SEZ
A6: Wage period: Monthly | D6: ='04-22-Master'!D10 -> 44652 | V6: Name and address of Principal Employer: | AB6: ='04-22-Master'!AJ10 -> INFOSYS LTD.IL Hyderabad SEZ
AB7: ='04-22-Master'!AJ11 -> Sy.No 42,Pocharam Village,Gatkesar Mandal
A10: S.No | B10: Name of Workman | C10: Serial No. in the Register of Workmen | D10: Designation / Nature of Work Done | E10: No.of Days worked | F10: Unit of work done | G10: Monthly rate of wages/ piece rate | H10: Basic wages | I10: Dearness Allowances | J10: Over time | K10: Other cash payments (Nature of payments to be indicated) | L10: HRA | M10: CONVEYANCE | N10: MEDICAL ALLOWANCES | O10: SPECIAL ALLOWNANCES | P10: Total | Q10: BONUS | R10: GRATUITY | S10: LTA/L.E | T10: ARREAR AMOUNT | U10: TOTAL AMOUNT | V10: Deductions, if any, (Indicate nature) | AC10: Net Amount paid | AD10: Time and Date of Payment | AE10: Place of Payment | AF10: Signature/Thumb Impression of workman | AG10: Initial of Contractor or his representative
V11: ESI | W11: PF | X11: PT | Y11: TDS | Z11: MED | AA11: Adjusted Amount | AB11: Total Deductions
A12: 1 | B12: ='04-22-Master'!P16 -> kaja Venkat Ragavendra | C12: ='04-22-Master'!AT16 -> 41 | D12: ='04-22-Master'!F16 -> SR.Application Consultant | E12: ='04-22-Master'!Q16 -> 30 | F12: ='04-22-Master'!R16 -> N/A | G12: ='04-22-Master'!S16 -> 84913 | H12: ='04-22-Master'!T16 -> 50947.8 | I12: ='04-22-Master'!U16 -> 0 | J12: ='04-22-Master'!V16 -> 0 | K12: =L12+M12+N12+O12 -> 34078.2 | L12: ='04-22-Master'!X16 -> 20379.12 | M12: ='04-22-Master'!Y16 -> 2083 | N12: ='04-22-Master'!Z16 -> 2083 | O12: ='04-22-Master'!AA16 -> 9533.08 | P12: =H12+K12 -> 85026 | Q12: ='04-22-Master'!AC16 -> 1554.609 | R12: ='04-22-Master'!AD16 -> 2450.5892 | S12: ='04-22-Master'!AE16 -> 4245.65 | T12: ='04-22-Master'!AF16 -> 0 | U12: =P12+Q12+R12+S12+T12 -> 93276.848 | V12: ='04-22-Master'!AH16 -> 0 | W12: ='04-22-Master'!AI16 -> 1800 | X12: ='04-22-Master'!AJ16 -> 200 | Y12: ='04-22-Master'!AK16 -> 0 | Z12: ='04-22-Master'!AL16 -> 391.78785 | AA12: 0 | AB12: =V12+W12+X12+Y12+Z12+AA12 -> 2391.7878 | AC12: =U12-AB12 -> 90885.06 | AD12: ='04-22-Master'!AP16 -> 44686 | AE12: ='04-22-Master'!AQ16 -> KMB | AF12: ='04-22-Master'!AR16 -> A/C'6812236194
A13: 2 | B13: ='04-22-Master'!P17 -> VeerendraBabu Galam | C13: ='04-22-Master'!AT17 -> 68 | D13: ='04-22-Master'!F17 -> Senior Test Engineer | E13: ='04-22-Master'!Q17 -> 30 | F13: ='04-22-Master'!R17 -> N/A | G13: ='04-22-Master'!S17 -> 66374 | H13: ='04-22-Master'!T17 -> 39824.4 | I13: ='04-22-Master'!U17 -> 0 | J13: ='04-22-Master'!V17 -> 0 | K13: =L13+M13+N13+O13 -> 26662.6 | L13: ='04-22-Master'!X17 -> 15929.76 | M13: ='04-22-Master'!Y17 -> 2083 | N13: ='04-22-Master'!Z17 -> 2083 | O13: ='04-22-Master'!AA17 -> 6566.84 | P13: =H13+K13 -> 66487 | Q13: ='04-22-Master'!AC17 -> 1554.609 | R13: ='04-22-Master'!AD17 -> 1915.5536 | S13: ='04-22-Master'!AE17 -> 3318.7 | T13: ='04-22-Master'!AF17 -> 0 | U13: =P13+Q13+R13+S13+T13 -> 73275.863 | V13: ='04-22-Master'!AH17 -> 0 | W13: ='04-22-Master'!AI17 -> 1800 | X13: ='04-22-Master'!AJ17 -> 200 | Y13: ='04-22-Master'!AK17 -> 0 | Z13: ='04-22-Master'!AL17 -> 391.78785 | AA13: 0 | AB13: =V13+W13+X13+Y13+Z13+AA13 -> 2391.7878 | AC13: =U13-AB13 -> 70884.075 | AD13: ='04-22-Master'!AP17 -> 44686 | AE13: ='04-22-Master'!AQ17 -> Standard chartered Bank | AF13: ='04-22-Master'!AR17 -> A/C'44511140919
A14: 3 | B14: ='04-22-Master'!P18 -> RUKNUDEEN S | C14: ='04-22-Master'!AT18 -> 75 | D14: ='04-22-Master'!F18 -> Technical consultant | E14: ='04-22-Master'!Q18 -> 30 | F14: ='04-22-Master'!R18 -> N/A | G14: ='04-22-Master'!S18 -> 89547 | H14: ='04-22-Master'!T18 -> 53728.2 | I14: ='04-22-Master'!U18 -> 0 | J14: ='04-22-Master'!V18 -> 0 | K14: =L14+M14+N14+O14 -> 35931.8 | L14: ='04-22-Master'!X18 -> 21491.28 | M14: ='04-22-Master'!Y18 -> 2083 | N14: ='04-22-Master'!Z18 -> 2083 | O14: ='04-22-Master'!AA18 -> 10274.52 | P14: =H14+K14 -> 89660 | Q14: ='04-22-Master'!AC18 -> 1554.609 | R14: ='04-22-Master'!AD18 -> 2584.3264 | S14: ='04-22-Master'!AE18 -> 4477.35 | T14: ='04-22-Master'!AF18 -> 0 | U14: =P14+Q14+R14+S14+T14 -> 98276.285 | V14: ='04-22-Master'!AH18 -> 0 | W14: ='04-22-Master'!AI18 -> 1800 | X14: ='04-22-Master'!AJ18 -> 200 | Y14: ='04-22-Master'!AK18 -> 0 | Z14: ='04-22-Master'!AL18 -> 391.78785 | AA14: 0 | AB14: =V14+W14+X14+Y14+Z14+AA14 -> 2391.7878 | AC14: =U14-AB14 -> 95884.498 | AD14: ='04-22-Master'!AP18 -> 44686 | AE14: ='04-22-Master'!AQ18 -> SBI | AF14: ='04-22-Master'!AR18 -> 39203094887
A15: 4 | B15: ='04-22-Master'!P19 -> Srikanth Thota | C15: ='04-22-Master'!AT19 -> 80 | D15: ='04-22-Master'!F19 -> PMO Manager | E15: ='04-22-Master'!Q19 -> 30 | F15: ='04-22-Master'!R19 -> N/A | G15: ='04-22-Master'!S19 -> 103451 | H15: ='04-22-Master'!T19 -> 62070.6 | I15: ='04-22-Master'!U19 -> 0 | J15: ='04-22-Master'!V19 -> 0 | K15: =L15+M15+N15+O15 -> 41493.4 | L15: ='04-22-Master'!X19 -> 24828.24 | M15: ='04-22-Master'!Y19 -> 2083 | N15: ='04-22-Master'!Z19 -> 2083 | O15: ='04-22-Master'!AA19 -> 12499.16 | P15: =H15+K15 -> 103564 | Q15: ='04-22-Master'!AC19 -> 1554.609 | R15: ='04-22-Master'!AD19 -> 2985.5959 | S15: ='04-22-Master'!AE19 -> 5172.55 | T15: ='04-22-Master'!AF19 -> 0 | U15: =P15+Q15+R15+S15+T15 -> 113276.75 | V15: ='04-22-Master'!AH19 -> 0 | W15: ='04-22-Master'!AI19 -> 1800 | X15: ='04-22-Master'!AJ19 -> 200 | Y15: ='04-22-Master'!AK19 -> 0 | Z15: ='04-22-Master'!AL19 -> 377 | AA15: 0 | AB15: =V15+W15+X15+Y15+Z15+AA15 -> 2377 | AC15: =U15-AB15 -> 110899.75 | AD15: ='04-22-Master'!AP19 -> 44686 | AE15: ='04-22-Master'!AQ19 -> ICICI BANK | AF15: ='04-22-Master'!AR19 -> 020201513961
A16: 5 | B16: ='04-22-Master'!P20 -> Shekhar Panchal | C16: ='04-22-Master'!AT20 -> 81 | D16: ='04-22-Master'!F20 -> Sr. Network Security Engineer | E16: ='04-22-Master'!Q20 -> 30 | F16: ='04-22-Master'!R20 -> N/A | G16: ='04-22-Master'!S20 -> 66374 | H16: ='04-22-Master'!T20 -> 39824.4 | I16: ='04-22-Master'!U20 -> 0 | J16: ='04-22-Master'!V20 -> 0 | K16: =L16+M16+N16+O16 -> 26662.6 | L16: ='04-22-Master'!X20 -> 15929.76 | M16: ='04-22-Master'!Y20 -> 2083 | N16: ='04-22-Master'!Z20 -> 2083 | O16: ='04-22-Master'!AA20 -> 6566.84 | P16: =H16+K16 -> 66487 | Q16: ='04-22-Master'!AC20 -> 1554.609 | R16: ='04-22-Master'!AD20 -> 1915.5536 | S16: ='04-22-Master'!AE20 -> 3318.7 | T16: ='04-22-Master'!AF20 -> 0 | U16: =P16+Q16+R16+S16+T16 -> 73275.863 | V16: ='04-22-Master'!AH20 -> 0 | W16: ='04-22-Master'!AI20 -> 1800 | X16: ='04-22-Master'!AJ20 -> 200 | Y16: ='04-22-Master'!AK20 -> 0 | Z16: ='04-22-Master'!AL20 -> 336 | AA16: 0 | AB16: =V16+W16+X16+Y16+Z16+AA16 -> 2336 | AC16: =U16-AB16 -> 70939.863 | AD16: ='04-22-Master'!AP20 -> 44686 | AE16: ='04-22-Master'!AQ20 -> ICICI BANK | AF16: ='04-22-Master'!AR20 -> 346801502975
A17: 6 | B17: ='04-22-Master'!P21 -> Gangadhar Yarabham | C17: ='04-22-Master'!AT21 -> 83 | D17: ='04-22-Master'!F21 -> Senior Specialist | E17: ='04-22-Master'!Q21 -> 30 | F17: ='04-22-Master'!R21 -> N/A | G17: ='04-22-Master'!S21 -> 84912 | H17: ='04-22-Master'!T21 -> 50947.2 | I17: ='04-22-Master'!U21 -> 0 | J17: ='04-22-Master'!V21 -> 0 | K17: =L17+M17+N17+O17 -> 34077.8 | L17: ='04-22-Master'!X21 -> 20378.88 | M17: ='04-22-Master'!Y21 -> 2083 | N17: ='04-22-Master'!Z21 -> 2083 | O17: ='04-22-Master'!AA21 -> 9532.92 | P17: =H17+K17 -> 85025 | Q17: ='04-22-Master'!AC21 -> 1554.609 | R17: ='04-22-Master'!AD21 -> 2450.5603 | S17: ='04-22-Master'!AE21 -> 4245.6 | T17: ='04-22-Master'!AF21 -> 0 | U17: =P17+Q17+R17+S17+T17 -> 93275.769 | V17: ='04-22-Master'!AH21 -> 0 | W17: ='04-22-Master'!AI21 -> 1800 | X17: ='04-22-Master'!AJ21 -> 200 | Y17: ='04-22-Master'!AK21 -> 0 | Z17: ='04-22-Master'!AL21 -> 377 | AA17: 0 | AB17: =V17+W17+X17+Y17+Z17+AA17 -> 2377 | AC17: =U17-AB17 -> 90898.769 | AD17: ='04-22-Master'!AP21 -> 44686 | AE17: ='04-22-Master'!AQ21 -> KOTAK BANK | AF17: ='04-22-Master'!AR21 -> A/C NUM:0745780762
A18: 7 | B18: ='04-22-Master'!P22 -> Nikhila Kaveri | C18: ='04-22-Master'!AT22 -> 89 | D18: ='04-22-Master'!F22 -> TECHNICAL SOLUTION CONSULTANT | E18: ='04-22-Master'!Q22 -> 30 | F18: ='04-22-Master'!R22 -> N/A | G18: ='04-22-Master'!S22 -> 108085 | H18: ='04-22-Master'!T22 -> 64851 | I18: ='04-22-Master'!U22 -> 0 | J18: ='04-22-Master'!V22 -> 0 | K18: =L18+M18+N18+O18 -> 43347 | L18: ='04-22-Master'!X22 -> 25940.4 | M18: ='04-22-Master'!Y22 -> 2083 | N18: ='04-22-Master'!Z22 -> 2083 | O18: ='04-22-Master'!AA22 -> 13240.6 | P18: =H18+K18 -> 108198 | Q18: ='04-22-Master'!AC22 -> 1554.609 | R18: ='04-22-Master'!AD22 -> 3119.3331 | S18: ='04-22-Master'!AE22 -> 5404.25 | T18: ='04-22-Master'!AF22 -> 0 | U18: =P18+Q18+R18+S18+T18 -> 118276.19 | V18: ='04-22-Master'!AH22 -> 0 | W18: ='04-22-Master'!AI22 -> 1800 | X18: ='04-22-Master'!AJ22 -> 200 | Y18: ='04-22-Master'!AK22 -> 0 | Z18: ='04-22-Master'!AL22 -> 252 | AA18: 0 | AB18: =V18+W18+X18+Y18+Z18+AA18 -> 2252 | AC18: =U18-AB18 -> 116024.19 | AD18: ='04-22-Master'!AP22 -> 44686 | AE18: ='04-22-Master'!AQ22 -> HDFC BANK | AF18: ='04-22-Master'!AR22 -> HDFC0002770
A19: 8 | B19: ='04-22-Master'!P23 -> Thaposh Ghosh | C19: ='04-22-Master'!AT23 -> 90 | D19: ='04-22-Master'!F23 -> Incident Governance Manager | E19: ='04-22-Master'!Q23 -> 30 | F19: ='04-22-Master'!R23 -> N/A | G19: ='04-22-Master'!S23 -> 140526 | H19: ='04-22-Master'!T23 -> 84315.6 | I19: ='04-22-Master'!U23 -> 0 | J19: ='04-22-Master'!V23 -> 0 | K19: =L19+M19+N19+O19 -> 56323.4 | L19: ='04-22-Master'!X23 -> 33726.24 | M19: ='04-22-Master'!Y23 -> 2083 | N19: ='04-22-Master'!Z23 -> 2083 | O19: ='04-22-Master'!AA23 -> 18431.16 | P19: =H19+K19 -> 140639 | Q19: ='04-22-Master'!AC23 -> 1554.609 | R19: ='04-22-Master'!AD23 -> 4055.5804 | S19: ='04-22-Master'!AE23 -> 7026.3 | T19: ='04-22-Master'!AF23 -> 0 | U19: =P19+Q19+R19+S19+T19 -> 153275.49 | V19: ='04-22-Master'!AH23 -> 0 | W19: ='04-22-Master'!AI23 -> 1800 | X19: ='04-22-Master'!AJ23 -> 200 | Y19: ='04-22-Master'!AK23 -> 0 | Z19: ='04-22-Master'!AL23 -> 283 | AA19: 0 | AB19: =V19+W19+X19+Y19+Z19+AA19 -> 2283 | AC19: =U19-AB19 -> 150992.49 | AD19: ='04-22-Master'!AP23 -> 44686 | AE19: ='04-22-Master'!AQ23 -> AXIS BANK | AF19: ='04-22-Master'!AR23 -> 914010012727732
A20: 9 | B20: ='04-22-Master'!P24 -> Nagashree Narayan | C20: ='04-22-Master'!AT24 -> 91 | D20: ='04-22-Master'!F24 -> Technical Lead | E20: ='04-22-Master'!Q24 -> 29 | F20: ='04-22-Master'!R24 -> N/A | G20: ='04-22-Master'!S24 -> 98816 | H20: ='04-22-Master'!T24 -> 57313.28 | I20: ='04-22-Master'!U24 -> 0 | J20: ='04-22-Master'!V24 -> 0 | K20: =L20+M20+N20+O20 -> 38321.853 | L20: ='04-22-Master'!X24 -> 22925.312 | M20: ='04-22-Master'!Y24 -> 2014 | N20: ='04-22-Master'!Z24 -> 2014 | O20: ='04-22-Master'!AA24 -> 11368.541 | P20: =H20+K20 -> 95635.133 | Q20: ='04-22-Master'!AC24 -> 1554.609 | R20: ='04-22-Master'!AD24 -> 2756.7688 | S20: ='04-22-Master'!AE24 -> 4776.1067 | T20: ='04-22-Master'!AF24 -> 0 | U20: =P20+Q20+R20+S20+T20 -> 104722.62 | V20: ='04-22-Master'!AH24 -> 0 | W20: ='04-22-Master'!AI24 -> 1800 | X20: ='04-22-Master'!AJ24 -> 200 | Y20: ='04-22-Master'!AK24 -> 0 | Z20: ='04-22-Master'!AL24 -> 283 | AA20: 0 | AB20: =V20+W20+X20+Y20+Z20+AA20 -> 2283 | AC20: =U20-AB20 -> 102439.62 | AD20: ='04-22-Master'!AP24 -> 44686 | AE20: ='04-22-Master'!AQ24 -> ICICI BANK | AF20: ='04-22-Master'!AR24 -> 098601510169
A21: 10 | B21: ='04-22-Master'!P25 -> ROOPINI CHIYYARAPU | C21: ='04-22-Master'!AT25 -> 92 | D21: ='04-22-Master'!F25 -> Service Now Developer | E21: ='04-22-Master'!Q25 -> 30 | F21: ='04-22-Master'!R25 -> N/A | G21: ='04-22-Master'!S25 -> 75643 | H21: ='04-22-Master'!T25 -> 45385.8 | I21: ='04-22-Master'!U25 -> 0 | J21: ='04-22-Master'!V25 -> 0 | K21: =L21+M21+N21+O21 -> 30370.2 | L21: ='04-22-Master'!X25 -> 18154.32 | M21: ='04-22-Master'!Y25 -> 2083 | N21: ='04-22-Master'!Z25 -> 2083 | O21: ='04-22-Master'!AA25 -> 8049.88 | P21: =H21+K21 -> 75756 | Q21: ='04-22-Master'!AC25 -> 1554.609 | R21: ='04-22-Master'!AD25 -> 2183.057 | S21: ='04-22-Master'!AE25 -> 3782.15 | T21: ='04-22-Master'!AF25 -> 0 | U21: =P21+Q21+R21+S21+T21 -> 83275.816 | V21: ='04-22-Master'!AH25 -> 0 | W21: ='04-22-Master'!AI25 -> 1800 | X21: ='04-22-Master'!AJ25 -> 200 | Y21: ='04-22-Master'!AK25 -> 0 | Z21: ='04-22-Master'!AL25 -> 283 | AA21: 0 | AB21: =V21+W21+X21+Y21+Z21+AA21 -> 2283 | AC21: =U21-AB21 -> 80992.816 | AD21: ='04-22-Master'!AP25 -> 44686 | AE21: ='04-22-Master'!AQ25 -> SBI | AF21: ='04-22-Master'!AR25 -> 39504382024
A22: 11 | B22: ='04-22-Master'!P26 -> D.Santhoshi | C22: ='04-22-Master'!AT26 -> 93 | D22: ='04-22-Master'!F26 -> SAP Basis Consultant | E22: ='04-22-Master'!Q26 -> 30 | F22: ='04-22-Master'!R26 -> N/A | G22: ='04-22-Master'!S26 -> 38567 | H22: ='04-22-Master'!T26 -> 23140.2 | I22: ='04-22-Master'!U26 -> 0 | J22: ='04-22-Master'!V26 -> 0 | K22: =L22+M22+N22+O22 -> 15539.8 | L22: ='04-22-Master'!X26 -> 9256.08 | M22: ='04-22-Master'!Y26 -> 2083 | N22: ='04-22-Master'!Z26 -> 2083 | O22: ='04-22-Master'!AA26 -> 2117.72 | P22: =H22+K22 -> 38680 | Q22: ='04-22-Master'!AC26 -> 1554.609 | R22: ='04-22-Master'!AD26 -> 1113.0436 | S22: ='04-22-Master'!AE26 -> 1928.35 | T22: ='04-22-Master'!AF26 -> 0 | U22: =P22+Q22+R22+S22+T22 -> 43276.003 | V22: ='04-22-Master'!AH26 -> 0 | W22: ='04-22-Master'!AI26 -> 1800 | X22: ='04-22-Master'!AJ26 -> 200 | Y22: ='04-22-Master'!AK26 -> 0 | Z22: ='04-22-Master'!AL26 -> 283 | AA22: 0 | AB22: =V22+W22+X22+Y22+Z22+AA22 -> 2283 | AC22: =U22-AB22 -> 40993.003 | AD22: ='04-22-Master'!AP26 -> 44686 | AE22: ='04-22-Master'!AQ26 -> INDIAN BANK | AF22: ='04-22-Master'!AR26 -> 6108665097
A23: 12 | B23: ='04-22-Master'!P27 -> Bharath | C23: ='04-22-Master'!AT27 -> 94 | D23: ='04-22-Master'!F27 -> SAP Basis Consultant | E23: ='04-22-Master'!Q27 -> 30 | F23: ='04-22-Master'!R27 -> N/A | G23: ='04-22-Master'!S27 -> 24636 | H23: ='04-22-Master'!T27 -> 14781.6 | I23: ='04-22-Master'!U27 -> 0 | J23: ='04-22-Master'!V27 -> 0 | K23: =L23+M23+N23+O23 -> 9967.4 | L23: ='04-22-Master'!X27 -> 5912.64 | M23: ='04-22-Master'!Y27 -> 1500 | N23: ='04-22-Master'!Z27 -> 1500 | O23: ='04-22-Master'!AA27 -> 1054.76 | P23: =H23+K23 -> 24749 | Q23: ='04-22-Master'!AC27 -> 1554.609 | R23: ='04-22-Master'!AD27 -> 710.99496 | S23: ='04-22-Master'!AE27 -> 1231.8 | T23: ='04-22-Master'!AF27 -> 0 | U23: =P23+Q23+R23+S23+T23 -> 28246.404 | V23: ='04-22-Master'!AH27 -> 0 | W23: ='04-22-Master'!AI27 -> 1774 | X23: ='04-22-Master'!AJ27 -> 200 | Y23: ='04-22-Master'!AK27 -> 0 | Z23: ='04-22-Master'!AL27 -> 283 | AA23: 0 | AB23: =V23+W23+X23+Y23+Z23+AA23 -> 2257 | AC23: =U23-AB23 -> 25989.404 | AD23: ='04-22-Master'!AP27 -> 44686 | AE23: ='04-22-Master'!AQ27 -> SBI | AF23: ='04-22-Master'!AR27 -> 34997967265
... A32: 21 | B32: ='04-22-Master'!P36 -> SADHAMHUSSAIN | C32: ='04-22-Master'!AT36 -> 103 | D32: ='04-22-Master'!F36 -> Security Administrator | E32: ='04-22-Master'!Q36 -> 6 | F32: ='04-22-Master'!R36 -> 0 | G32: ='04-22-Master'!S36 -> 135892 | H32: ='04-22-Master'!T36 -> 16307.04 | I32: ='04-22-Master'!U36 -> 0 | J32: ='04-22-Master'!V36 -> 0 | K32: =L32+M32+N32+O32 -> 10984.36 | L32: ='04-22-Master'!X36 -> 6522.816 | M32: ='04-22-Master'!Y36 -> 417 | N32: ='04-22-Master'!Z36 -> 417 | O32: ='04-22-Master'!AA36 -> 3627.544 | P32: =H32+K32 -> 27291.4 | Q32: ='04-22-Master'!AC36 -> 1554.609 | R32: ='04-22-Master'!AD36 -> 784.36862 | S32: ='04-22-Master'!AE36 -> 1358.92 | T32: ='04-22-Master'!AF36 -> 0 | U32: =P32+Q32+R32+S32+T32 -> 30989.298 | V32: ='04-22-Master'!AH36 -> 0 | W32: ='04-22-Master'!AI36 -> 1800 | X32: ='04-22-Master'!AJ36 -> 200 | Y32: ='04-22-Master'!AK36 -> 0 | Z32: ='04-22-Master'!AL36 -> 0 | AA32: 0 | AB32: =V32+W32+X32+Y32+Z32+AA32 -> 2000 | AC32: =U32-AB32 -> 28989.298 | AD32: ='04-22-Master'!AP36 -> 44686 | AE32: ='04-22-Master'!AQ36 -> HDFC BANK | AF32: ='04-22-Master'!AR36 -> 50100271012409
E33: =SUM(E12:E32) -> 583 | F33: =SUM(F12:F32) -> 0 | G33: =SUM(G12:G32) -> 1766399 | H33: =SUM(H12:H32) -> 957127.44 | I33: =SUM(I12:I32) -> 0 | J33: =SUM(J12:J32) -> 0 | K33: =SUM(K12:K32) -> 640457.96 | L33: =SUM(L12:L32) -> 382850.98 | ... AC33: =SUM(AC12:AC32) -> 1710396.3

Sheet Empt Cards
B1: FORM XIV
B2: EMPLOYMENT CUM WAGE CARD
B3: (Vide Rule 76 of Contract Labour (R&A) Central & A.P Rules, 1971)
B4: Name and Address of the Contractor | H4: Name and Address of the Establishment in/under which Contract is carried on:
B7: ='04-22-Master'!F5 -> Burgeon IT Services Pvt.Ltd. | H7: ='04-22-Master'!AJ5 -> Burgeon IT Services Pvt.Ltd.
B9: ='04-22-Master'!F6 -> Siri Mansion LIGB 436 Dr.A S Rao Nagar,Hyderabad | H9: ='04-22-Master'!AJ6 -> Siri Mansion LIGB 436 Dr.A S Rao Nagar,Hyderabad
B12: Nature of work and location of work: | H12: Name and address of Principal Employer:
H15: ='04-22-Master'!AJ10 -> INFOSYS LTD.IL Hyderabad SEZ
B16: ='04-22-Master'!F8 -> IT SUPPORTIVE SERVICES & HYDERABAD SEZ
H17: ='04-22-Master'!AJ11 -> Sy.No 42,Pocharam Village,Gatkesar Mandal
B19: 1. Name of the Workman and address | H19: ='04-22-Master'!B16 -> kaja Venkat Ragavendra
H20: ='04-22-Master'!G16 -> Kidambi Residency, Flat no 6, Agraharam, Guntur, 522003
B21: 2. S.No. in the Register of Workmen Employed | H21: ='04-22-Master'!AT16 -> 41
B22: 3. Nature of Employment /Designation | H22: ='04-22-Master'!F16 -> SR.Application Consultant
B23: 4. Date of entry into service | H23: ='04-22-Master'!I16 -> 43864
B24: 5. ESI No. | J24: ='04-22-Master'!O16 -> N/A
B25: 6.PF No. | J25: ='04-22-Master'!N16 -> 101308550178
B26: 7. Wage rate (With particulars of unit in case of piece - work) | H26: ='04-22-Master'!S16 -> 84913
B27: 8. Wage period | H27: ='04-22-Master'!D10 -> 44652
B28: 9. Tenure of Employment | H28: AS PER CONTRACT
B29: 10.No. of days worked in a month | J29: ='04-22-Master'!Q16 -> 30
B30: 11. No. of units worked in case of piece rate workers | J30: N/A
B31: 12. Rate of daily wages / piece rate | J31: 0
B32: 13. Amount of overtime wages | J32: 0
B33: 14. Gross wages payable | J33: ='04-22-Master'!AG16 -> 93276.848 | L33: MED
B34: 15. Deductions, if any, | D34: PF | E34: ='04-22-Master'!AI16 -> 1800 | F34: ESI | G34: ='04-22-Master'!AH16 -> 0 | H34: PT | I34: ='04-22-Master'!AJ16 -> 200 | J34: TDS | K34: ='04-22-Master'!AK16 -> 0 | L34: ='04-22-Master'!AL16 -> 391.78785
B35: 16. Net amount of wages paid | J35: ='04-22-Master'!AO16 -> 90885.06
B36: Signature of the Representative
B37: of Contractor
B46: FORM XIV
B47: EMPLOYMENT CUM WAGE CARD
B48: (Vide Rule 76 of Contract Labour (R&A) Central & A.P Rules, 1971)
B49: Name and Address of the Contractor | H49: Name and Address of the Establishment in/under which Contract is carried on:
B52: ='04-22-Master'!F5 -> Burgeon IT Services Pvt.Ltd. | H52: ='04-22-Master'!AJ5 -> Burgeon IT Services Pvt.Ltd.
B54: ='04-22-Master'!F6 -> Siri Mansion LIGB 436 Dr.A S Rao Nagar,Hyderabad | H54: ='04-22-Master'!AJ6 -> Siri Mansion LIGB 436 Dr.A S Rao Nagar,Hyderabad
B57: Nature of work and location of work: | H57: Name and address of Principal Employer:
H60: ='04-22-Master'!AJ10 -> INFOSYS LTD.IL Hyderabad SEZ
B61: ='04-22-Master'!F8 -> IT SUPPORTIVE SERVICES & HYDERABAD SEZ
H62: ='04-22-Master'!AJ11 -> Sy.No 42,Pocharam Village,Gatkesar Mandal
B64: 1. Name of the Workman and address | H64: ='04-22-Master'!B17 -> VeerendraBabu Galam
H65: ='04-22-Master'!G17 -> 1-66, Lakshmipuram Village, Kallur mandal, Khammam Dist, Telangana 507209
B66: 2. S.No. in the Register of Workmen Employed | H66: ='04-22-Master'!AT17 -> 68
B67: 3. Nature of Employment /Designation | H67: ='04-22-Master'!F17 -> Senior Test Engineer
B68: 4. Date of entry into service | H68: ='04-22-Master'!I17 -> 18-03-2021
B69: 5. ESI No. | J69: ='04-22-Master'!O17 -> N/A
B70: 6.PF No. | J70: ='04-22-Master'!N17 -> 100916499521
B71: 7. Wage rate (With particulars of unit in case of piece - work) | H71: ='04-22-Master'!S17 -> 66374
B72: 8. Wage period | H72: ='04-22-Master'!D10 -> 44652
B73: 9. Tenure of Employment | H73: AS PER CONTRACT
B74: 10.No. of days worked in a month | J74: ='04-22-Master'!Q17 -> 30
B75: 11. No. of units worked in case of piece rate workers | J75: N/A
B76: 12. Rate of daily wages / piece rate | J76: 0
B77: 13. Amount of overtime wages | J77: 0
B78: 14. Gross wages payable | J78: ='04-22-Master'!AG17 -> 73275.863 | L78: MED
B79: 15. Deductions, if any, | D79: PF | E79: ='04-22-Master'!AI17 -> 1800 | F79: ESI | G79: ='04-22-Master'!AH177 -> 0 | H79: PT | I79: ='04-22-Master'!AJ17 -> 200 | J79: TDS | K79: ='04-22-Master'!AK17 -> 0 | L79: ='04-22-Master'!AL17 -> 391.78785
B80: 16. Net amount of wages paid | J80: =J78-(E79+G79+I79+K79+L79) -> 70884.075
B81: Signature of the Representative
B82: of Contractor
B99: FORM XIV
B100: EMPLOYMENT CUM WAGE CARD
B101: (Vide Rule 76 of Contract Labour (R&A) Central & A.P Rules, 1971)
B102: Name and Address of the Contractor | H102: Name and Address of the Establishment in/under which Contract is carried on:
B105: ='04-22-Master'!F5 -> Burgeon IT Services Pvt.Ltd. | H105: ='04-22-Master'!AJ5 -> Burgeon IT Services Pvt.Ltd.
B107: ='04-22-Master'!F6 -> Siri Mansion LIGB 436 Dr.A S Rao Nagar,Hyderabad | H107: ='04-22-Master'!AJ6 -> Siri Mansion LIGB 436 Dr.A S Rao Nagar,Hyderabad
B110: Nature of work and location of work: | H110: Name and address of Principal Employer:
H113: ='04-22-Master'!AJ10 -> INFOSYS LTD.IL Hyderabad SEZ
B114: ='04-22-Master'!F8 -> IT SUPPORTIVE SERVICES & HYDERABAD SEZ
H115: ='04-22-Master'!AJ11 -> Sy.No 42,Pocharam Village,Gatkesar Mandal
B117: 1. Name of the Workman and address | H117: ='04-22-Master'!B18 -> RUKNUDEEN S
H118: ='04-22-Master'!G18 -> WARD 5-2-46/7,PTR COLONY ,UTHAMAPALAYAM,THENI,TAMILNADU-625533
B119: 2. S.No. in the Register of Workmen Employed | H119: ='04-22-Master'!AT18 -> 75
B120: 3. Nature of Employment /Designation | H120: ='04-22-Master'!F18 -> Technical consultant
B121: 4. Date of entry into service | H121: ='04-22-Master'!I18 -> 44330
B122: 5. ESI No. | J122: ='04-22-Master'!O18 -> N/A
B123: 6.PF No. | J123: ='04-22-Master'!N18 -> 101695261761
B124: 7. Wage rate (With particulars of unit in case of piece - work) | H124: ='04-22-Master'!Q18 -> 30
B125: 8. Wage period | H125: ='04-22-Master'!D10 -> 44652
B126: 9. Tenure of Employment | H126: AS PER CONTRACT
B127: 10.No. of days worked in a month | J127: ='04-22-Master'!S18 -> 89547
B128: 11. No. of units worked in case of piece rate workers | J128: N/A
B129: 12. Rate of daily wages / piece rate | J129: 0
B130: 13. Amount of overtime wages | J130: 0
B131: 14. Gross wages payable | J131: ='04-22-Master'!AG18 -> 98276.285 | L131: MED
B132: 15. Deductions, if any, | D132: PF | E132: ='04-22-Master'!AI18 -> 1800 | F132: ESI | G132: ='04-22-Master'!AH508 -> 0 | H132: PT | I132: ='04-22-Master'!AJ18 -> 200 | J132: TDS | K132: ='04-22-Master'!AK18 -> 0 | L132: ='04-22-Master'!AL18 -> 391.78785
B133: 16. Net amount of wages paid | J133: =J131-(E132+G132+I132+K132+L132) -> 95884.498
B134: Signature of the Representative
B135: of Contractor
B151: FORM XIV
B152: EMPLOYMENT CUM WAGE CARD
B153: (Vide Rule 76 of Contract Labour (R&A) Central & A.P Rules, 1971)
B154: Name and Address of the Contractor | H154: Name and Address of the Establishment in/under which Contract is carried on:
B157: ='04-22-Master'!F5 -> Burgeon IT Services Pvt.Ltd. | H157: =B157 -> Burgeon IT Services Pvt.Ltd.
B159: ='04-22-Master'!F6 -> Siri Mansion LIGB 436 Dr.A S Rao Nagar,Hyderabad | H159: =B159 -> Siri Mansion LIGB 436 Dr.A S Rao Nagar,Hyderabad
B162: Nature of work and location of work: | H162: Name and address of Principal Employer:
H165: ='04-22-Master'!AJ10 -> INFOSYS LTD.IL Hyderabad SEZ
B166: ='04-22-Master'!F8 -> IT SUPPORTIVE SERVICES & HYDERABAD SEZ
H167: ='04-22-Master'!AJ11 -> Sy.No 42,Pocharam Village,Gatkesar Mandal
B169: 1. Name of the Workman and address | H169: ='04-22-Master'!B19 -> Srikanth Thota
H170: ='04-22-Master'!G19 -> Plot No 779,Defence colony Sainikpuri Secunderabad 500094
B171: 2. S.No. in the Register of Workmen Employed | H171: ='04-22-Master'!AT19 -> 80
...

Sheet wage sllips
A1: Form XIX - WAGE SLIP | K1: Form XIX - WAGE SLIP
A2: [Vide rule 78 (1) (b) of the Contract Labour (Regulation and Abolition) Central and A.P Rules, 1971] | K2: [Vide rule 78 (1) (b) of the Contract Labour (Regulation and Abolition) Central and A.P Rules, 1971]
A4: Name and address of Contractor | D4: ='04-22-Master'!F5 -> Burgeon IT Services Pvt.Ltd. | K4: Name and address of Contractor | O4: =D4 -> Burgeon IT Services Pvt.Ltd.
B5: ='04-22-Master'!F6 -> Siri Mansion LIGB 436 Dr.A S Rao Nagar,Hyderabad | L5: =B5 -> Siri Mansion LIGB 436 Dr.A S Rao Nagar,Hyderabad
B6: ='04-22-Master'!F1034 -> 0 | L6: =B6 -> 0
A7: Name and Father's / Husband's name of the workman | K7: Name and Father's / Husband's name of the workman
E8: ='04-22-Master'!B16 -> kaja Venkat Ragavendra | H8: ='04-22-Master'!E16 -> Kaja Suresh Babu | O8: =E8 -> kaja Venkat Ragavendra | R8: =H8 -> Kaja Suresh Babu
A10: Nature and location of work | E10: ='04-22-Master'!F8 -> IT SUPPORTIVE SERVICES & HYDERABAD SEZ | K10: Nature and location of work | O10: =E10 -> IT SUPPORTIVE SERVICES & HYDERABAD SEZ
A12: For the Week / Fortnight / Month ending | E12: ='04-22-Master'!D10 -> 44652 | K12: For the Week / Fortnight / Month ending | O12: =E12 -> 44652
A14: 1 | B14: No. of days worked | E14: ='04-22-Master'!Q16 -> 30 | K14: 1 | L14: No. of days worked | O14: =E14 -> 30
A16: 2 | B16: No. of units worked in case of piece rate workers : | K16: 2 | L16: No. of units worked in case of piece rate workers :
E17: N/A | O17: N/A
A19: 3 | B19: Rate of daily wages / piece rate | E19: N/A | K19: 3 | L19: Rate of daily wages / piece rate | O19: =E19 -> N/A
A21: 4 | B21: Amount of overtime wages | E21: Nil | K21: 4 | L21: Amount of overtime wages | O21: Nil
A23: 5 | B23: Gross wages payble | E23: ='04-22-Master'!AG16 -> 93276.848 | K23: 5 | L23: Gross wages payble | O23: =E23 -> 93276.848
D24: EPF | E24: ESI | F24: PT | G24: TDS | H24: MEDICAL | I24: TOTAL | N24: EPF | O24: ESI | P24: PT | Q24: TDS | R24: MEDICAL | S24: TOTAL
A25: 6 | B25: Deductions, if any | D25: ='04-22-Master'!AI16 -> 1800 | E25: ='04-22-Master'!AH16 -> 0 | F25: ='04-22-Master'!AJ16 -> 200 | G25: ='04-22-Master'!AK16 -> 0 | H25: ='04-22-Master'!AL16 -> 391.78785 | I25: =D25+E25+F25+G25+H25 -> 2391.7878 | K25: 6 | L25: Deductions, if any | N25: =D25 -> 1800 | O25: =E25 -> 0 | P25: =F25 -> 200 | Q25: =G25 -> 0 | R25: =H25 -> 391.78785 | S25: =I25 -> 2391.7878
A27: 7 | B27: Net amount of wages paid | E27: =E23-I25 -> 90885.06 | K27: 7 | L27: Net amount of wages paid | O27: =E27 -> 90885.06
F31: Initial of the Contractor or his representative | P31: Initial of the Contractor or his representative
A49: Form XIX - WAGE SLIP | K49: Form XIX - WAGE SLIP
A50: [Vide rule 78 (1) (b) of the Contract Labour (Regulation and Abolition) Central and A.P Rules, 1971] | K50: [Vide rule 78 (1) (b) of the Contract Labour (Regulation and Abolition) Central and A.P Rules, 1971]
A52: Name and address of Contractor | D52: ='04-22-Master'!F5 -> Burgeon IT Services Pvt.Ltd. | K52: Name and address of Contractor | O52: =D52 -> Burgeon IT Services Pvt.Ltd.
B53: ='04-22-Master'!F6 -> Siri Mansion LIGB 436 Dr.A S Rao Nagar,Hyderabad | L53: =B53 -> Siri Mansion LIGB 436 Dr.A S Rao Nagar,Hyderabad
L54: =B54 -> 0
A55: Name and Father's / Husband's name of the workman | K55: Name and Father's / Husband's name of the workman
E56: ='04-22-Master'!B17 -> VeerendraBabu Galam | H56: ='04-22-Master'!E17 -> Gopal Rao | O56: =E56 -> VeerendraBabu Galam | R56: =H56 -> Gopal Rao
A58: Nature and location of work | E58: ='04-22-Master'!F8 -> IT SUPPORTIVE SERVICES & HYDERABAD SEZ | K58: Nature and location of work | O58: =E58 -> IT SUPPORTIVE SERVICES & HYDERABAD SEZ
A60: For the Week / Fortnight / Month ending | E60: ='04-22-Master'!D10 -> 44652 | K60: For the Week / Fortnight / Month ending | O60: =E60 -> 44652
A62: 1 | B62: No. of days worked | E62: ='04-22-Master'!Q143 -> 0 | K62: 1 | L62: No. of days worked | O62: =E62 -> 0
A64: 2 | B64: No. of units worked in case of piece rate workers : | K64: 2 | L64: No. of units worked in case of piece rate workers :
E65: N/A | O65: N/A
A67: 3 | B67: Rate of daily wages / piece rate | E67: N/A | K67: 3 | L67: Rate of daily wages / piece rate | O67: =E67 -> N/A
A69: 4 | B69: Amount of overtime wages | E69: Nil | K69: 4 | L69: Amount of overtime wages | O69: Nil
A71: 5 | B71: Gross wages payble | E71: ='04-22-Master'!AG17 -> 73275.863 | K71: 5 | L71: Gross wages payble | O71: =E71 -> 73275.863
D72: EPF | E72: ESI | F72: PT | G72: TDS | H72: MEDICAL | I72: TOTAL | N72: EPF | O72: ESI | P72: PT | Q72: TDS | R72: MEDICAL | S72: TOTAL
A73: 6 | B73: Deductions, if any | D73: ='04-22-Master'!AI17 -> 1800 | E73: ='04-22-Master'!AH143 -> 0 | F73: ='04-22-Master'!AJ17 -> 200 | G73: ='04-22-Master'!AK17 -> 0 | H73: ='04-22-Master'!AL17 -> 391.78785 | I73: =D73+E73+F73+G73+H73 -> 2391.7878 | K73: 6 | L73: Deductions, if any | N73: =D73 -> 1800 | O73: =E73 -> 0 | P73: =F73 -> 200 | Q73: =G73 -> 0 | R73: =H73 -> 391.78785 | S73: =I73 -> 2391.7878
A75: 7 | B75: Net amount of wages paid | E75: =E71-I73 -> 70884.075 | K75: 7 | L75: Net amount of wages paid | O75: =E75 -> 70884.075
F79: Initial of the Contractor or his representative | P79: Initial of the Contractor or his representative
A97: Form XIX - WAGE SLIP | K97: Form XIX - WAGE SLIP
A98: [Vide rule 78 (1) (b) of the Contract Labour (Regulation and Abolition) Central and A.P Rules, 1971] | K98: [Vide rule 78 (1) (b) of the Contract Labour (Regulation and Abolition) Central and A.P Rules, 1971]
A100: Name and address of Contractor | D100: ='04-22-Master'!F5 -> Burgeon IT Services Pvt.Ltd. | K100: Name and address of Contractor | O100: =D100 -> Burgeon IT Services Pvt.Ltd.
B101: ='04-22-Master'!F6 -> Siri Mansion LIGB 436 Dr.A S Rao Nagar,Hyderabad | L101: =B101 -> Siri Mansion LIGB 436 Dr.A S Rao Nagar,Hyderabad
L102: =B102 -> 0
A103: Name and Father's / Husband's name of the workman | K103: Name and Father's / Husband's name of the workman
E104: ='04-22-Master'!B18 -> RUKNUDEEN S | H104: ='04-22-Master'!E18 -> SIRBUDIN.T | O104: =E104 -> RUKNUDEEN S | R104: =H104 -> SIRBUDIN.T
A106: Nature and location of work | E106: ='04-22-Master'!F8 -> IT SUPPORTIVE SERVICES & HYDERABAD SEZ | K106: Nature and location of work | O106: =E106 -> IT SUPPORTIVE SERVICES & HYDERABAD SEZ
A108: For the Week / Fortnight / Month ending | E108: ='04-22-Master'!D10 -> 44652 | K108: For the Week / Fortnight / Month ending | O108: =E108 -> 44652
A110: 1 | B110: No. of days worked | E110: ='04-22-Master'!Q18 -> 30 | K110: 1 | L110: No. of days worked | O110: =E110 -> 30
A112: 2 | B112: No. of units worked in case of piece rate workers : | K112: 2 | L112: No. of units worked in case of piece rate workers :
E113: N/A | O113: N/A
A115: 3 | B115: Rate of daily wages / piece rate | E115: N/A | K115: 3 | L115: Rate of daily wages / piece rate | O115: =E115 -> N/A
A117: 4 | B117: Amount of overtime wages | E117: Nil | K117: 4 | L117: Amount of overtime wages | O117: Nil
A119: 5 | B119: Gross wages payble | E119: ='04-22-Master'!AG18 -> 98276.285 | K119: 5 | L119: Gross wages payble | O119: =E119 -> 98276.285
D120: EPF | E120: ESI | F120: PT | G120: TDS | H120: MEDICAL | I120: TOTAL | N120: EPF | O120: ESI | P120: PT | Q120: TDS | R120: MEDICAL | S120: TOTAL
A121: 6 | B121: Deductions, if any | D121: 1800 | E121: ='04-22-Master'!AH385 -> 0 | F121: 200 | G121: ='04-22-Master'!AK18 -> 0 | H121: ='04-22-Master'!AL18 -> 391.78785 | I121: =D121+E121+F121+G121+H121 -> 2391.7878 | K121: 6 | L121: Deductions, if any | N121: =D121 -> 1800 | O121: =E121 -> 0 | P121: =F121 -> 200 | Q121: =G121 -> 0 | R121: =H121 -> 391.78785 | S121: =I121 -> 2391.7878
A123: 7 | B123: Net amount of wages paid | E123: =E119-I121 -> 95884.498 | K123: 7 | L123: Net amount of wages paid | O123: =E123 -> 95884.498
F127: Initial of the Contractor or his representative | P127: Initial of the Contractor or his representative
A145: Form XIX - WAGE SLIP | K145: Form XIX - WAGE SLIP
A146: [Vide rule 78 (1) (b) of the Contract Labour (Regulation and Abolition) Central and A.P Rules, 1971] | K146: [Vide rule 78 (1) (b) of the Contract Labour (Regulation and Abolition) Central and A.P Rules, 1971]
A148: Name and address of Contractor | D148: ='04-22-Master'!F5 -> Burgeon IT Services Pvt.Ltd. | K148: Name and address of Contractor | O148: =D148 -> Burgeon IT Services Pvt.Ltd.
B149: ='04-22-Master'!F6 -> Siri Mansion LIGB 436 Dr.A S Rao Nagar,Hyderabad | L149: =B149 -> Siri Mansion LIGB 436 Dr.A S Rao Nagar,Hyderabad
L150: =B150 -> 0
A151: Name and Father's / Husband's name of the workman | K151: Name and Father's / Husband's name of the workman
E152: ='04-22-Master'!B19 -> Srikanth Thota | H152: ='04-22-Master'!E19 -> Vasudha thota | O152: =E152 -> Srikanth Thota | Q152: =H152 -> Vasudha thota
A154: Nature and location of work | E154: ='04-22-Master'!F8 -> IT SUPPORTIVE SERVICES & HYDERABAD SEZ | K154: Nature and location of work | O154: =E154 -> IT SUPPORTIVE SERVICES & HYDERABAD SEZ
A156: For the Week / Fortnight / Month ending | E156: ='04-22-Master'!D10 -> 44652 | K156: For the Week / Fortnight / Month ending | O156: =E156 -> 44652
A158: 1 | B158: No. of days worked | E158: ='04-22-Master'!Q19 -> 30 | K158: 1 | L158: No. of days worked | O158: =E158 -> 30
A160: 2 | B160: No. of units worked in case of piece rate workers : | K160: 2 | L160: No. of units worked in case of piece rate workers :
E161: N/A | O161: N/A
A163: 3 | B163: Rate of daily wages / piece rate | E163: N/A | K163: 3 | L163: Rate of daily wages / piece rate | O163: =E163 -> N/A
A165: 4 | B165: Amount of overtime wages | E165: Nil | K165: 4 | L165: Amount of overtime wages | O165: Nil
A167: 5 | B167: Gross wages payble | E167: ='04-22-Master'!AG19 -> 113276.75 | K167: 5 | L167: Gross wages payble | O167: =E167 -> 113276.75
D168: EPF | E168: ESI | F168: PT | G168: TDS | H168: MEDICAL | I168: TOTAL | N168: EPF | O168: ESI | P168: PT | Q168: TDS | R168: MEDICAL | S168: TOTAL
A169: 6 | B169: Deductions, if any | D169: ='04-22-Master'!AI19 -> 1800 | E169: ='04-22-Master'!AH32 -> 0 | F169: ='04-22-Master'!AJ19 -> 200 | G169: ='04-22-Master'!AK19 -> 0 | H169: ='04-22-Master'!AL19 -> 377 | I169: =D169+E169+F169+G169+H169 -> 2377 | K169: 6 | L169: Deductions, if any | N169: =D169 -> 1800 | O169: =E169 -> 0 | P169: =F169 -> 200 | Q169: =G169 -> 0 | R169: =H169 -> 377 | S169: =I169 -> 2377
A171: 7 | B171: Net amount of wages paid | E171: =E167-I169 -> 110899.75 | K171: 7 | L171: Net amount of wages paid | O171: =E171 -> 110899.75
F175: Initial of the Contractor or his representative | P175: Initial of the Contractor or his representative
A186: Form XIX - WAGE SLIP | K186: Form XIX - WAGE SLIP
A187: [Vide rule 78 (1) (b) of the Contract Labour (Regulation and Abolition) Central and A.P Rules, 1971] | K187: [Vide rule 78 (1) (b) of the Contract Labour (Regulation and Abolition) Central and A.P Rules, 1971]
A189: Name and address of Contractor | D189: ='04-22-Master'!F5 -> Burgeon IT Services Pvt.Ltd. | K189: Name and address of Contractor | O189: =D189 -> Burgeon IT Services Pvt.Ltd.
B190: ='04-22-Master'!F6 -> Siri Mansion LIGB 436 Dr.A S Rao Nagar,Hyderabad | L190: =B190 -> Siri Mansion LIGB 436 Dr.A S Rao Nagar,Hyderabad
L191: =B191 -> 0
A192: Name and Father's / Husband's name of the workman | K192: Name and Father's / Husband's name of the workman
E193: ='04-22-Master'!B20 -> Shekhar Panchal | H193: ='04-22-Master'!E20 -> Naresh Kumar Panchal | O193: =E193 -> Shekhar Panchal | Q193: =H193 -> Naresh Kumar Panchal
A195: Nature and location of work | E195: ='04-22-Master'!F8 -> IT SUPPORTIVE SERVICES & HYDERABAD SEZ | K195: Nature and location of work | O195: =E195 -> IT SUPPORTIVE SERVICES & HYDERABAD SEZ
A197: For the Week / Fortnight / Month ending | E197: ='04-22-Master'!D10 -> 44652 | K197: For the Week / Fortnight / Month ending | O197: =E197 -> 44652
A199: 1 | B199: No. of days worked | E199: ='04-22-Master'!Q20 -> 30 | K199: 1 | L199: No. of days worked | O199: =E199 -> 30
A201: 2 | B201: No. of units worked in case of piece rate workers : | K201: 2 | L201: No. of units worked in case of piece rate workers :
E202: N/A | O202: N/A
A204: 3 | B204: Rate of daily wages / piece rate | E204: N/A | K204: 3 | L204: Rate of daily wages / piece rate | O204: =E204 -> N/A
A206: 4 | B206: Amount of overtime wages | E206: Nil | K206: 4 | L206: Amount of overtime wages | O206: Nil
A208: 5 | B208: Gross wages payble | E208: ='04-22-Master'!AG20 -> 73275.863 | K208: 5 | L208: Gross wages payble | O208: =E208 -> 73275.863
D209: EPF | E209: ESI | F209: PT | G209: TDS | H209: MEDICAL | I209: TOTAL | N209: EPF | O209: ESI | P209: PT | Q209: TDS | R209: MEDICAL | S209: TOTAL
A210: 6 | B210: Deductions, if any | D210: 1800 | E210: ='04-22-Master'!AH66 -> 0 | F210: 200 | G210: ='04-22-Master'!AK20 -> 0 | H210: ='04-22-Master'!AL20 -> 336 | I210: =D210+E210+F210+G210+H210 -> 2336 | K210: 6 | L210: Deductions, if any | N210: =D210 -> 1800 | O210: =E210 -> 0 | P210: =F210 -> 200 | Q210: =G210 -> 0 | R210: =H210 -> 336 | S210: =I210 -> 2336
A212: 7 | B212: Net amount of wages paid | E212: =E208-I210 -> 70939.863 | K212: 7 | L212: Net amount of wages paid | O212: =E212 -> 70939.863
F216: Initial of the Contractor or his representative | P216: Initial of the Contractor or his representative
A227: Form XIX - WAGE SLIP | K227: Form XIX - WAGE SLIP
A228: [Vide rule 78 (1) (b) of the Contract Labour (Regulation and Abolition) Central and A.P Rules, 1971] | K228: [Vide rule 78 (1) (b) of the Contract Labour (Regulation and Abolition) Central and A.P Rules, 1971]
A230: Name and address of Contractor | D230: Burgeon IT Services Pvt.Ltd. | K230: Name and address of Contractor | O230: =D230 -> Burgeon IT Services Pvt.Ltd.
B231: Siri Mansion LIGB 436 Dr.A S Rao Nagar,Hyderabad
L232: =B231 -> Siri Mansion LIGB 436 Dr.A S Rao Nagar,Hyderabad
...

Sheet APRIL 22-Bonus
A1: BONUS REGISTER
A3: FORM "c" ( See rule 4 [c] )
K4: Wage Period | L4: ='04-22-Master'!D10 -> 44652
A5: Name of the Establishment : _____________________________ | D5: ='04-22-Master'!F5 -> Burgeon IT Services Pvt.Ltd. | K5: Financial year _____ | M5: 2022-2023
A7: Sr. No | B7: Name of the Employee | C7: Father's Name / Husband's Name | D7: Whether he has completed 15 yrs of age at the beginning of the accounting year | E7: Designation | F7: No. of days worked in the year | G7: Total Salary or wages in the year | H7: Amt. of bonus payable under section 10 or section 11 as the case may be Ex gratia | I7: DEDUCTIONS | L7: Total Sum Deducted (Col. 9,10 and 11) | M7: Net Amount payable (Col. 8 minus Col. 12) | N7: Amount Actually paid | O7: Date on which paid | P7: Signature / Thumb impression of the employee
I8: Puja Bonus or other customary bonus paid during the accounting year | J8: Interim Bonus or bonus paid in advance | K8: Deduction on account of financial loss if any caused by misconduct of the employee | Q8: Account Number
A9: 1 | B9: 2 | C9: 3 | D9: 4 | E9: 5 | F9: 6 | H9: 8 | I9: 9 | J9: 10 | K9: 11 | L9: 12 | M9: 13 | N9: 14 | O9: 15 | P9: 16
A10: 1 | B10: ='04-22-Master'!P16 -> kaja Venkat Ragavendra | C10: ='04-22-Master'!E16 -> Kaja Suresh Babu | D10: YES | E10: ='04-22-Master'!F16 -> SR.Application Consultant | F10: ='04-22-Master'!Q16 -> 30 | G10: ='04-22-Master'!AG16 -> 93276.848 | H10: ='04-22-Master'!AC16 -> 1554.609 | I10: N/A | J10: N/A | K10: N/A | L10: N/A | M10: =H10 -> 1554.609 | N10: =M10 -> 1554.609 | O10: ='04-22-Master'!AP16 -> 44686 | P10: ='04-22-Master'!AQ16 -> KMB | Q10: ='04-22-Master'!AR16 -> A/C'6812236194
A11: 2 | B11: ='04-22-Master'!P17 -> VeerendraBabu Galam | C11: ='04-22-Master'!E17 -> Gopal Rao | D11: YES | E11: ='04-22-Master'!F17 -> Senior Test Engineer | F11: ='04-22-Master'!Q17 -> 30 | G11: ='04-22-Master'!AG17 -> 73275.863 | H11: ='04-22-Master'!AC17 -> 1554.609 | I11: N/A | J11: N/A | K11: N/A | L11: N/A | M11: =H11 -> 1554.609 | N11: =M11 -> 1554.609 | O11: ='04-22-Master'!AP17 -> 44686 | P11: ='04-22-Master'!AQ17 -> Standard chartered Bank | Q11: ='04-22-Master'!AR17 -> A/C'44511140919
A12: 3 | B12: ='04-22-Master'!P18 -> RUKNUDEEN S | C12: ='04-22-Master'!E18 -> SIRBUDIN.T | D12: YES | E12: ='04-22-Master'!F18 -> Technical consultant | F12: ='04-22-Master'!Q18 -> 30 | G12: ='04-22-Master'!AG18 -> 98276.285 | H12: ='04-22-Master'!AC18 -> 1554.609 | I12: N/A | J12: N/A | K12: N/A | L12: N/A | M12: =H12 -> 1554.609 | N12: =M12 -> 1554.609 | O12: ='04-22-Master'!AP18 -> 44686 | P12: ='04-22-Master'!AQ18 -> SBI | Q12: ='04-22-Master'!AR18 -> 39203094887
A13: 4 | B13: ='04-22-Master'!P19 -> Srikanth Thota | C13: ='04-22-Master'!E19 -> Vasudha thota | D13: YES | E13: ='04-22-Master'!F19 -> PMO Manager | F13: ='04-22-Master'!Q19 -> 30 | G13: ='04-22-Master'!AG19 -> 113276.75 | H13: ='04-22-Master'!AC19 -> 1554.609 | I13: N/A | J13: N/A | K13: N/A | L13: N/A | M13: =H13 -> 1554.609 | N13: =M13 -> 1554.609 | O13: ='04-22-Master'!AP19 -> 44686 | P13: ='04-22-Master'!AQ19 -> ICICI BANK | Q13: ='04-22-Master'!AR19 -> 020201513961
A14: 5 | B14: ='04-22-Master'!P20 -> Shekhar Panchal | C14: ='04-22-Master'!E20 -> Naresh Kumar Panchal | D14: YES | E14: ='04-22-Master'!F20 -> Sr. Network Security Engineer | F14: ='04-22-Master'!Q20 -> 30 | G14: ='04-22-Master'!AG20 -> 73275.863 | H14: ='04-22-Master'!AC20 -> 1554.609 | I14: N/A | J14: N/A | K14: N/A | L14: N/A | M14: =H14 -> 1554.609 | N14: =M14 -> 1554.609 | O14: ='04-22-Master'!AP20 -> 44686 | P14: ='04-22-Master'!AQ20 -> ICICI BANK | Q14: ='04-22-Master'!AR20 -> 346801502975
A15: 6 | B15: ='04-22-Master'!P21 -> Gangadhar Yarabham | C15: ='04-22-Master'!E21 -> Yarabham Savaraiah | D15: YES | E15: ='04-22-Master'!F21 -> Senior Specialist | F15: ='04-22-Master'!Q21 -> 30 | G15: ='04-22-Master'!AG21 -> 93275.769 | H15: ='04-22-Master'!AC21 -> 1554.609 | I15: N/A | J15: N/A | K15: N/A | L15: N/A | M15: =H15 -> 1554.609 | N15: =M15 -> 1554.609 | O15: ='04-22-Master'!AP21 -> 44686 | P15: ='04-22-Master'!AQ21 -> KOTAK BANK | Q15: ='04-22-Master'!AR21 -> A/C NUM:0745780762
A16: 7 | B16: ='04-22-Master'!P22 -> Nikhila Kaveri | C16: ='04-22-Master'!E22 -> Sreehari | D16: YES | E16: ='04-22-Master'!F22 -> TECHNICAL SOLUTION CONSULTANT | F16: ='04-22-Master'!Q22 -> 30 | G16: ='04-22-Master'!AG22 -> 118276.19 | H16: ='04-22-Master'!AC22 -> 1554.609 | I16: N/A | J16: N/A | K16: N/A | L16: N/A | M16: =H16 -> 1554.609 | N16: =M16 -> 1554.609 | O16: ='04-22-Master'!AP22 -> 44686 | P16: ='04-22-Master'!AQ22 -> HDFC BANK | Q16: ='04-22-Master'!AR22 -> HDFC0002770
A17: 8 | B17: ='04-22-Master'!P23 -> Thaposh Ghosh | C17: ='04-22-Master'!E23 -> CH Divya Vani | D17: YES | E17: ='04-22-Master'!F23 -> Incident Governance Manager | F17: ='04-22-Master'!Q23 -> 30 | G17: ='04-22-Master'!AG23 -> 153275.49 | H17: ='04-22-Master'!AC23 -> 1554.609 | I17: N/A | J17: N/A | K17: N/A | L17: N/A | M17: =H17 -> 1554.609 | N17: =M17 -> 1554.609 | O17: ='04-22-Master'!AP23 -> 44686 | P17: ='04-22-Master'!AQ23 -> AXIS BANK | Q17: ='04-22-Master'!AR23 -> 914010012727732
A18: 9 | B18: ='04-22-Master'!P24 -> Nagashree Narayan | C18: ='04-22-Master'!E24 -> KANTHA KAMBAIAH LAKSHMI | D18: YES | E18: ='04-22-Master'!F24 -> Technical Lead | F18: ='04-22-Master'!Q24 -> 29 | G18: ='04-22-Master'!AG24 -> 104722.62 | H18: ='04-22-Master'!AC24 -> 1554.609 | I18: N/A | J18: N/A | K18: N/A | L18: N/A | M18: =H18 -> 1554.609 | N18: =M18 -> 1554.609 | O18: ='04-22-Master'!AP24 -> 44686 | P18: ='04-22-Master'!AQ24 -> ICICI BANK | Q18: ='04-22-Master'!AR24 -> 098601510169
A19: 10 | B19: ='04-22-Master'!P25 -> ROOPINI CHIYYARAPU | C19: ='04-22-Master'!E25 -> C.ChandraReddy | D19: YES | E19: ='04-22-Master'!F25 -> Service Now Developer | F19: ='04-22-Master'!Q25 -> 30 | G19: ='04-22-Master'!AG25 -> 83275.816 | H19: ='04-22-Master'!AC25 -> 1554.609 | I19: N/A | J19: N/A | K19: N/A | L19: N/A | M19: =H19 -> 1554.609 | N19: =M19 -> 1554.609 | O19: ='04-22-Master'!AP25 -> 44686 | P19: ='04-22-Master'!AQ25 -> SBI | Q19: ='04-22-Master'!AR25 -> 39504382024
A20: 11 | B20: ='04-22-Master'!P26 -> D.Santhoshi | C20: ='04-22-Master'!E26 -> Srinivasu | D20: YES | E20: ='04-22-Master'!F26 -> SAP Basis Consultant | F20: ='04-22-Master'!Q26 -> 30 | G20: ='04-22-Master'!AG26 -> 43276.003 | H20: ='04-22-Master'!AC26 -> 1554.609 | I20: N/A | J20: N/A | K20: N/A | L20: N/A | M20: =H20 -> 1554.609 | N20: =M20 -> 1554.609 | O20: ='04-22-Master'!AP26 -> 44686 | P20: ='04-22-Master'!AQ26 -> INDIAN BANK | Q20: ='04-22-Master'!AR26 -> 6108665097
A21: 12 | B21: ='04-22-Master'!P27 -> Bharath | C21: ='04-22-Master'!E27 -> Mani ram | D21: YES | E21: ='04-22-Master'!F27 -> SAP Basis Consultant | F21: ='04-22-Master'!Q27 -> 30 | G21: ='04-22-Master'!AG27 -> 28246.404 | H21: ='04-22-Master'!AC27 -> 1554.609 | I21: N/A | J21: N/A | K21: N/A | L21: N/A | M21: =H21 -> 1554.609 | N21: =M21 -> 1554.609 | O21: ='04-22-Master'!AP27 -> 44686 | P21: ='04-22-Master'!AQ27 -> SBI | Q21: ='04-22-Master'!AR27 -> 34997967265
... A30: 21 | B30: ='04-22-Master'!P36 -> SADHAMHUSSAIN | C30: ='04-22-Master'!E36 -> Shahul Hameed | D30: YES | E30: ='04-22-Master'!F36 -> Security Administrator | F30: ='04-22-Master'!Q36 -> 6 | G30: ='04-22-Master'!AG36 -> 30989.298 | H30: ='04-22-Master'!AC36 -> 1554.609 | I30: N/A | J30: N/A | K30: N/A | L30: N/A | M30: =H30 -> 1554.609 | N30: =M30 -> 1554.609 | O30: ='04-22-Master'!AP36 -> 44686 | P30: ='04-22-Master'!AQ36 -> HDFC BANK | Q30: ='04-22-Master'!AR36 -> 50100271012409
L34: Signature of the Contractor with Seal

Sheet Deds
A1: FORM XX- REGISTER OF DEDUCTIONS FOR DAMAGE OR LOSS
A3: (Vide Rule 78(1) (a) (i) of Contract Labour (Regulation and Abolition) Central /A.P.Rules 1971
A4: Name and address of Contractor: | D4: ='04-22-Master'!F5 -> Burgeon IT Services Pvt.Ltd. | E4: Name and address of the establishment in / under which contract is carried on:
B5: ='04-22-Master'!F6 -> Siri Mansion LIGB 436 Dr.A S Rao Nagar,Hyderabad
B6: ='04-22-Master'!F7 -> 0
A7: Nature and Location of Work: | D7: ='04-22-Master'!F8 -> IT SUPPORTIVE SERVICES & HYDERABAD SEZ | E7: Name and address of principal employer:
E8: ='04-22-Master'!AJ10 -> INFOSYS LTD.IL Hyderabad SEZ
E9: ='04-22-Master'!AJ11 -> Sy.No 42,Pocharam Village,Gatkesar Mandal
A11: S.No | B11: Name of workman | C11: Father's / Husband's Name | D11: Designation / Nature of employment | E11: Particulars of damage or loss | F11: Date of Damage or loss | G11: Whether workman showed cause against deduction | H11: Name of person in whose presence employee's explanation was heard | I11: Amount of deduction impossed | J11: Date of recovery | M11: Remarks
J12: No.of Instalments | K12: First Instalment | L12: Last instalment
A13: 1 | B13: 2 | C13: 3 | D13: 4 | E13: 5 | F13: 6 | G13: 7 | H13: 8 | I13: 9 | J13: 10 | K13: 11 | L13: 12 | M13: 13
B16: NO EMPLOYEE WAS IMPOSED DEDUCTIONS FOR DAMAGE OR LOSS FOR THE MONTH OF | H16: ='04-22-Master'!D10 -> 44652
J41: Signature of the Contractor with Seal

Sheet Serive Certificate
B1: FORM XV
B2: [Vide rule 77 of Contract Labour (Regul. & Abolition) Central & A.P. Rules, 1971]
B4: SERVICE CERTIFICATE
B6: Name and address of Contractor : | G6: Name and address of establishment in / under which contract is caried on :
B8: ='04-22-Master'!F5 -> Burgeon IT Services Pvt.Ltd. | G8: ='04-22-Master'!AJ5 -> Burgeon IT Services Pvt.Ltd.
B10: ='04-22-Master'!F6 -> Siri Mansion LIGB 436 Dr.A S Rao Nagar,Hyderabad | G10: ='04-22-Master'!AJ6 -> Siri Mansion LIGB 436 Dr.A S Rao Nagar,Hyderabad
B14: Nature and Location of work: | G14: Name and address of Principal Employer :
G16: ='04-22-Master'!AJ10 -> INFOSYS LTD.IL Hyderabad SEZ
B18: ='04-22-Master'!F8 -> IT SUPPORTIVE SERVICES & HYDERABAD SEZ | G18: ='04-22-Master'!AJ11 -> Sy.No 42,Pocharam Village,Gatkesar Mandal
B23: Name and address of the workman :
B28: Age or date of Birth :
B30: Identification Marks :
B32: Father's / Husband's Name :
B35: Sl.No. | C35: Total period for which employed | E35: Nature of work done | G35: Rate of wage ( with particulars of units in case of piece work) | J35: Remarks
C37: From | D37: To
B38: 1 | C38: 2 | D38: 3 | E38: 4 | G38: 5 | J38: 6
H53: Signature of the Employer with Seal

Sheet Fines
A1: FORM XXI- REGISTER OF FINES
A3: (Vide Rule 78(1) (a) (i) of Contract Labour (Regulation and Abolition) Central /A.P.Rules. 1971
A4: Name and address of Contractor: | D4: ='04-22-Master'!F5 -> Burgeon IT Services Pvt.Ltd. | E4: Name and address of the establishment in / under which contract is carried on:
B5: ='04-22-Master'!F6 -> Siri Mansion LIGB 436 Dr.A S Rao Nagar,Hyderabad
B6: ='04-22-Master'!F7 -> 0
A7: Nature and Location of Work: | D7: ='04-22-Master'!F8 -> IT SUPPORTIVE SERVICES & HYDERABAD SEZ | E7: Name and address of principal employer:
E8: ='04-22-Master'!AJ10 -> INFOSYS LTD.IL Hyderabad SEZ
E9: ='04-22-Master'!AJ11 -> Sy.No 42,Pocharam Village,Gatkesar Mandal
A11: S.No | B11: Name of workman | C11: Father's / Husband's Name | D11: Designation / Nature of employment | E11: Act/Omission for which fine imposed | F11: Date of offence | G11: Whether workman showed cause against fine | H11: Name of person in whose presence employee's explanation was heard | I11: Wage-period and wge payable | J11: Amount of fine Imposed | K11: Date on which fine realised | L11: Remarks
A13: 1 | B13: 2 | C13: 3 | D13: 4 | E13: 5 | F13: 6 | G13: 7 | H13: 8 | I13: 9 | J13: 10 | K13: 11 | L13: 12
B16: NO EMPLOYEE WAS IMPOSED FINESFOR THE MONTH OF | H16: ='04-22-Master'!D10 -> 44652
F40: Signature of the Contractor with Seal

Sheet Advances
A1: FORM XXII- REGISTER OF ADVANCES
A3: (Vide Rule 78(1) (a) (i) of Contract Labour (Regulation and Abolition) Central /A.P.Rules 1971
A4: Name and address of Contractor: | D4: ='04-22-Master'!F5 -> Burgeon IT Services Pvt.Ltd. | E4: Name and address of the establishment in / under which contract is carried on:
B5: ='04-22-Master'!F6 -> Siri Mansion LIGB 436 Dr.A S Rao Nagar,Hyderabad
B6: ='04-22-Master'!F7 -> 0
A7: Nature and Location of Work: | D7: ='04-22-Master'!F8 -> IT SUPPORTIVE SERVICES & HYDERABAD SEZ | E7: Name and address of principal employer:
E8: ='04-22-Master'!AJ10 -> INFOSYS LTD.IL Hyderabad SEZ
E9: ='04-22-Master'!AJ11 -> Sy.No 42,Pocharam Village,Gatkesar Mandal
A11: S.No | B11: Name of workman | C11: Father's / Husband's Name | D11: Designation / Nature of employment | E11: Wage period and wages payable | F11: Date and amount of advance given | G11: Purpose(s) for which advance made | H11: Number of instalments by which advance to be repaid | I11: Date and amount of each instalment repaid | J11: Date on which last instalment was repaid | K11: Remarks
A13: 1 | B13: 2 | C13: 3 | D13: 4 | E13: 5 | F13: 6 | G13: 7 | H13: 8 | I13: 9 | J13: 10 | K13: 11
B16: NO EMPLOYEE TAKEN ADVANCE FOR THE MONTH OF | F16: ='04-22-Master'!D10 -> 44652
G37: Signature of the Contractor with Seal

Sheet Overtime
A1: FORM XXIII- REGISTER OF OVERTIME
A3: (Vide Rule 78(1) (a) (i) of Contract Labour (Regulation and Abolition) Central /A.P.Rules. 1971
A4: Name and address of Contractor: E-35 GREATER KAILASH ENCLAVE-1 NEW DELHI | D4: ='04-22-Master'!F5 -> Burgeon IT Services Pvt.Ltd. | F4: Name and address of the establishment in which under contract is carried on:
B5: ='04-22-Master'!F6 -> Siri Mansion LIGB 436 Dr.A S Rao Nagar,Hyderabad
B6: ='04-22-Master'!F7 -> 0
A7: Nature and Location of Work: | D7: ='04-22-Master'!F8 -> IT SUPPORTIVE SERVICES & HYDERABAD SEZ | F7: Name and address of principal employer:
F8: ='04-22-Master'!AJ10 -> INFOSYS LTD.IL Hyderabad SEZ
F9: ='04-22-Master'!AJ11 -> Sy.No 42,Pocharam Village,Gatkesar Mandal
A11: S.No | B11: Name of workman | C11: Father's / Husband's Name | D11: Sex | E11: Designation / Nature of employment | F11: Date on which overtime worked | G11: Total overtime worked or production in case of piece-rates | H11: Normal rate of wages | I11: Overtime rate of wages | J11: overtime earnings | K11: Date on which overtime wages paid | L11: Remarks
A13: 1 | B13: 2 | C13: 3 | D13: 4 | E13: 5 | F13: 6 | G13: 7 | H13: 8 | I13: 9 | J13: 10 | K13: 11 | L13: 12
B16: NO EMPLOYEE DONE OVERTIME FOR THE MONTH OF | F16: ='04-22-Master'!D10 -> 44652
I38: Signature of the Contractor with Seal

Sheet Accident
A1: FORM 11
A3: ACCIDENT BOOK
A4: EMPLOYEE STATE INSURANCE CORPORATION
B5: (Regulation 66)
A7: S.No | B7: Date of Notice | C7: Time of Notice | D7: Name and Address of the Injured Person | E7: Sex | F7: Age | H7: Shift,Department and occupation of employee | I7: Details of Injury | P7: Signature and designation of the person who makes the entry in the accident book | Q7: Name,address and occupation of the two witnesses | R7: Remarks if any
G8: Insurance Number | N8: What exactly was the injured person doing at the time of accident | O8: Name,Occupation,address and signature or the thumb impression of the person(s) giving notice
I9: Cause | J9: Nature | K9: Date | L9: Time | M9: Place
A10: 1 | B10: 2 | C10: 3 | D10: 4 | E10: 5 | F10: 6 | G10: 7 | H10: 8 | I10: 9 | J10: 10 | K10: 11 | L10: 12 | M10: 13 | N10: 14 | O10: 15 | P10: 16 | Q10: 17 | R10: 18
B12: NO ACCIDENT OCCURRED FOR THE MONTH OF | F12: ='04-22-Master'!D10 -> 44652
J27: Signature of the Contractor with Seal

Sheet FORM A
B1: FORM A
B2: [See Rule 3 of Maternity Act Rules, 1965]
B3: MUSTER ROLL
B4: Name of [mine or circus]: | D4: ='04-22-Master'!F5 -> Burgeon IT Services Pvt.Ltd. | E4: ='04-22-Master'!F6 -> Siri Mansion LIGB 436 Dr.A S Rao Nagar,Hyderabad
B5: 1 | C5: Serial Number.
B6: 2 | C6: Name of woman and her father's (or, if married, husband's) name.
B7: 3 | C7: Date of appointment.
B8: 4 | C8: Nature of work.
B9: 5 | C9: Dates with month and year in which she is employed, laid off and not employed.
C10: Month | D10: No.of days employed | E10: No.of days laid off | F10: No.of days not employed | G10: Remarks
B17: 6 | C17: Date on which the woman gives notice under section 6.
B18: 7 | C18: Date of discharge/dismissal, if any.
B19: 8 | C19: Date of production of proof of pregnancy under section 6.
B20: 9 | C20: Date of birth of child.
B21: 10 | C21: Date of production of proof of delivery/miscarriage/ 1[Medical Termination of pregnancy/ tubectomy operation/death.]
B22: 11 | C22: Date of production of proof of illness referred to in section 10.
B23: 12 | C23: Date with the amount of maternity benefit paid in advance of expected delivery.
B24: 13 | C24: Date with the amount of subsequent payment of maternity benefit.
B25: 14 | C25: Date with the amount of bonus, if paid, under section 8.
B26: 15 | C26: Date with the amount of wages paid on account of leave under section 9.
B27: 15A | C27: Date with the amount of wages paid on account of leave under section 9A
B28: 16 | C28: Date with the amount of wages paid on account of leave under section 10 and period of leave granted
B29: 17 | C29: Name of the person nominated by the woman under section 6.
B30: 18 | C30: If the woman dies, the date of her death, the name of the person to whom maternity benefit and/or other amount was paid, the amount thereof, and the date of payment.
B31: 19 | C31: If the woman dies and the child survives, the name of the person to whom the amount of maternity benefit was paid on behalf of the child and the period for which it was paid.
B32: 20 | C32: Signature of the employer of 3[the mine or circus] authenticating the entries in the muster-roll.
B33: 21 | C33: Remarks column for the use of the Inspector.
B34: Certifited that no pregnant employee worked for the month of | G34: ='04-22-Master'!D10 -> 44652
E36: For | F36: ='04-22-Master'!F5 -> Burgeon IT Services Pvt.Ltd.
F38: Authorized Signatory

Sheet FORM B
B1: FORM B
B2: [See Rule 4(1) of Maternity Act Rules, 1965]
B3: Name of [mine or circus]: | D3: ='04-22-Master'!F5 -> Burgeon IT Services Pvt.Ltd. | E3: ='04-22-Master'!F6 -> Siri Mansion LIGB 436 Dr.A S Rao Nagar,Hyderabad
B6: This is to certify that I examined…. wife /daughter of ….. a woman employee in name of Mine or Circus on (Date)
D7: and found/ cannot discover that she is pregnant and is expected to be delivered of a child within (month/days) from the above
B8: mentioned date date/has undergone miscarriage/[Medical termination of pregnancy or tubectomy operation]/has been delivered
B9: of a child on….. (date) or is suffering from…..(date) from illness arising out of pregnancy/delivery/premature birth of a child or miscarriage/
B10: [Medical termination of pregnancy or tubectomy operation ].
D12: Signature, qualifications and designation of Medical Officer/Medical Practitioner.
B15: Date…..
B16: Definitions of "child" and "miscarriage" as in the Maternity Benefit Act, 1961.-
B17: 1. "Child" includes a still-born child.
B18: 2. "Miscarriage" means expulsion of the contents of a pregnant uterus at any period prior to or during the twenty-sixth week of pregnancy
B19: but does not include any miscarriage,the causing of which is punishable under the Indian Penal Code.
B20: Ins. by G.S.R. 70(E), dated 31st January, 1996 (w.e.f. 31-1-1996).
B22: Certifited that no pregnant employee worked for the month of | G22: ='04-22-Master'!D10 -> 44652
E25: For | F25: ='04-22-Master'!F5 -> Burgeon IT Services Pvt.Ltd.
F27: Authorized Signatory

Sheet FORM C
B1: FORM C
B2: [See Rule 4(4) of Maternity Act Rules, 1965]
B4: Name of [mine or circus]: | D4: ='04-22-Master'!F5 -> Burgeon IT Services Pvt.Ltd. | E4: ='04-22-Master'!F6 -> Siri Mansion LIGB 436 Dr.A S Rao Nagar,Hyderabad
B7: This is to certify that
B8: Smt……………………………….wife/daughter of ……………………….employed in ……………….(name of [Mine or Circus]
B9: expired on ……………………..before/during/after confinement. The child died on …./survives her.
D13: Signature, qualifications and designation of Medical Officer/Medical Practitioner.
C15: Ins. by G.S.R. 70(E), dated 31st January, 1996 (w.e.f. 31-1-1996).
B17: Certifited that no pregnant employee worked for the month of | G17: ='04-22-Master'!D10 -> 44652
E20: For | F20: ='04-22-Master'!F5 -> Burgeon IT Services Pvt.Ltd.
F22: Authorized Signatory

Sheet FORM D
B1: FORM D
B2: [See Rule 4(5) of Maternity Act Rules, 1965]
B4: Name of [mine or circus]: | D4: ='04-22-Master'!F5 -> Burgeon IT Services Pvt.Ltd. | E4: ='04-22-Master'!F6 -> Siri Mansion LIGB 436 Dr.A S Rao Nagar,Hyderabad
B7: This is to certify that I examined……………..wife/daughter of ……….a woman employed in ………..(name of [Mine or Circus ]
B8: and found that she has been delivered of a child/has undergone miscarriage on ….(date)
E11: Signature of registered Midwife
C13: Date….
C14: Definitions of "child" and "miscarriage" as in the Maternity Benefit Act, 1961-
C15: 1. "Child" includes a still-born child.
C16: 2. "Miscarriage" means expulsion of the contents of a pregnant uterus at any period prior to or during the twenty-sixth
C17: week of pregnancy but does not include any miscarriage, the causing of which is punishable under the Indian Penal Code.
C20: Subs. by G.S.R. 59(E), dated 27th February, 1975 (w.e.f. 1-3-1975).
B22: Certifited that no pregnant employee worked for the month of | G22: ='04-22-Master'!D10 -> 44652
E25: For | F25: ='04-22-Master'!F5 -> Burgeon IT Services Pvt.Ltd.
F27: Authorized Signatory

Sheet ESI cards Reg
C1: ='04-22-Master'!F5 -> Burgeon IT Services Pvt.Ltd. | E1: ESI PAHECHAN CARDS ISSUE REGISTER
B2: S.No | C2: Name of the Employee | D2: ESI Number | E2: Issue Date | F2: Signature | G2: Remarks
B3: 1 | C3: ='04-22-Master'!#REF! -> #REF! | D3: ='04-22-Master'!#REF! -> #REF!
B4: 2 | C4: ='04-22-Master'!#REF! -> #REF! | D4: ='04-22-Master'!#REF! -> #REF!
B5: 3 | C5: ='04-22-Master'!#REF! -> #REF! | D5: ='04-22-Master'!#REF! -> #REF!
B6: 4 | C6: ='04-22-Master'!#REF! -> #REF! | D6: ='04-22-Master'!#REF! -> #REF!
B7: 5 | C7: ='04-22-Master'!#REF! -> #REF! | D7: ='04-22-Master'!#REF! -> #REF!
B8: 6 | C8: ='04-22-Master'!#REF! -> #REF! | D8: ='04-22-Master'!#REF! -> #REF!
B9: 7 | C9: ='04-22-Master'!#REF! -> #REF! | D9: ='04-22-Master'!#REF! -> #REF!
B10: 8 | C10: ='04-22-Master'!#REF! -> #REF! | D10: ='04-22-Master'!#REF! -> #REF!
B11: 9 | C11: ='04-22-Master'!#REF! -> #REF! | D11: ='04-22-Master'!#REF! -> #REF!
B12: 10 | C12: ='04-22-Master'!#REF! -> #REF! | D12: ='04-22-Master'!#REF! -> #REF!
B13: 11 | C13: ='04-22-Master'!#REF! -> #REF! | D13: ='04-22-Master'!#REF! -> #REF!
B14: 12 | C14: ='04-22-Master'!#REF! -> #REF! | D14: ='04-22-Master'!#REF! -> #REF!
B15: 13 | C15: =[4]LEFT!U3 -> Bharath Dommaraju | D15: =[4]LEFT!T3 -> N/A
B16: 14 | C16: =[4]LEFT!U4 -> #REF! | D16: =[4]LEFT!T4 -> #REF!
B17: 15 | C17: =[4]LEFT!U5 -> #REF! | D17: =[4]LEFT!T5 -> #REF!
B18: 16 | C18: =[4]LEFT!U6 -> #REF! | D18: =[4]LEFT!T6 -> #REF!
B19: 17 | C19: =[4]LEFT!U7 -> #REF! | D19: =[4]LEFT!T7 -> #REF!
B20: 18 | C20: =[4]LEFT!U8 -> #REF! | D20: =[4]LEFT!T8 -> #REF!
B21: 19 | C21: =[4]LEFT!U9 -> #REF! | D21: =[4]LEFT!T9 -> #REF!
B22: 20 | C22: =[4]LEFT!U10 -> #REF! | D22: =[4]LEFT!T10 -> #REF!

Sheet Form-I
B1: FORM I
B2: NOMINATION AND DECLARATION FORM
B3: (Vide Rule 3 of Payment of wages Act Central & A.P Rules, 1936)
B4: Name and Address of the Contractor | H4: Name and Address of the Establishment in/under which Contract is carried on:
B7: =#REF! -> #REF! | H7: =#REF! -> #REF!
B9: =#REF! -> #REF! | H9: =#REF! -> #REF!
B12: Nature of work and location of work: | H12: Name and address of Principal Employer:
H15: =#REF! -> #REF!
B16: =#REF! -> #REF!
H17: =#REF! -> #REF!
B19: 1. Name of the person making nomination | H19: ='04-22-Master'!#REF! -> #REF!
B20: 2. Father's/Husband name | H20: ='04-22-Master'!#REF! -> #REF!
B21: 3. Date of Birth | H21: ='04-22-Master'!#REF! -> #REF!
B22: 4. Sex | H22: ='04-22-Master'!#REF! -> #REF!
B23: 5. Marital Status | H23: Un-Married
B24: 6.Address
B25: Permanent | H25: ='04-22-Master'!#REF! -> #REF!
H26: ='04-22-Master'!#REF! -> #REF!
H27: ='04-22-Master'!#REF! -> #REF!
B28: Temporary | H28: ='04-22-Master'!#REF! -> #REF!
H29: ='04-22-Master'!#REF! -> #REF!
H30: ='04-22-Master'!#REF! -> #REF!
B31: I hereby nominate the person(s)/cancel the nomination made by me previously and nominate the person(s) mentioned below to
B32: receive any amount due to me from the employer,in the event to my death.
B33: Name of the Nominee/nominees | E33: Address | G33: Nominee's relationship With the member | I33: Date of Birth | J33: Total amount of Share of accumulations | K33: If the nominee is minor,name,relationship and address of the guardian
B34: 1 | E34: 2 | G34: 3 | I34: 4 | J34: 5 | L34: 6
B35: ='04-22-Master'!#REF! -> #REF! | E35: Same as permanant address | G35: Father | I35: 54 years | J35: 1 | K35: N/A
B39: 1.Certified that I have no family and should I acquire a family hereafter,the above nomination shall be deemed as cancelled.
B40: 2.Certified that my father/mother is/ are dependent upon me.
B41: 3.Strike out whichever is not applicable.
I43: Signature or the thumb impression of the employed person
F44: CERTIFCATE BY EMPLOYER
A45: Certified that the above declaration and nomination has been signed/thumb impressed before me by Shri/Smt/Kum | K45: ='04-22-Master'!#REF! -> #REF!
A46: employed in my establishment after he/she has read the entry/entries have been read over to him/her by me and got confirmed by him/her.
F49: Signature or the employer or other authorized officer of the establiment and Designation
A50: Place | B50: Hyderabad | F50: ='04-22-Master'!AJ5 -> Burgeon IT Services Pvt.Ltd.
A51: Date | B51: ='04-22-Master'!#REF! -> #REF! | F51: ='04-22-Master'!AJ6 -> Siri Mansion LIGB 436 Dr.A S Rao Nagar,Hyderabad
B53: FORM I
B54: NOMINATION AND DECLARATION FORM
B55: (Vide Rule 3 of Payment of wages Act Central & A.P Rules, 1936)
B56: Name and Address of the Contractor | H56: Name and Address of the Establishment in/under which Contract is carried on:
B59: ='04-22-Master'!F5 -> Burgeon IT Services Pvt.Ltd. | H59: ='04-22-Master'!AJ5 -> Burgeon IT Services Pvt.Ltd.
B61: ='04-22-Master'!F6 -> Siri Mansion LIGB 436 Dr.A S Rao Nagar,Hyderabad | H61: ='04-22-Master'!AJ6 -> Siri Mansion LIGB 436 Dr.A S Rao Nagar,Hyderabad
B64: Nature of work and location of work: | H64: Name and address of Principal Employer:
H67: ='04-22-Master'!AJ10 -> INFOSYS LTD.IL Hyderabad SEZ
B68: ='04-22-Master'!F8 -> IT SUPPORTIVE SERVICES & HYDERABAD SEZ
H69: ='04-22-Master'!AJ11 -> Sy.No 42,Pocharam Village,Gatkesar Mandal
B71: 1. Name of the person making nomination | H71: ='04-22-Master'!#REF! -> #REF!
B72: 2. Father's/Husband name | H72: ='04-22-Master'!#REF! -> #REF!
B73: 3. Date of Birth | H73: ='04-22-Master'!#REF! -> #REF!
B74: 4. Sex | H74: ='04-22-Master'!#REF! -> #REF!
B75: 5. Marital Status | H75: Un-Married
B76: 6.Address
B77: Permanent | H77: ='04-22-Master'!#REF! -> #REF!
H78: ='04-22-Master'!#REF! -> #REF!
H79: ='04-22-Master'!#REF! -> #REF!
B80: Temporary | H80: ='04-22-Master'!#REF! -> #REF!
H81: ='04-22-Master'!#REF! -> #REF!
H82: ='04-22-Master'!#REF! -> #REF!
B83: I hereby nominate the person(s)/cancel the nomination made by me previously and nominate the person(s) mentioned below to
B84: receive any amount due to me from the employer,in the event to my death.
B85: Name of the Nominee/nominees | E85: Address | G85: Nominee's relationship With the member | I85: Date of Birth | J85: Total amount of Share of accumulations | K85: If the nominee is minor,name,relationship and address of the guardian
B86: 1 | E86: 2 | G86: 3 | I86: 4 | J86: 5 | L86: 6
B87: ='04-22-Master'!#REF! -> #REF! | E87: Same as permanant address | G87: Father | I87: 54 years | J87: 1 | K87: N/A
B91: 1.Certified that I have no family and should I acquire a family hereafter,the above nomination shall be deemed as cancelled.
B92: 2.Certified that my father/mother is/ are dependent upon me.
B93: 3.Strike out whichever is not applicable.
I95: Signature or the thumb impression of the employed person
F96: CERTIFCATE BY EMPLOYER
A97: Certified that the above declaration and nomination has been signed/thumb impressed before me by Shri/Smt/Kum | K97: ='04-22-Master'!#REF! -> #REF!
A98: employed in my establishment after he/she has read the entry/entries have been read over to him/her by me and got confirmed by him/her.
F101: Signature or the employer or other authorized officer of the establiment and Designation
A102: Place | B102: Hyderabad | F102: ='04-22-Master'!F5 -> Burgeon IT Services Pvt.Ltd.
A103: Date | B103: ='04-22-Master'!#REF! -> #REF! | F103: ='04-22-Master'!F6 -> Siri Mansion LIGB 436 Dr.A S Rao Nagar,Hyderabad
B107: FORM I
B108: NOMINATION AND DECLARATION FORM
B109: (Vide Rule 3 of Payment of wages Act Central & A.P Rules, 1936)
B110: Name and Address of the Contractor | H110: Name and Address of the Establishment in/under which Contract is carried on:
B113: ='04-22-Master'!F5 -> Burgeon IT Services Pvt.Ltd. | H113: ='04-22-Master'!AJ5 -> Burgeon IT Services Pvt.Ltd.
B115: ='04-22-Master'!F6 -> Siri Mansion LIGB 436 Dr.A S Rao Nagar,Hyderabad | H115: ='04-22-Master'!AJ6 -> Siri Mansion LIGB 436 Dr.A S Rao Nagar,Hyderabad
B118: Nature of work and location of work: | H118: Name and address of Principal Employer:
H121: ='04-22-Master'!AJ10 -> INFOSYS LTD.IL Hyderabad SEZ
B122: ='04-22-Master'!F8 -> IT SUPPORTIVE SERVICES & HYDERABAD SEZ
H123: ='04-22-Master'!AJ11 -> Sy.No 42,Pocharam Village,Gatkesar Mandal
B125: 1. Name of the person making nomination | H125: ='04-22-Master'!#REF! -> #REF!
B126: 2. Father's/Husband name | H126: ='04-22-Master'!#REF! -> #REF!
B127: 3. Date of Birth | H127: ='04-22-Master'!#REF! -> #REF!
B128: 4. Sex | H128: ='04-22-Master'!#REF! -> #REF!
B129: 5. Marital Status | H129: Un-Married
B130: 6.Address
B131: Permanent | H131: ='04-22-Master'!#REF! -> #REF!
H132: ='04-22-Master'!#REF! -> #REF!
H133: ='04-22-Master'!#REF! -> #REF!
B134: Temporary | H134: ='04-22-Master'!#REF! -> #REF!
H135: ='04-22-Master'!#REF! -> #REF!
H136: ='04-22-Master'!#REF! -> #REF!
B137: I hereby nominate the person(s)/cancel the nomination made by me previously and nominate the person(s) mentioned below to
B138: receive any amount due to me from the employer,in the event to my death.
B139: Name of the Nominee/nominees | E139: Address | G139: Nominee's relationship With the member | I139: Date of Birth | J139: Total amount of Share of accumulations | K139: If the nominee is minor,name,relationship and address of the guardian
B140: 1 | E140: 2 | G140: 3 | I140: 4 | J140: 5 | L140: 6
...

Sheet Form-2
K1: (FORM 2 REVISED)
B2: NOMINATION AND DECLARATION FORM FOR UNEXEMPTED/EXEMPTED ESTABLISHMENTS
B3: Declaration and Nomination Form under the Employees Provident Funds and Employees Pension Schemes
B4: (Paragraph 33 and 61(1) of the Employees Provident Fund Scheme 1952 and Paragraph 18 of the Employees Pension Scheme 1995)
B6: 1. Name of the person making nomination | H6: ='04-22-Master'!#REF! -> #REF!
B7: 2. Father's/Husband name | H7: ='04-22-Master'!#REF! -> #REF!
B8: 3. Date of Birth | H8: ='04-22-Master'!#REF! -> #REF!
B9: 4. Sex | H9: ='04-22-Master'!#REF! -> #REF!
B10: 5. Marital Status | H10: Un-Married
B11: 6.Address
B12: Permanent | H12: ='04-22-Master'!#REF! -> #REF!
H13: ='04-22-Master'!#REF! -> #REF!
H14: ='04-22-Master'!#REF! -> #REF!
G15: PART-A(EPF)
B16: I hereby nominate the person(s)/cancel the nomination made by me previously and nominate the person(s) mentioned below to
B17: receive any amount due to me from the employer,in the event to my death.
B18: Name of the Nominee/nominees | E18: Address | G18: Nominee's relationship With the member | I18: Date of Birth | J18: Total amount of Share of accumulations | K18: If the nominee is minor,name,relationship and address of the guardian
B19: 1 | E19: 2 | G19: 3 | I19: 4 | J19: 5 | L19: 6
B20: ='04-22-Master'!#REF! -> #REF! | E20: Same as Permanant Address | G20: Father | I20: 55 Years | J20: 1 | K20: N/A
B24: 1.Certified that I have no family and should I acquire a family hereafter,the above nomination shall be deemed as cancelled.
B25: 2.Certified that my father/mother is/ are dependent upon me.
B26: Strike out whichever is not applicable | J26: Signature/or thumb impression of the subscriber
G27: PART (EPS)
G28: Para 18
B29: I hereby furnish below particulars of the members of my family who would be eligible to receive Widow/Children Pension in the event of
B30: my premature death in service
B31: S.No | C31: Name & Address of the Family Member | I31: Age | J31: Relationship with the member
B32: 1 | E32: 2 | I32: 3 | K32: 4
B37: Certified that I have no family as defined in para 2 (vii) of the Employees's Family Pension Scheme 1995 and should I acquire a family hereafter
B38: I shall furnish Particulars there on in the above form.
B39: I hereby nominate the following person for receiving the monthly widow pension (admissible under para 16 2 (a) (1) & (ii) in the even of my death
B40: without leaving any eligible member for receiving pension.
B41: Name and Address of the nominee | G41: Date of Birth | I41: Relationship with member
B47: Date | C47: ='04-22-Master'!#REF! -> #REF! | I47: Signature or thumb impression of the subscriber
F48: CERTIFCATE BY EMPLOYER
A49: Certified that the above declaration and nomination has been signed/thumb impressed before me by Shri/Smt/Kum | K49: ='04-22-Master'!#REF! -> #REF!
A50: employed in my establishment after he/she has read the entry/entries have been read over to him/her by me and got confirmed by him/her.
F52: Signature or the employer or other authorized officer of the establiment and Designation
A53: Place | B53: Hyderabad | F53: ='04-22-Master'!F5 -> Burgeon IT Services Pvt.Ltd.
A54: Date | B54: ='04-22-Master'!#REF! -> #REF! | F54: ='04-22-Master'!F6 -> Siri Mansion LIGB 436 Dr.A S Rao Nagar,Hyderabad
K55: (FORM 2 REVISED)
B56: NOMINATION AND DECLARATION FORM FOR UNEXEMPTED/EXEMPTED ESTABLISHMENTS
B57: Declaration and Nomination Form under the Employees Provident Funds and Employees Pension Schemes
B58: (Paragraph 33 and 61(1) of the Employees Provident Fund Scheme 1952 and Paragraph 18 of the Employees Pension Scheme 1995)
B60: 1. Name of the person making nomination | H60: ='04-22-Master'!#REF! -> #REF!
B61: 2. Father's/Husband name | H61: ='04-22-Master'!#REF! -> #REF!
B62: 3. Date of Birth | H62: ='04-22-Master'!#REF! -> #REF!
B63: 4. Sex | H63: ='04-22-Master'!#REF! -> #REF!
B64: 5. Marital Status | H64: Un-Married
B65: 6.Address
B66: Permanent | H66: ='04-22-Master'!#REF! -> #REF!
H67: ='04-22-Master'!#REF! -> #REF!
H68: ='04-22-Master'!#REF! -> #REF!
G69: PART-A(EPF)
B70: I hereby nominate the person(s)/cancel the nomination made by me previously and nominate the person(s) mentioned below to
B71: receive any amount due to me from the employer,in the event to my death.
B72: Name of the Nominee/nominees | E72: Address | G72: Nominee's relationship With the member | I72: Date of Birth | J72: Total amount of Share of accumulations | K72: If the nominee is minor,name,relationship and address of the guardian
B73: 1 | E73: 2 | G73: 3 | I73: 4 | J73: 5 | L73: 6
B74: ='04-22-Master'!#REF! -> #REF! | E74: Same as Permanant Address | G74: Father | I74: 55 Years | J74: 1 | K74: N/A
B78: 1.Certified that I have no family and should I acquire a family hereafter,the above nomination shall be deemed as cancelled.
B79: 2.Certified that my father/mother is/ are dependent upon me.
B80: Strike out whichever is not applicable | J80: Signature/or thumb impression of the subscriber
G81: PART (EPS)
G82: Para 18
B83: I hereby furnish below particulars of the members of my family who would be eligible to receive Widow/Children Pension in the event of
B84: my premature death in service
B85: S.No | C85: Name & Address of the Family Member | I85: Age | J85: Relationship with the member
B86: 1 | E86: 2 | I86: 3 | K86: 4
B91: Certified that I have no family as defined in para 2 (vii) of the Employees's Family Pension Scheme 1995 and should I acquire a family hereafter
B92: I shall furnish Particulars there on in the above form.
B93: I hereby nominate the following person for receiving the monthly widow pension (admissible under para 16 2 (a) (1) & (ii) in the even of my death
B94: without leaving any eligible member for receiving pension.
B95: Name and Address of the nominee | G95: Date of Birth | I95: Relationship with member
B101: Date | C101: ='04-22-Master'!#REF! -> #REF! | I101: Signature or thumb impression of the subscriber
F102: CERTIFCATE BY EMPLOYER
A103: Certified that the above declaration and nomination has been signed/thumb impressed before me by Shri/Smt/Kum | K103: ='04-22-Master'!#REF! -> #REF!
A104: employed in my establishment after he/she has read the entry/entries have been read over to him/her by me and got confirmed by him/her.
F106: Signature or the employer or other authorized officer of the establiment and Designation
A107: Place | B107: Hyderabad | F107: ='04-22-Master'!F5 -> Burgeon IT Services Pvt.Ltd.
A108: Date | B108: ='04-22-Master'!#REF! -> #REF! | F108: ='04-22-Master'!F6 -> Siri Mansion LIGB 436 Dr.A S Rao Nagar,Hyderabad
K109: (FORM 2 REVISED)
B110: NOMINATION AND DECLARATION FORM FOR UNEXEMPTED/EXEMPTED ESTABLISHMENTS
B111: Declaration and Nomination Form under the Employees Provident Funds and Employees Pension Schemes
B112: (Paragraph 33 and 61(1) of the Employees Provident Fund Scheme 1952 and Paragraph 18 of the Employees Pension Scheme 1995)
B114: 1. Name of the person making nomination | H114: ='04-22-Master'!#REF! -> #REF!
B115: 2. Father's/Husband name | H115: ='04-22-Master'!#REF! -> #REF!
B116: 3. Date of Birth | H116: ='04-22-Master'!#REF! -> #REF!
B117: 4. Sex | H117: ='04-22-Master'!#REF! -> #REF!
B118: 5. Marital Status | H118: Un-Married
B119: 6.Address
B120: Permanent | H120: ='04-22-Master'!#REF! -> #REF!
H121: ='04-22-Master'!#REF! -> #REF!
H122: ='04-22-Master'!#REF! -> #REF!
G123: PART-A(EPF)
B124: I hereby nominate the person(s)/cancel the nomination made by me previously and nominate the person(s) mentioned below to
B125: receive any amount due to me from the employer,in the event to my death.
B126: Name of the Nominee/nominees | E126: Address | G126: Nominee's relationship With the member | I126: Date of Birth | J126: Total amount of Share of accumulations | K126: If the nominee is minor,name,relationship and address of the guardian
B127: 1 | E127: 2 | G127: 3 | I127: 4 | J127: 5 | L127: 6
B128: ='04-22-Master'!#REF! -> #REF! | E128: Same as Permanant Address | G128: Father | I128: 55 Years | J128: 1 | K128: N/A
B132: 1.Certified that I have no family and should I acquire a family hereafter,the above nomination shall be deemed as cancelled.
...

Sheet Form 11
I1: New Form No. 11 - Declaration Form
B2: (To be retained by t he employer for future reference)
D3: EMPLOYEES' PROVIDENT FUND ORGANIZATION | I3: Emp Code: | K3: ='04-22-Master'!#REF! -> #REF!
C4: Employees' Provident Funds Scheme, 1952 (Paragraph 34 & 57) & | I4: Company | J4: ='04-22-Master'!F5 -> Burgeon IT Services Pvt.Ltd.
C5: The Employees' Pension Scheme, 1995 (Paragraph 24) | I5: ='04-22-Master'!F6 -> Siri Mansion LIGB 436 Dr.A S Rao Nagar,Hyderabad
A8: 1 | B8: Name of the Member | H8: ='04-22-Master'!#REF! -> #REF!
A9: 2 | B9: Fathers' Name | F9: Husband's Name | H9: ='04-22-Master'!#REF! -> #REF!
B10: (Please tick whichever is applicable)
A11: 3 | B11: Date of Birth (DD/MM/YYYY) | H11: ='04-22-Master'!#REF! -> #REF!
A12: 4 | B12: Gender (Male/Female/Transgender) | H12: ='04-22-Master'!#REF! -> #REF!
A13: 5 | B13: Marital Status(married / Unmarried / Widow/divorce) | H13: UNMARRIED
A14: 6 | B14: (a) | C14: Email Id
B15: (b) | C15: Mobile No.
A16: 7 | B16: Whether earlier a member of the Employees' Provident Fund Scheme, 1952 ? | H16: Yes | K16: No
A17: 8 | B17: Whether earlier a member of the Employees' Pension Scheme, 1995? | H17: Yes | K17: No
F18: Previous employment details [if Yes to 7 &/or 8 above]
A19: 9 | B19: a) | C19: Universal Account Number
B20: b) | C20: Previous PF Account Number
B21: C) | C21: Date of exit from previous employment (DD/MM/YYYY)
B22: d) | C22: Scheme Certificate No. (if issued)
B23: e) | C23: Pension Payment Order (PPO) No. (if issued)
A24: 10 | B24: a) | C24: International Worker | H24: Yes | K24: No
B25: b) | C25: If yes, state country of origin(India/Name of other country)
B26: C) | C26: Passport No.
B27: d) | C27: Validity of passport [(DD/MM/YYYY) to (DD/MM/YYYY)]
E28: KYC Details (attach self attested copies of following KYCs)
A29: 11 | B29: a) | C29: Bank Account No. & IFS Code
B30: b) | C30: AADHAR No.
B31: c) | C31: Permanent Account No. (PAN), if available
F32: UNDERTAKING
B33: 1) | C33: Certified that the particulars are true to the best of my knowledge.
B34: 2) | C34: I authorize EPFO to use my Aadhar for verification/authentication/eKYC purpose for service delivery.
B35: 3) | C35: Kindly transfer the funds and service details, if applicable from the previous PF account as declared above to the present P.F. Account (The Transfer would be possible only if the identified KYC details approved by previous employer has been verified by present employer
B36: 4) | C36: In case of changes in above details, the same will be intimated to employer at the earliest.
C37: Date : | D37: ='04-22-Master'!#REF! -> #REF!
C38: Place: | D38: Hyderabad | J38: Signature of Member
F40: DECLARATION BY PRESENT EMPLOYER
A41: A) | B41: The member Mr./Ms./Mrs. | E41: ='04-22-Master'!#REF! -> #REF! | H41: has joined on | J41: ='04-22-Master'!#REF! -> #REF! | K41: and has been allotted PF Number
B42: ='04-22-Master'!#REF! -> #REF!
A43: B) | B43: In case the person was earlier not a member of EPF Scheme, 1952 and EPS, 1995:
B44: (Post allotment of UAN) The UAN allotted for the member is
B45: Please Tick the Appropriate Option:
B46: The KYC details of the above member in the UAN database
B47: Have not been uploaded
B48: Have been uploaded but not approved
B49: Have been uploaded and approved with DSC
A50: C) | B50: In case the person was earlier a member of EPF Scheme, 1952 and EPS, 1995:
B51: The above PF Account Number/ UAN of the member as mentioned in (A) above has been tagged with his/her UAN/Previous Member ID as declared by member.
B52: Please Tick the Appropriate Option:
B53: The KYC details of the above member in the UAN database have been approved with DSC and transfer request has been generated on portal.
B54: As the DSC of establishment are not registered with EPFO, the member has been informed to file physical claim (Form 13) for transfer of funds
B55: from his previous establishment.
B56: Date | C56: =D37 -> #REF! | I56: Signature of Employer with seal of Establishment
I59: New Form No. 11 - Declaration Form
B60: (To be retained by t he employer for future reference)
D61: EMPLOYEES' PROVIDENT FUND ORGANIZATION | I61: Emp Code: | K61: ='04-22-Master'!#REF! -> #REF!
C62: Employees' Provident Funds Scheme, 1952 (Paragraph 34 & 57) & | I62: Company | J62: ='04-22-Master'!F5 -> Burgeon IT Services Pvt.Ltd.
C63: The Employees' Pension Scheme, 1995 (Paragraph 24) | I63: ='04-22-Master'!F6 -> Siri Mansion LIGB 436 Dr.A S Rao Nagar,Hyderabad
A65: 1 | B65: Name of the Member | H65: ='04-22-Master'!#REF! -> #REF!
A66: 2 | B66: Fathers' Name | F66: Husband's Name | H66: ='04-22-Master'!#REF! -> #REF!
B67: (Please tick whichever is applicable)
A68: 3 | B68: Date of Birth (DD/MM/YYYY) | H68: ='04-22-Master'!#REF! -> #REF!
A69: 4 | B69: Gender (Male/Female/Transgender) | H69: ='04-22-Master'!#REF! -> #REF!
A70: 5 | B70: Marital Status(married / Unmarried / Widow/divorce) | H70: Unmarried
A71: 6 | B71: (a) | C71: Email Id
B72: (b) | C72: Mobile No.
A73: 7 | B73: Whether earlier a member of the Employees' Provident Fund Scheme, 1952 ? | H73: Yes | K73: No
A74: 8 | B74: Whether earlier a member of the Employees' Pension Scheme, 1995? | H74: Yes | K74: No
F75: Previous employment details [if Yes to 7 &/or 8 above]
A76: 9 | B76: a) | C76: Universal Account Number
B77: b) | C77: Previous PF Account Number
B78: C) | C78: Date of exit from previous employment (DD/MM/YYYY)
B79: d) | C79: Scheme Certificate No. (if issued)
B80: e) | C80: Pension Payment Order (PPO) No. (if issued)
A81: 10 | B81: a) | C81: International Worker | H81: Yes | K81: No
B82: b) | C82: If yes, state country of origin(India/Name of other country)
B83: C) | C83: Passport No.
B84: d) | C84: Validity of passport [(DD/MM/YYYY) to (DD/MM/YYYY)]
E85: KYC Details (attach self attested copies of following KYCs)
A86: 11 | B86: a) | C86: Bank Account No. & IFS Code
B87: b) | C87: AADHAR No.
B88: c) | C88: Permanent Account No. (PAN), if available
F89: UNDERTAKING
B90: 1) | C90: Certified that the particulars are true to the best of my knowledge.
B91: 2) | C91: I authorize EPFO to use my Aadhar for verification/authentication/eKYC purpose for service delivery.
B92: 3) | C92: Kindly transfer the funds and service details, if applicable from the previous PF account as declared above to the present P.F. Account (The Transfer would be possible only if the identified KYC details approved by previous employer has been verified by present employer
B93: 4) | C93: In case of changes in above details, the same will be intimated to employer at the earliest.
C94: Date : | D94: ='04-22-Master'!#REF! -> #REF!
C95: Place: | D95: Hyderabad | J95: Signature of Member
F97: DECLARATION BY PRESENT EMPLOYER
A98: A) | B98: The member Mr./Ms./Mrs. | E98: ='04-22-Master'!#REF! -> #REF! | H98: has joined on | J98: ='04-22-Master'!#REF! -> #REF! | K98: and has been allotted PF Number
B99: ='04-22-Master'!#REF! -> #REF!
A100: B) | B100: In case the person was earlier not a member of EPF Scheme, 1952 and EPS, 1995:
B101: (Post allotment of UAN) The UAN allotted for the member is
B102: Please Tick the Appropriate Option:
B103: The KYC details of the above member in the UAN database
B104: Have not been uploaded
B105: Have been uploaded but not approved
B106: Have been uploaded and approved with DSC
A107: C) | B107: In case the person was earlier a member of EPF Scheme, 1952 and EPS, 1995:
...

Sheet Form-F
A1: F O R M – F
A2: [See sub-Rule (1) of Rule 6] The Payment of Gratuity Rules, 1973:
A3: NOMINATION
A4: To
A5: ='04-22-Master'!F5 -> Burgeon IT Services Pvt.Ltd.
A6: ='04-22-Master'!F6 -> Siri Mansion LIGB 436 Dr.A S Rao Nagar,Hyderabad
A8: 1. I, Shri / Shrimati / Kumari | C8: ='04-22-Master'!#REF! -> #REF!
A9: whose particulars are given in the statement below, hereby nominate the person(s) mentioned below to receive the gratuity payable after my death as also the gratuity standing to my credit in the event of my death before that amount has become payable, or having become payable has not been paid and direct that the said amount of gratuity shall be paid in proportion indicated against the name(s) of the nominee(s).
A11: 2. I hereby certify that the person(s) mentioned is a /are member(s) of my family within the meaning of clause (h) of Section 2 of the Payment of Gratuity Act, 1972.
A13: 3. I hereby declare that I have no family within the meaning of clause (h) of Section 2 of the said Act.
A15: 4. (a) My father/mother/parents is/are not dependent on me
A16: (b) My husband’s father/mother/parents is/are not dependent on my husband.
A18: 5. I have excluded my husband from my family by a notice dated the ……………. to the Controlling Authority in terms of the proviso to clause (h) of Section 2 of the said Act.
A20: 6. Nomination made herein invalidates my previous nomination.
A22: NOMINEE(S)
A23: Name in full with full address of nominee(s): | B23: Relationship with the empliyee | C23: Age of nominee: | D23: Proportion by which the gratuity will be shared:
A24: 1 | B24: 2 | C24: 3 | D24: 4
A25: ='04-22-Master'!#REF! -> #REF! | B25: Father | C25: 54 Years | D25: 1
A29: STATEMENT
A31: 1. Name of employee in full: | C31: ='04-22-Master'!#REF! -> #REF!
A32: 2. Sex: | C32: ='04-22-Master'!#REF! -> #REF!
A33: 3. Religion: | C33: Muslim
A34: 4. Whether unmarried/married/widow/widower: | C34: Un married
A35: 5. Department/Branch/Section where employed: | C35: ='04-22-Master'!#REF! -> #REF!
A36: 6. Post held with Ticket No. or Serial No. if any: | C36: ='04-22-Master'!#REF! -> #REF!
A37: 7. Date of appointment: | C37: ='04-22-Master'!#REF! -> #REF!
A38: 8. Permanent address:
C39: ='04-22-Master'!#REF! -> #REF!
C40: ='04-22-Master'!#REF! -> #REF!
C41: ='04-22-Master'!#REF! -> #REF!
A42: Place: | B42: Hyderabad
A43: Date: | B43: ='04-22-Master'!#REF! -> #REF! | C43: Signature/Thumb impression of the employee
A45: Declaration by witnesses:
A46: Nomination signed/thumb impressed before me:
A48: Name in full and full address of witnesses: | C48: Signature of witnesses:
A49: 1 | C49: 1
A50: 2 | C50: 2
C51: Certificate by the Employer
A52: Certified that the particulars of the above nomination have been verified and recorded in t his establishment
A53: Employer's reference No, if any
C55: Signature of the employer/Officer authorized
C56: Designation
C57: Name address of the establishment or rubber stamp there of
C58: ='04-22-Master'!F5 -> Burgeon IT Services Pvt.Ltd.
A59: Place: | B59: =B42 -> Hyderabad | C59: ='04-22-Master'!F6 -> Siri Mansion LIGB 436 Dr.A S Rao Nagar,Hyderabad
A60: Date: | B60: =B43 -> #REF!
B61: Acknowledgment by the Employee
A62: Received the duplicate of the nomination in Form 'F'Filled by me and duly certified by the employer
A63: Date: | B63: =B60 -> #REF!
A64: Note: Strike out words/paragraph not applicable | D64: Signature of the Employee
A69: F O R M – F
A70: [See sub-Rule (1) of Rule 6] The Payment of Gratuity Rules, 1973:
A71: NOMINATION
A72: To
A73: ='04-22-Master'!F5 -> Burgeon IT Services Pvt.Ltd.
A74: ='04-22-Master'!F6 -> Siri Mansion LIGB 436 Dr.A S Rao Nagar,Hyderabad
A76: 1. I, Shri / Shrimati / Kumari | C76: ='04-22-Master'!#REF! -> #REF!
A77: whose particulars are given in the statement below, hereby nominate the person(s) mentioned below to receive the gratuity payable after my death as also the gratuity standing to my credit in the event of my death before that amount has become payable, or having become payable has not been paid and direct that the said amount of gratuity shall be paid in proportion indicated against the name(s) of the nominee(s).
A79: 2. I hereby certify that the person(s) mentioned is a /are member(s) of my family within the meaning of clause (h) of Section 2 of the Payment of Gratuity Act, 1972.
A81: 3. I hereby declare that I have no family within the meaning of clause (h) of Section 2 of the said Act.
A83: 4. (a) My father/mother/parents is/are not dependent on me
A84: (b) My husband’s father/mother/parents is/are not dependent on my husband.
A86: 5. I have excluded my husband from my family by a notice dated the ……………. to the Controlling Authority in terms of the proviso to clause (h) of Section 2 of the said Act.
A88: 6. Nomination made herein invalidates my previous nomination.
A90: NOMINEE(S)
A91: Name in full with full address of nominee(s): | B91: Relationship with the empliyee | C91: Age of nominee: | D91: Proportion by which the gratuity will be shared:
A92: 1 | B92: 2 | C92: 3 | D92: 4
A93: ='04-22-Master'!#REF! -> #REF! | B93: Father | C93: 54 Years | D93: 1
A97: STATEMENT
A99: 1. Name of employee in full: | C99: ='04-22-Master'!#REF! -> #REF!
A100: 2. Sex: | C100: ='04-22-Master'!#REF! -> #REF!
A101: 3. Religion: | C101: Hindu
A102: 4. Whether unmarried/married/widow/widower: | C102: Un married
A103: 5. Department/Branch/Section where employed: | C103: ='04-22-Master'!#REF! -> #REF!
A104: 6. Post held with Ticket No. or Serial No. if any: | C104: ='04-22-Master'!#REF! -> #REF!
A105: 7. Date of appointment: | C105: ='04-22-Master'!#REF! -> #REF!
A106: 8. Permanent address:
C107: ='04-22-Master'!#REF! -> #REF!
C108: ='04-22-Master'!#REF! -> #REF!
C109: ='04-22-Master'!#REF! -> #REF!
A110: Place: | B110: Hyderabad
A111: Date: | B111: ='04-22-Master'!#REF! -> #REF! | C111: Signature/Thumb impression of the employee
A113: Declaration by witnesses:
A114: Nomination signed/thumb impressed before me:
A116: Name in full and full address of witnesses: | C116: Signature of witnesses:
A117: 1 | C117: 1
A118: 2 | C118: 2
C119: Certificate by the Employer
A120: Certified that the particulars of the above nomination have been verified and recorded in t his establishment
A121: Employer's reference No, if any
C123: Signature of the employer/Officer authorized
C124: Designation
C125: Name address of the establishment or rubber stamp there of
C126: ='04-22-Master'!F5 -> Burgeon IT Services Pvt.Ltd.
A127: Place: | B127: =B110 -> Hyderabad | C127: ='04-22-Master'!F6 -> Siri Mansion LIGB 436 Dr.A S Rao Nagar,Hyderabad
A128: Date: | B128: =B111 -> #REF!
B129: Acknowledgment by the Employee
A130: Received the duplicate of the nomination in Form 'F'Filled by me and duly certified by the employer
A131: Date: | B131: =B128 -> #REF!
A132: Note: Strike out words/paragraph not applicable | D132: Signature of the Employee
...

Sheet Sheet1
