Workbook

Sheet PUNE ASC-APRIL 22WM REG
A1: FORM IX- REGISTER OF PERSONS EMPLOYED | N1: 44501
A3: (Vide Rule 78(1) (a) (i) of Contract Labour (Regulation and Abolition) Central /Maharastra.Rules 1974
A4: Name and address of Contractor:Burgeon IT services Pvt.Ltd. | F4: Name and address of the establishment in / under which contract is carried on: burgeon IT services Pvt.Ltd. Siri mansion LIGH 436 DR.A S Rao nagar,Hyderabad
B5: ='4-22MASTER'!G6 -> Siri Mansion LIGB 436 Dr.A S Rao Nagar,Hyderabad
A7: Name and address of Contractor:burgeon IT services Pvt.Ltd. | F7: Name and address of principal employer:
F8: ='4-22MASTER'!AQ10 -> INFOSYS LTD.IL Ascendas SEZ Unit,Building Juniper
F9: International Tech Park,Rajiv Gandhi Infotech Park,Hinjawadi,Pune,Maharashtra
A11: S.No | B11: Name and Surname of workman | C11: Age and Sex | E11: Father's/Husband's name | F11: Nature of Employement/Designation | G11: Permanent Home Address of worken | H11: Local Address | I11: Date of commencement of Employment | J11: Signature or Thumb impression of workman | K11: Date of Temination of Employment | M11: Remarks
L12: Reason for Termination
A13: 1 | B13: Rajkumar Samui | C13: 31900 | D13: MALE | E13: Tapan Samui | F13: Technical Consultant | G13: S.NO. 28/2 Keerthi Classic, Marunji Road,Hinjawadi Pune, MH 411057 | H13: S.NO. 28/2 Keerthi Classic, Marunji Road,Hinjawadi Pune, MH 411057 | I13: 42782 | K13: 43695 | L13: Resignation
A14: 2 | B14: Mohammed Mudassir | C14: 29382 | D14: MALE | E14: Abdullah ansari | F14: Technical Consultant | G14: 401, Simone Terrace, Lane 9, salunke Vihar,Rd kondhwa, Pune 411048 | H14: 401, Simone Terrace, Lane 9, salunke Vihar,Rd kondhwa, Pune 411048 | I14: 43206 | K14: 43700 | L14: Resignation
A15: 3 | B15: Abhishek Kumar | C15: 22/09/1987 | D15: MALE | E15: Vishwakarma | F15: Technical Consultant | G15: 210 skylite vesta villas, sarjapura, bangalore | H15: 210 skylite vesta villas, sarjapura, bangalore | I15: 43206 | K15: 43812 | L15: Resignation
A16: 4 | B16: Varsha Anket | C16: 32707 | D16: FEMALE | E16: Aniket Ajit pATil | F16: Technical Consultant | G16: A-492, Gondhalpada,Plot 5, alibagh, Raigadh, MH 402201 | H16: A-492, Gondhalpada,Plot 5, alibagh, Raigadh, MH 402201 | I16: 43228 | K16: 43672 | L16: Resignation
A17: 5 | B17: Ishita Debnath | C17: 33329 | D17: FEMALE | E17: Manoranjan debnath | F17: Technical Consultant | G17: Kiran Pathology, shivaji park,PO renukot, Sonebhadra dist UP 231217 | H17: Kiran Pathology, shivaji park,PO renukot, Sonebhadra dist UP 231217 | I17: 43228 | K17: 43517 | L17: Resignation
A18: 6 | B18: Subodh Vendikonda | C18: 28/05/1989 | D18: MALE | E18: Prakash | F18: Technical Consultant | G18: 5-183/4, Teachers colony, Ichoda,Adilababd 504307 | H18: 5-183/4, Teachers colony, Ichoda,Adilababd 504307 | I18: 43272 | K18: 43672 | L18: Resignation
A19: 7 | B19: Dilip Lillaney | C19: 29800 | D19: MALE | E19: Raju Arjandas Lillaney | F19: Technical Consultant | G19: 503-I1, jasminium, Magarpatta city, Hadapsar Pune 411013 | H19: 503-I1, jasminium, Magarpatta city, Hadapsar Pune 411013 | I19: 43297 | K19: 43637 | L19: Resignation
A20: 8 | B20: Shantanu Mukherjee | C20: 32942 | D20: MALE | E20: Samarnath Mukherjee | F20: Technical Consultant | G20: Musabani No.1, Near Shishu Mandir School, East Singhbhum, Jharkhand 632104 East Singhbhum, Jharkhand - 832104 | H20: Musabani No.1, Near Shishu Mandir School, East Singhbhum, Jharkhand 632104 East Singhbhum, Jharkhand - 832104 | I20: 43377 | K20: 43636 | L20: Resignation
A21: 9 | B21: Vamshi Krishna Billakanto | C21: 32665 | D21: MALE | E21: Lakshmi Narayana | F21: Technical Consultant | G21: 149/5/G4, Uppal Depot, Near Ravindra Bharati school, Mallikarjuna Nagar, Boduppal, KV rangareddy, Telangana 500092 | H21: 149/5/G4, Uppal Depot, Near Ravindra Bharati school, Mallikarjuna Nagar, Boduppal, KV rangareddy, Telangana 500092 | I21: 43398 | K21: 43546 | L21: Resignation
A22: 10 | B22: Dilip Arjun Kanabar | C22: 32750 | D22: MALE | E22: Arjun Kanabar | F22: Technical Consultant | G22: A/105, Prakash Bhavan, Khau Gali, Station Road. Bhayandar west. District-Thane 401101 | H22: 594/B Wing, 144 Wakadkar Wasti, Nisarg Vishwa, Wakad. Pune 411057 | I22: 43448 | K22: 43652 | L22: Resignation
A23: 11 | B23: Swati Sinha | C23: 34282 | D23: FEMALE | E23: Subodh kumar | F23: Technical Consultant | G23: POSTAL PARK ROAD NO 3 B PATNA BIHAR-800001 | H23: SAI NIVAS WAKAD KARVVASTI PUNE-411057 | I23: 43451 | K23: 43714 | L23: Resignation
A24: 12 | B24: Aparna Khaire | C24: 31088 | D24: FEMALE | E24: Kisan Khaire | F24: Technical Consultant | G24: C1202, DattSai CHSL, Krishna Borker Marg, Thane East - 400603 | H24: 1004, Orchids, Ashok Meadows, Hinjewadi Pahse 1, Pune, MH | I24: 43468 | K24: 43602 | L24: Resignation
A25: 13 | B25: Kiran Krishna Gondhali | C25: 33336 | D25: MALE | E25: krishna s | F25: Technical Consultant | G25: 1/5 saikrupa chaal,opp.ikon plaza,near R.T.O OFFICE,Kalyan(west),421301 | H25: 1/5 saikrupa chaal,opp.ikon plaza,near R.T.O OFFICE,Kalyan(west),421301 | I25: 43528 | K25: 43812 | L25: Resignation
A26: 14 | B26: Shwetha Thorat | C26: 24/11/1986 | D26: FEMALE | E26: Prabhakar deo ram | F26: Technical Consultant | G26: A/302,RAJESWAR TOER,NEAR PRATHAP CINEMA,KOLBAD,THANE WEST,400601 | H26: E/901,PARK IOD BULDING,PARK STREAT,SOC,WAKAD,PUNE,411057 | I26: 43556 | K26: 43854 | L26: Resignation
A27: 15 | B27: Mugesh R | C27: 34644 | D27: MALE | E27: RAJARATNAM A | F27: Senior Network Engineer L2 | G27: NO.44 ESWARAN KOVIL STREAT,MANAPARAI,TREACHY DISR,THAMILNADU,621306 | H27: 3RD FLOUR,OLD MADIVAALA,CHIKKAMADIVAALA,FISRT STAGE,BTM LAY OUT,BANGALURE,560076 | I27: 43742 | K27: 44420 | L27: Resignation
A28: 16 | B28: RAHOOL MORAY | C28: 16/6/1973 | D28: MALE | E28: M. B. More | F28: Program Manager | G28: Spring Valley, Lavender B-303, Next to Magarpatta City, Hadapsar, Pune 411013 | H28: Spring Valley, Lavender B-303, Next to Magarpatta City, Hadapsar, Pune 411013 | I28: 44172 | K28: 44408 | L28: Resignation
A29: 17 | B29: Mansidutt Sharma | C29: 28345 | D29: MALE | E29: J S Bhardwaj | F29: Senior Consultant | G29: Flat No : I1006, SPS Residency, Vaibhav Khand, Indirapuram, Ghaziabad, UP - 201014 | H29: Flat No : I1006, SPS Residency, Vaibhav Khand, Indirapuram, Ghaziabad, UP - 201014 | I29: 28/12/2020 | K29: 44384 | L29: Resignation
A30: 18 | B30: Sandeep Dange | C30: 32295 | D30: Male | E30: Shrikrishna Narayana rao | F30: Project Manager | G30: ND42, Flat No 21,Sambaji chowk, CICDO, Kautha, Nanded, MH 431003 | H30: ND42, Flat No 21,Sambaji chowk, CICDO, Kautha, Nanded, MH 431003 | I30: 44294 | K30: 44475 | L30: Resignation
A31: 19 | B31: Haneef | C31: 34715 | D31: Male | E31: D.Subahan | F31: System Administrator | G31: Sri Sai vaishnavi pg, 2nd cross, near Rajapalya, Hoodi, 560048 | H31: 6-1-356A, Lakshminagar, near Ramalayam Temple, Anantapur, 515004 | I31: 44298 | K31: ACTIVE | L31: ACTIVE | N31: 1
A32: 20 | B32: Y.Hemanth Kumar Reddy | C32: 30190 | D32: Male | E32: Y Venkatramana Reddy | F32: VMWare Admin | G32: #72B 1St Floor, 1st Bolck, 5th Main, Devasandra Main Road, Ayyappa Nagar, kr Puram, Bangalore, KA 560036 | H32: 15-5-5-B2, RRN main road, RRN colony, Madnapalle -517325, Chittoor Dis, AP | I32: 44298 | K32: 44508 | L32: Resignation | N32: 2
A33: 21 | B33: DevKant Shukla | C33: 31873 | D33: Male | E33: Late. Shri Surendra Kumar Shukla | F33: Project Manager | G33: Flat no-37; Pocket-5; Sector-2; Rohini; Delhi 110085 | H33: Flat no-37; Pocket-5; Sector-2; Rohini; Delhi 110085 | I33: 44301 | K33: ACTIVE | L33: ACTIVE
A34: 22 | B34: KAPIL KHADSE | C34: 33359 | D34: Male | E34: Harshada Khadse | F34: Sr. Project Coordinator | G34: 119, Gurukunj nagar, Near MIG colony, Besa Road, Manewada, Nagpur- 440034 | H34: 119, Gurukunj nagar, Near MIG colony, Besa Road, Manewada, Nagpur- 440034 | I34: 44296 | K34: 44439 | L34: Resignation
A35: 23 | B35: Rajaram Raosaheb Gusale | C35: 33767 | D35: MALE | E35: Supriya Rajaram Gusale | F35: Project Manager | G35: A/P: Chandolewadi,Sangola, Behind Sutgirni,Tal- Sangola, Dist-Solapur-413307 | I35: 4th May 2021 | K35: 44524 | L35: Resignation | N35: 4
B36: Nilesh Baviskar | C36: 33030 | D36: Male | E36: Ashok Bhavisar | F36: Project Manager | G36: Mukam post, Kanalda,Taluka,Jalgaon, Kanvashramroad, new Busstand, Kanalde, Jalgaon,MH 425002 | H36: Mukam post, Kanalda,Taluka,Jalgaon, Kanvashramroad, new Busstand, Kanalde, Jalgaon,MH 425002 | I36: 4th May 2021 | K36: ACTIVE | L36: ACTIVE
A37: 25 | B37: Ved Prakash | C37: 30321 | D37: Male | E37: J N Gupta | F37: Project Manager | G37: Flat No. A 203, Silver Palm Grove, Ravet, Pune 412101 | H37: Flat No. A 203, Silver Palm Grove, Ravet, Pune 412101 | I37: 4th May 2021 | K37: ACTIVE | L37: ACTIVE | N37: 2
A38: 26 | B38: Prashant Gangadharrao Hambarde | C38: 31554 | D38: MALE | E38: Gangadhar Avadhut rao | F38: Project Manager | G38: H No ND 42, P2 8/2, Near indira gandhi High school, Hudco, New Nanded, Maharashtra, 431603 | H38: H No ND 42, P2 8/2, Near indira gandhi High school, Hudco, New Nanded, Maharashtra, 431603 | I38: 4th May 2021 | K38: 44526 | L38: Resignation | N38: 7
A39: 27 | B39: GauravVispute | C39: 33721 | D39: MALE | E39: Bhika Jagannath | F39: Project Coordinator | G39: 5/2, Trimurti Housing Socieity,Central bank colony road, Pimprala,Jalgaon 425002 | H39: H No ND 42, P2 8/2, Near indira gandhi High school, Hudco, New Nanded, Maharashtra, 431603 | I39: 4th May 2021 | K39: ACTIVE | L39: ACTIVE | N39: 3
A40: 28 | B40: Sneha Panhalkar | C40: 23/11/1990 | D40: Male | E40: Kashinath Panhalkar | F40: Project Manager | G40: 502, Sai Sarth Residency, Adarsh Nagar, Famous Chawk, New Sanghavi, Pune-411027 | H40: 502, Sai Sarth Residency, Adarsh Nagar, Famous Chawk, New Sanghavi, Pune-411027 | I40: 10th May 2021 | K40: resigantion | L40: Resignation
A41: 29 | B41: SACHIN NANDKISHORPATIL | C41: 29/09/1992 | D41: Male | E41: NANDKISHOR PATIL | F41: Project Coordinator L2 | G41: FL-206, A wing, Orient Plaza, Keshsv Nagar chinchwad, Pune-411033 | H41: FL-206, A wing, Orient Plaza, Keshsv Nagar chinchwad, Pune-411033 | I41: 10th May 2021 | K41: 44512 | L41: Resignation | N41: 9
A42: 30 | B42: Rohit Mahalankar | C42: 31560 | D42: Male | E42: Deelip Rao sakharam | F42: Project Manager | G42: Flat No 305, Shalan Heights, Sai park Road, Opp Kamalraj Bajaj, Dighi, Pune, 411015 | H42: A/P, Satala(KHU), Ahmedpur Dist, Latur MH 413523 | I42: 31st May 2021 | K42: ACTIVE | L42: ACTIVE
A43: 31 | B43: AYESHA BANU.I | C43: 33951 | D43: FEMALE | E43: Ishaka | F43: Project Manager | G43: 2-36,Muslim street,Poothagaram,Thirupattur tq,Taminadu-635851 | H43: 2-36,Muslim street,Poothagaram,Thirupattur tq,Taminadu-635851 | I43: 44358 | J43: OO | K43: 44516 | L43: Resignation | N43: 11
A44: 32 | B44: SaiPrasad Cheruvukommu | C44: ='4-22MASTER'!#REF! -> #REF! | D44: MALE | E44: ='4-22MASTER'!#REF! -> #REF! | F44: ='4-22MASTER'!#REF! -> #REF! | G44: ='4-22MASTER'!#REF! -> #REF! | H44: ='4-22MASTER'!#REF! -> #REF! | I44: 44454 | J44: OO | K44: ACTIVE | L44: ACTIVE
A45: 33 | B45: Snehal Shirsat | C45: 32523 | D45: MALE | E45: Sumit Dongare | F45: Project Engineer | G45: Pno.22A Snehswapna Padma Colony Opp SSC Board Kolhapur 416008 | H45: MB92 New Indira colony Near public school Burhanpur 450331 | I45: 44481 | K45: ACTIVE | L45: ACTIVE
A46: 34 | B46: Shashanki Mishra | C46: 33253 | D46: MALE | E46: sharad shukla | F46: Project Lead | G46: 15/A chandra colony Rajanandgaon Chhattisgarh | H46: 15/A chandra colony Rajanandgaon Chhattisgarh | I46: 44481 | K46: ACTIVE | L46: ACTIVE
A47: 35 | B47: Anjali Dubey | C47: 27-12-1990 | D47: FEMALE | E47: Ravindra Nath Dubey | F47: Project Engineer | G47: H.N. 376/16, Behind P.K. School, Ravindra nagar Urrahat Rewa M.P. 486001 | H47: H.N. 376/16, Behind P.K. School, Ravindra nagar Urrahat Rewa M.P. 486001 | I47: 44487 | K47: ACTIVE | L47: ACTIVE | N47: 4
A48: 36 | B48: Mayuri Mishra | C48: 32567 | D48: FEMALE | E48: Shiv Vilas Mishra | F48: IT Project Manager | G48: 32,Ameer nagar,Lucknow,Uttar pradesh 226004 | H48: D 703,Asamanth Society,SUS Road,Pashan,Pune,Maharastra 411021 | I48: 44515 | K48: ACTIVE | L48: ACTIVE
A49: 37 | B49: SREENIVASULU NARISETTY | C49: 31552 | D49: MALE | E49: Rajaiah narisetty | F49: SENIOR SOFTWARE ENGINEER | G49: BN 348,Balaram nagar,Safilguda,Malkajgiri,Secunderabad 500047,TS | H49: BN 348,Balaram nagar,Safilguda,Malkajgiri,Secunderabad 500047,TS | I49: 44515 | K49: ACTIVE | L49: ACTIVE
A50: 38 | B50: TUSHAR UCHAGAONKAR | C50: 33656 | D50: MALE | E50: Pundalik Uchagaonkar | F50: Network Engineer | G50: Plot No 5,Sy No 140,Parijath colony,Hindwadi,Belgam,Karnataka 590011 | H50: Plot No 5,Sy No 140,Parijath colony,Hindwadi,Belgam,Karnataka 590011 | I50: 44546 | K50: ACTIVE | L50: ACTIVE | N50: 5
A51: 39 | B51: Sneha Hande | C51: 09/11/1994 | D51: FEMALE | E51: Ramchandra Nathu Hande | F51: Project manager | G51: OO | H51: OO | I51: 44566 | K51: ACTIVE | L51: ACTIVE | N51: 6
A52: 40 | B52: Amol Gole | C52: 32560 | D52: MALE | E52: Harishchandra Gole | F52: Project Manager | G52: Shri ,Gurudatta krupa housing socity hill road, Sion,Chunabhatti ,Mumbai, Maharashtra, 400022 | H52: Nilgiri socity Building no 27,4th floor /4th room ,C-5,Sector 5, CBD Belapur ,Navi Mumbai, Maharashtra, 400614 | I52: 44579 | K52: ACTIVE | L52: ACTIVE | N52: 7
A53: 41 | B53: Sandeep Dixit | C53: 28764 | D53: MALE | E53: Surendra Singh | F53: Sr. Project Manager | G53: 782,Sector 46,Gurgaon,Haryana 122002 | H53: 782,Sector 46,Gurgaon,Haryana 122002 | I53: 44593 | K53: ACTIVE | L53: ACTIVE | N53: 8
A54: 42 | B54: Jaikesh Upadhyay | C54: 31778 | D54: MALE | E54: Ashok Upadhyay | F54: Sr. Project Coordinator | G54: H No 134,Pratap nagar,Ratlam,Madhya pradesh 457001 | H54: Sri vathsava house,SR no. 261/1/1,Sri dharshan colony,Kalvad road,Dhanori,Pune,MH,411015 | I54: 44609 | K54: ACTIVE | L54: ACTIVE | N54: 9
A55: 43 | B55: Jyoti Singh | C55: 34895 | D55: FEMALE | E55: Ashok Kumar Singh | F55: Sr.Security analyst | G55: Room F1,C 38,Sai apartments,JBTS gardens,Chhatrapur,New Delhi 110074 | H55: Room F1,C 38,Sai apartments,JBTS gardens,Chhatrapur,New Delhi 110074 | I55: 44613 | K55: ACTIVE | L55: ACTIVE | N55: 10
A56: 44 | B56: Chandrashekar Patil | C56: 34710 | D56: MALE | E56: Shivraj Patil | F56: Project Manager | G56: At post Malegaon,Maqta,Taluq Deglur,Nanded district,Maharastra 431718 | H56: Q-198,Govt Quarters,Sastry nagar,Erawada,Pune 411006 | I56: 44634 | K56: ACTIVE | L56: ACTIVE | N56: 11
A57: 45 | B57: ShaikFarooq Basha | C57: 33370 | D57: MALE | E57: Shaik Mabu Subahan | F57: Software Engineer | G57: 2-112,Kakkalapally colony,Ananthapur,AP 515001 | H57: 2-112,Kakkalapally colony,Ananthapur,AP 515001 | I57: 44636 | K57: ACTIVE | L57: ACTIVE | N57: 12
A58: 46 | B58: NILOTPAL BHOWAL | C58: 31584 | D58: MALE | E58: Dwijendra Kumar Bhowal | F58: VM ware consultant | G58: P-53,Niva park extension,Badam Talad,Brahmapur,Kolkatta-700096 | H58: Sri laxmi PG narayan nagar,Hinjewadi phase I,Pune 411057 | I58: 44650 | K58: ACTIVE | L58: ACTIVE | N58: 13
A59: 47 | B59: Varsha AmitKadam | C59: 31018 | D59: FEMALE | E59: Amit Kadam | F59: Program Manager | G59: 1/87,Ramdut building,currey Road,Mumbai,Maharastra 400012 | H59: Flat No.204,Melody Appts,Waked,Pune,Maharastra,'411057 | I59: 44676 | K59: ACTIVE | L59: ACTIVE | N59: 14
H64: Signature of the Contractor with Seal

Sheet 4-22MASTER
A3: FORM - XIII REGISTER OF WORKMEN EMPLOYED BY CONTRACTOR
C4: (Vide Rule 75 of Contract Labour (Regulation and Abolition) Central/Maharastra Rules 1974)
A5: Name and address of Contractor: | G5: Burgeon IT Services Pvt.Ltd. | AC5: Name and address of Establishemnt in/ under which contract is carried on: | AQ5: =G5 -> Burgeon IT Services Pvt.Ltd.
G6: Siri Mansion LIGB 436 Dr.A S Rao Nagar,Hyderabad | AQ6: =G6 -> Siri Mansion LIGB 436 Dr.A S Rao Nagar,Hyderabad
AQ7: =G7 -> 0
A8: Nature and location of work: | G8: IT SUPPORTIVE SERVICES & PUNE ASC SEZ
A10: Wage period: Monthly | E10: 44652 | AL10: Name and address of Principal Employer: | AQ10: INFOSYS LTD.IL Ascendas SEZ Unit,Building Juniper
AQ11: International Tech Park,Rajiv Gandhi Infotech Park,Hinjawadi,Pune,Maharashtra
A14: Serial No. in the Register of Workmen | B14: Employee ID | C14: Name of Workman | D14: Age | E14: Sex | F14: Father's /Husband Name | G14: Designation / Nature of Work Done | H14: Permanent Address | K14: Local Address | O14: Date of Commencement of Employment | P14: Signature or thumb impression of Workman | Q14: Date of termination of Employment | R14: Reasons for termination | S14: Remarks | T14: EPF Number | U14: ESI Number | V14: Name of Workman | X14: No.of Days worked | Y14: Unit of work done | Z14: Monthly rate of wages/ piece rate | AA14: Basic wages | AB14: Dearness Allowances | AC14: Over time | AD14: Other cash payments (Nature of payments to be indicated) | AE14: HRA | AF14: CONVEYANCE | AG14: MEDICAL ALLOWANCES | AH14: SPECIAL ALLOWNANCES | AI14: Total | AJ14: BONUS | AK14: GRATUITY | AL14: LTA/L.E | AM14: ARREAR AMOUNT | AN14: TOTAL AMOUNT | AO14: Deductions, if any, (Indicate nature) | AU14: Net Amount paid | AV14: Time and Date of Payment | AW14: Place of Payment | AX14: Signature/Thumb Impression of workman | AY14: Initial of Contractor or his representative
AO15: ESI | AP15: PF | AQ15: PT | AR15: TDS | AS15: MED | AT15: Total Deductions
A17: 19 | B17: BITS-542 | C17: Haneef | D17: 34715 | E17: MALE | F17: D.Subahan | G17: System Administrator | H17: Sri Sai vaishnavi pg, 2nd cross, near Rajapalya, Hoodi, 560048 | K17: 6-1-356A, Lakshminagar, near Ramalayam Temple, Anantapur, 515004 | O17: 44298 | T17: 100947550505 | U17: N/A | V17: =C17 -> Haneef | W17: 30 | X17: =VLOOKUP(B17,'[1]Pay sheet-APRIL- 2022'!$C$12:$AF$139,10,0) -> 30 | Y17: N/A | Z17: =VLOOKUP(B17,'[2]Pay sheet-JAN- 2021'!$C$18:$AF$125,6,0) -> 61740 | AA17: =VLOOKUP(B17,'[1]Pay sheet-APRIL- 2022'!$C$12:$AF$139,11,0) -> 37044 | AB17: 0 | AC17: 0 | AD17: =AE17+AF17+AG17+AH17 -> 24809 | AE17: =VLOOKUP(B17,'[1]Pay sheet-APRIL- 2022'!$C$12:$AF$139,12,0) -> 14817.6 | AF17: =VLOOKUP(B17,'[1]Pay sheet-APRIL- 2022'!$C$12:$AF$139,13,0) -> 2083 | AG17: =VLOOKUP(B17,'[1]Pay sheet-APRIL- 2022'!$C$12:$AF$139,14,0) -> 2083 | AH17: =VLOOKUP(B17,'[1]Pay sheet-APRIL- 2022'!$C$12:$AF$139,15,0) -> 5825.4 | AI17: =AA17+AB17+AC17+AE17+AF17+AG17+AH17 -> 61853 | AJ17: =VLOOKUP(B17,'[1]Pay sheet-APRIL- 2022'!$C$12:$AF$139,18,0) -> 1554.609 | AK17: =VLOOKUP(B17,'[1]Pay sheet-APRIL- 2022'!$C$12:$AF$139,19,0) -> 1781.8164 | AL17: =VLOOKUP(B17,'[1]Pay sheet-APRIL- 2022'!$C$12:$AF$139,20,0) -> 3087 | AM17: 0 | AN17: =AI17+AJ17+AK17+AL17+AM17 -> 68276.425 | AO17: 0 | AP17: =VLOOKUP(B17,'[1]Pay sheet-APRIL- 2022'!$C$12:$AF$139,26,0) -> 1800 | AQ17: =VLOOKUP(B17,'[1]Pay sheet-APRIL- 2022'!$C$12:$AF$139,25,0) -> 200 | AR17: =VLOOKUP(B17,'[1]Pay sheet-APRIL- 2022'!$C$12:$AF$139,24,0) -> 0 | AS17: =VLOOKUP(B17,'[1]Pay sheet-APRIL- 2022'!$C$12:$AF$139,27,0) -> 391.78785 | AT17: =AP17+AQ17+AR17+AS17 -> 2391.7878 | AU17: =AN17-AT17 -> 65884.638 | AV17: 05.05.2022 | AW17: SBI | AX17: A/C'20434252219 | BA17: 1
A18: 25 | B18: BITS-557 | C18: Ved Prakash | D18: 30321 | E18: MALE | F18: J N Gupta | G18: Project Manager | H18: Flat No. A 203, Silver Palm Grove, Ravet, Pune 412101 | K18: Flat No. A 203, Silver Palm Grove, Ravet, Pune 412101 | O18: 4th May 2021 | T18: 100457474727 | U18: N/A | V18: =C18 -> Ved Prakash | W18: 30 | X18: =VLOOKUP(B18,'[1]Pay sheet-APRIL- 2022'!$C$12:$AF$139,10,0) -> 20 | Y18: N/A | Z18: =VLOOKUP(B18,'[2]Pay sheet-JAN- 2021'!$C$18:$AF$125,6,0) -> 71009 | AA18: =VLOOKUP(B18,'[1]Pay sheet-APRIL- 2022'!$C$12:$AF$139,11,0) -> 28403.6 | AB18: 0 | AC18: 0 | AD18: =AE18+AF18+AG18+AH18 -> 19048.733 | AE18: =VLOOKUP(B18,'[1]Pay sheet-APRIL- 2022'!$C$12:$AF$139,12,0) -> 11361.44 | AF18: =VLOOKUP(B18,'[1]Pay sheet-APRIL- 2022'!$C$12:$AF$139,13,0) -> 1389 | AG18: =VLOOKUP(B18,'[1]Pay sheet-APRIL- 2022'!$C$12:$AF$139,14,0) -> 1389 | AH18: =VLOOKUP(B18,'[1]Pay sheet-APRIL- 2022'!$C$12:$AF$139,15,0) -> 4909.2933 | AI18: =AA18+AB18+AC18+AE18+AF18+AG18+AH18 -> 47452.333 | AJ18: =VLOOKUP(B18,'[1]Pay sheet-APRIL- 2022'!$C$12:$AF$139,18,0) -> 1554.609 | AK18: =VLOOKUP(B18,'[1]Pay sheet-APRIL- 2022'!$C$12:$AF$139,19,0) -> 1366.2132 | AL18: =VLOOKUP(B18,'[1]Pay sheet-APRIL- 2022'!$C$12:$AF$139,20,0) -> 2366.9667 | AM18: 0 | AN18: =AI18+AJ18+AK18+AL18+AM18 -> 52740.122 | AO18: 0 | AP18: =VLOOKUP(B18,'[1]Pay sheet-APRIL- 2022'!$C$12:$AF$139,26,0) -> 1800 | AQ18: =VLOOKUP(B18,'[1]Pay sheet-APRIL- 2022'!$C$12:$AF$139,25,0) -> 200 | AR18: =VLOOKUP(B18,'[1]Pay sheet-APRIL- 2022'!$C$12:$AF$139,24,0) -> 0 | AS18: =VLOOKUP(B18,'[1]Pay sheet-APRIL- 2022'!$C$12:$AF$139,27,0) -> 440.76133 | AT18: =AP18+AQ18+AR18+AS18 -> 2440.7613 | AU18: =AN18-AT18 -> 50299.361 | AV18: 05.05.2022 | AW18: HDFC | AX18: A/C'50100052341452 | BA18: 3
A19: 27 | B19: BITS-559 | C19: GauravVispute | D19: 33721 | E19: MALE | F19: Bhika Jagannath | G19: Project Coordinator | H19: 5/2, Trimurti Housing Socieity,Central bank colony road, Pimprala,Jalgaon 425002 | O19: 4th May 2021 | T19: 101012347201 | U19: N/A | V19: =C19 -> GauravVispute | W19: 30 | X19: =VLOOKUP(B19,'[1]Pay sheet-APRIL- 2022'!$C$12:$AF$139,10,0) -> 29 | Y19: N/A | Z19: =VLOOKUP(B19,'[2]Pay sheet-JAN- 2021'!$C$18:$AF$125,6,0) -> 43202 | AA19: =VLOOKUP(B19,'[1]Pay sheet-APRIL- 2022'!$C$12:$AF$139,11,0) -> 25057.16 | AB19: 0 | AC19: 0 | AD19: =AE19+AF19+AG19+AH19 -> 16817.773 | AE19: =VLOOKUP(B19,'[1]Pay sheet-APRIL- 2022'!$C$12:$AF$139,12,0) -> 10022.864 | AF19: =VLOOKUP(B19,'[1]Pay sheet-APRIL- 2022'!$C$12:$AF$139,13,0) -> 2014 | AG19: =VLOOKUP(B19,'[1]Pay sheet-APRIL- 2022'!$C$12:$AF$139,14,0) -> 2014 | AH19: =VLOOKUP(B19,'[1]Pay sheet-APRIL- 2022'!$C$12:$AF$139,15,0) -> 2766.9093 | AI19: =AA19+AB19+AC19+AE19+AF19+AG19+AH19 -> 41874.933 | AJ19: =VLOOKUP(B19,'[1]Pay sheet-APRIL- 2022'!$C$12:$AF$139,18,0) -> 1554.609 | AK19: =VLOOKUP(B19,'[1]Pay sheet-APRIL- 2022'!$C$12:$AF$139,19,0) -> 1205.2494 | AL19: =VLOOKUP(B19,'[1]Pay sheet-APRIL- 2022'!$C$12:$AF$139,20,0) -> 2088.0967 | AM19: 0 | AN19: =AI19+AJ19+AK19+AL19+AM19 -> 46722.888 | AO19: 0 | AP19: =VLOOKUP(B19,'[1]Pay sheet-APRIL- 2022'!$C$12:$AF$139,26,0) -> 1800 | AQ19: =VLOOKUP(B19,'[1]Pay sheet-APRIL- 2022'!$C$12:$AF$139,25,0) -> 200 | AR19: =VLOOKUP(B19,'[1]Pay sheet-APRIL- 2022'!$C$12:$AF$139,24,0) -> 0 | AS19: =VLOOKUP(B19,'[1]Pay sheet-APRIL- 2022'!$C$12:$AF$139,27,0) -> 391.78785 | AT19: =AP19+AQ19+AR19+AS19 -> 2391.7878 | AU19: =AN19-AT19 -> 44331.101 | AV19: 05.05.2022 | AW19: SBI | AX19: A/C'31443937313 | BA19: 4
A20: 35 | B20: BITS-658 | C20: Anjali Dubey | D20: 27-12-1990 | E20: FEMALE | F20: Ravindra Nath Dubey | G20: Project Engineer | H20: H.N. 376/16, Behind P.K. School, Ravindra nagar Urrahat Rewa M.P. 486001 | K20: H.N. 376/16, Behind P.K. School, Ravindra nagar Urrahat Rewa M.P. 486001 | L20: OO | M20: OO | N20: OO | O20: 44487 | T20: 100514943656 | U20: N/A | V20: Anjali Dubey | W20: 30 | X20: =VLOOKUP(B20,'[1]Pay sheet-APRIL- 2022'!$C$12:$AF$139,10,0) -> 28 | Y20: N/A | Z20: =VLOOKUP(B20,'[2]Pay sheet-JAN- 2021'!$C$18:$AF$125,6,0) -> 58959 | AA20: =VLOOKUP(B20,'[1]Pay sheet-APRIL- 2022'!$C$12:$AF$139,11,0) -> 33017.04 | AB20: 0 | AC20: 0 | AD20: =AE20+AF20+AG20+AH20 -> 22124.36 | AE20: =VLOOKUP(B20,'[1]Pay sheet-APRIL- 2022'!$C$12:$AF$139,12,0) -> 13206.816 | AF20: =VLOOKUP(B20,'[1]Pay sheet-APRIL- 2022'!$C$12:$AF$139,13,0) -> 1944 | AG20: =VLOOKUP(B20,'[1]Pay sheet-APRIL- 2022'!$C$12:$AF$139,14,0) -> 1944 | AH20: =VLOOKUP(B20,'[1]Pay sheet-APRIL- 2022'!$C$12:$AF$139,15,0) -> 5029.544 | AI20: =AA20+AB20+AC20+AE20+AF20+AG20+AH20 -> 55141.4 | AJ20: =VLOOKUP(B20,'[1]Pay sheet-APRIL- 2022'!$C$12:$AF$139,18,0) -> 1554.609 | AK20: =VLOOKUP(B20,'[1]Pay sheet-APRIL- 2022'!$C$12:$AF$139,19,0) -> 1588.1196 | AL20: =VLOOKUP(B20,'[1]Pay sheet-APRIL- 2022'!$C$12:$AF$139,20,0) -> 2751.42 | AM20: 0 | AN20: =AI20+AJ20+AK20+AL20+AM20 -> 61035.549 | AO20: 0 | AP20: =VLOOKUP(B20,'[1]Pay sheet-APRIL- 2022'!$C$12:$AF$139,26,0) -> 1800 | AQ20: =VLOOKUP(B20,'[1]Pay sheet-APRIL- 2022'!$C$12:$AF$139,25,0) -> 200 | AR20: =VLOOKUP(B20,'[1]Pay sheet-APRIL- 2022'!$C$12:$AF$139,24,0) -> 0 | AS20: =VLOOKUP(B20,'[1]Pay sheet-APRIL- 2022'!$C$12:$AF$139,27,0) -> 254 | AT20: =AP20+AQ20+AR20+AS20 -> 2254 | AU20: =AN20-AT20 -> 58781.549 | AV20: 05.05.2022 | AW20: Union bank of India | AX20: 631302010000771 | BA20: 7
A21: 38 | B21: BITS-683 | C21: TUSHAR UCHAGAONKAR | D21: 33656 | E21: MALE | F21: Pundalik Uchagaonkar | G21: Network Engineer | H21: Plot No 5,Sy No 140,Parijath colony,Hindwadi,Belgam,Karnataka 590011 | I21: Plot No 5,Sy No 140,Parijath colony,Hindwadi,Belgam,Karnataka 590011 | L21: OOOO | M21: OOOO | N21: OOOO | O21: 44546 | T21: 100593810783 | U21: N/A | V21: TUSHAR UCHAGAONKAR | W21: 30 | X21: =VLOOKUP(B21,'[1]Pay sheet-APRIL- 2022'!$C$12:$AF$139,10,0) -> 30 | Y21: N/A | Z21: =VLOOKUP(B21,'[2]Pay sheet-JAN- 2021'!$C$18:$AF$125,6,0) -> 77497 | AA21: =VLOOKUP(B21,'[1]Pay sheet-APRIL- 2022'!$C$12:$AF$139,11,0) -> 46498.2 | AB21: 0 | AC21: 0 | AD21: =AE21+AF21+AG21+AH21 -> 31111.8 | AE21: =VLOOKUP(B21,'[1]Pay sheet-APRIL- 2022'!$C$12:$AF$139,12,0) -> 18599.28 | AF21: =VLOOKUP(B21,'[1]Pay sheet-APRIL- 2022'!$C$12:$AF$139,13,0) -> 2083 | AG21: =VLOOKUP(B21,'[1]Pay sheet-APRIL- 2022'!$C$12:$AF$139,14,0) -> 2083 | AH21: =VLOOKUP(B21,'[1]Pay sheet-APRIL- 2022'!$C$12:$AF$139,15,0) -> 8346.52 | AI21: =AA21+AB21+AC21+AE21+AF21+AG21+AH21 -> 77610 | AJ21: =VLOOKUP(B21,'[1]Pay sheet-APRIL- 2022'!$C$12:$AF$139,18,0) -> 1554.609 | AK21: =VLOOKUP(B21,'[1]Pay sheet-APRIL- 2022'!$C$12:$AF$139,19,0) -> 2236.5634 | AL21: =VLOOKUP(B21,'[1]Pay sheet-APRIL- 2022'!$C$12:$AF$139,20,0) -> 3874.85 | AM21: 0 | AN21: =AI21+AJ21+AK21+AL21+AM21 -> 85276.022 | AO21: 0 | AP21: =VLOOKUP(B21,'[1]Pay sheet-APRIL- 2022'!$C$12:$AF$139,26,0) -> 1800 | AQ21: =VLOOKUP(B21,'[1]Pay sheet-APRIL- 2022'!$C$12:$AF$139,25,0) -> 200 | AR21: =VLOOKUP(B21,'[1]Pay sheet-APRIL- 2022'!$C$12:$AF$139,24,0) -> 0 | AS21: =VLOOKUP(B21,'[1]Pay sheet-APRIL- 2022'!$C$12:$AF$139,27,0) -> 283 | AT21: =AP21+AQ21+AR21+AS21 -> 2283 | AU21: =AN21-AT21 -> 82993.022 | AV21: 05.05.2022 | AW21: ICICI BANK | AX21: 042401536750 | BA21: 8
A22: 39 | B22: BITS-692 | C22: Sneha Hande | D22: 09/11/1994 | E22: FEMALE | F22: Ramchandra Nathu Hande | G22: Project manager | H22: Ascendas,hinjawadi,phase 3 ,Hinjawadi Rajiv Gandhi Infotech Park. | I22: OOOO | J22: OOOO | K22: 35/A Hande niwas ,ganesh chawl,vasrang ,Khopoli,410203 | L22: OOOO | M22: OOOO | N22: OOOO | O22: 44566 | T22: 101257132190 | U22: N/A | V22: =C22 -> Sneha Hande | W22: 30 | X22: =VLOOKUP(B22,'[1]Pay sheet-APRIL- 2022'!$C$12:$AF$139,10,0) -> 30 | Y22: N/A | Z22: =VLOOKUP(B22,'[2]Pay sheet-JAN- 2021'!$C$18:$AF$125,6,0) -> 50617 | AA22: =VLOOKUP(B22,'[1]Pay sheet-APRIL- 2022'!$C$12:$AF$139,11,0) -> 30370.2 | AB22: 0 | AC22: 0 | AD22: =AE22+AF22+AG22+AH22 -> 20359.8 | AE22: =VLOOKUP(B22,'[1]Pay sheet-APRIL- 2022'!$C$12:$AF$139,12,0) -> 12148.08 | AF22: =VLOOKUP(B22,'[1]Pay sheet-APRIL- 2022'!$C$12:$AF$139,13,0) -> 2083 | AG22: =VLOOKUP(B22,'[1]Pay sheet-APRIL- 2022'!$C$12:$AF$139,14,0) -> 2083 | AH22: =VLOOKUP(B22,'[1]Pay sheet-APRIL- 2022'!$C$12:$AF$139,15,0) -> 4045.72 | AI22: =AA22+AB22+AC22+AE22+AF22+AG22+AH22 -> 50730 | AJ22: =VLOOKUP(B22,'[1]Pay sheet-APRIL- 2022'!$C$12:$AF$139,18,0) -> 1554.609 | AK22: =VLOOKUP(B22,'[1]Pay sheet-APRIL- 2022'!$C$12:$AF$139,19,0) -> 1460.8066 | AL22: =VLOOKUP(B22,'[1]Pay sheet-APRIL- 2022'!$C$12:$AF$139,20,0) -> 2530.85 | AM22: 0 | AN22: =AI22+AJ22+AK22+AL22+AM22 -> 56276.266 | AO22: 0 | AP22: =VLOOKUP(B22,'[1]Pay sheet-APRIL- 2022'!$C$12:$AF$139,26,0) -> 1800 | AQ22: =VLOOKUP(B22,'[1]Pay sheet-APRIL- 2022'!$C$12:$AF$139,25,0) -> 200 | AR22: =VLOOKUP(B22,'[1]Pay sheet-APRIL- 2022'!$C$12:$AF$139,24,0) -> 0 | AS22: =VLOOKUP(B22,'[1]Pay sheet-APRIL- 2022'!$C$12:$AF$139,27,0) -> 283 | AT22: =AP22+AQ22+AR22+AS22 -> 2283 | AU22: =AN22-AT22 -> 53993.266 | AV22: 05.05.2022 | AW22: ICICI BANK | AX22: 148001513263 | BA22: 9
A23: 40 | B23: BITS-698 | C23: Amol Gole | D23: 01/06/1991 | E23: MALE | F23: Harishchandra Gole | G23: Project Manager | H23: Shri ,Gurudatta krupa housing socity hill road, Sion,Chunabhatti ,Mumbai, Maharashtra, 400022 | I23: OOOO | J23: OOOO | K23: Nilgiri socity Building no 27,4th floor /4th room ,C-5,Sector 5, CBD Belapur ,Navi Mumbai, Maharashtra, 400614 | L23: OOOO | M23: OOOO | N23: OOOO | O23: 44579 | T23: 100769441289 | U23: N/A | V23: =C23 -> Amol Gole | W23: 30 | X23: =VLOOKUP(B23,'[1]Pay sheet-APRIL- 2022'!$C$12:$AF$139,10,0) -> 30 | Y23: N/A | Z23: =VLOOKUP(B23,'[2]Pay sheet-JAN- 2021'!$C$18:$AF$125,6,0) -> 66374 | AA23: =VLOOKUP(B23,'[1]Pay sheet-APRIL- 2022'!$C$12:$AF$139,11,0) -> 39824.4 | AB23: 0 | AC23: 0 | AD23: =AE23+AF23+AG23+AH23 -> 26662.6 | AE23: =VLOOKUP(B23,'[1]Pay sheet-APRIL- 2022'!$C$12:$AF$139,12,0) -> 15929.76 | AF23: =VLOOKUP(B23,'[1]Pay sheet-APRIL- 2022'!$C$12:$AF$139,13,0) -> 2083 | AG23: =VLOOKUP(B23,'[1]Pay sheet-APRIL- 2022'!$C$12:$AF$139,14,0) -> 2083 | AH23: =VLOOKUP(B23,'[1]Pay sheet-APRIL- 2022'!$C$12:$AF$139,15,0) -> 6566.84 | AI23: =AA23+AB23+AC23+AE23+AF23+AG23+AH23 -> 66487 | AJ23: =VLOOKUP(B23,'[1]Pay sheet-APRIL- 2022'!$C$12:$AF$139,18,0) -> 1554.609 | AK23: =VLOOKUP(B23,'[1]Pay sheet-APRIL- 2022'!$C$12:$AF$139,19,0) -> 1915.5536 | AL23: =VLOOKUP(B23,'[1]Pay sheet-APRIL- 2022'!$C$12:$AF$139,20,0) -> 3318.7 | AM23: 0 | AN23: =AI23+AJ23+AK23+AL23+AM23 -> 73275.863 | AO23: 0 | AP23: =VLOOKUP(B23,'[1]Pay sheet-APRIL- 2022'!$C$12:$AF$139,26,0) -> 1800 | AQ23: =VLOOKUP(B23,'[1]Pay sheet-APRIL- 2022'!$C$12:$AF$139,25,0) -> 200 | AR23: =VLOOKUP(B23,'[1]Pay sheet-APRIL- 2022'!$C$12:$AF$139,24,0) -> 0 | AS23: =VLOOKUP(B23,'[1]Pay sheet-APRIL- 2022'!$C$12:$AF$139,27,0) -> 283 | AT23: =AP23+AQ23+AR23+AS23 -> 2283 | AU23: =AN23-AT23 -> 70992.863 | AV23: 05.05.2022 | AW23: ICICI BANK | AX23: 623901548420 | BA23: 10
A24: 41 | B24: BITS-700 | C24: Sandeep Dixit | D24: 28764 | E24: MALE | F24: Surendra Singh | G24: Sr. Project Manager | H24: 782,sector 46 | I24: Gurgoan | J24: Haryana 122002 | K24: 782,Sector 46,Gurgaon,Haryana 122002 | L24: OOOO | M24: OOOO | N24: OOOO | O24: 44593 | T24: 100378934992 | U24: N/A | V24: Sandeep Dixit | W24: 30 | X24: =VLOOKUP(B24,'[1]Pay sheet-APRIL- 2022'!$C$12:$AF$139,10,0) -> 30 | Y24: N/A | Z24: 172968 | AA24: =VLOOKUP(B24,'[1]Pay sheet-APRIL- 2022'!$C$12:$AF$139,11,0) -> 103780.8 | AB24: 0 | AC24: 0 | AD24: =AE24+AF24+AG24+AH24 -> 69300.2 | AE24: =VLOOKUP(B24,'[1]Pay sheet-APRIL- 2022'!$C$12:$AF$139,12,0) -> 41512.32 | AF24: =VLOOKUP(B24,'[1]Pay sheet-APRIL- 2022'!$C$12:$AF$139,13,0) -> 2083 | AG24: =VLOOKUP(B24,'[1]Pay sheet-APRIL- 2022'!$C$12:$AF$139,14,0) -> 2083 | AH24: =VLOOKUP(B24,'[1]Pay sheet-APRIL- 2022'!$C$12:$AF$139,15,0) -> 23621.88 | AI24: =AA24+AB24+AC24+AE24+AF24+AG24+AH24 -> 173081 | AJ24: =VLOOKUP(B24,'[1]Pay sheet-APRIL- 2022'!$C$12:$AF$139,18,0) -> 1554.609 | AK24: =VLOOKUP(B24,'[1]Pay sheet-APRIL- 2022'!$C$12:$AF$139,19,0) -> 4991.8565 | AL24: =VLOOKUP(B24,'[1]Pay sheet-APRIL- 2022'!$C$12:$AF$139,20,0) -> 8648.4 | AM24: 0 | AN24: =AI24+AJ24+AK24+AL24+AM24 -> 188275.87 | AP24: =VLOOKUP(B24,'[1]Pay sheet-APRIL- 2022'!$C$12:$AF$139,26,0) -> 1800 | AQ24: =VLOOKUP(B24,'[1]Pay sheet-APRIL- 2022'!$C$12:$AF$139,25,0) -> 200 | AR24: =VLOOKUP(B24,'[1]Pay sheet-APRIL- 2022'!$C$12:$AF$139,24,0) -> 0 | AS24: =VLOOKUP(B24,'[1]Pay sheet-APRIL- 2022'!$C$12:$AF$139,27,0) -> 283 | AT24: =AP24+AQ24+AR24+AS24 -> 2283 | AU24: =AN24-AT24 -> 185992.87 | AV24: 05.05.2022 | AW24: Punjab National Bank | AX24: 12372191001001 | BA24: 11
A25: 42 | B25: BITS-717 | C25: Jaikesh Upadhyay | D25: 31778 | E25: MALE | F25: Ashok Upadhyay | G25: Sr. Project Coordinator | H25: H No 134,Pratap nagar | I25: Ratlam | J25: Madhya pradesh 457001 | K25: Sri vathsava house,SR no. 261/1/1,Sri dharshan colony,Kalvad road,Dhanori,Pune,MH,411015 | L25: OOOO | M25: OOOO | N25: OOOO | O25: 44609 | T25: 100448275999 | U25: N/A | V25: Jaikesh Upadhyay | W25: 30 | X25: =VLOOKUP(B25,'[1]Pay sheet-APRIL- 2022'!$C$12:$AF$139,10,0) -> 30 | Y25: N/A | Z25: 112719 | AA25: =VLOOKUP(B25,'[1]Pay sheet-APRIL- 2022'!$C$12:$AF$139,11,0) -> 67631.4 | AB25: 0 | AC25: 0 | AD25: =AE25+AF25+AG25+AH25 -> 45200.6 | AE25: =VLOOKUP(B25,'[1]Pay sheet-APRIL- 2022'!$C$12:$AF$139,12,0) -> 27052.56 | AF25: =VLOOKUP(B25,'[1]Pay sheet-APRIL- 2022'!$C$12:$AF$139,13,0) -> 2083 | AG25: =VLOOKUP(B25,'[1]Pay sheet-APRIL- 2022'!$C$12:$AF$139,14,0) -> 2083 | AH25: =VLOOKUP(B25,'[1]Pay sheet-APRIL- 2022'!$C$12:$AF$139,15,0) -> 13982.04 | AI25: =AA25+AB25+AC25+AE25+AF25+AG25+AH25 -> 112832 | AJ25: =VLOOKUP(B25,'[1]Pay sheet-APRIL- 2022'!$C$12:$AF$139,18,0) -> 1554.609 | AK25: =VLOOKUP(B25,'[1]Pay sheet-APRIL- 2022'!$C$12:$AF$139,19,0) -> 3253.0703 | AL25: =VLOOKUP(B25,'[1]Pay sheet-APRIL- 2022'!$C$12:$AF$139,20,0) -> 5635.95 | AM25: 0 | AN25: =AI25+AJ25+AK25+AL25+AM25 -> 123275.63 | AP25: =VLOOKUP(B25,'[1]Pay sheet-APRIL- 2022'!$C$12:$AF$139,26,0) -> 1800 | AQ25: =VLOOKUP(B25,'[1]Pay sheet-APRIL- 2022'!$C$12:$AF$139,25,0) -> 200 | AR25: =VLOOKUP(B25,'[1]Pay sheet-APRIL- 2022'!$C$12:$AF$139,24,0) -> 0 | AS25: =VLOOKUP(B25,'[1]Pay sheet-APRIL- 2022'!$C$12:$AF$139,27,0) -> 283 | AT25: =AP25+AQ25+AR25+AS25 -> 2283 | AU25: =AN25-AT25 -> 120992.63 | AV25: 05.05.2022 | AW25: ICICI BANK | AX25: 338201500480 | BA25: 12
A26: 43 | B26: BITS-720 | C26: Jyoti Singh | D26: 34895 | E26: FEMALE | F26: Ashok Kumar Singh | G26: Sr.Security analyst | H26: Room F1,C 38,Sai apartments,JBTS gardens,Chhatrapur,New Delhi 110074 | I26: JBTS gardens,Chhatrapur | J26: New Delhi 110074 | K26: Room F1,C 38,Sai apartments,JBTS gardens,Chhatrapur,New Delhi 110074 | L26: OOOO | M26: OOOO | N26: OOOO | O26: 44613 | T26: OOOO | U26: N/A | V26: Jyoti Singh | W26: 30 | X26: =VLOOKUP(B26,'[1]Pay sheet-APRIL- 2022'!$C$12:$AF$139,10,0) -> 30 | Y26: N/A | Z26: 103450 | AA26: =VLOOKUP(B26,'[1]Pay sheet-APRIL- 2022'!$C$12:$AF$139,11,0) -> 62070 | AB26: 0 | AC26: 0 | AD26: =AE26+AF26+AG26+AH26 -> 41493 | AE26: =VLOOKUP(B26,'[1]Pay sheet-APRIL- 2022'!$C$12:$AF$139,12,0) -> 24828 | AF26: =VLOOKUP(B26,'[1]Pay sheet-APRIL- 2022'!$C$12:$AF$139,13,0) -> 2083 | AG26: =VLOOKUP(B26,'[1]Pay sheet-APRIL- 2022'!$C$12:$AF$139,14,0) -> 2083 | AH26: =VLOOKUP(B26,'[1]Pay sheet-APRIL- 2022'!$C$12:$AF$139,15,0) -> 12499 | AI26: =AA26+AB26+AC26+AE26+AF26+AG26+AH26 -> 103563 | AJ26: =VLOOKUP(B26,'[1]Pay sheet-APRIL- 2022'!$C$12:$AF$139,18,0) -> 1554.609 | AK26: =VLOOKUP(B26,'[1]Pay sheet-APRIL- 2022'!$C$12:$AF$139,19,0) -> 2985.567 | AL26: =VLOOKUP(B26,'[1]Pay sheet-APRIL- 2022'!$C$12:$AF$139,20,0) -> 5172.5 | AM26: 0 | AN26: =AI26+AJ26+AK26+AL26+AM26 -> 113275.68 | AP26: =VLOOKUP(B26,'[1]Pay sheet-APRIL- 2022'!$C$12:$AF$139,26,0) -> 0 | AQ26: =VLOOKUP(B26,'[1]Pay sheet-APRIL- 2022'!$C$12:$AF$139,25,0) -> 200 | AR26: =VLOOKUP(B26,'[1]Pay sheet-APRIL- 2022'!$C$12:$AF$139,24,0) -> 0 | AS26: =VLOOKUP(B26,'[1]Pay sheet-APRIL- 2022'!$C$12:$AF$139,27,0) -> 283 | AT26: =AP26+AQ26+AR26+AS26 -> 483 | AU26: =AN26-AT26 -> 112792.68 | AV26: 05.05.2022 | AW26: ICICI BANK | AX26: 341901505420 | BA26: 13
A27: 44 | B27: BITS-733 | C27: Chandrashekar Patil | D27: 34710 | E27: MALE | F27: Shivraj Patil | G27: Project Manager | H27: At post Malegaon,Maqta,Taluq Deglur,Nanded district,Maharastra 431718 | I27: Q-198,Govt Quarters,Sastry nagar,Erawada,Pune 411006 | J27: qqqq | K27: qqqq | L27: qqqq | M27: qqqq | N27: qqqq | O27: 44634 | T27: 100783283673 | U27: N/A | V27: Chandrashekar Patil | W27: 30 | X27: =VLOOKUP(B27,'[1]Pay sheet-APRIL- 2022'!$C$12:$AF$139,10,0) -> 27 | Y27: N/A | Z27: 73789 | AA27: =VLOOKUP(B27,'[1]Pay sheet-APRIL- 2022'!$C$12:$AF$139,11,0) -> 39846.06 | AB27: 0 | AC27: 0 | AD27: =AE27+AF27+AG27+AH27 -> 26677.04 | AE27: =VLOOKUP(B27,'[1]Pay sheet-APRIL- 2022'!$C$12:$AF$139,12,0) -> 15938.424 | AF27: =VLOOKUP(B27,'[1]Pay sheet-APRIL- 2022'!$C$12:$AF$139,13,0) -> 1875 | AG27: =VLOOKUP(B27,'[1]Pay sheet-APRIL- 2022'!$C$12:$AF$139,14,0) -> 1875 | AH27: =VLOOKUP(B27,'[1]Pay sheet-APRIL- 2022'!$C$12:$AF$139,15,0) -> 6988.616 | AI27: =AA27+AB27+AC27+AE27+AF27+AG27+AH27 -> 66523.1 | AJ27: =VLOOKUP(B27,'[1]Pay sheet-APRIL- 2022'!$C$12:$AF$139,18,0) -> 1554.609 | AK27: =VLOOKUP(B27,'[1]Pay sheet-APRIL- 2022'!$C$12:$AF$139,19,0) -> 1916.5955 | AL27: =VLOOKUP(B27,'[1]Pay sheet-APRIL- 2022'!$C$12:$AF$139,20,0) -> 3320.505 | AM27: 0 | AN27: =AI27+AJ27+AK27+AL27+AM27 -> 73314.809 | AP27: =VLOOKUP(B27,'[1]Pay sheet-APRIL- 2022'!$C$12:$AF$139,26,0) -> 1800 | AQ27: =VLOOKUP(B27,'[1]Pay sheet-APRIL- 2022'!$C$12:$AF$139,25,0) -> 200 | AR27: =VLOOKUP(B27,'[1]Pay sheet-APRIL- 2022'!$C$12:$AF$139,24,0) -> 0 | AS27: =VLOOKUP(B27,'[1]Pay sheet-APRIL- 2022'!$C$12:$AF$139,27,0) -> 283 | AT27: =AP27+AQ27+AR27+AS27 -> 2283 | AU27: =AN27-AT27 -> 71031.809 | AV27: 05.05.2022 | AW27: HDFC | AX27: 100783283673 | BA27: 14
A28: 45 | B28: BITS-734 | C28: ShaikFarooq Basha | D28: 33370 | E28: MALE | F28: Shaik Mabu Subahan | G28: Software Engineer | H28: 2-112,Kakkalapally colony,Ananthapur,AP 515001 | I28: 2-112,Kakkalapally colony,Ananthapur,AP 515001 | J28: qqqq | K28: qqqq | L28: qqqq | M28: qqqq | N28: qqqq | O28: 44636 | T28: 101625103757 | U28: N/A | V28: ShaikFarooq Basha | W28: 30 | X28: =VLOOKUP(B28,'[1]Pay sheet-APRIL- 2022'!$C$12:$AF$139,10,0) -> 30 | Y28: N/A | Z28: 103450 | AA28: =VLOOKUP(B28,'[1]Pay sheet-APRIL- 2022'!$C$12:$AF$139,11,0) -> 62070 | AB28: 0 | AC28: 0 | AD28: =AE28+AF28+AG28+AH28 -> 41493 | AE28: =VLOOKUP(B28,'[1]Pay sheet-APRIL- 2022'!$C$12:$AF$139,12,0) -> 24828 | AF28: =VLOOKUP(B28,'[1]Pay sheet-APRIL- 2022'!$C$12:$AF$139,13,0) -> 2083 | AG28: =VLOOKUP(B28,'[1]Pay sheet-APRIL- 2022'!$C$12:$AF$139,14,0) -> 2083 | AH28: =VLOOKUP(B28,'[1]Pay sheet-APRIL- 2022'!$C$12:$AF$139,15,0) -> 12499 | AI28: =AA28+AB28+AC28+AE28+AF28+AG28+AH28 -> 103563 | AJ28: =VLOOKUP(B28,'[1]Pay sheet-APRIL- 2022'!$C$12:$AF$139,18,0) -> 1554.609 | AK28: =VLOOKUP(B28,'[1]Pay sheet-APRIL- 2022'!$C$12:$AF$139,19,0) -> 2985.567 | AL28: =VLOOKUP(B28,'[1]Pay sheet-APRIL- 2022'!$C$12:$AF$139,20,0) -> 5172.5 | AM28: 0 | AN28: =AI28+AJ28+AK28+AL28+AM28 -> 113275.68 | AP28: =VLOOKUP(B28,'[1]Pay sheet-APRIL- 2022'!$C$12:$AF$139,26,0) -> 1800 | AQ28: =VLOOKUP(B28,'[1]Pay sheet-APRIL- 2022'!$C$12:$AF$139,25,0) -> 200 | AR28: =VLOOKUP(B28,'[1]Pay sheet-APRIL- 2022'!$C$12:$AF$139,24,0) -> 7419 | AS28: =VLOOKUP(B28,'[1]Pay sheet-APRIL- 2022'!$C$12:$AF$139,27,0) -> 283 | AT28: =AP28+AQ28+AR28+AS28 -> 9702 | AU28: =AN28-AT28 -> 103573.68 | AV28: 05.05.2022 | AW28: HDFC | AX28: 50100383537784 | BA28: 15
A29: 46 | B29: BITS-738 | C29: NILOTPAL BHOWAL | D29: 31584 | E29: MALE | F29: Dwijendra Kumar Bhowal | G29: VM ware consultant | H29: P-53,Niva park extension,Badam Talad,Brahmapur,Kolkatta-700096 | I29: Sri laxmi PG narayan nagar,Hinjewadi phase I,Pune 411057 | J29: qqqq | K29: qqqq | L29: qqqq | M29: qqqq | N29: qqqq | O29: 44650 | T29: 101804644762 | U29: N/A | V29: NILOTPAL BHOWAL | W29: 30 | X29: =VLOOKUP(B29,'[1]Pay sheet-APRIL- 2022'!$C$12:$AF$139,10,0) -> 30 | Y29: N/A | Z29: 121988 | AA29: =VLOOKUP(B29,'[1]Pay sheet-APRIL- 2022'!$C$12:$AF$139,11,0) -> 73192.8 | AB29: 0 | AC29: 0 | AD29: =AE29+AF29+AG29+AH29 -> 48908.2 | AE29: =VLOOKUP(B29,'[1]Pay sheet-APRIL- 2022'!$C$12:$AF$139,12,0) -> 29277.12 | AF29: =VLOOKUP(B29,'[1]Pay sheet-APRIL- 2022'!$C$12:$AF$139,13,0) -> 2083 | AG29: =VLOOKUP(B29,'[1]Pay sheet-APRIL- 2022'!$C$12:$AF$139,14,0) -> 2083 | AH29: =VLOOKUP(B29,'[1]Pay sheet-APRIL- 2022'!$C$12:$AF$139,15,0) -> 15465.08 | AI29: =AA29+AB29+AC29+AE29+AF29+AG29+AH29 -> 122101 | AJ29: =VLOOKUP(B29,'[1]Pay sheet-APRIL- 2022'!$C$12:$AF$139,18,0) -> 1554.609 | AK29: =VLOOKUP(B29,'[1]Pay sheet-APRIL- 2022'!$C$12:$AF$139,19,0) -> 3520.5737 | AL29: =VLOOKUP(B29,'[1]Pay sheet-APRIL- 2022'!$C$12:$AF$139,20,0) -> 6099.4 | AM29: 0 | AN29: =AI29+AJ29+AK29+AL29+AM29 -> 133275.58 | AP29: =VLOOKUP(B29,'[1]Pay sheet-APRIL- 2022'!$C$12:$AF$139,26,0) -> 1800 | AQ29: =VLOOKUP(B29,'[1]Pay sheet-APRIL- 2022'!$C$12:$AF$139,25,0) -> 200 | AR29: =VLOOKUP(B29,'[1]Pay sheet-APRIL- 2022'!$C$12:$AF$139,24,0) -> 0 | AS29: =VLOOKUP(B29,'[1]Pay sheet-APRIL- 2022'!$C$12:$AF$139,27,0) -> 283 | AT29: =AP29+AQ29+AR29+AS29 -> 2283 | AU29: =AN29-AT29 -> 130992.58 | AV29: 05.05.2022 | AW29: ICICI bank | AX29: 272301504703 | BA29: 16
A30: 47 | B30: BITS-751 | C30: Varsha Amit Kadam | D30: 31018 | E30: FEMALE | F30: Amit Kadam | G30: Program Manager | H30: 1/87,Ramdut building,currey Road,Mumbai | I30: Mumbai | J30: Maharastra 400012 | K30: Flat No.204,Melody Appts,Waked | L30: Pune | M30: Maharastra | N30: 411057 | O30: 44676 | T30: 101012347096 | U30: N/A | V30: Varsha AmitKadam | W30: 30 | X30: =VLOOKUP(B30,'[1]Pay sheet-APRIL- 2022'!$C$12:$AF$139,10,0) -> 6 | Z30: 54324 | AA30: =VLOOKUP(B30,'[1]Pay sheet-APRIL- 2022'!$C$12:$AF$139,11,0) -> 6518.88 | AB30: 0 | AC30: 0 | AE30: =VLOOKUP(B30,'[1]Pay sheet-APRIL- 2022'!$C$12:$AF$139,12,0) -> 2607.552 | AF30: =VLOOKUP(B30,'[1]Pay sheet-APRIL- 2022'!$C$12:$AF$139,13,0) -> 417 | AG30: =VLOOKUP(B30,'[1]Pay sheet-APRIL- 2022'!$C$12:$AF$139,14,0) -> 417 | AH30: =VLOOKUP(B30,'[1]Pay sheet-APRIL- 2022'!$C$12:$AF$139,15,0) -> 1017.368 | AI30: =AA30+AB30+AC30+AE30+AF30+AG30+AH30 -> 10977.8 | AJ30: =VLOOKUP(B30,'[1]Pay sheet-APRIL- 2022'!$C$12:$AF$139,18,0) -> 1554.609 | AK30: =VLOOKUP(B30,'[1]Pay sheet-APRIL- 2022'!$C$12:$AF$139,19,0) -> 313.55813 | AL30: =VLOOKUP(B30,'[1]Pay sheet-APRIL- 2022'!$C$12:$AF$139,20,0) -> 543.24 | AM30: 0 | AN30: =AI30+AJ30+AK30+AL30+AM30 -> 13389.207 | AP30: =VLOOKUP(B30,'[1]Pay sheet-APRIL- 2022'!$C$12:$AF$139,26,0) -> 782 | AQ30: =VLOOKUP(B30,'[1]Pay sheet-APRIL- 2022'!$C$12:$AF$139,25,0) -> 0 | AR30: =VLOOKUP(B30,'[1]Pay sheet-APRIL- 2022'!$C$12:$AF$139,24,0) -> 0 | AS30: =VLOOKUP(B30,'[1]Pay sheet-APRIL- 2022'!$C$12:$AF$139,27,0) -> 0 | AT30: =AP30+AQ30+AR30+AS30 -> 782 | AU30: =AN30-AT30 -> 12607.207 | AV30: 05.05.2022 | AW30: Kotak Mahindra Bank | AX30: 7311156365
X31: =SUM(X17:X30) -> 380 | AA31: =SUM(AA17:AA30) -> 655324.54 | AE31: =SUM(AE17:AE30) -> 262129.82 | AF31: =SUM(AF17:AF30) -> 26386 | AG31: =SUM(AG17:AG30) -> 26386 | AH31: =SUM(AH17:AH30) -> 123563.21 | AI31: =SUM(AI17:AI30) -> 1093789.6 | AJ31: =SUM(AJ17:AJ30) -> 21764.526 | AK31: =SUM(AK17:AK30) -> 31521.11 | AL31: =SUM(AL17:AL30) -> 54610.378 | AP31: =SUM(AP17:AP30) -> 22382 | AQ31: =SUM(AQ17:AQ30) -> 2600 | AR31: =SUM(AR17:AR30) -> 7419 | AS31: =SUM(AS17:AS30) -> 4025.337 | AT31: =SUM(AT17:AT30) -> 36426.337 | AU31: =SUM(AU17:AU30) -> 1165259.2
A39: 24 | B39: BITS-556 | D39: 33030 | E39: MALE | F39: Ashok Bhavisar | H39: Mukam post, Kanalda,Taluka,Jalgaon, Kanvashramroad, new Busstand, Kanalde, Jalgaon,MH 425002 | K39: Mukam post, Kanalda,Taluka,Jalgaon, Kanvashramroad, new Busstand, Kanalde, Jalgaon,MH 425002 | O39: 4th May 2021 | T39: 100973367737 | U39: N/A | V39: =C39 -> 0 | W39: 31 | X39: =VLOOKUP(B39,'[3]Pay sheet-MARCH- 2022'!$C$13:$AF$146,10,0) -> 16 | Y39: N/A | Z39: =VLOOKUP(B39,'[2]Pay sheet-JAN- 2021'!$C$18:$AF$125,6,0) -> 68228 | AA39: =VLOOKUP(B39,'[3]Pay sheet-MARCH- 2022'!$C$13:$AF$146,11,0) -> 21128.671 | AB39: 0 | AC39: 0 | AD39: =AE39+AF39+AG39+AH39 -> 14085.781 | AE39: =VLOOKUP(B39,'[3]Pay sheet-MARCH- 2022'!$C$13:$AF$146,12,0) -> 8451.4684 | AF39: =VLOOKUP(B39,'[3]Pay sheet-MARCH- 2022'!$C$13:$AF$146,13,0) -> 1075 | AG39: =VLOOKUP(B39,'[3]Pay sheet-MARCH- 2022'!$C$13:$AF$146,14,0) -> 1075 | AH39: =VLOOKUP(B39,'[3]Pay sheet-MARCH- 2022'!$C$13:$AF$146,15,0) -> 3484.3123 | AI39: =AA39+AB39+AC39+AE39+AF39+AG39+AH39 -> 35214.452 | AJ39: =VLOOKUP(B39,'[3]Pay sheet-MARCH- 2022'!$C$13:$AF$146,18,0) -> 1441.609 | AK39: =VLOOKUP(B39,'[3]Pay sheet-MARCH- 2022'!$C$13:$AF$146,19,0) -> 1016.2891 | AL39: =VLOOKUP(B39,'[3]Pay sheet-MARCH- 2022'!$C$13:$AF$146,20,0) -> 1760.7226 | AM39: =VLOOKUP(B39,'[3]Pay sheet-MARCH- 2022'!$C$13:$AF$146,22,0) -> #REF! | AO39: 0 | AP39: =VLOOKUP(B39,'[3]Pay sheet-MARCH- 2022'!$C$13:$AF$146,26,0) -> 1800 | AQ39: =VLOOKUP(B39,'[3]Pay sheet-MARCH- 2022'!$C$13:$AF$146,25,0) -> 200 | AR39: =VLOOKUP(B39,'[3]Pay sheet-MARCH- 2022'!$C$13:$AF$146,24,0) -> 3232 | AS39: =VLOOKUP(B39,'[3]Pay sheet-MARCH- 2022'!$C$13:$AF$146,27,0) -> 391.78785 | AT39: =AP39+AQ39+AR39+AS39 -> 5623.7878 | AU39: =AN39-AT39 -> -5623.7878 | AV39: 05.05.2022 | AW39: SBI | AX39: A/C'20163843796 | BA39: 2
A40: 33 | B40: BITS-651 | D40: 32523 | E40: FEMALE | F40: Sumit Dongare | H40: Pno.22A Snehswapna Padma Colony Opp SSC Board Kolhapur 416008 | K40: MB92 New Indira colony Near public school Burhanpur 450331 | L40: OO | M40: OO | N40: OO | O40: 44481 | T40: 100812322217 | U40: N/A | V40: Snehal Shirsat | W40: 31 | X40: =VLOOKUP(B40,'[3]Pay sheet-MARCH- 2022'!$C$13:$AF$146,10,0) -> 31 | Y40: N/A | Z40: =VLOOKUP(B40,'[2]Pay sheet-JAN- 2021'!$C$18:$AF$125,6,0) -> 58959 | AA40: =VLOOKUP(B40,'[3]Pay sheet-MARCH- 2022'!$C$13:$AF$146,11,0) -> 35375.4 | AB40: 0 | AC40: 0 | AD40: =AE40+AF40+AG40+AH40 -> 23583.6 | AE40: =VLOOKUP(B40,'[3]Pay sheet-MARCH- 2022'!$C$13:$AF$146,12,0) -> 14150.16 | AF40: =VLOOKUP(B40,'[3]Pay sheet-MARCH- 2022'!$C$13:$AF$146,13,0) -> 2083 | AG40: =VLOOKUP(B40,'[3]Pay sheet-MARCH- 2022'!$C$13:$AF$146,14,0) -> 2083 | AH40: =VLOOKUP(B40,'[3]Pay sheet-MARCH- 2022'!$C$13:$AF$146,15,0) -> 5267.44 | AI40: =AA40+AB40+AC40+AE40+AF40+AG40+AH40 -> 58959 | AJ40: =VLOOKUP(B40,'[3]Pay sheet-MARCH- 2022'!$C$13:$AF$146,18,0) -> 1441.609 | AK40: =VLOOKUP(B40,'[3]Pay sheet-MARCH- 2022'!$C$13:$AF$146,19,0) -> 1701.5567 | AL40: =VLOOKUP(B40,'[3]Pay sheet-MARCH- 2022'!$C$13:$AF$146,20,0) -> 2947.95 | AM40: =VLOOKUP(B40,'[3]Pay sheet-MARCH- 2022'!$C$13:$AF$146,22,0) -> #REF! | AO40: 0 | AP40: =VLOOKUP(B40,'[3]Pay sheet-MARCH- 2022'!$C$13:$AF$146,26,0) -> 1800 | AQ40: =VLOOKUP(B40,'[3]Pay sheet-MARCH- 2022'!$C$13:$AF$146,25,0) -> 200 | AR40: =VLOOKUP(B40,'[3]Pay sheet-MARCH- 2022'!$C$13:$AF$146,24,0) -> #REF! | AS40: =VLOOKUP(B40,'[3]Pay sheet-MARCH- 2022'!$C$13:$AF$146,27,0) -> 254 | AT40: =AP40+AQ40+AR40+AS40 -> #REF! | AU40: =AN40-AT40 -> #REF! | AV40: 05.05.2022 | AW40: HDFC BANK | AX40: 50100083666209 | BA40: 5
A41: 34 | B41: BITS-657 | D41: 33253 | E41: FEMALE | F41: sharad shukla | H41: 15/A chandra colony Rajanandgaon Chhattisgarh | K41: 15/A chandra colony Rajanandgaon Chhattisgarh | L41: OO | M41: OO | N41: OO | O41: 44481 | T41: 100533606039 | U41: N/A | V41: Shashanki Mishra | W41: 31 | X41: =VLOOKUP(B41,'[3]Pay sheet-MARCH- 2022'!$C$13:$AF$146,10,0) -> 15 | Y41: N/A | Z41: =VLOOKUP(B41,'[2]Pay sheet-JAN- 2021'!$C$18:$AF$125,6,0) -> 47836 | AA41: =VLOOKUP(B41,'[3]Pay sheet-MARCH- 2022'!$C$13:$AF$146,11,0) -> 13887.871 | AB41: 0 | AC41: 0 | AD41: =AE41+AF41+AG41+AH41 -> 9258.5806 | AE41: =VLOOKUP(B41,'[3]Pay sheet-MARCH- 2022'!$C$13:$AF$146,12,0) -> 5555.1484 | AF41: =VLOOKUP(B41,'[3]Pay sheet-MARCH- 2022'!$C$13:$AF$146,13,0) -> 1008 | AG41: =VLOOKUP(B41,'[3]Pay sheet-MARCH- 2022'!$C$13:$AF$146,14,0) -> 1008 | AH41: =VLOOKUP(B41,'[3]Pay sheet-MARCH- 2022'!$C$13:$AF$146,15,0) -> 1687.4323 | AI41: =AA41+AB41+AC41+AE41+AF41+AG41+AH41 -> 23146.452 | AJ41: =VLOOKUP(B41,'[3]Pay sheet-MARCH- 2022'!$C$13:$AF$146,18,0) -> 1441.609 | AK41: =VLOOKUP(B41,'[3]Pay sheet-MARCH- 2022'!$C$13:$AF$146,19,0) -> 668.00659 | AL41: =VLOOKUP(B41,'[3]Pay sheet-MARCH- 2022'!$C$13:$AF$146,20,0) -> 1157.3226 | AM41: =VLOOKUP(B41,'[3]Pay sheet-MARCH- 2022'!$C$13:$AF$146,22,0) -> #REF! | AO41: 0 | AP41: =VLOOKUP(B41,'[3]Pay sheet-MARCH- 2022'!$C$13:$AF$146,26,0) -> 1667 | AQ41: =VLOOKUP(B41,'[3]Pay sheet-MARCH- 2022'!$C$13:$AF$146,25,0) -> 200 | AR41: =VLOOKUP(B41,'[3]Pay sheet-MARCH- 2022'!$C$13:$AF$146,24,0) -> #REF! | AS41: =VLOOKUP(B41,'[3]Pay sheet-MARCH- 2022'!$C$13:$AF$146,27,0) -> 254 | AT41: =AP41+AQ41+AR41+AS41 -> #REF! | AU41: =AN41-AT41 -> #REF! | AV41: 05.05.2022 | AW41: ICIC | AX41: 624001562353 | BA41: 6

Sheet 4-22Eq Rrem
A1: Form D
A2: (See rule 6)
A4: Register to be maintained by the employer under rule 6 of the Equal Remuneration Rules, 1976
E6: ='4-22MASTER'!E10 -> 44652
A8: Name and address of Contractor : | G8: ='4-22MASTER'!G5 -> Burgeon IT Services Pvt.Ltd.
A10: Name and address of establishment in/under which contract is carried on : | G10: ='4-22MASTER'!AQ5 -> Burgeon IT Services Pvt.Ltd.
G11: ='4-22MASTER'!AQ6 -> Siri Mansion LIGB 436 Dr.A S Rao Nagar,Hyderabad
A12: Name and address of Principal Employer : | G12: ='4-22MASTER'!AQ10 -> INFOSYS LTD.IL Ascendas SEZ Unit,Building Juniper
G13: ='4-22MASTER'!AQ11 -> International Tech Park,Rajiv Gandhi Infotech Park,Hinjawadi,Pune,Maharashtra
A14: Total number of men workers employed | D14: =E34 -> 10
A16: Total number of women workers employed | D16: =D34 -> 4
D18: Components of remuneration
A19: Category of workers | B19: Brief Description of work | D19: No of women employed | E19: No. of men employed | F19: Rate or remuneration paid | G19: Basic wage & Dearness Allowance | H19: House Rent allowance | I19: Other allowances | J19: Cash value of concessional supply of essential commodities | K19: Name of the Client | L19: Primary Work Place/ Location
A20: ='4-22MASTER'!G17 -> System Administrator | B20: IT SUPPORTIVE SERVICES | D20: 0 | E20: 1 | F20: ='4-22MASTER'!Z17 -> 61740 | G20: ='4-22MASTER'!AA17 -> 37044 | H20: ='4-22MASTER'!AE17 -> 14817.6 | I20: =F20-(G20+H20) -> 9878.4 | J20: 0
A21: ='4-22MASTER'!G18 -> Project Manager | B21: IT SUPPORTIVE SERVICES | D21: 0 | E21: 1 | F21: ='4-22MASTER'!Z18 -> 71009 | G21: ='4-22MASTER'!AA18 -> 28403.6 | H21: ='4-22MASTER'!AE18 -> 11361.44 | I21: =F21-(G21+H21) -> 31243.96 | J21: 0
A22: ='4-22MASTER'!G19 -> Project Coordinator | B22: IT SUPPORTIVE SERVICES | D22: 0 | E22: 1 | F22: ='4-22MASTER'!Z19 -> 43202 | G22: ='4-22MASTER'!AA19 -> 25057.16 | H22: ='4-22MASTER'!AE19 -> 10022.864 | I22: =F22-(G22+H22) -> 8121.976 | J22: 0
A23: ='4-22MASTER'!G20 -> Project Engineer | B23: IT SUPPORTIVE SERVICES | D23: 1 | E23: 0 | F23: ='4-22MASTER'!Z20 -> 58959 | G23: ='4-22MASTER'!AA20 -> 33017.04 | H23: ='4-22MASTER'!AE20 -> 13206.816 | I23: =F23-(G23+H23) -> 12735.144 | J23: 0
A24: ='4-22MASTER'!G21 -> Network Engineer | B24: IT SUPPORTIVE SERVICES | D24: 0 | E24: 1 | F24: ='4-22MASTER'!Z21 -> 77497 | G24: ='4-22MASTER'!AA21 -> 46498.2 | H24: ='4-22MASTER'!AE21 -> 18599.28 | I24: =F24-(G24+H24) -> 12399.52 | J24: 0
A25: ='4-22MASTER'!G22 -> Project manager | B25: IT SUPPORTIVE SERVICES | D25: 1 | E25: 0 | F25: ='4-22MASTER'!Z22 -> 50617 | G25: ='4-22MASTER'!AA22 -> 30370.2 | H25: ='4-22MASTER'!AE22 -> 12148.08 | I25: =F25-(G25+H25) -> 8098.72 | J25: 0
A26: ='4-22MASTER'!G23 -> Project Manager | B26: IT SUPPORTIVE SERVICES | D26: 0 | E26: 1 | F26: ='4-22MASTER'!Z23 -> 66374 | G26: ='4-22MASTER'!AA23 -> 39824.4 | H26: ='4-22MASTER'!AE23 -> 15929.76 | I26: =F26-(G26+H26) -> 10619.84 | J26: 0
A27: ='4-22MASTER'!G24 -> Sr. Project Manager | B27: IT SUPPORTIVE SERVICES | D27: 0 | E27: 1 | F27: ='4-22MASTER'!Z24 -> 172968 | G27: ='4-22MASTER'!AA24 -> 103780.8 | H27: ='4-22MASTER'!AE24 -> 41512.32 | I27: =F27-(G27+H27) -> 27674.88 | J27: 0
A28: ='4-22MASTER'!G25 -> Sr. Project Coordinator | B28: IT SUPPORTIVE SERVICES | D28: 0 | E28: 1 | F28: ='4-22MASTER'!Z25 -> 112719 | G28: ='4-22MASTER'!AA25 -> 67631.4 | H28: ='4-22MASTER'!AE25 -> 27052.56 | I28: =F28-(G28+H28) -> 18035.04 | J28: 0
A29: ='4-22MASTER'!G26 -> Sr.Security analyst | B29: IT SUPPORTIVE SERVICES | D29: 1 | E29: 0 | F29: ='4-22MASTER'!Z26 -> 103450 | G29: ='4-22MASTER'!AA26 -> 62070 | H29: ='4-22MASTER'!AE26 -> 24828 | I29: =F29-(G29+H29) -> 16552 | J29: 0
A30: ='4-22MASTER'!G27 -> Project Manager | B30: IT SUPPORTIVE SERVICES | D30: 0 | E30: 1 | F30: ='4-22MASTER'!Z27 -> 73789 | G30: ='4-22MASTER'!AA27 -> 39846.06 | H30: ='4-22MASTER'!AE27 -> 15938.424 | I30: =F30-(G30+H30) -> 18004.516 | J30: 0
A31: ='4-22MASTER'!G28 -> Software Engineer | B31: IT SUPPORTIVE SERVICES | D31: 0 | E31: 1 | F31: ='4-22MASTER'!Z28 -> 103450 | G31: ='4-22MASTER'!AA28 -> 62070 | H31: ='4-22MASTER'!AE28 -> 24828 | I31: =F31-(G31+H31) -> 16552 | J31: 0
... A33: ='4-22MASTER'!G30 -> Program Manager | B33: IT SUPPORTIVE SERVICES | D33: 1 | E33: 0 | F33: ='4-22MASTER'!Z30 -> 54324 | G33: ='4-22MASTER'!AA30 -> 6518.88 | H33: ='4-22MASTER'!AE30 -> 2607.552 | I33: =F33-(G33+H33) -> 45197.568 | J33: 0
D34: =SUM(D20:D33) -> 4 | E34: =SUM(E20:E33) -> 10
F48: Signature of the Contractor with Seal

Sheet APRIL  22 MH_MusT
A1: Form No. II
A2: [M. W. Rules under Maharashtra Contract Labour (Regulation and Abolition)1963 Rule 27 (I)]
A3: Muster Roll cum Wages Register for the month of APRIL 2022
A4: Name and Address of Contractor : BURGEON IT SERVICES PVT.LTD. SIRI MANSION LIG 436 DR.A S RAO NAGAR,HYDERABAD 500 060
H5: Working Hours | J5: Interval for Rest | L5: No. of Hours Worked
A6: Sl.No. | B6: Employee Code | C6: Full Name of Employee | D6: Date of Birth | E6: Gender | F6: Date of Entry into Service | G6: Nature of Work & Designation | H6: From | I6: To | J6: From | K6: To | L6: 1 | M6: 2 | N6: 3 | O6: 4 | P6: 5 | Q6: 6 | R6: 7 | S6: 8 | T6: 9 | U6: 10 | V6: 11 | W6: 12 | X6: 13 | Y6: 14 | Z6: 15 | AA6: 16 | AB6: 17 | AC6: 18 | AD6: 19 | AE6: 20 | AF6: 21 | AG6: 22 | AH6: 23 | AI6: 24 | AJ6: 25 | AK6: 26 | AL6: 27 | AM6: 28 | AN6: 29 | AO6: 30 | AP6: MONTH DAYS
A7: 1 | B7: ='4-22MASTER'!B17 -> BITS-542 | C7: ='4-22MASTER'!C17 -> Haneef | D7: ='4-22MASTER'!D17 -> 34715 | E7: ='4-22MASTER'!E17 -> MALE | F7: ='4-22MASTER'!O17 -> 44298 | G7: ='4-22MASTER'!G17 -> System Administrator | L7: P | M7: WO | N7: WO | O7: P | P7: P | Q7: P | R7: P | S7: P | T7: WO | U7: WO | V7: P | W7: P | X7: P | Y7: P | Z7: H | AA7: WO | AB7: WO | AC7: P | AD7: P | AE7: P | AF7: P | AG7: P | AH7: WO | AI7: WO | AJ7: P | AK7: P | AL7: P | AM7: P | AN7: P | AO7: WO | AP7: ='4-22MASTER'!X17 -> 30
A8: 2 | B8: ='4-22MASTER'!B18 -> BITS-557 | C8: ='4-22MASTER'!C18 -> Ved Prakash | D8: ='4-22MASTER'!D18 -> 30321 | E8: ='4-22MASTER'!E18 -> MALE | F8: ='4-22MASTER'!O18 -> 4th May 2021 | G8: ='4-22MASTER'!G18 -> Project Manager | L8: P | M8: WO | N8: WO | O8: P | P8: P | Q8: P | R8: P | S8: P | T8: WO | U8: WO | V8: P | W8: P | X8: P | Y8: P | Z8: H | AA8: WO | AB8: WO | AC8: P | AD8: P | AE8: P | AP8: ='4-22MASTER'!X18 -> 20
A9: 3 | B9: ='4-22MASTER'!B19 -> BITS-559 | C9: ='4-22MASTER'!C19 -> GauravVispute | D9: ='4-22MASTER'!D19 -> 33721 | E9: ='4-22MASTER'!E19 -> MALE | F9: ='4-22MASTER'!O19 -> 4th May 2021 | G9: ='4-22MASTER'!G19 -> Project Coordinator | L9: P | M9: WO | N9: WO | O9: P | P9: P | Q9: P | R9: P | S9: P | T9: WO | U9: WO | V9: P | W9: P | X9: P | Y9: P | Z9: H | AA9: WO | AB9: WO | AC9: EL | AD9: A | AE9: P | AF9: P | AG9: P | AH9: WO | AI9: WO | AJ9: P | AK9: P | AL9: P | AM9: P | AN9: P | AO9: WO | AP9: ='4-22MASTER'!X19 -> 29
A10: 4 | B10: ='4-22MASTER'!B20 -> BITS-658 | C10: ='4-22MASTER'!C20 -> Anjali Dubey | D10: ='4-22MASTER'!D20 -> 27-12-1990 | E10: ='4-22MASTER'!E20 -> FEMALE | F10: ='4-22MASTER'!O20 -> 44487 | G10: ='4-22MASTER'!G20 -> Project Engineer | L10: P | M10: WO | N10: WO | O10: P | P10: P | Q10: P | R10: P | S10: P | T10: WO | U10: WO | V10: P | W10: P | X10: P | Y10: P | Z10: H | AA10: WO | AB10: WO | AC10: P | AD10: P | AE10: P | AF10: P | AG10: P | AH10: WO | AI10: WO | AJ10: EL | AK10: A | AL10: A | AM10: P | AN10: P | AO10: WO | AP10: ='4-22MASTER'!X20 -> 28
A11: 5 | B11: ='4-22MASTER'!B21 -> BITS-683 | C11: ='4-22MASTER'!C21 -> TUSHAR UCHAGAONKAR | D11: ='4-22MASTER'!D21 -> 33656 | E11: ='4-22MASTER'!E21 -> MALE | F11: ='4-22MASTER'!O21 -> 44546 | G11: ='4-22MASTER'!G21 -> Network Engineer | L11: P | M11: WO | N11: WO | O11: P | P11: P | Q11: P | R11: P | S11: EL | T11: WO | U11: WO | V11: P | W11: P | X11: P | Y11: P | Z11: H | AA11: WO | AB11: WO | AC11: P | AD11: P | AE11: P | AF11: P | AG11: P | AH11: WO | AI11: WO | AJ11: P | AK11: P | AL11: P | AM11: P | AN11: P | AO11: WO | AP11: ='4-22MASTER'!X21 -> 30
A12: 6 | B12: ='4-22MASTER'!B22 -> BITS-692 | C12: ='4-22MASTER'!C22 -> Sneha Hande | D12: ='4-22MASTER'!D22 -> 09/11/1994 | E12: ='4-22MASTER'!E22 -> FEMALE | F12: ='4-22MASTER'!O22 -> 44566 | G12: ='4-22MASTER'!G22 -> Project manager | L12: P | M12: WO | N12: WO | O12: P | P12: P | Q12: P | R12: P | S12: P | T12: WO | U12: WO | V12: P | W12: P | X12: P | Y12: P | Z12: H | AA12: WO | AB12: WO | AC12: P | AD12: P | AE12: P | AF12: P | AG12: P | AH12: WO | AI12: WO | AJ12: P | AK12: P | AL12: P | AM12: P | AN12: P | AO12: WO | AP12: ='4-22MASTER'!X22 -> 30
A13: 7 | B13: ='4-22MASTER'!B23 -> BITS-698 | C13: ='4-22MASTER'!C23 -> Amol Gole | D13: ='4-22MASTER'!D23 -> 01/06/1991 | E13: ='4-22MASTER'!E23 -> MALE | F13: ='4-22MASTER'!O23 -> 44579 | G13: ='4-22MASTER'!G23 -> Project Manager | L13: P | M13: WO | N13: WO | O13: P | P13: P | Q13: P | R13: P | S13: P | T13: WO | U13: WO | V13: P | W13: P | X13: P | Y13: EL | Z13: H | AA13: WO | AB13: WO | AC13: P | AD13: P | AE13: P | AF13: P | AG13: P | AH13: WO | AI13: WO | AJ13: P | AK13: P | AL13: P | AM13: P | AN13: P | AO13: WO | AP13: ='4-22MASTER'!X23 -> 30
A14: 8 | B14: ='4-22MASTER'!B24 -> BITS-700 | C14: ='4-22MASTER'!C24 -> Sandeep Dixit | D14: ='4-22MASTER'!D24 -> 28764 | E14: ='4-22MASTER'!E24 -> MALE | F14: ='4-22MASTER'!O24 -> 44593 | G14: ='4-22MASTER'!G24 -> Sr. Project Manager | L14: P | M14: WO | N14: WO | O14: P | P14: P | Q14: P | R14: P | S14: P | T14: WO | U14: WO | V14: P | W14: P | X14: P | Y14: P | Z14: H | AA14: WO | AB14: WO | AC14: P | AD14: P | AE14: P | AF14: P | AG14: P | AH14: WO | AI14: WO | AJ14: P | AK14: P | AL14: P | AM14: P | AN14: P | AO14: WO | AP14: ='4-22MASTER'!X24 -> 30
A15: 9 | B15: ='4-22MASTER'!B25 -> BITS-717 | C15: ='4-22MASTER'!C25 -> Jaikesh Upadhyay | D15: ='4-22MASTER'!D25 -> 31778 | E15: ='4-22MASTER'!E25 -> MALE | F15: ='4-22MASTER'!O25 -> 44609 | G15: ='4-22MASTER'!G25 -> Sr. Project Coordinator | L15: P | M15: WO | N15: WO | O15: P | P15: P | Q15: P | R15: P | S15: P | T15: WO | U15: WO | V15: P | W15: P | X15: P | Y15: P | Z15: H | AA15: WO | AB15: WO | AC15: EL | AD15: P | AE15: P | AF15: P | AG15: P | AH15: WO | AI15: WO | AJ15: P | AK15: P | AL15: P | AM15: P | AN15: P | AO15: WO | AP15: ='4-22MASTER'!X25 -> 30
A16: 10 | B16: ='4-22MASTER'!B26 -> BITS-720 | C16: ='4-22MASTER'!C26 -> Jyoti Singh | D16: ='4-22MASTER'!D26 -> 34895 | E16: ='4-22MASTER'!E26 -> FEMALE | F16: ='4-22MASTER'!O26 -> 44613 | G16: ='4-22MASTER'!G26 -> Sr.Security analyst | L16: P | M16: WO | N16: WO | O16: P | P16: P | Q16: P | R16: P | S16: P | T16: WO | U16: WO | V16: P | W16: P | X16: P | Y16: P | Z16: H | AA16: WO | AB16: WO | AC16: P | AD16: P | AE16: P | AF16: P | AG16: P | AH16: WO | AI16: WO | AJ16: P | AK16: P | AL16: P | AM16: P | AN16: P | AO16: WO | AP16: ='4-22MASTER'!X26 -> 30
A17: 11 | B17: ='4-22MASTER'!B27 -> BITS-733 | C17: ='4-22MASTER'!C27 -> Chandrashekar Patil | D17: ='4-22MASTER'!D27 -> 34710 | E17: ='4-22MASTER'!E27 -> MALE | F17: ='4-22MASTER'!O27 -> 44634 | G17: ='4-22MASTER'!G27 -> Project Manager | L17: P | M17: WO | N17: WO | O17: P | P17: P | Q17: P | R17: P | S17: P | T17: WO | U17: WO | V17: P | W17: P | X17: P | Y17: P | Z17: H | AA17: WO | AB17: WO | AC17: P | AD17: P | AE17: P | AF17: P | AG17: EL | AH17: WO | AI17: WO | AJ17: A | AK17: A | AL17: A | AM17: P | AN17: P | AO17: WO | AP17: ='4-22MASTER'!X27 -> 27
A18: 12 | B18: ='4-22MASTER'!B28 -> BITS-734 | C18: ='4-22MASTER'!C28 -> ShaikFarooq Basha | D18: ='4-22MASTER'!D28 -> 33370 | E18: ='4-22MASTER'!E28 -> MALE | F18: ='4-22MASTER'!O28 -> 44636 | G18: ='4-22MASTER'!G28 -> Software Engineer | L18: P | M18: WO | N18: WO | O18: P | P18: P | Q18: P | R18: P | S18: P | T18: WO | U18: WO | V18: P | W18: P | X18: P | Y18: P | Z18: H | AA18: WO | AB18: WO | AC18: P | AD18: P | AE18: P | AF18: P | AG18: P | AH18: WO | AI18: WO | AJ18: P | AK18: P | AL18: P | AM18: P | AN18: P | AO18: WO | AP18: ='4-22MASTER'!X28 -> 30
A19: 13 | B19: ='4-22MASTER'!B29 -> BITS-738 | C19: ='4-22MASTER'!C29 -> NILOTPAL BHOWAL | D19: ='4-22MASTER'!D29 -> 31584 | E19: ='4-22MASTER'!E29 -> MALE | F19: ='4-22MASTER'!O29 -> 44650 | G19: ='4-22MASTER'!G29 -> VM ware consultant | L19: P | M19: WO | N19: WO | O19: P | P19: P | Q19: P | R19: P | S19: P | T19: WO | U19: WO | V19: P | W19: P | X19: P | Y19: P | Z19: H | AA19: WO | AB19: WO | AC19: P | AD19: P | AE19: P | AF19: P | AG19: P | AH19: WO | AI19: WO | AJ19: P | AK19: P | AL19: P | AM19: P | AN19: P | AO19: WO | AP19: ='4-22MASTER'!X29 -> 30
A20: 14 | B20: ='4-22MASTER'!B30 -> BITS-751 | C20: ='4-22MASTER'!C30 -> Varsha Amit Kadam | D20: ='4-22MASTER'!D30 -> 31018 | E20: ='4-22MASTER'!E30 -> FEMALE | F20: ='4-22MASTER'!O30 -> 44676 | G20: ='4-22MASTER'!G30 -> Program Manager | AJ20: P | AK20: P | AL20: P | AM20: P | AN20: P | AO20: WO | AP20: ='4-22MASTER'!X30 -> 6
AP21: =SUM(AP7:AP20) -> 380
AL32: Signature of the Contractor with Seal

Sheet F-M Leav
A1: FORM M- LEAVE REGISTER
A3: (Vide Rule 78(1) (a) (i) of Maharastra Shops&Establishment Act /Maharastra.Rules 1988
A4: Name of the Employer / Establishment: | E4: Name of the Employee:
B5: ='4-22MASTER'!G5 -> Burgeon IT Services Pvt.Ltd. | G5: ='4-22MASTER'!C17 -> Haneef
B6: ='4-22MASTER'!G6 -> Siri Mansion LIGB 436 Dr.A S Rao Nagar,Hyderabad
A7: Description of the dapartment if applicable: | E7: Date of entry into service | G7: ='4-22MASTER'!O17 -> 44298
C8: ='4-22MASTER'!G8 -> IT SUPPORTIVE SERVICES & PUNE ASC SEZ
A11: S.No | B11: Accumalation of Leave | D11: Leave allowed | F11: Balance of Leave Carried Over | G11: Payment of Leave made on | I11: Refusal of Leave | L11: Payment of Leave on Discharge of an employee quitting employment if a admissible | P11: Remarks
A13: 1 | F13: 6 | I13: 9 | L13: 9
B14: Leave due on | C14: No of Days | D14: From | E14: To | G14: 1st month | H14: 2nd month | I14: Date of Application | J14: Date of Refusal | K14: Amount of Leave refused | L14: Date of Discharge | M14: Date of Amount Paid | N14: Signature or Left hand thumb impression of employee
A15: JAN'22 | B15: 1.5 | C15: 1 | D15: 44589 | E15: 44589 | F15: 8.5 | J15: NO | K15: NO | L15: NO | M15: NO
A16: FEB'22 | B16: 1.5 | C16: 0 | D16: 0 | E16: 0 | F16: =F15+B16-C16 -> 10 | J16: NO | K16: NO | L16: NO | M16: NO
A17: MAR'22 | B17: 0 | C17: 0 | D17: 0 | E17: 0 | F17: =F16+B17-C17 -> 10 | J17: NO | K17: LESS DAYS | L17: NO | M17: NO
A18: APRIL'22 | B18: 1.5 | C18: 0 | D18: 0 | E18: 0 | F18: =F17+B18-C18 -> 11.5 | J18: NO | K18: NO | L18: NO | M18: NO
G42: Signature of the Contractor with Seal
A48: FORM M- LEAVE REGISTER
A50: (Vide Rule 78(1) (a) (i) of Maharastra Shops&Establishment Act /Maharastra.Rules 1988
A51: Name of the Employer / Establishment: | E51: Name of the Employee:
B52: ='4-22MASTER'!G5 -> Burgeon IT Services Pvt.Ltd. | G52: ='PUNE ASC-APRIL 22WM REG'!B37 -> Ved Prakash
B53: ='4-22MASTER'!G6 -> Siri Mansion LIGB 436 Dr.A S Rao Nagar,Hyderabad
A54: Description of the dapartment if applicable: | E54: Date of entry into service | G54: ='PUNE ASC-APRIL 22WM REG'!I37 -> 4th May 2021
C55: ='4-22MASTER'!G8 -> IT SUPPORTIVE SERVICES & PUNE ASC SEZ
A58: S.No | B58: Accumalation of Leave | D58: Leave allowed | F58: Balance of Leave Carried Over | G58: Payment of Leave made on | I58: Refusal of Leave | L58: Payment of Leave on Discharge of an employee quitting employment if a admissible | P58: Remarks
A60: 1 | F60: 6 | I60: 9 | L60: 9
B61: Leave due on | C61: No of Days | D61: From | E61: To | G61: 1st month | H61: 2nd month | I61: Date of Application | J61: Date of Refusal | K61: Amount of Leave refused | L61: Date of Discharge | M61: Date of Amount Paid | N61: Signature or Left hand thumb impression of employee
A62: JAN'22 | B62: 1.5 | F62: 9.5 | J62: NO | K62: NO | L62: NO | M62: NO
A63: FEB'22 | B63: 1.5 | C63: 1 | D63: 44603 | E63: 44603 | F63: =F62+B63-C63 -> 10 | J63: NO | K63: NO | L63: NO | M63: NO
A64: MAR'22 | B64: 1.5 | C64: 1 | D64: 44648 | E64: 44620 | F64: =F63+B64-C64 -> 10.5 | J64: NO | K64: NO | L64: NO | M64: NO
A65: APRIL'22 | B65: 1.5 | C65: 0 | D65: 0 | E65: 0 | F65: =F64+B65-C65 -> 12 | J65: NO | K65: NO | L65: NO | M65: NO
G89: Signature of the Contractor with Seal
A95: FORM M- LEAVE REGISTER
A97: (Vide Rule 78(1) (a) (i) of Maharastra Shops&Establishment Act /Maharastra.Rules 1988
A98: Name of the Employer / Establishment: | E98: Name of the Employee:
B99: ='4-22MASTER'!G5 -> Burgeon IT Services Pvt.Ltd. | G99: ='PUNE ASC-APRIL 22WM REG'!B39 -> GauravVispute
B100: ='4-22MASTER'!G6 -> Siri Mansion LIGB 436 Dr.A S Rao Nagar,Hyderabad
A101: Description of the dapartment if applicable: | E101: Date of entry into service | G101: ='PUNE ASC-APRIL 22WM REG'!I39 -> 4th May 2021
C102: ='4-22MASTER'!G8 -> IT SUPPORTIVE SERVICES & PUNE ASC SEZ
A105: S.No | B105: Accumalation of Leave | D105: Leave allowed | F105: Balance of Leave Carried Over | G105: Payment of Leave made on | I105: Refusal of Leave | L105: Payment of Leave on Discharge of an employee quitting employment if a admissible | P105: Remarks
A107: 1 | F107: 6 | I107: 9 | L107: 9
B108: Leave due on | C108: No of Days | D108: From | E108: To | G108: 1st month | H108: 2nd month | I108: Date of Application | J108: Date of Refusal | K108: Amount of Leave refused | L108: Date of Discharge | M108: Date of Amount Paid | N108: Signature or Left hand thumb impression of employee
A109: JAN'22 | B109: 1.5 | F109: 9.5 | J109: NO | K109: NO | L109: NO | M109: NO
A110: FEB'22 | B110: 1.5 | C110: 1 | D110: 44610 | E110: 44610 | F110: =F109+B110-C110 -> 10 | J110: NO | K110: NO | L110: NO | M110: NO
A111: MAR'22 | B111: 1.5 | C111: 0 | D111: 0 | E111: 0 | F111: =F110+B111-C111 -> 11.5 | J111: NO | K111: NO | L111: NO | M111: NO
A112: APRIL'22 | B112: 1.5 | C112: 1 | D112: 44669 | E112: 44669 | F112: =F111+B112-C112 -> 12 | J112: NO | K112: NO | L112: NO | M112: NO
G136: Signature of the Contractor with Seal
A141: FORM M- LEAVE REGISTER
A143: (Vide Rule 78(1) (a) (i) of Maharastra Shops&Establishment Act /Maharastra.Rules 1988
A144: Name of the Employer / Establishment: | E144: Name of the Employee:
B145: Burgeon IT Services Pvt.Ltd. | F145: ='4-22MASTER'!C20 -> Anjali Dubey
B146: Siri Mansion LIGB 436 Dr.A S Rao Nagar,Hyderabad
A147: Description of the dapartment if applicable: | E147: Date of entry into service
C148: ='4-22MASTER'!G178 -> 0 | F148: ='4-22MASTER'!O20 -> 44487
A151: S.No | B151: Accumalation of Leave | D151: Leave allowed | F151: Balance of Leave Carried Over | G151: Payment of Leave made on | I151: Refusal of Leave | L151: Payment of Leave on Discharge of an employee quitting employment if a admissible
A153: 1 | F153: 6 | I153: 9 | L153: 9
B154: Leave due on | C154: No of Days | D154: From | E154: To | G154: 1st month | H154: 2nd month | I154: Date of Application | J154: Date of Refusal | K154: Amount of Leave refused | L154: Date of Discharge | M154: Date of Amount Paid | N154: Signature or Left hand thumb impression of employee
A156: JAN'22 | B156: 1.5 | F156: 3.5 | J156: NO | K156: NO | L156: NO | M156: NO
A157: FEB'22 | B157: 1.5 | C157: 1 | D157: 44617 | E157: 44617 | F157: =F156+B157-C157 -> 4 | J157: NO | K157: NO | L157: NO | M157: NO
A158: MAR'22 | B158: 1.5 | C158: 1 | D158: 44624 | E158: 44624 | F158: =F157+B158-C158 -> 4.5 | J158: NO | K158: NO | L158: NO | M158: NO
A159: APRIL'22 | B159: 1.5 | C159: 1 | D159: 44676 | E159: 44676 | F159: =F158+B159-C159 -> 5 | J159: NO | K159: NO | L159: NO | M159: NO
A186: FORM M- LEAVE REGISTER
A188: (Vide Rule 78(1) (a) (i) of Maharastra Shops&Establishment Act /Maharastra.Rules 1988
A189: Name of the Employer / Establishment: | E189: Name of the Employee:
B190: Burgeon IT Services Pvt.Ltd. | F190: ='4-22MASTER'!C21 -> TUSHAR UCHAGAONKAR
B191: Siri Mansion LIGB 436 Dr.A S Rao Nagar,Hyderabad
A192: Description of the dapartment if applicable: | E192: Date of entry into service
C193: ='4-22MASTER'!G314 -> 0 | F193: ='4-22MASTER'!D21 -> 33656
A196: S.No | B196: Accumalation of Leave | D196: Leave allowed | F196: Balance of Leave Carried Over | G196: Payment of Leave made on | I196: Refusal of Leave | L196: Payment of Leave on Discharge of an employee quitting employment if a admissible
A198: 1 | F198: 6 | I198: 9 | L198: 9
B199: Leave due on | C199: No of Days | D199: From | E199: To | G199: 1st month | H199: 2nd month | I199: Date of Application | J199: Date of Refusal | K199: Amount of Leave refused | L199: Date of Discharge | M199: Date of Amount Paid | N199: Signature or Left hand thumb impression of employee
A202: JAN'22 | B202: 1.5 | C202: 1 | D202: 44575 | E202: 44575 | F202: =(F201+B202)-C202 -> 0.5 | J202: NO | K202: NO | L202: NO | M202: NO
A203: FEB'22 | B203: 1.5 | C203: 1 | D203: 44596 | E203: 44596 | F203: =F202+B203-C203 -> 1 | J203: NO | K203: NO | L203: NO | M203: NO
A204: MAR'22 | B204: 1.5 | C204: 1 | D204: 44641 | E204: 44641 | F204: =F203+B204-C204 -> 1.5 | J204: NO | K204: NO | L204: NO | M204: NO
A205: APRIL'22 | B205: 1.5 | C205: 1 | D205: 44659 | E205: 44659 | F205: =F204+B205-C205 -> 2 | J205: NO | K205: NO | L205: NO | M205: NO
A231: FORM M- LEAVE REGISTER
A233: (Vide Rule 78(1) (a) (i) of Maharastra Shops&Establishment Act /Maharastra.Rules 1988
A234: Name of the Employer / Establishment: | E234: Name of the Employee: | H234: ='4-22MASTER'!C22 -> Sneha Hande
B235: Burgeon IT Services Pvt.Ltd.
B236: Siri Mansion LIGB 436 Dr.A S Rao Nagar,Hyderabad
A237: Description of the dapartment if applicable: | E237: Date of entry into service | H237: ='4-22MASTER'!O22 -> 44566
C238: ='4-22MASTER'!G359 -> 0
A241: S.No | B241: Accumalation of Leave | D241: Leave allowed | F241: Balance of Leave Carried Over | G241: Payment of Leave made on | I241: Refusal of Leave | L241: Payment of Leave on Discharge of an employee quitting employment if a admissible
A243: 1 | F243: 6 | I243: 9 | L243: 9
B244: Leave due on | C244: No of Days | D244: From | E244: To | G244: 1st month | H244: 2nd month | I244: Date of Application | J244: Date of Refusal | K244: Amount of Leave refused | L244: Date of Discharge | M244: Date of Amount Paid | N244: Signature or Left hand thumb impression of employee
A247: JAN'22 | B247: 1.5 | F247: =(F246+B247)-C247 -> 1.5 | J247: NO | K247: NO | L247: NO | M247: NO
A248: FEB'22 | B248: 1.5 | C248: 0 | D248: 0 | E248: 0 | F248: =F247+B248-C248 -> 3 | J248: NO | K248: NO | L248: NO | M248: NO
A249: MAR'22 | B249: 1.5 | C249: 0 | D249: 0 | E249: 0 | F249: =F248+B249-C249 -> 4.5 | J249: NO | K249: NO | L249: NO | M249: NO
A250: APRIL'22 | B250: 1.5 | C250: 0 | D250: 0 | E250: 0 | F250: =F249+B250-C250 -> 6 | J250: NO | K250: NO | L250: NO | M250: NO
A276: FORM M- LEAVE REGISTER
A278: (Vide Rule 78(1) (a) (i) of Maharastra Shops&Establishment Act /Maharastra.Rules 1988
A279: Name of the Employer / Establishment: | E279: Name of the Employee: | H279: ='4-22MASTER'!C23 -> Amol Gole
B280: Burgeon IT Services Pvt.Ltd.
B281: Siri Mansion LIGB 436 Dr.A S Rao Nagar,Hyderabad
A282: Description of the dapartment if applicable: | E282: Date of entry into service
C283: ='4-22MASTER'!G404 -> 0 | G283: ='4-22MASTER'!O23 -> 44579
A286: S.No | B286: Accumalation of Leave | D286: Leave allowed | F286: Balance of Leave Carried Over | G286: Payment of Leave made on | I286: Refusal of Leave | L286: Payment of Leave on Discharge of an employee quitting employment if a admissible
A288: 1 | F288: 6 | I288: 9 | L288: 9
B289: Leave due on | C289: No of Days | D289: From | E289: To | G289: 1st month | H289: 2nd month | I289: Date of Application | J289: Date of Refusal | K289: Amount of Leave refused | L289: Date of Discharge | M289: Date of Amount Paid | N289: Signature or Left hand thumb impression of employee
A292: JAN'22 | B292: 0 | F292: =(F291+B292)-C292 -> 0 | I292: LESS DAYS | J292: NO | K292: NO | L292: NO | M292: NO
A293: FEB'22 | B293: 1.5 | C293: 0 | D293: 0 | E293: 0 | F293: =F292+B293-C293 -> 1.5 | J293: NO | K293: NO | L293: NO | M293: NO
A294: MAR'22 | B294: 1.5 | C294: 0 | D294: 0 | E294: 0 | F294: =F293+B294-C294 -> 3 | J294: NO | K294: NO | L294: NO | M294: NO
...

Sheet MH_Reg Wage
B2: Form No. II
B3: [M. W. Rules under Maharashtra Contract Labour (Regulation and Abolition)1963 Rule 27 (I)]
B4: Muster Roll cum Wages Register for the month of APRIL 2022
B5: Name and Address of Contractor : BURGEON IT SERVICES PVT.LTD. SIRI MANSION LIG 436 DR.A S RAO NAGAR,HYDERABAD 500 060
O6: Deductions | V6: Leave with Wages
B7: Sl.No. | C7: Employee Code | D7: Name of the Workmen | E7: Minimum Rate of Wages Payable Basic | F7: Actual Rate of Wages Payable HRA | G7: Conveyance | H7: Bonus | I7: Special Allowances | J7: Medical Allowances | K7: Total Production in Case of Piece Rate Other Allow | L7: Normal Earnings | M7: Overtime Earnings | N7: Gross Wages Payable | O7: Income Tax | P7: Other Deduction(Med) | Q7: Proff / Income Tax | R7: PF | S7: ESIC | T7: Total Deduction | U7: Net Wages Paid | V7: Previous Balance | W7: Further Enjoyed | X7: Refused | Y7: Accumulated | Z7: Date Payment of Wages | AA7: Signature or the Thumb Impression of the Employee | AB7: Account Number
B9: 1 | C9: ='4-22MASTER'!B17 -> BITS-542 | D9: ='4-22MASTER'!C17 -> Haneef | E9: ='4-22MASTER'!AA17 -> 37044 | F9: ='4-22MASTER'!AE17 -> 14817.6 | G9: ='4-22MASTER'!AF17 -> 2083 | H9: ='4-22MASTER'!AJ17 -> 1554.609 | I9: ='4-22MASTER'!AH17 -> 5825.4 | J9: ='4-22MASTER'!AG17 -> 2083 | L9: ='4-22MASTER'!AN17 -> 68276.425 | M9: 0 | N9: ='4-22MASTER'!AN17 -> 68276.425 | O9: ='4-22MASTER'!AR17 -> 0 | P9: ='4-22MASTER'!AS17 -> 391.78785 | Q9: ='4-22MASTER'!AQ17 -> 200 | R9: ='4-22MASTER'!AP17 -> 1800 | S9: ='4-22MASTER'!AO17 -> 0 | T9: ='4-22MASTER'!AT17 -> 2391.7878 | U9: ='4-22MASTER'!AU17 -> 65884.638 | V9: 10 | W9: 0 | X9: 0 | Y9: 11.5 | Z9: ='4-22MASTER'!AV17 -> 05.05.2022 | AA9: ='4-22MASTER'!AW17 -> SBI | AB9: ='4-22MASTER'!AX17 -> A/C'20434252219
B10: 2 | C10: ='4-22MASTER'!B18 -> BITS-557 | D10: ='4-22MASTER'!C18 -> Ved Prakash | E10: ='4-22MASTER'!AA18 -> 28403.6 | F10: ='4-22MASTER'!AE18 -> 11361.44 | G10: ='4-22MASTER'!AF18 -> 1389 | H10: ='4-22MASTER'!AJ18 -> 1554.609 | I10: ='4-22MASTER'!AH18 -> 4909.2933 | J10: ='4-22MASTER'!AG18 -> 1389 | L10: ='4-22MASTER'!AN18 -> 52740.122 | M10: 0 | N10: ='4-22MASTER'!AN18 -> 52740.122 | O10: ='4-22MASTER'!AR18 -> 0 | P10: ='4-22MASTER'!AS18 -> 440.76133 | Q10: ='4-22MASTER'!AQ18 -> 200 | R10: ='4-22MASTER'!AP18 -> 1800 | S10: ='4-22MASTER'!AO18 -> 0 | T10: ='4-22MASTER'!AT18 -> 2440.7613 | U10: ='4-22MASTER'!AU18 -> 50299.361 | V10: 10.5 | W10: 0 | X10: 0 | Y10: 12 | Z10: ='4-22MASTER'!AV18 -> 05.05.2022 | AA10: ='4-22MASTER'!AW18 -> HDFC | AB10: ='4-22MASTER'!AX18 -> A/C'50100052341452
B11: 3 | C11: ='4-22MASTER'!B19 -> BITS-559 | D11: ='4-22MASTER'!C19 -> GauravVispute | E11: ='4-22MASTER'!AA19 -> 25057.16 | F11: ='4-22MASTER'!AE19 -> 10022.864 | G11: ='4-22MASTER'!AF19 -> 2014 | H11: ='4-22MASTER'!AJ19 -> 1554.609 | I11: ='4-22MASTER'!AH19 -> 2766.9093 | J11: ='4-22MASTER'!AG19 -> 2014 | L11: ='4-22MASTER'!AN19 -> 46722.888 | M11: 0 | N11: ='4-22MASTER'!AN19 -> 46722.888 | O11: ='4-22MASTER'!AR19 -> 0 | P11: ='4-22MASTER'!AS19 -> 391.78785 | Q11: ='4-22MASTER'!AQ19 -> 200 | R11: ='4-22MASTER'!AP19 -> 1800 | S11: ='4-22MASTER'!AO19 -> 0 | T11: ='4-22MASTER'!AT19 -> 2391.7878 | U11: ='4-22MASTER'!AU19 -> 44331.101 | V11: 11.5 | W11: 1 | X11: 0 | Y11: 12 | Z11: ='4-22MASTER'!AV19 -> 05.05.2022 | AA11: ='4-22MASTER'!AW19 -> SBI | AB11: ='4-22MASTER'!AX19 -> A/C'31443937313
B12: 4 | C12: ='4-22MASTER'!B20 -> BITS-658 | D12: ='4-22MASTER'!C20 -> Anjali Dubey | E12: ='4-22MASTER'!AA20 -> 33017.04 | F12: ='4-22MASTER'!AE20 -> 13206.816 | G12: ='4-22MASTER'!AF20 -> 1944 | H12: ='4-22MASTER'!AJ20 -> 1554.609 | I12: ='4-22MASTER'!AH20 -> 5029.544 | J12: ='4-22MASTER'!AG20 -> 1944 | L12: ='4-22MASTER'!AN20 -> 61035.549 | M12: 0 | N12: ='4-22MASTER'!AN20 -> 61035.549 | O12: ='4-22MASTER'!AR20 -> 0 | P12: ='4-22MASTER'!AS20 -> 254 | Q12: ='4-22MASTER'!AQ20 -> 200 | R12: ='4-22MASTER'!AP20 -> 1800 | S12: ='4-22MASTER'!AO20 -> 0 | T12: ='4-22MASTER'!AT20 -> 2254 | U12: ='4-22MASTER'!AU20 -> 58781.549 | V12: 4.5 | W12: 1 | X12: 0 | Y12: 5 | Z12: ='4-22MASTER'!AV20 -> 05.05.2022 | AA12: ='4-22MASTER'!AW20 -> Union bank of India | AB12: ='4-22MASTER'!AX20 -> 631302010000771
B13: 5 | C13: ='4-22MASTER'!B21 -> BITS-683 | D13: ='4-22MASTER'!C21 -> TUSHAR UCHAGAONKAR | E13: ='4-22MASTER'!AA21 -> 46498.2 | F13: ='4-22MASTER'!AE21 -> 18599.28 | G13: ='4-22MASTER'!AF21 -> 2083 | H13: ='4-22MASTER'!AJ21 -> 1554.609 | I13: ='4-22MASTER'!AH21 -> 8346.52 | J13: ='4-22MASTER'!AG21 -> 2083 | L13: ='4-22MASTER'!AN21 -> 85276.022 | M13: 0 | N13: ='4-22MASTER'!AN21 -> 85276.022 | O13: ='4-22MASTER'!AR21 -> 0 | P13: ='4-22MASTER'!AS21 -> 283 | Q13: ='4-22MASTER'!AQ21 -> 200 | R13: ='4-22MASTER'!AP21 -> 1800 | S13: ='4-22MASTER'!AO21 -> 0 | T13: ='4-22MASTER'!AT21 -> 2283 | U13: ='4-22MASTER'!AU21 -> 82993.022 | V13: 1.5 | W13: 1 | X13: 0 | Y13: 2 | Z13: ='4-22MASTER'!AV21 -> 05.05.2022 | AA13: ='4-22MASTER'!AW21 -> ICICI BANK | AB13: ='4-22MASTER'!AX21 -> 042401536750
B14: 6 | C14: ='4-22MASTER'!B22 -> BITS-692 | D14: ='4-22MASTER'!C22 -> Sneha Hande | E14: ='4-22MASTER'!AA22 -> 30370.2 | F14: ='4-22MASTER'!AE22 -> 12148.08 | G14: ='4-22MASTER'!AF22 -> 2083 | H14: ='4-22MASTER'!AJ22 -> 1554.609 | I14: ='4-22MASTER'!AH22 -> 4045.72 | J14: ='4-22MASTER'!AG22 -> 2083 | L14: ='4-22MASTER'!AN22 -> 56276.266 | M14: 0 | N14: ='4-22MASTER'!AN22 -> 56276.266 | O14: ='4-22MASTER'!AR22 -> 0 | P14: ='4-22MASTER'!AS22 -> 283 | Q14: ='4-22MASTER'!AQ22 -> 200 | R14: ='4-22MASTER'!AP22 -> 1800 | S14: ='4-22MASTER'!AO22 -> 0 | T14: ='4-22MASTER'!AT22 -> 2283 | U14: ='4-22MASTER'!AU22 -> 53993.266 | V14: 4.5 | W14: 0 | X14: 0 | Y14: 6 | Z14: ='4-22MASTER'!AV22 -> 05.05.2022 | AA14: ='4-22MASTER'!AW22 -> ICICI BANK | AB14: ='4-22MASTER'!AX22 -> 148001513263
B15: 7 | C15: ='4-22MASTER'!B23 -> BITS-698 | D15: ='4-22MASTER'!C23 -> Amol Gole | E15: ='4-22MASTER'!AA23 -> 39824.4 | F15: ='4-22MASTER'!AE23 -> 15929.76 | G15: ='4-22MASTER'!AF23 -> 2083 | H15: ='4-22MASTER'!AJ23 -> 1554.609 | I15: ='4-22MASTER'!AH23 -> 6566.84 | J15: ='4-22MASTER'!AG23 -> 2083 | L15: ='4-22MASTER'!AN23 -> 73275.863 | M15: 0 | N15: ='4-22MASTER'!AN23 -> 73275.863 | O15: ='4-22MASTER'!AR23 -> 0 | P15: ='4-22MASTER'!AS23 -> 283 | Q15: ='4-22MASTER'!AQ23 -> 200 | R15: ='4-22MASTER'!AP23 -> 1800 | S15: ='4-22MASTER'!AO23 -> 0 | T15: ='4-22MASTER'!AT23 -> 2283 | U15: ='4-22MASTER'!AU23 -> 70992.863 | V15: 3 | W15: 1 | X15: 0 | Y15: 3.5 | Z15: ='4-22MASTER'!AV23 -> 05.05.2022 | AA15: ='4-22MASTER'!AW23 -> ICICI BANK | AB15: ='4-22MASTER'!AX23 -> 623901548420
B16: 8 | C16: ='4-22MASTER'!B24 -> BITS-700 | D16: ='4-22MASTER'!C24 -> Sandeep Dixit | E16: ='4-22MASTER'!AA24 -> 103780.8 | F16: ='4-22MASTER'!AE24 -> 41512.32 | G16: ='4-22MASTER'!AF24 -> 2083 | H16: ='4-22MASTER'!AJ24 -> 1554.609 | I16: ='4-22MASTER'!AH24 -> 23621.88 | J16: ='4-22MASTER'!AG24 -> 2083 | L16: ='4-22MASTER'!AN24 -> 188275.87 | M16: 0 | N16: ='4-22MASTER'!AN24 -> 188275.87 | O16: ='4-22MASTER'!AR24 -> 0 | P16: ='4-22MASTER'!AS24 -> 283 | Q16: ='4-22MASTER'!AQ24 -> 200 | R16: ='4-22MASTER'!AP24 -> 1800 | S16: ='4-22MASTER'!AO24 -> 0 | T16: ='4-22MASTER'!AT24 -> 2283 | U16: ='4-22MASTER'!AU24 -> 185992.87 | V16: 6 | W16: 0 | X16: 0 | Y16: 7.5 | Z16: ='4-22MASTER'!AV24 -> 05.05.2022 | AA16: ='4-22MASTER'!AW24 -> Punjab National Bank | AB16: ='4-22MASTER'!AX24 -> 12372191001001
B17: 9 | C17: ='4-22MASTER'!B25 -> BITS-717 | D17: ='4-22MASTER'!C25 -> Jaikesh Upadhyay | E17: ='4-22MASTER'!AA25 -> 67631.4 | F17: ='4-22MASTER'!AE25 -> 27052.56 | G17: ='4-22MASTER'!AF25 -> 2083 | H17: ='4-22MASTER'!AJ25 -> 1554.609 | I17: ='4-22MASTER'!AH25 -> 13982.04 | J17: ='4-22MASTER'!AG25 -> 2083 | L17: ='4-22MASTER'!AN25 -> 123275.63 | M17: 0 | N17: ='4-22MASTER'!AN25 -> 123275.63 | O17: ='4-22MASTER'!AR25 -> 0 | P17: ='4-22MASTER'!AS25 -> 283 | Q17: ='4-22MASTER'!AQ25 -> 200 | R17: ='4-22MASTER'!AP25 -> 1800 | S17: ='4-22MASTER'!AO25 -> 0 | T17: ='4-22MASTER'!AT25 -> 2283 | U17: ='4-22MASTER'!AU25 -> 120992.63 | V17: 8 | W17: 1 | X17: 0 | Y17: 8.5 | Z17: ='4-22MASTER'!AV25 -> 05.05.2022 | AA17: ='4-22MASTER'!AW25 -> ICICI BANK | AB17: ='4-22MASTER'!AX25 -> 338201500480
B18: 10 | C18: ='4-22MASTER'!B26 -> BITS-720 | D18: ='4-22MASTER'!C26 -> Jyoti Singh | E18: ='4-22MASTER'!AA26 -> 62070 | F18: ='4-22MASTER'!AE26 -> 24828 | G18: ='4-22MASTER'!AF26 -> 2083 | H18: ='4-22MASTER'!AJ26 -> 1554.609 | I18: ='4-22MASTER'!AH26 -> 12499 | J18: ='4-22MASTER'!AG26 -> 2083 | L18: ='4-22MASTER'!AN26 -> 113275.68 | M18: 0 | N18: ='4-22MASTER'!AN26 -> 113275.68 | O18: ='4-22MASTER'!AR26 -> 0 | P18: ='4-22MASTER'!AS26 -> 283 | Q18: ='4-22MASTER'!AQ26 -> 200 | R18: ='4-22MASTER'!AP26 -> 0 | S18: ='4-22MASTER'!AO26 -> 0 | T18: ='4-22MASTER'!AT26 -> 483 | U18: ='4-22MASTER'!AU26 -> 112792.68 | V18: 9 | W18: 0 | X18: 0 | Y18: 10.5 | Z18: ='4-22MASTER'!AV26 -> 05.05.2022 | AA18: ='4-22MASTER'!AW26 -> ICICI BANK | AB18: ='4-22MASTER'!AX26 -> 341901505420
B19: 11 | C19: ='4-22MASTER'!B27 -> BITS-733 | D19: ='4-22MASTER'!C27 -> Chandrashekar Patil | E19: ='4-22MASTER'!AA27 -> 39846.06 | F19: ='4-22MASTER'!AE27 -> 15938.424 | G19: ='4-22MASTER'!AF27 -> 1875 | H19: ='4-22MASTER'!AJ27 -> 1554.609 | I19: ='4-22MASTER'!AH27 -> 6988.616 | J19: ='4-22MASTER'!AG27 -> 1875 | L19: ='4-22MASTER'!AN27 -> 73314.809 | M19: 0 | N19: ='4-22MASTER'!AN27 -> 73314.809 | O19: ='4-22MASTER'!AR27 -> 0 | P19: ='4-22MASTER'!AS27 -> 283 | Q19: ='4-22MASTER'!AQ27 -> 200 | R19: ='4-22MASTER'!AP27 -> 1800 | S19: ='4-22MASTER'!AO27 -> 0 | T19: ='4-22MASTER'!AT27 -> 2283 | U19: ='4-22MASTER'!AU27 -> 71031.809 | V19: 0.5 | W19: 1 | X19: 0 | Y19: 1 | Z19: ='4-22MASTER'!AV27 -> 05.05.2022 | AA19: ='4-22MASTER'!AW27 -> HDFC | AB19: ='4-22MASTER'!AX27 -> 100783283673
B20: 12 | C20: ='4-22MASTER'!B28 -> BITS-734 | D20: ='4-22MASTER'!C28 -> ShaikFarooq Basha | E20: ='4-22MASTER'!AA28 -> 62070 | F20: ='4-22MASTER'!AE28 -> 24828 | G20: ='4-22MASTER'!AF28 -> 2083 | H20: ='4-22MASTER'!AJ28 -> 1554.609 | I20: ='4-22MASTER'!AH28 -> 12499 | J20: ='4-22MASTER'!AG28 -> 2083 | L20: ='4-22MASTER'!AN28 -> 113275.68 | M20: 0 | N20: ='4-22MASTER'!AN28 -> 113275.68 | O20: ='4-22MASTER'!AR28 -> 7419 | P20: ='4-22MASTER'!AS28 -> 283 | Q20: ='4-22MASTER'!AQ28 -> 200 | R20: ='4-22MASTER'!AP28 -> 1800 | S20: ='4-22MASTER'!AO28 -> 0 | T20: ='4-22MASTER'!AT28 -> 9702 | U20: ='4-22MASTER'!AU28 -> 103573.68 | V20: 0 | W20: 0 | X20: 0 | Y20: 1.5 | Z20: ='4-22MASTER'!AV28 -> 05.05.2022 | AA20: ='4-22MASTER'!AW28 -> HDFC | AB20: ='4-22MASTER'!AX28 -> 50100383537784
... B22: 14 | C22: ='4-22MASTER'!B30 -> BITS-751 | D22: ='4-22MASTER'!C30 -> Varsha Amit Kadam | E22: ='4-22MASTER'!AA30 -> 6518.88 | F22: ='4-22MASTER'!AE30 -> 2607.552 | G22: ='4-22MASTER'!AF30 -> 417 | H22: ='4-22MASTER'!AJ30 -> 1554.609 | I22: ='4-22MASTER'!AH30 -> 1017.368 | J22: ='4-22MASTER'!AG30 -> 417 | L22: ='4-22MASTER'!AN30 -> 13389.207 | M22: 0 | N22: ='4-22MASTER'!AN30 -> 13389.207 | O22: ='4-22MASTER'!AR30 -> 0 | P22: ='4-22MASTER'!AS30 -> 0 | Q22: ='4-22MASTER'!AQ30 -> 0 | R22: ='4-22MASTER'!AP30 -> 782 | S22: ='4-22MASTER'!AO30 -> 0 | T22: ='4-22MASTER'!AT30 -> 782 | U22: ='4-22MASTER'!AU30 -> 12607.207 | V22: 0 | W22: 0 | X22: 0 | Y22: 0 | Z22: ='4-22MASTER'!AV30 -> 05.05.2022 | AA22: ='4-22MASTER'!AW30 -> Kotak Mahindra Bank | AB22: ='4-22MASTER'!AX30 -> 7311156365
B23: 15 | E23: =SUM(E9:E22) -> 655324.54 | F23: =SUM(F9:F22) -> 262129.82 | G23: =SUM(G9:G22) -> 26386 | H23: =SUM(H9:H22) -> 21764.526 | I23: =SUM(I9:I22) -> 123563.21 | J23: =SUM(J9:J22) -> 26386 | L23: =SUM(L9:L22) -> 1201685.6 | M23: =SUM(M9:M22) -> 0 | N23: =SUM(N9:N22) -> 1201685.6 | O23: =SUM(O9:O22) -> 7419 | P23: =SUM(P9:P22) -> 4025.337 | Q23: =SUM(Q9:Q22) -> 2600 | R23: =SUM(R9:R22) -> 22382 | S23: =SUM(S9:S22) -> 0 | ... U23: =SUM(U9:U22) -> 1165259.2
B24: 16
K31: Signature of the Contractor with Seal

Sheet Emp Cards
A1: FORM XIV
A2: EMPLOYMENT CUM WAGE CARD
A3: (Vide Rule 76 of Contract Labour (R&A) Central &Maharastra Rules, 1974)
A4: Name and Address of the Contractor | G4: Name and Address of the Establishment in/under which Contract is carried on:
A7: ='4-22MASTER'!G5 -> Burgeon IT Services Pvt.Ltd. | G7: ='4-22MASTER'!AQ5 -> Burgeon IT Services Pvt.Ltd.
A9: ='4-22MASTER'!G6 -> Siri Mansion LIGB 436 Dr.A S Rao Nagar,Hyderabad | G9: ='4-22MASTER'!AQ6 -> Siri Mansion LIGB 436 Dr.A S Rao Nagar,Hyderabad
A12: Nature of work and location of work: | G12: Name and address of Principal Employer:
G15: ='4-22MASTER'!AQ10 -> INFOSYS LTD.IL Ascendas SEZ Unit,Building Juniper
A16: ='4-22MASTER'!G8 -> IT SUPPORTIVE SERVICES & PUNE ASC SEZ
G17: ='4-22MASTER'!AQ11 -> International Tech Park,Rajiv Gandhi Infotech Park,Hinjawadi,Pune,Maharashtra
A19: 1. Name of the Workman and address | G19: ='4-22MASTER'!C17 -> Haneef
G20: ='4-22MASTER'!H17 -> Sri Sai vaishnavi pg, 2nd cross, near Rajapalya, Hoodi, 560048
A21: 2. S.No. in the Register of Workmen Employed | G21: 19
A22: 3. Nature of Employment /Designation | G22: ='4-22MASTER'!G17 -> System Administrator
A23: 4. Date of entry into service | G23: ='4-22MASTER'!O17 -> 44298
A24: 5. ESI No. | G24: ='4-22MASTER'!U17 -> N/A
A25: 6.PF No. | G25: ='4-22MASTER'!T17 -> 100947550505 | I25: ='4-22MASTER'!T68 -> 0
A26: 7. Wage rate (With particulars of unit in case of piece - work) | G26: ='4-22MASTER'!Z17 -> 61740
A27: 8. Wage period | G27: ='4-22MASTER'!E10 -> 44652
A28: 9. Tenure of Employment | G28: AS PER CONTRACT
A29: 10.No. of days worked in a month | I29: ='4-22MASTER'!X17 -> 30
A30: 11. No. of units worked in case of piece rate workers | I30: N/A
A31: 12. Rate of daily wages / piece rate | I31: 0
A32: 13. Amount of overtime wages | I32: 0
A33: 14. Gross wages payable | I33: ='4-22MASTER'!AN17 -> 68276.425 | K33: MED
A34: 15. Deductions, if any, | C34: PF | D34: ='4-22MASTER'!AP17 -> 1800 | E34: ESI | F34: ='4-22MASTER'!AO68 -> 0 | G34: PT | H34: ='4-22MASTER'!AQ17 -> 200 | I34: TDS | J34: ='4-22MASTER'!AR17 -> 0 | K34: ='4-22MASTER'!AS17 -> 391.78785
A35: 16. Net amount of wages paid | I35: ='4-22MASTER'!AU17 -> 65884.638
A36: Signature of the Representative
A37: of Contractor
A53: FORM XIV
A54: EMPLOYMENT CUM WAGE CARD
A55: (Vide Rule 76 of Contract Labour (R&A) Central &Maharastra Rules, 1974)
A56: Name and Address of the Contractor | G56: Name and Address of the Establishment in/under which Contract is carried on:
A59: ='4-22MASTER'!G5 -> Burgeon IT Services Pvt.Ltd. | G59: ='4-22MASTER'!AQ5 -> Burgeon IT Services Pvt.Ltd.
A61: ='4-22MASTER'!G6 -> Siri Mansion LIGB 436 Dr.A S Rao Nagar,Hyderabad | G61: ='4-22MASTER'!AQ6 -> Siri Mansion LIGB 436 Dr.A S Rao Nagar,Hyderabad
A64: Nature of work and location of work: | G64: Name and address of Principal Employer:
G67: ='4-22MASTER'!AQ10 -> INFOSYS LTD.IL Ascendas SEZ Unit,Building Juniper
A68: ='4-22MASTER'!G8 -> IT SUPPORTIVE SERVICES & PUNE ASC SEZ
G69: ='4-22MASTER'!AQ11 -> International Tech Park,Rajiv Gandhi Infotech Park,Hinjawadi,Pune,Maharashtra
A71: 1. Name of the Workman and address | G71: ='4-22MASTER'!C18 -> Ved Prakash
G72: ='4-22MASTER'!H18 -> Flat No. A 203, Silver Palm Grove, Ravet, Pune 412101
A73: 2. S.No. in the Register of Workmen Employed | G73: ='PUNE ASC-APRIL 22WM REG'!A37 -> 25
A74: 3. Nature of Employment /Designation | G74: ='4-22MASTER'!G18 -> Project Manager
A75: 4. Date of entry into service | G75: ='4-22MASTER'!O18 -> 4th May 2021
A76: 5. ESI No. | I76: ='4-22MASTER'!U18 -> N/A
A77: 6.PF No. | I77: ='4-22MASTER'!T18 -> 100457474727
A78: 7. Wage rate (With particulars of unit in case of piece - work) | G78: ='4-22MASTER'!Z18 -> 71009
A79: 8. Wage period | G79: ='4-22MASTER'!E10 -> 44652
A80: 9. Tenure of Employment | G80: AS PER CONTRACT
A81: 10.No. of days worked in a month | I81: ='4-22MASTER'!X18 -> 20
A82: 11. No. of units worked in case of piece rate workers | I82: N/A
A83: 12. Rate of daily wages / piece rate | I83: 0
A84: 13. Amount of overtime wages | I84: 0
A85: 14. Gross wages payable | I85: ='4-22MASTER'!AN18 -> 52740.122 | K85: MED
A86: 15. Deductions, if any, | C86: PF | D86: ='4-22MASTER'!AP18 -> 1800 | E86: ESI | F86: ='4-22MASTER'!AO322 -> 0 | G86: PT | H86: ='4-22MASTER'!AQ18 -> 200 | I86: TDS | J86: ='4-22MASTER'!AR18 -> 0 | K86: ='4-22MASTER'!AS18 -> 440.76133
A87: 16. Net amount of wages paid | I87: =I85-(D86+F86+H86+J86+K86) -> 50299.361
A88: Signature of the Representative
A89: of Contractor
A107: FORM XIV
A108: EMPLOYMENT CUM WAGE CARD
A109: (Vide Rule 76 of Contract Labour (R&A) Central &Maharastra Rules, 1974)
A110: Name and Address of the Contractor | G110: Name and Address of the Establishment in/under which Contract is carried on:
A113: ='4-22MASTER'!G5 -> Burgeon IT Services Pvt.Ltd. | G113: ='4-22MASTER'!AQ5 -> Burgeon IT Services Pvt.Ltd.
A115: ='4-22MASTER'!G6 -> Siri Mansion LIGB 436 Dr.A S Rao Nagar,Hyderabad | G115: ='4-22MASTER'!AQ6 -> Siri Mansion LIGB 436 Dr.A S Rao Nagar,Hyderabad
A118: Nature of work and location of work: | G118: Name and address of Principal Employer:
G121: ='4-22MASTER'!AQ10 -> INFOSYS LTD.IL Ascendas SEZ Unit,Building Juniper
A122: ='4-22MASTER'!G8 -> IT SUPPORTIVE SERVICES & PUNE ASC SEZ
G123: ='4-22MASTER'!AQ11 -> International Tech Park,Rajiv Gandhi Infotech Park,Hinjawadi,Pune,Maharashtra
A125: 1. Name of the Workman and address | G125: ='4-22MASTER'!C19 -> GauravVispute
G126: ='4-22MASTER'!H19 -> 5/2, Trimurti Housing Socieity,Central bank colony road, Pimprala,Jalgaon 425002
A127: 2. S.No. in the Register of Workmen Employed | G127: ='4-22MASTER'!A19 -> 27
A128: 3. Nature of Employment /Designation | G128: ='4-22MASTER'!G19 -> Project Coordinator
A129: 4. Date of entry into service | G129: ='4-22MASTER'!O19 -> 4th May 2021
A130: 5. ESI No. | I130: ='4-22MASTER'!U78 -> 0
A131: 6.PF No. | I131: ='4-22MASTER'!T19 -> 101012347201
A132: 7. Wage rate (With particulars of unit in case of piece - work) | G132: ='4-22MASTER'!Z19 -> 43202
A133: 8. Wage period | G133: ='4-22MASTER'!E10 -> 44652
A134: 9. Tenure of Employment | G134: AS PER CONTRACT
A135: 10.No. of days worked in a month | I135: ='4-22MASTER'!X19 -> 29
A136: 11. No. of units worked in case of piece rate workers | I136: N/A
A137: 12. Rate of daily wages / piece rate | I137: 0
A138: 13. Amount of overtime wages | I138: 0
A139: 14. Gross wages payable | I139: ='4-22MASTER'!AN19 -> 46722.888 | K139: MED
A140: 15. Deductions, if any, | C140: PF | D140: ='4-22MASTER'!AP19 -> 1800 | E140: ESI | F140: ='4-22MASTER'!AO19 -> 0 | G140: PT | H140: ='4-22MASTER'!AQ19 -> 200 | I140: TDS | J140: ='4-22MASTER'!AR19 -> 0 | K140: ='4-22MASTER'!AS19 -> 391.78785
A141: 16. Net amount of wages paid | I141: =I139-(D140+F140+H140+J140+K140) -> 44331.101
A142: Signature of the Representative
A143: of Contractor
A160: FORM XIV
A161: EMPLOYMENT CUM WAGE CARD
A162: (Vide Rule 76 of Contract Labour (R&A) Central &Maharastra Rules, 1974)
A163: Name and Address of the Contractor | G163: Name and Address of the Establishment in/under which Contract is carried on:
A166: Burgeon IT Services Pvt.Ltd. | G166: Burgeon IT Services Pvt.Ltd.
A168: Siri Mansion LIGB 436 Dr.A S Rao Nagar,Hyderabad | G168: Siri Mansion LIGB 436 Dr.A S Rao Nagar,Hyderabad
A171: Nature of work and location of work: | G171: Name and address of Principal Employer:
G174: INFOSYS LTD.IL Ascendas SEZ Unit,Building Juniper
A175: IT SUPPORTIVE SERVICES & PUNE ASC SEZ
G176: International Tech Park,Rajiv Gandhi Infotech Park,Hinjawadi,Pune,Maharashtra
A178: 1. Name of the Workman and address | G178: ='4-22MASTER'!C20 -> Anjali Dubey
G179: ='4-22MASTER'!K20 -> H.N. 376/16, Behind P.K. School, Ravindra nagar Urrahat Rewa M.P. 486001
A180: 2. S.No. in the Register of Workmen Employed | G180: ='4-22MASTER'!A20 -> 35
...

Sheet wage sllips
A1: Form XIX - WAGE SLIP | K1: Form XIX - WAGE SLIP
A2: [Vide rule 78 (1) (b) of the Contract Labour (Regulation and Abolition) Central and Maharastra, 1971] | K2: =A2 -> [Vide rule 78 (1) (b) of the Contract Labour (Regulation and Abolition) Central and Maharastra, 1971]
A4: Name and address of Contractor | D4: ='4-22MASTER'!G5 -> Burgeon IT Services Pvt.Ltd. | K4: Name and address of Contractor | N4: =D4 -> Burgeon IT Services Pvt.Ltd.
B5: ='4-22MASTER'!G6 -> Siri Mansion LIGB 436 Dr.A S Rao Nagar,Hyderabad | L5: =B5 -> Siri Mansion LIGB 436 Dr.A S Rao Nagar,Hyderabad | T5: 2
B6: ='4-22MASTER'!G719 -> 0 | L6: =B6 -> 0
A7: Name and Father's / Husband's name of the workman | K7: Name and Father's / Husband's name of the workman
E8: ='4-22MASTER'!C17 -> Haneef | G8: ='4-22MASTER'!F17 -> D.Subahan | O8: =E8 -> Haneef | R8: =G8 -> D.Subahan
A10: Nature and location of work | E10: ='4-22MASTER'!G8 -> IT SUPPORTIVE SERVICES & PUNE ASC SEZ | K10: Nature and location of work | O10: =E10 -> IT SUPPORTIVE SERVICES & PUNE ASC SEZ
A12: For the Week / Fortnight / Month ending | E12: ='4-22MASTER'!E10 -> 44652 | K12: For the Week / Fortnight / Month ending | O12: =E12 -> 44652
A14: 1 | B14: No. of days worked | E14: ='4-22MASTER'!X17 -> 30 | K14: 1 | L14: No. of days worked | O14: =E14 -> 30
A16: 2 | B16: No. of units worked in case of piece rate workers : | K16: 2 | L16: No. of units worked in case of piece rate workers :
E17: N/A | O17: N/A
A19: 3 | B19: Rate of daily wages / piece rate | E19: N/A | K19: 3 | L19: Rate of daily wages / piece rate | O19: =E19 -> N/A
A21: 4 | B21: Amount of overtime wages | E21: Nil | K21: 4 | L21: Amount of overtime wages | O21: Nil
A23: 5 | B23: Gross wages payble | E23: ='4-22MASTER'!AN17 -> 68276.425 | K23: 5 | L23: Gross wages payble | O23: =E23 -> 68276.425
D24: EPF | E24: ESI | F24: PT | G24: TDS | H24: MEDICAL | I24: TOTAL | N24: EPF | O24: ESI | P24: PT | Q24: TDS | R24: MEDICAL | S24: TOTAL
A25: 6 | B25: Deductions, if any | D25: ='4-22MASTER'!AP17 -> 1800 | E25: ='4-22MASTER'!AO730 -> 0 | F25: ='4-22MASTER'!AQ17 -> 200 | G25: ='4-22MASTER'!AR17 -> 0 | H25: ='4-22MASTER'!AS17 -> 391.78785 | I25: =SUM(D25:H25) -> 2391.7878 | K25: 6 | L25: Deductions, if any | N25: =D25 -> 1800 | O25: =E25 -> 0 | P25: =F25 -> 200 | Q25: =G25 -> 0 | R25: =H25 -> 391.78785 | S25: =I25 -> 2391.7878
A27: 7 | B27: Net amount of wages paid | E27: =E23-I25 -> 65884.638 | K27: 7 | L27: Net amount of wages paid | O27: =E27 -> 65884.638
F31: Initial of the Contractor or his representative | P31: Initial of the Contractor or his representative
A46: Form XIX - WAGE SLIP | K46: Form XIX - WAGE SLIP
A47: [Vide rule 78 (1) (b) of the Contract Labour (Regulation and Abolition) Central and Maharastra, 1971] | K47: =A47 -> [Vide rule 78 (1) (b) of the Contract Labour (Regulation and Abolition) Central and Maharastra, 1971]
A49: Name and address of Contractor | D49: Burgeon IT Services Pvt.Ltd. | K49: Name and address of Contractor | N49: =D49 -> Burgeon IT Services Pvt.Ltd.
B50: Siri Mansion LIGB 436 Dr.A S Rao Nagar,Hyderabad | L50: =B50 -> Siri Mansion LIGB 436 Dr.A S Rao Nagar,Hyderabad
B51: ='4-22MASTER'!G887 -> 0 | L51: =B51 -> 0
A52: Name and Father's / Husband's name of the workman | K52: Name and Father's / Husband's name of the workman
E53: ='4-22MASTER'!C18 -> Ved Prakash | G53: ='4-22MASTER'!F18 -> J N Gupta | O53: =E53 -> Ved Prakash | R53: =G53 -> J N Gupta
A55: Nature and location of work | E55: ='4-22MASTER'!G8 -> IT SUPPORTIVE SERVICES & PUNE ASC SEZ | K55: Nature and location of work | O55: =E55 -> IT SUPPORTIVE SERVICES & PUNE ASC SEZ
A57: For the Week / Fortnight / Month ending | E57: ='4-22MASTER'!E10 -> 44652 | K57: For the Week / Fortnight / Month ending | O57: =E57 -> 44652
A59: 1 | B59: No. of days worked | E59: ='4-22MASTER'!X18 -> 20 | K59: 1 | L59: No. of days worked | O59: =E59 -> 20
A61: 2 | B61: No. of units worked in case of piece rate workers : | K61: 2 | L61: No. of units worked in case of piece rate workers : | T61: 7
E62: N/A | O62: N/A
A64: 3 | B64: Rate of daily wages / piece rate | E64: N/A | K64: 3 | L64: Rate of daily wages / piece rate | O64: =E64 -> N/A
A66: 4 | B66: Amount of overtime wages | E66: Nil | K66: 4 | L66: Amount of overtime wages | O66: Nil
A68: 5 | B68: Gross wages payble | E68: ='4-22MASTER'!AN18 -> 52740.122 | K68: 5 | L68: Gross wages payble | O68: =E68 -> 52740.122
D69: EPF | E69: ESI | F69: PT | G69: TDS | H69: MEDICAL | I69: TOTAL | N69: EPF | O69: ESI | P69: PT | Q69: TDS | R69: MEDICAL | S69: TOTAL
A70: 6 | B70: Deductions, if any | D70: ='4-22MASTER'!AP18 -> 1800 | E70: ='4-22MASTER'!AO898 -> 0 | F70: ='4-22MASTER'!AQ18 -> 200 | G70: ='4-22MASTER'!AR18 -> 0 | H70: ='4-22MASTER'!AS18 -> 440.76133 | I70: =SUM(D70:H70) -> 2440.7613 | K70: 6 | L70: Deductions, if any | N70: =D70 -> 1800 | O70: =E70 -> 0 | P70: =F70 -> 200 | Q70: =G70 -> 0 | R70: =H70 -> 440.76133 | S70: =I70 -> 2440.7613
A72: 7 | B72: Net amount of wages paid | E72: =E68-I70 -> 50299.361 | K72: 7 | L72: Net amount of wages paid | O72: =E72 -> 50299.361
F76: Initial of the Contractor or his representative | P76: Initial of the Contractor or his representative
A91: Form XIX - WAGE SLIP | K91: Form XIX - WAGE SLIP
A92: [Vide rule 78 (1) (b) of the Contract Labour (Regulation and Abolition) Central and Maharastra, 1971] | K92: =A92 -> [Vide rule 78 (1) (b) of the Contract Labour (Regulation and Abolition) Central and Maharastra, 1971]
A94: Name and address of Contractor | D94: Burgeon IT Services Pvt.Ltd. | K94: Name and address of Contractor | N94: =D94 -> Burgeon IT Services Pvt.Ltd.
B95: Siri Mansion LIGB 436 Dr.A S Rao Nagar,Hyderabad | L95: =B95 -> Siri Mansion LIGB 436 Dr.A S Rao Nagar,Hyderabad
B96: ='4-22MASTER'!G920 -> 0 | L96: =B96 -> 0
A97: Name and Father's / Husband's name of the workman | K97: Name and Father's / Husband's name of the workman
E98: ='4-22MASTER'!C19 -> GauravVispute | G98: ='4-22MASTER'!V19 -> GauravVispute | O98: =E98 -> GauravVispute | R98: =G98 -> GauravVispute
A100: Nature and location of work | E100: ='4-22MASTER'!G8 -> IT SUPPORTIVE SERVICES & PUNE ASC SEZ | K100: Nature and location of work | O100: =E100 -> IT SUPPORTIVE SERVICES & PUNE ASC SEZ
A102: For the Week / Fortnight / Month ending | E102: ='4-22MASTER'!E10 -> 44652 | K102: For the Week / Fortnight / Month ending | O102: =E102 -> 44652
A104: 1 | B104: No. of days worked | E104: ='4-22MASTER'!X19 -> 29 | K104: 1 | L104: No. of days worked | O104: =E104 -> 29
A106: 2 | B106: No. of units worked in case of piece rate workers : | K106: 2 | L106: No. of units worked in case of piece rate workers :
E107: N/A | O107: N/A
A109: 3 | B109: Rate of daily wages / piece rate | E109: N/A | K109: 3 | L109: Rate of daily wages / piece rate | O109: =E109 -> N/A
A111: 4 | B111: Amount of overtime wages | E111: Nil | K111: 4 | L111: Amount of overtime wages | O111: Nil
A113: 5 | B113: Gross wages payble | E113: ='4-22MASTER'!AN19 -> 46722.888 | K113: 5 | L113: Gross wages payble | O113: =E113 -> 46722.888
D114: EPF | E114: ESI | F114: PT | G114: TDS | H114: MEDICAL | I114: TOTAL | N114: EPF | O114: ESI | P114: PT | Q114: TDS | R114: MEDICAL | S114: TOTAL
A115: 6 | B115: Deductions, if any | D115: ='4-22MASTER'!AP19 -> 1800 | E115: ='4-22MASTER'!AO931 -> 0 | F115: ='4-22MASTER'!AQ19 -> 200 | G115: ='4-22MASTER'!AR19 -> 0 | H115: ='4-22MASTER'!AS19 -> 391.78785 | I115: =SUM(D115:H115) -> 2391.7878 | K115: 6 | L115: Deductions, if any | N115: =D115 -> 1800 | O115: =E115 -> 0 | P115: =F115 -> 200 | Q115: =G115 -> 0 | R115: =H115 -> 391.78785 | S115: =I115 -> 2391.7878
A117: 7 | B117: Net amount of wages paid | E117: =E113-I115 -> 44331.101 | K117: 7 | L117: Net amount of wages paid | O117: =E117 -> 44331.101
F121: Initial of the Contractor or his representative | P121: Initial of the Contractor or his representative
A136: Form XIX - WAGE SLIP | K136: Form XIX - WAGE SLIP
A137: [Vide rule 78 (1) (b) of the Contract Labour (Regulation and Abolition) Central and Maharastra, 1971] | K137: =A137 -> [Vide rule 78 (1) (b) of the Contract Labour (Regulation and Abolition) Central and Maharastra, 1971]
A139: Name and address of Contractor | D139: Burgeon IT Services Pvt.Ltd. | K139: Name and address of Contractor | N139: =D139 -> Burgeon IT Services Pvt.Ltd.
B140: Siri Mansion LIGB 436 Dr.A S Rao Nagar,Hyderabad | L140: =B140 -> Siri Mansion LIGB 436 Dr.A S Rao Nagar,Hyderabad
B141: ='4-22MASTER'!G1371 -> 0 | L141: =B141 -> 0
A142: Name and Father's / Husband's name of the workman | K142: Name and Father's / Husband's name of the workman
E143: ='4-22MASTER'!C20 -> Anjali Dubey | H143: ='4-22MASTER'!F20 -> Ravindra Nath Dubey | O143: =E143 -> Anjali Dubey | R143: =H143 -> Ravindra Nath Dubey
A145: Nature and location of work | E145: IT SUPPORTIVE SERVICES & PUNE ASC SEZ | K145: Nature and location of work | O145: =E145 -> IT SUPPORTIVE SERVICES & PUNE ASC SEZ
A147: For the Week / Fortnight / Month ending | E147: ='4-22MASTER'!E10 -> 44652 | K147: For the Week / Fortnight / Month ending | O147: =E147 -> 44652
A149: 1 | B149: No. of days worked | E149: ='4-22MASTER'!X20 -> 28 | K149: 1 | L149: No. of days worked | O149: =E149 -> 28
A151: 2 | B151: No. of units worked in case of piece rate workers : | K151: 2 | L151: No. of units worked in case of piece rate workers :
E152: N/A | O152: N/A
A154: 3 | B154: Rate of daily wages / piece rate | E154: N/A | K154: 3 | L154: Rate of daily wages / piece rate | O154: =E154 -> N/A
A156: 4 | B156: Amount of overtime wages | E156: Nil | K156: 4 | L156: Amount of overtime wages | O156: Nil
A158: 5 | B158: Gross wages payble | F158: ='4-22MASTER'!AN20 -> 61035.549 | K158: 5 | L158: Gross wages payble | O158: =E158 -> 0
D159: EPF | E159: ESI | F159: PT | G159: TDS | H159: MEDICAL | I159: TOTAL | N159: EPF | O159: ESI | P159: PT | Q159: TDS | R159: MEDICAL | S159: TOTAL
A160: 6 | B160: Deductions, if any | D160: ='4-22MASTER'!AP20 -> 1800 | E160: ='4-22MASTER'!AO1382 -> 0 | F160: ='4-22MASTER'!AQ20 -> 200 | G160: ='4-22MASTER'!AR20 -> 0 | H160: ='4-22MASTER'!AS20 -> 254 | I160: =SUM(D160:H160) -> 2254 | K160: 6 | L160: Deductions, if any | N160: =D160 -> 1800 | O160: =E160 -> 0 | P160: =F160 -> 200 | Q160: =G160 -> 0 | R160: =H160 -> 254 | S160: =I160 -> 2254
A162: 7 | B162: Net amount of wages paid | E162: =F158-D160-F160-G160-H160 -> 58781.549 | K162: 7 | L162: Net amount of wages paid | O162: =E162 -> 58781.549
F166: Initial of the Contractor or his representative | P166: Initial of the Contractor or his representative
A177: Form XIX - WAGE SLIP | K177: Form XIX - WAGE SLIP
A178: [Vide rule 78 (1) (b) of the Contract Labour (Regulation and Abolition) Central and Maharastra, 1971] | K178: =A178 -> [Vide rule 78 (1) (b) of the Contract Labour (Regulation and Abolition) Central and Maharastra, 1971]
A180: Name and address of Contractor | D180: Burgeon IT Services Pvt.Ltd. | K180: Name and address of Contractor | N180: =D180 -> Burgeon IT Services Pvt.Ltd.
B181: Siri Mansion LIGB 436 Dr.A S Rao Nagar,Hyderabad | L181: =B181 -> Siri Mansion LIGB 436 Dr.A S Rao Nagar,Hyderabad
B182: ='4-22MASTER'!G1488 -> 0 | L182: =B182 -> 0
A183: Name and Father's / Husband's name of the workman | K183: Name and Father's / Husband's name of the workman
E184: ='4-22MASTER'!C21 -> TUSHAR UCHAGAONKAR | G184: ='4-22MASTER'!F21 -> Pundalik Uchagaonkar | O184: =E184 -> TUSHAR UCHAGAONKAR | R184: =G184 -> Pundalik Uchagaonkar
A186: Nature and location of work | E186: IT SUPPORTIVE SERVICES & PUNE ASC SEZ | K186: Nature and location of work | O186: =E186 -> IT SUPPORTIVE SERVICES & PUNE ASC SEZ
A188: For the Week / Fortnight / Month ending | E188: ='4-22MASTER'!E10 -> 44652 | K188: For the Week / Fortnight / Month ending | O188: =E188 -> 44652
A190: 1 | B190: No. of days worked | E190: ='4-22MASTER'!X21 -> 30 | K190: 1 | L190: No. of days worked | O190: =E190 -> 30
A192: 2 | B192: No. of units worked in case of piece rate workers : | K192: 2 | L192: No. of units worked in case of piece rate workers :
E193: N/A | O193: N/A
A195: 3 | B195: Rate of daily wages / piece rate | E195: N/A | K195: 3 | L195: Rate of daily wages / piece rate | O195: =E195 -> N/A
A197: 4 | B197: Amount of overtime wages | E197: Nil | K197: 4 | L197: Amount of overtime wages | O197: Nil
A199: 5 | B199: Gross wages payble | E199: ='4-22MASTER'!AN21 -> 85276.022 | K199: 5 | L199: Gross wages payble | O199: =E199 -> 85276.022
D200: EPF | E200: ESI | F200: PT | G200: TDS | H200: MEDICAL | I200: TOTAL | N200: EPF | O200: ESI | P200: PT | Q200: TDS | R200: MEDICAL | S200: TOTAL
A201: 6 | B201: Deductions, if any | D201: ='4-22MASTER'!AP21 -> 1800 | E201: ='4-22MASTER'!AO1499 -> 0 | F201: ='4-22MASTER'!AQ21 -> 200 | G201: ='4-22MASTER'!AR21 -> 0 | H201: ='4-22MASTER'!AS21 -> 283 | I201: =SUM(D201:H201) -> 2283 | K201: 6 | L201: Deductions, if any | N201: =D201 -> 1800 | O201: =E201 -> 0 | P201: =F201 -> 200 | Q201: =G201 -> 0 | R201: =H201 -> 283 | S201: =I201 -> 2283
A203: 7 | B203: Net amount of wages paid | E203: =E199-I201 -> 82993.022 | K203: 7 | L203: Net amount of wages paid | O203: =E203 -> 82993.022
F207: Initial of the Contractor or his representative | P207: Initial of the Contractor or his representative
A216: Form XIX - WAGE SLIP | K216: Form XIX - WAGE SLIP
A217: [Vide rule 78 (1) (b) of the Contract Labour (Regulation and Abolition) Central and Maharastra, 1971] | K217: =A217 -> [Vide rule 78 (1) (b) of the Contract Labour (Regulation and Abolition) Central and Maharastra, 1971]
A219: Name and address of Contractor | D219: Burgeon IT Services Pvt.Ltd. | K219: Name and address of Contractor | N219: =D219 -> Burgeon IT Services Pvt.Ltd.
B220: Siri Mansion LIGB 436 Dr.A S Rao Nagar,Hyderabad | L220: =B220 -> Siri Mansion LIGB 436 Dr.A S Rao Nagar,Hyderabad
B221: ='4-22MASTER'!G1527 -> 0 | L221: =B221 -> 0
...

Sheet 4-22Bonus
A1: BONUS REGISTER
A3: FORM "c" ( See rule 4 [c] )
K4: Wage Period | L4: ='4-22MASTER'!E10 -> 44652
A5: Name of the Establishment : _____________________________ | D5: ='4-22MASTER'!G5 -> Burgeon IT Services Pvt.Ltd. | K5: Financial year _____ | M5: 2022-23
A6: ='4-22MASTER'!G6 -> Siri Mansion LIGB 436 Dr.A S Rao Nagar,Hyderabad
A7: Sr. No | B7: Name of the Employee | C7: Father's Name / Husband's Name | D7: Whether he has completed 15 yrs of age at the beginning of the accounting year | E7: Designation | F7: No. of days worked in the year | G7: Total Salary or wages in the Month | H7: Amt. of bonus payable under section 10 or section 11 as the case may be Ex gratia | I7: DEDUCTIONS | L7: Total Sum Deducted (Col. 9,10 and 11) | M7: Net Amount payable (Col. 8 minus Col. 12) | N7: Amount Actually paid | O7: Date on which paid | P7: Signature / Thumb impression of the employee
I8: Puja Bonus or other customary bonus paid during the accounting year | J8: Interim Bonus or bonus paid in advance | K8: Deduction on account of financial loss if any caused by misconduct of the employee | Q8: Account Number
A9: 1 | B9: 2 | C9: 3 | D9: 4 | E9: 5 | F9: 6 | H9: 8 | I9: 9 | J9: 10 | K9: 11 | L9: 12 | M9: 13 | N9: 14 | O9: 15 | P9: 16
A10: 1 | B10: Haneef | C10: D.Subahan | D10: YES | E10: System Administrator | F10: 30 | G10: 61853 | H10: 1555 | I10: N/A | J10: N/A | K10: N/A | L10: N/A | M10: =H10 -> 1555 | N10: =H10 -> 1555 | O10: ='4-22MASTER'!AV17 -> 05.05.2022 | P10: ='4-22MASTER'!AW17 -> SBI | Q10: ='4-22MASTER'!AX17 -> A/C'20434252219
A11: 2 | B11: Ved Prakash | C11: J N Gupta | D11: YES | E11: Project Manager | F11: 20 | G11: 47452.333 | H11: 1555 | I11: N/A | J11: N/A | K11: N/A | L11: N/A | M11: =H11 -> 1555 | N11: =H11 -> 1555 | O11: ='4-22MASTER'!AV18 -> 05.05.2022 | P11: ='4-22MASTER'!AW18 -> HDFC | Q11: ='4-22MASTER'!AX18 -> A/C'50100052341452
A12: 3 | B12: GauravVispute | C12: Bhika Jagannath | D12: YES | E12: Project Coordinator | F12: 29 | G12: 41874.933 | H12: 1555 | I12: N/A | J12: N/A | K12: N/A | L12: N/A | M12: =H12 -> 1555 | N12: =H12 -> 1555 | O12: ='4-22MASTER'!AV19 -> 05.05.2022 | P12: ='4-22MASTER'!AW19 -> SBI | Q12: ='4-22MASTER'!AX19 -> A/C'31443937313
A13: 4 | B13: Anjali Dubey | C13: Ravindra Nath Dubey | D13: YES | E13: Project Engineer | F13: 28 | G13: 55141.4 | H13: 1555 | I13: N/A | J13: N/A | K13: N/A | L13: N/A | M13: =H13 -> 1555 | N13: =H13 -> 1555 | O13: ='4-22MASTER'!AV20 -> 05.05.2022 | P13: ='4-22MASTER'!AW20 -> Union bank of India | Q13: ='4-22MASTER'!AX20 -> 631302010000771
A14: 5 | B14: TUSHAR UCHAGAONKAR | C14: Pundalik Uchagaonkar | D14: YES | E14: Network Engineer | F14: 30 | G14: 77610 | H14: 1555 | I14: N/A | J14: N/A | K14: N/A | L14: N/A | M14: =H14 -> 1555 | N14: =H14 -> 1555 | O14: ='4-22MASTER'!AV21 -> 05.05.2022 | P14: ='4-22MASTER'!AW21 -> ICICI BANK | Q14: ='4-22MASTER'!AX21 -> 042401536750
A15: 6 | B15: Sneha Hande | C15: Ramchandra Nathu Hande | D15: YES | E15: Project manager | F15: 30 | G15: 50730 | H15: 1555 | I15: N/A | J15: N/A | K15: N/A | L15: N/A | M15: =H15 -> 1555 | N15: =H15 -> 1555 | O15: ='4-22MASTER'!AV22 -> 05.05.2022 | P15: ='4-22MASTER'!AW22 -> ICICI BANK | Q15: ='4-22MASTER'!AX22 -> 148001513263
A16: 7 | B16: Amol Gole | C16: Harishchandra Gole | D16: YES | E16: Project Manager | F16: 30 | G16: 66487 | H16: 1555 | I16: N/A | J16: N/A | K16: N/A | L16: N/A | M16: =H16 -> 1555 | N16: =H16 -> 1555 | O16: ='4-22MASTER'!AV23 -> 05.05.2022 | P16: ='4-22MASTER'!AW23 -> ICICI BANK | Q16: ='4-22MASTER'!AX23 -> 623901548420
A17: 8 | B17: Sandeep Dixit | C17: Surendra Singh | D17: YES | E17: Sr. Project Manager | F17: 30 | G17: 173081 | H17: 1555 | I17: N/A | J17: N/A | K17: N/A | L17: N/A | M17: =H17 -> 1555 | N17: =H17 -> 1555 | O17: ='4-22MASTER'!AV24 -> 05.05.2022 | P17: ='4-22MASTER'!AW24 -> Punjab National Bank | Q17: ='4-22MASTER'!AX24 -> 12372191001001
A18: 9 | B18: Jaikesh Upadhyay | C18: Ashok Upadhyay | D18: YES | E18: Sr. Project Coordinator | F18: 30 | G18: 112832 | H18: 1555 | I18: N/A | J18: N/A | K18: N/A | L18: N/A | M18: =H18 -> 1555 | N18: =H18 -> 1555 | O18: ='4-22MASTER'!AV25 -> 05.05.2022 | P18: ='4-22MASTER'!AW25 -> ICICI BANK | Q18: ='4-22MASTER'!AX25 -> 338201500480
A19: 10 | B19: Jyoti Singh | C19: Ashok Kumar Singh | D19: YES | E19: Sr.Security analyst | F19: 30 | G19: 103563 | H19: 1555 | I19: N/A | J19: N/A | K19: N/A | L19: N/A | M19: =H19 -> 1555 | N19: =H19 -> 1555 | O19: ='4-22MASTER'!AV26 -> 05.05.2022 | P19: ='4-22MASTER'!AW26 -> ICICI BANK | Q19: ='4-22MASTER'!AX26 -> 341901505420
A20: 11 | B20: Chandrashekar Patil | C20: Shivraj Patil | D20: YES | E20: Project Manager | F20: 27 | G20: 66523.1 | H20: 1555 | I20: N/A | J20: N/A | K20: N/A | L20: N/A | M20: =H20 -> 1555 | N20: =H20 -> 1555 | O20: ='4-22MASTER'!AV27 -> 05.05.2022 | P20: ='4-22MASTER'!AW27 -> HDFC | Q20: ='4-22MASTER'!AX27 -> 100783283673
A21: 12 | B21: ShaikFarooq Basha | C21: Shaik Mabu Subahan | D21: YES | E21: Software Engineer | F21: 30 | G21: 103563 | H21: 1555 | I21: N/A | J21: N/A | K21: N/A | L21: N/A | M21: =H21 -> 1555 | N21: =H21 -> 1555 | O21: ='4-22MASTER'!AV28 -> 05.05.2022 | P21: ='4-22MASTER'!AW28 -> HDFC | Q21: ='4-22MASTER'!AX28 -> 50100383537784
A22: 13 | B22: NILOTPAL BHOWAL | C22: Dwijendra Kumar Bhowal | D22: YES | E22: VM ware consultant | F22: 30 | G22: 122101 | H22: 1555 | I22: N/A | J22: N/A | K22: N/A | L22: N/A | M22: =H22 -> 1555 | N22: =H22 -> 1555 | O22: ='4-22MASTER'!AV29 -> 05.05.2022 | P22: ='4-22MASTER'!AW29 -> ICICI bank | Q22: ='4-22MASTER'!AX29 -> 272301504703
A23: 14 | B23: Varsha Amit Kadam | C23: ='4-22MASTER'!F30 -> Amit Kadam | D23: YES | E23: Program Manager | F23: 6 | G23: 10977.8 | H23: 1555 | I23: N/A | J23: N/A | K23: N/A | L23: N/A | M23: =H23 -> 1555 | N23: =H23 -> 1555 | O23: ='4-22MASTER'!AV30 -> 05.05.2022 | P23: ='4-22MASTER'!AW30 -> Kotak Mahindra Bank | Q23: ='4-22MASTER'!AX30 -> 7311156365
F24: =SUM(F10:F23) -> 380
L34: Signature of the Contractor with Seal

Sheet Deductions
A1: FORM XVI- REGISTER OF DEDUCTIONS FOR DAMAGE OR LOSS
A3: (Vide Rule 78(1) (a) (i) of Contract Labour (Regulation and Abolition) Maharashtra Rules 1971.
A4: Name and address of Contractor: GROTECH LANDSCAPE DEVELOPERS PVT.LTD. | D4: ='4-22MASTER'!G5 -> Burgeon IT Services Pvt.Ltd. | E4: Name and address of the establishment in / under which contract is carried on:
B5: ='4-22MASTER'!G6 -> Siri Mansion LIGB 436 Dr.A S Rao Nagar,Hyderabad
B6: ='4-22MASTER'!G7 -> 0
A7: Nature and Location of Work: | D7: ='4-22MASTER'!G8 -> IT SUPPORTIVE SERVICES & PUNE ASC SEZ | E7: Name and address of principal employer:
E8: ='4-22MASTER'!AQ10 -> INFOSYS LTD.IL Ascendas SEZ Unit,Building Juniper
E9: ='4-22MASTER'!AQ11 -> International Tech Park,Rajiv Gandhi Infotech Park,Hinjawadi,Pune,Maharashtra
A11: S.No | B11: Name of workman | C11: Father's / Husband's Name | D11: Designation / Nature of employment | E11: Particulars of damage or loss | F11: Date of Damage or loss | G11: Whether workman showed cause against deduction | H11: Name of person in whose presence employee's explanation was heard | I11: Amount of deduction impossed | J11: Date of recovery | M11: Remarks
J12: No.of Instalments | K12: First Instalment | L12: Last instalment
A13: 1 | B13: 2 | C13: 3 | D13: 4 | E13: 5 | F13: 6 | G13: 7 | H13: 8 | I13: 9 | J13: 10 | K13: 11 | L13: 12 | M13: 13
B16: NO EMPLOYEE WAS IMPOSED DEDUCTIONS FOR DAMAGE OR LOSS FOR THE MONTH OF | H16: ='4-22MASTER'!E10 -> 44652
F41: Signature of the Contractor with Seal

Sheet Fines
A1: FORM XVII- REGISTER OF FINES
A3: (Vide Rule 78(1) (a) (i) of Contract Labour (Regulation and Abolition) Maharashtra Rules 1971
A4: Name and address of Contractor: | D4: ='4-22MASTER'!G5 -> Burgeon IT Services Pvt.Ltd. | E4: Name and address of the establishment in / under which contract is carried on:
B5: ='4-22MASTER'!G6 -> Siri Mansion LIGB 436 Dr.A S Rao Nagar,Hyderabad
B6: ='4-22MASTER'!G7 -> 0
A7: Nature and Location of Work: | D7: ='4-22MASTER'!G8 -> IT SUPPORTIVE SERVICES & PUNE ASC SEZ | E7: Name and address of principal employer:
E8: ='4-22MASTER'!AQ10 -> INFOSYS LTD.IL Ascendas SEZ Unit,Building Juniper
E9: ='4-22MASTER'!AQ11 -> International Tech Park,Rajiv Gandhi Infotech Park,Hinjawadi,Pune,Maharashtra
A11: S.No | B11: Name of workman | C11: Father's / Husband's Name | D11: Designation / Nature of employment | E11: Act/Omission for which fine imposed | F11: Date of offence | G11: Whether workman showed cause against fine | H11: Name of person in whose presence employee's explanation was heard | I11: Wage-period and wge payable | J11: Amount of fine Imposed | K11: Date on which fine realised | L11: Remarks
A13: 1 | B13: 2 | C13: 3 | D13: 4 | E13: 5 | F13: 6 | G13: 7 | H13: 8 | I13: 9 | J13: 10 | K13: 11 | L13: 12
B16: NO EMPLOYEE WAS IMPOSED FINESFOR THE MONTH OF | H16: ='4-22MASTER'!E10 -> 44652
F40: Signature of the Contractor with Seal

Sheet Advances
A1: FORM XVIII- REGISTER OF ADVANCES
A3: (Vide Rule 78(1) (a) (i) of Contract Labour (Regulation and Abolition) Maharashtra Rules 1971
A4: Name and address of Contractor: | D4: ='4-22MASTER'!G5 -> Burgeon IT Services Pvt.Ltd. | E4: Name and address of the establishment in / under which contract is carried on:
B5: ='4-22MASTER'!G6 -> Siri Mansion LIGB 436 Dr.A S Rao Nagar,Hyderabad
A7: Nature and Location of Work: | D7: ='4-22MASTER'!G8 -> IT SUPPORTIVE SERVICES & PUNE ASC SEZ | E7: Name and address of principal employer:
E8: ='4-22MASTER'!AQ10 -> INFOSYS LTD.IL Ascendas SEZ Unit,Building Juniper
E9: ='4-22MASTER'!AQ11 -> International Tech Park,Rajiv Gandhi Infotech Park,Hinjawadi,Pune,Maharashtra
A11: S.No | B11: Name of workman | C11: Father's / Husband's Name | D11: Designation / Nature of employment | E11: Wage period and wages payable | F11: Date and amount of advance given | G11: Purpose(s) for which advance made | H11: Number of instalments by which advance to be repaid | I11: Date and amount of each instalment repaid | J11: Date on which last instalment was repaid | K11: Remarks
A13: 1 | B13: 2 | C13: 3 | D13: 4 | E13: 5 | F13: 6 | G13: 7 | H13: 8 | I13: 9 | J13: 10 | K13: 11
B16: NO EMPLOYEE TAKEN ADVANCE FOR THE MONTH OF | F16: ='4-22MASTER'!E10 -> 44652
G39: Signature of the Contractor with Seal

Sheet Overtime
A1: FORM XIX- REGISTER OF OVERTIME
A3: (Vide Rule 78(1) (a) (i) of Contract Labour (Regulation and Abolition) Maharashtra Rules 1971
A4: Name and address of Contractor: GROTECH LANDSCAPE DEVELOPERS PVT.LTD. E-35 GREATER KAILASH ENCLAVE-1 NEW DELHI | D4: ='4-22MASTER'!G5 -> Burgeon IT Services Pvt.Ltd. | F4: Name and address of the establishment in which under contract is carried on:
B5: ='4-22MASTER'!G6 -> Siri Mansion LIGB 436 Dr.A S Rao Nagar,Hyderabad
A7: Nature and Location of Work: | D7: ='4-22MASTER'!G8 -> IT SUPPORTIVE SERVICES & PUNE ASC SEZ | F7: Name and address of principal employer:
F8: ='4-22MASTER'!AQ10 -> INFOSYS LTD.IL Ascendas SEZ Unit,Building Juniper
F9: ='4-22MASTER'!AQ11 -> International Tech Park,Rajiv Gandhi Infotech Park,Hinjawadi,Pune,Maharashtra
A11: S.No | B11: Name of workman | C11: Father's / Husband's Name | D11: Sex | E11: Designation / Nature of employment | F11: Date on which overtime worked | G11: Total overtime worked or production in case of piece-rates | H11: Normal rate of wages | I11: Overtime rate of wages | J11: overtime earnings | K11: Date on which overtime wages paid | L11: Remarks
A13: 1 | B13: 2 | C13: 3 | D13: 4 | E13: 5 | F13: 6 | G13: 7 | H13: 8 | I13: 9 | J13: 10 | K13: 11 | L13: 12
B16: NO EMPLOYEE DONE OVERTIME FOR THE MONTH OF | F16: ='4-22MASTER'!E10 -> 44652
G37: Signature of the Contractor with Seal

Sheet Accident
A1: FORM 11
A3: ACCIDENT BOOK
A4: EMPLOYEE STATE INSURANCE CORPORATION
B5: (Regulation 66)
A7: S.No | B7: Date of Notice | C7: Time of Notice | D7: Name and Address of the Injured Person | E7: Sex | F7: Age | H7: Shift,Department and occupation of employee | I7: Details of Injury | P7: Signature and designation of the person who makes the entry in the accident book | Q7: Name,address and occupation of the two witnesses | R7: Remarks if any
G8: Insurance Number | N8: What exactly was the injured person doing at the time of accident | O8: Name,Occupation,address and signature or the thumb impression of the person(s) giving notice
I9: Cause | J9: Nature | K9: Date | L9: Time | M9: Place
A10: 1 | B10: 2 | C10: 3 | D10: 4 | E10: 5 | F10: 6 | G10: 7 | H10: 8 | I10: 9 | J10: 10 | K10: 11 | L10: 12 | M10: 13 | N10: 14 | O10: 15 | P10: 16 | Q10: 17 | R10: 18
B12: NO ACCIDENT OCCURRED FOR THE MONTH OF | F12: ='4-22MASTER'!E10 -> 44652
J30: Signature of the Contractor with Seal

Sheet ESI cards Reg

Sheet Form-I
B1: FORM I
B2: NOMINATION AND DECLARATION FORM
B3: (Vide Rule 3 of Payment of wages Act Central & A.P Rules, 1936)
B4: Name and Address of the Contractor | H4: Name and Address of the Establishment in/under which Contract is carried on:
B7: =#REF! -> #REF! | H7: =#REF! -> #REF!
B9: =#REF! -> #REF! | H9: =#REF! -> #REF!
B12: Nature of work and location of work: | H12: Name and address of Principal Employer:
H15: =#REF! -> #REF!
B16: =#REF! -> #REF!
H17: =#REF! -> #REF!
B19: 1. Name of the person making nomination | H19: ='4-22MASTER'!#REF! -> #REF!
B20: 2. Father's/Husband name | H20: ='4-22MASTER'!#REF! -> #REF!
B21: 3. Date of Birth | H21: ='4-22MASTER'!#REF! -> #REF!
B22: 4. Sex | H22: ='4-22MASTER'!#REF! -> #REF!
B23: 5. Marital Status | H23: Un-Married
B24: 6.Address
B25: Permanent | H25: ='4-22MASTER'!#REF! -> #REF!
H26: ='4-22MASTER'!#REF! -> #REF!
H27: ='4-22MASTER'!#REF! -> #REF!
B28: Temporary | H28: ='4-22MASTER'!#REF! -> #REF!
H29: ='4-22MASTER'!#REF! -> #REF!
H30: ='4-22MASTER'!#REF! -> #REF!
B31: I hereby nominate the person(s)/cancel the nomination made by me previously and nominate the person(s) mentioned below to
B32: receive any amount due to me from the employer,in the event to my death.
B33: Name of the Nominee/nominees | E33: Address | G33: Nominee's relationship With the member | I33: Date of Birth | J33: Total amount of Share of accumulations | K33: If the nominee is minor,name,relationship and address of the guardian
B34: 1 | E34: 2 | G34: 3 | I34: 4 | J34: 5 | L34: 6
B35: ='4-22MASTER'!#REF! -> #REF! | E35: Same as permanant address | G35: Father | I35: 54 years | J35: 1 | K35: N/A
B39: 1.Certified that I have no family and should I acquire a family hereafter,the above nomination shall be deemed as cancelled.
B40: 2.Certified that my father/mother is/ are dependent upon me.
B41: 3.Strike out whichever is not applicable.
I43: Signature or the thumb impression of the employed person
F44: CERTIFCATE BY EMPLOYER
A45: Certified that the above declaration and nomination has been signed/thumb impressed before me by Shri/Smt/Kum | K45: ='4-22MASTER'!#REF! -> #REF!
A46: employed in my establishment after he/she has read the entry/entries have been read over to him/her by me and got confirmed by him/her.
F49: Signature or the employer or other authorized officer of the establiment and Designation
A50: Place | B50: Hyderabad | F50: ='4-22MASTER'!AQ5 -> Burgeon IT Services Pvt.Ltd.
A51: Date | B51: ='4-22MASTER'!#REF! -> #REF! | F51: ='4-22MASTER'!AQ6 -> Siri Mansion LIGB 436 Dr.A S Rao Nagar,Hyderabad
B53: FORM I
B54: NOMINATION AND DECLARATION FORM
B55: (Vide Rule 3 of Payment of wages Act Central & A.P Rules, 1936)
B56: Name and Address of the Contractor | H56: Name and Address of the Establishment in/under which Contract is carried on:
B59: ='4-22MASTER'!G5 -> Burgeon IT Services Pvt.Ltd. | H59: ='4-22MASTER'!AQ5 -> Burgeon IT Services Pvt.Ltd.
B61: ='4-22MASTER'!G6 -> Siri Mansion LIGB 436 Dr.A S Rao Nagar,Hyderabad | H61: ='4-22MASTER'!AQ6 -> Siri Mansion LIGB 436 Dr.A S Rao Nagar,Hyderabad
B64: Nature of work and location of work: | H64: Name and address of Principal Employer:
H67: ='4-22MASTER'!AQ10 -> INFOSYS LTD.IL Ascendas SEZ Unit,Building Juniper
B68: ='4-22MASTER'!G8 -> IT SUPPORTIVE SERVICES & PUNE ASC SEZ
H69: ='4-22MASTER'!AQ11 -> International Tech Park,Rajiv Gandhi Infotech Park,Hinjawadi,Pune,Maharashtra
B71: 1. Name of the person making nomination | H71: ='4-22MASTER'!#REF! -> #REF!
B72: 2. Father's/Husband name | H72: ='4-22MASTER'!#REF! -> #REF!
B73: 3. Date of Birth | H73: ='4-22MASTER'!#REF! -> #REF!
B74: 4. Sex | H74: ='4-22MASTER'!#REF! -> #REF!
B75: 5. Marital Status | H75: Un-Married
B76: 6.Address
B77: Permanent | H77: ='4-22MASTER'!#REF! -> #REF!
H78: ='4-22MASTER'!#REF! -> #REF!
H79: ='4-22MASTER'!#REF! -> #REF!
B80: Temporary | H80: ='4-22MASTER'!#REF! -> #REF!
H81: ='4-22MASTER'!#REF! -> #REF!
H82: ='4-22MASTER'!#REF! -> #REF!
B83: I hereby nominate the person(s)/cancel the nomination made by me previously and nominate the person(s) mentioned below to
B84: receive any amount due to me from the employer,in the event to my death.
B85: Name of the Nominee/nominees | E85: Address | G85: Nominee's relationship With the member | I85: Date of Birth | J85: Total amount of Share of accumulations | K85: If the nominee is minor,name,relationship and address of the guardian
B86: 1 | E86: 2 | G86: 3 | I86: 4 | J86: 5 | L86: 6
B87: ='4-22MASTER'!#REF! -> #REF! | E87: Same as permanant address | G87: Father | I87: 54 years | J87: 1 | K87: N/A
B91: 1.Certified that I have no family and should I acquire a family hereafter,the above nomination shall be deemed as cancelled.
B92: 2.Certified that my father/mother is/ are dependent upon me.
B93: 3.Strike out whichever is not applicable.
I95: Signature or the thumb impression of the employed person
F96: CERTIFCATE BY EMPLOYER
A97: Certified that the above declaration and nomination has been signed/thumb impressed before me by Shri/Smt/Kum | K97: ='4-22MASTER'!#REF! -> #REF!
A98: employed in my establishment after he/she has read the entry/entries have been read over to him/her by me and got confirmed by him/her.
F101: Signature or the employer or other authorized officer of the establiment and Designation
A102: Place | B102: Hyderabad | F102: ='4-22MASTER'!G5 -> Burgeon IT Services Pvt.Ltd.
A103: Date | B103: ='4-22MASTER'!#REF! -> #REF! | F103: ='4-22MASTER'!G6 -> Siri Mansion LIGB 436 Dr.A S Rao Nagar,Hyderabad
B107: FORM I
B108: NOMINATION AND DECLARATION FORM
B109: (Vide Rule 3 of Payment of wages Act Central & A.P Rules, 1936)
B110: Name and Address of the Contractor | H110: Name and Address of the Establishment in/under which Contract is carried on:
B113: ='4-22MASTER'!G5 -> Burgeon IT Services Pvt.Ltd. | H113: ='4-22MASTER'!AQ5 -> Burgeon IT Services Pvt.Ltd.
B115: ='4-22MASTER'!G6 -> Siri Mansion LIGB 436 Dr.A S Rao Nagar,Hyderabad | H115: ='4-22MASTER'!AQ6 -> Siri Mansion LIGB 436 Dr.A S Rao Nagar,Hyderabad
B118: Nature of work and location of work: | H118: Name and address of Principal Employer:
H121: ='4-22MASTER'!AQ10 -> INFOSYS LTD.IL Ascendas SEZ Unit,Building Juniper
B122: ='4-22MASTER'!G8 -> IT SUPPORTIVE SERVICES & PUNE ASC SEZ
H123: ='4-22MASTER'!AQ11 -> International Tech Park,Rajiv Gandhi Infotech Park,Hinjawadi,Pune,Maharashtra
B125: 1. Name of the person making nomination | H125: ='4-22MASTER'!#REF! -> #REF!
B126: 2. Father's/Husband name | H126: ='4-22MASTER'!#REF! -> #REF!
B127: 3. Date of Birth | H127: ='4-22MASTER'!#REF! -> #REF!
B128: 4. Sex | H128: ='4-22MASTER'!#REF! -> #REF!
B129: 5. Marital Status | H129: Un-Married
B130: 6.Address
B131: Permanent | H131: ='4-22MASTER'!#REF! -> #REF!
H132: ='4-22MASTER'!#REF! -> #REF!
H133: ='4-22MASTER'!#REF! -> #REF!
B134: Temporary | H134: ='4-22MASTER'!#REF! -> #REF!
H135: ='4-22MASTER'!#REF! -> #REF!
H136: ='4-22MASTER'!#REF! -> #REF!
B137: I hereby nominate the person(s)/cancel the nomination made by me previously and nominate the person(s) mentioned below to
B138: receive any amount due to me from the employer,in the event to my death.
B139: Name of the Nominee/nominees | E139: Address | G139: Nominee's relationship With the member | I139: Date of Birth | J139: Total amount of Share of accumulations | K139: If the nominee is minor,name,relationship and address of the guardian
B140: 1 | E140: 2 | G140: 3 | I140: 4 | J140: 5 | L140: 6
...

Sheet Form-2
K1: (FORM 2 REVISED)
B2: NOMINATION AND DECLARATION FORM FOR UNEXEMPTED/EXEMPTED ESTABLISHMENTS
B3: Declaration and Nomination Form under the Employees Provident Funds and Employees Pension Schemes
B4: (Paragraph 33 and 61(1) of the Employees Provident Fund Scheme 1952 and Paragraph 18 of the Employees Pension Scheme 1995)
B6: 1. Name of the person making nomination | H6: ='4-22MASTER'!#REF! -> #REF!
B7: 2. Father's/Husband name | H7: ='4-22MASTER'!#REF! -> #REF!
B8: 3. Date of Birth | H8: ='4-22MASTER'!#REF! -> #REF!
B9: 4. Sex | H9: ='4-22MASTER'!#REF! -> #REF!
B10: 5. Marital Status | H10: Un-Married
B11: 6.Address
B12: Permanent | H12: ='4-22MASTER'!#REF! -> #REF!
H13: ='4-22MASTER'!#REF! -> #REF!
H14: ='4-22MASTER'!#REF! -> #REF!
G15: PART-A(EPF)
B16: I hereby nominate the person(s)/cancel the nomination made by me previously and nominate the person(s) mentioned below to
B17: receive any amount due to me from the employer,in the event to my death.
B18: Name of the Nominee/nominees | E18: Address | G18: Nominee's relationship With the member | I18: Date of Birth | J18: Total amount of Share of accumulations | K18: If the nominee is minor,name,relationship and address of the guardian
B19: 1 | E19: 2 | G19: 3 | I19: 4 | J19: 5 | L19: 6
B20: ='4-22MASTER'!#REF! -> #REF! | E20: Same as Permanant Address | G20: Father | I20: 55 Years | J20: 1 | K20: N/A
B24: 1.Certified that I have no family and should I acquire a family hereafter,the above nomination shall be deemed as cancelled.
B25: 2.Certified that my father/mother is/ are dependent upon me.
B26: Strike out whichever is not applicable | J26: Signature/or thumb impression of the subscriber
G27: PART (EPS)
G28: Para 18
B29: I hereby furnish below particulars of the members of my family who would be eligible to receive Widow/Children Pension in the event of
B30: my premature death in service
B31: S.No | C31: Name & Address of the Family Member | I31: Age | J31: Relationship with the member
B32: 1 | E32: 2 | I32: 3 | K32: 4
B37: Certified that I have no family as defined in para 2 (vii) of the Employees's Family Pension Scheme 1995 and should I acquire a family hereafter
B38: I shall furnish Particulars there on in the above form.
B39: I hereby nominate the following person for receiving the monthly widow pension (admissible under para 16 2 (a) (1) & (ii) in the even of my death
B40: without leaving any eligible member for receiving pension.
B41: Name and Address of the nominee | G41: Date of Birth | I41: Relationship with member
B47: Date | C47: ='4-22MASTER'!#REF! -> #REF! | I47: Signature or thumb impression of the subscriber
F48: CERTIFCATE BY EMPLOYER
A49: Certified that the above declaration and nomination has been signed/thumb impressed before me by Shri/Smt/Kum | K49: ='4-22MASTER'!#REF! -> #REF!
A50: employed in my establishment after he/she has read the entry/entries have been read over to him/her by me and got confirmed by him/her.
F52: Signature or the employer or other authorized officer of the establiment and Designation
A53: Place | B53: Hyderabad | F53: ='4-22MASTER'!G5 -> Burgeon IT Services Pvt.Ltd.
A54: Date | B54: ='4-22MASTER'!#REF! -> #REF! | F54: ='4-22MASTER'!G6 -> Siri Mansion LIGB 436 Dr.A S Rao Nagar,Hyderabad
K55: (FORM 2 REVISED)
B56: NOMINATION AND DECLARATION FORM FOR UNEXEMPTED/EXEMPTED ESTABLISHMENTS
B57: Declaration and Nomination Form under the Employees Provident Funds and Employees Pension Schemes
B58: (Paragraph 33 and 61(1) of the Employees Provident Fund Scheme 1952 and Paragraph 18 of the Employees Pension Scheme 1995)
B60: 1. Name of the person making nomination | H60: ='4-22MASTER'!#REF! -> #REF!
B61: 2. Father's/Husband name | H61: ='4-22MASTER'!#REF! -> #REF!
B62: 3. Date of Birth | H62: ='4-22MASTER'!#REF! -> #REF!
B63: 4. Sex | H63: ='4-22MASTER'!#REF! -> #REF!
B64: 5. Marital Status | H64: Un-Married
B65: 6.Address
B66: Permanent | H66: ='4-22MASTER'!#REF! -> #REF!
H67: ='4-22MASTER'!#REF! -> #REF!
H68: ='4-22MASTER'!#REF! -> #REF!
G69: PART-A(EPF)
B70: I hereby nominate the person(s)/cancel the nomination made by me previously and nominate the person(s) mentioned below to
B71: receive any amount due to me from the employer,in the event to my death.
B72: Name of the Nominee/nominees | E72: Address | G72: Nominee's relationship With the member | I72: Date of Birth | J72: Total amount of Share of accumulations | K72: If the nominee is minor,name,relationship and address of the guardian
B73: 1 | E73: 2 | G73: 3 | I73: 4 | J73: 5 | L73: 6
B74: ='4-22MASTER'!#REF! -> #REF! | E74: Same as Permanant Address | G74: Father | I74: 55 Years | J74: 1 | K74: N/A
B78: 1.Certified that I have no family and should I acquire a family hereafter,the above nomination shall be deemed as cancelled.
B79: 2.Certified that my father/mother is/ are dependent upon me.
B80: Strike out whichever is not applicable | J80: Signature/or thumb impression of the subscriber
G81: PART (EPS)
G82: Para 18
B83: I hereby furnish below particulars of the members of my family who would be eligible to receive Widow/Children Pension in the event of
B84: my premature death in service
B85: S.No | C85: Name & Address of the Family Member | I85: Age | J85: Relationship with the member
B86: 1 | E86: 2 | I86: 3 | K86: 4
B91: Certified that I have no family as defined in para 2 (vii) of the Employees's Family Pension Scheme 1995 and should I acquire a family hereafter
B92: I shall furnish Particulars there on in the above form.
B93: I hereby nominate the following person for receiving the monthly widow pension (admissible under para 16 2 (a) (1) & (ii) in the even of my death
B94: without leaving any eligible member for receiving pension.
B95: Name and Address of the nominee | G95: Date of Birth | I95: Relationship with member
B101: Date | C101: ='4-22MASTER'!#REF! -> #REF! | I101: Signature or thumb impression of the subscriber
F102: CERTIFCATE BY EMPLOYER
A103: Certified that the above declaration and nomination has been signed/thumb impressed before me by Shri/Smt/Kum | K103: ='4-22MASTER'!#REF! -> #REF!
A104: employed in my establishment after he/she has read the entry/entries have been read over to him/her by me and got confirmed by him/her.
F106: Signature or the employer or other authorized officer of the establiment and Designation
A107: Place | B107: Hyderabad | F107: ='4-22MASTER'!G5 -> Burgeon IT Services Pvt.Ltd.
A108: Date | B108: ='4-22MASTER'!#REF! -> #REF! | F108: ='4-22MASTER'!G6 -> Siri Mansion LIGB 436 Dr.A S Rao Nagar,Hyderabad
K109: (FORM 2 REVISED)
B110: NOMINATION AND DECLARATION FORM FOR UNEXEMPTED/EXEMPTED ESTABLISHMENTS
B111: Declaration and Nomination Form under the Employees Provident Funds and Employees Pension Schemes
B112: (Paragraph 33 and 61(1) of the Employees Provident Fund Scheme 1952 and Paragraph 18 of the Employees Pension Scheme 1995)
B114: 1. Name of the person making nomination | H114: ='4-22MASTER'!#REF! -> #REF!
B115: 2. Father's/Husband name | H115: ='4-22MASTER'!#REF! -> #REF!
B116: 3. Date of Birth | H116: ='4-22MASTER'!#REF! -> #REF!
B117: 4. Sex | H117: ='4-22MASTER'!#REF! -> #REF!
B118: 5. Marital Status | H118: Un-Married
B119: 6.Address
B120: Permanent | H120: ='4-22MASTER'!#REF! -> #REF!
H121: ='4-22MASTER'!#REF! -> #REF!
H122: ='4-22MASTER'!#REF! -> #REF!
G123: PART-A(EPF)
B124: I hereby nominate the person(s)/cancel the nomination made by me previously and nominate the person(s) mentioned below to
B125: receive any amount due to me from the employer,in the event to my death.
B126: Name of the Nominee/nominees | E126: Address | G126: Nominee's relationship With the member | I126: Date of Birth | J126: Total amount of Share of accumulations | K126: If the nominee is minor,name,relationship and address of the guardian
B127: 1 | E127: 2 | G127: 3 | I127: 4 | J127: 5 | L127: 6
B128: ='4-22MASTER'!#REF! -> #REF! | E128: Same as Permanant Address | G128: Father | I128: 55 Years | J128: 1 | K128: N/A
B132: 1.Certified that I have no family and should I acquire a family hereafter,the above nomination shall be deemed as cancelled.
...

Sheet Form 11
I1: New Form No. 11 - Declaration Form
B2: (To be retained by t he employer for future reference)
D3: EMPLOYEES' PROVIDENT FUND ORGANIZATION | I3: Emp Code: | K3: ='4-22MASTER'!#REF! -> #REF!
C4: Employees' Provident Funds Scheme, 1952 (Paragraph 34 & 57) & | I4: Company | J4: ='4-22MASTER'!G5 -> Burgeon IT Services Pvt.Ltd.
C5: The Employees' Pension Scheme, 1995 (Paragraph 24) | I5: ='4-22MASTER'!G6 -> Siri Mansion LIGB 436 Dr.A S Rao Nagar,Hyderabad
A8: 1 | B8: Name of the Member | H8: ='4-22MASTER'!#REF! -> #REF!
A9: 2 | B9: Fathers' Name | F9: Husband's Name | H9: ='4-22MASTER'!#REF! -> #REF!
B10: (Please tick whichever is applicable)
A11: 3 | B11: Date of Birth (DD/MM/YYYY) | H11: ='4-22MASTER'!#REF! -> #REF!
A12: 4 | B12: Gender (Male/Female/Transgender) | H12: ='4-22MASTER'!#REF! -> #REF!
A13: 5 | B13: Marital Status(married / Unmarried / Widow/divorce) | H13: UNMARRIED
A14: 6 | B14: (a) | C14: Email Id
B15: (b) | C15: Mobile No.
A16: 7 | B16: Whether earlier a member of the Employees' Provident Fund Scheme, 1952 ? | H16: Yes | K16: No
A17: 8 | B17: Whether earlier a member of the Employees' Pension Scheme, 1995? | H17: Yes | K17: No
F18: Previous employment details [if Yes to 7 &/or 8 above]
A19: 9 | B19: a) | C19: Universal Account Number
B20: b) | C20: Previous PF Account Number
B21: C) | C21: Date of exit from previous employment (DD/MM/YYYY)
B22: d) | C22: Scheme Certificate No. (if issued)
B23: e) | C23: Pension Payment Order (PPO) No. (if issued)
A24: 10 | B24: a) | C24: International Worker | H24: Yes | K24: No
B25: b) | C25: If yes, state country of origin(India/Name of other country)
B26: C) | C26: Passport No.
B27: d) | C27: Validity of passport [(DD/MM/YYYY) to (DD/MM/YYYY)]
E28: KYC Details (attach self attested copies of following KYCs)
A29: 11 | B29: a) | C29: Bank Account No. & IFS Code
B30: b) | C30: AADHAR No.
B31: c) | C31: Permanent Account No. (PAN), if available
F32: UNDERTAKING
B33: 1) | C33: Certified that the particulars are true to the best of my knowledge.
B34: 2) | C34: I authorize EPFO to use my Aadhar for verification/authentication/eKYC purpose for service delivery.
B35: 3) | C35: Kindly transfer the funds and service details, if applicable from the previous PF account as declared above to the present P.F. Account (The Transfer would be possible only if the identified KYC details approved by previous employer has been verified by present employer
B36: 4) | C36: In case of changes in above details, the same will be intimated to employer at the earliest.
C37: Date : | D37: ='4-22MASTER'!#REF! -> #REF!
C38: Place: | D38: Hyderabad | J38: Signature of Member
F40: DECLARATION BY PRESENT EMPLOYER
A41: A) | B41: The member Mr./Ms./Mrs. | E41: ='4-22MASTER'!#REF! -> #REF! | H41: has joined on | J41: ='4-22MASTER'!#REF! -> #REF! | K41: and has been allotted PF Number
B42: ='4-22MASTER'!#REF! -> #REF!
A43: B) | B43: In case the person was earlier not a member of EPF Scheme, 1952 and EPS, 1995:
B44: (Post allotment of UAN) The UAN allotted for the member is
B45: Please Tick the Appropriate Option:
B46: The KYC details of the above member in the UAN database
B47: Have not been uploaded
B48: Have been uploaded but not approved
B49: Have been uploaded and approved with DSC
A50: C) | B50: In case the person was earlier a member of EPF Scheme, 1952 and EPS, 1995:
B51: The above PF Account Number/ UAN of the member as mentioned in (A) above has been tagged with his/her UAN/Previous Member ID as declared by member.
B52: Please Tick the Appropriate Option:
B53: The KYC details of the above member in the UAN database have been approved with DSC and transfer request has been generated on portal.
B54: As the DSC of establishment are not registered with EPFO, the member has been informed to file physical claim (Form 13) for transfer of funds
B55: from his previous establishment.
B56: Date | C56: =D37 -> #REF! | I56: Signature of Employer with seal of Establishment
I59: New Form No. 11 - Declaration Form
B60: (To be retained by t he employer for future reference)
D61: EMPLOYEES' PROVIDENT FUND ORGANIZATION | I61: Emp Code: | K61: ='4-22MASTER'!#REF! -> #REF!
C62: Employees' Provident Funds Scheme, 1952 (Paragraph 34 & 57) & | I62: Company | J62: ='4-22MASTER'!G5 -> Burgeon IT Services Pvt.Ltd.
C63: The Employees' Pension Scheme, 1995 (Paragraph 24) | I63: ='4-22MASTER'!G6 -> Siri Mansion LIGB 436 Dr.A S Rao Nagar,Hyderabad
A65: 1 | B65: Name of the Member | H65: ='4-22MASTER'!#REF! -> #REF!
A66: 2 | B66: Fathers' Name | F66: Husband's Name | H66: ='4-22MASTER'!#REF! -> #REF!
B67: (Please tick whichever is applicable)
A68: 3 | B68: Date of Birth (DD/MM/YYYY) | H68: ='4-22MASTER'!#REF! -> #REF!
A69: 4 | B69: Gender (Male/Female/Transgender) | H69: ='4-22MASTER'!#REF! -> #REF!
A70: 5 | B70: Marital Status(married / Unmarried / Widow/divorce) | H70: Unmarried
A71: 6 | B71: (a) | C71: Email Id
B72: (b) | C72: Mobile No.
A73: 7 | B73: Whether earlier a member of the Employees' Provident Fund Scheme, 1952 ? | H73: Yes | K73: No
A74: 8 | B74: Whether earlier a member of the Employees' Pension Scheme, 1995? | H74: Yes | K74: No
F75: Previous employment details [if Yes to 7 &/or 8 above]
A76: 9 | B76: a) | C76: Universal Account Number
B77: b) | C77: Previous PF Account Number
B78: C) | C78: Date of exit from previous employment (DD/MM/YYYY)
B79: d) | C79: Scheme Certificate No. (if issued)
B80: e) | C80: Pension Payment Order (PPO) No. (if issued)
A81: 10 | B81: a) | C81: International Worker | H81: Yes | K81: No
B82: b) | C82: If yes, state country of origin(India/Name of other country)
B83: C) | C83: Passport No.
B84: d) | C84: Validity of passport [(DD/MM/YYYY) to (DD/MM/YYYY)]
E85: KYC Details (attach self attested copies of following KYCs)
A86: 11 | B86: a) | C86: Bank Account No. & IFS Code
B87: b) | C87: AADHAR No.
B88: c) | C88: Permanent Account No. (PAN), if available
F89: UNDERTAKING
B90: 1) | C90: Certified that the particulars are true to the best of my knowledge.
B91: 2) | C91: I authorize EPFO to use my Aadhar for verification/authentication/eKYC purpose for service delivery.
B92: 3) | C92: Kindly transfer the funds and service details, if applicable from the previous PF account as declared above to the present P.F. Account (The Transfer would be possible only if the identified KYC details approved by previous employer has been verified by present employer
B93: 4) | C93: In case of changes in above details, the same will be intimated to employer at the earliest.
C94: Date : | D94: ='4-22MASTER'!#REF! -> #REF!
C95: Place: | D95: Hyderabad | J95: Signature of Member
F97: DECLARATION BY PRESENT EMPLOYER
A98: A) | B98: The member Mr./Ms./Mrs. | E98: ='4-22MASTER'!#REF! -> #REF! | H98: has joined on | J98: ='4-22MASTER'!#REF! -> #REF! | K98: and has been allotted PF Number
B99: ='4-22MASTER'!#REF! -> #REF!
A100: B) | B100: In case the person was earlier not a member of EPF Scheme, 1952 and EPS, 1995:
B101: (Post allotment of UAN) The UAN allotted for the member is
B102: Please Tick the Appropriate Option:
B103: The KYC details of the above member in the UAN database
B104: Have not been uploaded
B105: Have been uploaded but not approved
B106: Have been uploaded and approved with DSC
A107: C) | B107: In case the person was earlier a member of EPF Scheme, 1952 and EPS, 1995:
...

Sheet Form-F
A1: F O R M – F
A2: [See sub-Rule (1) of Rule 6] The Payment of Gratuity Rules, 1973:
A3: NOMINATION
A4: To
A5: ='4-22MASTER'!G5 -> Burgeon IT Services Pvt.Ltd.
A6: ='4-22MASTER'!G6 -> Siri Mansion LIGB 436 Dr.A S Rao Nagar,Hyderabad
A8: 1. I, Shri / Shrimati / Kumari | C8: ='4-22MASTER'!#REF! -> #REF!
A9: whose particulars are given in the statement below, hereby nominate the person(s) mentioned below to receive the gratuity payable after my death as also the gratuity standing to my credit in the event of my death before that amount has become payable, or having become payable has not been paid and direct that the said amount of gratuity shall be paid in proportion indicated against the name(s) of the nominee(s).
A11: 2. I hereby certify that the person(s) mentioned is a /are member(s) of my family within the meaning of clause (h) of Section 2 of the Payment of Gratuity Act, 1972.
A13: 3. I hereby declare that I have no family within the meaning of clause (h) of Section 2 of the said Act.
A15: 4. (a) My father/mother/parents is/are not dependent on me
A16: (b) My husband’s father/mother/parents is/are not dependent on my husband.
A18: 5. I have excluded my husband from my family by a notice dated the ……………. to the Controlling Authority in terms of the proviso to clause (h) of Section 2 of the said Act.
A20: 6. Nomination made herein invalidates my previous nomination.
A22: NOMINEE(S)
A23: Name in full with full address of nominee(s): | B23: Relationship with the empliyee | C23: Age of nominee: | D23: Proportion by which the gratuity will be shared:
A24: 1 | B24: 2 | C24: 3 | D24: 4
A25: ='4-22MASTER'!#REF! -> #REF! | B25: Father | C25: 54 Years | D25: 1
A29: STATEMENT
A31: 1. Name of employee in full: | C31: ='4-22MASTER'!#REF! -> #REF!
A32: 2. Sex: | C32: ='4-22MASTER'!#REF! -> #REF!
A33: 3. Religion: | C33: Muslim
A34: 4. Whether unmarried/married/widow/widower: | C34: Un married
A35: 5. Department/Branch/Section where employed: | C35: ='4-22MASTER'!#REF! -> #REF!
A36: 6. Post held with Ticket No. or Serial No. if any: | C36: ='4-22MASTER'!#REF! -> #REF!
A37: 7. Date of appointment: | C37: ='4-22MASTER'!#REF! -> #REF!
A38: 8. Permanent address:
C39: ='4-22MASTER'!#REF! -> #REF!
C40: ='4-22MASTER'!#REF! -> #REF!
C41: ='4-22MASTER'!#REF! -> #REF!
A42: Place: | B42: Hyderabad
A43: Date: | B43: ='4-22MASTER'!#REF! -> #REF! | C43: Signature/Thumb impression of the employee
A45: Declaration by witnesses:
A46: Nomination signed/thumb impressed before me:
A48: Name in full and full address of witnesses: | C48: Signature of witnesses:
A49: 1 | C49: 1
A50: 2 | C50: 2
C51: Certificate by the Employer
A52: Certified that the particulars of the above nomination have been verified and recorded in t his establishment
A53: Employer's reference No, if any
C55: Signature of the employer/Officer authorized
C56: Designation
C57: Name address of the establishment or rubber stamp there of
C58: ='4-22MASTER'!G5 -> Burgeon IT Services Pvt.Ltd.
A59: Place: | B59: =B42 -> Hyderabad | C59: ='4-22MASTER'!G6 -> Siri Mansion LIGB 436 Dr.A S Rao Nagar,Hyderabad
A60: Date: | B60: =B43 -> #REF!
B61: Acknowledgment by the Employee
A62: Received the duplicate of the nomination in Form 'F'Filled by me and duly certified by the employer
A63: Date: | B63: =B60 -> #REF!
A64: Note: Strike out words/paragraph not applicable | D64: Signature of the Employee
A69: F O R M – F
A70: [See sub-Rule (1) of Rule 6] The Payment of Gratuity Rules, 1973:
A71: NOMINATION
A72: To
A73: ='4-22MASTER'!G5 -> Burgeon IT Services Pvt.Ltd.
A74: ='4-22MASTER'!G6 -> Siri Mansion LIGB 436 Dr.A S Rao Nagar,Hyderabad
A76: 1. I, Shri / Shrimati / Kumari | C76: ='4-22MASTER'!#REF! -> #REF!
A77: whose particulars are given in the statement below, hereby nominate the person(s) mentioned below to receive the gratuity payable after my death as also the gratuity standing to my credit in the event of my death before that amount has become payable, or having become payable has not been paid and direct that the said amount of gratuity shall be paid in proportion indicated against the name(s) of the nominee(s).
A79: 2. I hereby certify that the person(s) mentioned is a /are member(s) of my family within the meaning of clause (h) of Section 2 of the Payment of Gratuity Act, 1972.
A81: 3. I hereby declare that I have no family within the meaning of clause (h) of Section 2 of the said Act.
A83: 4. (a) My father/mother/parents is/are not dependent on me
A84: (b) My husband’s father/mother/parents is/are not dependent on my husband.
A86: 5. I have excluded my husband from my family by a notice dated the ……………. to the Controlling Authority in terms of the proviso to clause (h) of Section 2 of the said Act.
A88: 6. Nomination made herein invalidates my previous nomination.
A90: NOMINEE(S)
A91: Name in full with full address of nominee(s): | B91: Relationship with the empliyee | C91: Age of nominee: | D91: Proportion by which the gratuity will be shared:
A92: 1 | B92: 2 | C92: 3 | D92: 4
A93: ='4-22MASTER'!#REF! -> #REF! | B93: Father | C93: 54 Years | D93: 1
A97: STATEMENT
A99: 1. Name of employee in full: | C99: ='4-22MASTER'!#REF! -> #REF!
A100: 2. Sex: | C100: ='4-22MASTER'!#REF! -> #REF!
A101: 3. Religion: | C101: Hindu
A102: 4. Whether unmarried/married/widow/widower: | C102: Un married
A103: 5. Department/Branch/Section where employed: | C103: ='4-22MASTER'!#REF! -> #REF!
A104: 6. Post held with Ticket No. or Serial No. if any: | C104: ='4-22MASTER'!#REF! -> #REF!
A105: 7. Date of appointment: | C105: ='4-22MASTER'!#REF! -> #REF!
A106: 8. Permanent address:
C107: ='4-22MASTER'!#REF! -> #REF!
C108: ='4-22MASTER'!#REF! -> #REF!
C109: ='4-22MASTER'!#REF! -> #REF!
A110: Place: | B110: Hyderabad
A111: Date: | B111: ='4-22MASTER'!#REF! -> #REF! | C111: Signature/Thumb impression of the employee
A113: Declaration by witnesses:
A114: Nomination signed/thumb impressed before me:
A116: Name in full and full address of witnesses: | C116: Signature of witnesses:
A117: 1 | C117: 1
A118: 2 | C118: 2
C119: Certificate by the Employer
A120: Certified that the particulars of the above nomination have been verified and recorded in t his establishment
A121: Employer's reference No, if any
C123: Signature of the employer/Officer authorized
C124: Designation
C125: Name address of the establishment or rubber stamp there of
C126: ='4-22MASTER'!G5 -> Burgeon IT Services Pvt.Ltd.
A127: Place: | B127: =B110 -> Hyderabad | C127: ='4-22MASTER'!G6 -> Siri Mansion LIGB 436 Dr.A S Rao Nagar,Hyderabad
A128: Date: | B128: =B111 -> #REF!
B129: Acknowledgment by the Employee
A130: Received the duplicate of the nomination in Form 'F'Filled by me and duly certified by the employer
A131: Date: | B131: =B128 -> #REF!
A132: Note: Strike out words/paragraph not applicable | D132: Signature of the Employee
...

Sheet Serive Certificate
B4: FORM XV
B5: [Vide rule 77 of Contract Labour (Regul. & Abolition) Central & A.P. Rules, 1971]
B7: SERVICE CERTIFICATE
B9: Name and address of Contractor : | G9: Name and address of establishment in / under which contract is caried on :
B11: ='4-22MASTER'!G5 -> Burgeon IT Services Pvt.Ltd. | G11: ='4-22MASTER'!AQ5 -> Burgeon IT Services Pvt.Ltd.
B13: ='4-22MASTER'!G6 -> Siri Mansion LIGB 436 Dr.A S Rao Nagar,Hyderabad | G13: ='4-22MASTER'!AQ6 -> Siri Mansion LIGB 436 Dr.A S Rao Nagar,Hyderabad
B17: Nature and Location of work: | G17: Name and address of Principal Employer :
G19: ='4-22MASTER'!AQ10 -> INFOSYS LTD.IL Ascendas SEZ Unit,Building Juniper
B21: ='4-22MASTER'!G8 -> IT SUPPORTIVE SERVICES & PUNE ASC SEZ | G21: ='4-22MASTER'!AQ11 -> International Tech Park,Rajiv Gandhi Infotech Park,Hinjawadi,Pune,Maharashtra
B26: Name and address of the workman :
B31: Age or date of Birth :
B33: Identification Marks :
B35: Father's / Husband's Name :
B38: Sl.No. | C38: Total period for which employed | E38: Nature of work done | G38: Rate of wage ( with particulars of units in case of piece work) | J38: Remarks
C40: From | D40: To
B41: 1 | C41: 2 | D41: 3 | E41: 4 | G41: 5 | J41: 6
H56: Signature of the Employer with Seal
