Workbook

Sheet PUNE SEZ UNIt-1-APRIL22WM Reg
A1: FORM IX- REGISTER OF PERSONS EMPLOYED
A3: (Vide Rule 78(1) (a) (i) of Contract Labour (Regulation and Abolition) Central /Maharastra.Rules 1974
A4: Name and address of Contractor:burgeon IT services Pvt.Ltd. | F4: Name and address of the establishment in / under which contract is carried on: burgeon IT services Pvt.Ltd. Siri mansion LIGH 436 DR.A S Rao nagar,Hyderabad
A5: Siri Mansion LIGB 436 Dr.A S Rao Nagar,Hyderabad
A7: Name and address of Contractor:burgeon IT services Pvt.Ltd. | F7: Name and address of principal employer:
F8: ='04-221Master'!AP10 -> INFOSYS LTD.IL Pune SEZ Unit-I,Plot No. 24/3
F9: Rajiv gandhi Info tech park,Village Mann,Pune,Maharashtra 411057
A11: S.No | B11: Name and Surname of workman | C11: Age | D11: SEX | E11: Father's/Husband's name | F11: Nature of Employement/Designation | G11: Permanent Home Address of worken | H11: Local Address | I11: Date of commencement of Employment | J11: Signature or Thumb impression of workman | K11: Date of Temination of Employment | L11: Reason for Termination | M11: Remarks
A13: 1 | B13: 2 | C13: 3 | E13: 4 | F13: 5 | G13: 6 | H13: 7 | I13: 8 | J13: 9 | K13: 10 | M13: 11
A14: 1 | B14: Asish kumar satapathy | C14: 33571 | D14: Male | E14: Kamal Kishore Gupta | F14: Technical Consultant | G14: 289/A Mangalwar Peth behind kamla nehru hospital Pune 11 | H14: E-4, MIG-II , BDA COLONY, C.S PUR, Bhubaneshwar 751016 | I14: 43283 | K14: 28.06.2019 | L14: Resigned
A15: 2 | B15: Shreyash Gupta | C15: 33571 | D15: Male | E15: Kamal Kishore Gupta | F15: Software Developer | G15: 289/A Mangalwar Peth behind kamla nehru hospital Pune 11 | H15: 289/A Mangalwar Peth behind kamla nehru hospital Pune 11 | I15: 43515 | K15: 26.12.2019 | L15: Resigned
A16: 3 | B16: Mahendra shiva das more | C16: 29587 | D16: Male | E16: MINAL MAHENDRA MORE | F16: Senior Software Engineer | G16: FLOT NO.B-905,OXY VOLI2,GATE NO.744 BAKORI ROAD,BIHIND JUNG COLLGE,GADHE VASTI WAGHOLI,PUNE 412207 | H16: FLOT NO.A 304,SLNO.32/3 SUMAN SILPHA,NEAR SIDHI LAWNS,NARHE GAON,PUNE,411041 | I16: 27/5/2019 | L16: Resigned
A17: 4 | B17: Amodh Kamble | C17: 34630 | D17: MALE | E17: NANDU KAMBLE | F17: Technical Consultant | G17: FL.NO-16, BLDG- 3, QUARTER GATE HOUSING SOCIETY, NANAPETH, PUNE-411002 | H17: FL.NO-16, BLDG- 3, QUARTER GATE HOUSING SOCIETY, NANAPETH, PUNE-411002 | I17: 43871 | K17: 31.may.2020 | L17: Resigned
A18: 5 | B18: Tanmay Saxena | C18: 33431 | D18: Female | E18: Alok Saxena | F18: Senior Software Developer | G18: h.no-51 shubhalay villas barkheda pathani BHEL Bhopal MP, 462023 | H18: h.no-51 shubhalay villas barkheda pathani BHEL Bhopal MP, 462023 | I18: 44021 | L18: Resigned
A19: 6 | B19: Venegella Kanaka durga | C19: 31669 | D19: Female | E19: Venkateshwar Rao | F19: Senior Software Engineer | G19: Dr no-115,Sujatha nagar, vinjamur SPSR Nellore ,Andra Pradesh,pincode:560066 | H19: No.3,Malempati Homes,8th A cross, Manjunatha Layout, Munekollala, Maratahalli, Bangalore - 560037 | I19: 44021 | K19: Active | L19: Active | N19: 1
A20: 7 | B20: A Achyuthram Kumar | C20: 35595 | D20: MALE | E20: naredra Babu | F20: AS400 Consultant | G20: c/4-3, Near Nagarpamma Temple, Vadaku, Nellore, AP 524415 | H20: c/4-3, Near Nagarpamma Temple, Vadaku, Nellore, AP 524415 | I20: 44021 | L20: Resigned
A21: 8 | B21: Prakash Tammishetty | C21: 33034 | D21: MALE | E21: Thammisetti Narasimhulu | F21: Senior Software Engineer | G21: Vadde Agraharam vli,Rachayapet Post,Gopavaram mandal,Kadapa dist,Andhrapradesh.Pin-516233. | H21: Khavyasree Mens Pg,Cyberhills Colony,Near Magnum oppus,Gachibowli,Hyderabad,Telangana,500032 | I21: 44020 | L21: Resigned
A22: 9 | B22: TARANNUM MUDASSAR IDRIS RAUT | C22: 33301 | D22: MALE | E22: Mudassar Idris Raut | F22: Software Engineer | G22: Plot no.16,St ni45/1A/part 1,Joshi Colony,Shahunagar,Belagavi | H22: Flat no.18,wing b1,Libera Garden,NIBM,Pune | I22: 44034 | L22: Resigned
A23: 10 | B23: Moeenahmed Shakilahmed Shaikh | C23: 30310 | D23: MALE | E23: Shaik Azara Shakilahmed | F23: Splunk Developer | G23: 967 Ravivarpet, Ghulamali,Chambers laxmi Road, Pune, MH 411002 | H23: 967 Ravivarpet, Ghulamali,Chambers laxmi Road, Pune, MH 411002 | I23: 44034 | K23: Active | L23: Active | N23: 2
A24: 11 | B24: Swati Panjwani | C24: 33523 | D24: Female | E24: Niranjan Kumar Panjwani | F24: SENIOR SOFTWARE ENGINEER | G24: 168 ADM LIne , Acharya Kriplani Ward Madhav Nagar Katni 483504 | H24: R2 9 Samdariya City, ahead parth health club, Madhav Nagar , Katni MP -483501 | I24: 44048 | L24: Resigned
A25: 12 | B25: Pravin Dattatray Karde | C25: 32053 | D25: MALE | E25: Dattatray | F25: Solution Architect Cloud | G25: Saakar Almond Park, B 402, Near Kumar Meadows, off solapur Highway, Manjari BK . 412307 | H25: Saakar Almond Park, B 402, Near Kumar Meadows, off solapur Highway, Manjari BK . 412307 | I25: 44064 | L25: Resigned
A26: 13 | B26: SHARJEEL REHMANY | C26: 33552 | D26: MALE | E26: Javed Akhtar Rehmany | F26: Analyst System Administrator | G26: 9/D, 2nd floor, Madina compound,80 tenaments, B.J Road , Jacob circle,mumbai :- 400011 | H26: 9/D, 2nd floor, Madina compound,80 tenaments, B.J Road , Jacob circle,mumbai :- 400011 | I26: 44123 | L26: Resigned
A27: 14 | B27: Jagdish Salian | C27: 27051 | D27: MALE | E27: Babita Jagdish Salian | F27: Senior Project Manager | G27: 2/26, Mehta Chambers, Seth Motishah Marg, Mazgaon, Mumbai - 400010 | H27: C-404, Vardhaman Heights, Survey No.66/2, Chatrapati Chowk, Gopinath Munde Marg, Rahatani-Kalewadi Link Road, Kalewadi, Pune - 411017 | I27: 44145 | K27: Active | L27: Active
A28: 15 | B28: Shaik Naseer | C28: 31968 | D28: MALE | E28: Shaik Nanne Sab | F28: Senior Technical Consultant | G28: #12-199-a,Narayana rao Street ,Valisab Road,kadiri-515591,Anantapur dist,AP | H28: Door No: 302,CKB Layout,munnekollla,Marathahalli-560037,Bangalore,Karnataka | I28: 44249 | K28: Active | L28: Active
A29: 16 | B29: Apurva Kumari | C29: 32603 | D29: Female | E29: sunil kumar thakur | F29: Senior Support analyst | G29: VILL POST BHARWARA POLICE STATION SINGHWARA DIST DARBHNGA BIHAR 847104 | H29: VILL POST BHARWARA POLICE STATION SINGHWARA DIST DARBHNGA BIHAR 847104 | I29: 44264 | L29: Resigned
A30: 17 | B30: Mahesh babu | C30: 32150 | D30: Male | E30: Muralikrishna | F30: ITPM Servicenow | G30: 16-178,Pamarru, Krishna Dist, AP 521157 | H30: 16-178,Pamarru, Krishna Dist, AP 521157 | I30: 44292 | K30: Active | L30: Active
A31: 18 | B31: AMARDEEP BORKAR | C31: 29174 | D31: Male | E31: TUKARAM | F31: Technical Consultant | G31: SR.NO.317,PLOT NO.314,LANE NO.3,RUTUJA PARK, BEHIND BHARAT VAJAN KATA, URULI DEVACHI,PUNE - 412308 | H31: SR.NO.317,PLOT NO.314,LANE NO.3,RUTUJA PARK, BEHIND BHARAT VAJAN KATA, URULI DEVACHI,PUNE - 412308 | I31: 44312 | K31: Active | L31: Active
A32: 19 | B32: Yarramaddu Raveendra Reddy | C32: 32972 | D32: Male | E32: Ramachandra Reddy | F32: Sr Citrix Administrator | G32: 11/25,Baddipally village,Mudivedu post,Kura Balakota mandal,Chittor district,AP 517350 | H32: 11/25,Baddipally village,Mudivedu post,Kura Balakota mandal,Chittor district,AP 517350 | I32: 44335 | K32: Active | L32: Active | N32: 3
A33: 20 | B33: Chitra Kulkarni | C33: 32113 | D33: Female | E33: Nirbay Gopal | F33: Project Manager | G33: H No 479,Sy No 39,Road no.5, Mathenagar,Vadgaon sheri,Pune,Maharastra 411014 | H33: H No 479,Sy No 39,Road no.5, Mathenagar,Vadgaon sheri,Pune,Maharastra 411014 | I33: 44390 | K33: Active | L33: Active | N33: 4
A34: 21 | B34: Reddiah Gumitha | C34: OOOO | D34: Male | E34: ZZZ | F34: Sr. Software Engineer | G34: WWWW | H34: WWWW | I34: 44409 | K34: Active | L34: Active
A35: 22 | B35: Sunnapalli Anil | C35: 32813 | D35: Male | E35: Narsingam | F35: Sr. Software Engineer | G35: 16-9-239,Puppalagutta,Railway flyover bridge,Chital,Warangal,TS 506002 | H35: 16-9-239,Puppalagutta,Railway flyover bridge,Chital,Warangal,TS 506002 | I35: 44409 | K35: Active | L35: Active | N35: 5
A36: 23 | B36: Viswanath B | C36: 34917 | D36: Male | E36: Jayachandra Reddy | F36: SQL DBA Administrator | G36: H No 3-59,Shiva sandhya nagar,KSRM engineering college,CK Dinne Mandal,Kadapa,AP 516003 | H36: H No 3-59,Shiva sandhya nagar,KSRM engineering college,CK Dinne Mandal,Kadapa,AP 516003 | I36: 44420 | K36: RESIGNATION | L36: Resigned
A37: 24 | B37: Himanshu Anand | C37: 31328 | D37: Male | E37: A.K. Gupta | F37: Sr. DBA / Sr. Administrator | G37: 25-B Radha Nagar, Rohini complex, Mathura, UP 281004 | H37: J-901 City Apartments,aditya world city, Gaziabad, UP 201002 | I37: 44432 | K37: Active | L37: Active | N37: 6
A38: 25 | B38: Kanchupati Kondaiah | C38: 32669 | D38: Male | E38: U MALLESWARAMMA | F38: SQL DATABASE ADMINISTRATOR | G38: CHENNAVARAM Village, Rachayapost, gopavaram mandal, YSR Kadapa, AP 516233 | H38: CHENNAVARAM Village, Rachayapost, gopavaram mandal, YSR Kadapa, AP 516233 | I38: 44434 | K38: Active | L38: Active | N38: 7
A39: 26 | B39: Santosh Patel | C39: 32336 | D39: Male | E39: Kishorilal Patel | F39: Senior Support Engineer | G39: RNA- Plaza, Bldg R-6, Flat 714,Shree Ganesh CHS,Somani Gram, Rammandr road, Goregaon (west), Mumbai 400104. | H39: RNA- Plaza, Bldg R-6, Flat 714,Shree Ganesh CHS,Somani Gram, Rammandr road, Goregaon (west), Mumbai 400104. | I39: 44438 | K39: Active | L39: Active | N39: 8
A40: 27 | B40: Basweshwar Pawar | C40: 31899 | D40: Male | E40: Nandakumar eknath pawar | F40: Lead PMO | G40: H-302, Kohinoor Abhimaan Homes, somatane-Kasarai Road,Near Sai Temple, Mawal, PUNE 410506 | H40: H-302, Kohinoor Abhimaan Homes, somatane-Kasarai Road,Near Sai Temple, Mawal, PUNE 410506 | I40: 44446 | K40: Active | L40: Active | N40: 9
A41: 28 | B41: Swati Bhattacharya | C41: 29587 | D41: Female | E41: Madhav singnapurkar | F41: Service Manager -Cyber security | G41: B-605, gagan adira, Siraj Bokadia Road, Wagholi, Pune 412207 | H41: B-605, gagan adira, Siraj Bokadia Road, Wagholi, Pune 412207 | I41: 44466 | K41: Active | L41: Active
A42: 29 | B42: Hemanth Mishra | C42: 17/10/1976 | D42: MALE | E42: Satish Chandra Mishra | F42: Technology Analyst | G42: 16 B,Braj Nagar,Rameshwar Ward, opp. Anima Ubeja's Banglow, KHANDWA Pin-450001, Madhra Pradesh | H42: 16 B,Braj Nagar,Rameshwar Ward, opp. Anima Ubeja's Banglow, KHANDWA Pin-450001, Madhra Pradesh | I42: 44490 | K42: Active | L42: Active | N42: 10
A43: 30 | B43: FAZALAHMED IRKAL | C43: 32932 | D43: MALE | E43: CHANDSAHEB IRKAL | F43: SENIOR HADOOP ADMIN | G43: 558, 37/133 New Paccha Peth, Ashok Chowk, Behind Taj Medical Solapur | H43: 201, Sunaina Apartment, Near Poona College Camp Pune-411001 | I43: 44494 | K43: Active | L43: Active | N43: 11
A44: 31 | B44: SUKRUTH YELLAMBOTLA | C44: 34146 | D44: MALE | E44: Yellambotla Vijay Kumar | F44: SENIOR APPLICATION CONSULTANT | G44: H No 6-311/1/B/1,Sri krishna nagar,Qutubullapur,Suchitra,Hyderabad | H44: H No 6-311/1/B/1,Sri krishna nagar,Qutubullapur,Suchitra,Hyderabad | I44: 44509 | K44: Active | L44: Active | N44: 12
A45: 32 | B45: Ajay Singh | C45: 33635 | D45: MALE | E45: Santhosh Singh | F45: Sr.Cloud Network Engineer | G45: EM-36,Indus Town,Phase II,Ratanpur,Missrod,Bhopal,Madhya pradesh 462047 | H45: EM-36,Indus Town,Phase II,Ratanpur,Missrod,Bhopal,Madhya pradesh 462047 | I45: 44538 | J45: OOO | K45: Active | L45: Active | M45: OOO | N45: 13
A46: 33 | B46: Rajesh Dhumal | C46: 32947 | D46: MALE | E46: Ramakrishna | F46: Senior network security analyst. | G46: Deshpande Galli, Kholeshwar Collage Samor, Ambejogai, Bid, Maharashtra 431517 | H46: Deshpande Galli, Kholeshwar Collage Samor, Ambejogai, Bid, Maharashtra 431517 | I46: 44579 | K46: Active | L46: Active | N46: 14
A47: 34 | B47: Ajay Pal Singh | C47: 31491 | D47: MALE | E47: kunwar rohitash singh | F47: Network security consultant | G47: H No 32,Jalalpur-Raghunadhpur,Murad nagar,Gaziyabad,UP 201206 | H47: H No 66,New Gandhi layout,Jaffar nagar,Nagpur,Maharastra 440013 | I47: 44601 | K47: Active | L47: Active | N47: 15
A48: 35 | B48: PAVANKUMAR | C48: 35211 | D48: MALE | E48: P YELLAIAH | F48: SAP Basis consultant | G48: 7-8/1, palmakole(V), shamshabad(M), RR Dist,509325 | H48: 7-8/1, palmakole(V), shamshabad(M), RR Dist,509325 | I48: 44602 | K48: Active | L48: Active | N48: 16
A49: 36 | B49: Rahul Suryawanshi | C49: 35236 | D49: MALE | E49: Tarun Suryawanshi | F49: Sr.Network security Analyst | G49: H No 53,Near Durga mandir,at po sarra,gram sarra,tahsil multai dist bethul,Madhya pradesh 460661 | H49: H No 53,Near Durga mandir,at po sarra,gram sarra,tahsil multai dist bethul,Madhya pradesh 460661 | I49: 44624 | K49: Active | L49: Active | N49: 17
A50: 37 | B50: Shantanu Patankar | C50: 32959 | D50: MALE | E50: shivajirao balasaheb | F50: Network security consultant | G50: Patankar house,kuntharwada,at post patan,taluq patan,dist satare,maharastra 415206 | H50: 204,Gaurav roy appts,tirangachowk,bharati vidyapitt,katray,pune,Maharastra 411046 | I50: 44629 | K50: Active | L50: Active | N50: 18
A51: 38 | B51: Varalakshmi Vijay | C51: 29711 | D51: Female | E51: Vijay srinivasan | F51: Network security consultant | G51: 902,Link view appts,sethia complex-2, opp MG road,Motilal nagar,Road no.3,Goregaon west,Mumbai,Maharastra 400104 | H51: 902,Link view appts,sethia complex-2, opp MG road,Motilal nagar,Road no.3,Goregaon west,Mumbai,Maharastra 400104 | I51: 44641 | K51: Active | L51: Active | N51: 19
A52: 39 | B52: OMPRAKASH PURI | C52: 31427 | D52: Male | E52: Shankarnath Singh | F52: CONSULTANT | G52: LIG-162,2nd floor,7th phase,KPHB,Near basket ball ground,Hyderabad,TS 500085 | H52: LIG-162,2nd floor,7th phase,KPHB,Near basket ball ground,Hyderabad,TS 500085 | I52: 44652 | K52: Active | L52: Active | N52: 20
A53: 40 | B53: Dipti Ranjan Dikhit | C53: 31991 | D53: Female | E53: Purna chandra | F53: Network Security Engineer | G53: At-Sanakanjiya nuva sahi,IV Irrigation Market colony,Gate No.2,PO Satyardhi,near sakhi gopi bus stand,Puri,Odissa 752014 | H53: At-Sanakanjiya nuva sahi,IV Irrigation Market colony,Gate No.2,PO Satyardhi,near sakhi gopi bus stand,Puri,Odissa 752014 | I53: 44655 | K53: Active | L53: Active | N53: 21
J61: Signature of the Contractor with Seal

Sheet 04-221Master
A3: FORM - XIII REGISTER OF WORKMEN EMPLOYED BY CONTRACTOR
B4: (Vide Rule 75 of Contract Labour (Regulation and Abolition) Central/Karnataka Rules 1974)
A5: Name and address of Contractor: | F5: Burgeon IT Services Pvt.Ltd. | AB5: Name and address of Establishemnt in/ under which contract is carried on: | AP5: =F5 -> Burgeon IT Services Pvt.Ltd.
F6: Siri Mansion LIGB 436 Dr.A S Rao Nagar,Hyderabad | AP6: =F6 -> Siri Mansion LIGB 436 Dr.A S Rao Nagar,Hyderabad
AP7: =F7 -> 0
A8: Nature and location of work: | F8: IT SUPPORTIVE SERVICES& Pune SEZ Unit-1
A10: Wage period: Monthly | D10: 44652 | AK10: Name and address of Principal Employer: | AP10: INFOSYS LTD.IL Pune SEZ Unit-I,Plot No. 24/3
AP11: Rajiv gandhi Info tech park,Village Mann,Pune,Maharashtra 411057
B13: 1 | C13: 2 | D13: 3 | E13: 4 | F13: 5 | G13: 6 | H13: 7 | I13: 8 | J13: 9 | K13: 10 | L13: 11 | M13: 12 | N13: 13 | O13: 14 | P13: 15 | Q13: 16 | R13: 17 | S13: 18 | T13: 19 | U13: 20 | V13: 21 | W13: 22 | X13: 23 | Y13: 24 | Z13: 25 | AA13: 26 | AB13: 27 | AC13: 28 | AD13: 29 | AE13: 30 | AF13: 31 | AG13: 32 | AH13: 33 | AI13: 34 | AJ13: 35 | AK13: 36 | AL13: 37 | AM13: 38 | AN13: 39 | AO13: 40 | AP13: 41 | AQ13: 42 | AR13: 43 | AS13: 44 | AT13: 45
B14: Name of Workman | C14: Age | D14: Sex | E14: Father's /Husband Name | F14: Designation / Nature of Work Done | G14: Permanent Address | J14: Local Address | N14: Date of Commencement of Employment | O14: Signature or thumb impression of Workman | P14: Date of termination of Employment | Q14: Reasons for termination | R14: Remarks | S14: EPF Number | T14: ESI Number | U14: Name of Workman | V14: NO.OF DAYS | W14: No.of Days worked | X14: Unit of work done | Y14: Monthly rate of wages/ piece rate | Z14: Basic wages | AA14: Dearness Allowances | AB14: Over time | AC14: Other cash payments (Nature of payments to be indicated) | AD14: HRA | AE14: CONVEYANCE | AF14: MEDICAL ALLOWANCES | AG14: SPECIAL ALLOWNANCES | AH14: Total | AI14: BONUS | AJ14: GRATUITY | AK14: LTA/L.E | AL14: ARREAR AMOUNT | AM14: TOTAL AMOUNT | AN14: Deductions, if any, (Indicate nature) | AT14: Net Amount paid | AU14: Time and Date of Payment | AV14: Place of Payment | AW14: Signature/Thumb Impression of workman | AX14: Initial of Contractor or his representative | AY14: Serial No. in the Register of Workmen
AN15: ESI | AO15: PF | AP15: PT | AQ15: TDS | AR15: MED | AS15: Total Deductions
A16: BITS-461 | B16: Venegella Kanaka durga | C16: 31669 | D16: Female | E16: Venkateshwar Rao | F16: Senior Software Engineer | G16: Dr no-115,Sujatha nagar, vinjamur SPSR Nellore ,Andra Pradesh,pincode:560066 | J16: No.3,Malempati Homes,8th A cross, Manjunatha Layout, Munekollala, Maratahalli, Bangalore - 560037 | N16: 44021 | S16: 100748390738 | T16: N/A | U16: =B16 -> Venegella Kanaka durga | V16: 30 | W16: =VLOOKUP(A16,'[1]Pay sheet-APRIL- 2022'!$C$5:$AF$134,10,0) -> 30 | X16: N/A | Y16: 75643 | Z16: =VLOOKUP(A16,'[1]Pay sheet-APRIL- 2022'!$C$5:$AF$134,11,0) -> 45385.8 | AA16: 0 | AB16: 0 | AC16: =AD16+AE16+AF16+AG16 -> 30370.2 | AD16: =VLOOKUP(A16,'[1]Pay sheet-APRIL- 2022'!$C$5:$AF$134,12,0) -> 18154.32 | AE16: =VLOOKUP(A16,'[1]Pay sheet-APRIL- 2022'!$C$5:$AF$134,13,0) -> 2083 | AF16: =VLOOKUP(A16,'[1]Pay sheet-APRIL- 2022'!$C$5:$AF$134,14,0) -> 2083 | AG16: =VLOOKUP(A16,'[1]Pay sheet-APRIL- 2022'!$C$5:$AF$134,15,0) -> 8049.88 | AH16: =Z16+AC16 -> 75756 | AI16: =VLOOKUP(A16,'[1]Pay sheet-APRIL- 2022'!$C$5:$AF$134,18,0) -> 1554.609 | AJ16: =VLOOKUP(A16,'[1]Pay sheet-APRIL- 2022'!$C$5:$AF$134,19,0) -> 2183.057 | AK16: =VLOOKUP(A16,'[1]Pay sheet-APRIL- 2022'!$C$5:$AF$134,20,0) -> 3782.15 | AL16: =VLOOKUP(A16,'[1]Pay sheet-APRIL- 2022'!$C$5:$AF$134,22,0) -> 0 | AM16: =Z16+AD16+AE16+AF16+AG16+AI16+AJ16+AK16 -> 83275.816 | AO16: =VLOOKUP(A16,'[1]Pay sheet-APRIL- 2022'!$C$5:$AF$134,26,0) -> 1800 | AP16: =VLOOKUP(A16,'[1]Pay sheet-APRIL- 2022'!$C$5:$AF$134,25,0) -> 200 | AQ16: =VLOOKUP(A16,'[1]Pay sheet-APRIL- 2022'!$C$5:$AF$134,24,0) -> 0 | AR16: =VLOOKUP(A16,'[1]Pay sheet-APRIL- 2022'!$C$5:$AF$134,27,0) -> 391.78785 | AS16: =SUM(AO16:AR16) -> 2391.7878 | AT16: =AM16-AS16 -> 80884.028 | AU16: 05.05.2022 | AV16: KVBL | AW16: A/C'1498155000027380 | AY16: 6 | AZ16: 1
A17: BITS-469 | B17: Moeenahmed Shakilahmed Shaikh | C17: 30310 | D17: MALE | E17: Shaik Azara Shakilahmed | F17: Splunk Developer | G17: 967 Ravivarpet, Ghulamali,Chambers laxmi Road, Pune, MH 411002 | J17: 967 Ravivarpet, Ghulamali,Chambers laxmi Road, Pune, MH 411002 | N17: 44041 | S17: 101607851856 | T17: N/A | U17: =B17 -> Moeenahmed Shakilahmed Shaikh | V17: 30 | W17: =VLOOKUP(A17,'[1]Pay sheet-APRIL- 2022'!$C$5:$AF$134,10,0) -> 30 | X17: N/A | Y17: 149795 | Z17: =VLOOKUP(A17,'[1]Pay sheet-APRIL- 2022'!$C$5:$AF$134,11,0) -> 89877 | AA17: 0 | AB17: 0 | AC17: =AD17+AE17+AF17+AG17 -> 60031 | AD17: =VLOOKUP(A17,'[1]Pay sheet-APRIL- 2022'!$C$5:$AF$134,12,0) -> 35950.8 | AE17: =VLOOKUP(A17,'[1]Pay sheet-APRIL- 2022'!$C$5:$AF$134,13,0) -> 2083 | AF17: =VLOOKUP(A17,'[1]Pay sheet-APRIL- 2022'!$C$5:$AF$134,14,0) -> 2083 | AG17: =VLOOKUP(A17,'[1]Pay sheet-APRIL- 2022'!$C$5:$AF$134,15,0) -> 19914.2 | AH17: =Z17+AC17 -> 149908 | AI17: =VLOOKUP(A17,'[1]Pay sheet-APRIL- 2022'!$C$5:$AF$134,18,0) -> 1554.609 | AJ17: =VLOOKUP(A17,'[1]Pay sheet-APRIL- 2022'!$C$5:$AF$134,19,0) -> 4323.0837 | AK17: =VLOOKUP(A17,'[1]Pay sheet-APRIL- 2022'!$C$5:$AF$134,20,0) -> 7489.75 | AL17: =VLOOKUP(A17,'[1]Pay sheet-APRIL- 2022'!$C$5:$AF$134,22,0) -> 0 | AM17: =Z17+AD17+AE17+AF17+AG17+AI17+AJ17+AK17 -> 163275.44 | AO17: =VLOOKUP(A17,'[1]Pay sheet-APRIL- 2022'!$C$5:$AF$134,26,0) -> 6000 | AP17: =VLOOKUP(A17,'[1]Pay sheet-APRIL- 2022'!$C$5:$AF$134,25,0) -> 200 | AQ17: =VLOOKUP(A17,'[1]Pay sheet-APRIL- 2022'!$C$5:$AF$134,24,0) -> 0 | AR17: =VLOOKUP(A17,'[1]Pay sheet-APRIL- 2022'!$C$5:$AF$134,27,0) -> 440.76133 | AS17: =SUM(AO17:AR17) -> 6640.7613 | AT17: =AM17-AS17 -> 156634.68 | AU17: 05.05.2022 | AV17: KKBK | AW17: A/C'7311230416 | AY17: 10 | AZ17: 2
A18: BITS-572 | B18: Yarramaddu Raveendra Reddy | C18: 32972 | D18: Male | E18: Ramachandra Reddy | F18: Sr Citrix Administrator | G18: 11/25,Baddipally village,Mudivedu post,Kura Balakota mandal,Chittor district,AP 517350 | J18: 11/25,Baddipally village,Mudivedu post,Kura Balakota mandal,Chittor district,AP 517350 | N18: 44335 | S18: 101695261757 | T18: N/A | U18: Yarramaddu Raveendra Reddy | V18: 30 | W18: =VLOOKUP(A18,'[1]Pay sheet-APRIL- 2022'!$C$5:$AF$134,10,0) -> 30 | X18: N/A | Y18: 61740 | Z18: =VLOOKUP(A18,'[1]Pay sheet-APRIL- 2022'!$C$5:$AF$134,11,0) -> 37044 | AA18: 0 | AB18: 0 | AC18: =AD18+AE18+AF18+AG18 -> 24809 | AD18: =VLOOKUP(A18,'[1]Pay sheet-APRIL- 2022'!$C$5:$AF$134,12,0) -> 14817.6 | AE18: =VLOOKUP(A18,'[1]Pay sheet-APRIL- 2022'!$C$5:$AF$134,13,0) -> 2083 | AF18: =VLOOKUP(A18,'[1]Pay sheet-APRIL- 2022'!$C$5:$AF$134,14,0) -> 2083 | AG18: =VLOOKUP(A18,'[1]Pay sheet-APRIL- 2022'!$C$5:$AF$134,15,0) -> 5825.4 | AH18: =Z18+AC18 -> 61853 | AI18: =VLOOKUP(A18,'[1]Pay sheet-APRIL- 2022'!$C$5:$AF$134,18,0) -> 1554.609 | AJ18: =VLOOKUP(A18,'[1]Pay sheet-APRIL- 2022'!$C$5:$AF$134,19,0) -> 1781.8164 | AK18: =VLOOKUP(A18,'[1]Pay sheet-APRIL- 2022'!$C$5:$AF$134,20,0) -> 3087 | AL18: =VLOOKUP(A18,'[1]Pay sheet-APRIL- 2022'!$C$5:$AF$134,22,0) -> 0 | AM18: =Z18+AD18+AE18+AF18+AG18+AI18+AJ18+AK18 -> 68276.425 | AO18: =VLOOKUP(A18,'[1]Pay sheet-APRIL- 2022'!$C$5:$AF$134,26,0) -> 1800 | AP18: =VLOOKUP(A18,'[1]Pay sheet-APRIL- 2022'!$C$5:$AF$134,25,0) -> 200 | AQ18: =VLOOKUP(A18,'[1]Pay sheet-APRIL- 2022'!$C$5:$AF$134,24,0) -> 0 | AR18: =VLOOKUP(A18,'[1]Pay sheet-APRIL- 2022'!$C$5:$AF$134,27,0) -> 391.78785 | AS18: =SUM(AO18:AR18) -> 2391.7878 | AT18: =AM18-AS18 -> 65884.638 | AU18: 05.05.2022 | AV18: HDFC BANK | AW18: A/C'50100313077055 | AY18: 19 | AZ18: 3
A19: BITS-605 | B19: Chitra Kulkarni | C19: 32113 | D19: Female | E19: Nirbay Gopal | F19: Project Manager | G19: H No 479,Sy No 39,Road no.5, Mathenagar,Vadgaon sheri,Pune,Maharastra 411014 | J19: H No 479,Sy No 39,Road no.5, Mathenagar,Vadgaon sheri,Pune,Maharastra 411014 | N19: 44390 | S19: 100126170346 | T19: N/A | U19: Chitra Kulkarni | V19: 30 | W19: =VLOOKUP(A19,'[1]Pay sheet-APRIL- 2022'!$C$5:$AF$134,10,0) -> 30 | X19: N/A | Y19: 82132 | Z19: =VLOOKUP(A19,'[1]Pay sheet-APRIL- 2022'!$C$5:$AF$134,11,0) -> 49279.2 | AA19: 0 | AB19: 0 | AC19: =AD19+AE19+AF19+AG19 -> 32965.8 | AD19: =VLOOKUP(A19,'[1]Pay sheet-APRIL- 2022'!$C$5:$AF$134,12,0) -> 19711.68 | AE19: =VLOOKUP(A19,'[1]Pay sheet-APRIL- 2022'!$C$5:$AF$134,13,0) -> 2083 | AF19: =VLOOKUP(A19,'[1]Pay sheet-APRIL- 2022'!$C$5:$AF$134,14,0) -> 2083 | AG19: =VLOOKUP(A19,'[1]Pay sheet-APRIL- 2022'!$C$5:$AF$134,15,0) -> 9088.12 | AH19: =Z19+AC19 -> 82245 | AI19: =VLOOKUP(A19,'[1]Pay sheet-APRIL- 2022'!$C$5:$AF$134,18,0) -> 1554.609 | AJ19: =VLOOKUP(A19,'[1]Pay sheet-APRIL- 2022'!$C$5:$AF$134,19,0) -> 2370.3295 | AK19: =VLOOKUP(A19,'[1]Pay sheet-APRIL- 2022'!$C$5:$AF$134,20,0) -> 4106.6 | AL19: =VLOOKUP(A19,'[1]Pay sheet-APRIL- 2022'!$C$5:$AF$134,22,0) -> 0 | AM19: =Z19+AD19+AE19+AF19+AG19+AI19+AJ19+AK19 -> 90276.539 | AO19: =VLOOKUP(A19,'[1]Pay sheet-APRIL- 2022'!$C$5:$AF$134,26,0) -> 1800 | AP19: =VLOOKUP(A19,'[1]Pay sheet-APRIL- 2022'!$C$5:$AF$134,25,0) -> 200 | AQ19: =VLOOKUP(A19,'[1]Pay sheet-APRIL- 2022'!$C$5:$AF$134,24,0) -> 0 | AR19: =VLOOKUP(A19,'[1]Pay sheet-APRIL- 2022'!$C$5:$AF$134,27,0) -> 335 | AS19: =SUM(AO19:AR19) -> 2335 | AT19: =AM19-AS19 -> 87941.539 | AU19: 05.05.2022 | AV19: ICICI | AW19: A/C' 055801521228 | AY19: 20 | AZ19: 4
A20: BITS-617 | B20: Sunnapalli Anil | C20: 32813 | D20: Male | E20: Narsingam | F20: Sr. Software Engineer | G20: 16-9-239,Puppalagutta,Railway flyover bridge,Chital,Warangal,TS 506002 | J20: 16-9-239,Puppalagutta,Railway flyover bridge,Chital,Warangal,TS 506002 | N20: 44409 | S20: 100051658997 | T20: N/A | U20: Sunnapalli Anil | V20: 30 | W20: =VLOOKUP(A20,'[1]Pay sheet-APRIL- 2022'!$C$5:$AF$134,10,0) -> 30 | X20: N/A | Y20: 69580 | Z20: =VLOOKUP(A20,'[1]Pay sheet-APRIL- 2022'!$C$5:$AF$134,11,0) -> 41748 | AA20: 0 | AB20: 0 | AC20: =AD20+AE20+AF20+AG20 -> 27945 | AD20: =VLOOKUP(A20,'[1]Pay sheet-APRIL- 2022'!$C$5:$AF$134,12,0) -> 16699.2 | AE20: =VLOOKUP(A20,'[1]Pay sheet-APRIL- 2022'!$C$5:$AF$134,13,0) -> 2083 | AF20: =VLOOKUP(A20,'[1]Pay sheet-APRIL- 2022'!$C$5:$AF$134,14,0) -> 2083 | AG20: =VLOOKUP(A20,'[1]Pay sheet-APRIL- 2022'!$C$5:$AF$134,15,0) -> 7079.8 | AH20: =Z20+AC20 -> 69693 | AI20: =VLOOKUP(A20,'[1]Pay sheet-APRIL- 2022'!$C$5:$AF$134,18,0) -> 1554.609 | AJ20: =VLOOKUP(A20,'[1]Pay sheet-APRIL- 2022'!$C$5:$AF$134,19,0) -> 2008.0788 | AK20: =VLOOKUP(A20,'[1]Pay sheet-APRIL- 2022'!$C$5:$AF$134,20,0) -> 3479 | AL20: =VLOOKUP(A20,'[1]Pay sheet-APRIL- 2022'!$C$5:$AF$134,22,0) -> 0 | AM20: =Z20+AD20+AE20+AF20+AG20+AI20+AJ20+AK20 -> 76734.688 | AO20: =VLOOKUP(A20,'[1]Pay sheet-APRIL- 2022'!$C$5:$AF$134,26,0) -> 1800 | AP20: =VLOOKUP(A20,'[1]Pay sheet-APRIL- 2022'!$C$5:$AF$134,25,0) -> 200 | AQ20: =VLOOKUP(A20,'[1]Pay sheet-APRIL- 2022'!$C$5:$AF$134,24,0) -> 0 | AR20: =VLOOKUP(A20,'[1]Pay sheet-APRIL- 2022'!$C$5:$AF$134,27,0) -> 335 | AS20: =SUM(AO20:AR20) -> 2335 | AT20: =AM20-AS20 -> 74399.688 | AU20: 05.05.2022 | AV20: STATE BANK OF INDIA | AW20: 20222665512 | AY20: 22 | AZ20: 5
A21: BITS-632 | B21: Himanshu Anand | C21: 31328 | D21: Male | E21: A.K. Gupta | F21: Sr. DBA / Sr. Administrator | G21: 25-B Radha Nagar, Rohini complex, Mathura, UP 281004 | J21: J-901 City Apartments,aditya world city, Gaziabad, UP 201002 | N21: 44432 | S21: 100582540876 | T21: N/A | U21: Himanshu Anand | V21: 30 | W21: =VLOOKUP(A21,'[1]Pay sheet-APRIL- 2022'!$C$5:$AF$134,10,0) -> 30 | X21: N/A | Y21: 98501 | Z21: =VLOOKUP(A21,'[1]Pay sheet-APRIL- 2022'!$C$5:$AF$134,11,0) -> 59100.6 | AA21: 0 | AB21: 0 | AC21: =AD21+AE21+AF21+AG21 -> 39513.4 | AD21: =VLOOKUP(A21,'[1]Pay sheet-APRIL- 2022'!$C$5:$AF$134,12,0) -> 23640.24 | AE21: =VLOOKUP(A21,'[1]Pay sheet-APRIL- 2022'!$C$5:$AF$134,13,0) -> 2083 | AF21: =VLOOKUP(A21,'[1]Pay sheet-APRIL- 2022'!$C$5:$AF$134,14,0) -> 2083 | AG21: =VLOOKUP(A21,'[1]Pay sheet-APRIL- 2022'!$C$5:$AF$134,15,0) -> 11707.16 | AH21: =Z21+AC21 -> 98614 | AI21: =VLOOKUP(A21,'[1]Pay sheet-APRIL- 2022'!$C$5:$AF$134,18,0) -> 1554.609 | AJ21: =VLOOKUP(A21,'[1]Pay sheet-APRIL- 2022'!$C$5:$AF$134,19,0) -> 2842.7389 | AK21: =VLOOKUP(A21,'[1]Pay sheet-APRIL- 2022'!$C$5:$AF$134,20,0) -> 4925.05 | AL21: =VLOOKUP(A21,'[1]Pay sheet-APRIL- 2022'!$C$5:$AF$134,22,0) -> 0 | AM21: =Z21+AD21+AE21+AF21+AG21+AI21+AJ21+AK21 -> 107936.4 | AO21: =VLOOKUP(A21,'[1]Pay sheet-APRIL- 2022'!$C$5:$AF$134,26,0) -> 1800 | AP21: =VLOOKUP(A21,'[1]Pay sheet-APRIL- 2022'!$C$5:$AF$134,25,0) -> 200 | AQ21: =VLOOKUP(A21,'[1]Pay sheet-APRIL- 2022'!$C$5:$AF$134,24,0) -> 0 | AR21: =VLOOKUP(A21,'[1]Pay sheet-APRIL- 2022'!$C$5:$AF$134,27,0) -> 336 | AS21: =SUM(AO21:AR21) -> 2336 | AT21: =AM21-AS21 -> 105600.4 | AU21: 05.05.2022 | AV21: HDFC BANK | AW21: A/C 07281140023731 | AY21: 24 | AZ21: 6
A22: BITS-633 | B22: Kanchupati Kondaiah | C22: 32669 | D22: Male | E22: U MALLESWARAMMA | F22: SQL DATABASE ADMINISTRATOR | G22: CHENNAVARAM Village, Rachayapost, gopavaram mandal, YSR Kadapa, AP 516233 | J22: CHENNAVARAM Village, Rachayapost, gopavaram mandal, YSR Kadapa, AP 516233 | N22: 44434 | S22: 101439478209 | T22: N/A | U22: Kanchupati Kondaiah | V22: 30 | W22: =VLOOKUP(A22,'[1]Pay sheet-APRIL- 2022'!$C$5:$AF$134,10,0) -> 30 | X22: N/A | Y22: 46909 | Z22: =VLOOKUP(A22,'[1]Pay sheet-APRIL- 2022'!$C$5:$AF$134,11,0) -> 28145.4 | AA22: 0 | AB22: 0 | AC22: =AD22+AE22+AF22+AG22 -> 18876.6 | AD22: =VLOOKUP(A22,'[1]Pay sheet-APRIL- 2022'!$C$5:$AF$134,12,0) -> 11258.16 | AE22: =VLOOKUP(A22,'[1]Pay sheet-APRIL- 2022'!$C$5:$AF$134,13,0) -> 2083 | AF22: =VLOOKUP(A22,'[1]Pay sheet-APRIL- 2022'!$C$5:$AF$134,14,0) -> 2083 | AG22: =VLOOKUP(A22,'[1]Pay sheet-APRIL- 2022'!$C$5:$AF$134,15,0) -> 3452.44 | AH22: =Z22+AC22 -> 47022 | AI22: =VLOOKUP(A22,'[1]Pay sheet-APRIL- 2022'!$C$5:$AF$134,18,0) -> 1554.609 | AJ22: =VLOOKUP(A22,'[1]Pay sheet-APRIL- 2022'!$C$5:$AF$134,19,0) -> 1353.7937 | AK22: =VLOOKUP(A22,'[1]Pay sheet-APRIL- 2022'!$C$5:$AF$134,20,0) -> 2345.45 | AL22: =VLOOKUP(A22,'[1]Pay sheet-APRIL- 2022'!$C$5:$AF$134,22,0) -> 0 | AM22: =Z22+AD22+AE22+AF22+AG22+AI22+AJ22+AK22 -> 52275.853 | AO22: =VLOOKUP(A22,'[1]Pay sheet-APRIL- 2022'!$C$5:$AF$134,26,0) -> 1800 | AP22: =VLOOKUP(A22,'[1]Pay sheet-APRIL- 2022'!$C$5:$AF$134,25,0) -> 200 | AQ22: =VLOOKUP(A22,'[1]Pay sheet-APRIL- 2022'!$C$5:$AF$134,24,0) -> 0 | AR22: =VLOOKUP(A22,'[1]Pay sheet-APRIL- 2022'!$C$5:$AF$134,27,0) -> 336 | AS22: =SUM(AO22:AR22) -> 2336 | AT22: =AM22-AS22 -> 49939.853 | AU22: 05.05.2022 | AV22: UCO | AW22: A/c no 16280110106877 | AY22: 25 | AZ22: 7
A23: BITS-634 | B23: Santosh Patel | C23: 32336 | D23: Male | E23: Kishorilal Patel | F23: Senior Support Engineer | G23: RNA- Plaza, Bldg R-6, Flat 714,Shree Ganesh CHS,Somani Gram, Rammandr road, Goregaon (west), Mumbai 400104. | J23: RNA- Plaza, Bldg R-6, Flat 714,Shree Ganesh CHS,Somani Gram, Rammandr road, Goregaon (west), Mumbai 400104. | N23: 44438 | S23: 100893476080 | T23: N/A | U23: Santosh Patel | V23: 30 | W23: =VLOOKUP(A23,'[1]Pay sheet-APRIL- 2022'!$C$5:$AF$134,10,0) -> 30 | X23: N/A | Y23: 131257 | Z23: =VLOOKUP(A23,'[1]Pay sheet-APRIL- 2022'!$C$5:$AF$134,11,0) -> 78754.2 | AA23: 0 | AB23: 0 | AC23: =AD23+AE23+AF23+AG23 -> 52615.8 | AD23: =VLOOKUP(A23,'[1]Pay sheet-APRIL- 2022'!$C$5:$AF$134,12,0) -> 31501.68 | AE23: =VLOOKUP(A23,'[1]Pay sheet-APRIL- 2022'!$C$5:$AF$134,13,0) -> 2083 | AF23: =VLOOKUP(A23,'[1]Pay sheet-APRIL- 2022'!$C$5:$AF$134,14,0) -> 2083 | AG23: =VLOOKUP(A23,'[1]Pay sheet-APRIL- 2022'!$C$5:$AF$134,15,0) -> 16948.12 | AH23: =Z23+AC23 -> 131370 | AI23: =VLOOKUP(A23,'[1]Pay sheet-APRIL- 2022'!$C$5:$AF$134,18,0) -> 1554.609 | AJ23: =VLOOKUP(A23,'[1]Pay sheet-APRIL- 2022'!$C$5:$AF$134,19,0) -> 3788.077 | AK23: =VLOOKUP(A23,'[1]Pay sheet-APRIL- 2022'!$C$5:$AF$134,20,0) -> 6562.85 | AL23: =VLOOKUP(A23,'[1]Pay sheet-APRIL- 2022'!$C$5:$AF$134,22,0) -> 0 | AM23: =Z23+AD23+AE23+AF23+AG23+AI23+AJ23+AK23 -> 143275.54 | AO23: =VLOOKUP(A23,'[1]Pay sheet-APRIL- 2022'!$C$5:$AF$134,26,0) -> 1800 | AP23: =VLOOKUP(A23,'[1]Pay sheet-APRIL- 2022'!$C$5:$AF$134,25,0) -> 200 | AQ23: =VLOOKUP(A23,'[1]Pay sheet-APRIL- 2022'!$C$5:$AF$134,24,0) -> 0 | AR23: =VLOOKUP(A23,'[1]Pay sheet-APRIL- 2022'!$C$5:$AF$134,27,0) -> 336 | AS23: =SUM(AO23:AR23) -> 2336 | AT23: =AM23-AS23 -> 140939.54 | AU23: 05.05.2022 | AV23: Axis Bank | AW23: A/c No: 919010057225623 | AY23: 26 | AZ23: 8
A24: BITS-638 | B24: Basweshwar Pawar | C24: 31899 | D24: Male | E24: Nandakumar eknath pawar | F24: Lead PMO | G24: H-302, Kohinoor Abhimaan Homes, somatane-Kasarai Road,Near Sai Temple, Mawal, PUNE 410506 | I24: OOOO | J24: H-302, Kohinoor Abhimaan Homes, somatane-Kasarai Road,Near Sai Temple, Mawal, PUNE 410506 | K24: OOOO | L24: OOOO | M24: OOOO | N24: 44446 | O24: OOOO | P24: OOOO | Q24: OOOO | R24: OOOO | S24: 100233436495 | T24: N/A | U24: Basweshwar Pawar | V24: 30 | W24: =VLOOKUP(A24,'[1]Pay sheet-APRIL- 2022'!$C$5:$AF$134,10,0) -> 30 | X24: N/A | Y24: 89547 | Z24: =VLOOKUP(A24,'[1]Pay sheet-APRIL- 2022'!$C$5:$AF$134,11,0) -> 53728.2 | AA24: 0 | AB24: 0 | AC24: =AD24+AE24+AF24+AG24 -> 35931.8 | AD24: =VLOOKUP(A24,'[1]Pay sheet-APRIL- 2022'!$C$5:$AF$134,12,0) -> 21491.28 | AE24: =VLOOKUP(A24,'[1]Pay sheet-APRIL- 2022'!$C$5:$AF$134,13,0) -> 2083 | AF24: =VLOOKUP(A24,'[1]Pay sheet-APRIL- 2022'!$C$5:$AF$134,14,0) -> 2083 | AG24: =VLOOKUP(A24,'[1]Pay sheet-APRIL- 2022'!$C$5:$AF$134,15,0) -> 10274.52 | AH24: =Z24+AC24 -> 89660 | AI24: =VLOOKUP(A24,'[1]Pay sheet-APRIL- 2022'!$C$5:$AF$134,18,0) -> 1554.609 | AJ24: =VLOOKUP(A24,'[1]Pay sheet-APRIL- 2022'!$C$5:$AF$134,19,0) -> 2584.3264 | AK24: =VLOOKUP(A24,'[1]Pay sheet-APRIL- 2022'!$C$5:$AF$134,20,0) -> 4477.35 | AL24: =VLOOKUP(A24,'[1]Pay sheet-APRIL- 2022'!$C$5:$AF$134,22,0) -> 0 | AM24: =Z24+AD24+AE24+AF24+AG24+AI24+AJ24+AK24 -> 98276.285 | AO24: =VLOOKUP(A24,'[1]Pay sheet-APRIL- 2022'!$C$5:$AF$134,26,0) -> 1800 | AP24: =VLOOKUP(A24,'[1]Pay sheet-APRIL- 2022'!$C$5:$AF$134,25,0) -> 200 | AQ24: =VLOOKUP(A24,'[1]Pay sheet-APRIL- 2022'!$C$5:$AF$134,24,0) -> 0 | AR24: =VLOOKUP(A24,'[1]Pay sheet-APRIL- 2022'!$C$5:$AF$134,27,0) -> 224 | AS24: =SUM(AO24:AR24) -> 2224 | AT24: =AM24-AS24 -> 96052.285 | AU24: 05.05.2022 | AV24: ICICI BANK | AW24: 042401535769 | AY24: 27 | AZ24: 9
A25: BITS-661 | B25: Hemanth Mishra | C25: 17/10/1976 | D25: MALE | E25: Satish Chandra Mishra | F25: Technology Analyst | G25: 16 B,Braj Nagar,Rameshwar Ward, opp. Anima Ubeja's Banglow, KHANDWA Pin-450001, Madhra Pradesh | H25: OOOO | I25: OOOO | J25: 16 B,Braj Nagar,Rameshwar Ward, opp. Anima Ubeja's Banglow, KHANDWA Pin-450001, Madhra Pradesh | K25: OOOO | L25: OOOO | M25: OOOO | N25: 44490 | O25: OOOO | P25: OOOO | Q25: OOOO | R25: OOOO | S25: 100163951857 | T25: N/A | U25: Hemanth Mishra | V25: 30 | W25: =VLOOKUP(A25,'[1]Pay sheet-APRIL- 2022'!$C$5:$AF$134,10,0) -> 30 | X25: N/A | Y25: 98816 | Z25: =VLOOKUP(A25,'[1]Pay sheet-APRIL- 2022'!$C$5:$AF$134,11,0) -> 59289.6 | AA25: 0 | AB25: 0 | AC25: =AD25+AE25+AF25+AG25 -> 39639.4 | AD25: =VLOOKUP(A25,'[1]Pay sheet-APRIL- 2022'!$C$5:$AF$134,12,0) -> 23715.84 | AE25: =VLOOKUP(A25,'[1]Pay sheet-APRIL- 2022'!$C$5:$AF$134,13,0) -> 2083 | AF25: =VLOOKUP(A25,'[1]Pay sheet-APRIL- 2022'!$C$5:$AF$134,14,0) -> 2083 | AG25: =VLOOKUP(A25,'[1]Pay sheet-APRIL- 2022'!$C$5:$AF$134,15,0) -> 11757.56 | AH25: =Z25+AC25 -> 98929 | AI25: =VLOOKUP(A25,'[1]Pay sheet-APRIL- 2022'!$C$5:$AF$134,18,0) -> 1554.609 | AJ25: =VLOOKUP(A25,'[1]Pay sheet-APRIL- 2022'!$C$5:$AF$134,19,0) -> 2851.8298 | AK25: =VLOOKUP(A25,'[1]Pay sheet-APRIL- 2022'!$C$5:$AF$134,20,0) -> 4940.8 | AL25: =VLOOKUP(A25,'[1]Pay sheet-APRIL- 2022'!$C$5:$AF$134,22,0) -> 0 | AM25: =Z25+AD25+AE25+AF25+AG25+AI25+AJ25+AK25 -> 108276.24 | AO25: =VLOOKUP(A25,'[1]Pay sheet-APRIL- 2022'!$C$5:$AF$134,26,0) -> 1800 | AP25: =VLOOKUP(A25,'[1]Pay sheet-APRIL- 2022'!$C$5:$AF$134,25,0) -> 200 | AQ25: =VLOOKUP(A25,'[1]Pay sheet-APRIL- 2022'!$C$5:$AF$134,24,0) -> 0 | AR25: =VLOOKUP(A25,'[1]Pay sheet-APRIL- 2022'!$C$5:$AF$134,27,0) -> 254 | AS25: =SUM(AO25:AR25) -> 2254 | AT25: =AM25-AS25 -> 106022.24 | AU25: 05.05.2022 | AV25: ICICI BANK | AW25: 057001509856 | AY25: 29 | AZ25: 10
A26: BITS-663 | B26: FAZALAHMED IRKAL | C26: 32932 | D26: MALE | E26: CHANDSAHEB IRKAL | F26: SENIOR HADOOP ADMIN | G26: 558, 37/133 New Paccha Peth, Ashok Chowk, Behind Taj Medical Solapur | H26: OOOO | I26: OOOO | J26: 201, Sunaina Apartment, Near Poona College Camp Pune-411001 | K26: OOOO | L26: OOOO | M26: OOOO | N26: 44494 | O26: OOOO | P26: OOOO | Q26: OOOO | R26: OOOO | S26: 101148301276 | T26: N/A | U26: CHANDSAHEB IRKA FAZALA | V26: 30 | W26: =VLOOKUP(A26,'[1]Pay sheet-APRIL- 2022'!$C$5:$AF$134,10,0) -> 22 | X26: N/A | Y26: 59886 | Z26: =VLOOKUP(A26,'[1]Pay sheet-APRIL- 2022'!$C$5:$AF$134,11,0) -> 26349.84 | AA26: 0 | AB26: 0 | AC26: =AD26+AE26+AF26+AG26 -> 17679.56 | AD26: =VLOOKUP(A26,'[1]Pay sheet-APRIL- 2022'!$C$5:$AF$134,12,0) -> 10539.936 | AE26: =VLOOKUP(A26,'[1]Pay sheet-APRIL- 2022'!$C$5:$AF$134,13,0) -> 1528 | AF26: =VLOOKUP(A26,'[1]Pay sheet-APRIL- 2022'!$C$5:$AF$134,14,0) -> 1528 | AG26: =VLOOKUP(A26,'[1]Pay sheet-APRIL- 2022'!$C$5:$AF$134,15,0) -> 4083.624 | AH26: =Z26+AC26 -> 44029.4 | AI26: =VLOOKUP(A26,'[1]Pay sheet-APRIL- 2022'!$C$5:$AF$134,18,0) -> 1554.609 | AJ26: =VLOOKUP(A26,'[1]Pay sheet-APRIL- 2022'!$C$5:$AF$134,19,0) -> 1267.4273 | AK26: =VLOOKUP(A26,'[1]Pay sheet-APRIL- 2022'!$C$5:$AF$134,20,0) -> 2195.82 | AL26: =VLOOKUP(A26,'[1]Pay sheet-APRIL- 2022'!$C$5:$AF$134,22,0) -> 0 | AM26: =Z26+AD26+AE26+AF26+AG26+AI26+AJ26+AK26 -> 49047.256 | AO26: =VLOOKUP(A26,'[1]Pay sheet-APRIL- 2022'!$C$5:$AF$134,26,0) -> 1800 | AP26: =VLOOKUP(A26,'[1]Pay sheet-APRIL- 2022'!$C$5:$AF$134,25,0) -> 200 | AQ26: =VLOOKUP(A26,'[1]Pay sheet-APRIL- 2022'!$C$5:$AF$134,24,0) -> 0 | AR26: =VLOOKUP(A26,'[1]Pay sheet-APRIL- 2022'!$C$5:$AF$134,27,0) -> 254 | AS26: =SUM(AO26:AR26) -> 2254 | AT26: =AM26-AS26 -> 46793.256 | AU26: 05.05.2022 | AV26: SBI | AW26: 32722181716 | AY26: 30 | AZ26: 11
A27: BITS-667 | B27: SUKRUTH YELLAMBOTLA | C27: 34146 | D27: MALE | E27: Yellambotla Vijay Kumar | F27: SENIOR APPLICATION CONSULTANT | G27: H No 6-311/1/B/1,Sri krishna nagar,Qutubullapur,Suchitra,Hyderabad | I27: OOOO | J27: H No 6-311/1/B/1,Sri krishna nagar,Qutubullapur,Suchitra,Hyderabad | K27: OOOO | L27: OOOO | M27: OOOO | N27: 44509 | O27: OOOO | P27: OOOO | Q27: OOOO | R27: OOOO | S27: 100627572976 | T27: N/A | U27: SUKRUTH YELLAMBOTLA | V27: 30 | W27: =VLOOKUP(A27,'[1]Pay sheet-APRIL- 2022'!$C$5:$AF$134,10,0) -> 30 | X27: N/A | Y27: 35786 | Z27: =VLOOKUP(A27,'[1]Pay sheet-APRIL- 2022'!$C$5:$AF$134,11,0) -> 21471.6 | AA27: 0 | AB27: 0 | AC27: =AD27+AE27+AF27+AG27 -> 14427.4 | AD27: =VLOOKUP(A27,'[1]Pay sheet-APRIL- 2022'!$C$5:$AF$134,12,0) -> 8588.64 | AE27: =VLOOKUP(A27,'[1]Pay sheet-APRIL- 2022'!$C$5:$AF$134,13,0) -> 2083 | AF27: =VLOOKUP(A27,'[1]Pay sheet-APRIL- 2022'!$C$5:$AF$134,14,0) -> 2083 | AG27: =VLOOKUP(A27,'[1]Pay sheet-APRIL- 2022'!$C$5:$AF$134,15,0) -> 1672.76 | AH27: =Z27+AC27 -> 35899 | AI27: =VLOOKUP(A27,'[1]Pay sheet-APRIL- 2022'!$C$5:$AF$134,18,0) -> 1554.609 | AJ27: =VLOOKUP(A27,'[1]Pay sheet-APRIL- 2022'!$C$5:$AF$134,19,0) -> 1032.784 | AK27: =VLOOKUP(A27,'[1]Pay sheet-APRIL- 2022'!$C$5:$AF$134,20,0) -> 1789.3 | AL27: =VLOOKUP(A27,'[1]Pay sheet-APRIL- 2022'!$C$5:$AF$134,22,0) -> 0 | AM27: =Z27+AD27+AE27+AF27+AG27+AI27+AJ27+AK27 -> 40275.693 | AO27: =VLOOKUP(A27,'[1]Pay sheet-APRIL- 2022'!$C$5:$AF$134,26,0) -> 1800 | AP27: =VLOOKUP(A27,'[1]Pay sheet-APRIL- 2022'!$C$5:$AF$134,25,0) -> 200 | AQ27: =VLOOKUP(A27,'[1]Pay sheet-APRIL- 2022'!$C$5:$AF$134,24,0) -> 0 | AR27: =VLOOKUP(A27,'[1]Pay sheet-APRIL- 2022'!$C$5:$AF$134,27,0) -> 252 | AS27: =SUM(AO27:AR27) -> 2252 | AT27: =AM27-AS27 -> 38023.693 | AU27: 05.05.2022 | AV27: HDFC0000486 | AW27: 50100468093660 | AY27: 31 | AZ27: 12
A28: BITS-682 | B28: Ajay Singh | C28: 33635 | D28: MALE | E28: Santhosh Singh | F28: Sr.Cloud Network Engineer | G28: EM-36,Indus Town,Phase II,Ratanpur,Missrod,Bhopal,Madhya pradesh 462047 | I28: OOOO | J28: EM-36,Indus Town,Phase II,Ratanpur,Missrod,Bhopal,Madhya pradesh 462047 | K28: OOOO | L28: OOOO | M28: OOOO | N28: 44538 | O28: OOOO | P28: OOOO | Q28: OOOO | R28: OOOO | S28: 101265633203 | T28: N/A | U28: Ajay Singh | V28: 30 | W28: =VLOOKUP(A28,'[1]Pay sheet-APRIL- 2022'!$C$5:$AF$134,10,0) -> 30 | X28: N/A | Y28: 128477 | Z28: =VLOOKUP(A28,'[1]Pay sheet-APRIL- 2022'!$C$5:$AF$134,11,0) -> 77086.2 | AA28: 0 | AB28: 0 | AC28: =AD28+AE28+AF28+AG28 -> 51503.8 | AD28: =VLOOKUP(A28,'[1]Pay sheet-APRIL- 2022'!$C$5:$AF$134,12,0) -> 30834.48 | AE28: =VLOOKUP(A28,'[1]Pay sheet-APRIL- 2022'!$C$5:$AF$134,13,0) -> 2083 | AF28: =VLOOKUP(A28,'[1]Pay sheet-APRIL- 2022'!$C$5:$AF$134,14,0) -> 2083 | AG28: =VLOOKUP(A28,'[1]Pay sheet-APRIL- 2022'!$C$5:$AF$134,15,0) -> 16503.32 | AH28: =Z28+AC28 -> 128590 | AI28: =VLOOKUP(A28,'[1]Pay sheet-APRIL- 2022'!$C$5:$AF$134,18,0) -> 1554.609 | AJ28: =VLOOKUP(A28,'[1]Pay sheet-APRIL- 2022'!$C$5:$AF$134,19,0) -> 3707.8462 | AK28: =VLOOKUP(A28,'[1]Pay sheet-APRIL- 2022'!$C$5:$AF$134,20,0) -> 6423.85 | AL28: =VLOOKUP(A28,'[1]Pay sheet-APRIL- 2022'!$C$5:$AF$134,22,0) -> 0 | AM28: =Z28+AD28+AE28+AF28+AG28+AI28+AJ28+AK28 -> 140276.31 | AO28: =VLOOKUP(A28,'[1]Pay sheet-APRIL- 2022'!$C$5:$AF$134,26,0) -> 1800 | AP28: =VLOOKUP(A28,'[1]Pay sheet-APRIL- 2022'!$C$5:$AF$134,25,0) -> 200 | AQ28: =VLOOKUP(A28,'[1]Pay sheet-APRIL- 2022'!$C$5:$AF$134,24,0) -> 0 | AR28: =VLOOKUP(A28,'[1]Pay sheet-APRIL- 2022'!$C$5:$AF$134,27,0) -> 283 | AS28: =SUM(AO28:AR28) -> 2283 | AT28: =AM28-AS28 -> 137993.31 | AU28: 05.05.2022 | AV28: Axis Bank | AW28: 916010061379733 | AY28: 32 | AZ28: 13
A29: BITS-697 | B29: Rajesh Dhumal | C29: 15-03-1990 | D29: MALE | E29: Ramakrishna | F29: Senior network security analyst. | G29: Deshpande Galli, Kholeshwar Collage Samor, Ambejogai, Bid, Maharashtra 431517 | H29: OOOO | I29: OOOO | J29: Deshpande Galli, Kholeshwar Collage Samor, Ambejogai, Bid, Maharashtra 431517 | K29: OOOO | L29: OOOO | M29: OOOO | N29: 44579 | O29: OOOO | P29: OOOO | Q29: OOOO | R29: OOOO | S29: 100637149311 | T29: N/A | U29: Rajesh Dhumal | V29: 30 | W29: =VLOOKUP(A29,'[1]Pay sheet-APRIL- 2022'!$C$5:$AF$134,10,0) -> 30 | X29: N/A | Y29: 74716 | Z29: =VLOOKUP(A29,'[1]Pay sheet-APRIL- 2022'!$C$5:$AF$134,11,0) -> 44829.6 | AA29: 0 | AB29: 0 | AC29: =AD29+AE29+AF29+AG29 -> 29999.4 | AD29: =VLOOKUP(A29,'[1]Pay sheet-APRIL- 2022'!$C$5:$AF$134,12,0) -> 17931.84 | AE29: =VLOOKUP(A29,'[1]Pay sheet-APRIL- 2022'!$C$5:$AF$134,13,0) -> 2083 | AF29: =VLOOKUP(A29,'[1]Pay sheet-APRIL- 2022'!$C$5:$AF$134,14,0) -> 2083 | AG29: =VLOOKUP(A29,'[1]Pay sheet-APRIL- 2022'!$C$5:$AF$134,15,0) -> 7901.56 | AH29: =Z29+AC29 -> 74829 | AI29: =VLOOKUP(A29,'[1]Pay sheet-APRIL- 2022'!$C$5:$AF$134,18,0) -> 1554.609 | AJ29: =VLOOKUP(A29,'[1]Pay sheet-APRIL- 2022'!$C$5:$AF$134,19,0) -> 2156.3038 | AK29: =VLOOKUP(A29,'[1]Pay sheet-APRIL- 2022'!$C$5:$AF$134,20,0) -> 3735.8 | AL29: =VLOOKUP(A29,'[1]Pay sheet-APRIL- 2022'!$C$5:$AF$134,22,0) -> 0 | AM29: =Z29+AD29+AE29+AF29+AG29+AI29+AJ29+AK29 -> 82275.713 | AO29: =VLOOKUP(A29,'[1]Pay sheet-APRIL- 2022'!$C$5:$AF$134,26,0) -> 1800 | AP29: =VLOOKUP(A29,'[1]Pay sheet-APRIL- 2022'!$C$5:$AF$134,25,0) -> 200 | AQ29: =VLOOKUP(A29,'[1]Pay sheet-APRIL- 2022'!$C$5:$AF$134,24,0) -> 0 | AR29: =VLOOKUP(A29,'[1]Pay sheet-APRIL- 2022'!$C$5:$AF$134,27,0) -> 283 | AS29: =SUM(AO29:AR29) -> 2283 | AT29: =AM29-AS29 -> 79992.713 | AU29: 05.05.2022 | AV29: AXIS BANK | AW29: 921010021808628 | AY29: 33 | AZ29: 14
A30: BITS-704 | B30: Ajay Pal Singh | C30: 31491 | D30: MALE | E30: kunwar rohitash singh | F30: Network security consultant | G30: H No 32,Jalalpur-Raghunadhpur,Murad nagar,Gaziyabad,UP 201206 | H30: OOOO | I30: OOOO | J30: H No 66,New Gandhi layout,Jaffar nagar,Nagpur,Maharastra 440013 | K30: OOOO | L30: OOOO | M30: OOOO | N30: 44601 | O30: OOOO | P30: OOOO | Q30: OOOO | R30: OOOO | S30: 100897320115 | T30: N/A | U30: Ajay Pal Singh | V30: 30 | W30: =VLOOKUP(A30,'[1]Pay sheet-APRIL- 2022'!$C$5:$AF$134,10,0) -> 30 | X30: N/A | Y30: 71009 | Z30: =VLOOKUP(A30,'[1]Pay sheet-APRIL- 2022'!$C$5:$AF$134,11,0) -> 42605.4 | AA30: 0 | AB30: 0 | AC30: =AD30+AE30+AF30+AG30 -> 28516.6 | AD30: =VLOOKUP(A30,'[1]Pay sheet-APRIL- 2022'!$C$5:$AF$134,12,0) -> 17042.16 | AE30: =VLOOKUP(A30,'[1]Pay sheet-APRIL- 2022'!$C$5:$AF$134,13,0) -> 2083 | AF30: =VLOOKUP(A30,'[1]Pay sheet-APRIL- 2022'!$C$5:$AF$134,14,0) -> 2083 | AG30: =VLOOKUP(A30,'[1]Pay sheet-APRIL- 2022'!$C$5:$AF$134,15,0) -> 7308.44 | AH30: =Z30+AC30 -> 71122 | AI30: =VLOOKUP(A30,'[1]Pay sheet-APRIL- 2022'!$C$5:$AF$134,18,0) -> 1554.609 | AJ30: =VLOOKUP(A30,'[1]Pay sheet-APRIL- 2022'!$C$5:$AF$134,19,0) -> 2049.3197 | AK30: =VLOOKUP(A30,'[1]Pay sheet-APRIL- 2022'!$C$5:$AF$134,20,0) -> 3550.45 | AL30: =VLOOKUP(A30,'[1]Pay sheet-APRIL- 2022'!$C$5:$AF$134,22,0) -> 0 | AM30: =Z30+AD30+AE30+AF30+AG30+AI30+AJ30+AK30 -> 78276.379 | AO30: =VLOOKUP(A30,'[1]Pay sheet-APRIL- 2022'!$C$5:$AF$134,26,0) -> 1800 | AP30: =VLOOKUP(A30,'[1]Pay sheet-APRIL- 2022'!$C$5:$AF$134,25,0) -> 200 | AQ30: =VLOOKUP(A30,'[1]Pay sheet-APRIL- 2022'!$C$5:$AF$134,24,0) -> 0 | AR30: =VLOOKUP(A30,'[1]Pay sheet-APRIL- 2022'!$C$5:$AF$134,27,0) -> 283 | AS30: =SUM(AO30:AR30) -> 2283 | AT30: =AM30-AS30 -> 75993.379 | AU30: 05.05.2022 | AV30: DBS Bank | AW30: 881015838995 | AY30: 34 | AZ30: 15
A31: BITS-716 | B31: PAVANKUMAR | C31: 35211 | D31: MALE | E31: P YELLAIAH | F31: SAP Basis consultant | G31: 7-8/1, palmakole(V), shamshabad(M), RR Dist,509325 | H31: OOOO | I31: OOOO | J31: 7-8/1, palmakole(V), shamshabad(M), RR Dist,509325 | K31: OOOO | L31: OOOO | M31: OOOO | N31: 44602 | O31: OOOO | P31: OOOO | Q31: OOOO | R31: OOOO | S31: 101593987074 | T31: N/A | U31: PAVANKUMAR | V31: 30 | W31: =VLOOKUP(A31,'[1]Pay sheet-APRIL- 2022'!$C$5:$AF$134,10,0) -> 30 | X31: N/A | Y31: 38567 | Z31: =VLOOKUP(A31,'[1]Pay sheet-APRIL- 2022'!$C$5:$AF$134,11,0) -> 23140.2 | AA31: 0 | AB31: 0 | AC31: =AD31+AE31+AF31+AG31 -> 15539.8 | AD31: =VLOOKUP(A31,'[1]Pay sheet-APRIL- 2022'!$C$5:$AF$134,12,0) -> 9256.08 | AE31: =VLOOKUP(A31,'[1]Pay sheet-APRIL- 2022'!$C$5:$AF$134,13,0) -> 2083 | AF31: =VLOOKUP(A31,'[1]Pay sheet-APRIL- 2022'!$C$5:$AF$134,14,0) -> 2083 | AG31: =VLOOKUP(A31,'[1]Pay sheet-APRIL- 2022'!$C$5:$AF$134,15,0) -> 2117.72 | AH31: =Z31+AC31 -> 38680 | AI31: =VLOOKUP(A31,'[1]Pay sheet-APRIL- 2022'!$C$5:$AF$134,18,0) -> 1554.609 | AJ31: =VLOOKUP(A31,'[1]Pay sheet-APRIL- 2022'!$C$5:$AF$134,19,0) -> 1113.0436 | AK31: =VLOOKUP(A31,'[1]Pay sheet-APRIL- 2022'!$C$5:$AF$134,20,0) -> 1928.35 | AL31: =VLOOKUP(A31,'[1]Pay sheet-APRIL- 2022'!$C$5:$AF$134,22,0) -> 0 | AM31: =Z31+AD31+AE31+AF31+AG31+AI31+AJ31+AK31 -> 43276.003 | AO31: =VLOOKUP(A31,'[1]Pay sheet-APRIL- 2022'!$C$5:$AF$134,26,0) -> 1800 | AP31: =VLOOKUP(A31,'[1]Pay sheet-APRIL- 2022'!$C$5:$AF$134,25,0) -> 200 | AQ31: =VLOOKUP(A31,'[1]Pay sheet-APRIL- 2022'!$C$5:$AF$134,24,0) -> 0 | AR31: =VLOOKUP(A31,'[1]Pay sheet-APRIL- 2022'!$C$5:$AF$134,27,0) -> 283 | AS31: =SUM(AO31:AR31) -> 2283 | AT31: =AM31-AS31 -> 40993.003 | AU31: 05.05.2022 | AV31: STATE BANK OF INDIA | AW31: 62318158569 | AY31: 35 | AZ31: 16
A32: BITS-729 | B32: Rahul Suryawanshi | C32: 35236 | D32: MALE | E32: Tarun Suryawanshi | F32: Sr.Network security Analyst | G32: H No 53,Near Durga mandir,at po sarra,gram sarra,tahsil multai dist bethul,Madhya pradesh 460661 | H32: H No 53,Near Durga mandir,at po sarra,gram sarra,tahsil multai dist bethul,Madhya pradesh 460661 | I32: OOOO | J32: OOOO | K32: OOOO | L32: OOOO | M32: OOOO | N32: 44624 | O32: OOOO | P32: OOOO | Q32: OOOO | R32: OOOO | S32: 101274942480 | T32: N/A | U32: Rahul Suryawanshi | V32: 30 | W32: =VLOOKUP(A32,'[1]Pay sheet-APRIL- 2022'!$C$5:$AF$134,10,0) -> 30 | X32: N/A | Y32: 80278 | Z32: =VLOOKUP(A32,'[1]Pay sheet-APRIL- 2022'!$C$5:$AF$134,11,0) -> 48166.8 | AA32: 0 | AB32: 0 | AC32: =AD32+AE32+AF32+AG32 -> 32224.2 | AD32: =VLOOKUP(A32,'[1]Pay sheet-APRIL- 2022'!$C$5:$AF$134,12,0) -> 19266.72 | AE32: =VLOOKUP(A32,'[1]Pay sheet-APRIL- 2022'!$C$5:$AF$134,13,0) -> 2083 | AF32: =VLOOKUP(A32,'[1]Pay sheet-APRIL- 2022'!$C$5:$AF$134,14,0) -> 2083 | AG32: =VLOOKUP(A32,'[1]Pay sheet-APRIL- 2022'!$C$5:$AF$134,15,0) -> 8791.48 | AH32: =Z32+AC32 -> 80391 | AI32: =VLOOKUP(A32,'[1]Pay sheet-APRIL- 2022'!$C$5:$AF$134,18,0) -> 1554.609 | AJ32: =VLOOKUP(A32,'[1]Pay sheet-APRIL- 2022'!$C$5:$AF$134,19,0) -> 2316.8231 | AK32: =VLOOKUP(A32,'[1]Pay sheet-APRIL- 2022'!$C$5:$AF$134,20,0) -> 4013.9 | AL32: =VLOOKUP(A32,'[1]Pay sheet-APRIL- 2022'!$C$5:$AF$134,22,0) -> 0 | AM32: =Z32+AD32+AE32+AF32+AG32+AI32+AJ32+AK32 -> 88276.332 | AO32: =VLOOKUP(A32,'[1]Pay sheet-APRIL- 2022'!$C$5:$AF$134,26,0) -> 1800 | AP32: =VLOOKUP(A32,'[1]Pay sheet-APRIL- 2022'!$C$5:$AF$134,25,0) -> 200 | AQ32: =VLOOKUP(A32,'[1]Pay sheet-APRIL- 2022'!$C$5:$AF$134,24,0) -> 0 | AR32: =VLOOKUP(A32,'[1]Pay sheet-APRIL- 2022'!$C$5:$AF$134,27,0) -> 283 | AS32: =SUM(AO32:AR32) -> 2283 | AT32: =AM32-AS32 -> 85993.332 | AU32: 05.05.2022 | AV32: standard chartered | AW32: 27011616110 | AY32: 36 | AZ32: 17
A33: BITS-730 | B33: Shantanu Patankar | C33: 32959 | D33: MALE | E33: shivajirao balasaheb | F33: Network security consultant | G33: Patankar house,kuntharwada,at post patan,taluq patan,dist satare,maharastra 415206 | H33: 204,Gaurav roy appts,tirangachowk,bharati vidyapitt,katray,pune,Maharastra 411046 | I33: OOOO | J33: OOOO | K33: OOOO | L33: OOOO | M33: OOOO | N33: 44629 | O33: OOOO | P33: OOOO | Q33: OOOO | R33: OOOO | S33: 100894664218 | T33: N/A | U33: Shantanu Patankar | V33: 30 | W33: =VLOOKUP(A33,'[1]Pay sheet-APRIL- 2022'!$C$5:$AF$134,10,0) -> 30 | X33: N/A | Y33: 112719 | Z33: =VLOOKUP(A33,'[1]Pay sheet-APRIL- 2022'!$C$5:$AF$134,11,0) -> 67631.4 | AA33: 0 | AB33: 0 | AC33: =AD33+AE33+AF33+AG33 -> 45200.6 | AD33: =VLOOKUP(A33,'[1]Pay sheet-APRIL- 2022'!$C$5:$AF$134,12,0) -> 27052.56 | AE33: =VLOOKUP(A33,'[1]Pay sheet-APRIL- 2022'!$C$5:$AF$134,13,0) -> 2083 | AF33: =VLOOKUP(A33,'[1]Pay sheet-APRIL- 2022'!$C$5:$AF$134,14,0) -> 2083 | AG33: =VLOOKUP(A33,'[1]Pay sheet-APRIL- 2022'!$C$5:$AF$134,15,0) -> 13982.04 | AH33: =Z33+AC33 -> 112832 | AI33: =VLOOKUP(A33,'[1]Pay sheet-APRIL- 2022'!$C$5:$AF$134,18,0) -> 1554.609 | AJ33: =VLOOKUP(A33,'[1]Pay sheet-APRIL- 2022'!$C$5:$AF$134,19,0) -> 3253.0703 | AK33: =VLOOKUP(A33,'[1]Pay sheet-APRIL- 2022'!$C$5:$AF$134,20,0) -> 5635.95 | AL33: =VLOOKUP(A33,'[1]Pay sheet-APRIL- 2022'!$C$5:$AF$134,22,0) -> 0 | AM33: =Z33+AD33+AE33+AF33+AG33+AI33+AJ33+AK33 -> 123275.63 | AO33: =VLOOKUP(A33,'[1]Pay sheet-APRIL- 2022'!$C$5:$AF$134,26,0) -> 1800 | AP33: =VLOOKUP(A33,'[1]Pay sheet-APRIL- 2022'!$C$5:$AF$134,25,0) -> 200 | AQ33: =VLOOKUP(A33,'[1]Pay sheet-APRIL- 2022'!$C$5:$AF$134,24,0) -> 0 | AR33: =VLOOKUP(A33,'[1]Pay sheet-APRIL- 2022'!$C$5:$AF$134,27,0) -> 283 | AS33: =SUM(AO33:AR33) -> 2283 | AT33: =AM33-AS33 -> 120992.63 | AU33: 05.05.2022 | AV33: ICICI bank | AW33: 239001508763 | AY33: 37 | AZ33: 18
A34: BITS-736 | B34: Varalakshmi Vijay | C34: 29711 | D34: Female | E34: Vijay srinivasan | F34: Network security consultant | G34: 902,Link view appts,sethia complex-2, opp MG road,Motilal nagar,Road no.3,Goregaon west,Mumbai,Maharastra 400104 | H34: 902,Link view appts,sethia complex-2, opp MG road,Motilal nagar,Road no.3,Goregaon west,Mumbai,Maharastra 400104 | I34: OOOO | J34: OOOO | K34: OOOO | L34: OOOO | M34: OOOO | N34: 44641 | O34: OOOO | P34: OOOO | Q34: OOOO | R34: OOOO | S34: 101804644758 | T34: N/A | U34: Varalakshmi Vijay | V34: 30 | W34: =VLOOKUP(A34,'[1]Pay sheet-APRIL- 2022'!$C$5:$AF$134,10,0) -> 30 | X34: N/A | Y34: 66374 | Z34: =VLOOKUP(A34,'[1]Pay sheet-APRIL- 2022'!$C$5:$AF$134,11,0) -> 39824.4 | AA34: 0 | AB34: 0 | AC34: =AD34+AE34+AF34+AG34 -> 26662.6 | AD34: =VLOOKUP(A34,'[1]Pay sheet-APRIL- 2022'!$C$5:$AF$134,12,0) -> 15929.76 | AE34: =VLOOKUP(A34,'[1]Pay sheet-APRIL- 2022'!$C$5:$AF$134,13,0) -> 2083 | AF34: =VLOOKUP(A34,'[1]Pay sheet-APRIL- 2022'!$C$5:$AF$134,14,0) -> 2083 | AG34: =VLOOKUP(A34,'[1]Pay sheet-APRIL- 2022'!$C$5:$AF$134,15,0) -> 6566.84 | AH34: =Z34+AC34 -> 66487 | AI34: =VLOOKUP(A34,'[1]Pay sheet-APRIL- 2022'!$C$5:$AF$134,18,0) -> 1554.609 | AJ34: =VLOOKUP(A34,'[1]Pay sheet-APRIL- 2022'!$C$5:$AF$134,19,0) -> 1915.5536 | AK34: =VLOOKUP(A34,'[1]Pay sheet-APRIL- 2022'!$C$5:$AF$134,20,0) -> 3318.7 | AL34: =VLOOKUP(A34,'[1]Pay sheet-APRIL- 2022'!$C$5:$AF$134,22,0) -> 0 | AM34: =Z34+AD34+AE34+AF34+AG34+AI34+AJ34+AK34 -> 73275.863 | AO34: =VLOOKUP(A34,'[1]Pay sheet-APRIL- 2022'!$C$5:$AF$134,26,0) -> 1800 | AP34: =VLOOKUP(A34,'[1]Pay sheet-APRIL- 2022'!$C$5:$AF$134,25,0) -> 200 | AQ34: =VLOOKUP(A34,'[1]Pay sheet-APRIL- 2022'!$C$5:$AF$134,24,0) -> 0 | AR34: =VLOOKUP(A34,'[1]Pay sheet-APRIL- 2022'!$C$5:$AF$134,27,0) -> 283 | AS34: =SUM(AO34:AR34) -> 2283 | AT34: =AM34-AS34 -> 70992.863 | AU34: 05.05.2022 | AV34: ICICI bank | AW34: 055501503361 | AY34: 38 | AZ34: 19
A35: BITS-744 | B35: OMPRAKASH PURI | C35: 31427 | D35: Male | E35: Shankarnath Singh | F35: CONSULTANT | G35: LIG-162,2nd floor,7th phase,KPHB,Near basket ball ground,Hyderabad,TS 500085 | H35: LIG-162,2nd floor,7th phase,KPHB,Near basket ball ground,Hyderabad,TS 500085 | I35: QQQQQ | J35: QQQQQ | K35: QQQQQ | L35: QQQQQ | M35: QQQQQ | N35: 44652 | O35: OOOO | P35: OOOO | Q35: OOOO | R35: OOOO | S35: 100260928334 | T35: N/A | U35: OMPRAKASH PURI | V35: 30 | W35: =VLOOKUP(A35,'[1]Pay sheet-APRIL- 2022'!$C$5:$AF$134,10,0) -> 30 | X35: N/A | Y35: 108085 | Z35: =VLOOKUP(A35,'[1]Pay sheet-APRIL- 2022'!$C$5:$AF$134,11,0) -> 64851 | AA35: 0 | AB35: 0 | AC35: =AD35+AE35+AF35+AG35 -> 43347 | AD35: =VLOOKUP(A35,'[1]Pay sheet-APRIL- 2022'!$C$5:$AF$134,12,0) -> 25940.4 | AE35: =VLOOKUP(A35,'[1]Pay sheet-APRIL- 2022'!$C$5:$AF$134,13,0) -> 2083 | AF35: =VLOOKUP(A35,'[1]Pay sheet-APRIL- 2022'!$C$5:$AF$134,14,0) -> 2083 | AG35: =VLOOKUP(A35,'[1]Pay sheet-APRIL- 2022'!$C$5:$AF$134,15,0) -> 13240.6 | AH35: =Z35+AC35 -> 108198 | AI35: =VLOOKUP(A35,'[1]Pay sheet-APRIL- 2022'!$C$5:$AF$134,18,0) -> 1554.609 | AJ35: =VLOOKUP(A35,'[1]Pay sheet-APRIL- 2022'!$C$5:$AF$134,19,0) -> 3119.3331 | AK35: =VLOOKUP(A35,'[1]Pay sheet-APRIL- 2022'!$C$5:$AF$134,20,0) -> 5404.25 | AL35: =VLOOKUP(A35,'[1]Pay sheet-APRIL- 2022'!$C$5:$AF$134,22,0) -> 0 | AM35: =Z35+AD35+AE35+AF35+AG35+AI35+AJ35+AK35 -> 118276.19 | AO35: =VLOOKUP(A35,'[1]Pay sheet-APRIL- 2022'!$C$5:$AF$134,26,0) -> 1800 | AP35: =VLOOKUP(A35,'[1]Pay sheet-APRIL- 2022'!$C$5:$AF$134,25,0) -> 200 | AQ35: =VLOOKUP(A35,'[1]Pay sheet-APRIL- 2022'!$C$5:$AF$134,24,0) -> 0 | AR35: =VLOOKUP(A35,'[1]Pay sheet-APRIL- 2022'!$C$5:$AF$134,27,0) -> 0 | AS35: =SUM(AO35:AR35) -> 2000 | AT35: =AM35-AS35 -> 116276.19 | AU35: 05.05.2022 | AV35: STATE BANK OF INDIA | AW35: 30067197155 | AY35: 39 | AZ35: 20
A36: BITS-746 | B36: DiptiRanjan Dikhit | C36: 31991 | D36: Female | E36: Purna chandra | F36: Network Security Engineer | G36: At-Sanakanjiya nuva sahi,IV Irrigation Market colony,Gate No.2,PO Satyardhi,near sakhi gopi bus stand,Puri,Odissa 752014 | I36: QQQQQ | J36: At-Sanakanjiya nuva sahi,IV Irrigation Market colony,Gate No.2,PO Satyardhi,near sakhi gopi bus stand,Puri,Odissa 752014 | K36: QQQQQ | L36: QQQQQ | M36: QQQQQ | N36: 44655 | O36: OOOO | P36: OOOO | Q36: OOOO | R36: OOOO | S36: 101345259957 | T36: N/A | U36: DiptiRanjan Dikhit | V36: 30 | W36: =VLOOKUP(A36,'[1]Pay sheet-APRIL- 2022'!$C$5:$AF$134,10,0) -> 27 | X36: N/A | Y36: 62667 | Z36: =VLOOKUP(A36,'[1]Pay sheet-APRIL- 2022'!$C$5:$AF$134,11,0) -> 33840.18 | AA36: 0 | AB36: 0 | AC36: =AD36+AE36+AF36+AG36 -> 22673.12 | AD36: =VLOOKUP(A36,'[1]Pay sheet-APRIL- 2022'!$C$5:$AF$134,12,0) -> 13536.072 | AE36: =VLOOKUP(A36,'[1]Pay sheet-APRIL- 2022'!$C$5:$AF$134,13,0) -> 1875 | AF36: =VLOOKUP(A36,'[1]Pay sheet-APRIL- 2022'!$C$5:$AF$134,14,0) -> 1875 | AG36: =VLOOKUP(A36,'[1]Pay sheet-APRIL- 2022'!$C$5:$AF$134,15,0) -> 5387.048 | AH36: =Z36+AC36 -> 56513.3 | AI36: =VLOOKUP(A36,'[1]Pay sheet-APRIL- 2022'!$C$5:$AF$134,18,0) -> 1554.609 | AJ36: =VLOOKUP(A36,'[1]Pay sheet-APRIL- 2022'!$C$5:$AF$134,19,0) -> 1627.7127 | AK36: =VLOOKUP(A36,'[1]Pay sheet-APRIL- 2022'!$C$5:$AF$134,20,0) -> 2820.015 | AL36: =VLOOKUP(A36,'[1]Pay sheet-APRIL- 2022'!$C$5:$AF$134,22,0) -> 0 | AM36: =Z36+AD36+AE36+AF36+AG36+AI36+AJ36+AK36 -> 62515.637 | AO36: =VLOOKUP(A36,'[1]Pay sheet-APRIL- 2022'!$C$5:$AF$134,26,0) -> 1800 | AP36: =VLOOKUP(A36,'[1]Pay sheet-APRIL- 2022'!$C$5:$AF$134,25,0) -> 200 | AQ36: =VLOOKUP(A36,'[1]Pay sheet-APRIL- 2022'!$C$5:$AF$134,24,0) -> 0 | AR36: =VLOOKUP(A36,'[1]Pay sheet-APRIL- 2022'!$C$5:$AF$134,27,0) -> 0 | AS36: =SUM(AO36:AR36) -> 2000 | AT36: =AM36-AS36 -> 60515.637 | AU36: 05.05.2022 | AV36: State Bank Of India | AW36: 31162392468 | AY36: 40 | AZ36: 21
W37: =SUM(W16:W36) -> 619 | X37: =SUM(X16:X36) -> 0 | Y37: =SUM(Y16:Y36) -> 1742484 | Z37: =SUM(Z16:Z36) -> 1032148.6 | AA37: =SUM(AA16:AA36) -> 0 | AB37: =SUM(AB16:AB36) -> 0 | AC37: =SUM(AC16:AC36) -> 690472.08 | AD37: =SUM(AD16:AD36) -> 412859.45 | ... AL37: =SUM(AL16:AL36) -> 0 | AM37: =Z37+AD37+AE37+AF37+AG37+AI37+AJ37+AK37 -> 1890926.2 | AN37: =SUM(AN16:AN36) -> 0 | AO37: =SUM(AO16:AO36) -> 42000 | AP37: =SUM(AP16:AP36) -> 4200 | AQ37: =SUM(AQ16:AQ36) -> 0 | AR37: =SUM(AR16:AR36) -> 5867.337 | AS37: =SUM(AS16:AS36) -> 52067.337 | AT37: =SUM(AT16:AT36) -> 1838858.9

Sheet 04-22 eq ren
A1: Form D
A2: (See rule 6)
A4: Register to be maintained by the employer under rule 6 of the Equal Remuneration Rules, 1976
D6: ='04-221Master'!D10 -> 44652
A8: Name and address of Contractor : | F8: ='04-221Master'!F5 -> Burgeon IT Services Pvt.Ltd.
A10: Name and address of establishment in/under which contract is carried on : | F10: ='04-221Master'!AP5 -> Burgeon IT Services Pvt.Ltd.
F11: ='04-221Master'!AP6 -> Siri Mansion LIGB 436 Dr.A S Rao Nagar,Hyderabad
A12: Name and address of Principal Employer : | F12: ='04-221Master'!AP10 -> INFOSYS LTD.IL Pune SEZ Unit-I,Plot No. 24/3
F13: ='04-221Master'!AP11 -> Rajiv gandhi Info tech park,Village Mann,Pune,Maharashtra 411057
A14: Total number of men workers employed | C14: =D41 -> 17
A16: Total number of women workers employed | C16: =C41 -> 4
C18: Components of remuneration
A19: Category of workers | B19: Brief Description of work | C19: No of women employed | D19: No. of men employed | E19: Rate or remuneration paid | F19: Basic wage & Dearness Allowance | G19: House Rent allowance | H19: Other allowances | I19: Cash value of concessional supply of essential commodities | J19: Name of the Client | K19: Primary Work Place/ Location
A20: ='04-221Master'!F16 -> Senior Software Engineer | B20: IT SUPPORTIVE SERICE | C20: 1 | D20: 0 | E20: ='04-221Master'!Y16 -> 75643 | F20: ='04-221Master'!Z16 -> 45385.8 | G20: ='04-221Master'!AD16 -> 18154.32 | H20: =E20-(F20+G20) -> 12102.88 | I20: 0 | J20: INFOSYS LTD | K20: PUNE
A21: ='04-221Master'!F17 -> Splunk Developer | B21: IT SUPPORTIVE SERICE | C21: 0 | D21: 1 | E21: ='04-221Master'!Y17 -> 149795 | F21: ='04-221Master'!Z17 -> 89877 | G21: ='04-221Master'!AD17 -> 35950.8 | H21: =E21-(F21+G21) -> 23967.2 | I21: 0 | K21: SEZ 1
A22: ='04-221Master'!F18 -> Sr Citrix Administrator | B22: IT SUPPORTIVE SERICE | C22: 0 | D22: 1 | E22: ='04-221Master'!Y18 -> 61740 | F22: ='04-221Master'!Z18 -> 37044 | G22: ='04-221Master'!AD18 -> 14817.6 | H22: =E22-(F22+G22) -> 9878.4 | I22: 0
A23: ='04-221Master'!F19 -> Project Manager | B23: IT SUPPORTIVE SERICE | C23: 1 | D23: 0 | E23: ='04-221Master'!Y19 -> 82132 | F23: ='04-221Master'!Z19 -> 49279.2 | G23: ='04-221Master'!AD19 -> 19711.68 | H23: =E23-(F23+G23) -> 13141.12 | I23: 0
A24: ='04-221Master'!F20 -> Sr. Software Engineer | B24: IT SUPPORTIVE SERICE | C24: 0 | D24: 1 | E24: ='04-221Master'!Y20 -> 69580 | F24: ='04-221Master'!Z20 -> 41748 | G24: ='04-221Master'!AD20 -> 16699.2 | H24: =E24-(F24+G24) -> 11132.8 | I24: 0
A25: ='04-221Master'!F21 -> Sr. DBA / Sr. Administrator | B25: IT SUPPORTIVE SERICE | C25: 0 | D25: 1 | E25: ='04-221Master'!Y21 -> 98501 | F25: ='04-221Master'!Z21 -> 59100.6 | G25: ='04-221Master'!AD21 -> 23640.24 | H25: =E25-(F25+G25) -> 15760.16 | I25: 0
A26: ='04-221Master'!F22 -> SQL DATABASE ADMINISTRATOR | B26: IT SUPPORTIVE SERICE | C26: 0 | D26: 1 | E26: ='04-221Master'!Y22 -> 46909 | F26: ='04-221Master'!Z22 -> 28145.4 | G26: ='04-221Master'!AD22 -> 11258.16 | H26: =E26-(F26+G26) -> 7505.44 | I26: 0
A27: ='04-221Master'!F23 -> Senior Support Engineer | B27: IT SUPPORTIVE SERICE | C27: 0 | D27: 1 | E27: ='04-221Master'!Y23 -> 131257 | F27: ='04-221Master'!Z23 -> 78754.2 | G27: ='04-221Master'!AD23 -> 31501.68 | H27: =E27-(F27+G27) -> 21001.12 | I27: 0
A28: ='04-221Master'!F24 -> Lead PMO | B28: IT SUPPORTIVE SERICE | C28: 0 | D28: 1 | E28: ='04-221Master'!Y24 -> 89547 | F28: ='04-221Master'!Z24 -> 53728.2 | G28: ='04-221Master'!AD24 -> 21491.28 | H28: =E28-(F28+G28) -> 14327.52 | I28: 0
A29: ='04-221Master'!F25 -> Technology Analyst | B29: IT SUPPORTIVE SERICE | C29: 0 | D29: 1 | E29: ='04-221Master'!Y25 -> 98816 | F29: ='04-221Master'!Z25 -> 59289.6 | G29: ='04-221Master'!AD25 -> 23715.84 | H29: =E29-(F29+G29) -> 15810.56 | I29: 0
A30: ='04-221Master'!F26 -> SENIOR HADOOP ADMIN | B30: IT SUPPORTIVE SERICE | C30: 0 | D30: 1 | E30: ='04-221Master'!Y26 -> 59886 | F30: ='04-221Master'!Z26 -> 26349.84 | G30: ='04-221Master'!AD26 -> 10539.936 | H30: =E30-(F30+G30) -> 22996.224 | I30: 0
A31: ='04-221Master'!F27 -> SENIOR APPLICATION CONSULTANT | B31: IT SUPPORTIVE SERICE | C31: 0 | D31: 1 | E31: ='04-221Master'!Y27 -> 35786 | F31: ='04-221Master'!Z27 -> 21471.6 | G31: ='04-221Master'!AD27 -> 8588.64 | H31: =E31-(F31+G31) -> 5725.76 | I31: 0
A32: ='04-221Master'!F28 -> Sr.Cloud Network Engineer | B32: IT SUPPORTIVE SERICE | C32: 0 | D32: 1 | E32: ='04-221Master'!Y28 -> 128477 | F32: ='04-221Master'!Z28 -> 77086.2 | G32: ='04-221Master'!AD28 -> 30834.48 | H32: =E32-(F32+G32) -> 20556.32 | I32: 0
A33: ='04-221Master'!F29 -> Senior network security analyst. | B33: IT SUPPORTIVE SERICE | C33: 0 | D33: 1 | E33: ='04-221Master'!Y29 -> 74716 | F33: ='04-221Master'!Z29 -> 44829.6 | G33: ='04-221Master'!AD29 -> 17931.84 | H33: =E33-(F33+G33) -> 11954.56 | I33: 0
... A35: ='04-221Master'!F31 -> SAP Basis consultant | B35: IT SUPPORTIVE SERICE | C35: 0 | D35: 1 | E35: ='04-221Master'!Y31 -> 38567 | F35: ='04-221Master'!Z31 -> 23140.2 | G35: ='04-221Master'!AD31 -> 9256.08 | H35: =E35-(F35+G35) -> 6170.72 | I35: 0
A36: ='04-221Master'!G32 -> H No 53,Near Durga mandir,at po sarra,gram sarra,tahsil multai dist bethul,Madhya pradesh 460661 | B36: IT SUPPORTIVE SERICE | C36: 0 | D36: 1 | E36: ='04-221Master'!Y32 -> 80278 | F36: ='04-221Master'!Z32 -> 48166.8 | G36: ='04-221Master'!AD32 -> 19266.72 | H36: =E36-(F36+G36) -> 12844.48 | I36: 0
A37: ='04-221Master'!F33 -> Network security consultant | B37: IT SUPPORTIVE SERICE | C37: 0 | D37: 1 | E37: ='04-221Master'!Y33 -> 112719 | F37: ='04-221Master'!Z33 -> 67631.4 | G37: ='04-221Master'!AD33 -> 27052.56 | H37: =E37-(F37+G37) -> 18035.04 | I37: 0
A38: ='04-221Master'!F34 -> Network security consultant | B38: IT SUPPORTIVE SERICE | C38: 1 | D38: 0 | E38: ='04-221Master'!Y34 -> 66374 | F38: ='04-221Master'!Z34 -> 39824.4 | G38: ='04-221Master'!AD34 -> 15929.76 | H38: =E38-(F38+G38) -> 10619.84 | I38: 0
A39: ='04-221Master'!F35 -> CONSULTANT | B39: IT SUPPORTIVE SERICE | C39: 0 | D39: 1 | E39: ='04-221Master'!Y35 -> 108085 | F39: ='04-221Master'!Z35 -> 64851 | G39: ='04-221Master'!AD35 -> 25940.4 | H39: =E39-(F39+G39) -> 17293.6 | I39: 0
A40: ='04-221Master'!F36 -> Network Security Engineer | B40: IT SUPPORTIVE SERICE | C40: 1 | D40: 0 | E40: ='04-221Master'!Y36 -> 62667 | F40: ='04-221Master'!Z36 -> 33840.18 | G40: ='04-221Master'!AD36 -> 13536.072 | H40: =E40-(F40+G40) -> 15290.748 | I40: 0
C41: =SUM(C20:C40) -> 4 | D41: =SUM(D20:D40) -> 17
E48: Signature of the Contractor with Seal

Sheet MH_Must Roll
A1: Form No. II
A2: [M. W. Rules under Maharashtra Contract Labour (Regulation and Abolition)1963 Rule 27 (I)]
A3: Muster Roll cum Wages Register for the month of APRIL 2022
A4: Name and Address of Contractor : BURGEON IT SERVICES PVT.LTD. SIRI MANSION LIG 436 DR.A S RAO NAGAR,HYDERABAD 500 060
G5: Working Hours | I5: Interval for Rest | K5: No. of Hours Worked
A6: Sl.No. | B6: Full Name of Employee | C6: Date of Birth | D6: Gender | E6: Date of Entry into Service | F6: Nature of Work & Designation | G6: From | H6: To | I6: From | J6: To | K6: 1 | L6: 2 | M6: 3 | N6: 4 | O6: 5 | P6: 6 | Q6: 7 | R6: 8 | S6: 9 | T6: 10 | U6: 11 | V6: 12 | W6: 13 | X6: 14 | Y6: 15 | Z6: 16 | AA6: 17 | AB6: 18 | AC6: 19 | AD6: 20 | AE6: 21 | AF6: 22 | AG6: 23 | AH6: 24 | AI6: 25 | AJ6: 26 | AK6: 27 | AL6: 28 | AM6: 29 | AN6: 30 | AO6: MONTH DAYS
A7: 1 | B7: ='04-221Master'!B16 -> Venegella Kanaka durga | C7: ='04-221Master'!C16 -> 31669 | D7: ='04-221Master'!D16 -> Female | E7: ='04-221Master'!N16 -> 44021 | F7: ='04-221Master'!F16 -> Senior Software Engineer | K7: P | L7: WO | M7: WO | N7: P | O7: P | P7: P | Q7: P | R7: P | S7: WO | T7: WO | U7: EL | V7: P | W7: P | X7: P | Y7: H | Z7: WO | AA7: WO | AB7: P | AC7: P | AD7: P | AE7: P | AF7: P | AG7: WO | AH7: WO | AI7: P | AJ7: P | AK7: P | AL7: P | AM7: P | AN7: WO | AO7: ='04-221Master'!W16 -> 30
A8: 2 | B8: ='04-221Master'!B17 -> Moeenahmed Shakilahmed Shaikh | C8: ='04-221Master'!C17 -> 30310 | D8: ='04-221Master'!D17 -> MALE | E8: ='04-221Master'!N17 -> 44041 | F8: ='04-221Master'!F17 -> Splunk Developer | K8: P | L8: WO | M8: WO | N8: P | O8: P | P8: P | Q8: P | R8: P | S8: WO | T8: WO | U8: P | V8: P | W8: P | X8: P | Y8: H | Z8: WO | AA8: WO | AB8: P | AC8: P | AD8: P | AE8: P | AF8: P | AG8: WO | AH8: WO | AI8: P | AJ8: P | AK8: P | AL8: P | AM8: P | AN8: WO | AO8: ='04-221Master'!W17 -> 30
A9: 3 | B9: ='04-221Master'!B18 -> Yarramaddu Raveendra Reddy | C9: ='04-221Master'!C18 -> 32972 | D9: ='04-221Master'!D18 -> Male | E9: ='04-221Master'!N18 -> 44335 | F9: ='04-221Master'!F18 -> Sr Citrix Administrator | K9: P | L9: WO | M9: WO | N9: EL | O9: P | P9: P | Q9: P | R9: P | S9: WO | T9: WO | U9: P | V9: P | W9: P | X9: P | Y9: H | Z9: WO | AA9: WO | AB9: P | AC9: P | AD9: P | AE9: P | AF9: P | AG9: WO | AH9: WO | AI9: P | AJ9: P | AK9: P | AL9: P | AM9: P | AN9: WO | AO9: ='04-221Master'!W18 -> 30
A10: 4 | B10: ='04-221Master'!B19 -> Chitra Kulkarni | C10: ='04-221Master'!C19 -> 32113 | D10: ='04-221Master'!D19 -> Female | E10: ='04-221Master'!N19 -> 44390 | F10: ='04-221Master'!F19 -> Project Manager | K10: P | L10: WO | M10: WO | N10: P | O10: P | P10: P | Q10: P | R10: P | S10: WO | T10: WO | U10: P | V10: P | W10: P | X10: P | Y10: H | Z10: WO | AA10: WO | AB10: EL | AC10: P | AD10: P | AE10: P | AF10: P | AG10: WO | AH10: WO | AI10: P | AJ10: P | AK10: P | AL10: P | AM10: P | AN10: WO | AO10: ='04-221Master'!W19 -> 30
A11: 5 | B11: ='04-221Master'!B20 -> Sunnapalli Anil | C11: ='04-221Master'!C20 -> 32813 | D11: ='04-221Master'!D20 -> Male | E11: ='04-221Master'!N20 -> 44409 | F11: ='04-221Master'!F20 -> Sr. Software Engineer | K11: P | L11: WO | M11: WO | N11: P | O11: P | P11: P | Q11: P | R11: P | S11: WO | T11: WO | U11: P | V11: P | W11: P | X11: P | Y11: H | Z11: WO | AA11: WO | AB11: P | AC11: P | AD11: P | AE11: P | AF11: P | AG11: WO | AH11: WO | AI11: P | AJ11: P | AK11: P | AL11: P | AM11: P | AN11: WO | AO11: ='04-221Master'!W20 -> 30
A12: 6 | B12: ='04-221Master'!B21 -> Himanshu Anand | C12: ='04-221Master'!C21 -> 31328 | D12: ='04-221Master'!D21 -> Male | E12: ='04-221Master'!N21 -> 44432 | F12: ='04-221Master'!F21 -> Sr. DBA / Sr. Administrator | K12: P | L12: WO | M12: WO | N12: P | O12: P | P12: P | Q12: P | R12: P | S12: WO | T12: WO | U12: P | V12: P | W12: P | X12: P | Y12: H | Z12: WO | AA12: WO | AB12: P | AC12: P | AD12: P | AE12: P | AF12: P | AG12: WO | AH12: WO | AI12: P | AJ12: P | AK12: P | AL12: P | AM12: P | AN12: WO | AO12: ='04-221Master'!W21 -> 30
A13: 7 | B13: ='04-221Master'!B22 -> Kanchupati Kondaiah | C13: ='04-221Master'!C22 -> 32669 | D13: ='04-221Master'!D22 -> Male | E13: ='04-221Master'!N22 -> 44434 | F13: ='04-221Master'!F22 -> SQL DATABASE ADMINISTRATOR | K13: P | L13: WO | M13: WO | N13: P | O13: P | P13: P | Q13: P | R13: P | S13: WO | T13: WO | U13: P | V13: P | W13: P | X13: P | Y13: H | Z13: WO | AA13: WO | AB13: P | AC13: P | AD13: P | AE13: P | AF13: EL | AG13: WO | AH13: WO | AI13: P | AJ13: P | AK13: P | AL13: P | AM13: P | AN13: WO | AO13: ='04-221Master'!W22 -> 30
A14: 8 | B14: ='04-221Master'!B23 -> Santosh Patel | C14: ='04-221Master'!C23 -> 32336 | D14: ='04-221Master'!D23 -> Male | E14: ='04-221Master'!N23 -> 44438 | F14: ='04-221Master'!F23 -> Senior Support Engineer | K14: P | L14: WO | M14: WO | N14: P | O14: P | P14: P | Q14: P | R14: P | S14: WO | T14: WO | U14: P | V14: P | W14: P | X14: P | Y14: H | Z14: WO | AA14: WO | AB14: P | AC14: P | AD14: P | AE14: P | AF14: P | AG14: WO | AH14: WO | AI14: P | AJ14: P | AK14: P | AL14: P | AM14: P | AN14: WO | AO14: ='04-221Master'!W23 -> 30
A15: 9 | B15: ='04-221Master'!B24 -> Basweshwar Pawar | C15: ='04-221Master'!C24 -> 31899 | D15: ='04-221Master'!D24 -> Male | E15: ='04-221Master'!N24 -> 44446 | F15: ='04-221Master'!F24 -> Lead PMO | K15: P | L15: WO | M15: WO | N15: P | O15: P | P15: P | Q15: P | R15: P | S15: WO | T15: WO | U15: P | V15: P | W15: P | X15: P | Y15: H | Z15: WO | AA15: WO | AB15: P | AC15: P | AD15: P | AE15: P | AF15: P | AG15: WO | AH15: WO | AI15: P | AJ15: P | AK15: P | AL15: P | AM15: P | AN15: WO | AO15: ='04-221Master'!W24 -> 30
A16: 10 | B16: ='04-221Master'!B25 -> Hemanth Mishra | C16: ='04-221Master'!C25 -> 17/10/1976 | D16: ='04-221Master'!D25 -> MALE | E16: ='04-221Master'!N25 -> 44490 | F16: ='04-221Master'!F25 -> Technology Analyst | K16: EL | L16: WO | M16: WO | N16: P | O16: P | P16: P | Q16: P | R16: P | S16: WO | T16: WO | U16: P | V16: P | W16: P | X16: P | Y16: H | Z16: WO | AA16: WO | AB16: P | AC16: P | AD16: P | AE16: P | AF16: P | AG16: WO | AH16: WO | AI16: P | AJ16: P | AK16: P | AL16: P | AM16: P | AN16: WO | AO16: ='04-221Master'!W25 -> 30
A17: 11 | B17: ='04-221Master'!B26 -> FAZALAHMED IRKAL | C17: ='04-221Master'!C26 -> 32932 | D17: ='04-221Master'!D26 -> MALE | E17: ='04-221Master'!N26 -> 44494 | F17: ='04-221Master'!F26 -> SENIOR HADOOP ADMIN | K17: P | L17: WO | M17: WO | N17: P | O17: P | P17: P | Q17: P | R17: P | S17: WO | T17: WO | U17: P | V17: P | W17: P | X17: P | Y17: H | Z17: WO | AA17: WO | AB17: P | AC17: P | AD17: P | AE17: P | AF17: P | AO17: ='04-221Master'!W26 -> 22
A18: 12 | B18: ='04-221Master'!B27 -> SUKRUTH YELLAMBOTLA | C18: ='04-221Master'!C27 -> 34146 | D18: ='04-221Master'!D27 -> MALE | E18: ='04-221Master'!N27 -> 44509 | F18: ='04-221Master'!F27 -> SENIOR APPLICATION CONSULTANT | K18: P | L18: WO | M18: WO | N18: P | O18: P | P18: P | Q18: P | R18: P | S18: WO | T18: WO | U18: P | V18: P | W18: P | X18: P | Y18: H | Z18: WO | AA18: WO | AB18: P | AC18: P | AD18: P | AE18: P | AF18: P | AG18: WO | AH18: WO | AI18: P | AJ18: P | AK18: P | AL18: P | AM18: EL | AN18: WO | AO18: ='04-221Master'!W27 -> 30
A19: 13 | B19: ='04-221Master'!B28 -> Ajay Singh | C19: ='04-221Master'!C28 -> 33635 | D19: ='04-221Master'!D28 -> MALE | E19: ='04-221Master'!N28 -> 44538 | F19: ='04-221Master'!F28 -> Sr.Cloud Network Engineer | K19: P | L19: WO | M19: WO | N19: P | O19: P | P19: P | Q19: P | R19: P | S19: WO | T19: WO | U19: P | V19: P | W19: P | X19: EL | Y19: H | Z19: WO | AA19: WO | AB19: P | AC19: P | AD19: P | AE19: P | AF19: P | AG19: WO | AH19: WO | AI19: P | AJ19: P | AK19: P | AL19: P | AM19: P | AN19: WO | AO19: ='04-221Master'!W28 -> 30
A20: 14 | B20: ='04-221Master'!B29 -> Rajesh Dhumal | C20: ='04-221Master'!C29 -> 15-03-1990 | D20: ='04-221Master'!D29 -> MALE | E20: ='04-221Master'!N29 -> 44579 | F20: ='04-221Master'!F29 -> Senior network security analyst. | K20: P | L20: WO | M20: WO | N20: P | O20: P | P20: P | Q20: P | R20: P | S20: WO | T20: WO | U20: P | V20: P | W20: P | X20: P | Y20: H | Z20: WO | AA20: WO | AB20: P | AC20: P | AD20: P | AE20: P | AF20: P | AG20: WO | AH20: WO | AI20: P | AJ20: P | AK20: P | AL20: P | AM20: P | AN20: WO | AO20: ='04-221Master'!W29 -> 30
A21: 15 | B21: ='04-221Master'!B30 -> Ajay Pal Singh | C21: ='04-221Master'!C30 -> 31491 | D21: ='04-221Master'!D30 -> MALE | E21: ='04-221Master'!N30 -> 44601 | F21: ='04-221Master'!F30 -> Network security consultant | K21: P | L21: WO | M21: WO | N21: P | O21: P | P21: P | Q21: P | R21: P | S21: WO | T21: WO | U21: P | V21: P | W21: P | X21: P | Y21: H | Z21: WO | AA21: WO | AB21: EL | AC21: P | AD21: P | AE21: P | AF21: P | AG21: WO | AH21: WO | AI21: P | AJ21: P | AK21: P | AL21: P | AM21: P | AN21: WO | AO21: ='04-221Master'!W30 -> 30
A22: 16 | B22: ='04-221Master'!B31 -> PAVANKUMAR | C22: ='04-221Master'!C31 -> 35211 | D22: ='04-221Master'!D31 -> MALE | E22: ='04-221Master'!N31 -> 44602 | F22: ='04-221Master'!F31 -> SAP Basis consultant | K22: P | L22: WO | M22: WO | N22: P | O22: P | P22: P | Q22: P | R22: P | S22: WO | T22: WO | U22: P | V22: P | W22: P | X22: P | Y22: H | Z22: WO | AA22: WO | AB22: P | AC22: P | AD22: P | AE22: P | AF22: P | AG22: WO | AH22: WO | AI22: P | AJ22: P | AK22: P | AL22: P | AM22: P | AN22: WO | AO22: ='04-221Master'!W31 -> 30
A23: 17 | B23: ='04-221Master'!B32 -> Rahul Suryawanshi | C23: ='04-221Master'!C32 -> 35236 | D23: ='04-221Master'!D32 -> MALE | E23: ='04-221Master'!N32 -> 44624 | F23: ='04-221Master'!F32 -> Sr.Network security Analyst | K23: P | L23: WO | M23: WO | N23: P | O23: P | P23: P | Q23: P | R23: EL | S23: WO | T23: WO | U23: P | V23: P | W23: P | X23: P | Y23: H | Z23: WO | AA23: WO | AB23: P | AC23: P | AD23: P | AE23: P | AF23: P | AG23: WO | AH23: WO | AI23: P | AJ23: P | AK23: P | AL23: P | AM23: P | AN23: WO | AO23: ='04-221Master'!W32 -> 30
A24: 18 | B24: ='04-221Master'!B33 -> Shantanu Patankar | C24: ='04-221Master'!C33 -> 32959 | D24: ='04-221Master'!D33 -> MALE | E24: ='04-221Master'!N33 -> 44629 | F24: ='04-221Master'!F33 -> Network security consultant | K24: P | L24: WO | M24: WO | N24: P | O24: P | P24: P | Q24: P | R24: P | S24: WO | T24: WO | U24: P | V24: P | W24: P | X24: P | Y24: H | Z24: WO | AA24: WO | AB24: P | AC24: P | AD24: P | AE24: P | AF24: P | AG24: WO | AH24: WO | AI24: P | AJ24: P | AK24: P | AL24: P | AM24: P | AN24: WO | AO24: ='04-221Master'!W33 -> 30
A25: 19 | B25: ='04-221Master'!B34 -> Varalakshmi Vijay | C25: ='04-221Master'!C34 -> 29711 | D25: ='04-221Master'!D34 -> Female | E25: ='04-221Master'!N34 -> 44641 | F25: ='04-221Master'!F34 -> Network security consultant | K25: P | L25: WO | M25: WO | N25: P | O25: P | P25: P | Q25: P | R25: P | S25: WO | T25: WO | U25: P | V25: P | W25: P | X25: P | Y25: H | Z25: WO | AA25: WO | AB25: P | AC25: P | AD25: P | AE25: P | AF25: P | AG25: WO | AH25: WO | AI25: P | AJ25: P | AK25: P | AL25: P | AM25: P | AN25: WO | AO25: ='04-221Master'!W34 -> 30
A26: 20 | B26: ='04-221Master'!B35 -> OMPRAKASH PURI | C26: ='04-221Master'!C35 -> 31427 | D26: ='04-221Master'!D35 -> Male | E26: ='04-221Master'!N35 -> 44652 | F26: ='04-221Master'!F35 -> CONSULTANT | K26: P | L26: WO | M26: WO | N26: P | O26: P | P26: P | Q26: P | R26: P | S26: WO | T26: WO | U26: P | V26: P | W26: P | X26: P | Y26: H | Z26: WO | AA26: WO | AB26: P | AC26: P | AD26: P | AE26: P | AF26: P | AG26: WO | AH26: WO | AI26: P | AJ26: P | AK26: P | AL26: P | AM26: P | AN26: WO | AO26: ='04-221Master'!W35 -> 30
A27: 21 | B27: ='04-221Master'!B36 -> DiptiRanjan Dikhit | C27: ='04-221Master'!C36 -> 31991 | D27: ='04-221Master'!D36 -> Female | E27: ='04-221Master'!N36 -> 44655 | F27: ='04-221Master'!F36 -> Network Security Engineer | N27: P | O27: P | P27: P | Q27: P | R27: P | S27: WO | T27: WO | U27: P | V27: P | W27: P | X27: P | Y27: H | Z27: WO | AA27: WO | AB27: P | AC27: P | AD27: P | AE27: P | AF27: P | AG27: WO | AH27: WO | AI27: P | AJ27: P | AK27: P | AL27: P | AM27: P | AN27: WO | AO27: ='04-221Master'!W36 -> 27
AO28: =SUM(AO7:AO27) -> 619
AD36: Signature of the Contractor with Seal

Sheet Form M Lea Reg
A1: FORM M- LEAVE REGISTER
A3: (Vide Rule 78(1) (a) (i) of Maharastra Shops&Establishment Act /Maharastra.Rules 1988
A4: Name of the Employer / Establishment: | E4: Name of the Employee:
B5: ='04-221Master'!F5 -> Burgeon IT Services Pvt.Ltd. | G5: ='04-221Master'!B16 -> Venegella Kanaka durga
B6: ='04-221Master'!F6 -> Siri Mansion LIGB 436 Dr.A S Rao Nagar,Hyderabad
A7: Description of the dapartment if applicable: | E7: Date of entry into service | G7: ='04-221Master'!N16 -> 44021
C8: ='04-221Master'!F8 -> IT SUPPORTIVE SERVICES& Pune SEZ Unit-1
A11: S.No | B11: Accumalation of Leave | D11: Leave allowed | F11: Balance of Leave Carried Over | G11: Payment of Leave made on | I11: Refusal of Leave | L11: Payment of Leave on Discharge of an employee quitting employment if a admissible
A13: 1 | F13: 6 | I13: 9 | L13: 9
B14: Leave due on | C14: No of Days | D14: From | E14: To | G14: 1st month | H14: 2nd month | I14: Date of Application | J14: Date of Refusal | K14: Amount of Leave refused | L14: Date of Discharge | M14: Date of Amount Paid | N14: Signature or Left hand thumb impression of employee
A17: JAN'22 | B17: 1.5 | C17: 1 | D17: 44575 | E17: 44575 | F17: 18.5 | I17: NO | J17: NO | K17: NO
A18: FEB'22 | B18: 1.5 | C18: 1 | D18: 44603 | E18: 44603 | F18: =F17+B18-C18 -> 19 | I18: NO | J18: NO | K18: NO
A19: MAR,22 | B19: 1.5 | C19: 0 | D19: 0 | E19: 0 | F19: =F18+B19-C19 -> 20.5 | I19: NO | J19: NO | K19: NO
A20: APRIL'22 | B20: 1.5 | C20: 1 | D20: 44662 | E20: 44662 | F20: =F19+B20-C20 -> 21 | I20: NO | J20: NO | K20: NO | O20: 1
G44: Signature of the Contractor with Seal
A62: FORM M- LEAVE REGISTER
A64: (Vide Rule 78(1) (a) (i) of Maharastra Shops&Establishment Act /Maharastra.Rules 1988
A65: Name of the Employer / Establishment: | E65: Name of the Employee:
B66: ='04-221Master'!F5 -> Burgeon IT Services Pvt.Ltd. | G66: ='04-221Master'!B17 -> Moeenahmed Shakilahmed Shaikh
B67: ='04-221Master'!F6 -> Siri Mansion LIGB 436 Dr.A S Rao Nagar,Hyderabad
A68: Description of the dapartment if applicable: | E68: Date of entry into service | G68: ='04-221Master'!N17 -> 44041
C69: ='04-221Master'!F8 -> IT SUPPORTIVE SERVICES& Pune SEZ Unit-1
A72: S.No | B72: Accumalation of Leave | D72: Leave allowed | F72: Balance of Leave Carried Over | G72: Payment of Leave made on | I72: Refusal of Leave | L72: Payment of Leave on Discharge of an employee quitting employment if a admissible
A74: 1 | F74: 6 | I74: 9 | L74: 9
B75: Leave due on | C75: No of Days | D75: From | E75: To | G75: 1st month | H75: 2nd month | I75: Date of Application | J75: Date of Refusal | K75: Amount of Leave refused | L75: Date of Discharge | M75: Date of Amount Paid | N75: Signature or Left hand thumb impression of employee
A78: JAN'22 | B78: 1.5 | F78: 24 | I78: NO | J78: NO | K78: NO
A79: FEB'22 | B79: 1.5 | C79: 0 | D79: 0 | E79: 0 | F79: =F78+B79-C79 -> 25.5 | I79: NO | J79: NO | K79: NO
A80: MAR,22 | B80: 1.5 | C80: 1 | D80: 44627 | E80: 44627 | F80: =F79+B80-C80 -> 26 | I80: NO | J80: NO | K80: NO
A81: APRIL'22 | B81: 1.5 | C81: 0 | D81: 0 | E81: 0 | F81: =F80+B81-C81 -> 27.5 | I81: NO | J81: NO | K81: NO | O81: 2
G105: Signature of the Contractor with Seal
A123: FORM M- LEAVE REGISTER
A125: (Vide Rule 78(1) (a) (i) of Maharastra Shops&Establishment Act /Maharastra.Rules 1988
A126: Name of the Employer / Establishment: | E126: Name of the Employee:
B127: Burgeon IT Services Pvt.Ltd. | G127: ='04-221Master'!B18 -> Yarramaddu Raveendra Reddy
B128: Siri Mansion LIGB 436 Dr.A S Rao Nagar,Hyderabad
A129: Description of the dapartment if applicable: | E129: Date of entry into service | G129: ='04-221Master'!N18 -> 44335
C130: ='04-221Master'!F308 -> 0
A133: S.No | B133: Accumalation of Leave | D133: Leave allowed | F133: Balance of Leave Carried Over | G133: Payment of Leave made on | I133: Refusal of Leave | L133: Payment of Leave on Discharge of an employee quitting employment if a admissible
A135: 1 | F135: 6 | I135: 9 | L135: 9
B136: Leave due on | C136: No of Days | D136: From | E136: To | G136: 1st month | H136: 2nd month | I136: Date of Application | J136: Date of Refusal | K136: Amount of Leave refused | L136: Date of Discharge | M136: Date of Amount Paid | N136: Signature or Left hand thumb impression of employee
A138: JAN'22 | B138: 1.5 | F138: 5 | I138: NO | J138: NO | K138: NO
A139: FEB'22 | B139: 1.5 | C139: 1 | D139: 44596 | E139: 44596 | F139: =F138+B139-C139 -> 5.5 | I139: NO | J139: NO | K139: NO
A140: MAR'22 | B140: 1.5 | C140: 0 | D140: 0 | E140: 0 | F140: =F139+B140-C140 -> 7 | I140: NO | J140: NO | K140: NO
A141: APRIL'22 | B141: 1.5 | C141: 1 | D141: 44655 | E141: 44655 | F141: =F140+B141-C141 -> 7.5 | I141: NO | J141: NO | K141: NO | O141: 3
G164: Signature of the Contractor with Seal
A184: FORM M- LEAVE REGISTER
A186: (Vide Rule 78(1) (a) (i) of Maharastra Shops&Establishment Act /Maharastra.Rules 1988
A187: Name of the Employer / Establishment: | E187: Name of the Employee:
B188: Burgeon IT Services Pvt.Ltd. | G188: ='04-221Master'!B19 -> Chitra Kulkarni
B189: Siri Mansion LIGB 436 Dr.A S Rao Nagar,Hyderabad
A190: Description of the dapartment if applicable: | E190: Date of entry into service | G190: ='04-221Master'!N19 -> 44390
C191: ='04-221Master'!F355 -> 0
A194: S.No | B194: Accumalation of Leave | D194: Leave allowed | F194: Balance of Leave Carried Over | G194: Payment of Leave made on | I194: Refusal of Leave | L194: Payment of Leave on Discharge of an employee quitting employment if a admissible
A196: 1 | F196: 6 | I196: 9 | L196: 9
B197: Leave due on | C197: No of Days | D197: From | E197: To | G197: 1st month | H197: 2nd month | I197: Date of Application | J197: Date of Refusal | K197: Amount of Leave refused | L197: Date of Discharge | M197: Date of Amount Paid | N197: Signature or Left hand thumb impression of employee
A201: JAN'22 | B201: 1.5 | F201: 5.5 | I201: NO | J201: NO | K201: NO
A202: FEB'22 | B202: 1.5 | C202: 0 | D202: 0 | E202: 0 | F202: =F201+B202-C202 -> 7 | I202: NO | J202: NO | K202: NO
A203: MAR'22 | B203: 1.5 | C203: 0 | D203: 0 | E203: 0 | F203: =F202+B203-C203 -> 8.5 | I203: NO | J203: NO | K203: NO
A204: APRIL'22 | B204: 1.5 | C204: 1 | D204: 44669 | E204: 44669 | F204: =F203+B204-C204 -> 9 | I204: NO | J204: NO | K204: NO | O204: 4
G225: Signature of the Contractor with Seal
A245: FORM M- LEAVE REGISTER
A247: (Vide Rule 78(1) (a) (i) of Maharastra Shops&Establishment Act /Maharastra.Rules 1988
A248: Name of the Employer / Establishment: | E248: Name of the Employee:
B249: Burgeon IT Services Pvt.Ltd. | G249: ='04-221Master'!B20 -> Sunnapalli Anil
B250: Siri Mansion LIGB 436 Dr.A S Rao Nagar,Hyderabad
A251: Description of the dapartment if applicable: | E251: Date of entry into service | G251: ='04-221Master'!N20 -> 44409
C252: ='04-221Master'!F401 -> 0
A255: S.No | B255: Accumalation of Leave | D255: Leave allowed | F255: Balance of Leave Carried Over | G255: Payment of Leave made on | I255: Refusal of Leave | L255: Payment of Leave on Discharge of an employee quitting employment if a admissible
A257: 1 | F257: 6 | I257: 9 | L257: 9
B258: Leave due on | C258: No of Days | D258: From | E258: To | G258: 1st month | H258: 2nd month | I258: Date of Application | J258: Date of Refusal | K258: Amount of Leave refused | L258: Date of Discharge | M258: Date of Amount Paid | N258: Signature or Left hand thumb impression of employee
A260: JAN'22 | B260: 1.5 | C260: 1 | D260: 44564 | E260: 44564 | F260: 6.5 | I260: NO | J260: NO | K260: NO
A261: FEB'22 | B261: 1.5 | C261: 1 | D261: 44603 | E261: 44603 | F261: =F260+B261-C261 -> 7 | I261: NO | J261: NO | K261: NO
A262: MAR'22 | B262: 1.5 | C262: 0 | D262: 0 | E262: 0 | F262: =F261+B262-C262 -> 8.5 | I262: NO | J262: NO | K262: NO
A263: APRIL'22 | B263: 1.5 | C263: 0 | D263: 0 | E263: 0 | F263: =F262+B263-C263 -> 10 | I263: NO | J263: NO | K263: NO | O263: 5
G286: Signature of the Contractor with Seal
A306: FORM M- LEAVE REGISTER
A308: (Vide Rule 78(1) (a) (i) of Maharastra Shops&Establishment Act /Maharastra.Rules 1988
A309: Name of the Employer / Establishment: | E309: Name of the Employee:
B310: Burgeon IT Services Pvt.Ltd. | G310: ='04-221Master'!B21 -> Himanshu Anand
B311: Siri Mansion LIGB 436 Dr.A S Rao Nagar,Hyderabad
A312: Description of the dapartment if applicable: | E312: Date of entry into service | G312: ='04-221Master'!N21 -> 44432
C313: ='04-221Master'!F21 -> Sr. DBA / Sr. Administrator
A316: S.No | B316: Accumalation of Leave | D316: Leave allowed | F316: Balance of Leave Carried Over | G316: Payment of Leave made on | I316: Refusal of Leave | L316: Payment of Leave on Discharge of an employee quitting employment if a admissible
A318: 1 | F318: 6 | I318: 9 | L318: 9
B319: Leave due on | C319: No of Days | D319: From | E319: To | G319: 1st month | H319: 2nd month | I319: Date of Application | J319: Date of Refusal | K319: Amount of Leave refused | L319: Date of Discharge | M319: Date of Amount Paid | N319: Signature or Left hand thumb impression of employee
A321: JAN'22 | B321: 1.5 | F321: 5.5 | I321: NO | J321: NO | K321: NO
A322: FEB'22 | B322: 1.5 | C322: 0 | D322: 0 | E322: 0 | F322: =F321+B322-C322 -> 7 | I322: NO | J322: NO | K322: NO
A323: MAR'22 | B323: 1.5 | C323: 0 | D323: 0 | E323: 0 | F323: =F322+B323-C323 -> 8.5 | I323: NO | J323: NO | K323: NO
A324: APRIL'22 | B324: 1.5 | C324: 0 | D324: 0 | E324: 0 | F324: =F323+B324-C324 -> 10 | I324: NO | J324: NO | K324: NO | O324: 6
G347: Signature of the Contractor with Seal
A364: FORM M- LEAVE REGISTER
A366: (Vide Rule 78(1) (a) (i) of Maharastra Shops&Establishment Act /Maharastra.Rules 1988
A367: Name of the Employer / Establishment: | E367: Name of the Employee:
B368: Burgeon IT Services Pvt.Ltd. | G368: ='04-221Master'!B22 -> Kanchupati Kondaiah
B369: Siri Mansion LIGB 436 Dr.A S Rao Nagar,Hyderabad
A370: Description of the dapartment if applicable: | E370: Date of entry into service | G370: ='04-221Master'!N22 -> 44434
C371: ='04-221Master'!F22 -> SQL DATABASE ADMINISTRATOR
A374: S.No | B374: Accumalation of Leave | D374: Leave allowed | F374: Balance of Leave Carried Over | G374: Payment of Leave made on | I374: Refusal of Leave | L374: Payment of Leave on Discharge of an employee quitting employment if a admissible
A376: 1 | F376: 6 | I376: 9 | L376: 9
B377: Leave due on | C377: No of Days | D377: From | E377: To | G377: 1st month | H377: 2nd month | I377: Date of Application | J377: Date of Refusal | K377: Amount of Leave refused | L377: Date of Discharge | M377: Date of Amount Paid | N377: Signature or Left hand thumb impression of employee
...

Sheet MH_Regr of Wages
A2: Form No. II
A3: [M. W. Rules under Maharashtra Contract Labour (Regulation and Abolition)1963 Rule 27 (I)]
A4: Muster Roll cum Wages Register for the month of APRIL 2022
A5: Name and Address of Contractor : BURGEON IT SERVICES PVT.LTD. SIRI MANSION LIG 436 DR.A S RAO NAGAR,HYDERABAD 500 060
O6: Deductions | V6: Leave with Wages
A7: Sl.No. | B7: Deputy ID | C7: Employee Code | D7: Name of the Workmen | E7: Minimum Rate of Wages Payable Basic | F7: Actual Rate of Wages Payable HRA | G7: Conveyance | H7: Bonus | I7: Special Allowances | J7: Medical Allowances | K7: Total Production in Case of Piece Rate Other Allow | L7: Normal Earnings | M7: Overtime Earnings | N7: Gross Wages Payable | O7: Income Tax | P7: Other Deduction(Med) | Q7: Proff / Income Tax | R7: PF | S7: ESIC | T7: Total Deduction | U7: Net Wages Paid | V7: Previous Balance | W7: Further Enjoyed | X7: Refused | Y7: Accumulated | Z7: Date Payment of Wages | AA7: Signature or the Thumb Impression of the Employee | AB7: Account Number
A8: 1 | D8: ='04-221Master'!B16 -> Venegella Kanaka durga | E8: ='04-221Master'!Z16 -> 45385.8 | F8: ='04-221Master'!AD16 -> 18154.32 | G8: ='04-221Master'!AE16 -> 2083 | H8: ='04-221Master'!AI16 -> 1554.609 | I8: ='04-221Master'!AG16 -> 8049.88 | J8: ='04-221Master'!AF16 -> 2083 | L8: ='04-221Master'!AH16 -> 75756 | M8: 0 | N8: ='04-221Master'!AM16 -> 83275.816 | O8: ='04-221Master'!AQ16 -> 0 | P8: ='04-221Master'!AR16 -> 391.78785 | Q8: ='04-221Master'!AP16 -> 200 | R8: ='04-221Master'!AO16 -> 1800 | S8: ='04-221Master'!AN16 -> 0 | T8: ='04-221Master'!AS16 -> 2391.7878 | U8: ='04-221Master'!AT16 -> 80884.028 | V8: 20.5 | W8: 1 | Y8: 21 | Z8: ='04-221Master'!AU16 -> 05.05.2022 | AA8: ='04-221Master'!AV16 -> KVBL | AB8: ='04-221Master'!AW16 -> A/C'1498155000027380
A9: 2 | D9: ='04-221Master'!B17 -> Moeenahmed Shakilahmed Shaikh | E9: ='04-221Master'!Z17 -> 89877 | F9: ='04-221Master'!AD17 -> 35950.8 | G9: ='04-221Master'!AE17 -> 2083 | H9: ='04-221Master'!AI17 -> 1554.609 | I9: ='04-221Master'!AG17 -> 19914.2 | J9: ='04-221Master'!AF17 -> 2083 | L9: ='04-221Master'!AH17 -> 149908 | M9: 1 | N9: ='04-221Master'!AM17 -> 163275.44 | O9: ='04-221Master'!AQ17 -> 0 | P9: ='04-221Master'!AR17 -> 440.76133 | Q9: ='04-221Master'!AP17 -> 200 | R9: ='04-221Master'!AO17 -> 6000 | S9: ='04-221Master'!AN17 -> 0 | T9: ='04-221Master'!AS17 -> 6640.7613 | U9: ='04-221Master'!AT17 -> 156634.68 | V9: 26 | W9: 0 | Y9: 27.5 | Z9: ='04-221Master'!AU17 -> 05.05.2022 | AA9: ='04-221Master'!AV17 -> KKBK | AB9: ='04-221Master'!AW17 -> A/C'7311230416
A10: 3 | D10: ='04-221Master'!B18 -> Yarramaddu Raveendra Reddy | E10: ='04-221Master'!Z18 -> 37044 | F10: ='04-221Master'!AD18 -> 14817.6 | G10: ='04-221Master'!AE18 -> 2083 | H10: ='04-221Master'!AI18 -> 1554.609 | I10: ='04-221Master'!AG18 -> 5825.4 | J10: ='04-221Master'!AF18 -> 2083 | L10: ='04-221Master'!AH18 -> 61853 | M10: 2 | N10: ='04-221Master'!AM18 -> 68276.425 | O10: ='04-221Master'!AQ18 -> 0 | P10: ='04-221Master'!AR18 -> 391.78785 | Q10: ='04-221Master'!AP18 -> 200 | R10: ='04-221Master'!AO18 -> 1800 | S10: ='04-221Master'!AN18 -> 0 | T10: ='04-221Master'!AS18 -> 2391.7878 | U10: ='04-221Master'!AT18 -> 65884.638 | V10: 18 | W10: 0 | Y10: 18 | Z10: ='04-221Master'!AU18 -> 05.05.2022 | AA10: ='04-221Master'!AV18 -> HDFC BANK | AB10: ='04-221Master'!AW18 -> A/C'50100313077055
A11: 4 | D11: ='04-221Master'!B19 -> Chitra Kulkarni | E11: ='04-221Master'!Z19 -> 49279.2 | F11: ='04-221Master'!AD19 -> 19711.68 | G11: ='04-221Master'!AE19 -> 2083 | H11: ='04-221Master'!AI19 -> 1554.609 | I11: ='04-221Master'!AG19 -> 9088.12 | J11: ='04-221Master'!AF19 -> 2083 | L11: ='04-221Master'!AH19 -> 82245 | M11: 3 | N11: ='04-221Master'!AM19 -> 90276.539 | O11: ='04-221Master'!AQ19 -> 0 | P11: ='04-221Master'!AR19 -> 335 | Q11: ='04-221Master'!AP19 -> 200 | R11: ='04-221Master'!AO19 -> 1800 | S11: ='04-221Master'!AN19 -> 0 | T11: ='04-221Master'!AS19 -> 2335 | U11: ='04-221Master'!AT19 -> 87941.539 | V11: 7 | W11: 1 | Y11: 7.5 | Z11: ='04-221Master'!AU19 -> 05.05.2022 | AA11: ='04-221Master'!AV19 -> ICICI | AB11: ='04-221Master'!AW19 -> A/C' 055801521228
A12: 5 | D12: ='04-221Master'!B20 -> Sunnapalli Anil | E12: ='04-221Master'!Z20 -> 41748 | F12: ='04-221Master'!AD20 -> 16699.2 | G12: ='04-221Master'!AE20 -> 2083 | H12: ='04-221Master'!AI20 -> 1554.609 | I12: ='04-221Master'!AG20 -> 7079.8 | J12: ='04-221Master'!AF20 -> 2083 | L12: ='04-221Master'!AH20 -> 69693 | M12: 4 | N12: ='04-221Master'!AM20 -> 76734.688 | O12: ='04-221Master'!AQ20 -> 0 | P12: ='04-221Master'!AR20 -> 335 | Q12: ='04-221Master'!AP20 -> 200 | R12: ='04-221Master'!AO20 -> 1800 | S12: ='04-221Master'!AN20 -> 0 | T12: ='04-221Master'!AS20 -> 2335 | U12: ='04-221Master'!AT20 -> 74399.688 | V12: 8.5 | W12: 1 | Y12: 9 | Z12: ='04-221Master'!AU20 -> 05.05.2022 | AA12: ='04-221Master'!AV20 -> STATE BANK OF INDIA | AB12: ='04-221Master'!AW20 -> 20222665512
A13: 6 | D13: ='04-221Master'!B21 -> Himanshu Anand | E13: ='04-221Master'!Z21 -> 59100.6 | F13: ='04-221Master'!AD21 -> 23640.24 | G13: ='04-221Master'!AE21 -> 2083 | H13: ='04-221Master'!AI21 -> 1554.609 | I13: ='04-221Master'!AG21 -> 11707.16 | J13: ='04-221Master'!AF21 -> 2083 | L13: ='04-221Master'!AH21 -> 98614 | M13: 5 | N13: ='04-221Master'!AM21 -> 107936.4 | O13: ='04-221Master'!AQ21 -> 0 | P13: ='04-221Master'!AR21 -> 336 | Q13: ='04-221Master'!AP21 -> 200 | R13: ='04-221Master'!AO21 -> 1800 | S13: ='04-221Master'!AN21 -> 0 | T13: ='04-221Master'!AS21 -> 2336 | U13: ='04-221Master'!AT21 -> 105600.4 | V13: 8.5 | W13: 0 | Y13: 10 | Z13: ='04-221Master'!AU21 -> 05.05.2022 | AA13: ='04-221Master'!AV21 -> HDFC BANK | AB13: ='04-221Master'!AW21 -> A/C 07281140023731
A14: 7 | D14: ='04-221Master'!B22 -> Kanchupati Kondaiah | E14: ='04-221Master'!Z22 -> 28145.4 | F14: ='04-221Master'!AD22 -> 11258.16 | G14: ='04-221Master'!AE22 -> 2083 | H14: ='04-221Master'!AI22 -> 1554.609 | I14: ='04-221Master'!AG22 -> 3452.44 | J14: ='04-221Master'!AF22 -> 2083 | L14: ='04-221Master'!AH22 -> 47022 | M14: 6 | N14: ='04-221Master'!AM22 -> 52275.853 | O14: ='04-221Master'!AQ22 -> 0 | P14: ='04-221Master'!AR22 -> 336 | Q14: ='04-221Master'!AP22 -> 200 | R14: ='04-221Master'!AO22 -> 1800 | S14: ='04-221Master'!AN22 -> 0 | T14: ='04-221Master'!AS22 -> 2336 | U14: ='04-221Master'!AT22 -> 49939.853 | V14: 8.5 | W14: 0 | Y14: 10 | Z14: ='04-221Master'!AU22 -> 05.05.2022 | AA14: ='04-221Master'!AV22 -> UCO | AB14: ='04-221Master'!AW22 -> A/c no 16280110106877
A15: 8 | D15: ='04-221Master'!B23 -> Santosh Patel | E15: ='04-221Master'!Z23 -> 78754.2 | F15: ='04-221Master'!AD23 -> 31501.68 | G15: ='04-221Master'!AE23 -> 2083 | H15: ='04-221Master'!AI23 -> 1554.609 | I15: ='04-221Master'!AG23 -> 16948.12 | J15: ='04-221Master'!AF23 -> 2083 | L15: ='04-221Master'!AH23 -> 131370 | M15: 7 | N15: ='04-221Master'!AM23 -> 143275.54 | O15: ='04-221Master'!AQ23 -> 0 | P15: ='04-221Master'!AR23 -> 336 | Q15: ='04-221Master'!AP23 -> 200 | R15: ='04-221Master'!AO23 -> 1800 | S15: ='04-221Master'!AN23 -> 0 | T15: ='04-221Master'!AS23 -> 2336 | U15: ='04-221Master'!AT23 -> 140939.54 | V15: 7.5 | W15: 1 | Y15: 8 | Z15: ='04-221Master'!AU23 -> 05.05.2022 | AA15: ='04-221Master'!AV23 -> Axis Bank | AB15: ='04-221Master'!AW23 -> A/c No: 919010057225623
A16: 9 | D16: ='04-221Master'!B24 -> Basweshwar Pawar | E16: ='04-221Master'!Z24 -> 53728.2 | F16: ='04-221Master'!AD24 -> 21491.28 | G16: ='04-221Master'!AE24 -> 2083 | H16: ='04-221Master'!AI24 -> 1554.609 | I16: ='04-221Master'!AG24 -> 10274.52 | J16: ='04-221Master'!AF24 -> 2083 | L16: ='04-221Master'!AH24 -> 89660 | M16: 8 | N16: ='04-221Master'!AM24 -> 98276.285 | O16: ='04-221Master'!AQ24 -> 0 | P16: ='04-221Master'!AR24 -> 224 | Q16: ='04-221Master'!AP24 -> 200 | R16: ='04-221Master'!AO24 -> 1800 | S16: ='04-221Master'!AN24 -> 0 | T16: ='04-221Master'!AS24 -> 2224 | U16: ='04-221Master'!AT24 -> 96052.285 | V16: 8 | W16: 0 | Y16: 9.5 | Z16: ='04-221Master'!AU24 -> 05.05.2022 | AA16: ='04-221Master'!AV24 -> ICICI BANK | AB16: ='04-221Master'!AW24 -> 042401535769
A17: 10 | D17: ='04-221Master'!B25 -> Hemanth Mishra | E17: ='04-221Master'!Z25 -> 59289.6 | F17: ='04-221Master'!AD25 -> 23715.84 | G17: ='04-221Master'!AE25 -> 2083 | H17: ='04-221Master'!AI25 -> 1554.609 | I17: ='04-221Master'!AG25 -> 11757.56 | J17: ='04-221Master'!AF25 -> 2083 | L17: ='04-221Master'!AH25 -> 98929 | M17: 9 | N17: ='04-221Master'!AM25 -> 108276.24 | O17: ='04-221Master'!AQ25 -> 0 | P17: ='04-221Master'!AR25 -> 254 | Q17: ='04-221Master'!AP25 -> 200 | R17: ='04-221Master'!AO25 -> 1800 | S17: ='04-221Master'!AN25 -> 0 | T17: ='04-221Master'!AS25 -> 2254 | U17: ='04-221Master'!AT25 -> 106022.24 | V17: 6 | W17: 0 | Y17: 7.5 | Z17: ='04-221Master'!AU25 -> 05.05.2022 | AA17: ='04-221Master'!AV25 -> ICICI BANK | AB17: ='04-221Master'!AW25 -> 057001509856
A18: 11 | D18: ='04-221Master'!B26 -> FAZALAHMED IRKAL | E18: ='04-221Master'!Z26 -> 26349.84 | F18: ='04-221Master'!AD26 -> 10539.936 | G18: ='04-221Master'!AE26 -> 1528 | H18: ='04-221Master'!AI26 -> 1554.609 | I18: ='04-221Master'!AG26 -> 4083.624 | J18: ='04-221Master'!AF26 -> 1528 | L18: ='04-221Master'!AH26 -> 44029.4 | M18: 10 | N18: ='04-221Master'!AM26 -> 49047.256 | O18: ='04-221Master'!AQ26 -> 0 | P18: ='04-221Master'!AR26 -> 254 | Q18: ='04-221Master'!AP26 -> 200 | R18: ='04-221Master'!AO26 -> 1800 | S18: ='04-221Master'!AN26 -> 0 | T18: ='04-221Master'!AS26 -> 2254 | U18: ='04-221Master'!AT26 -> 46793.256 | V18: 4.5 | W18: 1 | Y18: 5 | Z18: ='04-221Master'!AU26 -> 05.05.2022 | AA18: ='04-221Master'!AV26 -> SBI | AB18: ='04-221Master'!AW26 -> 32722181716
A19: 12 | D19: ='04-221Master'!B27 -> SUKRUTH YELLAMBOTLA | E19: ='04-221Master'!Z27 -> 21471.6 | F19: ='04-221Master'!AD27 -> 8588.64 | G19: ='04-221Master'!AE27 -> 2083 | H19: ='04-221Master'!AI27 -> 1554.609 | I19: ='04-221Master'!AG27 -> 1672.76 | J19: ='04-221Master'!AF27 -> 2083 | L19: ='04-221Master'!AH27 -> 35899 | M19: 11 | N19: ='04-221Master'!AM27 -> 40275.693 | O19: ='04-221Master'!AQ27 -> 0 | P19: ='04-221Master'!AR27 -> 252 | Q19: ='04-221Master'!AP27 -> 200 | R19: ='04-221Master'!AO27 -> 1800 | S19: ='04-221Master'!AN27 -> 0 | T19: ='04-221Master'!AS27 -> 2252 | U19: ='04-221Master'!AT27 -> 38023.693 | V19: 5.5 | W19: 0 | Y19: 7 | Z19: ='04-221Master'!AU27 -> 05.05.2022 | AA19: ='04-221Master'!AV27 -> HDFC0000486 | AB19: ='04-221Master'!AW27 -> 50100468093660
... A28: 21 | D28: ='04-221Master'!B36 -> DiptiRanjan Dikhit | E28: ='04-221Master'!Z36 -> 33840.18 | F28: ='04-221Master'!AD36 -> 13536.072 | G28: ='04-221Master'!AE36 -> 1875 | H28: ='04-221Master'!AI36 -> 1554.609 | I28: ='04-221Master'!AG36 -> 5387.048 | J28: ='04-221Master'!AF36 -> 1875 | L28: ='04-221Master'!AH36 -> 56513.3 | M28: 20 | N28: ='04-221Master'!AM36 -> 62515.637 | O28: ='04-221Master'!AQ36 -> 0 | P28: ='04-221Master'!AR36 -> 0 | Q28: ='04-221Master'!AP36 -> 200 | R28: ='04-221Master'!AO36 -> 1800 | S28: ='04-221Master'!AN36 -> 0 | T28: ='04-221Master'!AS36 -> 2000 | U28: ='04-221Master'!AT36 -> 60515.637 | V28: 0 | W28: 0 | Y28: 1.5 | Z28: ='04-221Master'!AU36 -> 05.05.2022 | AA28: ='04-221Master'!AV36 -> State Bank Of India | AB28: ='04-221Master'!AW36 -> 31162392468
E29: =SUM(E8:E28) -> 1032148.6 | F29: =SUM(F8:F28) -> 412859.45 | G29: =SUM(G8:G28) -> 42980 | H29: =SUM(H8:H28) -> 32646.789 | I29: =SUM(I8:I28) -> 191652.63 | J29: =SUM(J8:J28) -> 42980 | L29: =SUM(L8:L28) -> 1722620.7 | M29: =SUM(M8:M28) -> 210 | N29: =SUM(N8:N28) -> 1890926.2 | O29: =SUM(O8:O28) -> 0 | P29: =SUM(P8:P28) -> 5867.337 | Q29: =SUM(Q8:Q28) -> 4200 | R29: =SUM(R8:R28) -> 42000 | S29: =SUM(S8:S28) -> 0 | T29: =SUM(T8:T28) -> 52067.337 | U29: ='04-221Master'!AT37 -> 1838858.9
R41: Signature of the Contractor with Seal

Sheet Empl Cards
B1: FORM X
B2: EMPLOYMENT CUM WAGE CARD
B3: (Vide Rule 76 of Contract Labour (R&A) Central & Maharashtra Rules, 1971)
B4: Name and Address of the Contractor | H4: Name and Address of the Establishment in/under which Contract is carried on:
B7: ='04-221Master'!F5 -> Burgeon IT Services Pvt.Ltd. | H7: ='04-221Master'!AP5 -> Burgeon IT Services Pvt.Ltd.
B9: ='04-221Master'!F6 -> Siri Mansion LIGB 436 Dr.A S Rao Nagar,Hyderabad | H9: ='04-221Master'!AP6 -> Siri Mansion LIGB 436 Dr.A S Rao Nagar,Hyderabad
B12: Nature of work and location of work: | H12: Name and address of Principal Employer:
H15: ='04-221Master'!AP10 -> INFOSYS LTD.IL Pune SEZ Unit-I,Plot No. 24/3
B16: ='04-221Master'!F8 -> IT SUPPORTIVE SERVICES& Pune SEZ Unit-1
H17: ='04-221Master'!AP11 -> Rajiv gandhi Info tech park,Village Mann,Pune,Maharashtra 411057
B19: 1. Name of the Workman and address | H19: ='04-221Master'!B16 -> Venegella Kanaka durga
H20: ='04-221Master'!G16 -> Dr no-115,Sujatha nagar, vinjamur SPSR Nellore ,Andra Pradesh,pincode:560066
B21: 2. S.No. in the Register of Workmen Employed | H21: ='04-221Master'!AY16 -> 6
B22: 3. Nature of Employment /Designation | H22: ='04-221Master'!F16 -> Senior Software Engineer
B23: 4. Date of entry into service | H23: ='04-221Master'!N16 -> 44021
B24: 5. ESI No. | J24: ='04-221Master'!T16 -> N/A
B25: 6.PF No. | J25: ='04-221Master'!S16 -> 100748390738
B26: 7. Wage rate (With particulars of unit in case of piece - work) | H26: ='04-221Master'!Y16 -> 75643
B27: 8. Wage period | H27: ='04-221Master'!D10 -> 44652
B28: 9. Tenure of Employment | H28: AS PER CONTRACT
B29: 10.No. of days worked in a month | J29: ='04-221Master'!W16 -> 30
B30: 11. No. of units worked in case of piece rate workers | J30: N/A
B31: 12. Rate of daily wages / piece rate | J31: 0
B32: 13. Amount of overtime wages | J32: 0
B33: 14. Gross wages payable | J33: ='04-221Master'!AM16 -> 83275.816 | L33: MED
B34: 15. Deductions, if any, | D34: PF | E34: ='04-221Master'!AO16 -> 1800 | F34: ESI | G34: ='04-221Master'!AN16 -> 0 | H34: PT | I34: ='04-221Master'!AP16 -> 200 | J34: TDS | K34: ='04-221Master'!AQ16 -> 0 | L34: ='04-221Master'!AR16 -> 391.78785
B35: 16. Net amount of wages paid | J35: =J33-(E34+G34+I34+K34+L34) -> 80884.028
B36: Signature of the Representative
B37: of Contractor
B55: FORM X
B56: EMPLOYMENT CUM WAGE CARD
B57: (Vide Rule 76 of Contract Labour (R&A) Central & Maharashtra Rules, 1971)
B58: Name and Address of the Contractor | H58: Name and Address of the Establishment in/under which Contract is carried on:
B61: ='04-221Master'!F5 -> Burgeon IT Services Pvt.Ltd. | H61: ='04-221Master'!AP5 -> Burgeon IT Services Pvt.Ltd.
B63: ='04-221Master'!F6 -> Siri Mansion LIGB 436 Dr.A S Rao Nagar,Hyderabad | H63: ='04-221Master'!AP6 -> Siri Mansion LIGB 436 Dr.A S Rao Nagar,Hyderabad
B66: Nature of work and location of work: | H66: Name and address of Principal Employer:
H69: ='04-221Master'!AP10 -> INFOSYS LTD.IL Pune SEZ Unit-I,Plot No. 24/3
B70: ='04-221Master'!F8 -> IT SUPPORTIVE SERVICES& Pune SEZ Unit-1
H71: ='04-221Master'!AP11 -> Rajiv gandhi Info tech park,Village Mann,Pune,Maharashtra 411057
B73: 1. Name of the Workman and address | H73: ='04-221Master'!B17 -> Moeenahmed Shakilahmed Shaikh
H74: ='04-221Master'!G17 -> 967 Ravivarpet, Ghulamali,Chambers laxmi Road, Pune, MH 411002
B75: 2. S.No. in the Register of Workmen Employed | H75: ='04-221Master'!AY17 -> 10
B76: 3. Nature of Employment /Designation | H76: ='04-221Master'!F17 -> Splunk Developer
B77: 4. Date of entry into service | H77: ='04-221Master'!N17 -> 44041
B78: 5. ESI No. | J78: ='04-221Master'!T17 -> N/A
B79: 6.PF No. | J79: ='04-221Master'!S17 -> 101607851856
B80: 7. Wage rate (With particulars of unit in case of piece - work) | H80: ='04-221Master'!Y17 -> 149795
B81: 8. Wage period | H81: ='04-221Master'!D10 -> 44652
B82: 9. Tenure of Employment | H82: AS PER CONTRACT
B83: 10.No. of days worked in a month | J83: ='04-221Master'!W17 -> 30
B84: 11. No. of units worked in case of piece rate workers | J84: N/A
B85: 12. Rate of daily wages / piece rate | J85: 0
B86: 13. Amount of overtime wages | J86: 0
B87: 14. Gross wages payable | J87: ='04-221Master'!AM17 -> 163275.44 | L87: MED
B88: 15. Deductions, if any, | D88: PF | E88: ='04-221Master'!AO17 -> 6000 | F88: ESI | G88: ='04-221Master'!AN17 -> 0 | H88: PT | I88: ='04-221Master'!AP17 -> 200 | J88: TDS | K88: ='04-221Master'!AQ17 -> 0 | L88: ='04-221Master'!AR17 -> 440.76133
B89: 16. Net amount of wages paid | J89: =J87-(E88+G88+I88+K88+L88) -> 156634.68
B90: Signature of the Representative
B91: of Contractor
B110: FORM X
B111: EMPLOYMENT CUM WAGE CARD
B112: (Vide Rule 76 of Contract Labour (R&A) Central & Maharashtra Rules, 1971)
B113: Name and Address of the Contractor | H113: Name and Address of the Establishment in/under which Contract is carried on:
B116: ='04-221Master'!F5 -> Burgeon IT Services Pvt.Ltd. | H116: ='04-221Master'!AP5 -> Burgeon IT Services Pvt.Ltd.
B118: ='04-221Master'!F6 -> Siri Mansion LIGB 436 Dr.A S Rao Nagar,Hyderabad | H118: ='04-221Master'!AP6 -> Siri Mansion LIGB 436 Dr.A S Rao Nagar,Hyderabad
B121: Nature of work and location of work: | H121: Name and address of Principal Employer:
H124: ='04-221Master'!AP10 -> INFOSYS LTD.IL Pune SEZ Unit-I,Plot No. 24/3
B125: ='04-221Master'!F8 -> IT SUPPORTIVE SERVICES& Pune SEZ Unit-1
H126: ='04-221Master'!AP11 -> Rajiv gandhi Info tech park,Village Mann,Pune,Maharashtra 411057
B128: 1. Name of the Workman and address | H128: ='04-221Master'!#REF! -> #REF!
H129: ='04-221Master'!#REF! -> #REF!
B130: 2. S.No. in the Register of Workmen Employed | H130: ='04-221Master'!#REF! -> #REF!
B131: 3. Nature of Employment /Designation | H131: ='04-221Master'!#REF! -> #REF!
B132: 4. Date of entry into service | H132: ='04-221Master'!#REF! -> #REF!
B133: 5. ESI No. | J133: ='04-221Master'!#REF! -> #REF!
B134: 6.PF No. | J134: ='04-221Master'!#REF! -> #REF!
B135: 7. Wage rate (With particulars of unit in case of piece - work) | H135: ='04-221Master'!#REF! -> #REF!
B136: 8. Wage period
B137: 9. Tenure of Employment | H137: AS PER CONTRACT
B138: 10.No. of days worked in a month | J138: ='04-221Master'!#REF! -> #REF!
B139: 11. No. of units worked in case of piece rate workers | J139: N/A
B140: 12. Rate of daily wages / piece rate | J140: 0
B141: 13. Amount of overtime wages | J141: 0
B142: 14. Gross wages payable | L142: MED
B143: 15. Deductions, if any, | D143: PF | E143: ='04-221Master'!#REF! -> #REF! | F143: ESI | G143: ='04-221Master'!#REF! -> #REF! | H143: PT | I143: ='04-221Master'!#REF! -> #REF! | J143: TDS | K143: ='04-221Master'!#REF! -> #REF! | L143: ='04-221Master'!#REF! -> #REF!
B144: 16. Net amount of wages paid
B145: Signature of the Representative
B146: of Contractor
B162: FORM X
B163: EMPLOYMENT CUM WAGE CARD
B164: (Vide Rule 76 of Contract Labour (R&A) Central & Maharashtra Rules, 1971)
B165: Name and Address of the Contractor | H165: Name and Address of the Establishment in/under which Contract is carried on:
B168: Burgeon IT Services Pvt.Ltd. | H168: Burgeon IT Services Pvt.Ltd.
B169: Siri Mansion LIGB 436 Dr.A S Rao Nagar,Hyderabad | H169: Siri Mansion LIGB 436 Dr.A S Rao Nagar,Hyderabad
B173: Nature of work and location of work: | H173: Name and address of Principal Employer:
H176: INFOSYS LTD.IL Pune SEZ Unit-I,Plot No. 24/3
B177: IT SUPPORTIVE SERVICES | H177: Rajiv gandhi Info tech park,Village Mann,Pune,Maharashtra 411057
B180: 1. Name of the Workman and address | H180: ='04-221Master'!B18 -> Yarramaddu Raveendra Reddy
H181: ='04-221Master'!G18 -> 11/25,Baddipally village,Mudivedu post,Kura Balakota mandal,Chittor district,AP 517350
B182: 2. S.No. in the Register of Workmen Employed | H182: ='04-221Master'!AY18 -> 19
B183: 3. Nature of Employment /Designation | H183: ='04-221Master'!E18 -> Ramachandra Reddy
...

Sheet wage sllips
A2: Form XV - WAGE SLIP | K2: Form XV - WAGE SLIP
A3: [Vide rule 78 (1) (b) of the Contract Labour (Regulation and Abolition) and Maharashtra Rules, 1971] | K3: [Vide rule 78 (1) (b) of the Contract Labour (Regulation and Abolition) and Maharashtra Rules, 1971]
A5: Name and address of Contractor | D5: ='04-221Master'!F5 -> Burgeon IT Services Pvt.Ltd. | K5: Name and address of Contractor | N5: =D5 -> Burgeon IT Services Pvt.Ltd.
B6: ='04-221Master'!F6 -> Siri Mansion LIGB 436 Dr.A S Rao Nagar,Hyderabad | L6: =B6 -> Siri Mansion LIGB 436 Dr.A S Rao Nagar,Hyderabad
B7: ='04-221Master'!F7 -> 0 | L7: =B7 -> 0
A8: Name and Father's / Husband's name of the workman | K8: Name and Father's / Husband's name of the workman
E9: ='04-221Master'!B16 -> Venegella Kanaka durga | H9: ='04-221Master'!E16 -> Venkateshwar Rao | O9: =E9 -> Venegella Kanaka durga | R9: =H9 -> Venkateshwar Rao
A11: Nature and location of work | E11: ='04-221Master'!F8 -> IT SUPPORTIVE SERVICES& Pune SEZ Unit-1 | K11: Nature and location of work | O11: =E11 -> IT SUPPORTIVE SERVICES& Pune SEZ Unit-1
A13: For the Week / Fortnight / Month ending | E13: ='04-221Master'!D10 -> 44652 | K13: For the Week / Fortnight / Month ending | O13: =E13 -> 44652
A15: 1 | B15: No. of days worked | E15: ='04-221Master'!W16 -> 30 | K15: 1 | L15: No. of days worked | O15: =E15 -> 30
A17: 2 | B17: No. of units worked in case of piece rate workers : | K17: 2 | L17: No. of units worked in case of piece rate workers :
E18: N/A | O18: N/A
A20: 3 | B20: Rate of daily wages / piece rate | E20: N/A | K20: 3 | L20: Rate of daily wages / piece rate | O20: =E20 -> N/A
A22: 4 | B22: Amount of overtime wages | E22: Nil | K22: 4 | L22: Amount of overtime wages | O22: Nil
A24: 5 | B24: Gross wages payble | E24: ='04-221Master'!AM16 -> 83275.816 | K24: 5 | L24: Gross wages payble | O24: =E24 -> 83275.816
D25: EPF | E25: ESI | F25: PT | G25: TDS | H25: MEDICAL | I25: TOTAL | N25: EPF | O25: ESI | P25: PT | Q25: TDS | R25: MEDICAL | S25: TOTAL
A26: 6 | B26: Deductions, if any | D26: ='04-221Master'!AO16 -> 1800 | E26: ='04-221Master'!AN16 -> 0 | F26: ='04-221Master'!AP16 -> 200 | G26: ='04-221Master'!AQ16 -> 0 | H26: ='04-221Master'!AR16 -> 391.78785 | I26: =D26+E26+F26+G26+H26 -> 2391.7878 | K26: 6 | L26: Deductions, if any | N26: =D26 -> 1800 | O26: =E26 -> 0 | P26: =F26 -> 200 | Q26: =G26 -> 0 | R26: =H26 -> 391.78785 | S26: =I26 -> 2391.7878
A28: 7 | B28: Net amount of wages paid | E28: =E24-I26 -> 80884.028 | K28: 7 | L28: Net amount of wages paid | O28: =E28 -> 80884.028
F32: Initial of the Contractor or his representative | P32: Initial of the Contractor or his representative
A49: Form XV - WAGE SLIP | K49: Form XV - WAGE SLIP
A50: [Vide rule 78 (1) (b) of the Contract Labour (Regulation and Abolition) and Maharashtra Rules, 1971] | K50: [Vide rule 78 (1) (b) of the Contract Labour (Regulation and Abolition) and Maharashtra Rules, 1971]
A52: Name and address of Contractor | D52: ='04-221Master'!F5 -> Burgeon IT Services Pvt.Ltd. | K52: Name and address of Contractor | N52: =D52 -> Burgeon IT Services Pvt.Ltd.
B53: ='04-221Master'!F6 -> Siri Mansion LIGB 436 Dr.A S Rao Nagar,Hyderabad | L53: =B53 -> Siri Mansion LIGB 436 Dr.A S Rao Nagar,Hyderabad
B54: ='04-221Master'!F7 -> 0 | L54: =B54 -> 0
A55: Name and Father's / Husband's name of the workman | K55: Name and Father's / Husband's name of the workman
E56: ='04-221Master'!B17 -> Moeenahmed Shakilahmed Shaikh | H56: ='04-221Master'!E17 -> Shaik Azara Shakilahmed | O56: =E56 -> Moeenahmed Shakilahmed Shaikh | R56: =H56 -> Shaik Azara Shakilahmed
A58: Nature and location of work | E58: ='04-221Master'!F8 -> IT SUPPORTIVE SERVICES& Pune SEZ Unit-1 | K58: Nature and location of work | O58: =E58 -> IT SUPPORTIVE SERVICES& Pune SEZ Unit-1
A60: For the Week / Fortnight / Month ending | E60: ='04-221Master'!D10 -> 44652 | K60: For the Week / Fortnight / Month ending | O60: =E60 -> 44652
A62: 1 | B62: No. of days worked | E62: ='04-221Master'!W17 -> 30 | K62: 1 | L62: No. of days worked | O62: =E62 -> 30
A64: 2 | B64: No. of units worked in case of piece rate workers : | K64: 2 | L64: No. of units worked in case of piece rate workers :
E65: N/A | O65: N/A
A67: 3 | B67: Rate of daily wages / piece rate | E67: N/A | K67: 3 | L67: Rate of daily wages / piece rate | O67: =E67 -> N/A
A69: 4 | B69: Amount of overtime wages | E69: Nil | K69: 4 | L69: Amount of overtime wages | O69: Nil
A71: 5 | B71: Gross wages payble | E71: ='04-221Master'!AM17 -> 163275.44 | K71: 5 | L71: Gross wages payble | O71: =E71 -> 163275.44
D72: EPF | E72: ESI | F72: PT | G72: TDS | H72: MEDICAL | I72: TOTAL | N72: EPF | O72: ESI | P72: PT | Q72: TDS | R72: MEDICAL | S72: TOTAL
A73: 6 | B73: Deductions, if any | D73: ='04-221Master'!AO17 -> 6000 | E73: ='04-221Master'!AN17 -> 0 | F73: ='04-221Master'!AP17 -> 200 | G73: ='04-221Master'!AQ17 -> 0 | H73: ='04-221Master'!AR17 -> 440.76133 | I73: =D73+E73+F73+G73+H73 -> 6640.7613 | K73: 6 | L73: Deductions, if any | N73: =D73 -> 6000 | O73: =E73 -> 0 | P73: =F73 -> 200 | Q73: =G73 -> 0 | R73: =H73 -> 440.76133 | S73: =I73 -> 6640.7613
A75: 7 | B75: Net amount of wages paid | E75: =E71-I73 -> 156634.68 | K75: 7 | L75: Net amount of wages paid | O75: =E75 -> 156634.68
F79: Initial of the Contractor or his representative | P79: Initial of the Contractor or his representative
A97: Form XV - WAGE SLIP | K97: Form XV - WAGE SLIP
A98: [Vide rule 78 (1) (b) of the Contract Labour (Regulation and Abolition) and Maharashtra Rules, 1971] | K98: [Vide rule 78 (1) (b) of the Contract Labour (Regulation and Abolition) and Maharashtra Rules, 1971]
A100: Name and address of Contractor | D100: ='04-221Master'!F5 -> Burgeon IT Services Pvt.Ltd. | K100: Name and address of Contractor | N100: =D100 -> Burgeon IT Services Pvt.Ltd.
B101: ='04-221Master'!F6 -> Siri Mansion LIGB 436 Dr.A S Rao Nagar,Hyderabad | L101: =B101 -> Siri Mansion LIGB 436 Dr.A S Rao Nagar,Hyderabad
B102: ='04-221Master'!F389 -> 0 | L102: =B102 -> 0
A103: Name and Father's / Husband's name of the workman | K103: Name and Father's / Husband's name of the workman
E104: ='04-221Master'!#REF! -> #REF! | H104: ='04-221Master'!#REF! -> #REF! | O104: =E104 -> #REF! | Q104: =H104 -> #REF!
A106: Nature and location of work | E106: ='04-221Master'!F8 -> IT SUPPORTIVE SERVICES& Pune SEZ Unit-1 | K106: Nature and location of work | O106: =E106 -> IT SUPPORTIVE SERVICES& Pune SEZ Unit-1
A108: For the Week / Fortnight / Month ending | E108: ='04-221Master'!D10 -> 44652 | K108: For the Week / Fortnight / Month ending | O108: =E108 -> 44652
A110: 1 | B110: No. of days worked | E110: ='04-221Master'!#REF! -> #REF! | K110: 1 | L110: No. of days worked | O110: =E110 -> #REF!
A112: 2 | B112: No. of units worked in case of piece rate workers : | K112: 2 | L112: No. of units worked in case of piece rate workers :
E113: N/A | O113: N/A
A115: 3 | B115: Rate of daily wages / piece rate | E115: N/A | K115: 3 | L115: Rate of daily wages / piece rate | O115: =E115 -> N/A
A117: 4 | B117: Amount of overtime wages | E117: Nil | K117: 4 | L117: Amount of overtime wages | O117: Nil
A119: 5 | B119: Gross wages payble | E119: ='04-221Master'!#REF! -> #REF! | K119: 5 | L119: Gross wages payble | O119: =E119 -> #REF!
D120: EPF | E120: ESI | F120: PT | G120: TDS | H120: MEDICAL | I120: TOTAL | N120: EPF | O120: ESI | P120: PT | Q120: TDS | R120: MEDICAL | S120: TOTAL
A121: 6 | B121: Deductions, if any | D121: ='04-221Master'!#REF! -> #REF! | E121: ='04-221Master'!#REF! -> #REF! | F121: ='04-221Master'!#REF! -> #REF! | G121: ='04-221Master'!#REF! -> #REF! | H121: ='04-221Master'!#REF! -> #REF! | I121: ='04-221Master'!#REF! -> #REF! | K121: 6 | L121: Deductions, if any | N121: =D121 -> #REF! | O121: =E121 -> #REF! | P121: =F121 -> #REF! | Q121: =G121 -> #REF! | R121: =H121 -> #REF! | S121: =I121 -> #REF!
A123: 7 | B123: Net amount of wages paid | E123: =E119-I121 -> #REF! | K123: 7 | L123: Net amount of wages paid | O123: =E123 -> #REF!
F127: Initial of the Contractor or his representative | P127: Initial of the Contractor or his representative
A145: Form XV - WAGE SLIP | K145: Form XV - WAGE SLIP
A146: [Vide rule 78 (1) (b) of the Contract Labour (Regulation and Abolition) and Maharashtra Rules, 1971] | K146: [Vide rule 78 (1) (b) of the Contract Labour (Regulation and Abolition) and Maharashtra Rules, 1971]
A148: Name and address of Contractor | D148: Burgeon IT Services Pvt.Ltd. | K148: Name and address of Contractor | N148: Burgeon IT Services Pvt.Ltd.
D149: Siri Mansion LIGB 436 Dr.A S Rao Nagar,Hyderabad | N149: Siri Mansion LIGB 436 Dr.A S Rao Nagar,Hyderabad
A151: Name and Father's / Husband's name of the workman | K151: Name and Father's / Husband's name of the workman
E152: ='04-221Master'!B18 -> Yarramaddu Raveendra Reddy | G152: ='04-221Master'!E18 -> Ramachandra Reddy | O152: =E152 -> Yarramaddu Raveendra Reddy | R152: =G152 -> Ramachandra Reddy
A154: Nature and location of work | E154: IT SUPPORTIVE SERVICES | K154: Nature and location of work | O154: =E154 -> IT SUPPORTIVE SERVICES
A156: For the Week / Fortnight / Month ending | E156: ='04-221Master'!D10 -> 44652 | K156: For the Week / Fortnight / Month ending | O156: =E156 -> 44652
A158: 1 | B158: No. of days worked | E158: ='04-221Master'!W18 -> 30 | K158: 1 | L158: No. of days worked | O158: =E158 -> 30
A160: 2 | B160: No. of units worked in case of piece rate workers : | K160: 2 | L160: No. of units worked in case of piece rate workers :
E161: N/A | O161: N/A
A163: 3 | B163: Rate of daily wages / piece rate | E163: N/A | K163: 3 | L163: Rate of daily wages / piece rate | O163: =E163 -> N/A
A165: 4 | B165: Amount of overtime wages | E165: Nil | K165: 4 | L165: Amount of overtime wages | O165: Nil
A167: 5 | B167: Gross wages payble | E167: ='04-221Master'!AM18 -> 68276.425 | K167: 5 | L167: Gross wages payble | O167: =E167 -> 68276.425
D168: EPF | E168: ESI | F168: PT | G168: TDS | H168: MEDICAL | I168: TOTAL | N168: EPF | O168: ESI | P168: PT | Q168: TDS | R168: MEDICAL | S168: TOTAL
A169: 6 | B169: Deductions, if any | D169: ='04-221Master'!AO18 -> 1800 | E169: ='04-221Master'!AN257 -> 0 | F169: ='04-221Master'!AP18 -> 200 | G169: ='04-221Master'!AQ18 -> 0 | H169: ='04-221Master'!AR18 -> 391.78785 | I169: =SUM(D169:H169) -> 2391.7878 | K169: 6 | L169: Deductions, if any | N169: =D169 -> 1800 | O169: =E169 -> 0 | P169: =F169 -> 200 | Q169: =G169 -> 0 | R169: =H169 -> 391.78785 | S169: =I169 -> 2391.7878
A171: 7 | B171: Net amount of wages paid | E171: =E167-I169 -> 65884.638 | K171: 7 | L171: Net amount of wages paid | O171: =E171 -> 65884.638
F175: Initial of the Contractor or his representative | P175: Initial of the Contractor or his representative
A192: Form XV - WAGE SLIP | K192: Form XV - WAGE SLIP
A193: [Vide rule 78 (1) (b) of the Contract Labour (Regulation and Abolition) and Maharashtra Rules, 1971] | K193: [Vide rule 78 (1) (b) of the Contract Labour (Regulation and Abolition) and Maharashtra Rules, 1971]
A195: Name and address of Contractor | D195: Burgeon IT Services Pvt.Ltd. | K195: Name and address of Contractor | N195: Burgeon IT Services Pvt.Ltd.
D196: Siri Mansion LIGB 436 Dr.A S Rao Nagar,Hyderabad | N196: Siri Mansion LIGB 436 Dr.A S Rao Nagar,Hyderabad
A198: Name and Father's / Husband's name of the workman | K198: Name and Father's / Husband's name of the workman
E199: ='04-221Master'!B19 -> Chitra Kulkarni | G199: ='04-221Master'!E19 -> Nirbay Gopal | O199: =E199 -> Chitra Kulkarni | R199: =G199 -> Nirbay Gopal
A201: Nature and location of work | E201: IT SUPPORTIVE SERVICES | K201: Nature and location of work | O201: =E201 -> IT SUPPORTIVE SERVICES
A203: For the Week / Fortnight / Month ending | E203: ='04-221Master'!D10 -> 44652 | K203: For the Week / Fortnight / Month ending | O203: =E203 -> 44652
A205: 1 | B205: No. of days worked | E205: ='04-221Master'!W19 -> 30 | K205: 1 | L205: No. of days worked | O205: =E205 -> 30
A207: 2 | B207: No. of units worked in case of piece rate workers : | K207: 2 | L207: No. of units worked in case of piece rate workers :
E208: N/A | O208: N/A
A210: 3 | B210: Rate of daily wages / piece rate | E210: N/A | K210: 3 | L210: Rate of daily wages / piece rate | O210: =E210 -> N/A
A212: 4 | B212: Amount of overtime wages | E212: Nil | K212: 4 | L212: Amount of overtime wages | O212: Nil
A214: 5 | B214: Gross wages payble | E214: ='04-221Master'!AM19 -> 90276.539 | K214: 5 | L214: Gross wages payble | O214: =E214 -> 90276.539
D215: EPF | E215: ESI | F215: PT | G215: TDS | H215: MEDICAL | I215: TOTAL | N215: EPF | O215: ESI | P215: PT | Q215: TDS | R215: MEDICAL | S215: TOTAL
A216: 6 | B216: Deductions, if any | D216: ='04-221Master'!AO19 -> 1800 | E216: ='04-221Master'!AN300 -> 0 | F216: ='04-221Master'!AP19 -> 200 | G216: ='04-221Master'!AQ19 -> 0 | H216: ='04-221Master'!AR19 -> 335 | I216: =SUM(D216:H216) -> 2335 | K216: 6 | L216: Deductions, if any | N216: =D216 -> 1800 | O216: =E216 -> 0 | P216: =F216 -> 200 | Q216: =G216 -> 0 | R216: =H216 -> 335 | S216: =I216 -> 2335
A218: 7 | B218: Net amount of wages paid | E218: =E214-I216 -> 87941.539 | K218: 7 | L218: Net amount of wages paid | O218: =E218 -> 87941.539
F222: Initial of the Contractor or his representative | P222: Initial of the Contractor or his representative
A240: Form XV - WAGE SLIP | K240: Form XV - WAGE SLIP
A241: [Vide rule 78 (1) (b) of the Contract Labour (Regulation and Abolition) and Maharashtra Rules, 1971] | K241: [Vide rule 78 (1) (b) of the Contract Labour (Regulation and Abolition) and Maharashtra Rules, 1971]
A243: Name and address of Contractor | D243: Burgeon IT Services Pvt.Ltd. | K243: Name and address of Contractor | N243: Burgeon IT Services Pvt.Ltd.
D244: Siri Mansion LIGB 436 Dr.A S Rao Nagar,Hyderabad | N244: Siri Mansion LIGB 436 Dr.A S Rao Nagar,Hyderabad
A246: Name and Father's / Husband's name of the workman | K246: Name and Father's / Husband's name of the workman
E247: ='04-221Master'!B20 -> Sunnapalli Anil | G247: ='04-221Master'!E20 -> Narsingam | O247: =E247 -> Sunnapalli Anil | R247: =G247 -> Narsingam
A249: Nature and location of work | E249: IT SUPPORTIVE SERVICES | K249: Nature and location of work | O249: =E249 -> IT SUPPORTIVE SERVICES
...

Sheet 04-22Bonus
A1: BONUS REGISTER
A3: FORM "c" ( See rule 4 [c] )
K4: Wage Period | L4: ='04-221Master'!D10 -> 44652
A5: Name of the Establishment : _____________________________ | D5: ='04-221Master'!F5 -> Burgeon IT Services Pvt.Ltd. | K5: Financial year _____ | M5: 2022-23
A6: ='04-221Master'!F6 -> Siri Mansion LIGB 436 Dr.A S Rao Nagar,Hyderabad
A7: Sr. No | B7: Name of the Employee | C7: Father's Name / Husband's Name | D7: Whether he has completed 15 yrs of age at the beginning of the accounting year | E7: Designation | F7: No. of days worked in the year | G7: Total Salary or wages in the Month | H7: Amt. of bonus payable under section 10 or section 11 as the case may be Ex gratia | I7: DEDUCTIONS | L7: Total Sum Deducted (Col. 9,10 and 11) | M7: Net Amount payable (Col. 8 minus Col. 12) | N7: Amount Actually paid | O7: Date on which paid | P7: Signature / Thumb impression of the employee
I8: Puja Bonus or other customary bonus paid during the accounting year | J8: Interim Bonus or bonus paid in advance | K8: Deduction on account of financial loss if any caused by misconduct of the employee | Q8: Account Number
A9: 1 | B9: 2 | C9: 3 | D9: 4 | E9: 5 | F9: 6 | H9: 8 | I9: 9 | J9: 10 | K9: 11 | L9: 12 | M9: 13 | N9: 14 | O9: 15 | P9: 16
A10: 1 | B10: ='04-221Master'!B16 -> Venegella Kanaka durga | C10: ='04-221Master'!E16 -> Venkateshwar Rao | D10: YES | E10: ='04-221Master'!F16 -> Senior Software Engineer | F10: ='04-221Master'!W16 -> 30 | G10: ='04-221Master'!AM16 -> 83275.816 | H10: ='04-221Master'!AI16 -> 1554.609 | I10: N/A | J10: N/A | K10: N/A | L10: N/A | M10: =H10 -> 1554.609 | N10: =H10 -> 1554.609 | O10: ='04-221Master'!AU16 -> 05.05.2022 | P10: ='04-221Master'!AV16 -> KVBL | Q10: ='04-221Master'!AW16 -> A/C'1498155000027380
A11: 2 | B11: ='04-221Master'!B17 -> Moeenahmed Shakilahmed Shaikh | C11: ='04-221Master'!E17 -> Shaik Azara Shakilahmed | D11: YES | E11: ='04-221Master'!F17 -> Splunk Developer | F11: ='04-221Master'!W17 -> 30 | G11: ='04-221Master'!AM17 -> 163275.44 | H11: ='04-221Master'!AI17 -> 1554.609 | I11: N/A | J11: N/A | K11: N/A | L11: N/A | M11: =H11 -> 1554.609 | N11: =H11 -> 1554.609 | O11: ='04-221Master'!AU17 -> 05.05.2022 | P11: ='04-221Master'!AV17 -> KKBK | Q11: ='04-221Master'!AW17 -> A/C'7311230416
A12: 3 | B12: ='04-221Master'!B18 -> Yarramaddu Raveendra Reddy | C12: ='04-221Master'!E18 -> Ramachandra Reddy | D12: YES | E12: ='04-221Master'!F18 -> Sr Citrix Administrator | F12: ='04-221Master'!W18 -> 30 | G12: ='04-221Master'!AM18 -> 68276.425 | H12: ='04-221Master'!AI18 -> 1554.609 | I12: N/A | J12: N/A | K12: N/A | L12: N/A | M12: =H12 -> 1554.609 | N12: =H12 -> 1554.609 | O12: ='04-221Master'!AU18 -> 05.05.2022 | P12: ='04-221Master'!AV18 -> HDFC BANK | Q12: ='04-221Master'!AW18 -> A/C'50100313077055
A13: 4 | B13: ='04-221Master'!B19 -> Chitra Kulkarni | C13: ='04-221Master'!E19 -> Nirbay Gopal | D13: YES | E13: ='04-221Master'!F19 -> Project Manager | F13: ='04-221Master'!W19 -> 30 | G13: ='04-221Master'!AM19 -> 90276.539 | H13: ='04-221Master'!AI19 -> 1554.609 | I13: N/A | J13: N/A | K13: N/A | L13: N/A | M13: =H13 -> 1554.609 | N13: =H13 -> 1554.609 | O13: ='04-221Master'!AU19 -> 05.05.2022 | P13: ='04-221Master'!AV19 -> ICICI | Q13: ='04-221Master'!AW19 -> A/C' 055801521228
A14: 5 | B14: ='04-221Master'!B20 -> Sunnapalli Anil | C14: ='04-221Master'!E20 -> Narsingam | D14: YES | E14: ='04-221Master'!F20 -> Sr. Software Engineer | F14: ='04-221Master'!W20 -> 30 | G14: ='04-221Master'!AM20 -> 76734.688 | H14: ='04-221Master'!AI20 -> 1554.609 | I14: N/A | J14: N/A | K14: N/A | L14: N/A | M14: =H14 -> 1554.609 | N14: =H14 -> 1554.609 | O14: ='04-221Master'!AU20 -> 05.05.2022 | P14: ='04-221Master'!AV20 -> STATE BANK OF INDIA | Q14: ='04-221Master'!AW20 -> 20222665512
A15: 6 | B15: ='04-221Master'!B21 -> Himanshu Anand | C15: ='04-221Master'!E21 -> A.K. Gupta | D15: YES | E15: ='04-221Master'!F21 -> Sr. DBA / Sr. Administrator | F15: ='04-221Master'!W21 -> 30 | G15: ='04-221Master'!AM21 -> 107936.4 | H15: ='04-221Master'!AI21 -> 1554.609 | I15: N/A | J15: N/A | K15: N/A | L15: N/A | M15: =H15 -> 1554.609 | N15: =H15 -> 1554.609 | O15: ='04-221Master'!AU21 -> 05.05.2022 | P15: ='04-221Master'!AV21 -> HDFC BANK | Q15: ='04-221Master'!AW21 -> A/C 07281140023731
A16: 7 | B16: ='04-221Master'!B22 -> Kanchupati Kondaiah | C16: ='04-221Master'!E22 -> U MALLESWARAMMA | D16: YES | E16: ='04-221Master'!F22 -> SQL DATABASE ADMINISTRATOR | F16: ='04-221Master'!W22 -> 30 | G16: ='04-221Master'!AM22 -> 52275.853 | H16: ='04-221Master'!AI22 -> 1554.609 | I16: N/A | J16: N/A | K16: N/A | L16: N/A | M16: =H16 -> 1554.609 | N16: =H16 -> 1554.609 | O16: ='04-221Master'!AU22 -> 05.05.2022 | P16: ='04-221Master'!AV22 -> UCO | Q16: ='04-221Master'!AW22 -> A/c no 16280110106877
A17: 8 | B17: ='04-221Master'!B23 -> Santosh Patel | C17: ='04-221Master'!E23 -> Kishorilal Patel | D17: YES | E17: ='04-221Master'!F23 -> Senior Support Engineer | F17: ='04-221Master'!W23 -> 30 | G17: ='04-221Master'!AM23 -> 143275.54 | H17: ='04-221Master'!AI23 -> 1554.609 | I17: N/A | J17: N/A | K17: N/A | L17: N/A | M17: =H17 -> 1554.609 | N17: =H17 -> 1554.609 | O17: ='04-221Master'!AU23 -> 05.05.2022 | P17: ='04-221Master'!AV23 -> Axis Bank | Q17: ='04-221Master'!AW23 -> A/c No: 919010057225623
A18: 9 | B18: ='04-221Master'!B24 -> Basweshwar Pawar | C18: ='04-221Master'!E24 -> Nandakumar eknath pawar | D18: YES | E18: ='04-221Master'!F24 -> Lead PMO | F18: ='04-221Master'!W24 -> 30 | G18: ='04-221Master'!AM24 -> 98276.285 | H18: ='04-221Master'!AI24 -> 1554.609 | I18: N/A | J18: N/A | K18: N/A | L18: N/A | M18: =H18 -> 1554.609 | N18: =H18 -> 1554.609 | O18: ='04-221Master'!AU24 -> 05.05.2022 | P18: ='04-221Master'!AV24 -> ICICI BANK | Q18: ='04-221Master'!AW24 -> 042401535769
A19: 10 | B19: ='04-221Master'!B25 -> Hemanth Mishra | C19: ='04-221Master'!E25 -> Satish Chandra Mishra | D19: YES | E19: ='04-221Master'!F25 -> Technology Analyst | F19: ='04-221Master'!W25 -> 30 | G19: ='04-221Master'!AM25 -> 108276.24 | H19: ='04-221Master'!AI25 -> 1554.609 | I19: N/A | J19: N/A | K19: N/A | L19: N/A | M19: =H19 -> 1554.609 | N19: =H19 -> 1554.609 | O19: ='04-221Master'!AU25 -> 05.05.2022 | P19: ='04-221Master'!AV25 -> ICICI BANK | Q19: ='04-221Master'!AW25 -> 057001509856
A20: 11 | B20: ='04-221Master'!B26 -> FAZALAHMED IRKAL | C20: ='04-221Master'!E26 -> CHANDSAHEB IRKAL | D20: YES | E20: ='04-221Master'!F26 -> SENIOR HADOOP ADMIN | F20: ='04-221Master'!W26 -> 22 | G20: ='04-221Master'!AM26 -> 49047.256 | H20: ='04-221Master'!AI26 -> 1554.609 | I20: N/A | J20: N/A | K20: N/A | L20: N/A | M20: =H20 -> 1554.609 | N20: =H20 -> 1554.609 | O20: ='04-221Master'!AU26 -> 05.05.2022 | P20: ='04-221Master'!AV26 -> SBI | Q20: ='04-221Master'!AW26 -> 32722181716
A21: 12 | B21: ='04-221Master'!B27 -> SUKRUTH YELLAMBOTLA | C21: ='04-221Master'!E27 -> Yellambotla Vijay Kumar | D21: YES | E21: ='04-221Master'!F27 -> SENIOR APPLICATION CONSULTANT | F21: ='04-221Master'!W27 -> 30 | G21: ='04-221Master'!AM27 -> 40275.693 | H21: ='04-221Master'!AI27 -> 1554.609 | I21: N/A | J21: N/A | K21: N/A | L21: N/A | M21: =H21 -> 1554.609 | N21: =H21 -> 1554.609 | O21: ='04-221Master'!AU27 -> 05.05.2022 | P21: ='04-221Master'!AV27 -> HDFC0000486 | Q21: ='04-221Master'!AW27 -> 50100468093660
... A30: 21 | B30: ='04-221Master'!B36 -> DiptiRanjan Dikhit | C30: ='04-221Master'!E36 -> Purna chandra | D30: YES | E30: ='04-221Master'!F36 -> Network Security Engineer | F30: ='04-221Master'!W36 -> 27 | G30: ='04-221Master'!AM36 -> 62515.637 | H30: ='04-221Master'!AI36 -> 1554.609 | I30: N/A | J30: N/A | K30: N/A | L30: N/A | M30: =H30 -> 1554.609 | N30: =H30 -> 1554.609 | O30: ='04-221Master'!AU36 -> 05.05.2022 | P30: ='04-221Master'!AV36 -> State Bank Of India | Q30: ='04-221Master'!AW36 -> 31162392468
F31: =SUM(F10:F30) -> 619 | G31: =SUM(G10:G30) -> 1890926.2 | H31: =SUM(H10:H30) -> 32646.789
L41: Signature of the Contractor with Seal

Sheet Deductions
A1: FORM XVI- REGISTER OF DEDUCTIONS FOR DAMAGE OR LOSS
A3: (Vide Rule 78(1) (a) (i) of Contract Labour (Regulation and Abolition) Maharashtra Rules 1971.
A4: Name and address of Contractor: GROTECH LANDSCAPE DEVELOPERS PVT.LTD. | D4: ='04-221Master'!F5 -> Burgeon IT Services Pvt.Ltd. | E4: Name and address of the establishment in / under which contract is carried on:
B5: ='04-221Master'!F6 -> Siri Mansion LIGB 436 Dr.A S Rao Nagar,Hyderabad | E5: ='04-221Master'!AP5 -> Burgeon IT Services Pvt.Ltd.
B6: ='04-221Master'!F7 -> 0 | E6: ='04-221Master'!AP6 -> Siri Mansion LIGB 436 Dr.A S Rao Nagar,Hyderabad
A7: Nature and Location of Work: | D7: ='04-221Master'!F8 -> IT SUPPORTIVE SERVICES& Pune SEZ Unit-1 | E7: Name and address of principal employer:
E8: ='04-221Master'!AP10 -> INFOSYS LTD.IL Pune SEZ Unit-I,Plot No. 24/3
E9: ='04-221Master'!AP11 -> Rajiv gandhi Info tech park,Village Mann,Pune,Maharashtra 411057
A11: S.No | B11: Name of workman | C11: Father's / Husband's Name | D11: Designation / Nature of employment | E11: Particulars of damage or loss | F11: Date of Damage or loss | G11: Whether workman showed cause against deduction | H11: Name of person in whose presence employee's explanation was heard | I11: Amount of deduction impossed | J11: Date of recovery | M11: Remarks
J12: No.of Instalments | K12: First Instalment | L12: Last instalment
A13: 1 | B13: 2 | C13: 3 | D13: 4 | E13: 5 | F13: 6 | G13: 7 | H13: 8 | I13: 9 | J13: 10 | K13: 11 | L13: 12 | M13: 13
B16: NO EMPLOYEE WAS IMPOSED DEDUCTIONS FOR DAMAGE OR LOSS FOR THE MONTH OF | H16: ='04-221Master'!D10 -> 44652
F39: Signature of the Contractor with Seal

Sheet Fines
A1: FORM XVII- REGISTER OF FINES
A3: (Vide Rule 78(1) (a) (i) of Contract Labour (Regulation and Abolition) Maharashtra Rules 1971
A4: Name and address of Contractor: | D4: ='04-221Master'!F5 -> Burgeon IT Services Pvt.Ltd. | E4: Name and address of the establishment in / under which contract is carried on:
B5: ='04-221Master'!F6 -> Siri Mansion LIGB 436 Dr.A S Rao Nagar,Hyderabad | E5: ='04-221Master'!AP5 -> Burgeon IT Services Pvt.Ltd.
B6: ='04-221Master'!F7 -> 0 | E6: ='04-221Master'!AP6 -> Siri Mansion LIGB 436 Dr.A S Rao Nagar,Hyderabad
A7: Nature and Location of Work: | D7: ='04-221Master'!F8 -> IT SUPPORTIVE SERVICES& Pune SEZ Unit-1 | E7: Name and address of principal employer:
E8: ='04-221Master'!AP10 -> INFOSYS LTD.IL Pune SEZ Unit-I,Plot No. 24/3
E9: ='04-221Master'!AP11 -> Rajiv gandhi Info tech park,Village Mann,Pune,Maharashtra 411057
A11: S.No | B11: Name of workman | C11: Father's / Husband's Name | D11: Designation / Nature of employment | E11: Act/Omission for which fine imposed | F11: Date of offence | G11: Whether workman showed cause against fine | H11: Name of person in whose presence employee's explanation was heard | I11: Wage-period and wge payable | J11: Amount of fine Imposed | K11: Date on which fine realised | L11: Remarks
A13: 1 | B13: 2 | C13: 3 | D13: 4 | E13: 5 | F13: 6 | G13: 7 | H13: 8 | I13: 9 | J13: 10 | K13: 11 | L13: 12
B16: NO EMPLOYEE WAS IMPOSED FINESFOR THE MONTH OF | H16: ='04-221Master'!D10 -> 44652
F38: Signature of the Contractor with Seal

Sheet Advances
A1: FORM XVIII- REGISTER OF ADVANCES
A3: (Vide Rule 78(1) (a) (i) of Contract Labour (Regulation and Abolition) Maharashtra Rules 1971
A4: Name and address of Contractor: | D4: ='04-221Master'!F5 -> Burgeon IT Services Pvt.Ltd. | E4: Name and address of the establishment in / under which contract is carried on:
B5: ='04-221Master'!F6 -> Siri Mansion LIGB 436 Dr.A S Rao Nagar,Hyderabad
B6: ='04-221Master'!F7 -> 0
A7: Nature and Location of Work: | D7: ='04-221Master'!F8 -> IT SUPPORTIVE SERVICES& Pune SEZ Unit-1 | E7: Name and address of principal employer:
E8: ='04-221Master'!AP10 -> INFOSYS LTD.IL Pune SEZ Unit-I,Plot No. 24/3
E9: ='04-221Master'!AP11 -> Rajiv gandhi Info tech park,Village Mann,Pune,Maharashtra 411057
A11: S.No | B11: Name of workman | C11: Father's / Husband's Name | D11: Designation / Nature of employment | E11: Wage period and wages payable | F11: Date and amount of advance given | G11: Purpose(s) for which advance made | H11: Number of instalments by which advance to be repaid | I11: Date and amount of each instalment repaid | J11: Date on which last instalment was repaid | K11: Remarks
A13: 1 | B13: 2 | C13: 3 | D13: 4 | E13: 5 | F13: 6 | G13: 7 | H13: 8 | I13: 9 | J13: 10 | K13: 11
B16: NO EMPLOYEE TAKEN ADVANCE FOR THE MONTH OF | F16: ='04-221Master'!D10 -> 44652
G39: Signature of the Contractor with Seal

Sheet Overtime
A1: FORM XIX- REGISTER OF OVERTIME
A3: (Vide Rule 78(1) (a) (i) of Contract Labour (Regulation and Abolition) Maharashtra Rules 1971
A4: Name and address of Contractor: GROTECH LANDSCAPE DEVELOPERS PVT.LTD. E-35 GREATER KAILASH ENCLAVE-1 NEW DELHI | D4: ='04-221Master'!F5 -> Burgeon IT Services Pvt.Ltd. | F4: Name and address of the establishment in which under contract is carried on:
B5: ='04-221Master'!F6 -> Siri Mansion LIGB 436 Dr.A S Rao Nagar,Hyderabad
B6: ='04-221Master'!F7 -> 0
A7: Nature and Location of Work: | D7: ='04-221Master'!F8 -> IT SUPPORTIVE SERVICES& Pune SEZ Unit-1 | F7: Name and address of principal employer:
F8: ='04-221Master'!AP10 -> INFOSYS LTD.IL Pune SEZ Unit-I,Plot No. 24/3
F9: ='04-221Master'!AP11 -> Rajiv gandhi Info tech park,Village Mann,Pune,Maharashtra 411057
A11: S.No | B11: Name of workman | C11: Father's / Husband's Name | D11: Sex | E11: Designation / Nature of employment | F11: Date on which overtime worked | G11: Total overtime worked or production in case of piece-rates | H11: Normal rate of wages | I11: Overtime rate of wages | J11: overtime earnings | K11: Date on which overtime wages paid | L11: Remarks
A13: 1 | B13: 2 | C13: 3 | D13: 4 | E13: 5 | F13: 6 | G13: 7 | H13: 8 | I13: 9 | J13: 10 | K13: 11 | L13: 12
B16: NO EMPLOYEE DONE OVERTIME FOR THE MONTH OF | F16: ='04-221Master'!D10 -> 44652
G33: Signature of the Contractor with Seal

Sheet Accident
A1: FORM 11
A3: ACCIDENT BOOK
A4: EMPLOYEE STATE INSURANCE CORPORATION
B5: (Regulation 66)
A7: S.No | B7: Date of Notice | C7: Time of Notice | D7: Name and Address of the Injured Person | E7: Sex | F7: Age | H7: Shift,Department and occupation of employee | I7: Details of Injury | P7: Signature and designation of the person who makes the entry in the accident book | Q7: Name,address and occupation of the two witnesses | R7: Remarks if any
G8: Insurance Number | N8: What exactly was the injured person doing at the time of accident | O8: Name,Occupation,address and signature or the thumb impression of the person(s) giving notice
I9: Cause | J9: Nature | K9: Date | L9: Time | M9: Place
A10: 1 | B10: 2 | C10: 3 | D10: 4 | E10: 5 | F10: 6 | G10: 7 | H10: 8 | I10: 9 | J10: 10 | K10: 11 | L10: 12 | M10: 13 | N10: 14 | O10: 15 | P10: 16 | Q10: 17 | R10: 18
B12: NO ACCIDENT OCCURRED FOR THE MONTH OF | F12: ='04-221Master'!D10 -> 44652
M27: Signature of the Contractor with Seal
M32: Signature of the Contractor with Seal

Sheet FORM A
B1: FORM A
B2: [See Rule 3 of Maternity Act Rules, 1965]
B3: MUSTER ROLL
B4: Name of [mine or circus]: | D4: ='04-221Master'!F5 -> Burgeon IT Services Pvt.Ltd. | E4: ='04-221Master'!F6 -> Siri Mansion LIGB 436 Dr.A S Rao Nagar,Hyderabad
B5: 1 | C5: Serial Number.
B6: 2 | C6: Name of woman and her father's (or, if married, husband's) name.
B7: 3 | C7: Date of appointment.
B8: 4 | C8: Nature of work.
B9: 5 | C9: Dates with month and year in which she is employed, laid off and not employed.
C10: Month | D10: No.of days employed | E10: No.of days laid off | F10: No.of days not employed | G10: Remarks
B17: 6 | C17: Date on which the woman gives notice under section 6.
B18: 7 | C18: Date of discharge/dismissal, if any.
B19: 8 | C19: Date of production of proof of pregnancy under section 6.
B20: 9 | C20: Date of birth of child.
B21: 10 | C21: Date of production of proof of delivery/miscarriage/ 1[Medical Termination of pregnancy/ tubectomy operation/death.]
B22: 11 | C22: Date of production of proof of illness referred to in section 10.
B23: 12 | C23: Date with the amount of maternity benefit paid in advance of expected delivery.
B24: 13 | C24: Date with the amount of subsequent payment of maternity benefit.
B25: 14 | C25: Date with the amount of bonus, if paid, under section 8.
B26: 15 | C26: Date with the amount of wages paid on account of leave under section 9.
B27: 15A | C27: Date with the amount of wages paid on account of leave under section 9A
B28: 16 | C28: Date with the amount of wages paid on account of leave under section 10 and period of leave granted
B29: 17 | C29: Name of the person nominated by the woman under section 6.
B30: 18 | C30: If the woman dies, the date of her death, the name of the person to whom maternity benefit and/or other amount was paid, the amount thereof, and the date of payment.
B31: 19 | C31: If the woman dies and the child survives, the name of the person to whom the amount of maternity benefit was paid on behalf of the child and the period for which it was paid.
B32: 20 | C32: Signature of the employer of 3[the mine or circus] authenticating the entries in the muster-roll.
B33: 21 | C33: Remarks column for the use of the Inspector.
B34: Certifited that no pregnant employee worked for the month of | G34: ='04-221Master'!D10 -> 44652
E36: For | F36: ='04-221Master'!F5 -> Burgeon IT Services Pvt.Ltd.
F38: Authorized Signatory

Sheet FORM B
B1: FORM B
B2: [See Rule 4(1) of Maternity Act Rules, 1965]
B3: Name of [mine or circus]: | D3: ='04-221Master'!F5 -> Burgeon IT Services Pvt.Ltd. | E3: ='04-221Master'!F6 -> Siri Mansion LIGB 436 Dr.A S Rao Nagar,Hyderabad
B6: This is to certify that I examined…. wife /daughter of ….. a woman employee in name of Mine or Circus on (Date)
D7: and found/ cannot discover that she is pregnant and is expected to be delivered of a child within (month/days) from the above
B8: mentioned date date/has undergone miscarriage/[Medical termination of pregnancy or tubectomy operation]/has been delivered
B9: of a child on….. (date) or is suffering from…..(date) from illness arising out of pregnancy/delivery/premature birth of a child or miscarriage/
B10: [Medical termination of pregnancy or tubectomy operation ].
D12: Signature, qualifications and designation of Medical Officer/Medical Practitioner.
B15: Date…..
B16: Definitions of "child" and "miscarriage" as in the Maternity Benefit Act, 1961.-
B17: 1. "Child" includes a still-born child.
B18: 2. "Miscarriage" means expulsion of the contents of a pregnant uterus at any period prior to or during the twenty-sixth week of pregnancy
B19: but does not include any miscarriage,the causing of which is punishable under the Indian Penal Code.
B20: Ins. by G.S.R. 70(E), dated 31st January, 1996 (w.e.f. 31-1-1996).
B22: Certifited that no pregnant employee worked for the month of | G22: ='04-221Master'!D10 -> 44652
E25: For | F25: ='04-221Master'!F5 -> Burgeon IT Services Pvt.Ltd.
F27: Authorized Signatory

Sheet FORM C
B1: FORM C
B2: [See Rule 4(4) of Maternity Act Rules, 1965]
B4: Name of [mine or circus]: | D4: ='04-221Master'!F5 -> Burgeon IT Services Pvt.Ltd. | E4: ='04-221Master'!F6 -> Siri Mansion LIGB 436 Dr.A S Rao Nagar,Hyderabad
B7: This is to certify that
B8: Smt……………………………….wife/daughter of ……………………….employed in ……………….(name of [Mine or Circus]
B9: expired on ……………………..before/during/after confinement. The child died on …./survives her.
D13: Signature, qualifications and designation of Medical Officer/Medical Practitioner.
C15: Ins. by G.S.R. 70(E), dated 31st January, 1996 (w.e.f. 31-1-1996).
B17: Certifited that no pregnant employee worked for the month of | G17: ='04-221Master'!D10 -> 44652
E20: For | F20: ='04-221Master'!F5 -> Burgeon IT Services Pvt.Ltd.
F22: Authorized Signatory

Sheet FORM D
B1: FORM D
B2: [See Rule 4(5) of Maternity Act Rules, 1965]
B4: Name of [mine or circus]: | D4: ='04-221Master'!F5 -> Burgeon IT Services Pvt.Ltd. | E4: ='04-221Master'!F6 -> Siri Mansion LIGB 436 Dr.A S Rao Nagar,Hyderabad
B7: This is to certify that I examined……………..wife/daughter of ……….a woman employed in ………..(name of [Mine or Circus ]
B8: and found that she has been delivered of a child/has undergone miscarriage on ….(date)
E11: Signature of registered Midwife
C13: Date….
C14: Definitions of "child" and "miscarriage" as in the Maternity Benefit Act, 1961-
C15: 1. "Child" includes a still-born child.
C16: 2. "Miscarriage" means expulsion of the contents of a pregnant uterus at any period prior to or during the twenty-sixth
C17: week of pregnancy but does not include any miscarriage, the causing of which is punishable under the Indian Penal Code.
C20: Subs. by G.S.R. 59(E), dated 27th February, 1975 (w.e.f. 1-3-1975).
B22: Certifited that no pregnant employee worked for the month of | G22: ='04-221Master'!D10 -> 44652
E25: For | F25: ='04-221Master'!F5 -> Burgeon IT Services Pvt.Ltd.
F27: Authorized Signatory

Sheet ESI cards Reg
C1: ='04-221Master'!F5 -> Burgeon IT Services Pvt.Ltd. | E1: ESI PAHECHAN CARDS ISSUE REGISTER
B2: S.No | C2: Name of the Employee | D2: ESI Number | E2: Issue Date | F2: Signature | G2: Remarks
B3: 1 | C3: ='04-221Master'!#REF! -> #REF! | D3: ='04-221Master'!#REF! -> #REF!
B4: 2 | C4: ='04-221Master'!#REF! -> #REF! | D4: ='04-221Master'!#REF! -> #REF!
B5: 3 | C5: ='04-221Master'!#REF! -> #REF! | D5: ='04-221Master'!#REF! -> #REF!
B6: 4 | C6: ='04-221Master'!#REF! -> #REF! | D6: ='04-221Master'!#REF! -> #REF!
B7: 5 | C7: ='04-221Master'!#REF! -> #REF! | D7: ='04-221Master'!#REF! -> #REF!
B8: 6 | C8: ='04-221Master'!#REF! -> #REF! | D8: ='04-221Master'!#REF! -> #REF!
B9: 7 | C9: ='04-221Master'!#REF! -> #REF! | D9: ='04-221Master'!#REF! -> #REF!
B10: 8 | C10: ='04-221Master'!#REF! -> #REF! | D10: ='04-221Master'!#REF! -> #REF!
B11: 9 | C11: ='04-221Master'!#REF! -> #REF! | D11: ='04-221Master'!#REF! -> #REF!
B12: 10 | C12: ='04-221Master'!#REF! -> #REF! | D12: ='04-221Master'!#REF! -> #REF!
B13: 11 | C13: ='04-221Master'!#REF! -> #REF! | D13: ='04-221Master'!#REF! -> #REF!
B14: 12 | C14: ='04-221Master'!#REF! -> #REF! | D14: ='04-221Master'!#REF! -> #REF!
... B22: 20 | C22: ='04-221Master'!#REF! -> #REF! | D22: ='04-221Master'!#REF! -> #REF!

Sheet Form-I
B1: FORM I
B2: NOMINATION AND DECLARATION FORM
B3: (Vide Rule 3 of Payment of wages Act Central & A.P Rules, 1936)
B4: Name and Address of the Contractor | H4: Name and Address of the Establishment in/under which Contract is carried on:
B7: =#REF! -> #REF! | H7: =#REF! -> #REF!
B9: =#REF! -> #REF! | H9: =#REF! -> #REF!
B12: Nature of work and location of work: | H12: Name and address of Principal Employer:
H15: =#REF! -> #REF!
B16: =#REF! -> #REF!
H17: =#REF! -> #REF!
B19: 1. Name of the person making nomination | H19: ='04-221Master'!#REF! -> #REF!
B20: 2. Father's/Husband name | H20: ='04-221Master'!#REF! -> #REF!
B21: 3. Date of Birth | H21: ='04-221Master'!#REF! -> #REF!
B22: 4. Sex | H22: ='04-221Master'!#REF! -> #REF!
B23: 5. Marital Status | H23: Un-Married
B24: 6.Address
B25: Permanent | H25: ='04-221Master'!#REF! -> #REF!
H26: ='04-221Master'!#REF! -> #REF!
H27: ='04-221Master'!#REF! -> #REF!
B28: Temporary | H28: ='04-221Master'!#REF! -> #REF!
H29: ='04-221Master'!#REF! -> #REF!
H30: ='04-221Master'!#REF! -> #REF!
B31: I hereby nominate the person(s)/cancel the nomination made by me previously and nominate the person(s) mentioned below to
B32: receive any amount due to me from the employer,in the event to my death.
B33: Name of the Nominee/nominees | E33: Address | G33: Nominee's relationship With the member | I33: Date of Birth | J33: Total amount of Share of accumulations | K33: If the nominee is minor,name,relationship and address of the guardian
B34: 1 | E34: 2 | G34: 3 | I34: 4 | J34: 5 | L34: 6
B35: ='04-221Master'!#REF! -> #REF! | E35: Same as permanant address | G35: Father | I35: 54 years | J35: 1 | K35: N/A
B39: 1.Certified that I have no family and should I acquire a family hereafter,the above nomination shall be deemed as cancelled.
B40: 2.Certified that my father/mother is/ are dependent upon me.
B41: 3.Strike out whichever is not applicable.
I43: Signature or the thumb impression of the employed person
F44: CERTIFCATE BY EMPLOYER
A45: Certified that the above declaration and nomination has been signed/thumb impressed before me by Shri/Smt/Kum | K45: ='04-221Master'!#REF! -> #REF!
A46: employed in my establishment after he/she has read the entry/entries have been read over to him/her by me and got confirmed by him/her.
F49: Signature or the employer or other authorized officer of the establiment and Designation
A50: Place | B50: Hyderabad | F50: ='04-221Master'!AP5 -> Burgeon IT Services Pvt.Ltd.
A51: Date | B51: ='04-221Master'!#REF! -> #REF! | F51: ='04-221Master'!AP6 -> Siri Mansion LIGB 436 Dr.A S Rao Nagar,Hyderabad
B53: FORM I
B54: NOMINATION AND DECLARATION FORM
B55: (Vide Rule 3 of Payment of wages Act Central & A.P Rules, 1936)
B56: Name and Address of the Contractor | H56: Name and Address of the Establishment in/under which Contract is carried on:
B59: ='04-221Master'!F5 -> Burgeon IT Services Pvt.Ltd. | H59: ='04-221Master'!AP5 -> Burgeon IT Services Pvt.Ltd.
B61: ='04-221Master'!F6 -> Siri Mansion LIGB 436 Dr.A S Rao Nagar,Hyderabad | H61: ='04-221Master'!AP6 -> Siri Mansion LIGB 436 Dr.A S Rao Nagar,Hyderabad
B64: Nature of work and location of work: | H64: Name and address of Principal Employer:
H67: ='04-221Master'!AP10 -> INFOSYS LTD.IL Pune SEZ Unit-I,Plot No. 24/3
B68: ='04-221Master'!F8 -> IT SUPPORTIVE SERVICES& Pune SEZ Unit-1
H69: ='04-221Master'!AP11 -> Rajiv gandhi Info tech park,Village Mann,Pune,Maharashtra 411057
B71: 1. Name of the person making nomination | H71: ='04-221Master'!#REF! -> #REF!
B72: 2. Father's/Husband name | H72: ='04-221Master'!#REF! -> #REF!
B73: 3. Date of Birth | H73: ='04-221Master'!#REF! -> #REF!
B74: 4. Sex | H74: ='04-221Master'!#REF! -> #REF!
B75: 5. Marital Status | H75: Un-Married
B76: 6.Address
B77: Permanent | H77: ='04-221Master'!#REF! -> #REF!
H78: ='04-221Master'!#REF! -> #REF!
H79: ='04-221Master'!#REF! -> #REF!
B80: Temporary | H80: ='04-221Master'!#REF! -> #REF!
H81: ='04-221Master'!#REF! -> #REF!
H82: ='04-221Master'!#REF! -> #REF!
B83: I hereby nominate the person(s)/cancel the nomination made by me previously and nominate the person(s) mentioned below to
B84: receive any amount due to me from the employer,in the event to my death.
B85: Name of the Nominee/nominees | E85: Address | G85: Nominee's relationship With the member | I85: Date of Birth | J85: Total amount of Share of accumulations | K85: If the nominee is minor,name,relationship and address of the guardian
B86: 1 | E86: 2 | G86: 3 | I86: 4 | J86: 5 | L86: 6
B87: ='04-221Master'!#REF! -> #REF! | E87: Same as permanant address | G87: Father | I87: 54 years | J87: 1 | K87: N/A
B91: 1.Certified that I have no family and should I acquire a family hereafter,the above nomination shall be deemed as cancelled.
B92: 2.Certified that my father/mother is/ are dependent upon me.
B93: 3.Strike out whichever is not applicable.
I95: Signature or the thumb impression of the employed person
F96: CERTIFCATE BY EMPLOYER
A97: Certified that the above declaration and nomination has been signed/thumb impressed before me by Shri/Smt/Kum | K97: ='04-221Master'!#REF! -> #REF!
A98: employed in my establishment after he/she has read the entry/entries have been read over to him/her by me and got confirmed by him/her.
F101: Signature or the employer or other authorized officer of the establiment and Designation
A102: Place | B102: Hyderabad | F102: ='04-221Master'!F5 -> Burgeon IT Services Pvt.Ltd.
A103: Date | B103: ='04-221Master'!#REF! -> #REF! | F103: ='04-221Master'!F6 -> Siri Mansion LIGB 436 Dr.A S Rao Nagar,Hyderabad
B107: FORM I
B108: NOMINATION AND DECLARATION FORM
B109: (Vide Rule 3 of Payment of wages Act Central & A.P Rules, 1936)
B110: Name and Address of the Contractor | H110: Name and Address of the Establishment in/under which Contract is carried on:
B113: ='04-221Master'!F5 -> Burgeon IT Services Pvt.Ltd. | H113: ='04-221Master'!AP5 -> Burgeon IT Services Pvt.Ltd.
B115: ='04-221Master'!F6 -> Siri Mansion LIGB 436 Dr.A S Rao Nagar,Hyderabad | H115: ='04-221Master'!AP6 -> Siri Mansion LIGB 436 Dr.A S Rao Nagar,Hyderabad
B118: Nature of work and location of work: | H118: Name and address of Principal Employer:
H121: ='04-221Master'!AP10 -> INFOSYS LTD.IL Pune SEZ Unit-I,Plot No. 24/3
B122: ='04-221Master'!F8 -> IT SUPPORTIVE SERVICES& Pune SEZ Unit-1
H123: ='04-221Master'!AP11 -> Rajiv gandhi Info tech park,Village Mann,Pune,Maharashtra 411057
B125: 1. Name of the person making nomination | H125: ='04-221Master'!#REF! -> #REF!
B126: 2. Father's/Husband name | H126: ='04-221Master'!#REF! -> #REF!
B127: 3. Date of Birth | H127: ='04-221Master'!#REF! -> #REF!
B128: 4. Sex | H128: ='04-221Master'!#REF! -> #REF!
B129: 5. Marital Status | H129: Un-Married
B130: 6.Address
B131: Permanent | H131: ='04-221Master'!#REF! -> #REF!
H132: ='04-221Master'!#REF! -> #REF!
H133: ='04-221Master'!#REF! -> #REF!
B134: Temporary | H134: ='04-221Master'!#REF! -> #REF!
H135: ='04-221Master'!#REF! -> #REF!
H136: ='04-221Master'!#REF! -> #REF!
B137: I hereby nominate the person(s)/cancel the nomination made by me previously and nominate the person(s) mentioned below to
B138: receive any amount due to me from the employer,in the event to my death.
B139: Name of the Nominee/nominees | E139: Address | G139: Nominee's relationship With the member | I139: Date of Birth | J139: Total amount of Share of accumulations | K139: If the nominee is minor,name,relationship and address of the guardian
B140: 1 | E140: 2 | G140: 3 | I140: 4 | J140: 5 | L140: 6
...

Sheet Form-2
K1: (FORM 2 REVISED)
B2: NOMINATION AND DECLARATION FORM FOR UNEXEMPTED/EXEMPTED ESTABLISHMENTS
B3: Declaration and Nomination Form under the Employees Provident Funds and Employees Pension Schemes
B4: (Paragraph 33 and 61(1) of the Employees Provident Fund Scheme 1952 and Paragraph 18 of the Employees Pension Scheme 1995)
B6: 1. Name of the person making nomination | H6: ='04-221Master'!#REF! -> #REF!
B7: 2. Father's/Husband name | H7: ='04-221Master'!#REF! -> #REF!
B8: 3. Date of Birth | H8: ='04-221Master'!#REF! -> #REF!
B9: 4. Sex | H9: ='04-221Master'!#REF! -> #REF!
B10: 5. Marital Status | H10: Un-Married
B11: 6.Address
B12: Permanent | H12: ='04-221Master'!#REF! -> #REF!
H13: ='04-221Master'!#REF! -> #REF!
H14: ='04-221Master'!#REF! -> #REF!
G15: PART-A(EPF)
B16: I hereby nominate the person(s)/cancel the nomination made by me previously and nominate the person(s) mentioned below to
B17: receive any amount due to me from the employer,in the event to my death.
B18: Name of the Nominee/nominees | E18: Address | G18: Nominee's relationship With the member | I18: Date of Birth | J18: Total amount of Share of accumulations | K18: If the nominee is minor,name,relationship and address of the guardian
B19: 1 | E19: 2 | G19: 3 | I19: 4 | J19: 5 | L19: 6
B20: ='04-221Master'!#REF! -> #REF! | E20: Same as Permanant Address | G20: Father | I20: 55 Years | J20: 1 | K20: N/A
B24: 1.Certified that I have no family and should I acquire a family hereafter,the above nomination shall be deemed as cancelled.
B25: 2.Certified that my father/mother is/ are dependent upon me.
B26: Strike out whichever is not applicable | J26: Signature/or thumb impression of the subscriber
G27: PART (EPS)
G28: Para 18
B29: I hereby furnish below particulars of the members of my family who would be eligible to receive Widow/Children Pension in the event of
B30: my premature death in service
B31: S.No | C31: Name & Address of the Family Member | I31: Age | J31: Relationship with the member
B32: 1 | E32: 2 | I32: 3 | K32: 4
B37: Certified that I have no family as defined in para 2 (vii) of the Employees's Family Pension Scheme 1995 and should I acquire a family hereafter
B38: I shall furnish Particulars there on in the above form.
B39: I hereby nominate the following person for receiving the monthly widow pension (admissible under para 16 2 (a) (1) & (ii) in the even of my death
B40: without leaving any eligible member for receiving pension.
B41: Name and Address of the nominee | G41: Date of Birth | I41: Relationship with member
B47: Date | C47: ='04-221Master'!#REF! -> #REF! | I47: Signature or thumb impression of the subscriber
F48: CERTIFCATE BY EMPLOYER
A49: Certified that the above declaration and nomination has been signed/thumb impressed before me by Shri/Smt/Kum | K49: ='04-221Master'!#REF! -> #REF!
A50: employed in my establishment after he/she has read the entry/entries have been read over to him/her by me and got confirmed by him/her.
F52: Signature or the employer or other authorized officer of the establiment and Designation
A53: Place | B53: Hyderabad | F53: ='04-221Master'!F5 -> Burgeon IT Services Pvt.Ltd.
A54: Date | B54: ='04-221Master'!#REF! -> #REF! | F54: ='04-221Master'!F6 -> Siri Mansion LIGB 436 Dr.A S Rao Nagar,Hyderabad
K55: (FORM 2 REVISED)
B56: NOMINATION AND DECLARATION FORM FOR UNEXEMPTED/EXEMPTED ESTABLISHMENTS
B57: Declaration and Nomination Form under the Employees Provident Funds and Employees Pension Schemes
B58: (Paragraph 33 and 61(1) of the Employees Provident Fund Scheme 1952 and Paragraph 18 of the Employees Pension Scheme 1995)
B60: 1. Name of the person making nomination | H60: ='04-221Master'!#REF! -> #REF!
B61: 2. Father's/Husband name | H61: ='04-221Master'!#REF! -> #REF!
B62: 3. Date of Birth | H62: ='04-221Master'!#REF! -> #REF!
B63: 4. Sex | H63: ='04-221Master'!#REF! -> #REF!
B64: 5. Marital Status | H64: Un-Married
B65: 6.Address
B66: Permanent | H66: ='04-221Master'!#REF! -> #REF!
H67: ='04-221Master'!#REF! -> #REF!
H68: ='04-221Master'!#REF! -> #REF!
G69: PART-A(EPF)
B70: I hereby nominate the person(s)/cancel the nomination made by me previously and nominate the person(s) mentioned below to
B71: receive any amount due to me from the employer,in the event to my death.
B72: Name of the Nominee/nominees | E72: Address | G72: Nominee's relationship With the member | I72: Date of Birth | J72: Total amount of Share of accumulations | K72: If the nominee is minor,name,relationship and address of the guardian
B73: 1 | E73: 2 | G73: 3 | I73: 4 | J73: 5 | L73: 6
B74: ='04-221Master'!#REF! -> #REF! | E74: Same as Permanant Address | G74: Father | I74: 55 Years | J74: 1 | K74: N/A
B78: 1.Certified that I have no family and should I acquire a family hereafter,the above nomination shall be deemed as cancelled.
B79: 2.Certified that my father/mother is/ are dependent upon me.
B80: Strike out whichever is not applicable | J80: Signature/or thumb impression of the subscriber
G81: PART (EPS)
G82: Para 18
B83: I hereby furnish below particulars of the members of my family who would be eligible to receive Widow/Children Pension in the event of
B84: my premature death in service
B85: S.No | C85: Name & Address of the Family Member | I85: Age | J85: Relationship with the member
B86: 1 | E86: 2 | I86: 3 | K86: 4
B91: Certified that I have no family as defined in para 2 (vii) of the Employees's Family Pension Scheme 1995 and should I acquire a family hereafter
B92: I shall furnish Particulars there on in the above form.
B93: I hereby nominate the following person for receiving the monthly widow pension (admissible under para 16 2 (a) (1) & (ii) in the even of my death
B94: without leaving any eligible member for receiving pension.
B95: Name and Address of the nominee | G95: Date of Birth | I95: Relationship with member
B101: Date | C101: ='04-221Master'!#REF! -> #REF! | I101: Signature or thumb impression of the subscriber
F102: CERTIFCATE BY EMPLOYER
A103: Certified that the above declaration and nomination has been signed/thumb impressed before me by Shri/Smt/Kum | K103: ='04-221Master'!#REF! -> #REF!
A104: employed in my establishment after he/she has read the entry/entries have been read over to him/her by me and got confirmed by him/her.
F106: Signature or the employer or other authorized officer of the establiment and Designation
A107: Place | B107: Hyderabad | F107: ='04-221Master'!F5 -> Burgeon IT Services Pvt.Ltd.
A108: Date | B108: ='04-221Master'!#REF! -> #REF! | F108: ='04-221Master'!F6 -> Siri Mansion LIGB 436 Dr.A S Rao Nagar,Hyderabad
K109: (FORM 2 REVISED)
B110: NOMINATION AND DECLARATION FORM FOR UNEXEMPTED/EXEMPTED ESTABLISHMENTS
B111: Declaration and Nomination Form under the Employees Provident Funds and Employees Pension Schemes
B112: (Paragraph 33 and 61(1) of the Employees Provident Fund Scheme 1952 and Paragraph 18 of the Employees Pension Scheme 1995)
B114: 1. Name of the person making nomination | H114: ='04-221Master'!#REF! -> #REF!
B115: 2. Father's/Husband name | H115: ='04-221Master'!#REF! -> #REF!
B116: 3. Date of Birth | H116: ='04-221Master'!#REF! -> #REF!
B117: 4. Sex | H117: ='04-221Master'!#REF! -> #REF!
B118: 5. Marital Status | H118: Un-Married
B119: 6.Address
B120: Permanent | H120: ='04-221Master'!#REF! -> #REF!
H121: ='04-221Master'!#REF! -> #REF!
H122: ='04-221Master'!#REF! -> #REF!
G123: PART-A(EPF)
B124: I hereby nominate the person(s)/cancel the nomination made by me previously and nominate the person(s) mentioned below to
B125: receive any amount due to me from the employer,in the event to my death.
B126: Name of the Nominee/nominees | E126: Address | G126: Nominee's relationship With the member | I126: Date of Birth | J126: Total amount of Share of accumulations | K126: If the nominee is minor,name,relationship and address of the guardian
B127: 1 | E127: 2 | G127: 3 | I127: 4 | J127: 5 | L127: 6
B128: ='04-221Master'!#REF! -> #REF! | E128: Same as Permanant Address | G128: Father | I128: 55 Years | J128: 1 | K128: N/A
B132: 1.Certified that I have no family and should I acquire a family hereafter,the above nomination shall be deemed as cancelled.
...

Sheet Form 11
I1: New Form No. 11 - Declaration Form
B2: (To be retained by t he employer for future reference)
D3: EMPLOYEES' PROVIDENT FUND ORGANIZATION | I3: Emp Code: | K3: ='04-221Master'!#REF! -> #REF!
C4: Employees' Provident Funds Scheme, 1952 (Paragraph 34 & 57) & | I4: Company | J4: ='04-221Master'!F5 -> Burgeon IT Services Pvt.Ltd.
C5: The Employees' Pension Scheme, 1995 (Paragraph 24) | I5: ='04-221Master'!F6 -> Siri Mansion LIGB 436 Dr.A S Rao Nagar,Hyderabad
A8: 1 | B8: Name of the Member | H8: ='04-221Master'!#REF! -> #REF!
A9: 2 | B9: Fathers' Name | F9: Husband's Name | H9: ='04-221Master'!#REF! -> #REF!
B10: (Please tick whichever is applicable)
A11: 3 | B11: Date of Birth (DD/MM/YYYY) | H11: ='04-221Master'!#REF! -> #REF!
A12: 4 | B12: Gender (Male/Female/Transgender) | H12: ='04-221Master'!#REF! -> #REF!
A13: 5 | B13: Marital Status(married / Unmarried / Widow/divorce) | H13: UNMARRIED
A14: 6 | B14: (a) | C14: Email Id
B15: (b) | C15: Mobile No.
A16: 7 | B16: Whether earlier a member of the Employees' Provident Fund Scheme, 1952 ? | H16: Yes | K16: No
A17: 8 | B17: Whether earlier a member of the Employees' Pension Scheme, 1995? | H17: Yes | K17: No
F18: Previous employment details [if Yes to 7 &/or 8 above]
A19: 9 | B19: a) | C19: Universal Account Number
B20: b) | C20: Previous PF Account Number
B21: C) | C21: Date of exit from previous employment (DD/MM/YYYY)
B22: d) | C22: Scheme Certificate No. (if issued)
B23: e) | C23: Pension Payment Order (PPO) No. (if issued)
A24: 10 | B24: a) | C24: International Worker | H24: Yes | K24: No
B25: b) | C25: If yes, state country of origin(India/Name of other country)
B26: C) | C26: Passport No.
B27: d) | C27: Validity of passport [(DD/MM/YYYY) to (DD/MM/YYYY)]
E28: KYC Details (attach self attested copies of following KYCs)
A29: 11 | B29: a) | C29: Bank Account No. & IFS Code
B30: b) | C30: AADHAR No.
B31: c) | C31: Permanent Account No. (PAN), if available
F32: UNDERTAKING
B33: 1) | C33: Certified that the particulars are true to the best of my knowledge.
B34: 2) | C34: I authorize EPFO to use my Aadhar for verification/authentication/eKYC purpose for service delivery.
B35: 3) | C35: Kindly transfer the funds and service details, if applicable from the previous PF account as declared above to the present P.F. Account (The Transfer would be possible only if the identified KYC details approved by previous employer has been verified by present employer
B36: 4) | C36: In case of changes in above details, the same will be intimated to employer at the earliest.
C37: Date : | D37: ='04-221Master'!#REF! -> #REF!
C38: Place: | D38: Hyderabad | J38: Signature of Member
F40: DECLARATION BY PRESENT EMPLOYER
A41: A) | B41: The member Mr./Ms./Mrs. | E41: ='04-221Master'!#REF! -> #REF! | H41: has joined on | J41: ='04-221Master'!#REF! -> #REF! | K41: and has been allotted PF Number
B42: ='04-221Master'!#REF! -> #REF!
A43: B) | B43: In case the person was earlier not a member of EPF Scheme, 1952 and EPS, 1995:
B44: (Post allotment of UAN) The UAN allotted for the member is
B45: Please Tick the Appropriate Option:
B46: The KYC details of the above member in the UAN database
B47: Have not been uploaded
B48: Have been uploaded but not approved
B49: Have been uploaded and approved with DSC
A50: C) | B50: In case the person was earlier a member of EPF Scheme, 1952 and EPS, 1995:
B51: The above PF Account Number/ UAN of the member as mentioned in (A) above has been tagged with his/her UAN/Previous Member ID as declared by member.
B52: Please Tick the Appropriate Option:
B53: The KYC details of the above member in the UAN database have been approved with DSC and transfer request has been generated on portal.
B54: As the DSC of establishment are not registered with EPFO, the member has been informed to file physical claim (Form 13) for transfer of funds
B55: from his previous establishment.
B56: Date | C56: =D37 -> #REF! | I56: Signature of Employer with seal of Establishment
I59: New Form No. 11 - Declaration Form
B60: (To be retained by t he employer for future reference)
D61: EMPLOYEES' PROVIDENT FUND ORGANIZATION | I61: Emp Code: | K61: ='04-221Master'!#REF! -> #REF!
C62: Employees' Provident Funds Scheme, 1952 (Paragraph 34 & 57) & | I62: Company | J62: ='04-221Master'!F5 -> Burgeon IT Services Pvt.Ltd.
C63: The Employees' Pension Scheme, 1995 (Paragraph 24) | I63: ='04-221Master'!F6 -> Siri Mansion LIGB 436 Dr.A S Rao Nagar,Hyderabad
A65: 1 | B65: Name of the Member | H65: ='04-221Master'!#REF! -> #REF!
A66: 2 | B66: Fathers' Name | F66: Husband's Name | H66: ='04-221Master'!#REF! -> #REF!
B67: (Please tick whichever is applicable)
A68: 3 | B68: Date of Birth (DD/MM/YYYY) | H68: ='04-221Master'!#REF! -> #REF!
A69: 4 | B69: Gender (Male/Female/Transgender) | H69: ='04-221Master'!#REF! -> #REF!
A70: 5 | B70: Marital Status(married / Unmarried / Widow/divorce) | H70: Unmarried
A71: 6 | B71: (a) | C71: Email Id
B72: (b) | C72: Mobile No.
A73: 7 | B73: Whether earlier a member of the Employees' Provident Fund Scheme, 1952 ? | H73: Yes | K73: No
A74: 8 | B74: Whether earlier a member of the Employees' Pension Scheme, 1995? | H74: Yes | K74: No
F75: Previous employment details [if Yes to 7 &/or 8 above]
A76: 9 | B76: a) | C76: Universal Account Number
B77: b) | C77: Previous PF Account Number
B78: C) | C78: Date of exit from previous employment (DD/MM/YYYY)
B79: d) | C79: Scheme Certificate No. (if issued)
B80: e) | C80: Pension Payment Order (PPO) No. (if issued)
A81: 10 | B81: a) | C81: International Worker | H81: Yes | K81: No
B82: b) | C82: If yes, state country of origin(India/Name of other country)
B83: C) | C83: Passport No.
B84: d) | C84: Validity of passport [(DD/MM/YYYY) to (DD/MM/YYYY)]
E85: KYC Details (attach self attested copies of following KYCs)
A86: 11 | B86: a) | C86: Bank Account No. & IFS Code
B87: b) | C87: AADHAR No.
B88: c) | C88: Permanent Account No. (PAN), if available
F89: UNDERTAKING
B90: 1) | C90: Certified that the particulars are true to the best of my knowledge.
B91: 2) | C91: I authorize EPFO to use my Aadhar for verification/authentication/eKYC purpose for service delivery.
B92: 3) | C92: Kindly transfer the funds and service details, if applicable from the previous PF account as declared above to the present P.F. Account (The Transfer would be possible only if the identified KYC details approved by previous employer has been verified by present employer
B93: 4) | C93: In case of changes in above details, the same will be intimated to employer at the earliest.
C94: Date : | D94: ='04-221Master'!#REF! -> #REF!
C95: Place: | D95: Hyderabad | J95: Signature of Member
F97: DECLARATION BY PRESENT EMPLOYER
A98: A) | B98: The member Mr./Ms./Mrs. | E98: ='04-221Master'!#REF! -> #REF! | H98: has joined on | J98: ='04-221Master'!#REF! -> #REF! | K98: and has been allotted PF Number
B99: ='04-221Master'!#REF! -> #REF!
A100: B) | B100: In case the person was earlier not a member of EPF Scheme, 1952 and EPS, 1995:
B101: (Post allotment of UAN) The UAN allotted for the member is
B102: Please Tick the Appropriate Option:
B103: The KYC details of the above member in the UAN database
B104: Have not been uploaded
B105: Have been uploaded but not approved
B106: Have been uploaded and approved with DSC
A107: C) | B107: In case the person was earlier a member of EPF Scheme, 1952 and EPS, 1995:
...

Sheet Form-F
A1: F O R M – F
A2: [See sub-Rule (1) of Rule 6] The Payment of Gratuity Rules, 1973:
A3: NOMINATION
A4: To
A5: ='04-221Master'!F5 -> Burgeon IT Services Pvt.Ltd.
A6: ='04-221Master'!F6 -> Siri Mansion LIGB 436 Dr.A S Rao Nagar,Hyderabad
A8: 1. I, Shri / Shrimati / Kumari | C8: ='04-221Master'!#REF! -> #REF!
A9: whose particulars are given in the statement below, hereby nominate the person(s) mentioned below to receive the gratuity payable after my death as also the gratuity standing to my credit in the event of my death before that amount has become payable, or having become payable has not been paid and direct that the said amount of gratuity shall be paid in proportion indicated against the name(s) of the nominee(s).
A11: 2. I hereby certify that the person(s) mentioned is a /are member(s) of my family within the meaning of clause (h) of Section 2 of the Payment of Gratuity Act, 1972.
A13: 3. I hereby declare that I have no family within the meaning of clause (h) of Section 2 of the said Act.
A15: 4. (a) My father/mother/parents is/are not dependent on me
A16: (b) My husband’s father/mother/parents is/are not dependent on my husband.
A18: 5. I have excluded my husband from my family by a notice dated the ……………. to the Controlling Authority in terms of the proviso to clause (h) of Section 2 of the said Act.
A20: 6. Nomination made herein invalidates my previous nomination.
A22: NOMINEE(S)
A23: Name in full with full address of nominee(s): | B23: Relationship with the empliyee | C23: Age of nominee: | D23: Proportion by which the gratuity will be shared:
A24: 1 | B24: 2 | C24: 3 | D24: 4
A25: ='04-221Master'!#REF! -> #REF! | B25: Father | C25: 54 Years | D25: 1
A29: STATEMENT
A31: 1. Name of employee in full: | C31: ='04-221Master'!#REF! -> #REF!
A32: 2. Sex: | C32: ='04-221Master'!#REF! -> #REF!
A33: 3. Religion: | C33: Muslim
A34: 4. Whether unmarried/married/widow/widower: | C34: Un married
A35: 5. Department/Branch/Section where employed: | C35: ='04-221Master'!#REF! -> #REF!
A36: 6. Post held with Ticket No. or Serial No. if any: | C36: ='04-221Master'!#REF! -> #REF!
A37: 7. Date of appointment: | C37: ='04-221Master'!#REF! -> #REF!
A38: 8. Permanent address:
C39: ='04-221Master'!#REF! -> #REF!
C40: ='04-221Master'!#REF! -> #REF!
C41: ='04-221Master'!#REF! -> #REF!
A42: Place: | B42: Hyderabad
A43: Date: | B43: ='04-221Master'!#REF! -> #REF! | C43: Signature/Thumb impression of the employee
A45: Declaration by witnesses:
A46: Nomination signed/thumb impressed before me:
A48: Name in full and full address of witnesses: | C48: Signature of witnesses:
A49: 1 | C49: 1
A50: 2 | C50: 2
C51: Certificate by the Employer
A52: Certified that the particulars of the above nomination have been verified and recorded in t his establishment
A53: Employer's reference No, if any
C55: Signature of the employer/Officer authorized
C56: Designation
C57: Name address of the establishment or rubber stamp there of
C58: ='04-221Master'!F5 -> Burgeon IT Services Pvt.Ltd.
A59: Place: | B59: =B42 -> Hyderabad | C59: ='04-221Master'!F6 -> Siri Mansion LIGB 436 Dr.A S Rao Nagar,Hyderabad
A60: Date: | B60: =B43 -> #REF!
B61: Acknowledgment by the Employee
A62: Received the duplicate of the nomination in Form 'F'Filled by me and duly certified by the employer
A63: Date: | B63: =B60 -> #REF!
A64: Note: Strike out words/paragraph not applicable | D64: Signature of the Employee
A69: F O R M – F
A70: [See sub-Rule (1) of Rule 6] The Payment of Gratuity Rules, 1973:
A71: NOMINATION
A72: To
A73: ='04-221Master'!F5 -> Burgeon IT Services Pvt.Ltd.
A74: ='04-221Master'!F6 -> Siri Mansion LIGB 436 Dr.A S Rao Nagar,Hyderabad
A76: 1. I, Shri / Shrimati / Kumari | C76: ='04-221Master'!#REF! -> #REF!
A77: whose particulars are given in the statement below, hereby nominate the person(s) mentioned below to receive the gratuity payable after my death as also the gratuity standing to my credit in the event of my death before that amount has become payable, or having become payable has not been paid and direct that the said amount of gratuity shall be paid in proportion indicated against the name(s) of the nominee(s).
A79: 2. I hereby certify that the person(s) mentioned is a /are member(s) of my family within the meaning of clause (h) of Section 2 of the Payment of Gratuity Act, 1972.
A81: 3. I hereby declare that I have no family within the meaning of clause (h) of Section 2 of the said Act.
A83: 4. (a) My father/mother/parents is/are not dependent on me
A84: (b) My husband’s father/mother/parents is/are not dependent on my husband.
A86: 5. I have excluded my husband from my family by a notice dated the ……………. to the Controlling Authority in terms of the proviso to clause (h) of Section 2 of the said Act.
A88: 6. Nomination made herein invalidates my previous nomination.
A90: NOMINEE(S)
A91: Name in full with full address of nominee(s): | B91: Relationship with the empliyee | C91: Age of nominee: | D91: Proportion by which the gratuity will be shared:
A92: 1 | B92: 2 | C92: 3 | D92: 4
A93: ='04-221Master'!#REF! -> #REF! | B93: Father | C93: 54 Years | D93: 1
A97: STATEMENT
A99: 1. Name of employee in full: | C99: ='04-221Master'!#REF! -> #REF!
A100: 2. Sex: | C100: ='04-221Master'!#REF! -> #REF!
A101: 3. Religion: | C101: Hindu
A102: 4. Whether unmarried/married/widow/widower: | C102: Un married
A103: 5. Department/Branch/Section where employed: | C103: ='04-221Master'!#REF! -> #REF!
A104: 6. Post held with Ticket No. or Serial No. if any: | C104: ='04-221Master'!#REF! -> #REF!
A105: 7. Date of appointment: | C105: ='04-221Master'!#REF! -> #REF!
A106: 8. Permanent address:
C107: ='04-221Master'!#REF! -> #REF!
C108: ='04-221Master'!#REF! -> #REF!
C109: ='04-221Master'!#REF! -> #REF!
A110: Place: | B110: Hyderabad
A111: Date: | B111: ='04-221Master'!#REF! -> #REF! | C111: Signature/Thumb impression of the employee
A113: Declaration by witnesses:
A114: Nomination signed/thumb impressed before me:
A116: Name in full and full address of witnesses: | C116: Signature of witnesses:
A117: 1 | C117: 1
A118: 2 | C118: 2
C119: Certificate by the Employer
A120: Certified that the particulars of the above nomination have been verified and recorded in t his establishment
A121: Employer's reference No, if any
C123: Signature of the employer/Officer authorized
C124: Designation
C125: Name address of the establishment or rubber stamp there of
C126: ='04-221Master'!F5 -> Burgeon IT Services Pvt.Ltd.
A127: Place: | B127: =B110 -> Hyderabad | C127: ='04-221Master'!F6 -> Siri Mansion LIGB 436 Dr.A S Rao Nagar,Hyderabad
A128: Date: | B128: =B111 -> #REF!
B129: Acknowledgment by the Employee
A130: Received the duplicate of the nomination in Form 'F'Filled by me and duly certified by the employer
A131: Date: | B131: =B128 -> #REF!
A132: Note: Strike out words/paragraph not applicable | D132: Signature of the Employee
...

Sheet Serive Certificate
B4: FORM XV
B5: [Vide rule 77 of Contract Labour (Regul. & Abolition) Central & A.P. Rules, 1971]
B7: SERVICE CERTIFICATE
B9: Name and address of Contractor : | G9: Name and address of establishment in / under which contract is caried on :
B11: ='04-221Master'!F5 -> Burgeon IT Services Pvt.Ltd. | G11: ='04-221Master'!AP5 -> Burgeon IT Services Pvt.Ltd.
B13: ='04-221Master'!F6 -> Siri Mansion LIGB 436 Dr.A S Rao Nagar,Hyderabad | G13: ='04-221Master'!AP6 -> Siri Mansion LIGB 436 Dr.A S Rao Nagar,Hyderabad
B17: Nature and Location of work: | G17: Name and address of Principal Employer :
G19: ='04-221Master'!AP10 -> INFOSYS LTD.IL Pune SEZ Unit-I,Plot No. 24/3
B21: ='04-221Master'!F8 -> IT SUPPORTIVE SERVICES& Pune SEZ Unit-1 | G21: ='04-221Master'!AP11 -> Rajiv gandhi Info tech park,Village Mann,Pune,Maharashtra 411057
B26: Name and address of the workman :
B31: Age or date of Birth :
B33: Identification Marks :
B35: Father's / Husband's Name :
B38: Sl.No. | C38: Total period for which employed | E38: Nature of work done | G38: Rate of wage ( with particulars of units in case of piece work) | J38: Remarks
C40: From | D40: To
B41: 1 | C41: 2 | D41: 3 | E41: 4 | G41: 5 | J41: 6
H56: Signature of the Employer with Seal
