Workbook

Sheet APRIL2 PUNE SEZ UNIT-2 WM Reg
A1: FORM IX- REGISTER OF PERSONS EMPLOYED
A3: (Vide Rule 78(1) (a) (i) of Contract Labour (Regulation and Abolition) Central /Maharastra.Rules 1974
A4: Name and address of Contractor:burgeon IT services Pvt.Ltd. | F4: Name and address of the establishment in / under which contract is carried on: burgeon IT services Pvt.Ltd. Siri mansion LIGH 436 DR.A S Rao nagar,Hyderabad
A5: Siri Mansion LIGB 436 Dr.A S Rao Nagar,Hyderabad
A7: Name and address of Contractor:burgeon IT services Pvt.Ltd. | F7: Name and address of principal employer:
F8: ='0422Master'!AP10 -> INFOSYS LTD.IL Pune SEZ Unit-II,Plot No. 24/3
F9: Rajiv gandhi Info tech park,Village Mann,Pune,Maharashtra 411057
A11: S.No | B11: Name and Surname of workman | C11: Age | D11: SEX | E11: Father's/Husband's name | F11: Nature of Employement/Designation | G11: Permanent Home Address of worken | H11: Local Address | I11: Date of commencement of Employment | J11: Signature or Thumb impression of workman | K11: Date of Temination of Employment | M11: Remarks
L12: Reason for Termination
A13: 1 | B13: 2 | C13: 3 | E13: 4 | F13: 5 | G13: 6 | H13: 7 | I13: 8 | J13: 9 | K13: 10 | M13: 11
A14: 1 | B14: Sumith Sharma | C14: 31356 | D14: MALE | E14: Mahesh Chand jain | F14: Project Manager | G14: 492/1, shivloxpuri, konkerkhem, Meerat contonment UP250001 | H14: 492/1, shivloxpuri, konkerkhem, Meerat contonment UP250001 | I14: 43160 | K14: 43630 | L14: RESIGNATION
A15: 2 | B15: Prithvi Raj Patil | C15: 24/06/1980 | D15: MALE | E15: shripati vittal patil | F15: Project Manager | G15: flat no 304, D wing, B Building ramakrishna paradise, Survey No 113, Near Bhairavnath Temple, Dhayan, Pune city 411041 | H15: flat no 304, D wing, B Building ramakrishna paradise, Survey No 113, Near Bhairavnath Temple, Dhayan, Pune city 411041 | I15: 43160 | K15: 43644 | L15: RESIGNATION
A16: 3 | B16: Nikhil Ghaikwad | C16: 29/03/1985 | D16: MALE | E16: shrikanth govind | F16: Project Coordinator | G16: 5th Floor, 113/114, nanapet, Nawawada, pune 411002 | H16: 5th Floor, 113/114, nanapet, Nawawada, pune 411002 | I16: 43160 | K16: 43553 | L16: RESIGNATION
A17: 4 | B17: Abhik Pandit | C17: 31870 | D17: MALE | E17: Amarnath Pandit | F17: Project Coordinator | G17: Flat B2, Niharika apts, Vivekanand nagar, podrah, Howrah,WB 711109 | H17: Flat B2, Niharika apts, Vivekanand nagar, podrah, Howrah,WB 711109 | I17: 43193 | K17: 43496 | L17: RESIGNATION
A18: 5 | B18: Neha Verma | C18: 27/10/1988 | D18: MALE | E18: Pramod kumar verma | F18: Project Coordinator | G18: post shewra ps patory ward no 7, Hazrat shiura, Samastipur, Bihar 848504 | H18: post shewra ps patory ward no 7, Hazrat shiura, Samastipur, Bihar 848504 | I18: 43194 | K18: 43511 | L18: RESIGNATION
A19: 6 | B19: Kavita Gosavi | C19: 23/08/1985 | D19: MALE | E19: Govindgeer vikramgeer | F19: Project Coordinator | G19: B1-303, saptashri CHS, Anand Nagar, Manpada Road, Dombivalli, MH Thane 421201 | H19: B1-303, saptashri CHS, Anand Nagar, Manpada Road, Dombivalli, MH Thane 421201 | I19: 43208 | K19: 43560 | L19: RESIGNATION
A20: 7 | B20: Bhumika Sachdeva | C20: 19/05/1984 | D20: MALE | E20: Vikram sachdeva | F20: Technical Consultant | G20: 8/416, Anbu Illam, Pilliyar koli street,pozhichellur, chennai, TN 600074 | H20: 8/416, Anbu Illam, Pilliyar koli street,pozhichellur, chennai, TN 600074 | I20: 43194 | K20: 43599 | L20: RESIGNATION
A21: 8 | B21: Vivek Hariharan | C21: 31206 | D21: MALE | E21: P C Hariharan | F21: Project Coordinator | G21: A-10/1, Telco Soc No 9, Sector-24, Pradhikaran, Pune, MH 411044 | H21: A-10/1, Telco Soc No 9, Sector-24, Pradhikaran, Pune, MH 411044 | I21: 43221 | K21: 43552 | L21: RESIGNATION
A22: 9 | B22: Vishaka Salvi | C22: 31513 | D22: MALE | E22: shivaji ganpat | F22: Client Delivery Manager | G22: 302, New Ekta CHS, sector -8, airholi, NAVI MUMBAI 400708 | H22: 302, New Ekta CHS, sector -8, airholi, NAVI MUMBAI 400708 | I22: 43236 | K22: 43644 | L22: RESIGNATION
A23: 10 | B23: DHANANJAY RAMESH GHODMARE | C23: 25/03/1984 | D23: MALE | E23: Ramesh ramji ghodmare | F23: Associate Lead | G23: F37, Indraprastha Apts, pawansuth nagar, nandangan, nagpur, 440009 | H23: F37, Indraprastha Apts, pawansuth nagar, nandangan, nagpur, 440009 | I23: 43241 | K23: 43539 | L23: RESIGNATION
A24: 11 | B24: KAPIL SOPANRAO RASAL | C24: 30804 | D24: MALE | E24: sopan srimant rasal | F24: Project Coordinator | G24: vivekanand puram,kokat f nagar,Latur,413512 | H24: vivekanand puram,kokat f nagar,Latur,413512 | I24: 43248 | K24: 43532 | L24: RESIGNATION
A25: 12 | B25: PRERNA NARAYAN | C25: 28/02/1987 | D25: MALE | E25: Roop Krishen Narayan | F25: Project Manager | G25: Flat no 1302, Towerr-12, Asbridge c, Lodha belmondo gahunje, OPP MCA cricket stadium, Pune MH 412021 | H25: Flat no 1302, Towerr-12, Asbridge c, Lodha belmondo gahunje, OPP MCA cricket stadium, Pune MH 412021 | I25: 43248 | K25: 43602 | L25: RESIGNATION
A26: 13 | B26: VYANKATESH NANDAPURKAR | C26: 19/10/1969 | D26: MALE | E26: Devidas keshavrao | F26: Project Manager | G26: Flat No 402, Wamen Ganesh Paradise, shinde nagar, maratha mandir,Bavdhan pune MH 411021 | H26: Flat No 402, Wamen Ganesh Paradise, shinde nagar, maratha mandir,Bavdhan pune MH 411021 | I26: 43258 | K26: 43595 | L26: RESIGNATION
A27: 14 | B27: PRAVIN PANDURANG WAJE | C27: 31233 | D27: MALE | E27: pandurang dhondu waje | F27: Wintel Administrator | G27: shree society building no D-9, Room no 1/3, Sector 22, Near Matabaai hospital,koper khairne, Navi mumbai, thane , MH 400.079 | H27: shree society building no D-9, Room no 1/3, Sector 22, Near Matabaai hospital,koper khairne, Navi mumbai, thane , MH 400.079 | I27: 43262 | K27: 43630 | L27: RESIGNATION
A28: 15 | B28: PRIYA BASWANT MORE | C28: 18/04/1990 | D28: MALE | E28: Baswant More | F28: Project Coordinator | G28: At Post Rajgoli khurd, Tal Chandgad, Dist kolhapur, Maharashtra 416508 | H28: At Post Rajgoli khurd, Tal Chandgad, Dist kolhapur, Maharashtra 416508 | I28: 43263 | K28: 43504 | L28: RESIGNATION
A29: 16 | B29: VINITA SAWANT | C29: 19/01/1989 | D29: MALE | E29: Anand rao | F29: Project Manager | G29: B12/1 6, Trimurti CHS, sec-24, JUI Nagar, Navi mumbai, 400705 | H29: B12/1 6, Trimurti CHS, sec-24, JUI Nagar, Navi mumbai, 400705 | I29: 43271 | K29: 43623 | L29: RESIGNATION
A30: 17 | B30: SUMIT SANJAY JOSHI | C30: 23/06/1988 | D30: MALE | E30: Sanjay joshi | F30: Project Coordinator | G30: 127 A/P Bahirewadi, Tal-ajara,Dist kolhapur, MH 416220 | H30: 127 A/P Bahirewadi, Tal-ajara,Dist kolhapur, MH 416220 | I30: 43271 | K30: 43490 | L30: RESIGNATION
A31: 18 | B31: BHAGYASHRI awtare | C31: 17/09/1992 | D31: MALE | E31: Bhagwan nathu awate | F31: Project Coordinator | G31: Gangapur, BK Tal ambegaon, shiroli, Pune 410516 | H31: Gangapur, BK Tal ambegaon, shiroli, Pune 410516 | I31: 43276 | K31: 43616 | L31: RESIGNATION
A32: 19 | B32: RAHUL CHAKRADHARE | C32: 17/11/1991 | D32: MALE | E32: vasant moreshwar chakradhare | F32: Project Coordinator | G32: flat no 1001, R- Building, 10th floor, Tanish orchid phase -3, charholi patha pune MH 412105 | H32: flat no 1001, R- Building, 10th floor, Tanish orchid phase -3, charholi patha pune MH 412105 | I32: 43276 | K32: 43616 | L32: RESIGNATION
A33: 20 | B33: Kazi Sayyedsalman Jalaluddin | C33: 23/05/1991 | D33: MALE | E33: Jalaluddin Rashid Kazi | F33: Project Manager | G33: A - 702, Suyog Leher, Near Sai Service, Kondhwa Budruk, Pune - 411048. | H33: A - 702, Suyog Leher, Near Sai Service, Kondhwa Budruk, Pune - 411048. | I33: 43285 | K33: 43630 | L33: RESIGNATION
A34: 21 | B34: Asish kumar satapathy | C34: 33851 | D34: MALE | E34: Harshad Trivedi | F34: SR.Project Coordinator | G34: AT/P-MUNGURWADI,TAL-GADHINGLAJ,DIST-KOLHAPUR, MAHARASHTRA 416503 | H34: AT/P-MUNGURWADI,TAL-GADHINGLAJ,DIST-KOLHAPUR, MAHARASHTRA 416503 | I34: 43286 | K34: 43644 | L34: RESIGNATION
A35: 22 | B35: Pritanjali Patil | C35: 33189 | D35: MALE | E35: Narendra Singh Patil | F35: Project Coordinator | G35: 52, Vidyanagar, Bodwad, Jalgaon Dist, MH | H35: 52, Vidyanagar, Bodwad, Jalgaon Dist, MH | I35: 43283 | K35: 43665 | L35: RESIGNATION
A36: 23 | B36: Madhura Divekar | C36: 24/05/1990 | D36: MALE | E36: Shaunak Divekar | F36: Project Coordinator | G36: Flat No M104, Ramyanagri, Opp Central bank, Bibvewadi, Pune 411037 | H36: Flat No M104, Ramyanagri, Opp Central bank, Bibvewadi, Pune 411037 | I36: 43290 | K36: 43707 | L36: RESIGNATION
A37: 24 | B37: Yash Trivedi | C37: 23/03/1992 | D37: MALE | E37: Harshad Trivedi | F37: Project Coordinator | G37: G/7, Jayambe Colony, Babul Pada,achole road, nalasopara E 401209 | H37: G/7, Jayambe Colony, Babul Pada,achole road, nalasopara E 401209 | I37: 43293 | K37: 43623 | L37: RESIGNATION
A38: 25 | B38: Sumit pande | C38: 25/09/1991 | D38: MALE | E38: Janardhan pande | F38: Project Coordinator | G38: SS/499, SECTOR N1 ALIGANJ LUCKNOW UTTAR PRADESH 226024 | H38: SS/499, SECTOR N1 ALIGANJ LUCKNOW UTTAR PRADESH 226024 | I38: 43297 | K38: 43658 | L38: RESIGNATION
A39: 26 | B39: Rahul Patil | C39: 33851 | D39: MALE | E39: Maruti T patil | F39: Project Coordinator | G39: AT/P-MUNGURWADI,TAL-GADHINGLAJ,DIST-KOLHAPUR, MAHARASHTRA 416503 | H39: AT/P-MUNGURWADI,TAL-GADHINGLAJ,DIST-KOLHAPUR, MAHARASHTRA 416503 | I39: 43297 | K39: 43623 | L39: RESIGNATION
A40: 27 | B40: Prachi Duble | C40: 33096 | D40: MALE | E40: pandurang shantaram duble | F40: Project Coordinator | G40: H No 661,C/o Sateri Medical stores, Aronda, Tal-sawantwadi, Dist-Sindhudurg, Maharashtra 416513 | H40: H No 661,C/o Sateri Medical stores, Aronda, Tal-sawantwadi, Dist-Sindhudurg, Maharashtra 416513 | I40: 43299 | K40: 43630 | L40: RESIGNATION
A41: 28 | B41: Rohit Shellar | C41: 17/07/1994 | D41: MALE | E41: Shivaji Babanrao Shelar | F41: Project Coordinator | G41: plot no. 126 Mohininagar , kedgaon , Ahmednagar,414005 | H41: plot no. 126 Mohininagar , kedgaon , Ahmednagar,414005 | I41: 43300 | K41: 43637 | L41: RESIGNATION
A42: 29 | B42: Harshad Daphane | C42: 32697 | D42: MALE | E42: Dinakar Balaji | F42: Project Coordinator | G42: Rh No.A-5,Renuka Puram,Satara Parisar,Beed Bypass,Aurangabad-431010 | H42: Rh No.A-5,Renuka Puram,Satara Parisar,Beed Bypass,Aurangabad-431010 | I42: 43304 | K42: 43630 | L42: RESIGNATION
A43: 30 | B43: Raj Prakash Pandya | C43: 34094 | D43: MALE | E43: Prakash Pandya | F43: Project Delivery Manager | G43: 1B/42, Kalpataru Gardens, Ashok Nagar, Kanoivali E Mumbai 400101 | H43: 1B/42, Kalpataru Gardens, Ashok Nagar, Kanoivali E Mumbai 400101 | I43: 43306 | K43: 43637 | L43: RESIGNATION
A44: 31 | B44: Kedar Walunj | C44: 34306 | D44: MALE | E44: Dnyandeo Walunj | F44: Project Coordinator | G44: Samartha, House No 872, Maruthi Mandir Jawal, Joshirwadi, Shirur, Pune, MH 412210 | H44: Samartha, House No 872, Maruthi Mandir Jawal, Joshirwadi, Shirur, Pune, MH 412210 | I44: 43332 | K44: 43490 | L44: RESIGNATION
A45: 32 | B45: Shikha Tiwari | C45: 34211 | D45: MALE | E45: Radheshyam Tiwari | F45: Project Coordinator | G45: A204, Chaitanshyasheel Cooperative society, Thakurwadi, Dombivali W Thane 421201 | H45: A204, Chaitanshyasheel Cooperative society, Thakurwadi, Dombivali W Thane 421201 | I45: 43346 | K45: 43714 | L45: RESIGNATION
A46: 33 | B46: Sonam K. Subbanwar | C46: 32876 | D46: MALE | E46: K Sakharam Subbanwar | F46: Project Coordinator | G46: Plot no 62, Ranala colony, Pragathi Nagar, Nagpur Road, Kamptee, Nagpur dist Maharashtra 441002 | H46: Plot no 62, Ranala colony, Pragathi Nagar, Nagpur Road, Kamptee, Nagpur dist Maharashtra 441002 | I46: 43355 | K46: 43518 | L46: RESIGNATION
A47: 34 | B47: Anmol Bansal | C47: 32370 | D47: MALE | E47: Manmohan Bansal | F47: Project Manager | G47: 9/466/A Babra Mohalla, Khari Kui, Rohtak - 124001, Haryana | H47: 9/466/A Babra Mohalla, Khari Kui, Rohtak - 124001, Haryana | I47: 43360 | K47: 43693 | L47: RESIGNATION
A48: 35 | B48: Kaustubh Varadkar | C48: 30832 | D48: MALE | E48: Nishikant Vaman Varadkar | F48: Project Manager | G48: 11,Matruchhaya building,ram maruti road, dadar,mumbai-400028 | H48: 11,Matruchhaya building,ram maruti road, dadar,mumbai-400028 | I48: 43378 | K48: 43714 | L48: RESIGNATION
A49: 36 | B49: Netai Mallick | C49: 31934 | D49: MALE | E49: Nemai Mallick | F49: Project Manager | G49: 203, Near Arambagh High school, Bottola ward no 3, Arambagh, Hugli, West Bengal 712601 | H49: 203, Near Arambagh High school, Bottola ward no 3, Arambagh, Hugli, West Bengal 712601 | I49: 43395 | K49: 43714 | L49: RESIGNATION
A50: 37 | B50: Shweta Pote | C50: 32326 | D50: MALE | E50: Vishal Pote | F50: Project Manager | G50: H4/503, Rose Icon, Pimple Saudagar, Pune - 411027. Maharashtra. | H50: H4/503, Rose Icon, Pimple Saudagar, Pune - 411027. Maharashtra. | I50: 43395 | K50: 43700 | L50: RESIGNATION
A51: 38 | B51: Rohit Lokhande | C51: 31903 | D51: MALE | E51: Chandrakant Lokhande | F51: Project Manager | G51: Junna Satara, Koliwada, Near Shivshankar Bekari, Bhusawal-425201 | H51: Junna Satara, Koliwada, Near Shivshankar Bekari, Bhusawal-425201 | I51: 43398 | K51: 43700 | L51: RESIGNATION
A52: 39 | B52: Sagar Khandwe | C52: 32544 | D52: Male | E52: Suhas Jairam Khandwe | F52: Project Manager | G52: Renuka Nagar,Dabki Road,Behind Renuka Mandir,Akola, Maharashtra 444002 | H52: B-703,Chaitanya Vihar Society,Boat Club Road,Datta Nagar Lane no.1,Thergaon,Chinchwad,Pune | I52: 43416 | K52: 43696 | L52: RESIGNATION
A53: 40 | B53: Snehal Kulkarni | C53: 24/7/1990 | D53: MALE | E53: SOAURABH | F53: Project Manager | G53: B-18 OZONE VILLA,WAGHOLI,PUNE,412207 | H53: B-18 OZONE VILLA,WAGHOLI,PUNE,412207 | I53: 43469 | K53: 43677 | L53: RESIGNATION
A54: 41 | B54: Aruna Ballal | C54: 32174 | D54: Female | E54: Sudam Ballal | F54: Project Manager | G54: B.102, Bora Park, Pimple Soudagar, Pune. 411027 | H54: B.102, Bora Park, Pimple Soudagar, Pune. 411027 | I54: 43488 | K54: 43830 | L54: RESIGNATION
A55: 42 | B55: Shamik Podder | C55: 33517 | D55: MALE | E55: Sib shankar Poddar | F55: Project Coordinator | G55: 59/c, PK Guha Lane,Dum Dum Contonment, Kolkata, WB 700028 | H55: 59/c, PK Guha Lane,Dum Dum Contonment, Kolkata, WB 700028 | I55: 43515 | K55: 43894 | L55: RESIGNATION
A56: 43 | B56: Ayushi Dalela | C56: 13/9/1988 | D56: MALE | E56: PD Dalela | F56: Project Coordinator | G56: Snehasish Niwas, Masjid wali gali, Sikandar Kampo, Gwalior, MP 474001 | H56: Flat No 2, 35 South Wing, Sector 3804, Pratik Nagar, Yerawada, Pune, 411006 | I56: 43497 | K56: 43714 | L56: RESIGNATION
A57: 44 | B57: Jaganath Senapathi | C57: 33029 | D57: MALE | E57: Gopal Krushna Senapati | F57: Project Delivery Manager | G57: At/PO, Beguniapada, Dist Ganjam, Kodala, Beguniapada, Odissha 761031 | H57: Room No 6, Lane No 4, Srinivas Reddy PG, Bhavani Nagar, Kharadi, Pune, 411014 | I57: 43497 | K57: 43818 | L57: RESIGNATION
A58: 45 | B58: Niranjan Jawale | C58: 33667 | D58: MALE | E58: Sunil banakrao Jawale | F58: Project Coordinator | G58: SR NO 74/A, COLONY NO 4, SHRAVASTINAGAR, GORPADI GAON,PUNE 41101 | H58: SR NO 74/A, COLONY NO 4, SHRAVASTINAGAR, GORPADI GAON,PUNE 41101 | I58: 43528 | K58: 43894 | L58: RESIGNATION
A59: 46 | B59: Sanchali Paul | C59: 26/11/1990 | D59: MALE | E59: Dipak Paul | F59: Project Coordinator | G59: Qt. No. SPT -lll/19, Forest Colony Chandranagar, Itanagar Arunachal Pradesh, pin 791113 | H59: Flat. No 6, Anuraj society, Parihaar Chowk, Aundh, Pune | I59: 43528 | K59: 43714 | L59: RESIGNATION
A60: 47 | B60: Pravin Pralhad Deulkar - no data in JULY 21 wage register | C60: 31707 | D60: MALE | E60: Pralhad Ramdas Deulkar | F60: Senior Software Engineer | G60: Near Jain Temple Malipura,balapur-444302,jain temple,akola.maharastra | H60: Near Jain Temple Malipura,balapur-444302,jain temple,akola.maharastra | I60: 44137
A61: 48 | B61: BISWAJIT PANDA - NO TIN JULY 21 | C61: 31284 | D61: MALE | E61: golak bihari Panda | F61: Senior Oracle DBA Admin | G61: 402,laxmisagar,near melan padia,bhubaneswar,odisha-751006 | H61: 402,laxmisagar,near melan padia,bhubaneswar,odisha-751006 | I61: 44242
A62: 49 | B62: Arifulla Shaik | C62: 34920 | D62: MALE | E62: Shaik Asad | F62: Citrix Administrator | G62: 1-1015/t balineni bharath nagar, backside karuna colony, ongole, prakasam district, andhra pradesh, 523001 | H62: 1-1015/t balineni bharath nagar, backside karuna colony, ongole, prakasam district, andhra pradesh, 523001 | I62: 44298 | K62: Active | L62: Active
A63: 50 | B63: VenkataRamanaia Rayani | C63: 10th June 1990 | D63: MALE | E63: Ankamaiah | F63: Senior Software Engineer | G63: Rudrakota village, Kavali, SPSR Nellore AP 524203 | H63: Rudrakota village, Kavali, SPSR Nellore AP 524203 | I63: 26th April 21 | K63: Resigned | L63: Resignation
A64: 51 | B64: AshishTukaram Mhaskar | C64: 30803 | D64: MALE | E64: Tukaram Sakaram Mhaskar | F64: MS sql DBA | G64: Plot No 3,Road No 14,Sector 12,New panvel,Opp BSNL office,Raigarh,Maharastra 410206 | H64: Plot No 3,Road No 14,Sector 12,New panvel,Opp BSNL office,Raigarh,Maharastra 410206 | I64: 44355 | J64: oo | K64: Active | L64: Active
A65: 52 | B65: DESIR KOIPURATH | C65: 30222 | D65: MALE | E65: Brijou Gopalan Koipurath | F65: ITPM | G65: 1753,Jayaram colony,Behind Holy family,Vidyanagar,Karad district Satara,Maharastra 415124 | H65: F-803,Mount Vert Vesta,Urawade,Pirangut,Pune 412108 | I65: 44390 | J65: oo | K65: Active | L65: Active
A66: 53 | B66: Shaikh Mohammed Sartaj | C66: 31453 | D66: MALE | E66: Shaikh Mohammad Rafique | F66: Network Security Admin | G66: plot no 110, Sadatnagar, Near Railway station, Aurangabad, 431001 | H66: plot no 110, Sadatnagar, Near Railway station, Aurangabad, 431001 | I66: 44470 | K66: Active | L66: Active | P66: 1
A67: 54 | B67: Moin Ahemad Jahur Ahemad Kumarkiri | C67: 31507 | D67: MALE | E67: Jahur Ahemad Kumarkiri | F67: Infrastructure Lead | G67: E 111, Ace City Police Chowki, Sector-1, Bishrak, Greater Noida West, Yatharth Hospital, Noida, 201306 | H67: River Residency, Chikhali , Pune | I67: 44491 | K67: Active | L67: Active | P67: 2
A68: 55 | B68: Savana Saritha Dora | C68: 29965 | D68: FEMALE | E68: Laxman gupta | F68: ASSISTANT PROJECT MANAGER | G68: Shafa Nagar Ausa, Dist- Latur, Maharashtra | H68: E 111, Ace City Police Chowki, Sector-1, Bishrak, Greater Noida West, Yatharth Hospital, Noida, 201306 | I68: 44495 | K68: Active | L68: Active | P68: 3
A69: 56 | B69: Minakshi Joshi | C69: 31239 | D69: Female | E69: Hiren Joshi | F69: Project Manager | G69: B-30, Ramnagar Society, Nizampura, Vadodara, Gujarat | H69: A-10/401, Planet Millennium Society, Pimple Saudagar, Pune Maharashtra | I69: 44496 | K69: Resigned | L69: RESIGNATION
A70: 57 | B70: Mandar Shetty | C70: 31205 | D70: MALE | E70: Vijay Shetty | F70: Project Manager | G70: B-301,Hemarold Isle,Wagholi-Lohegaon,Behind Wagheshwar Temple,Wagholi,Pune 412207 | H70: B-301,Hemarold Isle,Wagholi-Lohegaon,Behind Wagheshwar Temple,Wagholi,Pune 412207 | I70: 44509 | K70: Active | L70: Active | P70: 4
A71: 58 | B71: Vivek Dongre | C71: 32931 | D71: MALE | E71: Purushottam Dongre | F71: Project Manager | G71: B-8,Good will Samwrudhi,Gokul nagar,Dhanuri road No.15,Pune 411015 | H71: B-8,Good will Samwrudhi,Gokul nagar,Dhanuri road No.15,Pune 411015 | I71: 44515 | K71: Active | L71: Active | P71: 5
A72: 59 | B72: Amit Chawadi | C72: 31279 | D72: MALE | E72: Veerendra | F72: Sr.Software Engineer | G72: Block No.C-9/10,Bhagyodhaya housing society,Opp Parsi vihar,Nai zindagi road,Solapur,Maharastra 413003 | H72: Block No.C-9/10,Bhagyodhaya housing society,Opp Parsi vihar,Nai zindagi road,Solapur,Maharastra 413003 | I72: 44522 | K72: Active | L72: Active | P72: 6
A73: 60 | B73: Ashwini Nanaware | C73: 33778 | D73: MALE | E73: Suresh Sadashiv Male | F73: Project Manager | G73: Flat No 305,Pandarinath Appartments,Sanath nagar lane,No7,Lohegaon,Pune 411047 | H73: Flat No 305,Pandarinath Appartments,Sanath nagar lane,No7,Lohegaon,Pune 411047 | I73: 44536 | K73: Active | L73: Active | P73: 7
A74: 61 | B74: Kaushal Sushil Sharma | C74: 35033 | D74: MALE | E74: Sushil Sharma | F74: Network Engineer L2 | G74: Room No.2, Ambica singh Chawl,New Deepak wadi,Khar east,Mumbai,400051 | H74: Room No.2, Ambica singh Chawl,New Deepak wadi,Khar east,Mumbai,400051 | I74: 44536 | K74: Active | L74: Active | P74: 8
A75: 62 | B75: Arvind Akhare | C75: 32329 | D75: MALE | E75: Vasanth Rao Ramkishan Akhare | F75: Project Manager | G75: AP.Shelgaon Deshmukh sub distruct,Mehkar,District Buldana,Maharastra 443303 | H75: AP.Shelgaon Deshmukh sub distruct,Mehkar,District Buldana,Maharastra 443303 | I75: 44537 | K75: Active | L75: Active | P75: 9
A76: 63 | B76: Pallavi Rishikesh Naik | C76: 34094 | D76: Female | E76: Rishikesh Naik | F76: Project Manager | G76: C/3,Ekta Housing Society,MIDC,G Block,Sambajinagar,Chinchiwad,Pune 411019 | H76: C/O Prameela Savath,Suryasirvad society,Flat No.5,Near Waghere wada,Priyadarshini school,Nehru nagar,Pimpri,Pune 411048 | I76: 44538 | K76: Active | L76: Active | P76: 10
A77: 64 | B77: Amit Kumar | C77: 31700 | D77: MALE | E77: Yadram | F77: Linux Administrator | G77: 525,Galli No.1,Sector 44,Chalera,Noida,Gowtham Budda nagar,Uttarpradesh 201301 | H77: 525,Galli No.1,Sector 44,Chalera,Noida,Gowtham Budda nagar,Uttarpradesh 201301 | I77: 44557 | K77: Active | L77: Active | P77: 11
A78: 65 | B78: Pranav Thakare | C78: 28/02/1994 | D78: MALE | E78: Pramod Motiram Thakare | F78: Project Manager | G78: B-78, State Employees Society,Ashoknagar,Satpur,Nashik | H78: B-78, State Employees Society,Ashoknagar,Satpur,Nashik | I78: 44564 | K78: Active | L78: Active | P78: 12
A79: 66 | B79: Asita Kumar Sahoo | C79: 02/07/1977 | D79: MALE | E79: Dambarudar Sahoo | F79: Network Admin | G79: Airforce station, Achalgarh, Delwara, Abu road, Sirohi, Rajasthan 307501 | H79: Airforce station, Achalgarh, Delwara, Abu road, Sirohi, Rajasthan 307501 | I79: 44567 | K79: Active | L79: Active | P79: 13
A80: 67 | B80: Arun Arra | C80: 34378 | D80: MALE | E80: Anjam Raju | F80: SAP Basis consultant | G80: 1-52/3, Suryanager Colony, Uppal, HYD 500039 | H80: H.No: 2-3-226, Dubbawada, Metpally, 505325 | I80: 44602 | P80: 14
A81: 68 | B81: Ramya Nalla | C81: 22-03-1998 | D81: FEMALE | E81: W/O Chitharanjan Allem | F81: SAP Basis consultant | G81: C-101, Akruthi Arcade, Anand Nagar, GB road, Thane West, Mumbai, Maharashtra,400615 | H81: C-101, Akruthi Arcade, Anand Nagar, GB road, Thane West, Mumbai, Maharashtra,400615 | I81: 44602 | P81: 15
A82: 69 | B82: SYED MOHAMMED AZHER | C82: 33172 | D82: MALE | E82: SYED MOHAMMED NASEER | F82: SAP Basis consultant | G82: 11-5-205 Flat No 202 2nd Floor Beside Red Hills Poly Clinic Nampally Hyderabad , Telangana - 500 004 | H82: 11-5-205 Flat No 202 2nd Floor Beside Red Hills Poly Clinic Nampally Hyderabad , Telangana - 500 004 | I82: 44602
A83: 70 | B83: Uma Mahesh P | C83: 35748 | D83: MALE | E83: PENTAKOTA LAKSHI | F83: SAP Basis consultant | G83: D.NO: 1-1 , PENTAKOTA VARI STREET , CHUCHUKONDA (VILLAGE),MUNAGAPAKA (MANDAL),VISHAKAPATNAM(DISTRICT),PIN CODE:531055 | H83: D.NO: 1-1 , PENTAKOTA VARI STREET , CHUCHUKONDA(VILLAGE),MUNAGAPAKA(MANDAL),VISHAKAPATNAM(DISTRICT),PINCODE:531055 | I83: 44602 | P83: 16
A84: 71 | B84: GONTHINI SAIBABU | C84: 35895 | D84: MALE | E84: GONTHINI SATTIBABU | F84: SAP Basis consultant | G84: Falt: 202, Pecan Creek,Plot 790, Road no 4c, Gopal Nagar, Gokul Enclave, Venkata Ramana Colony, Kukatpally, Hyderabad, Telangana 500085, India | H84: D.NO: 4-65, YADAGIRIPALEM VILLAGE, MELUPAKA POST, MUNAGAPAKA MANDAL, VISAKHAPATNAM, A.P. PINCODE -531055. | I84: 44602
A85: 72 | B85: Pavan Nagendra Tatina | C85: 36086 | D85: MALE | E85: TATINA PULLARAO | F85: SAP Basis consultant | G85: Dr no:1-73,near high school,lingapalem,west godavari district-534462 | H85: Dr no:1-73,near high school,lingapalem,west godavari district-534462 | I85: 44602
A86: 73 | B86: Mohd Azhar Shareef | C86: 31019 | D86: MALE | E86: Mohd Mazhar Shareer | F86: SAP Basis consultant | G86: OOOO | H86: OOOO | I86: 44602
A87: 74 | B87: NAGA SAI TEJA NUTHI | C87: 33292 | D87: MALE | E87: G seshaiah | F87: SAP Basis consultant | G87: Hno 15-21-237/1,Flat no G2,sattenapally towers,Balaji Nagar,Kukatpally,Hyderabad,500072 | H87: Hno 15-21-237/1,Flat no G2,sattenapally towers,Balaji Nagar,Kukatpally,Hyderabad,500072 | I87: 44602 | P87: 17
A88: 75 | B88: Mani Krishna Nandineedi | C88: 35088 | D88: MALE | E88: N Srinivasu | F88: SAP Basis consultant | G88: 204-7-343, Nagireddy Nagar, Near Three temples | H88: 3-542, 10th street RK Nagar, Rajahmundry 533107 | I88: 44602 | P88: 18
A89: 76 | B89: Sushma P | C89: 32638 | D89: FEMALE | E89: Veeraswamy | F89: SAP Basis consultant | G89: H No 5-11/1, Janakipuram, bonakal,Khammam, Telangana 507204 | H89: H No 5-11/1, Janakipuram, bonakal,Khammam, Telangana 507204 | I89: 44602 | P89: 19
A90: 77 | B90: susheelKumar Gandla | C90: 30056 | D90: MALE | E90: Narayana Gandla | F90: Sr Software Engineer | G90: Flat no.308,Block A,Akruthi srinivasan Appts,Balaji nagar,Road.3,Nizampet,Hyderabad,TS 500090 | H90: Flat no.308,Block A,Akruthi srinivasan Appts,Balaji nagar,Road.3,Nizampet,Hyderabad,TS 500090 | I90: 44652 | P90: 20
J102: Signature of the Contractor with Seal

Sheet 0422Master
A3: FORM - XIII REGISTER OF WORKMEN EMPLOYED BY CONTRACTOR
B4: (Vide Rule 75 of Contract Labour (Regulation and Abolition) Central/Karnataka Rules 1974)
A5: Name and address of Contractor: | F5: Burgeon IT Services Pvt.Ltd. | AB5: Name and address of Establishemnt in/ under which contract is carried on: | AP5: =F5 -> Burgeon IT Services Pvt.Ltd.
F6: Siri Mansion LIGB 436 Dr.A S Rao Nagar,Hyderabad | AP6: =F6 -> Siri Mansion LIGB 436 Dr.A S Rao Nagar,Hyderabad
AP7: =F7 -> 0
A8: Nature and location of work: | F8: IT SUPPORTIVE SERVICES& PUNE SEZ UNIT-II
A10: Wage period: Monthly | D10: 44652 | AK10: Name and address of Principal Employer: | AP10: INFOSYS LTD.IL Pune SEZ Unit-II,Plot No. 24/3
AP11: Rajiv gandhi Info tech park,Village Mann,Pune,Maharashtra 411057
B13: 1 | C13: 2 | D13: 3 | E13: 4 | F13: 5 | G13: 6 | H13: 7 | I13: 8 | J13: 9 | K13: 10 | L13: 11 | M13: 12 | N13: 13 | O13: 14 | P13: 15 | Q13: 16 | R13: 17 | S13: 18 | T13: 19 | U13: 20 | V13: 21 | W13: 22 | X13: 23 | Y13: 24 | Z13: 25 | AA13: 26 | AB13: 27 | AC13: 28 | AD13: 29 | AE13: 30 | AF13: 31 | AG13: 32 | AH13: 33 | AI13: 34 | AJ13: 35 | AK13: 36 | AL13: 37 | AM13: 38 | AN13: 39 | AO13: 40 | AP13: 41 | AQ13: 42 | AR13: 43 | AS13: 44 | AT13: 45 | AU13: 46
B14: Name of Workman | C14: Age | D14: Sex | E14: Father's /Husband Name | F14: Designation / Nature of Work Done | G14: Permanent Address | J14: Local Address | N14: Date of Commencement of Employment | O14: Signature or thumb impression of Workman | P14: Date of termination of Employment | Q14: Reasons for termination | R14: Remarks | S14: EPF Number | T14: ESI Number | U14: Name of Workman | V14: NO.OF DAYS | W14: No.of Days worked | X14: Unit of work done | Y14: Monthly rate of wages/ piece rate | Z14: Basic wages | AA14: Dearness Allowances | AB14: Over time | AC14: Other cash payments (Nature of payments to be indicated) | AD14: HRA | AE14: CONVEYANCE | AF14: MEDICAL ALLOWANCES | AG14: SPECIAL ALLOWNANCES | AH14: Total | AI14: BONUS | AJ14: GRATUITY | AK14: LTA/L.E | AL14: ARREAR AMOUNT | AM14: TOTAL AMOUNT | AN14: Deductions, if any, (Indicate nature) | AT14: Net Amount paid | AU14: Time and Date of Payment | AV14: Place of Payment | AW14: Signature/Thumb Impression of workman | AX14: Initial of Contractor or his representative | AY14: Serial No. in the Register of Workmen
AN15: ESI | AO15: PF | AP15: PT | AQ15: TDS | AR15: MED | AS15: Total Deductions
A16: BITS-652 | B16: Shaikh Mohammed Sartaj | C16: 31453 | D16: MALE | E16: Shaikh Mohammad Rafique | F16: Network Security Admin | G16: plot no 110, Sadatnagar, Near Railway station, Aurangabad, 431001 | J16: plot no 110, Sadatnagar, Near Railway station, Aurangabad, 431001 | N16: 44470 | S16: 100468499225 | T16: N/A | U16: Shaikh Mohammed Sartaj | V16: 30 | W16: =VLOOKUP(A16,'[1]Pay sheet-APRIL- 2022'!$C$57:$AF$129,10,0) -> 30 | X16: N/A | Y16: 80278 | Z16: =VLOOKUP(A16,'[1]Pay sheet-APRIL- 2022'!$C$57:$AF$129,11,0) -> 48166.8 | AA16: 0 | AB16: 0 | AC16: =AD16+AE16+AF16+AG16 -> 32224.2 | AD16: =VLOOKUP(A16,'[1]Pay sheet-APRIL- 2022'!$C$57:$AF$129,12,0) -> 19266.72 | AE16: =VLOOKUP(A16,'[1]Pay sheet-APRIL- 2022'!$C$57:$AF$129,13,0) -> 2083 | AF16: =VLOOKUP(A16,'[1]Pay sheet-APRIL- 2022'!$C$57:$AF$129,14,0) -> 2083 | AG16: =VLOOKUP(A16,'[1]Pay sheet-APRIL- 2022'!$C$57:$AF$129,15,0) -> 8791.48 | AH16: =Z16+AC16 -> 80391 | AI16: =VLOOKUP(A16,'[1]Pay sheet-APRIL- 2022'!$C$57:$AF$129,18,0) -> 1554.609 | AJ16: =VLOOKUP(A16,'[1]Pay sheet-APRIL- 2022'!$C$57:$AF$129,19,0) -> 2316.8231 | AK16: =VLOOKUP(A16,'[1]Pay sheet-APRIL- 2022'!$C$57:$AF$129,20,0) -> 4013.9 | AL16: =VLOOKUP(A16,'[1]Pay sheet-APRIL- 2022'!$C$57:$AF$129,22,0) -> 0 | AM16: =Z16+AD16+AE16+AF16+AG16+AI16+AJ16+AK16 -> 88276.332 | AN16: 0 | AO16: =VLOOKUP(A16,'[1]Pay sheet-APRIL- 2022'!$C$57:$AF$129,26,0) -> 1800 | AP16: =VLOOKUP(A16,'[1]Pay sheet-APRIL- 2022'!$C$57:$AF$129,25,0) -> 200 | AQ16: =VLOOKUP(A16,'[1]Pay sheet-APRIL- 2022'!$C$57:$AF$129,24,0) -> 0 | AR16: =VLOOKUP(A16,'[1]Pay sheet-APRIL- 2022'!$C$57:$AF$129,27,0) -> 254 | AS16: =SUM(AO16:AR16) -> 2254 | AT16: =AM16+AL16+-AS16 -> 86022.332 | AU16: 05.05.2022 | AV16: HDFC BANK | AW16: 50100405646907 | AY16: 53 | AZ16: 1
A17: BITS-660 | B17: Moin Ahemad Jahur Ahemad Kumarkiri | C17: 31507 | D17: MALE | E17: Jahur Ahemad Kumarkiri | F17: Infrastructure Lead | G17: E 111, Ace City Police Chowki, Sector-1, Bishrak, Greater Noida West, Yatharth Hospital, Noida, 201306 | J17: River Residency, Chikhali , Pune | N17: 44491 | S17: 100505159752 | T17: N/A | U17: Moin Ahemad Jahur Ahemad Kumarkiri | V17: 30 | W17: =VLOOKUP(A17,'[1]Pay sheet-APRIL- 2022'!$C$57:$AF$129,10,0) -> 30 | X17: N/A | Y17: 143307 | Z17: =VLOOKUP(A17,'[1]Pay sheet-APRIL- 2022'!$C$57:$AF$129,11,0) -> 85984.2 | AA17: 0 | AB17: 0 | AC17: =AD17+AE17+AF17+AG17 -> 57435.8 | AD17: =VLOOKUP(A17,'[1]Pay sheet-APRIL- 2022'!$C$57:$AF$129,12,0) -> 34393.68 | AE17: =VLOOKUP(A17,'[1]Pay sheet-APRIL- 2022'!$C$57:$AF$129,13,0) -> 2083 | AF17: =VLOOKUP(A17,'[1]Pay sheet-APRIL- 2022'!$C$57:$AF$129,14,0) -> 2083 | AG17: =VLOOKUP(A17,'[1]Pay sheet-APRIL- 2022'!$C$57:$AF$129,15,0) -> 18876.12 | AH17: =Z17+AC17 -> 143420 | AI17: =VLOOKUP(A17,'[1]Pay sheet-APRIL- 2022'!$C$57:$AF$129,18,0) -> 1554.609 | AJ17: =VLOOKUP(A17,'[1]Pay sheet-APRIL- 2022'!$C$57:$AF$129,19,0) -> 4135.84 | AK17: =VLOOKUP(A17,'[1]Pay sheet-APRIL- 2022'!$C$57:$AF$129,20,0) -> 7165.35 | AL17: =VLOOKUP(A17,'[1]Pay sheet-APRIL- 2022'!$C$57:$AF$129,22,0) -> 0 | AM17: =Z17+AD17+AE17+AF17+AG17+AI17+AJ17+AK17 -> 156275.8 | AN17: 0 | AO17: =VLOOKUP(A17,'[1]Pay sheet-APRIL- 2022'!$C$57:$AF$129,26,0) -> 1800 | AP17: =VLOOKUP(A17,'[1]Pay sheet-APRIL- 2022'!$C$57:$AF$129,25,0) -> 200 | AQ17: =VLOOKUP(A17,'[1]Pay sheet-APRIL- 2022'!$C$57:$AF$129,24,0) -> 0 | AR17: =VLOOKUP(A17,'[1]Pay sheet-APRIL- 2022'!$C$57:$AF$129,27,0) -> 254 | AS17: =SUM(AO17:AR17) -> 2254 | AT17: =AM17+AL17+-AS17 -> 154021.8 | AU17: 05.05.2022 | AV17: HDFC BANK | AW17: 50100103229547 | AY17: 54 | AZ17: 2
A18: BITS-664 | B18: Savana Saritha Dora | C18: 29965 | D18: FEMALE | E18: Laxman gupta | F18: ASSISTANT PROJECT MANAGER | G18: Shafa Nagar Ausa, Dist- Latur, Maharashtra | J18: E 111, Ace City Police Chowki, Sector-1, Bishrak, Greater Noida West, Yatharth Hospital, Noida, 201306 | N18: 44495 | S18: 101749326014 | T18: N/A | U18: Savana Saritha Dora | V18: 30 | W18: =VLOOKUP(A18,'[1]Pay sheet-APRIL- 2022'!$C$57:$AF$129,10,0) -> 30 | X18: N/A | Y18: 55251 | Z18: =VLOOKUP(A18,'[1]Pay sheet-APRIL- 2022'!$C$57:$AF$129,11,0) -> 33150.6 | AA18: 0 | AB18: 0 | AC18: =AD18+AE18+AF18+AG18 -> 22213.4 | AD18: =VLOOKUP(A18,'[1]Pay sheet-APRIL- 2022'!$C$57:$AF$129,12,0) -> 13260.24 | AE18: =VLOOKUP(A18,'[1]Pay sheet-APRIL- 2022'!$C$57:$AF$129,13,0) -> 2083 | AF18: =VLOOKUP(A18,'[1]Pay sheet-APRIL- 2022'!$C$57:$AF$129,14,0) -> 2083 | AG18: =VLOOKUP(A18,'[1]Pay sheet-APRIL- 2022'!$C$57:$AF$129,15,0) -> 4787.16 | AH18: =Z18+AC18 -> 55364 | AI18: =VLOOKUP(A18,'[1]Pay sheet-APRIL- 2022'!$C$57:$AF$129,18,0) -> 1554.609 | AJ18: =VLOOKUP(A18,'[1]Pay sheet-APRIL- 2022'!$C$57:$AF$129,19,0) -> 1594.5439 | AK18: =VLOOKUP(A18,'[1]Pay sheet-APRIL- 2022'!$C$57:$AF$129,20,0) -> 2762.55 | AL18: =VLOOKUP(A18,'[1]Pay sheet-APRIL- 2022'!$C$57:$AF$129,22,0) -> 0 | AM18: =Z18+AD18+AE18+AF18+AG18+AI18+AJ18+AK18 -> 61275.703 | AN18: 0 | AO18: =VLOOKUP(A18,'[1]Pay sheet-APRIL- 2022'!$C$57:$AF$129,26,0) -> 1800 | AP18: =VLOOKUP(A18,'[1]Pay sheet-APRIL- 2022'!$C$57:$AF$129,25,0) -> 200 | AQ18: =VLOOKUP(A18,'[1]Pay sheet-APRIL- 2022'!$C$57:$AF$129,24,0) -> 0 | AR18: =VLOOKUP(A18,'[1]Pay sheet-APRIL- 2022'!$C$57:$AF$129,27,0) -> 286 | AS18: =SUM(AO18:AR18) -> 2286 | AT18: =AM18+AL18+-AS18 -> 58989.703 | AU18: 05.05.2022 | AV18: SBI | AW18: 20101763786 | AY18: 55 | AZ18: 3
A19: BITS-668 | B19: Mandar Shetty | C19: 31205 | D19: MALE | E19: Vijay Shetty | F19: Project Manager | G19: B-301,Hemarold Isle,Wagholi-Lohegaon,Behind Wagheshwar Temple,Wagholi,Pune 412207 | H19: B-301,Hemarold Isle,Wagholi-Lohegaon,Behind Wagheshwar Temple,Wagholi,Pune 412207 | J19: B-301,Hemarold Isle,Wagholi-Lohegaon,Behind Wagheshwar Temple,Wagholi,Pune 412207 | N19: 44509 | S19: 100217449855 | T19: N/A | U19: Mandar Shetty | V19: 30 | W19: =VLOOKUP(A19,'[1]Pay sheet-APRIL- 2022'!$C$57:$AF$129,10,0) -> 30 | X19: N/A | Y19: 104377 | Z19: =VLOOKUP(A19,'[1]Pay sheet-APRIL- 2022'!$C$57:$AF$129,11,0) -> 62626.2 | AA19: 0 | AB19: 0 | AC19: =AD19+AE19+AF19+AG19 -> 41863.8 | AD19: =VLOOKUP(A19,'[1]Pay sheet-APRIL- 2022'!$C$57:$AF$129,12,0) -> 25050.48 | AE19: =VLOOKUP(A19,'[1]Pay sheet-APRIL- 2022'!$C$57:$AF$129,13,0) -> 2083 | AF19: =VLOOKUP(A19,'[1]Pay sheet-APRIL- 2022'!$C$57:$AF$129,14,0) -> 2083 | AG19: =VLOOKUP(A19,'[1]Pay sheet-APRIL- 2022'!$C$57:$AF$129,15,0) -> 12647.32 | AH19: =Z19+AC19 -> 104490 | AI19: =VLOOKUP(A19,'[1]Pay sheet-APRIL- 2022'!$C$57:$AF$129,18,0) -> 1554.609 | AJ19: =VLOOKUP(A19,'[1]Pay sheet-APRIL- 2022'!$C$57:$AF$129,19,0) -> 3012.3202 | AK19: =VLOOKUP(A19,'[1]Pay sheet-APRIL- 2022'!$C$57:$AF$129,20,0) -> 5218.85 | AL19: =VLOOKUP(A19,'[1]Pay sheet-APRIL- 2022'!$C$57:$AF$129,22,0) -> 0 | AM19: =Z19+AD19+AE19+AF19+AG19+AI19+AJ19+AK19 -> 114275.78 | AN19: 0 | AO19: =VLOOKUP(A19,'[1]Pay sheet-APRIL- 2022'!$C$57:$AF$129,26,0) -> 1800 | AP19: =VLOOKUP(A19,'[1]Pay sheet-APRIL- 2022'!$C$57:$AF$129,25,0) -> 200 | AQ19: =VLOOKUP(A19,'[1]Pay sheet-APRIL- 2022'!$C$57:$AF$129,24,0) -> 0 | AR19: =VLOOKUP(A19,'[1]Pay sheet-APRIL- 2022'!$C$57:$AF$129,27,0) -> 283 | AS19: =SUM(AO19:AR19) -> 2283 | AT19: =AM19+AL19+-AS19 -> 111992.78 | AU19: 05.05.2022 | AV19: Axis Bank | AW19: 910010033970009 | AY19: 57 | AZ19: 4
A20: BITS-672 | B20: Vivek Dongre | C20: 32931 | D20: MALE | E20: Purushottam Dongre | F20: Project Manager | G20: B-8,Good will Samwrudhi,Gokul nagar,Dhanuri road No.15,Pune 411015 | J20: B-8,Good will Samwrudhi,Gokul nagar,Dhanuri road No.15,Pune 411015 | N20: 44515 | S20: 100857629834 | T20: N/A | U20: Vivek Dongre | V20: 30 | W20: =VLOOKUP(A20,'[1]Pay sheet-APRIL- 2022'!$C$57:$AF$129,10,0) -> 30 | X20: N/A | Y20: 66374 | Z20: =VLOOKUP(A20,'[1]Pay sheet-APRIL- 2022'!$C$57:$AF$129,11,0) -> 39824.4 | AA20: 0 | AB20: 0 | AC20: =AD20+AE20+AF20+AG20 -> 26662.6 | AD20: =VLOOKUP(A20,'[1]Pay sheet-APRIL- 2022'!$C$57:$AF$129,12,0) -> 15929.76 | AE20: =VLOOKUP(A20,'[1]Pay sheet-APRIL- 2022'!$C$57:$AF$129,13,0) -> 2083 | AF20: =VLOOKUP(A20,'[1]Pay sheet-APRIL- 2022'!$C$57:$AF$129,14,0) -> 2083 | AG20: =VLOOKUP(A20,'[1]Pay sheet-APRIL- 2022'!$C$57:$AF$129,15,0) -> 6566.84 | AH20: =Z20+AC20 -> 66487 | AI20: =VLOOKUP(A20,'[1]Pay sheet-APRIL- 2022'!$C$57:$AF$129,18,0) -> 1554.609 | AJ20: =VLOOKUP(A20,'[1]Pay sheet-APRIL- 2022'!$C$57:$AF$129,19,0) -> 1915.5536 | AK20: =VLOOKUP(A20,'[1]Pay sheet-APRIL- 2022'!$C$57:$AF$129,20,0) -> 3318.7 | AL20: =VLOOKUP(A20,'[1]Pay sheet-APRIL- 2022'!$C$57:$AF$129,22,0) -> 0 | AM20: =Z20+AD20+AE20+AF20+AG20+AI20+AJ20+AK20 -> 73275.863 | AN20: 0 | AO20: =VLOOKUP(A20,'[1]Pay sheet-APRIL- 2022'!$C$57:$AF$129,26,0) -> 1800 | AP20: =VLOOKUP(A20,'[1]Pay sheet-APRIL- 2022'!$C$57:$AF$129,25,0) -> 200 | AQ20: =VLOOKUP(A20,'[1]Pay sheet-APRIL- 2022'!$C$57:$AF$129,24,0) -> 0 | AR20: =VLOOKUP(A20,'[1]Pay sheet-APRIL- 2022'!$C$57:$AF$129,27,0) -> 252 | AS20: =SUM(AO20:AR20) -> 2252 | AT20: =AM20+AL20+-AS20 -> 71023.863 | AU20: 05.05.2022 | AV20: CITI Bank | AW20: 5297131705 | AY20: 58 | AZ20: 5
A21: BITS-674 | B21: Amit Chawadi | C21: 31279 | D21: MALE | E21: Veerendra | F21: Sr.Software Engineer | G21: Block No.C-9/10,Bhagyodhaya housing society,Opp Parsi vihar,Nai zindagi road,Solapur,Maharastra 413003 | J21: Block No.C-9/10,Bhagyodhaya housing society,Opp Parsi vihar,Nai zindagi road,Solapur,Maharastra 413003 | N21: 44522 | S21: 100930453611 | T21: N/A | U21: Amit Chawadi | V21: 30 | W21: =VLOOKUP(A21,'[1]Pay sheet-APRIL- 2022'!$C$57:$AF$129,10,0) -> 30 | X21: N/A | Y21: 80278 | Z21: =VLOOKUP(A21,'[1]Pay sheet-APRIL- 2022'!$C$57:$AF$129,11,0) -> 48166.8 | AA21: 0 | AB21: 0 | AC21: =AD21+AE21+AF21+AG21 -> 32224.2 | AD21: =VLOOKUP(A21,'[1]Pay sheet-APRIL- 2022'!$C$57:$AF$129,12,0) -> 19266.72 | AE21: =VLOOKUP(A21,'[1]Pay sheet-APRIL- 2022'!$C$57:$AF$129,13,0) -> 2083 | AF21: =VLOOKUP(A21,'[1]Pay sheet-APRIL- 2022'!$C$57:$AF$129,14,0) -> 2083 | AG21: =VLOOKUP(A21,'[1]Pay sheet-APRIL- 2022'!$C$57:$AF$129,15,0) -> 8791.48 | AH21: =Z21+AC21 -> 80391 | AI21: =VLOOKUP(A21,'[1]Pay sheet-APRIL- 2022'!$C$57:$AF$129,18,0) -> 1554.609 | AJ21: =VLOOKUP(A21,'[1]Pay sheet-APRIL- 2022'!$C$57:$AF$129,19,0) -> 2316.8231 | AK21: =VLOOKUP(A21,'[1]Pay sheet-APRIL- 2022'!$C$57:$AF$129,20,0) -> 4013.9 | AL21: =VLOOKUP(A21,'[1]Pay sheet-APRIL- 2022'!$C$57:$AF$129,22,0) -> 0 | AM21: =Z21+AD21+AE21+AF21+AG21+AI21+AJ21+AK21 -> 88276.332 | AN21: 0 | AO21: =VLOOKUP(A21,'[1]Pay sheet-APRIL- 2022'!$C$57:$AF$129,26,0) -> 1800 | AP21: =VLOOKUP(A21,'[1]Pay sheet-APRIL- 2022'!$C$57:$AF$129,25,0) -> 200 | AQ21: =VLOOKUP(A21,'[1]Pay sheet-APRIL- 2022'!$C$57:$AF$129,24,0) -> 0 | AR21: =VLOOKUP(A21,'[1]Pay sheet-APRIL- 2022'!$C$57:$AF$129,27,0) -> 283 | AS21: =SUM(AO21:AR21) -> 2283 | AT21: =AM21+AL21+-AS21 -> 85993.332 | AU21: 05.05.2022 | AV21: ICICI Bank | AW21: 007401540582 | AY21: 59 | AZ21: 6
A22: BITS-677 | B22: Ashwini Nanaware | C22: 33778 | D22: MALE | E22: Suresh Sadashiv Male | F22: Project Manager | G22: Flat No 305,Pandarinath Appartments,Sanath nagar lane,No7,Lohegaon,Pune 411047 | I22: OOO | J22: Flat No 305,Pandarinath Appartments,Sanath nagar lane,No7,Lohegaon,Pune 411047 | K22: OOO | L22: OOO | M22: OOO | N22: 44536 | S22: 100734752719 | T22: N/A | U22: Ashwini Nanaware | V22: 30 | W22: =VLOOKUP(A22,'[1]Pay sheet-APRIL- 2022'!$C$57:$AF$129,10,0) -> 30 | X22: N/A | Y22: 54324 | Z22: =VLOOKUP(A22,'[1]Pay sheet-APRIL- 2022'!$C$57:$AF$129,11,0) -> 32594.4 | AA22: 0 | AB22: 0 | AC22: =AD22+AE22+AF22+AG22 -> 21842.6 | AD22: =VLOOKUP(A22,'[1]Pay sheet-APRIL- 2022'!$C$57:$AF$129,12,0) -> 13037.76 | AE22: =VLOOKUP(A22,'[1]Pay sheet-APRIL- 2022'!$C$57:$AF$129,13,0) -> 2083 | AF22: =VLOOKUP(A22,'[1]Pay sheet-APRIL- 2022'!$C$57:$AF$129,14,0) -> 2083 | AG22: =VLOOKUP(A22,'[1]Pay sheet-APRIL- 2022'!$C$57:$AF$129,15,0) -> 4638.84 | AH22: =Z22+AC22 -> 54437 | AI22: =VLOOKUP(A22,'[1]Pay sheet-APRIL- 2022'!$C$57:$AF$129,18,0) -> 1554.609 | AJ22: =VLOOKUP(A22,'[1]Pay sheet-APRIL- 2022'!$C$57:$AF$129,19,0) -> 1567.7906 | AK22: =VLOOKUP(A22,'[1]Pay sheet-APRIL- 2022'!$C$57:$AF$129,20,0) -> 2716.2 | AL22: =VLOOKUP(A22,'[1]Pay sheet-APRIL- 2022'!$C$57:$AF$129,22,0) -> 0 | AM22: =Z22+AD22+AE22+AF22+AG22+AI22+AJ22+AK22 -> 60275.6 | AN22: 0 | AO22: =VLOOKUP(A22,'[1]Pay sheet-APRIL- 2022'!$C$57:$AF$129,26,0) -> 1800 | AP22: =VLOOKUP(A22,'[1]Pay sheet-APRIL- 2022'!$C$57:$AF$129,25,0) -> 200 | AQ22: =VLOOKUP(A22,'[1]Pay sheet-APRIL- 2022'!$C$57:$AF$129,24,0) -> 0 | AR22: =VLOOKUP(A22,'[1]Pay sheet-APRIL- 2022'!$C$57:$AF$129,27,0) -> 283 | AS22: =SUM(AO22:AR22) -> 2283 | AT22: =AM22+AL22+-AS22 -> 57992.6 | AU22: 05.05.2022 | AV22: HDFC Bank | AW22: 50100191546051 | AY22: 60 | AZ22: 7
A23: BITS-678 | B23: Kaushal Sushil Sharma | C23: 35033 | D23: MALE | E23: Sushil Sharma | F23: Network Engineer L2 | G23: Room No.2, Ambica singh Chawl,New Deepak wadi,Khar east,Mumbai,400051 | I23: OOO | J23: Room No.2, Ambica singh Chawl,New Deepak wadi,Khar east,Mumbai,400051 | K23: OOO | L23: OOO | M23: OOO | N23: 44536 | S23: 100779324583 | T23: N/A | U23: Kaushal Sushil Sharma | V23: 30 | W23: =VLOOKUP(A23,'[1]Pay sheet-APRIL- 2022'!$C$57:$AF$129,10,0) -> 30 | X23: N/A | Y23: 61740 | Z23: =VLOOKUP(A23,'[1]Pay sheet-APRIL- 2022'!$C$57:$AF$129,11,0) -> 37044 | AA23: 0 | AB23: 0 | AC23: =AD23+AE23+AF23+AG23 -> 24809 | AD23: =VLOOKUP(A23,'[1]Pay sheet-APRIL- 2022'!$C$57:$AF$129,12,0) -> 14817.6 | AE23: =VLOOKUP(A23,'[1]Pay sheet-APRIL- 2022'!$C$57:$AF$129,13,0) -> 2083 | AF23: =VLOOKUP(A23,'[1]Pay sheet-APRIL- 2022'!$C$57:$AF$129,14,0) -> 2083 | AG23: =VLOOKUP(A23,'[1]Pay sheet-APRIL- 2022'!$C$57:$AF$129,15,0) -> 5825.4 | AH23: =Z23+AC23 -> 61853 | AI23: =VLOOKUP(A23,'[1]Pay sheet-APRIL- 2022'!$C$57:$AF$129,18,0) -> 1554.609 | AJ23: =VLOOKUP(A23,'[1]Pay sheet-APRIL- 2022'!$C$57:$AF$129,19,0) -> 1781.8164 | AK23: =VLOOKUP(A23,'[1]Pay sheet-APRIL- 2022'!$C$57:$AF$129,20,0) -> 3087 | AL23: =VLOOKUP(A23,'[1]Pay sheet-APRIL- 2022'!$C$57:$AF$129,22,0) -> 0 | AM23: =Z23+AD23+AE23+AF23+AG23+AI23+AJ23+AK23 -> 68276.425 | AN23: 0 | AO23: =VLOOKUP(A23,'[1]Pay sheet-APRIL- 2022'!$C$57:$AF$129,26,0) -> 1800 | AP23: =VLOOKUP(A23,'[1]Pay sheet-APRIL- 2022'!$C$57:$AF$129,25,0) -> 200 | AQ23: =VLOOKUP(A23,'[1]Pay sheet-APRIL- 2022'!$C$57:$AF$129,24,0) -> 0 | AR23: =VLOOKUP(A23,'[1]Pay sheet-APRIL- 2022'!$C$57:$AF$129,27,0) -> 283 | AS23: =SUM(AO23:AR23) -> 2283 | AT23: =AM23+AL23+-AS23 -> 65993.425 | AU23: 05.05.2022 | AV23: ICICI Bank | AW23: 001901524778 | AY23: 61 | AZ23: 8
A24: BITS-680 | B24: Arvind Akhare | C24: 32329 | D24: MALE | E24: Vasanth Rao Ramkishan Akhare | F24: Project Manager | G24: AP.Shelgaon Deshmukh sub distruct,Mehkar,District Buldana,Maharastra 443303 | I24: OOO | J24: AP.Shelgaon Deshmukh sub distruct,Mehkar,District Buldana,Maharastra 443303 | K24: OOO | L24: OOO | M24: OOO | N24: 44537 | S24: 100743126845 | T24: N/A | U24: Arvind Akhare | V24: 30 | W24: =VLOOKUP(A24,'[1]Pay sheet-APRIL- 2022'!$C$57:$AF$129,10,0) -> 28 | X24: N/A | Y24: 84912 | Z24: =VLOOKUP(A24,'[1]Pay sheet-APRIL- 2022'!$C$57:$AF$129,11,0) -> 47550.72 | AA24: 0 | AB24: 0 | AC24: =AD24+AE24+AF24+AG24 -> 31813.48 | AD24: =VLOOKUP(A24,'[1]Pay sheet-APRIL- 2022'!$C$57:$AF$129,12,0) -> 19020.288 | AE24: =VLOOKUP(A24,'[1]Pay sheet-APRIL- 2022'!$C$57:$AF$129,13,0) -> 1944 | AF24: =VLOOKUP(A24,'[1]Pay sheet-APRIL- 2022'!$C$57:$AF$129,14,0) -> 1944 | AG24: =VLOOKUP(A24,'[1]Pay sheet-APRIL- 2022'!$C$57:$AF$129,15,0) -> 8905.192 | AH24: =Z24+AC24 -> 79364.2 | AI24: =VLOOKUP(A24,'[1]Pay sheet-APRIL- 2022'!$C$57:$AF$129,18,0) -> 1554.609 | AJ24: =VLOOKUP(A24,'[1]Pay sheet-APRIL- 2022'!$C$57:$AF$129,19,0) -> 2287.1896 | AK24: =VLOOKUP(A24,'[1]Pay sheet-APRIL- 2022'!$C$57:$AF$129,20,0) -> 3962.56 | AL24: =VLOOKUP(A24,'[1]Pay sheet-APRIL- 2022'!$C$57:$AF$129,22,0) -> 0 | AM24: =Z24+AD24+AE24+AF24+AG24+AI24+AJ24+AK24 -> 87168.559 | AN24: 0 | AO24: =VLOOKUP(A24,'[1]Pay sheet-APRIL- 2022'!$C$57:$AF$129,26,0) -> 1800 | AP24: =VLOOKUP(A24,'[1]Pay sheet-APRIL- 2022'!$C$57:$AF$129,25,0) -> 200 | AQ24: =VLOOKUP(A24,'[1]Pay sheet-APRIL- 2022'!$C$57:$AF$129,24,0) -> 0 | AR24: =VLOOKUP(A24,'[1]Pay sheet-APRIL- 2022'!$C$57:$AF$129,27,0) -> 283 | AS24: =SUM(AO24:AR24) -> 2283 | AT24: =AM24+AL24+-AS24 -> 84885.559 | AU24: 05.05.2022 | AV24: HDFC Bank | AW24: 50100150364960 | AY24: 62 | AZ24: 9
A25: BITS-681 | B25: Pallavi Rishikesh Naik | C25: 34094 | D25: Female | E25: Rishikesh Naik | F25: Project Manager | G25: C/3,Ekta Housing Society,MIDC,G Block,Sambajinagar,Chinchiwad,Pune 411019 | I25: OOO | J25: C/O Prameela Savath,Suryasirvad society,Flat No.5,Near Waghere wada,Priyadarshini school,Nehru nagar,Pimpri,Pune 411048 | K25: OOO | L25: OOO | M25: OOO | N25: 44538 | S25: 100905532909 | T25: N/A | U25: Pallavi Rishikesh Naik | V25: 30 | W25: =VLOOKUP(A25,'[1]Pay sheet-APRIL- 2022'!$C$57:$AF$129,10,0) -> 30 | X25: N/A | Y25: 71009 | Z25: =VLOOKUP(A25,'[1]Pay sheet-APRIL- 2022'!$C$57:$AF$129,11,0) -> 42605.4 | AA25: 0 | AB25: 0 | AC25: =AD25+AE25+AF25+AG25 -> 28516.6 | AD25: =VLOOKUP(A25,'[1]Pay sheet-APRIL- 2022'!$C$57:$AF$129,12,0) -> 17042.16 | AE25: =VLOOKUP(A25,'[1]Pay sheet-APRIL- 2022'!$C$57:$AF$129,13,0) -> 2083 | AF25: =VLOOKUP(A25,'[1]Pay sheet-APRIL- 2022'!$C$57:$AF$129,14,0) -> 2083 | AG25: =VLOOKUP(A25,'[1]Pay sheet-APRIL- 2022'!$C$57:$AF$129,15,0) -> 7308.44 | AH25: =Z25+AC25 -> 71122 | AI25: =VLOOKUP(A25,'[1]Pay sheet-APRIL- 2022'!$C$57:$AF$129,18,0) -> 1554.609 | AJ25: =VLOOKUP(A25,'[1]Pay sheet-APRIL- 2022'!$C$57:$AF$129,19,0) -> 2049.3197 | AK25: =VLOOKUP(A25,'[1]Pay sheet-APRIL- 2022'!$C$57:$AF$129,20,0) -> 3550.45 | AL25: =VLOOKUP(A25,'[1]Pay sheet-APRIL- 2022'!$C$57:$AF$129,22,0) -> 0 | AM25: =Z25+AD25+AE25+AF25+AG25+AI25+AJ25+AK25 -> 78276.379 | AN25: 0 | AO25: =VLOOKUP(A25,'[1]Pay sheet-APRIL- 2022'!$C$57:$AF$129,26,0) -> 1800 | AP25: =VLOOKUP(A25,'[1]Pay sheet-APRIL- 2022'!$C$57:$AF$129,25,0) -> 200 | AQ25: =VLOOKUP(A25,'[1]Pay sheet-APRIL- 2022'!$C$57:$AF$129,24,0) -> 0 | AR25: =VLOOKUP(A25,'[1]Pay sheet-APRIL- 2022'!$C$57:$AF$129,27,0) -> 283 | AS25: =SUM(AO25:AR25) -> 2283 | AT25: =AM25+AL25+-AS25 -> 75993.379 | AU25: 05.05.2022 | AV25: CITI Bank | AW25: 5696586708 | AY25: 63 | AZ25: 10
A26: BITS-686 | B26: Amit Kumar | C26: 31700 | D26: MALE | E26: Yadram | F26: Linux Administrator | G26: 525,Galli No.1,Sector 44,Chalera,Noida,Gowtham Budda nagar,Uttarpradesh 201301 | I26: OOO | J26: 525,Galli No.1,Sector 44,Chalera,Noida,Gowtham Budda nagar,Uttarpradesh 201301 | K26: OOO | L26: OOO | M26: OOO | N26: 44557 | S26: 100986290999 | T26: N/A | U26: Amit Kumar | V26: 30 | W26: =VLOOKUP(A26,'[1]Pay sheet-APRIL- 2022'!$C$57:$AF$129,10,0) -> 30 | X26: N/A | Y26: 94181 | Z26: =VLOOKUP(A26,'[1]Pay sheet-APRIL- 2022'!$C$57:$AF$129,11,0) -> 56508.6 | AA26: 0 | AB26: 0 | AC26: =AD26+AE26+AF26+AG26 -> 37785.4 | AD26: =VLOOKUP(A26,'[1]Pay sheet-APRIL- 2022'!$C$57:$AF$129,12,0) -> 22603.44 | AE26: =VLOOKUP(A26,'[1]Pay sheet-APRIL- 2022'!$C$57:$AF$129,13,0) -> 2083 | AF26: =VLOOKUP(A26,'[1]Pay sheet-APRIL- 2022'!$C$57:$AF$129,14,0) -> 2083 | AG26: =VLOOKUP(A26,'[1]Pay sheet-APRIL- 2022'!$C$57:$AF$129,15,0) -> 11015.96 | AH26: =Z26+AC26 -> 94294 | AI26: =VLOOKUP(A26,'[1]Pay sheet-APRIL- 2022'!$C$57:$AF$129,18,0) -> 1554.609 | AJ26: =VLOOKUP(A26,'[1]Pay sheet-APRIL- 2022'!$C$57:$AF$129,19,0) -> 2718.0637 | AK26: =VLOOKUP(A26,'[1]Pay sheet-APRIL- 2022'!$C$57:$AF$129,20,0) -> 4709.05 | AL26: =VLOOKUP(A26,'[1]Pay sheet-APRIL- 2022'!$C$57:$AF$129,22,0) -> 0 | AM26: =Z26+AD26+AE26+AF26+AG26+AI26+AJ26+AK26 -> 103275.72 | AN26: 0 | AO26: =VLOOKUP(A26,'[1]Pay sheet-APRIL- 2022'!$C$57:$AF$129,26,0) -> 1800 | AP26: =VLOOKUP(A26,'[1]Pay sheet-APRIL- 2022'!$C$57:$AF$129,25,0) -> 200 | AQ26: =VLOOKUP(A26,'[1]Pay sheet-APRIL- 2022'!$C$57:$AF$129,24,0) -> 0 | AR26: =VLOOKUP(A26,'[1]Pay sheet-APRIL- 2022'!$C$57:$AF$129,27,0) -> 283 | AS26: =SUM(AO26:AR26) -> 2283 | AT26: =AM26+AL26+-AS26 -> 100992.72 | AU26: 05.05.2022 | AV26: HDFC Bank | AW26: 05121140023169 | AY26: 64 | AZ26: 11
A27: BITS-688 | B27: Pranav Thakare | C27: 34393 | D27: MALE | E27: Pramod Motiram Thakare | F27: Project Manager | G27: B-78, State Employees Society,Ashoknagar,Satpur,Nashik | I27: OOO | J27: B-78, State Employees Society,Ashoknagar,Satpur,Nashik | K27: OOO | L27: OOO | M27: OOO | N27: 44564 | O27: OOO | P27: OOO | Q27: OOO | R27: OOO | S27: 100716206034 | T27: N/A | U27: Pranav Thakare | V27: 30 | W27: =VLOOKUP(A27,'[1]Pay sheet-APRIL- 2022'!$C$57:$AF$129,10,0) -> 27 | X27: N/A | Y27: 75643 | Z27: =VLOOKUP(A27,'[1]Pay sheet-APRIL- 2022'!$C$57:$AF$129,11,0) -> 40847.22 | AA27: 0 | AB27: 0 | AC27: =AD27+AE27+AF27+AG27 -> 27344.48 | AD27: =VLOOKUP(A27,'[1]Pay sheet-APRIL- 2022'!$C$57:$AF$129,12,0) -> 16338.888 | AE27: =VLOOKUP(A27,'[1]Pay sheet-APRIL- 2022'!$C$57:$AF$129,13,0) -> 1875 | AF27: =VLOOKUP(A27,'[1]Pay sheet-APRIL- 2022'!$C$57:$AF$129,14,0) -> 1875 | AG27: =VLOOKUP(A27,'[1]Pay sheet-APRIL- 2022'!$C$57:$AF$129,15,0) -> 7255.592 | AH27: =Z27+AC27 -> 68191.7 | AI27: =VLOOKUP(A27,'[1]Pay sheet-APRIL- 2022'!$C$57:$AF$129,18,0) -> 1554.609 | AJ27: =VLOOKUP(A27,'[1]Pay sheet-APRIL- 2022'!$C$57:$AF$129,19,0) -> 1964.7513 | AK27: =VLOOKUP(A27,'[1]Pay sheet-APRIL- 2022'!$C$57:$AF$129,20,0) -> 3403.935 | AL27: =VLOOKUP(A27,'[1]Pay sheet-APRIL- 2022'!$C$57:$AF$129,22,0) -> 0 | AM27: =Z27+AD27+AE27+AF27+AG27+AI27+AJ27+AK27 -> 75114.995 | AN27: 0 | AO27: =VLOOKUP(A27,'[1]Pay sheet-APRIL- 2022'!$C$57:$AF$129,26,0) -> 1800 | AP27: =VLOOKUP(A27,'[1]Pay sheet-APRIL- 2022'!$C$57:$AF$129,25,0) -> 200 | AQ27: =VLOOKUP(A27,'[1]Pay sheet-APRIL- 2022'!$C$57:$AF$129,24,0) -> 0 | AR27: =VLOOKUP(A27,'[1]Pay sheet-APRIL- 2022'!$C$57:$AF$129,27,0) -> 283 | AS27: =SUM(AO27:AR27) -> 2283 | AT27: =AM27+AL27+-AS27 -> 72831.995 | AU27: 05.05.2022 | AV27: ICICI BANK | AW27: 056601532765 | AY27: 65 | AZ27: 12
A28: BITS-694 | B28: Asita Kumar Sahoo | C28: 28308 | D28: MALE | E28: Dambarudar Sahoo | F28: Network Admin | G28: Airforce station, Achalgarh, Delwara, Abu road, Sirohi, Rajasthan 307501 | H28: OOO | I28: OOO | J28: Airforce station, Achalgarh, Delwara, Abu road, Sirohi, Rajasthan 307501 | K28: OOO | L28: OOO | M28: OOO | N28: 44567 | O28: OOO | P28: OOO | Q28: OOO | R28: OOO | S28: 100716206034 | T28: N/A | U28: Asita Kumar Sahoo | V28: 30 | W28: =VLOOKUP(A28,'[1]Pay sheet-APRIL- 2022'!$C$57:$AF$129,10,0) -> 30 | X28: N/A | Y28: 52471 | Z28: =VLOOKUP(A28,'[1]Pay sheet-APRIL- 2022'!$C$57:$AF$129,11,0) -> 31482.6 | AA28: 0 | AB28: 0 | AC28: =AD28+AE28+AF28+AG28 -> 21101.4 | AD28: =VLOOKUP(A28,'[1]Pay sheet-APRIL- 2022'!$C$57:$AF$129,12,0) -> 12593.04 | AE28: =VLOOKUP(A28,'[1]Pay sheet-APRIL- 2022'!$C$57:$AF$129,13,0) -> 2083 | AF28: =VLOOKUP(A28,'[1]Pay sheet-APRIL- 2022'!$C$57:$AF$129,14,0) -> 2083 | AG28: =VLOOKUP(A28,'[1]Pay sheet-APRIL- 2022'!$C$57:$AF$129,15,0) -> 4342.36 | AH28: =Z28+AC28 -> 52584 | AI28: =VLOOKUP(A28,'[1]Pay sheet-APRIL- 2022'!$C$57:$AF$129,18,0) -> 1554.609 | AJ28: =VLOOKUP(A28,'[1]Pay sheet-APRIL- 2022'!$C$57:$AF$129,19,0) -> 1514.3131 | AK28: =VLOOKUP(A28,'[1]Pay sheet-APRIL- 2022'!$C$57:$AF$129,20,0) -> 2623.55 | AL28: =VLOOKUP(A28,'[1]Pay sheet-APRIL- 2022'!$C$57:$AF$129,22,0) -> 0 | AM28: =Z28+AD28+AE28+AF28+AG28+AI28+AJ28+AK28 -> 58276.472 | AN28: 0 | AO28: =VLOOKUP(A28,'[1]Pay sheet-APRIL- 2022'!$C$57:$AF$129,26,0) -> 1800 | AP28: =VLOOKUP(A28,'[1]Pay sheet-APRIL- 2022'!$C$57:$AF$129,25,0) -> 200 | AQ28: =VLOOKUP(A28,'[1]Pay sheet-APRIL- 2022'!$C$57:$AF$129,24,0) -> 0 | AR28: =VLOOKUP(A28,'[1]Pay sheet-APRIL- 2022'!$C$57:$AF$129,27,0) -> 283 | AS28: =SUM(AO28:AR28) -> 2283 | AT28: =AM28+AL28+-AS28 -> 55993.472 | AU28: 05.05.2022 | AV28: ICICI BANK | AW28: 056601532765 | AY28: 66 | AZ28: 13
A29: BITS-706 | B29: Arun Arra | C29: 34378 | D29: MALE | E29: Anjam Raju | F29: SAP Basis consultant | G29: 1-52/3, Suryanager Colony, Uppal, HYD 500039 | H29: OOO | I29: OOO | J29: H.No: 2-3-226, Dubbawada, Metpally, 505325 | K29: OOO | L29: OOO | M29: OOO | N29: 44602 | O29: OOO | P29: OOO | Q29: OOO | R29: OOO | S29: 101377758010 | T29: N/A | U29: Arun Arra | V29: 30 | W29: =VLOOKUP(A29,'[1]Pay sheet-APRIL- 2022'!$C$57:$AF$129,10,0) -> 30 | X29: N/A | Y29: 38567 | Z29: =VLOOKUP(A29,'[1]Pay sheet-APRIL- 2022'!$C$57:$AF$129,11,0) -> 23140.2 | AA29: 0 | AB29: 0 | AC29: =AD29+AE29+AF29+AG29 -> 15539.8 | AD29: =VLOOKUP(A29,'[1]Pay sheet-APRIL- 2022'!$C$57:$AF$129,12,0) -> 9256.08 | AE29: =VLOOKUP(A29,'[1]Pay sheet-APRIL- 2022'!$C$57:$AF$129,13,0) -> 2083 | AF29: =VLOOKUP(A29,'[1]Pay sheet-APRIL- 2022'!$C$57:$AF$129,14,0) -> 2083 | AG29: =VLOOKUP(A29,'[1]Pay sheet-APRIL- 2022'!$C$57:$AF$129,15,0) -> 2117.72 | AH29: =Z29+AC29 -> 38680 | AI29: =VLOOKUP(A29,'[1]Pay sheet-APRIL- 2022'!$C$57:$AF$129,18,0) -> 1554.609 | AJ29: =VLOOKUP(A29,'[1]Pay sheet-APRIL- 2022'!$C$57:$AF$129,19,0) -> 1113.0436 | AK29: =VLOOKUP(A29,'[1]Pay sheet-APRIL- 2022'!$C$57:$AF$129,20,0) -> 1928.35 | AL29: =VLOOKUP(A29,'[1]Pay sheet-APRIL- 2022'!$C$57:$AF$129,22,0) -> 0 | AM29: =Z29+AD29+AE29+AF29+AG29+AI29+AJ29+AK29 -> 43276.003 | AO29: =VLOOKUP(A29,'[1]Pay sheet-APRIL- 2022'!$C$57:$AF$129,26,0) -> 1800 | AP29: =VLOOKUP(A29,'[1]Pay sheet-APRIL- 2022'!$C$57:$AF$129,25,0) -> 200 | AQ29: =VLOOKUP(A29,'[1]Pay sheet-APRIL- 2022'!$C$57:$AF$129,24,0) -> 0 | AR29: =VLOOKUP(A29,'[1]Pay sheet-APRIL- 2022'!$C$57:$AF$129,27,0) -> 283 | AS29: =SUM(AO29:AR29) -> 2283 | AT29: =AM29+AL29+-AS29 -> 40993.003 | AU29: 05.05.2022 | AV29: SBI | AW29: A/C No : 32523021338, | AY29: 67 | AZ29: 14
A30: BITS-707 | B30: Ramya Nalla | C30: 22-03-1998 | D30: FEMALE | E30: W/O Chitharanjan Allem | F30: SAP Basis consultant | G30: C-101, Akruthi Arcade, Anand Nagar, GB road, Thane West, Mumbai, Maharashtra,400615 | H30: OOO | I30: OOO | J30: C-101, Akruthi Arcade, Anand Nagar, GB road, Thane West, Mumbai, Maharashtra,400615 | K30: OOO | L30: OOO | M30: OOO | N30: 10/2/2022 | O30: OOO | P30: OOO | Q30: OOO | R30: OOO | S30: 10179269235 | T30: N/A | U30: Ramya Nalla | V30: 30 | W30: =VLOOKUP(A30,'[1]Pay sheet-APRIL- 2022'!$C$57:$AF$129,10,0) -> 30 | X30: N/A | Y30: 38567 | Z30: =VLOOKUP(A30,'[1]Pay sheet-APRIL- 2022'!$C$57:$AF$129,11,0) -> 23140.2 | AA30: 0 | AB30: 0 | AC30: =AD30+AE30+AF30+AG30 -> 15539.8 | AD30: =VLOOKUP(A30,'[1]Pay sheet-APRIL- 2022'!$C$57:$AF$129,12,0) -> 9256.08 | AE30: =VLOOKUP(A30,'[1]Pay sheet-APRIL- 2022'!$C$57:$AF$129,13,0) -> 2083 | AF30: =VLOOKUP(A30,'[1]Pay sheet-APRIL- 2022'!$C$57:$AF$129,14,0) -> 2083 | AG30: =VLOOKUP(A30,'[1]Pay sheet-APRIL- 2022'!$C$57:$AF$129,15,0) -> 2117.72 | AH30: =Z30+AC30 -> 38680 | AI30: =VLOOKUP(A30,'[1]Pay sheet-APRIL- 2022'!$C$57:$AF$129,18,0) -> 1554.609 | AJ30: =VLOOKUP(A30,'[1]Pay sheet-APRIL- 2022'!$C$57:$AF$129,19,0) -> 1113.0436 | AK30: =VLOOKUP(A30,'[1]Pay sheet-APRIL- 2022'!$C$57:$AF$129,20,0) -> 1928.35 | AL30: =VLOOKUP(A30,'[1]Pay sheet-APRIL- 2022'!$C$57:$AF$129,22,0) -> 0 | AM30: =Z30+AD30+AE30+AF30+AG30+AI30+AJ30+AK30 -> 43276.003 | AO30: =VLOOKUP(A30,'[1]Pay sheet-APRIL- 2022'!$C$57:$AF$129,26,0) -> 1800 | AP30: =VLOOKUP(A30,'[1]Pay sheet-APRIL- 2022'!$C$57:$AF$129,25,0) -> 200 | AQ30: =VLOOKUP(A30,'[1]Pay sheet-APRIL- 2022'!$C$57:$AF$129,24,0) -> 0 | AR30: =VLOOKUP(A30,'[1]Pay sheet-APRIL- 2022'!$C$57:$AF$129,27,0) -> 283 | AS30: =SUM(AO30:AR30) -> 2283 | AT30: =AM30+AL30+-AS30 -> 40993.003 | AU30: 05.05.2022 | AV30: SBI | AW30: A/C no: 37660478448 | AY30: 68 | AZ30: 15
A31: BITS-709 | B31: Uma Mahesh P | C31: 35748 | D31: MALE | E31: PENTAKOTA LAKSHI | F31: SAP Basis consultant | G31: D.NO: 1-1 , PENTAKOTA VARI STREET , CHUCHUKONDA (VILLAGE),MUNAGAPAKA (MANDAL),VISHAKAPATNAM(DISTRICT),PIN CODE:531055 | H31: OOO | I31: OOO | J31: D.NO: 1-1 , PENTAKOTA VARI STREET , CHUCHUKONDA(VILLAGE),MUNAGAPAKA(MANDAL),VISHAKAPATNAM(DISTRICT),PINCODE:531055 | K31: OOO | L31: OOO | M31: OOO | N31: 10/2/2022 | O31: OOO | P31: OOO | Q31: OOO | R31: OOO | S31: 101792969226 | T31: N/A | U31: Uma Mahesh P | V31: 30 | W31: =VLOOKUP(A31,'[1]Pay sheet-APRIL- 2022'!$C$57:$AF$129,10,0) -> 29 | X31: N/A | Y31: 38567 | Z31: =VLOOKUP(A31,'[1]Pay sheet-APRIL- 2022'!$C$57:$AF$129,11,0) -> 22368.86 | AA31: 0 | AB31: 0 | AC31: =AD31+AE31+AF31+AG31 -> 15025.573 | AD31: =VLOOKUP(A31,'[1]Pay sheet-APRIL- 2022'!$C$57:$AF$129,12,0) -> 8947.544 | AE31: =VLOOKUP(A31,'[1]Pay sheet-APRIL- 2022'!$C$57:$AF$129,13,0) -> 2014 | AF31: =VLOOKUP(A31,'[1]Pay sheet-APRIL- 2022'!$C$57:$AF$129,14,0) -> 2014 | AG31: =VLOOKUP(A31,'[1]Pay sheet-APRIL- 2022'!$C$57:$AF$129,15,0) -> 2050.0293 | AH31: =Z31+AC31 -> 37394.433 | AI31: =VLOOKUP(A31,'[1]Pay sheet-APRIL- 2022'!$C$57:$AF$129,18,0) -> 1554.609 | AJ31: =VLOOKUP(A31,'[1]Pay sheet-APRIL- 2022'!$C$57:$AF$129,19,0) -> 1075.9422 | AK31: =VLOOKUP(A31,'[1]Pay sheet-APRIL- 2022'!$C$57:$AF$129,20,0) -> 1864.0717 | AL31: =VLOOKUP(A31,'[1]Pay sheet-APRIL- 2022'!$C$57:$AF$129,22,0) -> 0 | AM31: =Z31+AD31+AE31+AF31+AG31+AI31+AJ31+AK31 -> 41889.056 | AO31: =VLOOKUP(A31,'[1]Pay sheet-APRIL- 2022'!$C$57:$AF$129,26,0) -> 1800 | AP31: =VLOOKUP(A31,'[1]Pay sheet-APRIL- 2022'!$C$57:$AF$129,25,0) -> 200 | AQ31: =VLOOKUP(A31,'[1]Pay sheet-APRIL- 2022'!$C$57:$AF$129,24,0) -> 0 | AR31: =VLOOKUP(A31,'[1]Pay sheet-APRIL- 2022'!$C$57:$AF$129,27,0) -> 283 | AS31: =SUM(AO31:AR31) -> 2283 | AT31: =AM31+AL31+-AS31 -> 39606.056 | AU31: 05.05.2022 | AV31: HDFC BANK | AW31: A/C NO 50100444213458 | AY31: 70 | AZ31: 16
A32: BITS-713 | B32: NAGA SAI TEJA NUTHI | C32: 33292 | D32: MALE | E32: G seshaiah | F32: SAP Basis consultant | G32: Hno 15-21-237/1,Flat no G2,sattenapally towers,Balaji Nagar,Kukatpally,Hyderabad,500072 | H32: OOOO | I32: OOOO | J32: Hno 15-21-237/1,Flat no G2,sattenapally towers,Balaji Nagar,Kukatpally,Hyderabad,500072 | K32: OOOO | L32: OOOO | M32: OOOO | N32: 44602 | O32: OOO | P32: OOO | Q32: OOO | R32: OOO | S32: 101756843175 | T32: N/A | U32: NAGA SAI TEJA NUTHI | V32: 30 | W32: =VLOOKUP(A32,'[1]Pay sheet-APRIL- 2022'!$C$57:$AF$129,10,0) -> 27 | X32: N/A | Y32: 43202 | Z32: =VLOOKUP(A32,'[1]Pay sheet-APRIL- 2022'!$C$57:$AF$129,11,0) -> 23329.08 | AA32: 0 | AB32: 0 | AC32: =AD32+AE32+AF32+AG32 -> 15665.72 | AD32: =VLOOKUP(A32,'[1]Pay sheet-APRIL- 2022'!$C$57:$AF$129,12,0) -> 9331.632 | AE32: =VLOOKUP(A32,'[1]Pay sheet-APRIL- 2022'!$C$57:$AF$129,13,0) -> 1875 | AF32: =VLOOKUP(A32,'[1]Pay sheet-APRIL- 2022'!$C$57:$AF$129,14,0) -> 1875 | AG32: =VLOOKUP(A32,'[1]Pay sheet-APRIL- 2022'!$C$57:$AF$129,15,0) -> 2584.088 | AH32: =Z32+AC32 -> 38994.8 | AI32: =VLOOKUP(A32,'[1]Pay sheet-APRIL- 2022'!$C$57:$AF$129,18,0) -> 1554.609 | AJ32: =VLOOKUP(A32,'[1]Pay sheet-APRIL- 2022'!$C$57:$AF$129,19,0) -> 1122.1287 | AK32: =VLOOKUP(A32,'[1]Pay sheet-APRIL- 2022'!$C$57:$AF$129,20,0) -> 1944.09 | AL32: =VLOOKUP(A32,'[1]Pay sheet-APRIL- 2022'!$C$57:$AF$129,22,0) -> 0 | AM32: =Z32+AD32+AE32+AF32+AG32+AI32+AJ32+AK32 -> 43615.628 | AO32: =VLOOKUP(A32,'[1]Pay sheet-APRIL- 2022'!$C$57:$AF$129,26,0) -> 1800 | AP32: =VLOOKUP(A32,'[1]Pay sheet-APRIL- 2022'!$C$57:$AF$129,25,0) -> 200 | AQ32: =VLOOKUP(A32,'[1]Pay sheet-APRIL- 2022'!$C$57:$AF$129,24,0) -> 0 | AR32: =VLOOKUP(A32,'[1]Pay sheet-APRIL- 2022'!$C$57:$AF$129,27,0) -> 283 | AS32: =SUM(AO32:AR32) -> 2283 | AT32: =AM32+AL32+-AS32 -> 41332.628 | AU32: 05.05.2022 | AV32: SBI | AW32: A/C NO 20297714176 | AY32: 74 | AZ32: 17
A33: BITS-714 | B33: Mani Krishna Nandineedi | C33: 35088 | D33: MALE | E33: N Srinivasu | F33: SAP Basis consultant | G33: 204-7-343, Nagireddy Nagar, Near Three temples | H33: OOOO | I33: OOOO | J33: 3-542, 10th street RK Nagar, Rajahmundry 533107 | K33: OOOO | L33: OOOO | M33: OOOO | N33: 44602 | O33: OOO | P33: OOO | Q33: OOO | R33: OOO | S33: 101589884490 | T33: N/A | U33: Mani Krishna Nandineedi | V33: 30 | W33: =VLOOKUP(A33,'[1]Pay sheet-APRIL- 2022'!$C$57:$AF$129,10,0) -> 30 | X33: N/A | Y33: 38567 | Z33: =VLOOKUP(A33,'[1]Pay sheet-APRIL- 2022'!$C$57:$AF$129,11,0) -> 23140.2 | AA33: 0 | AB33: 0 | AC33: =AD33+AE33+AF33+AG33 -> 15539.8 | AD33: =VLOOKUP(A33,'[1]Pay sheet-APRIL- 2022'!$C$57:$AF$129,12,0) -> 9256.08 | AE33: =VLOOKUP(A33,'[1]Pay sheet-APRIL- 2022'!$C$57:$AF$129,13,0) -> 2083 | AF33: =VLOOKUP(A33,'[1]Pay sheet-APRIL- 2022'!$C$57:$AF$129,14,0) -> 2083 | AG33: =VLOOKUP(A33,'[1]Pay sheet-APRIL- 2022'!$C$57:$AF$129,15,0) -> 2117.72 | AH33: =Z33+AC33 -> 38680 | AI33: =VLOOKUP(A33,'[1]Pay sheet-APRIL- 2022'!$C$57:$AF$129,18,0) -> 1554.609 | AJ33: =VLOOKUP(A33,'[1]Pay sheet-APRIL- 2022'!$C$57:$AF$129,19,0) -> 1113.0436 | AK33: =VLOOKUP(A33,'[1]Pay sheet-APRIL- 2022'!$C$57:$AF$129,20,0) -> 1928.35 | AL33: =VLOOKUP(A33,'[1]Pay sheet-APRIL- 2022'!$C$57:$AF$129,22,0) -> 0 | AM33: =Z33+AD33+AE33+AF33+AG33+AI33+AJ33+AK33 -> 43276.003 | AO33: =VLOOKUP(A33,'[1]Pay sheet-APRIL- 2022'!$C$57:$AF$129,26,0) -> 1800 | AP33: =VLOOKUP(A33,'[1]Pay sheet-APRIL- 2022'!$C$57:$AF$129,25,0) -> 200 | AQ33: =VLOOKUP(A33,'[1]Pay sheet-APRIL- 2022'!$C$57:$AF$129,24,0) -> 0 | AR33: =VLOOKUP(A33,'[1]Pay sheet-APRIL- 2022'!$C$57:$AF$129,27,0) -> 283 | AS33: =SUM(AO33:AR33) -> 2283 | AT33: =AM33+AL33+-AS33 -> 40993.003 | AU33: 05.05.2022 | AV33: HDFC BANK | AW33: A/C NO 50100360114888 | AY33: 75 | AZ33: 18
A34: BITS-715 | B34: Sushma P | C34: 32638 | D34: FEMALE | E34: Veeraswamy | F34: SAP Basis consultant | G34: H No 5-11/1, Janakipuram, bonakal,Khammam, Telangana 507204 | H34: OOOO | I34: OOOO | J34: H No 5-11/1, Janakipuram, bonakal,Khammam, Telangana 507204 | K34: OOOO | L34: OOOO | M34: OOOO | N34: 44602 | O34: OOO | P34: OOO | Q34: OOO | R34: OOO | S34: 100542320584 | T34: N/A | U34: Sushma P | V34: 30 | W34: =VLOOKUP(A34,'[1]Pay sheet-APRIL- 2022'!$C$57:$AF$129,10,0) -> 30 | X34: N/A | Y34: 38567 | Z34: =VLOOKUP(A34,'[1]Pay sheet-APRIL- 2022'!$C$57:$AF$129,11,0) -> 23140.2 | AA34: 0 | AB34: 0 | AC34: =AD34+AE34+AF34+AG34 -> 15539.8 | AD34: =VLOOKUP(A34,'[1]Pay sheet-APRIL- 2022'!$C$57:$AF$129,12,0) -> 9256.08 | AE34: =VLOOKUP(A34,'[1]Pay sheet-APRIL- 2022'!$C$57:$AF$129,13,0) -> 2083 | AF34: =VLOOKUP(A34,'[1]Pay sheet-APRIL- 2022'!$C$57:$AF$129,14,0) -> 2083 | AG34: =VLOOKUP(A34,'[1]Pay sheet-APRIL- 2022'!$C$57:$AF$129,15,0) -> 2117.72 | AH34: =Z34+AC34 -> 38680 | AI34: =VLOOKUP(A34,'[1]Pay sheet-APRIL- 2022'!$C$57:$AF$129,18,0) -> 1554.609 | AJ34: =VLOOKUP(A34,'[1]Pay sheet-APRIL- 2022'!$C$57:$AF$129,19,0) -> 1113.0436 | AK34: =VLOOKUP(A34,'[1]Pay sheet-APRIL- 2022'!$C$57:$AF$129,20,0) -> 1928.35 | AL34: =VLOOKUP(A34,'[1]Pay sheet-APRIL- 2022'!$C$57:$AF$129,22,0) -> 0 | AM34: =Z34+AD34+AE34+AF34+AG34+AI34+AJ34+AK34 -> 43276.003 | AO34: =VLOOKUP(A34,'[1]Pay sheet-APRIL- 2022'!$C$57:$AF$129,26,0) -> 1800 | AP34: =VLOOKUP(A34,'[1]Pay sheet-APRIL- 2022'!$C$57:$AF$129,25,0) -> 200 | AQ34: =VLOOKUP(A34,'[1]Pay sheet-APRIL- 2022'!$C$57:$AF$129,24,0) -> 0 | AR34: =VLOOKUP(A34,'[1]Pay sheet-APRIL- 2022'!$C$57:$AF$129,27,0) -> 283 | AS34: =SUM(AO34:AR34) -> 2283 | AT34: =AM34+AL34+-AS34 -> 40993.003 | AU34: 05.05.2022 | AV34: SBI | AW34: A/C NO 62111073370 | AY34: 76 | AZ34: 19
A35: BITS-741 | B35: susheelKumar Gandla | C35: 30056 | D35: MALE | E35: Narayana Gandla | F35: Sr.Software Engineer | G35: Flat no.308,Block A,Akruthi srinivasan Appts,Balaji nagar,Road.3,Nizampet,Hyderabad,TS 500090 | I35: OOOO | J35: Flat no.308,Block A,Akruthi srinivasan Appts,Balaji nagar,Road.3,Nizampet,Hyderabad,TS 500090 | K35: OOOO | L35: OOOO | M35: OOOO | N35: 44652 | O35: OOOO | P35: OOOO | Q35: OOOO | R35: OOOO | S35: N/A | T35: N/A | U35: susheelKumar Gabndla | V35: 30 | W35: =VLOOKUP(A35,'[1]Pay sheet-APRIL- 2022'!$C$57:$AF$129,10,0) -> 30 | X35: N/A | Y35: =AH35/W35*31 -> 83070.7 | Z35: =VLOOKUP(A35,'[1]Pay sheet-APRIL- 2022'!$C$57:$AF$129,11,0) -> 48166.8 | AA35: 0 | AB35: 0 | AC35: =AD35+AE35+AF35+AG35 -> 32224.2 | AD35: =VLOOKUP(A35,'[1]Pay sheet-APRIL- 2022'!$C$57:$AF$129,12,0) -> 19266.72 | AE35: =VLOOKUP(A35,'[1]Pay sheet-APRIL- 2022'!$C$57:$AF$129,13,0) -> 2083 | AF35: =VLOOKUP(A35,'[1]Pay sheet-APRIL- 2022'!$C$57:$AF$129,14,0) -> 2083 | AG35: =VLOOKUP(A35,'[1]Pay sheet-APRIL- 2022'!$C$57:$AF$129,15,0) -> 8791.48 | AH35: =Z35+AC35 -> 80391 | AI35: =VLOOKUP(A35,'[1]Pay sheet-APRIL- 2022'!$C$57:$AF$129,18,0) -> 1554.609 | AJ35: =VLOOKUP(A35,'[1]Pay sheet-APRIL- 2022'!$C$57:$AF$129,19,0) -> 2316.8231 | AK35: =VLOOKUP(A35,'[1]Pay sheet-APRIL- 2022'!$C$57:$AF$129,20,0) -> 4013.9 | AL35: =VLOOKUP(A35,'[1]Pay sheet-APRIL- 2022'!$C$57:$AF$129,22,0) -> 0 | AM35: =Z35+AD35+AE35+AF35+AG35+AI35+AJ35+AK35 -> 88276.332 | AO35: =VLOOKUP(A35,'[1]Pay sheet-APRIL- 2022'!$C$57:$AF$129,26,0) -> 0 | AP35: =VLOOKUP(A35,'[1]Pay sheet-APRIL- 2022'!$C$57:$AF$129,25,0) -> 200 | AQ35: =VLOOKUP(A35,'[1]Pay sheet-APRIL- 2022'!$C$57:$AF$129,24,0) -> 0 | AR35: =VLOOKUP(A35,'[1]Pay sheet-APRIL- 2022'!$C$57:$AF$129,27,0) -> 0 | AS35: =SUM(AO35:AR35) -> 200 | AT35: =AM35+AL35+-AS35 -> 88076.332 | AU35: 05.05.2022 | AV35: ICICI BANK | AW35: A/C NO 007601548378 | AY35: 77 | AZ35: 20
W36: =SUM(W16:W35) -> 591 | Z36: =SUM(Z16:Z35) -> 792977.48 | AA36: =SUM(AA16:AA35) -> 0 | AB36: =SUM(AB16:AB35) -> 0 | AC36: =SUM(AC16:AC35) -> 530911.65 | AD36: =SUM(AD16:AD35) -> 317190.99 | AE36: =SUM(AE16:AE35) -> 41036 | AF36: =SUM(AF16:AF35) -> 41036 | AG36: =SUM(AG16:AG35) -> 131648.66 | ... AK36: =SUM(AK16:AK35) -> 66081.457 | AL36: 0 | AM36: =SUM(AM16:AM35) -> 1459205 | AN36: =SUM(AN16:AN35) -> 0 | AO36: =SUM(AO16:AO35) -> 34200 | AP36: =SUM(AP16:AP35) -> 4000 | AQ36: =SUM(AQ16:AQ35) -> 0 | AR36: =SUM(AR16:AR35) -> 5291 | AS36: =SUM(AS16:AS35) -> 43491 | AT36: =SUM(AT16:AT35) -> 1415714
C48: 30222 | D48: MALE | E48: Brijou Gopalan Koipurath | G48: 1753,Jayaram colony,Behind Holy family,Vidyanagar,Karad district Satara,Maharastra 415124 | J48: F-803,Mount Vert Vesta,Urawade,Pirangut,Pune 412108 | N48: 44390 | S48: 100142924932 | T48: N/A | U48: =B48 -> 0 | V48: 31 | W48: =VLOOKUP(A48,'[2]Pay sheet-MARCH- 2022'!$C$34:$AF$122,10,0) -> #N/A | X48: N/A | Y48: 100670 | Z48: =VLOOKUP(A48,'[2]Pay sheet-MARCH- 2022'!$C$34:$AF$122,11,0) -> #N/A | AA48: 0 | AB48: 0 | AC48: =AD48+AE48+AF48+AG48 -> #N/A | AD48: =VLOOKUP(A48,'[2]Pay sheet-MARCH- 2022'!$C$34:$AF$122,12,0) -> #N/A | AE48: =VLOOKUP(A48,'[2]Pay sheet-MARCH- 2022'!$C$34:$AF$122,13,0) -> #N/A | AF48: =VLOOKUP(A48,'[2]Pay sheet-MARCH- 2022'!$C$34:$AF$122,14,0) -> #N/A | AY48: 52 | AZ48: 1
C49: 33172 | D49: MALE | E49: SYED MOHAMMED NASEER | G49: 11-5-205 Flat No 202 2nd Floor Beside Red Hills Poly Clinic Nampally Hyderabad , Telangana - 500 004 | H49: OOO | I49: OOO | J49: 11-5-205 Flat No 202 2nd Floor Beside Red Hills Poly Clinic Nampally Hyderabad , Telangana - 500 004 | K49: OOO | L49: OOO | M49: OOO | N49: 10/2/2022 | O49: OOO | P49: OOO | Q49: OOO | R49: OOO | S49: 101081477079 | T49: N/A | U49: SYED MOHAMMED AZHER | V49: 31 | W49: =VLOOKUP(A49,'[2]Pay sheet-MARCH- 2022'!$C$34:$AF$122,10,0) -> #N/A | X49: N/A | Y49: 38567 | Z49: =VLOOKUP(A49,'[2]Pay sheet-MARCH- 2022'!$C$34:$AF$122,11,0) -> #N/A | AA49: 0 | AB49: 0 | AC49: =AD49+AE49+AF49+AG49 -> #N/A | AD49: =VLOOKUP(A49,'[2]Pay sheet-MARCH- 2022'!$C$34:$AF$122,12,0) -> #N/A | AE49: =VLOOKUP(A49,'[2]Pay sheet-MARCH- 2022'!$C$34:$AF$122,13,0) -> #N/A | AF49: =VLOOKUP(A49,'[2]Pay sheet-MARCH- 2022'!$C$34:$AF$122,14,0) -> #N/A | AY49: 69 | AZ49: 17
C50: 35895 | D50: MALE | E50: GONTHINI SATTIBABU | G50: Falt: 202, Pecan Creek,Plot 790, Road no 4c, Gopal Nagar, Gokul Enclave, Venkata Ramana Colony, Kukatpally, Hyderabad, Telangana 500085, India | H50: OOO | I50: OOO | J50: D.NO: 4-65, YADAGIRIPALEM VILLAGE, MELUPAKA POST, MUNAGAPAKA MANDAL, VISAKHAPATNAM, A.P. PINCODE -531055. | K50: OOO | L50: OOO | M50: OOO | N50: 10-2-2022 | O50: OOO | P50: OOO | Q50: OOO | R50: OOO | S50: 101478192192 | T50: N/A | U50: GONTHINI SAIBABU | V50: 31 | W50: =VLOOKUP(A50,'[2]Pay sheet-MARCH- 2022'!$C$34:$AF$122,10,0) -> #N/A | X50: N/A | Y50: 38567 | Z50: =VLOOKUP(A50,'[2]Pay sheet-MARCH- 2022'!$C$34:$AF$122,11,0) -> #N/A | AA50: 0 | AB50: 0 | AC50: =AD50+AE50+AF50+AG50 -> #N/A | AD50: =VLOOKUP(A50,'[2]Pay sheet-MARCH- 2022'!$C$34:$AF$122,12,0) -> #N/A | AE50: =VLOOKUP(A50,'[2]Pay sheet-MARCH- 2022'!$C$34:$AF$122,13,0) -> #N/A | AF50: =VLOOKUP(A50,'[2]Pay sheet-MARCH- 2022'!$C$34:$AF$122,14,0) -> #N/A | AY50: 71 | AZ50: 19
C51: 36086 | D51: MALE | E51: TATINA PULLARAO | G51: Dr no:1-73,near high school,lingapalem,west godavari district-534462 | J51: Dr no:1-73,near high school,lingapalem,west godavari district-534462 | K51: OOO | L51: OOO | M51: OOO | N51: 44602 | O51: OOO | P51: OOO | Q51: OOO | R51: OOO | S51: 101793033196 | T51: N/A | U51: Pavan Nagendra Tatina | V51: 31 | W51: =VLOOKUP(A51,'[2]Pay sheet-MARCH- 2022'!$C$34:$AF$122,10,0) -> #N/A | X51: N/A | Y51: 29298 | Z51: =VLOOKUP(A51,'[2]Pay sheet-MARCH- 2022'!$C$34:$AF$122,11,0) -> #N/A | AA51: 0 | AB51: 0 | AC51: =AD51+AE51+AF51+AG51 -> #N/A | AD51: =VLOOKUP(A51,'[2]Pay sheet-MARCH- 2022'!$C$34:$AF$122,12,0) -> #N/A | AE51: =VLOOKUP(A51,'[2]Pay sheet-MARCH- 2022'!$C$34:$AF$122,13,0) -> #N/A | AF51: =VLOOKUP(A51,'[2]Pay sheet-MARCH- 2022'!$C$34:$AF$122,14,0) -> #N/A | AY51: 72 | AZ51: 20
C52: 31019 | D52: MALE | E52: Mohd Mazhar Shareer | G52: 4-3-90/1,Attapur,Kanganagar,Near SNR function hall,Pillar no 123,Hyderabad,TS 500048 | H52: OOOO | I52: OOOO | J52: 4-3-90/1,Attapur,Kanganagar,Near SNR function hall,Pillar no 123,Hyderabad,TS 500048 | K52: OOOO | L52: OOOO | M52: OOOO | N52: 44602 | O52: OOO | P52: OOO | Q52: OOO | R52: OOO | S52: OOO | T52: N/A | U52: Mohd Azhar Shareef | V52: 31 | W52: =VLOOKUP(A52,'[2]Pay sheet-MARCH- 2022'!$C$34:$AF$122,10,0) -> #N/A | X52: N/A | Y52: 38567 | Z52: =VLOOKUP(A52,'[2]Pay sheet-MARCH- 2022'!$C$34:$AF$122,11,0) -> #N/A | AA52: 0 | AB52: 0 | AC52: =AD52+AE52+AF52+AG52 -> #N/A | AD52: =VLOOKUP(A52,'[2]Pay sheet-MARCH- 2022'!$C$34:$AF$122,12,0) -> #N/A | AE52: =VLOOKUP(A52,'[2]Pay sheet-MARCH- 2022'!$C$34:$AF$122,13,0) -> #N/A | AF52: =VLOOKUP(A52,'[2]Pay sheet-MARCH- 2022'!$C$34:$AF$122,14,0) -> #N/A | AY52: 73 | AZ52: 21

Sheet 04-22Eq Remu
A1: Form D
A2: (See rule 6)
A4: Register to be maintained by the employer under rule 6 of the Equal Remuneration Rules, 1976
D6: ='0422Master'!D10 -> 44652
A8: Name and address of Contractor : | F8: ='0422Master'!F5 -> Burgeon IT Services Pvt.Ltd.
A10: Name and address of establishment in/under which contract is carried on : | F10: ='0422Master'!AP5 -> Burgeon IT Services Pvt.Ltd.
F11: ='0422Master'!AP6 -> Siri Mansion LIGB 436 Dr.A S Rao Nagar,Hyderabad
A12: Name and address of Principal Employer : | F12: ='0422Master'!AP10 -> INFOSYS LTD.IL Pune SEZ Unit-II,Plot No. 24/3
F13: ='0422Master'!AP11 -> Rajiv gandhi Info tech park,Village Mann,Pune,Maharashtra 411057
A14: Total number of men workers employed | C14: =D40 -> 16
A16: Total number of women workers employed | C16: =C40 -> 4
C18: Components of remuneration
A19: Category of workers | B19: Brief Description of work | C19: No of women employed | D19: No. of men employed | E19: Rate or remuneration paid | F19: Basic wage & Dearness Allowance | G19: House Rent allowance | H19: Other allowances | I19: Cash value of concessional supply of essential commodities | J19: Name of the Client | K19: Primary Work Place/ Location
A20: ='0422Master'!F16 -> Network Security Admin | B20: IT SUPPORTIVE SERICE | C20: 0 | D20: 1 | E20: ='0422Master'!AM16 -> 88276.332 | F20: ='0422Master'!Z16 -> 48166.8 | G20: ='0422Master'!AD16 -> 19266.72 | H20: =E20-(F20+G20) -> 20842.812 | I20: 0 | K20: SEZ UNIT-II
A21: ='0422Master'!F17 -> Infrastructure Lead | B21: IT SUPPORTIVE SERICE | C21: 0 | D21: 1 | E21: ='0422Master'!AM17 -> 156275.8 | F21: ='0422Master'!Z17 -> 85984.2 | G21: ='0422Master'!AD17 -> 34393.68 | H21: =E21-(F21+G21) -> 35897.919 | I21: 0
A22: ='0422Master'!F18 -> ASSISTANT PROJECT MANAGER | B22: IT SUPPORTIVE SERICE | C22: 1 | D22: 0 | E22: ='0422Master'!AM18 -> 61275.703 | F22: ='0422Master'!Z18 -> 33150.6 | G22: ='0422Master'!AD18 -> 13260.24 | H22: =E22-(F22+G22) -> 14864.863 | I22: 0
A23: ='0422Master'!F19 -> Project Manager | B23: IT SUPPORTIVE SERICE | C23: 0 | D23: 1 | E23: ='0422Master'!AM19 -> 114275.78 | F23: ='0422Master'!Z19 -> 62626.2 | G23: ='0422Master'!AD19 -> 25050.48 | H23: =E23-(F23+G23) -> 26599.099 | I23: 0
A24: ='0422Master'!F20 -> Project Manager | B24: IT SUPPORTIVE SERICE | C24: 0 | D24: 1 | E24: ='0422Master'!AM20 -> 73275.863 | F24: ='0422Master'!Z20 -> 39824.4 | G24: ='0422Master'!AD20 -> 15929.76 | H24: =E24-(F24+G24) -> 17521.703 | I24: 0
A25: ='0422Master'!F21 -> Sr.Software Engineer | B25: IT SUPPORTIVE SERICE | C25: 0 | D25: 1 | E25: ='0422Master'!AM21 -> 88276.332 | F25: ='0422Master'!Z21 -> 48166.8 | G25: ='0422Master'!AD21 -> 19266.72 | H25: =E25-(F25+G25) -> 20842.812 | I25: 0
A26: ='0422Master'!F22 -> Project Manager | B26: IT SUPPORTIVE SERICE | C26: 0 | D26: 1 | E26: ='0422Master'!AM22 -> 60275.6 | F26: ='0422Master'!Z22 -> 32594.4 | G26: ='0422Master'!AD22 -> 13037.76 | H26: =E26-(F26+G26) -> 14643.44 | I26: 0
A27: ='0422Master'!F23 -> Network Engineer L2 | B27: IT SUPPORTIVE SERICE | C27: 0 | D27: 1 | E27: ='0422Master'!AM23 -> 68276.425 | F27: ='0422Master'!Z23 -> 37044 | G27: ='0422Master'!AD23 -> 14817.6 | H27: =E27-(F27+G27) -> 16414.825 | I27: 0
A28: ='0422Master'!F24 -> Project Manager | B28: IT SUPPORTIVE SERICE | C28: 0 | D28: 1 | E28: ='0422Master'!AM24 -> 87168.559 | F28: ='0422Master'!Z24 -> 47550.72 | G28: ='0422Master'!AD24 -> 19020.288 | H28: =E28-(F28+G28) -> 20597.551 | I28: 0
A29: ='0422Master'!F25 -> Project Manager | B29: IT SUPPORTIVE SERICE | C29: 1 | D29: 0 | E29: ='0422Master'!AM25 -> 78276.379 | F29: ='0422Master'!Z25 -> 42605.4 | G29: ='0422Master'!AD25 -> 17042.16 | H29: =E29-(F29+G29) -> 18628.819 | I29: 0
A30: ='0422Master'!F26 -> Linux Administrator | B30: IT SUPPORTIVE SERICE | C30: 0 | D30: 1 | E30: ='0422Master'!AM26 -> 103275.72 | F30: ='0422Master'!Z26 -> 56508.6 | G30: ='0422Master'!AD26 -> 22603.44 | H30: =E30-(F30+G30) -> 24163.683 | I30: 0
A31: ='0422Master'!F27 -> Project Manager | B31: IT SUPPORTIVE SERICE | C31: 0 | D31: 1 | E31: ='0422Master'!AM27 -> 75114.995 | F31: ='0422Master'!Z27 -> 40847.22 | G31: ='0422Master'!AD27 -> 16338.888 | H31: =E31-(F31+G31) -> 17928.887 | I31: 0
A32: ='0422Master'!F28 -> Network Admin | B32: IT SUPPORTIVE SERICE | C32: 0 | D32: 1 | E32: ='0422Master'!AM28 -> 58276.472 | F32: ='0422Master'!Z28 -> 31482.6 | G32: ='0422Master'!AD28 -> 12593.04 | H32: =E32-(F32+G32) -> 14200.832 | I32: 0
... A39: ='0422Master'!F35 -> Sr.Software Engineer | B39: IT SUPPORTIVE SERICE | C39: 0 | D39: 1 | E39: ='0422Master'!AM35 -> 88276.332 | F39: ='0422Master'!Z35 -> 48166.8 | G39: ='0422Master'!AD35 -> 19266.72 | H39: =E39-(F39+G39) -> 20842.812 | I39: 0
C40: =SUM(C20:C39) -> 4 | D40: =SUM(D20:D39) -> 16
E48: Signature of the Contractor with Seal

Sheet MH_Must Roll
A2: Form No. II
A3: [M. W. Rules under Maharashtra Contract Labour (Regulation and Abolition)1963 Rule 27 (I)]
A4: Muster Roll cum Wage Register for the month of APRIL 2022
A5: Name and Address of Contractor : BURGEON IT SERVICES PVT.LTD. SIRI MANSION LIG 436 DR.A S RAO NAGAR,HYDERABAD 500 060
G6: Working Hours | I6: Interval for Rest | K6: No. of Hours Worked
A7: Sl.No. | B7: Full Name of Employee | C7: Date of Birth | D7: Gender | E7: Date of Entry into Service | F7: Nature of Work & Designation | G7: From | H7: To | I7: From | J7: To | K7: 1 | L7: 2 | M7: 3 | N7: 4 | O7: 5 | P7: 6 | Q7: 7 | R7: 8 | S7: 9 | T7: 10 | U7: 11 | V7: 12 | W7: 13 | X7: 14 | Y7: 15 | Z7: 16 | AA7: 17 | AB7: 18 | AC7: 19 | AD7: 20 | AE7: 21 | AF7: 22 | AG7: 23 | AH7: 24 | AI7: 25 | AJ7: 26 | AK7: 27 | AL7: 28 | AM7: 29 | AN7: 30 | AO7: MONTH DAYS
A8: 1 | B8: ='0422Master'!B16 -> Shaikh Mohammed Sartaj | C8: ='0422Master'!C16 -> 31453 | D8: ='0422Master'!D16 -> MALE | E8: ='0422Master'!N16 -> 44470 | F8: ='0422Master'!F16 -> Network Security Admin | K8: P | L8: WO | M8: WO | N8: P | O8: P | P8: P | Q8: P | R8: EL | S8: WO | T8: WO | U8: P | V8: P | W8: P | X8: P | Y8: H | Z8: WO | AA8: WO | AB8: P | AC8: P | AD8: P | AE8: P | AF8: P | AG8: WO | AH8: WO | AI8: P | AJ8: P | AK8: P | AL8: P | AM8: P | AN8: WO | AO8: ='0422Master'!W16 -> 30
A9: 2 | B9: ='0422Master'!B17 -> Moin Ahemad Jahur Ahemad Kumarkiri | C9: ='0422Master'!C17 -> 31507 | D9: ='0422Master'!D17 -> MALE | E9: ='0422Master'!N17 -> 44491 | F9: ='0422Master'!F17 -> Infrastructure Lead | K9: P | L9: WO | M9: WO | N9: P | O9: P | P9: P | Q9: P | R9: P | S9: WO | T9: WO | U9: P | V9: P | W9: P | X9: P | Y9: H | Z9: WO | AA9: WO | AB9: P | AC9: P | AD9: P | AE9: P | AF9: P | AG9: WO | AH9: WO | AI9: P | AJ9: P | AK9: P | AL9: P | AM9: P | AN9: WO | AO9: ='0422Master'!W17 -> 30
A10: 3 | B10: ='0422Master'!B18 -> Savana Saritha Dora | C10: ='0422Master'!C18 -> 29965 | D10: ='0422Master'!D18 -> FEMALE | E10: ='0422Master'!N18 -> 44495 | F10: ='0422Master'!F18 -> ASSISTANT PROJECT MANAGER | K10: EL | L10: WO | M10: WO | N10: P | O10: P | P10: P | Q10: P | R10: P | S10: WO | T10: WO | U10: P | V10: P | W10: P | X10: P | Y10: H | Z10: WO | AA10: WO | AB10: P | AC10: P | AD10: P | AE10: P | AF10: P | AG10: WO | AH10: WO | AI10: P | AJ10: P | AK10: P | AL10: P | AM10: P | AN10: WO | AO10: ='0422Master'!W18 -> 30
A11: 4 | B11: ='0422Master'!B19 -> Mandar Shetty | C11: ='0422Master'!C19 -> 31205 | D11: ='0422Master'!D19 -> MALE | E11: ='0422Master'!N19 -> 44509 | F11: ='0422Master'!F19 -> Project Manager | K11: P | L11: WO | M11: WO | N11: P | O11: P | P11: P | Q11: P | R11: P | S11: WO | T11: WO | U11: P | V11: P | W11: P | X11: EL | Y11: H | Z11: WO | AA11: WO | AB11: P | AC11: P | AD11: P | AE11: P | AF11: P | AG11: WO | AH11: WO | AI11: P | AJ11: P | AK11: P | AL11: P | AM11: P | AN11: WO | AO11: ='0422Master'!W19 -> 30
A12: 5 | B12: ='0422Master'!B20 -> Vivek Dongre | C12: ='0422Master'!C20 -> 32931 | D12: ='0422Master'!D20 -> MALE | E12: ='0422Master'!N20 -> 44515 | F12: ='0422Master'!F20 -> Project Manager | K12: P | L12: WO | M12: WO | N12: P | O12: P | P12: P | Q12: P | R12: P | S12: WO | T12: WO | U12: P | V12: P | W12: P | X12: P | Y12: H | Z12: WO | AA12: WO | AB12: P | AC12: P | AD12: P | AE12: P | AF12: P | AG12: WO | AH12: WO | AI12: P | AJ12: P | AK12: P | AL12: P | AM12: P | AN12: WO | AO12: ='0422Master'!W20 -> 30
A13: 6 | B13: ='0422Master'!B21 -> Amit Chawadi | C13: ='0422Master'!C21 -> 31279 | D13: ='0422Master'!D21 -> MALE | E13: ='0422Master'!N21 -> 44522 | F13: ='0422Master'!F21 -> Sr.Software Engineer | K13: P | L13: WO | M13: WO | N13: P | O13: P | P13: P | Q13: P | R13: P | S13: WO | T13: WO | U13: P | V13: P | W13: P | X13: P | Y13: H | Z13: WO | AA13: WO | AB13: P | AC13: P | AD13: P | AE13: P | AF13: P | AG13: WO | AH13: WO | AI13: P | AJ13: P | AK13: P | AL13: P | AM13: P | AN13: WO | AO13: ='0422Master'!W21 -> 30
A14: 7 | B14: ='0422Master'!B22 -> Ashwini Nanaware | C14: ='0422Master'!C22 -> 33778 | D14: ='0422Master'!D22 -> MALE | E14: ='0422Master'!N22 -> 44536 | F14: ='0422Master'!F22 -> Project Manager | K14: P | L14: WO | M14: WO | N14: P | O14: P | P14: P | Q14: P | R14: P | S14: WO | T14: WO | U14: P | V14: P | W14: P | X14: P | Y14: H | Z14: WO | AA14: WO | AB14: P | AC14: P | AD14: P | AE14: P | AF14: P | AG14: WO | AH14: WO | AI14: P | AJ14: P | AK14: P | AL14: P | AM14: EL | AN14: WO | AO14: ='0422Master'!W22 -> 30
A15: 8 | B15: ='0422Master'!B23 -> Kaushal Sushil Sharma | C15: ='0422Master'!C23 -> 35033 | D15: ='0422Master'!D23 -> MALE | E15: ='0422Master'!N23 -> 44536 | F15: ='0422Master'!F23 -> Network Engineer L2 | K15: P | L15: WO | M15: WO | N15: P | O15: P | P15: P | Q15: P | R15: P | S15: WO | T15: WO | U15: P | V15: P | W15: P | X15: P | Y15: H | Z15: WO | AA15: WO | AB15: P | AC15: P | AD15: P | AE15: P | AF15: P | AG15: WO | AH15: WO | AI15: P | AJ15: P | AK15: P | AL15: P | AM15: P | AN15: WO | AO15: ='0422Master'!W23 -> 30
A16: 9 | B16: ='0422Master'!B24 -> Arvind Akhare | C16: ='0422Master'!C24 -> 32329 | D16: ='0422Master'!D24 -> MALE | E16: ='0422Master'!N24 -> 44537 | F16: ='0422Master'!F24 -> Project Manager | K16: P | L16: WO | M16: WO | N16: P | O16: P | P16: P | Q16: P | R16: P | S16: WO | T16: WO | U16: EL | V16: A | W16: A | X16: P | Y16: H | Z16: WO | AA16: WO | AB16: P | AC16: P | AD16: P | AE16: P | AF16: P | AG16: WO | AH16: WO | AI16: P | AJ16: P | AK16: P | AL16: P | AM16: P | AN16: WO | AO16: ='0422Master'!W24 -> 28
A17: 10 | B17: ='0422Master'!B25 -> Pallavi Rishikesh Naik | C17: ='0422Master'!C25 -> 34094 | D17: ='0422Master'!D25 -> Female | E17: ='0422Master'!N25 -> 44538 | F17: ='0422Master'!F25 -> Project Manager | K17: P | L17: WO | M17: WO | N17: P | O17: P | P17: P | Q17: P | R17: P | S17: WO | T17: WO | U17: P | V17: P | W17: P | X17: P | Y17: H | Z17: WO | AA17: WO | AB17: P | AC17: P | AD17: P | AE17: P | AF17: P | AG17: WO | AH17: WO | AI17: P | AJ17: P | AK17: P | AL17: P | AM17: P | AN17: WO | AO17: ='0422Master'!W25 -> 30
A18: 11 | B18: ='0422Master'!B26 -> Amit Kumar | C18: ='0422Master'!C26 -> 31700 | D18: ='0422Master'!D26 -> MALE | E18: ='0422Master'!N26 -> 44557 | F18: ='0422Master'!F26 -> Linux Administrator | K18: P | L18: WO | M18: WO | N18: P | O18: P | P18: P | Q18: P | R18: P | S18: WO | T18: WO | U18: EL | V18: P | W18: P | X18: P | Y18: H | Z18: WO | AA18: WO | AB18: P | AC18: P | AD18: P | AE18: P | AF18: P | AG18: WO | AH18: WO | AI18: P | AJ18: P | AK18: P | AL18: P | AM18: P | AN18: WO | AO18: ='0422Master'!W26 -> 30
A19: 12 | B19: ='0422Master'!B27 -> Pranav Thakare | C19: ='0422Master'!C27 -> 34393 | D19: ='0422Master'!D27 -> MALE | E19: ='0422Master'!N27 -> 44564 | F19: ='0422Master'!F27 -> Project Manager | K19: P | L19: WO | M19: WO | N19: P | O19: P | P19: P | Q19: P | R19: P | S19: WO | T19: WO | U19: P | V19: P | W19: P | X19: P | Y19: H | Z19: WO | AA19: WO | AB19: P | AC19: P | AD19: P | AE19: P | AF19: P | AG19: WO | AH19: WO | AI19: EL | AJ19: A | AK19: A | AL19: A | AM19: P | AN19: WO | AO19: ='0422Master'!W27 -> 27
... A27: 20 | B27: ='0422Master'!B35 -> susheelKumar Gandla | C27: ='0422Master'!C35 -> 30056 | D27: ='0422Master'!D35 -> MALE | E27: ='0422Master'!N35 -> 44652 | F27: ='0422Master'!F35 -> Sr.Software Engineer | K27: P | L27: WO | M27: WO | N27: P | O27: P | P27: P | Q27: P | R27: P | S27: WO | T27: WO | U27: P | V27: P | W27: P | X27: P | Y27: H | Z27: WO | AA27: WO | AB27: P | AC27: P | AD27: P | AE27: P | AF27: P | AG27: WO | AH27: WO | AI27: P | AJ27: P | AK27: P | AL27: P | AM27: P | AN27: WO | AO27: ='0422Master'!W35 -> 30
AO28: =SUM(AO8:AO27) -> 591
AG41: Signature of the Contractor with Seal

Sheet F M Lev Reg
A1: FORM M- LEAVE REGISTER
A3: (Vide Rule 78(1) (a) (i) of Maharastra Shops&Establishment Act /Maharastra.Rules 1988
A4: Name of the Employer / Establishment: | E4: Name of the Employee:
B5: ='0422Master'!F5 -> Burgeon IT Services Pvt.Ltd. | G5: ='0422Master'!B16 -> Shaikh Mohammed Sartaj
B6: ='0422Master'!F6 -> Siri Mansion LIGB 436 Dr.A S Rao Nagar,Hyderabad
A7: Description of the dapartment if applicable: | E7: Date of entry into service | G7: ='0422Master'!N16 -> 44470
C8: ='0422Master'!F488 -> 0
A11: S.No | B11: Accumalation of Leave | D11: Leave allowed | F11: Balance of Leave Carried Over | G11: Payment of Leave made on | I11: Refusal of Leave | L11: Payment of Leave on Discharge of an employee quitting employment if a admissible | O11: Signature or the Thumb impression of employee on Receipt of Leave Book in Form N | P11: Remarks
A13: 1 | F13: 6 | I13: 9 | L13: 9 | O13: Impression of
B14: Leave due on | C14: No of Days | D14: From | E14: To | G14: 1st month | H14: 2nd month | I14: Date of Application | J14: Date of Refusal | K14: Amount of Leave refused | L14: Date of Discharge | M14: Date of Amount Paid | N14: Signature or Left hand thumb impression of employee
A17: JAN'22 | B17: 1.5 | C17: 0 | D17: 0 | E17: 0 | F17: 4 | I17: NO | J17: NO | K17: NO
A18: FEB'22 | B18: 1.5 | C18: 1 | D18: 44596 | E18: 44596 | F18: =F17+B18-C18 -> 4.5 | I18: NO | J18: NO | K18: NO
A19: MAR'22 | B19: 1.5 | C19: 1 | D19: 44648 | E19: 44648 | F19: =F18+B19-C19 -> 5 | I19: NO | J19: NO | K19: NO
A20: APRIL'22 | B20: 1.5 | C20: 1 | D20: 44659 | E20: 44659 | F20: =F19+B20-C20 -> 5.5 | I20: NO | J20: NO | K20: NO | Q20: 1
G42: Signature of the Contractor with Seal
A80: FORM M- LEAVE REGISTER
A82: (Vide Rule 78(1) (a) (i) of Maharastra Shops&Establishment Act /Maharastra.Rules 1988
A83: Name of the Employer / Establishment: | E83: Name of the Employee:
B84: ='0422Master'!F5 -> Burgeon IT Services Pvt.Ltd. | G84: ='0422Master'!B17 -> Moin Ahemad Jahur Ahemad Kumarkiri
B85: ='0422Master'!F6 -> Siri Mansion LIGB 436 Dr.A S Rao Nagar,Hyderabad
A86: Description of the dapartment if applicable: | E86: Date of entry into service | G86: ='0422Master'!N17 -> 44491
C87: ='0422Master'!F8 -> IT SUPPORTIVE SERVICES& PUNE SEZ UNIT-II
A90: S.No | B90: Accumalation of Leave | D90: Leave allowed | F90: Balance of Leave Carried Over | G90: Payment of Leave made on | I90: Refusal of Leave | L90: Payment of Leave on Discharge of an employee quitting employment if a admissible | O90: Signature or the Thumb impression of employee on Receipt of Leave Book in Form N | P90: Remarks
A92: 1 | F92: 6 | I92: 9 | L92: 9 | O92: Impression of
B93: Leave due on | C93: No of Days | D93: From | E93: To | G93: 1st month | H93: 2nd month | I93: Date of Application | J93: Date of Refusal | K93: Amount of Leave refused | L93: Date of Discharge | M93: Date of Amount Paid | N93: Signature or Left hand thumb impression of employee
A96: JAN'22 | B96: 1.5 | C96: 1 | D96: 44592 | E96: 44592 | F96: 2.5 | I96: NO | J96: NO | K96: NO
A97: FEB'22 | B97: 1.5 | C97: 1 | D97: 44603 | E97: 44603 | F97: =F96+B97-C97 -> 3 | I97: NO | J97: NO | K97: NO
A98: MAR'22 | B98: 1.5 | C98: 0 | D98: 0 | E98: 0 | F98: =F97+B98-C98 -> 4.5 | I98: NO | J98: NO | K98: NO
A99: APRIL'22 | B99: 1.5 | C99: 0 | D99: 0 | E99: 0 | F99: =F98+B99-C99 -> 6 | I99: NO | J99: NO | K99: NO | Q99: 3
G121: Signature of the Contractor with Seal
A148: FORM M- LEAVE REGISTER
A150: (Vide Rule 78(1) (a) (i) of Maharastra Shops&Establishment Act /Maharastra.Rules 1988
A151: Name of the Employer / Establishment: | E151: Name of the Employee:
B152: ='0422Master'!F5 -> Burgeon IT Services Pvt.Ltd. | G152: ='0422Master'!B18 -> Savana Saritha Dora
B153: ='0422Master'!F6 -> Siri Mansion LIGB 436 Dr.A S Rao Nagar,Hyderabad
A154: Description of the dapartment if applicable: | E154: Date of entry into service | G154: ='0422Master'!N18 -> 44495
C155: ='0422Master'!F8 -> IT SUPPORTIVE SERVICES& PUNE SEZ UNIT-II
A158: S.No | B158: Accumalation of Leave | D158: Leave allowed | F158: Balance of Leave Carried Over | G158: Payment of Leave made on | I158: Refusal of Leave | L158: Payment of Leave on Discharge of an employee quitting employment if a admissible | O158: Signature or the Thumb impression of employee on Receipt of Leave Book in Form N | P158: Remarks
A160: 1 | F160: 6 | I160: 9 | L160: 9 | O160: Impression of
B161: Leave due on | C161: No of Days | D161: From | E161: To | G161: 1st month | H161: 2nd month | I161: Date of Application | J161: Date of Refusal | K161: Amount of Leave refused | L161: Date of Discharge | M161: Date of Amount Paid | N161: Signature or Left hand thumb impression of employee
A164: JAN'22 | B164: 1.5 | C164: 1 | D164: 44578 | E164: 44609 | F164: 2.5 | I164: NO | J164: NO | K164: NO
A165: FEB'22 | B165: 1.5 | C165: 0 | D165: 0 | E165: 0 | F165: =F164+B165-C165 -> 4 | I165: NO | J165: NO | K165: NO
A166: MAR'22 | B166: 1.5 | C166: 1 | D166: 44624 | E166: 44624 | F166: =F165+B166-C166 -> 4.5 | I166: NO | J166: NO | K166: NO
A167: APRIL'22 | B167: 1.5 | C167: 1 | D167: 44652 | E167: 44652 | F167: =F166+B167-C167 -> 5 | I167: NO | J167: NO | K167: NO | Q167: 3
G189: Signature of the Contractor with Seal
A216: FORM M- LEAVE REGISTER
A218: (Vide Rule 78(1) (a) (i) of Maharastra Shops&Establishment Act /Maharastra.Rules 1988
A219: Name of the Employer / Establishment: | E219: Name of the Employee: | H219: ='0422Master'!B19 -> Mandar Shetty
B220: Burgeon IT Services Pvt.Ltd.
B221: Siri Mansion LIGB 436 Dr.A S Rao Nagar,Hyderabad
A222: Description of the dapartment if applicable: | E222: Date of entry into service | G222: 44509
C223: IT SUPPORTIVE SERVICES
A226: S.No | B226: Accumalation of Leave | D226: Leave allowed | F226: Balance of Leave Carried Over | G226: Payment of Leave made on | I226: Refusal of Leave | L226: Payment of Leave on Discharge of an employee quitting employment if a admissible | O226: Signature or the Thumb impression of employee on Receipt of Leave Book in Form N | P226: Remarks
A228: 1 | F228: 6 | I228: 9 | L228: 9 | O228: Impression of
B229: Leave due on | C229: No of Days | D229: From | E229: To | G229: 1st month | H229: 2nd month | I229: Date of Application | J229: Date of Refusal | K229: Amount of Leave refused | L229: Date of Discharge | M229: Date of Amount Paid | N229: Signature or Left hand thumb impression of employee
A232: JAN'22 | B232: 1.5 | C232: 1 | D232: 44564 | E232: 44564 | F232: 3.5 | I232: NO | J232: NO | K232: NO
A233: FEB'22 | B233: 1.5 | C233: 1 | D233: 44606 | E233: 44606 | F233: =F232+B233-C233 -> 4 | I233: NO | J233: NO | K233: NO
A234: MAR'22 | B234: 1.5 | C234: 0 | D234: 0 | E234: 0 | F234: =F233+B234-C234 -> 5.5 | I234: NO | J234: NO | K234: NO
A235: APRIL'22 | B235: 1.5 | C235: 1 | D235: 44665 | E235: 44665 | F235: =F234+B235-C235 -> 6 | I235: NO | J235: NO | K235: NO | Q235: 4
G257: Signature of the Contractor with Seal
A284: FORM M- LEAVE REGISTER
A286: (Vide Rule 78(1) (a) (i) of Maharastra Shops&Establishment Act /Maharastra.Rules 1988
A287: Name of the Employer / Establishment: | E287: Name of the Employee:
B288: Burgeon IT Services Pvt.Ltd. | G288: ='0422Master'!B20 -> Vivek Dongre
B289: Siri Mansion LIGB 436 Dr.A S Rao Nagar,Hyderabad
A290: Description of the dapartment if applicable: | E290: Date of entry into service | G290: 44515
C291: IT SUPPORTIVE SERVICES
A294: S.No | B294: Accumalation of Leave | D294: Leave allowed | F294: Balance of Leave Carried Over | G294: Payment of Leave made on | I294: Refusal of Leave | L294: Payment of Leave on Discharge of an employee quitting employment if a admissible | O294: Signature or the Thumb impression of employee on Receipt of Leave Book in Form N | P294: Remarks
A296: 1 | F296: 6 | I296: 9 | L296: 9 | O296: Impression of
B297: Leave due on | C297: No of Days | D297: From | E297: To | G297: 1st month | H297: 2nd month | I297: Date of Application | J297: Date of Refusal | K297: Amount of Leave refused | L297: Date of Discharge | M297: Date of Amount Paid | N297: Signature or Left hand thumb impression of employee
A300: JAN'22 | B300: 1.5 | C300: 1 | D300: 44578 | E300: 44578 | F300: 2 | I300: NO | J300: NO | K300: NO
A301: FEB'22 | B301: 1.5 | C301: 1 | D301: 44620 | E301: 44620 | F301: =F300+B301-C301 -> 2.5 | I301: NO | J301: NO | K301: NO
A302: MAR'22 | B302: 1.5 | C302: 1 | D302: 44631 | E302: 44631 | F302: =F301+B302-C302 -> 3 | I302: NO | J302: NO | K302: NO
A303: APRIL'22 | B303: 1.5 | C303: 0 | D303: 0 | E303: 0 | F303: =F302+B303-C303 -> 4.5 | I303: NO | J303: NO | K303: NO | Q303: 5
G325: Signature of the Contractor with Seal
A352: FORM M- LEAVE REGISTER
A354: (Vide Rule 78(1) (a) (i) of Maharastra Shops&Establishment Act /Maharastra.Rules 1988
A355: Name of the Employer / Establishment: | E355: Name of the Employee:
B356: Burgeon IT Services Pvt.Ltd. | G356: ='0422Master'!B21 -> Amit Chawadi
B357: Siri Mansion LIGB 436 Dr.A S Rao Nagar,Hyderabad
A358: Description of the dapartment if applicable: | E358: Date of entry into service | G358: 44522
C359: IT SUPPORTIVE SERVICES
A362: S.No | B362: Accumalation of Leave | D362: Leave allowed | F362: Balance of Leave Carried Over | G362: Payment of Leave made on | I362: Refusal of Leave | L362: Payment of Leave on Discharge of an employee quitting employment if a admissible | O362: Signature or the Thumb impression of employee on Receipt of Leave Book in Form N | P362: Remarks
A364: 1 | F364: 6 | I364: 9 | L364: 9 | O364: Impression of
B365: Leave due on | C365: No of Days | D365: From | E365: To | G365: 1st month | H365: 2nd month | I365: Date of Application | J365: Date of Refusal | K365: Amount of Leave refused | L365: Date of Discharge | M365: Date of Amount Paid | N365: Signature or Left hand thumb impression of employee
A368: JAN'22 | B368: 1.5 | C368: 0 | D368: 0 | E368: 0 | F368: 3 | I368: NO | J368: NO | K368: NO
A369: FEB'22 | B369: 1.5 | C369: 0 | D369: 0 | E369: 0 | F369: =F368+B369-C369 -> 4.5 | I369: NO | J369: NO | K369: NO
A370: MAR'22 | B370: 1.5 | C370: 0 | D370: 0 | E370: 0 | F370: =F369+B370-C370 -> 6 | I370: NO | J370: NO | K370: NO
A371: APRIL'22 | B371: 1.5 | C371: 0 | D371: 0 | E371: 0 | F371: =F370+B371-C371 -> 7.5 | I371: NO | J371: NO | K371: NO | Q371: 6
G393: Signature of the Contractor with Seal
A420: FORM M- LEAVE REGISTER
A422: (Vide Rule 78(1) (a) (i) of Maharastra Shops&Establishment Act /Maharastra.Rules 1988
A423: Name of the Employer / Establishment: | E423: Name of the Employee:
B424: Burgeon IT Services Pvt.Ltd. | G424: ='0422Master'!B22 -> Ashwini Nanaware
B425: Siri Mansion LIGB 436 Dr.A S Rao Nagar,Hyderabad
A426: Description of the dapartment if applicable: | E426: Date of entry into service | G426: ='0422Master'!N22 -> 44536
C427: IT SUPPORTIVE SERVICES
A430: S.No | B430: Accumalation of Leave | D430: Leave allowed | F430: Balance of Leave Carried Over | G430: Payment of Leave made on | I430: Refusal of Leave | L430: Payment of Leave on Discharge of an employee quitting employment if a admissible | O430: Signature or the Thumb impression of employee on Receipt of Leave Book in Form N | P430: Remarks
A432: 1 | F432: 6 | I432: 9 | L432: 9 | O432: Impression of
B433: Leave due on | C433: No of Days | D433: From | E433: To | G433: 1st month | H433: 2nd month | I433: Date of Application | J433: Date of Refusal | K433: Amount of Leave refused | L433: Date of Discharge | M433: Date of Amount Paid | N433: Signature or Left hand thumb impression of employee
...

Sheet MH_Reg of Wgs
A2: Form No. II
A3: [M. W. Rules under Maharashtra Contract Labour (Regulation and Abolition)1963 Rule 27 (I)]
A4: Muster Roll cum Wages Register for the month of APRIL 2022
A5: Name and Address of Contractor : BURGEON IT SERVICES PVT.LTD. SIRI MANSION LIG 436 DR.A S RAO NAGAR,HYDERABAD 500 060
O6: Deductions | V6: Leave with Wages
A7: Sl.No. | B7: Deputy ID | C7: Employee Code | D7: Name of the Workmen | E7: Minimum Rate of Wages Payable Basic | F7: Actual Rate of Wages Payable HRA | G7: Conveyance | H7: Bonus | I7: Special Allowances | J7: Medical Allowances | K7: Total Production in Case of Piece Rate Other Allow | L7: Normal Earnings | M7: Overtime Earnings | N7: Gross Wages Payable | O7: Income Tax | P7: Other Deduction(Med) | Q7: Proff / Income Tax | R7: PF | S7: ESIC | T7: Total Deduction | U7: Net Wages Paid | V7: Previous Balance | W7: Further Enjoyed | X7: Refused | Y7: Accumulated | Z7: Date Payment of Wages | AA7: Signature or the Thumb Impression of the Employee | AB7: Account Number
A8: 1 | C8: ='0422Master'!A16 -> BITS-652 | D8: ='0422Master'!B16 -> Shaikh Mohammed Sartaj | E8: ='0422Master'!Z16 -> 48166.8 | F8: ='0422Master'!AD16 -> 19266.72 | G8: ='0422Master'!AE16 -> 2083 | H8: ='0422Master'!AI16 -> 1554.609 | I8: ='0422Master'!AG16 -> 8791.48 | J8: ='0422Master'!AF16 -> 2083 | L8: ='0422Master'!AH16 -> 80391 | M8: 1 | N8: ='0422Master'!AM16 -> 88276.332 | O8: ='0422Master'!AQ16 -> 0 | P8: ='0422Master'!AR16 -> 254 | Q8: ='0422Master'!AP16 -> 200 | R8: ='0422Master'!AO16 -> 1800 | S8: ='0422Master'!AN16 -> 0 | T8: ='0422Master'!AS16 -> 2254 | U8: ='0422Master'!AT16 -> 86022.332 | V8: 5 | W8: 1 | X8: 0 | Y8: 5.5 | Z8: ='0422Master'!AU16 -> 05.05.2022 | AA8: ='0422Master'!AV16 -> HDFC BANK | AB8: ='0422Master'!AW16 -> 50100405646907
A9: 2 | C9: ='0422Master'!A17 -> BITS-660 | D9: ='0422Master'!B17 -> Moin Ahemad Jahur Ahemad Kumarkiri | E9: ='0422Master'!Z17 -> 85984.2 | F9: ='0422Master'!AD17 -> 34393.68 | G9: ='0422Master'!AE17 -> 2083 | H9: ='0422Master'!AI17 -> 1554.609 | I9: ='0422Master'!AG17 -> 18876.12 | J9: ='0422Master'!AF17 -> 2083 | L9: ='0422Master'!AH17 -> 143420 | M9: 2 | N9: ='0422Master'!AM17 -> 156275.8 | O9: ='0422Master'!AQ17 -> 0 | P9: ='0422Master'!AR17 -> 254 | Q9: ='0422Master'!AP17 -> 200 | R9: ='0422Master'!AO17 -> 1800 | S9: ='0422Master'!AN17 -> 0 | T9: ='0422Master'!AS17 -> 2254 | U9: ='0422Master'!AT17 -> 154021.8 | V9: 4.5 | W9: 0 | X9: 0 | Y9: 6 | Z9: ='0422Master'!AU17 -> 05.05.2022 | AA9: ='0422Master'!AV17 -> HDFC BANK | AB9: ='0422Master'!AW17 -> 50100103229547
A10: 3 | C10: ='0422Master'!A18 -> BITS-664 | D10: ='0422Master'!B18 -> Savana Saritha Dora | E10: ='0422Master'!Z18 -> 33150.6 | F10: ='0422Master'!AD18 -> 13260.24 | G10: ='0422Master'!AE18 -> 2083 | H10: ='0422Master'!AI18 -> 1554.609 | I10: ='0422Master'!AG18 -> 4787.16 | J10: ='0422Master'!AF18 -> 2083 | L10: ='0422Master'!AH18 -> 55364 | M10: 3 | N10: ='0422Master'!AM18 -> 61275.703 | O10: ='0422Master'!AQ18 -> 0 | P10: ='0422Master'!AR18 -> 286 | Q10: ='0422Master'!AP18 -> 200 | R10: ='0422Master'!AO18 -> 1800 | S10: ='0422Master'!AN18 -> 0 | T10: ='0422Master'!AS18 -> 2286 | U10: ='0422Master'!AT18 -> 58989.703 | V10: 4.5 | W10: 1 | X10: 0 | Y10: 5 | Z10: ='0422Master'!AU18 -> 05.05.2022 | AA10: ='0422Master'!AV18 -> SBI | AB10: ='0422Master'!AW18 -> 20101763786
A11: 4 | C11: ='0422Master'!A19 -> BITS-668 | D11: ='0422Master'!B19 -> Mandar Shetty | E11: ='0422Master'!Z19 -> 62626.2 | F11: ='0422Master'!AD19 -> 25050.48 | G11: ='0422Master'!AE19 -> 2083 | H11: ='0422Master'!AI19 -> 1554.609 | I11: ='0422Master'!AG19 -> 12647.32 | J11: ='0422Master'!AF19 -> 2083 | L11: ='0422Master'!AH19 -> 104490 | M11: 4 | N11: ='0422Master'!AM19 -> 114275.78 | O11: ='0422Master'!AQ19 -> 0 | P11: ='0422Master'!AR19 -> 283 | Q11: ='0422Master'!AP19 -> 200 | R11: ='0422Master'!AO19 -> 1800 | S11: ='0422Master'!AN19 -> 0 | T11: ='0422Master'!AS19 -> 2283 | U11: ='0422Master'!AT19 -> 111992.78 | V11: 5.5 | W11: 1 | X11: 0 | Y11: 6 | Z11: ='0422Master'!AU19 -> 05.05.2022 | AA11: ='0422Master'!AV19 -> Axis Bank | AB11: ='0422Master'!AW19 -> 910010033970009
A12: 5 | C12: ='0422Master'!A20 -> BITS-672 | D12: ='0422Master'!B20 -> Vivek Dongre | E12: ='0422Master'!Z20 -> 39824.4 | F12: ='0422Master'!AD20 -> 15929.76 | G12: ='0422Master'!AE20 -> 2083 | H12: ='0422Master'!AI20 -> 1554.609 | I12: ='0422Master'!AG20 -> 6566.84 | J12: ='0422Master'!AF20 -> 2083 | L12: ='0422Master'!AH20 -> 66487 | M12: 5 | N12: ='0422Master'!AM20 -> 73275.863 | O12: ='0422Master'!AQ20 -> 0 | P12: ='0422Master'!AR20 -> 252 | Q12: ='0422Master'!AP20 -> 200 | R12: ='0422Master'!AO20 -> 1800 | S12: ='0422Master'!AN20 -> 0 | T12: ='0422Master'!AS20 -> 2252 | U12: ='0422Master'!AT20 -> 71023.863 | V12: 3 | W12: 0 | X12: 0 | Y12: 4.5 | Z12: ='0422Master'!AU20 -> 05.05.2022 | AA12: ='0422Master'!AV20 -> CITI Bank | AB12: ='0422Master'!AW20 -> 5297131705
A13: 6 | C13: ='0422Master'!A21 -> BITS-674 | D13: ='0422Master'!B21 -> Amit Chawadi | E13: ='0422Master'!Z21 -> 48166.8 | F13: ='0422Master'!AD21 -> 19266.72 | G13: ='0422Master'!AE21 -> 2083 | H13: ='0422Master'!AI21 -> 1554.609 | I13: ='0422Master'!AG21 -> 8791.48 | J13: ='0422Master'!AF21 -> 2083 | L13: ='0422Master'!AH21 -> 80391 | M13: 6 | N13: ='0422Master'!AM21 -> 88276.332 | O13: ='0422Master'!AQ21 -> 0 | P13: ='0422Master'!AR21 -> 283 | Q13: ='0422Master'!AP21 -> 200 | R13: ='0422Master'!AO21 -> 1800 | S13: ='0422Master'!AN21 -> 0 | T13: ='0422Master'!AS21 -> 2283 | U13: ='0422Master'!AT21 -> 85993.332 | V13: 6 | W13: 0 | X13: 0 | Y13: 7.5 | Z13: ='0422Master'!AU21 -> 05.05.2022 | AA13: ='0422Master'!AV21 -> ICICI Bank | AB13: ='0422Master'!AW21 -> 007401540582
A14: 7 | C14: ='0422Master'!A22 -> BITS-677 | D14: ='0422Master'!B22 -> Ashwini Nanaware | E14: ='0422Master'!Z22 -> 32594.4 | F14: ='0422Master'!AD22 -> 13037.76 | G14: ='0422Master'!AE22 -> 2083 | H14: ='0422Master'!AI22 -> 1554.609 | I14: ='0422Master'!AG22 -> 4638.84 | J14: ='0422Master'!AF22 -> 2083 | L14: ='0422Master'!AH22 -> 54437 | M14: 7 | N14: ='0422Master'!AM22 -> 60275.6 | O14: ='0422Master'!AQ22 -> 0 | P14: ='0422Master'!AR22 -> 283 | Q14: ='0422Master'!AP22 -> 200 | R14: ='0422Master'!AO22 -> 1800 | S14: ='0422Master'!AN22 -> 0 | T14: ='0422Master'!AS22 -> 2283 | U14: ='0422Master'!AT22 -> 57992.6 | V14: 5 | W14: 1 | X14: 0 | Y14: 5.5 | Z14: ='0422Master'!AU22 -> 05.05.2022 | AA14: ='0422Master'!AV22 -> HDFC Bank | AB14: ='0422Master'!AW22 -> 50100191546051
A15: 8 | C15: ='0422Master'!A23 -> BITS-678 | D15: ='0422Master'!B23 -> Kaushal Sushil Sharma | E15: ='0422Master'!Z23 -> 37044 | F15: ='0422Master'!AD23 -> 14817.6 | G15: ='0422Master'!AE23 -> 2083 | H15: ='0422Master'!AI23 -> 1554.609 | I15: ='0422Master'!AG23 -> 5825.4 | J15: ='0422Master'!AF23 -> 2083 | L15: ='0422Master'!AH23 -> 61853 | M15: 8 | N15: ='0422Master'!AM23 -> 68276.425 | O15: ='0422Master'!AQ23 -> 0 | P15: ='0422Master'!AR23 -> 283 | Q15: ='0422Master'!AP23 -> 200 | R15: ='0422Master'!AO23 -> 1800 | S15: ='0422Master'!AN23 -> 0 | T15: ='0422Master'!AS23 -> 2283 | U15: ='0422Master'!AT23 -> 65993.425 | V15: 4 | W15: 0 | X15: 0 | Y15: 5.5 | Z15: ='0422Master'!AU23 -> 05.05.2022 | AA15: ='0422Master'!AV23 -> ICICI Bank | AB15: ='0422Master'!AW23 -> 001901524778
A16: 9 | C16: ='0422Master'!A24 -> BITS-680 | D16: ='0422Master'!B24 -> Arvind Akhare | E16: ='0422Master'!Z24 -> 47550.72 | F16: ='0422Master'!AD24 -> 19020.288 | G16: ='0422Master'!AE24 -> 1944 | H16: ='0422Master'!AI24 -> 1554.609 | I16: ='0422Master'!AG24 -> 8905.192 | J16: ='0422Master'!AF24 -> 1944 | L16: ='0422Master'!AH24 -> 79364.2 | M16: 9 | N16: ='0422Master'!AM24 -> 87168.559 | O16: ='0422Master'!AQ24 -> 0 | P16: ='0422Master'!AR24 -> 283 | Q16: ='0422Master'!AP24 -> 200 | R16: ='0422Master'!AO24 -> 1800 | S16: ='0422Master'!AN24 -> 0 | T16: ='0422Master'!AS24 -> 2283 | U16: ='0422Master'!AT24 -> 84885.559 | V16: 6 | W16: 1 | X16: 0 | Y16: 6.5 | Z16: ='0422Master'!AU24 -> 05.05.2022 | AA16: ='0422Master'!AV24 -> HDFC Bank | AB16: ='0422Master'!AW24 -> 50100150364960
A17: 10 | C17: ='0422Master'!A25 -> BITS-681 | D17: ='0422Master'!B25 -> Pallavi Rishikesh Naik | E17: ='0422Master'!Z25 -> 42605.4 | F17: ='0422Master'!AD25 -> 17042.16 | G17: ='0422Master'!AE25 -> 2083 | H17: ='0422Master'!AI25 -> 1554.609 | I17: ='0422Master'!AG25 -> 7308.44 | J17: ='0422Master'!AF25 -> 2083 | L17: ='0422Master'!AH25 -> 71122 | M17: 10 | N17: ='0422Master'!AM25 -> 78276.379 | O17: ='0422Master'!AQ25 -> 0 | P17: ='0422Master'!AR25 -> 283 | Q17: ='0422Master'!AP25 -> 200 | R17: ='0422Master'!AO25 -> 1800 | S17: ='0422Master'!AN25 -> 0 | T17: ='0422Master'!AS25 -> 2283 | U17: ='0422Master'!AT25 -> 75993.379 | V17: 4 | W17: 0 | X17: 0 | Y17: 5.5 | Z17: ='0422Master'!AU25 -> 05.05.2022 | AA17: ='0422Master'!AV25 -> CITI Bank | AB17: ='0422Master'!AW25 -> 5696586708
A18: 11 | C18: ='0422Master'!A26 -> BITS-686 | D18: ='0422Master'!B26 -> Amit Kumar | E18: ='0422Master'!Z26 -> 56508.6 | F18: ='0422Master'!AD26 -> 22603.44 | G18: ='0422Master'!AE26 -> 2083 | H18: ='0422Master'!AI26 -> 1554.609 | I18: ='0422Master'!AG26 -> 11015.96 | J18: ='0422Master'!AF26 -> 2083 | L18: ='0422Master'!AH26 -> 94294 | M18: 11 | N18: ='0422Master'!AM26 -> 103275.72 | O18: ='0422Master'!AQ26 -> 0 | P18: ='0422Master'!AR26 -> 283 | Q18: ='0422Master'!AP26 -> 200 | R18: ='0422Master'!AO26 -> 1800 | S18: ='0422Master'!AN26 -> 0 | T18: ='0422Master'!AS26 -> 2283 | U18: ='0422Master'!AT26 -> 100992.72 | V18: 3.5 | W18: 1 | X18: 0 | Y18: 4 | Z18: ='0422Master'!AU26 -> 05.05.2022 | AA18: ='0422Master'!AV26 -> HDFC Bank | AB18: ='0422Master'!AW26 -> 05121140023169
A19: 12 | C19: ='0422Master'!A27 -> BITS-688 | D19: ='0422Master'!B27 -> Pranav Thakare | E19: ='0422Master'!Z27 -> 40847.22 | F19: ='0422Master'!AD27 -> 16338.888 | G19: ='0422Master'!AE27 -> 1875 | H19: ='0422Master'!AI27 -> 1554.609 | I19: ='0422Master'!AG27 -> 7255.592 | J19: ='0422Master'!AF27 -> 1875 | L19: ='0422Master'!AH27 -> 68191.7 | M19: 12 | N19: ='0422Master'!AM27 -> 75114.995 | O19: ='0422Master'!AQ27 -> 0 | P19: ='0422Master'!AR27 -> 283 | Q19: ='0422Master'!AP27 -> 200 | R19: ='0422Master'!AO27 -> 1800 | S19: ='0422Master'!AN27 -> 0 | T19: ='0422Master'!AS27 -> 2283 | U19: ='0422Master'!AT27 -> 72831.995 | V19: 2.5 | W19: 1 | X19: 0 | Y19: 3 | Z19: ='0422Master'!AU27 -> 05.05.2022 | AA19: ='0422Master'!AV27 -> ICICI BANK | AB19: ='0422Master'!AW27 -> 056601532765
... A23: 16 | C23: ='0422Master'!A31 -> BITS-709 | D23: ='0422Master'!B31 -> Uma Mahesh P | E23: ='0422Master'!Z31 -> 22368.86 | F23: ='0422Master'!AD31 -> 8947.544 | G23: ='0422Master'!AE31 -> 2014 | H23: ='0422Master'!AI31 -> 1554.609 | I23: ='0422Master'!AG31 -> 2050.0293 | J23: ='0422Master'!AF31 -> 2014 | L23: ='0422Master'!AH31 -> 37394.433 | M23: 16 | N23: ='0422Master'!AM31 -> 41889.056 | O23: ='0422Master'!AQ31 -> 0 | P23: ='0422Master'!AR31 -> 283 | Q23: ='0422Master'!AP31 -> 200 | R23: ='0422Master'!AO31 -> 1800 | S23: ='0422Master'!AN31 -> 0 | T23: ='0422Master'!AS31 -> 2283 | U23: ='0422Master'!AT31 -> 39606.056 | V23: 3 | W23: 1 | X23: 0 | Y23: 3.5 | Z23: ='0422Master'!AU31 -> 05.05.2022 | AA23: ='0422Master'!AV31 -> HDFC BANK | AB23: ='0422Master'!AW31 -> A/C NO 50100444213458
A24: 17 | C24: ='0422Master'!A32 -> BITS-713 | D24: ='0422Master'!B32 -> NAGA SAI TEJA NUTHI | E24: ='0422Master'!Z32 -> 23329.08 | F24: ='0422Master'!AD32 -> 9331.632 | G24: ='0422Master'!AE32 -> 1875 | H24: ='0422Master'!AI32 -> 1554.609 | I24: ='0422Master'!AG32 -> 2584.088 | J24: ='0422Master'!AF32 -> 1875 | L24: ='0422Master'!AH32 -> 38994.8 | M24: 17 | N24: ='0422Master'!AM32 -> 43615.628 | O24: ='0422Master'!AQ32 -> 0 | P24: ='0422Master'!AR32 -> 283 | Q24: ='0422Master'!AP32 -> 200 | R24: ='0422Master'!AO32 -> 1800 | S24: ='0422Master'!AN32 -> 0 | T24: ='0422Master'!AS32 -> 2283 | U24: ='0422Master'!AT32 -> 41332.628 | V24: 2 | W24: 1 | X24: 0 | Y24: 2.5 | Z24: ='0422Master'!AU33 -> 05.05.2022 | AA24: ='0422Master'!AV32 -> SBI | AB24: ='0422Master'!AW32 -> A/C NO 20297714176
A25: 18 | C25: ='0422Master'!A33 -> BITS-714 | D25: ='0422Master'!B33 -> Mani Krishna Nandineedi | E25: ='0422Master'!Z33 -> 23140.2 | F25: ='0422Master'!AD33 -> 9256.08 | G25: ='0422Master'!AE33 -> 2083 | H25: ='0422Master'!AI33 -> 1554.609 | I25: ='0422Master'!AG33 -> 2117.72 | J25: ='0422Master'!AF33 -> 2083 | L25: ='0422Master'!AH33 -> 38680 | M25: 18 | N25: ='0422Master'!AM33 -> 43276.003 | O25: ='0422Master'!AQ33 -> 0 | P25: ='0422Master'!AR33 -> 283 | Q25: ='0422Master'!AP33 -> 200 | R25: ='0422Master'!AO33 -> 1800 | S25: ='0422Master'!AN33 -> 0 | T25: ='0422Master'!AS33 -> 2283 | U25: ='0422Master'!AT33 -> 40993.003 | V25: 3 | W25: 0 | X25: 0 | Y25: 4.5 | Z25: ='0422Master'!AU34 -> 05.05.2022 | AA25: ='0422Master'!AV33 -> HDFC BANK | AB25: ='0422Master'!AW33 -> A/C NO 50100360114888
A26: 19 | C26: ='0422Master'!A34 -> BITS-715 | D26: ='0422Master'!B34 -> Sushma P | E26: ='0422Master'!Z34 -> 23140.2 | F26: ='0422Master'!AD34 -> 9256.08 | G26: ='0422Master'!AE34 -> 2083 | H26: ='0422Master'!AI34 -> 1554.609 | I26: ='0422Master'!AG34 -> 2117.72 | J26: ='0422Master'!AF34 -> 2083 | L26: ='0422Master'!AH34 -> 38680 | M26: 19 | N26: ='0422Master'!AM34 -> 43276.003 | O26: ='0422Master'!AQ34 -> 0 | P26: ='0422Master'!AR34 -> 283 | Q26: ='0422Master'!AP34 -> 200 | R26: ='0422Master'!AO34 -> 1800 | S26: ='0422Master'!AN34 -> 0 | T26: ='0422Master'!AS34 -> 2283 | U26: ='0422Master'!AT34 -> 40993.003 | V26: 3 | W26: 0 | X26: 0 | Y26: 4.5 | Z26: ='0422Master'!AU35 -> 05.05.2022 | AA26: ='0422Master'!AV34 -> SBI | AB26: ='0422Master'!AW34 -> A/C NO 62111073370
A27: 20 | C27: ='0422Master'!A35 -> BITS-741 | D27: ='0422Master'!B35 -> susheelKumar Gandla | E27: ='0422Master'!Z35 -> 48166.8 | F27: ='0422Master'!AD35 -> 19266.72 | G27: ='0422Master'!AE35 -> 2083 | H27: ='0422Master'!AI35 -> 1554.609 | I27: ='0422Master'!AG35 -> 8791.48 | J27: ='0422Master'!AF35 -> 2083 | L27: ='0422Master'!AH35 -> 80391 | M27: 20 | N27: ='0422Master'!AM35 -> 88276.332 | O27: ='0422Master'!AQ35 -> 0 | P27: ='0422Master'!AR35 -> 0 | Q27: ='0422Master'!AP35 -> 200 | R27: ='0422Master'!AO35 -> 0 | S27: ='0422Master'!AN35 -> 0 | T27: ='0422Master'!AS35 -> 200 | U27: ='0422Master'!AT35 -> 88076.332 | V27: 0 | W27: 0 | X27: 0 | Y27: 1.5 | Z27: ='0422Master'!AU36 -> 0 | AA27: ='0422Master'!AV35 -> ICICI BANK | AB27: ='0422Master'!AW35 -> A/C NO 007601548378
E28: =SUM(E8:E27) -> 792977.48 | F28: =SUM(F8:F27) -> 317190.99 | G28: =SUM(G8:G27) -> 41036 | H28: =SUM(H8:H27) -> 31092.18 | I28: =SUM(I8:I27) -> 131648.66 | J28: =SUM(J8:J27) -> 41036 | L28: =SUM(L8:L27) -> 1323889.1 | M28: =SUM(M8:M27) -> 210 | N28: =SUM(N8:N27) -> 1459205 | O28: =SUM(O8:O27) -> 0 | P28: =SUM(P8:P27) -> 5291 | Q28: =SUM(Q8:Q27) -> 4000 | R28: =SUM(R8:R27) -> 34200 | S28: =SUM(S8:S27) -> 0 | ... U28: =SUM(U8:U27) -> 1415714
X38: Signature of the Contractor with Seal

Sheet Empt Cards
B1: FORM XIV
B2: EMPLOYMENT CUM WAGE CARD
B3: (Vide Rule 76 of Contract Labour (R&A) Central & Karnataka Rules, 1974)
B4: Name and Address of the Contractor | H4: Name and Address of the Establishment in/under which Contract is carried on:
B7: ='0422Master'!F5 -> Burgeon IT Services Pvt.Ltd. | H7: ='0422Master'!AP5 -> Burgeon IT Services Pvt.Ltd.
B9: ='0422Master'!F6 -> Siri Mansion LIGB 436 Dr.A S Rao Nagar,Hyderabad | H9: ='0422Master'!AP6 -> Siri Mansion LIGB 436 Dr.A S Rao Nagar,Hyderabad
B12: Nature of work and location of work: | H12: Name and address of Principal Employer:
H15: ='0422Master'!AP10 -> INFOSYS LTD.IL Pune SEZ Unit-II,Plot No. 24/3
B16: ='0422Master'!F8 -> IT SUPPORTIVE SERVICES& PUNE SEZ UNIT-II
H17: ='0422Master'!AP11 -> Rajiv gandhi Info tech park,Village Mann,Pune,Maharashtra 411057
B19: 1. Name of the Workman and address | H19: ='0422Master'!B16 -> Shaikh Mohammed Sartaj | M19: 2
H20: ='0422Master'!G16 -> plot no 110, Sadatnagar, Near Railway station, Aurangabad, 431001
B21: 2. S.No. in the Register of Workmen Employed | H21: ='0422Master'!AY16 -> 53
B22: 3. Nature of Employment /Designation | H22: ='0422Master'!F16 -> Network Security Admin
B23: 4. Date of entry into service | H23: ='0422Master'!N16 -> 44470
B24: 5. ESI No. | J24: ='0422Master'!T16 -> N/A
B25: 6.PF No. | J25: ='0422Master'!S16 -> 100468499225
B26: 7. Wage rate (With particulars of unit in case of piece - work) | H26: ='0422Master'!Y16 -> 80278
B27: 8. Wage period | H27: ='0422Master'!D10 -> 44652
B28: 9. Tenure of Employment | H28: AS PER CONTRACT
B29: 10.No. of days worked in a month | J29: ='0422Master'!W16 -> 30
B30: 11. No. of units worked in case of piece rate workers | J30: N/A
B31: 12. Rate of daily wages / piece rate | J31: 0
B32: 13. Amount of overtime wages | J32: 0
B33: 14. Gross wages payable | J33: ='0422Master'!AM16 -> 88276.332 | L33: MED
B34: 15. Deductions, if any, | D34: PF | E34: ='0422Master'!AO16 -> 1800 | F34: ESI | G34: ='0422Master'!AN16 -> 0 | H34: PT | I34: ='0422Master'!AP16 -> 200 | J34: TDS | K34: ='0422Master'!AQ16 -> 0 | L34: ='0422Master'!AR16 -> 254
B35: 16. Net amount of wages paid | J35: =J33-(E34+G34+I34+K34+L34) -> 86022.332
B36: Signature of the Representative
B37: of Contractor
B55: FORM XIV
B56: EMPLOYMENT CUM WAGE CARD
B57: (Vide Rule 76 of Contract Labour (R&A) Central & Karnataka Rules, 1974)
B58: Name and Address of the Contractor | H58: Name and Address of the Establishment in/under which Contract is carried on:
B61: ='0422Master'!F5 -> Burgeon IT Services Pvt.Ltd. | H61: ='0422Master'!AP5 -> Burgeon IT Services Pvt.Ltd.
B63: ='0422Master'!F6 -> Siri Mansion LIGB 436 Dr.A S Rao Nagar,Hyderabad | H63: ='0422Master'!AP6 -> Siri Mansion LIGB 436 Dr.A S Rao Nagar,Hyderabad
B66: Nature of work and location of work: | H66: Name and address of Principal Employer:
H69: ='0422Master'!AP10 -> INFOSYS LTD.IL Pune SEZ Unit-II,Plot No. 24/3
B70: ='0422Master'!F8 -> IT SUPPORTIVE SERVICES& PUNE SEZ UNIT-II
H71: ='0422Master'!AP11 -> Rajiv gandhi Info tech park,Village Mann,Pune,Maharashtra 411057
B73: 1. Name of the Workman and address | H73: ='0422Master'!B17 -> Moin Ahemad Jahur Ahemad Kumarkiri
H74: ='0422Master'!J17 -> River Residency, Chikhali , Pune
B75: 2. S.No. in the Register of Workmen Employed | H75: ='0422Master'!AY17 -> 54
B76: 3. Nature of Employment /Designation | H76: ='0422Master'!F17 -> Infrastructure Lead
B77: 4. Date of entry into service | H77: ='0422Master'!N17 -> 44491
B78: 5. ESI No. | J78: ='0422Master'!T17 -> N/A
B79: 6.PF No. | J79: ='0422Master'!S17 -> 100505159752
B80: 7. Wage rate (With particulars of unit in case of piece - work) | H80: ='0422Master'!Y17 -> 143307
B81: 8. Wage period | H81: ='0422Master'!D10 -> 44652
B82: 9. Tenure of Employment | H82: AS PER CONTRACT
B83: 10.No. of days worked in a month | J83: ='0422Master'!W17 -> 30
B84: 11. No. of units worked in case of piece rate workers | J84: N/A | M84: 3
B85: 12. Rate of daily wages / piece rate | J85: 0
B86: 13. Amount of overtime wages | J86: 0
B87: 14. Gross wages payable | J87: ='0422Master'!AM17 -> 156275.8 | L87: MED
B88: 15. Deductions, if any, | D88: PF | E88: ='0422Master'!AO17 -> 1800 | F88: ESI | G88: ='0422Master'!AN17 -> 0 | H88: PT | I88: ='0422Master'!AP17 -> 200 | J88: TDS | K88: ='0422Master'!AQ17 -> 0 | L88: ='0422Master'!AR17 -> 254
B89: 16. Net amount of wages paid | J89: =J87-(E88+G88+I88+K88+L88) -> 154021.8
B90: Signature of the Representative
B91: of Contractor
B109: FORM XIV
B110: EMPLOYMENT CUM WAGE CARD
B111: (Vide Rule 76 of Contract Labour (R&A) Central & Karnataka Rules, 1974)
B112: Name and Address of the Contractor | H112: Name and Address of the Establishment in/under which Contract is carried on:
B115: ='0422Master'!F5 -> Burgeon IT Services Pvt.Ltd. | H115: ='0422Master'!AP5 -> Burgeon IT Services Pvt.Ltd.
B117: ='0422Master'!F6 -> Siri Mansion LIGB 436 Dr.A S Rao Nagar,Hyderabad | H117: ='0422Master'!AP6 -> Siri Mansion LIGB 436 Dr.A S Rao Nagar,Hyderabad
B120: Nature of work and location of work: | H120: Name and address of Principal Employer:
H123: ='0422Master'!AP10 -> INFOSYS LTD.IL Pune SEZ Unit-II,Plot No. 24/3
B124: ='0422Master'!F8 -> IT SUPPORTIVE SERVICES& PUNE SEZ UNIT-II
H125: ='0422Master'!AP11 -> Rajiv gandhi Info tech park,Village Mann,Pune,Maharashtra 411057
B127: 1. Name of the Workman and address | H127: ='0422Master'!B18 -> Savana Saritha Dora
H128: ='0422Master'!G18 -> Shafa Nagar Ausa, Dist- Latur, Maharashtra
B129: 2. S.No. in the Register of Workmen Employed | H129: ='0422Master'!AY18 -> 55
B130: 3. Nature of Employment /Designation | H130: ='0422Master'!F18 -> ASSISTANT PROJECT MANAGER
B131: 4. Date of entry into service | H131: ='0422Master'!N18 -> 44495
B132: 5. ESI No. | J132: ='0422Master'!T18 -> N/A
B133: 6.PF No. | J133: ='0422Master'!S18 -> 101749326014
B134: 7. Wage rate (With particulars of unit in case of piece - work) | H134: ='0422Master'!Y18 -> 55251
B135: 8. Wage period | H135: ='0422Master'!D10 -> 44652
B136: 9. Tenure of Employment | H136: AS PER CONTRACT
B137: 10.No. of days worked in a month | J137: ='0422Master'!W18 -> 30
B138: 11. No. of units worked in case of piece rate workers | J138: N/A
B139: 12. Rate of daily wages / piece rate | J139: 0
B140: 13. Amount of overtime wages | J140: 0
B141: 14. Gross wages payable | J141: ='0422Master'!AM18 -> 61275.703 | L141: MED
B142: 15. Deductions, if any, | D142: PF | E142: ='0422Master'!AO18 -> 1800 | F142: ESI | G142: ='0422Master'!AN18 -> 0 | H142: PT | I142: ='0422Master'!AP18 -> 200 | J142: TDS | K142: ='0422Master'!AQ18 -> 0 | L142: ='0422Master'!AR18 -> 286
B143: 16. Net amount of wages paid | J143: =J141-(E142+G142+I142+K142+L142) -> 58989.703 | M143: 4
B144: Signature of the Representative
B145: of Contractor
B166: FORM XIV
B167: EMPLOYMENT CUM WAGE CARD
B168: (Vide Rule 76 of Contract Labour (R&A) Central & Karnataka Rules, 1974)
B169: Name and Address of the Contractor | H169: Name and Address of the Establishment in/under which Contract is carried on:
B172: Burgeon IT Services Pvt.Ltd. | H172: Burgeon IT Services Pvt.Ltd.
B174: Siri Mansion LIGB 436 Dr.A S Rao Nagar,Hyderabad | H174: Siri Mansion LIGB 436 Dr.A S Rao Nagar,Hyderabad
B177: Nature of work and location of work: | H177: Name and address of Principal Employer:
H180: INFOSYS LTD.IL Pune SEZ Unit-II,Plot No. 24/3
B181: IT SUPPORTIVE SERVICES
H182: Rajiv gandhi Info tech park,Village Mann,Pune,Maharashtra 411057
B184: 1. Name of the Workman and address | H184: ='0422Master'!B19 -> Mandar Shetty
H185: ='0422Master'!G19 -> B-301,Hemarold Isle,Wagholi-Lohegaon,Behind Wagheshwar Temple,Wagholi,Pune 412207
B186: 2. S.No. in the Register of Workmen Employed | H186: 57
...

Sheet wage sllips
A1: Form XV - WAGE SLIP | K1: Form XV - WAGE SLIP
A2: [Vide rule 78 (1) (b) of the Contract Labour (Regulation and Abolition) and Maharashtra Rules, 1971] | K2: [Vide rule 78 (1) (b) of the Contract Labour (Regulation and Abolition) and Maharashtra Rules, 1971]
A4: Name and address of Contractor | D4: ='0422Master'!F5 -> Burgeon IT Services Pvt.Ltd. | K4: Name and address of Contractor | N4: =D4 -> Burgeon IT Services Pvt.Ltd.
B5: ='0422Master'!F6 -> Siri Mansion LIGB 436 Dr.A S Rao Nagar,Hyderabad | L5: =B5 -> Siri Mansion LIGB 436 Dr.A S Rao Nagar,Hyderabad
B6: ='0422Master'!F7 -> 0 | L6: =B6 -> 0
A7: Name and Father's / Husband's name of the workman | K7: Name and Father's / Husband's name of the workman
E8: ='0422Master'!B16 -> Shaikh Mohammed Sartaj | H8: ='0422Master'!E16 -> Shaikh Mohammad Rafique | O8: =E8 -> Shaikh Mohammed Sartaj | R8: =H8 -> Shaikh Mohammad Rafique
A10: Nature and location of work | E10: ='0422Master'!F8 -> IT SUPPORTIVE SERVICES& PUNE SEZ UNIT-II | K10: Nature and location of work | O10: =E10 -> IT SUPPORTIVE SERVICES& PUNE SEZ UNIT-II
A12: For the Week / Fortnight / Month ending | E12: ='0422Master'!D10 -> 44652 | K12: For the Week / Fortnight / Month ending | O12: =E12 -> 44652
A14: 1 | B14: No. of days worked | E14: ='0422Master'!W16 -> 30 | K14: 1 | L14: No. of days worked | O14: =E14 -> 30
A16: 2 | B16: No. of units worked in case of piece rate workers : | K16: 2 | L16: No. of units worked in case of piece rate workers :
E17: N/A | O17: N/A
A19: 3 | B19: Rate of daily wages / piece rate | E19: N/A | K19: 3 | L19: Rate of daily wages / piece rate | O19: =E19 -> N/A
A21: 4 | B21: Amount of overtime wages | E21: Nil | K21: 4 | L21: Amount of overtime wages | O21: Nil
A23: 5 | B23: Gross wages payble | E23: ='0422Master'!AM16 -> 88276.332 | K23: 5 | L23: Gross wages payble | O23: =E23 -> 88276.332
D24: EPF | E24: ESI | F24: PT | G24: TDS | H24: MEDICAL | I24: TOTAL | N24: EPF | O24: ESI | P24: PT | Q24: TDS | R24: MEDICAL | S24: TOTAL
A25: 6 | B25: Deductions, if any | D25: ='0422Master'!AO16 -> 1800 | E25: ='0422Master'!AN16 -> 0 | F25: ='0422Master'!AP16 -> 200 | G25: ='0422Master'!AQ16 -> 0 | H25: ='0422Master'!AR16 -> 254 | I25: =D25+E25+F25+G25+H25 -> 2254 | K25: 6 | L25: Deductions, if any | N25: =D25 -> 1800 | O25: =E25 -> 0 | P25: =F25 -> 200 | Q25: =G25 -> 0 | R25: =H25 -> 254 | S25: =I25 -> 2254
A27: 7 | B27: Net amount of wages paid | E27: =E23-I25 -> 86022.332 | K27: 7 | L27: Net amount of wages paid | O27: =E27 -> 86022.332 | T27: 2
F31: Initial of the Contractor or his representative | P31: Initial of the Contractor or his representative
A48: Form XV - WAGE SLIP | K48: Form XV - WAGE SLIP
A49: [Vide rule 78 (1) (b) of the Contract Labour (Regulation and Abolition) and Maharashtra Rules, 1971] | K49: [Vide rule 78 (1) (b) of the Contract Labour (Regulation and Abolition) and Maharashtra Rules, 1971]
A51: Name and address of Contractor | D51: Burgeon IT Services Pvt.Ltd. | K51: Name and address of Contractor | N51: =D51 -> Burgeon IT Services Pvt.Ltd.
B52: Siri Mansion LIGB 436 Dr.A S Rao Nagar,Hyderabad | L52: =B52 -> Siri Mansion LIGB 436 Dr.A S Rao Nagar,Hyderabad
B53: ='0422Master'!F351 -> 0 | L53: =B53 -> 0
A54: Name and Father's / Husband's name of the workman | K54: Name and Father's / Husband's name of the workman
E55: ='0422Master'!B17 -> Moin Ahemad Jahur Ahemad Kumarkiri | H55: ='0422Master'!E17 -> Jahur Ahemad Kumarkiri | O55: =E55 -> Moin Ahemad Jahur Ahemad Kumarkiri | R55: =H55 -> Jahur Ahemad Kumarkiri
A57: Nature and location of work | E57: IT SUPPORTIVE SERVICES | K57: Nature and location of work | O57: =E57 -> IT SUPPORTIVE SERVICES
A59: For the Week / Fortnight / Month ending | E59: ='0422Master'!D10 -> 44652 | K59: For the Week / Fortnight / Month ending | O59: =E59 -> 44652
A61: 1 | B61: No. of days worked | E61: ='0422Master'!W17 -> 30 | K61: 1 | L61: No. of days worked | O61: =E61 -> 30
A63: 2 | B63: No. of units worked in case of piece rate workers : | K63: 2 | L63: No. of units worked in case of piece rate workers :
E64: N/A | O64: N/A
A66: 3 | B66: Rate of daily wages / piece rate | E66: N/A | K66: 3 | L66: Rate of daily wages / piece rate | O66: =E66 -> N/A
A68: 4 | B68: Amount of overtime wages | E68: Nil | K68: 4 | L68: Amount of overtime wages | O68: Nil
A70: 5 | B70: Gross wages payble | E70: ='0422Master'!AM17 -> 156275.8 | K70: 5 | L70: Gross wages payble | O70: =E70 -> 156275.8
D71: EPF | E71: ESI | F71: PT | G71: TDS | H71: MEDICAL | I71: TOTAL | N71: EPF | O71: ESI | P71: PT | Q71: TDS | R71: MEDICAL | S71: TOTAL
A72: 6 | B72: Deductions, if any | D72: ='0422Master'!AO17 -> 1800 | E72: ='0422Master'!AN17 -> 0 | F72: ='0422Master'!AP17 -> 200 | G72: ='0422Master'!AQ17 -> 0 | H72: ='0422Master'!AR17 -> 254 | I72: =D72+E72+F72+G72+H72 -> 2254 | K72: 6 | L72: Deductions, if any | N72: =D72 -> 1800 | O72: =E72 -> 0 | P72: =F72 -> 200 | Q72: =G72 -> 0 | R72: =H72 -> 254 | S72: =I72 -> 2254 | T72: 3
A74: 7 | B74: Net amount of wages paid | E74: =E70-I72 -> 154021.8 | K74: 7 | L74: Net amount of wages paid | O74: =E74 -> 154021.8
F78: Initial of the Contractor or his representative | P78: Initial of the Contractor or his representative
A95: Form XV - WAGE SLIP | K95: Form XV - WAGE SLIP
A96: [Vide rule 78 (1) (b) of the Contract Labour (Regulation and Abolition) and Maharashtra Rules, 1971] | K96: [Vide rule 78 (1) (b) of the Contract Labour (Regulation and Abolition) and Maharashtra Rules, 1971]
A98: Name and address of Contractor | D98: ='0422Master'!F5 -> Burgeon IT Services Pvt.Ltd. | K98: Name and address of Contractor | N98: =D98 -> Burgeon IT Services Pvt.Ltd.
B99: ='0422Master'!F6 -> Siri Mansion LIGB 436 Dr.A S Rao Nagar,Hyderabad | L99: =B99 -> Siri Mansion LIGB 436 Dr.A S Rao Nagar,Hyderabad
B100: ='0422Master'!F395 -> 0 | L100: =B100 -> 0
A101: Name and Father's / Husband's name of the workman | K101: Name and Father's / Husband's name of the workman
E102: ='0422Master'!B18 -> Savana Saritha Dora | H102: ='0422Master'!E18 -> Laxman gupta | O102: =E102 -> Savana Saritha Dora | R102: =H102 -> Laxman gupta
A104: Nature and location of work | E104: ='0422Master'!F8 -> IT SUPPORTIVE SERVICES& PUNE SEZ UNIT-II | K104: Nature and location of work | O104: =E104 -> IT SUPPORTIVE SERVICES& PUNE SEZ UNIT-II
A106: For the Week / Fortnight / Month ending | E106: ='0422Master'!D10 -> 44652 | K106: For the Week / Fortnight / Month ending | O106: =E106 -> 44652
A108: 1 | B108: No. of days worked | E108: ='0422Master'!W18 -> 30 | K108: 1 | L108: No. of days worked | O108: =E108 -> 30
A110: 2 | B110: No. of units worked in case of piece rate workers : | K110: 2 | L110: No. of units worked in case of piece rate workers :
E111: N/A | O111: N/A
A113: 3 | B113: Rate of daily wages / piece rate | E113: N/A | K113: 3 | L113: Rate of daily wages / piece rate | O113: =E113 -> N/A
A115: 4 | B115: Amount of overtime wages | E115: Nil | K115: 4 | L115: Amount of overtime wages | O115: Nil
A117: 5 | B117: Gross wages payble | E117: ='0422Master'!AM18 -> 61275.703 | K117: 5 | L117: Gross wages payble | O117: =E117 -> 61275.703
D118: EPF | E118: ESI | F118: PT | G118: TDS | H118: MEDICAL | I118: TOTAL | N118: EPF | O118: ESI | P118: PT | Q118: TDS | R118: MEDICAL | S118: TOTAL
A119: 6 | B119: Deductions, if any | D119: ='0422Master'!AO18 -> 1800 | E119: ='0422Master'!AN18 -> 0 | F119: ='0422Master'!AP18 -> 200 | G119: ='0422Master'!AQ18 -> 0 | H119: ='0422Master'!AR18 -> 286 | I119: =D119+E119+F119+G119+H119 -> 2286 | K119: 6 | L119: Deductions, if any | N119: =D119 -> 1800 | O119: =E119 -> 0 | P119: =F119 -> 200 | Q119: =G119 -> 0 | R119: =H119 -> 286 | S119: =I119 -> 2286
A121: 7 | B121: Net amount of wages paid | E121: =E117-I119 -> 58989.703 | K121: 7 | L121: Net amount of wages paid | O121: =E121 -> 58989.703 | T121: 4
F125: Initial of the Contractor or his representative | P125: Initial of the Contractor or his representative
A143: Form XV - WAGE SLIP | K143: Form XV - WAGE SLIP
A144: [Vide rule 78 (1) (b) of the Contract Labour (Regulation and Abolition) and Maharashtra Rules, 1971] | K144: [Vide rule 78 (1) (b) of the Contract Labour (Regulation and Abolition) and Maharashtra Rules, 1971]
A146: Name and address of Contractor | D146: Burgeon IT Services Pvt.Ltd. | K146: Name and address of Contractor | N146: =D146 -> Burgeon IT Services Pvt.Ltd.
B147: Siri Mansion LIGB 436 Dr.A S Rao Nagar,Hyderabad | L147: =B147 -> Siri Mansion LIGB 436 Dr.A S Rao Nagar,Hyderabad
B148: ='0422Master'!F484 -> 0 | L148: =B148 -> 0
A149: Name and Father's / Husband's name of the workman | K149: Name and Father's / Husband's name of the workman
E150: ='0422Master'!B19 -> Mandar Shetty | H150: ='0422Master'!E19 -> Vijay Shetty | O150: =E150 -> Mandar Shetty | R150: =H150 -> Vijay Shetty
A152: Nature and location of work | E152: IT SUPPORTIVE SERVICES | K152: Nature and location of work | O152: =E152 -> IT SUPPORTIVE SERVICES
A154: For the Week / Fortnight / Month ending | E154: ='0422Master'!D10 -> 44652 | K154: For the Week / Fortnight / Month ending | O154: =E154 -> 44652
A156: 1 | B156: No. of days worked | E156: ='0422Master'!W19 -> 30 | K156: 1 | L156: No. of days worked | O156: =E156 -> 30
A158: 2 | B158: No. of units worked in case of piece rate workers : | K158: 2 | L158: No. of units worked in case of piece rate workers :
E159: N/A | O159: N/A
A161: 3 | B161: Rate of daily wages / piece rate | E161: N/A | K161: 3 | L161: Rate of daily wages / piece rate | O161: =E161 -> N/A
A163: 4 | B163: Amount of overtime wages | E163: Nil | K163: 4 | L163: Amount of overtime wages | O163: Nil
A165: 5 | B165: Gross wages payble | E165: ='0422Master'!AM19 -> 114275.78 | K165: 5 | L165: Gross wages payble | O165: =E165 -> 114275.78
D166: EPF | E166: ESI | F166: PT | G166: TDS | H166: MEDICAL | I166: TOTAL | N166: EPF | O166: ESI | P166: PT | Q166: TDS | R166: MEDICAL | S166: TOTAL
A167: 6 | B167: Deductions, if any | D167: ='0422Master'!AO19 -> 1800 | E167: ='0422Master'!AN495 -> 0 | F167: ='0422Master'!AP19 -> 200 | G167: ='0422Master'!AQ19 -> 0 | H167: ='0422Master'!AR19 -> 283 | I167: ='0422Master'!AS495 -> 0 | K167: 6 | L167: Deductions, if any | N167: =D167 -> 1800 | O167: =E167 -> 0 | P167: =F167 -> 200 | Q167: =G167 -> 0 | R167: =H167 -> 283 | S167: =I167 -> 0
A169: 7 | B169: Net amount of wages paid | E169: =E165-D167-F167-G167-H167 -> 111992.78 | K169: 7 | L169: Net amount of wages paid | O169: =E169 -> 111992.78 | T169: 5
F173: Initial of the Contractor or his representative | P173: Initial of the Contractor or his representative
A188: Form XV - WAGE SLIP | K188: Form XV - WAGE SLIP
A189: [Vide rule 78 (1) (b) of the Contract Labour (Regulation and Abolition) and Maharashtra Rules, 1971] | K189: [Vide rule 78 (1) (b) of the Contract Labour (Regulation and Abolition) and Maharashtra Rules, 1971]
A191: Name and address of Contractor | D191: Burgeon IT Services Pvt.Ltd. | K191: Name and address of Contractor | N191: =D191 -> Burgeon IT Services Pvt.Ltd.
B192: Siri Mansion LIGB 436 Dr.A S Rao Nagar,Hyderabad | L192: =B192 -> Siri Mansion LIGB 436 Dr.A S Rao Nagar,Hyderabad
B193: ='0422Master'!F529 -> 0 | L193: =B193 -> 0
A194: Name and Father's / Husband's name of the workman | K194: Name and Father's / Husband's name of the workman
E195: ='0422Master'!B20 -> Vivek Dongre | H195: ='0422Master'!E20 -> Purushottam Dongre | O195: =E195 -> Vivek Dongre | R195: =H195 -> Purushottam Dongre
A197: Nature and location of work | E197: IT SUPPORTIVE SERVICES | K197: Nature and location of work | O197: =E197 -> IT SUPPORTIVE SERVICES
A199: For the Week / Fortnight / Month ending | E199: ='0422Master'!D10 -> 44652 | K199: For the Week / Fortnight / Month ending | O199: =E199 -> 44652
A201: 1 | B201: No. of days worked | E201: ='0422Master'!W20 -> 30 | K201: 1 | L201: No. of days worked | O201: =E201 -> 30
A203: 2 | B203: No. of units worked in case of piece rate workers : | K203: 2 | L203: No. of units worked in case of piece rate workers :
E204: N/A | O204: N/A
A206: 3 | B206: Rate of daily wages / piece rate | E206: N/A | K206: 3 | L206: Rate of daily wages / piece rate | O206: =E206 -> N/A
A208: 4 | B208: Amount of overtime wages | E208: Nil | K208: 4 | L208: Amount of overtime wages | O208: Nil
A210: 5 | B210: Gross wages payble | F210: ='0422Master'!AM20 -> 73275.863 | K210: 5 | L210: Gross wages payble | O210: =F210 -> 73275.863
D211: EPF | E211: ESI | F211: PT | G211: TDS | H211: MEDICAL | I211: TOTAL | N211: EPF | O211: ESI | P211: PT | Q211: TDS | R211: MEDICAL | S211: TOTAL
A212: 6 | B212: Deductions, if any | D212: ='0422Master'!AO20 -> 1800 | E212: ='0422Master'!AN540 -> 0 | F212: ='0422Master'!AP20 -> 200 | G212: ='0422Master'!AQ20 -> 0 | H212: ='0422Master'!AR20 -> 252 | I212: ='0422Master'!AS540 -> 0 | K212: 6 | L212: Deductions, if any | N212: =D212 -> 1800 | O212: =E212 -> 0 | P212: =F212 -> 200 | Q212: =G212 -> 0 | R212: =H212 -> 252 | S212: =I212 -> 0
T213: 6
A214: 7 | B214: Net amount of wages paid | F214: =F210-D212-F212-G212-H212 -> 71023.863 | K214: 7 | L214: Net amount of wages paid | O214: =F214 -> 71023.863
F218: Initial of the Contractor or his representative | P218: Initial of the Contractor or his representative
A233: Form XV - WAGE SLIP | K233: Form XV - WAGE SLIP
A234: [Vide rule 78 (1) (b) of the Contract Labour (Regulation and Abolition) and Maharashtra Rules, 1971] | K234: [Vide rule 78 (1) (b) of the Contract Labour (Regulation and Abolition) and Maharashtra Rules, 1971]
A236: Name and address of Contractor | D236: Burgeon IT Services Pvt.Ltd. | K236: Name and address of Contractor | N236: =D236 -> Burgeon IT Services Pvt.Ltd.
B237: Siri Mansion LIGB 436 Dr.A S Rao Nagar,Hyderabad | L237: =B237 -> Siri Mansion LIGB 436 Dr.A S Rao Nagar,Hyderabad
...

Sheet 04-22Bonus
A1: BONUS REGISTER
A3: FORM "c" ( See rule 4 [c] )
K4: Wage Period | L4: ='0422Master'!D10 -> 44652
A5: Name of the Establishment : _____________________________ | D5: ='0422Master'!F5 -> Burgeon IT Services Pvt.Ltd. | K5: Financial year _____ | M5: 2022-23
A6: ='0422Master'!F6 -> Siri Mansion LIGB 436 Dr.A S Rao Nagar,Hyderabad
A7: Sr. No | B7: Name of the Employee | C7: Father's Name / Husband's Name | D7: Whether he has completed 15 yrs of age at the beginning of the accounting year | E7: Designation | F7: No. of days worked in the year | G7: Total Salary or wages in the Month | H7: Amt. of bonus payable under section 10 or section 11 as the case may be Ex gratia | I7: DEDUCTIONS | L7: Total Sum Deducted (Col. 9,10 and 11) | M7: Net Amount payable (Col. 8 minus Col. 12) | N7: Amount Actually paid | O7: Date on which paid | P7: Signature / Thumb impression of the employee
I8: Puja Bonus or other customary bonus paid during the accounting year | J8: Interim Bonus or bonus paid in advance | K8: Deduction on account of financial loss if any caused by misconduct of the employee | Q8: Account Number
A9: 1 | B9: 2 | C9: 3 | D9: 4 | E9: 5 | F9: 6 | H9: 8 | I9: 9 | J9: 10 | K9: 11 | L9: 12 | M9: 13 | N9: 14 | O9: 15 | P9: 16
A10: 1 | B10: ='0422Master'!B16 -> Shaikh Mohammed Sartaj | C10: ='0422Master'!E16 -> Shaikh Mohammad Rafique | D10: YES | E10: ='0422Master'!F16 -> Network Security Admin | F10: ='0422Master'!W16 -> 30 | G10: ='0422Master'!AM16 -> 88276.332 | H10: ='0422Master'!AI16 -> 1554.609 | I10: N/A | J10: N/A | K10: N/A | L10: N/A | M10: =H10 -> 1554.609 | N10: =H10 -> 1554.609 | O10: ='0422Master'!AU16 -> 05.05.2022 | P10: ='0422Master'!AV16 -> HDFC BANK | Q10: ='0422Master'!AW16 -> 50100405646907
A11: 2 | B11: ='0422Master'!B17 -> Moin Ahemad Jahur Ahemad Kumarkiri | C11: ='0422Master'!E17 -> Jahur Ahemad Kumarkiri | D11: YES | E11: ='0422Master'!F17 -> Infrastructure Lead | F11: ='0422Master'!W17 -> 30 | G11: ='0422Master'!AM17 -> 156275.8 | H11: ='0422Master'!AI17 -> 1554.609 | I11: N/A | J11: N/A | K11: N/A | L11: N/A | M11: =H11 -> 1554.609 | N11: =H11 -> 1554.609 | O11: ='0422Master'!AU17 -> 05.05.2022 | P11: ='0422Master'!AV17 -> HDFC BANK | Q11: ='0422Master'!AW17 -> 50100103229547
A12: 3 | B12: ='0422Master'!B18 -> Savana Saritha Dora | C12: ='0422Master'!E18 -> Laxman gupta | D12: YES | E12: ='0422Master'!F18 -> ASSISTANT PROJECT MANAGER | F12: ='0422Master'!W18 -> 30 | G12: ='0422Master'!AM18 -> 61275.703 | H12: ='0422Master'!AI18 -> 1554.609 | I12: N/A | J12: N/A | K12: N/A | L12: N/A | M12: =H12 -> 1554.609 | N12: =H12 -> 1554.609 | O12: ='0422Master'!AU18 -> 05.05.2022 | P12: ='0422Master'!AV18 -> SBI | Q12: ='0422Master'!AW18 -> 20101763786
A13: 4 | B13: ='0422Master'!B19 -> Mandar Shetty | C13: ='0422Master'!E19 -> Vijay Shetty | D13: YES | E13: ='0422Master'!F19 -> Project Manager | F13: ='0422Master'!W19 -> 30 | G13: ='0422Master'!AM19 -> 114275.78 | H13: ='0422Master'!AI19 -> 1554.609 | I13: N/A | J13: N/A | K13: N/A | L13: N/A | M13: =H13 -> 1554.609 | N13: =H13 -> 1554.609 | O13: ='0422Master'!AU19 -> 05.05.2022 | P13: ='0422Master'!AV19 -> Axis Bank | Q13: ='0422Master'!AW19 -> 910010033970009
A14: 5 | B14: ='0422Master'!B20 -> Vivek Dongre | C14: ='0422Master'!E20 -> Purushottam Dongre | D14: YES | E14: ='0422Master'!F20 -> Project Manager | F14: ='0422Master'!W20 -> 30 | G14: ='0422Master'!AM20 -> 73275.863 | H14: ='0422Master'!AI20 -> 1554.609 | I14: N/A | J14: N/A | K14: N/A | L14: N/A | M14: =H14 -> 1554.609 | N14: =H14 -> 1554.609 | O14: ='0422Master'!AU20 -> 05.05.2022 | P14: ='0422Master'!AV20 -> CITI Bank | Q14: ='0422Master'!AW20 -> 5297131705
A15: 6 | B15: ='0422Master'!B21 -> Amit Chawadi | C15: ='0422Master'!E21 -> Veerendra | D15: YES | E15: ='0422Master'!F21 -> Sr.Software Engineer | F15: ='0422Master'!W21 -> 30 | G15: ='0422Master'!AM21 -> 88276.332 | H15: ='0422Master'!AI21 -> 1554.609 | I15: N/A | J15: N/A | K15: N/A | L15: N/A | M15: =H15 -> 1554.609 | N15: =H15 -> 1554.609 | O15: ='0422Master'!AU21 -> 05.05.2022 | P15: ='0422Master'!AV21 -> ICICI Bank | Q15: ='0422Master'!AW21 -> 007401540582
A16: 7 | B16: ='0422Master'!B22 -> Ashwini Nanaware | C16: ='0422Master'!E22 -> Suresh Sadashiv Male | D16: YES | E16: ='0422Master'!F22 -> Project Manager | F16: ='0422Master'!W22 -> 30 | G16: ='0422Master'!AM22 -> 60275.6 | H16: ='0422Master'!AI22 -> 1554.609 | I16: N/A | J16: N/A | K16: N/A | L16: N/A | M16: =H16 -> 1554.609 | N16: =H16 -> 1554.609 | O16: ='0422Master'!AU22 -> 05.05.2022 | P16: ='0422Master'!AV22 -> HDFC Bank | Q16: ='0422Master'!AW22 -> 50100191546051
A17: 8 | B17: ='0422Master'!B23 -> Kaushal Sushil Sharma | C17: ='0422Master'!E23 -> Sushil Sharma | D17: YES | E17: ='0422Master'!F23 -> Network Engineer L2 | F17: ='0422Master'!W23 -> 30 | G17: ='0422Master'!AM23 -> 68276.425 | H17: ='0422Master'!AI23 -> 1554.609 | I17: N/A | J17: N/A | K17: N/A | L17: N/A | M17: =H17 -> 1554.609 | N17: =H17 -> 1554.609 | O17: ='0422Master'!AU23 -> 05.05.2022 | P17: ='0422Master'!AV23 -> ICICI Bank | Q17: ='0422Master'!AW23 -> 001901524778
A18: 9 | B18: ='0422Master'!B24 -> Arvind Akhare | C18: ='0422Master'!E24 -> Vasanth Rao Ramkishan Akhare | D18: YES | E18: ='0422Master'!F24 -> Project Manager | F18: ='0422Master'!W24 -> 28 | G18: ='0422Master'!AM24 -> 87168.559 | H18: ='0422Master'!AI24 -> 1554.609 | I18: N/A | J18: N/A | K18: N/A | L18: N/A | M18: =H18 -> 1554.609 | N18: =H18 -> 1554.609 | O18: ='0422Master'!AU24 -> 05.05.2022 | P18: ='0422Master'!AV24 -> HDFC Bank | Q18: ='0422Master'!AW24 -> 50100150364960
A19: 10 | B19: ='0422Master'!B25 -> Pallavi Rishikesh Naik | C19: ='0422Master'!E25 -> Rishikesh Naik | D19: YES | E19: ='0422Master'!F25 -> Project Manager | F19: ='0422Master'!W25 -> 30 | G19: ='0422Master'!AM25 -> 78276.379 | H19: ='0422Master'!AI25 -> 1554.609 | I19: N/A | J19: N/A | K19: N/A | L19: N/A | M19: =H19 -> 1554.609 | N19: =H19 -> 1554.609 | O19: ='0422Master'!AU25 -> 05.05.2022 | P19: ='0422Master'!AV25 -> CITI Bank | Q19: ='0422Master'!AW25 -> 5696586708
A20: 11 | B20: ='0422Master'!B26 -> Amit Kumar | C20: ='0422Master'!E26 -> Yadram | D20: YES | E20: ='0422Master'!F26 -> Linux Administrator | F20: ='0422Master'!W26 -> 30 | G20: ='0422Master'!AM26 -> 103275.72 | H20: ='0422Master'!AI26 -> 1554.609 | I20: N/A | J20: N/A | K20: N/A | L20: N/A | M20: =H20 -> 1554.609 | N20: =H20 -> 1554.609 | O20: ='0422Master'!AU26 -> 05.05.2022 | P20: ='0422Master'!AV26 -> HDFC Bank | Q20: ='0422Master'!AW26 -> 05121140023169
A21: 12 | B21: ='0422Master'!B27 -> Pranav Thakare | C21: ='0422Master'!E27 -> Pramod Motiram Thakare | D21: YES | E21: ='0422Master'!F27 -> Project Manager | F21: ='0422Master'!W27 -> 27 | G21: ='0422Master'!AM27 -> 75114.995 | H21: ='0422Master'!AI27 -> 1554.609 | I21: N/A | J21: N/A | K21: N/A | L21: N/A | M21: =H21 -> 1554.609 | N21: =H21 -> 1554.609 | O21: ='0422Master'!AU27 -> 05.05.2022 | P21: ='0422Master'!AV27 -> ICICI BANK | Q21: ='0422Master'!AW27 -> 056601532765
... A29: 20 | B29: ='0422Master'!B35 -> susheelKumar Gandla | C29: ='0422Master'!E35 -> Narayana Gandla | D29: YES | E29: ='0422Master'!F35 -> Sr.Software Engineer | F29: ='0422Master'!W35 -> 30 | G29: ='0422Master'!AM35 -> 88276.332 | H29: ='0422Master'!AI35 -> 1554.609 | I29: N/A | J29: N/A | K29: N/A | L29: N/A | M29: =H29 -> 1554.609 | N29: =H29 -> 1554.609 | O29: ='0422Master'!AU35 -> 05.05.2022 | P29: ='0422Master'!AV35 -> ICICI BANK | Q29: ='0422Master'!AW35 -> A/C NO 007601548378
K40: Signature of the Contractor with Seal

Sheet Ser Cert
B4: FORM XV
B5: [Vide rule 77 of Contract Labour (Regul. & Abolition) Central & A.P. Rules, 1971]
B7: SERVICE CERTIFICATE
B9: Name and address of Contractor : | G9: Name and address of establishment in / under which contract is caried on :
B11: ='0422Master'!F5 -> Burgeon IT Services Pvt.Ltd. | G11: ='0422Master'!AP5 -> Burgeon IT Services Pvt.Ltd.
B13: ='0422Master'!F6 -> Siri Mansion LIGB 436 Dr.A S Rao Nagar,Hyderabad | G13: ='0422Master'!AP6 -> Siri Mansion LIGB 436 Dr.A S Rao Nagar,Hyderabad
B17: Nature and Location of work: | G17: Name and address of Principal Employer :
G19: ='0422Master'!AP10 -> INFOSYS LTD.IL Pune SEZ Unit-II,Plot No. 24/3
B21: ='0422Master'!F8 -> IT SUPPORTIVE SERVICES& PUNE SEZ UNIT-II | G21: ='0422Master'!AP11 -> Rajiv gandhi Info tech park,Village Mann,Pune,Maharashtra 411057
B26: Name and address of the workman :
B31: Age or date of Birth :
B33: Identification Marks :
B35: Father's / Husband's Name :
B38: Sl.No. | C38: Total period for which employed | E38: Nature of work done | G38: Rate of wage ( with particulars of units in case of piece work) | J38: Remarks
C40: From | D40: To
B41: 1 | C41: 2 | D41: 3 | E41: 4 | G41: 5 | J41: 6
H56: Signature of the Employer with Seal

Sheet Deductions
A1: FORM XVI- REGISTER OF DEDUCTIONS FOR DAMAGE OR LOSS
A3: (Vide Rule 78(1) (a) (i) of Contract Labour (Regulation and Abolition) Maharashtra Rules 1971.
A4: Name and address of Contractor: GROTECH LANDSCAPE DEVELOPERS PVT.LTD. | D4: ='0422Master'!F5 -> Burgeon IT Services Pvt.Ltd. | E4: Name and address of the establishment in / under which contract is carried on:
B5: ='0422Master'!F6 -> Siri Mansion LIGB 436 Dr.A S Rao Nagar,Hyderabad
B6: ='0422Master'!F7 -> 0
A7: Nature and Location of Work: | D7: ='0422Master'!F8 -> IT SUPPORTIVE SERVICES& PUNE SEZ UNIT-II | E7: Name and address of principal employer:
E8: ='0422Master'!AP10 -> INFOSYS LTD.IL Pune SEZ Unit-II,Plot No. 24/3
E9: ='0422Master'!AP11 -> Rajiv gandhi Info tech park,Village Mann,Pune,Maharashtra 411057
A11: S.No | B11: Name of workman | C11: Father's / Husband's Name | D11: Designation / Nature of employment | E11: Particulars of damage or loss | F11: Date of Damage or loss | G11: Whether workman showed cause against deduction | H11: Name of person in whose presence employee's explanation was heard | I11: Amount of deduction impossed | J11: Date of recovery | M11: Remarks
J12: No.of Instalments | K12: First Instalment | L12: Last instalment
A13: 1 | B13: 2 | C13: 3 | D13: 4 | E13: 5 | F13: 6 | G13: 7 | H13: 8 | I13: 9 | J13: 10 | K13: 11 | L13: 12 | M13: 13
B16: NO EMPLOYEE WAS IMPOSED DEDUCTIONS FOR DAMAGE OR LOSS FOR THE MONTH OF | H16: ='0422Master'!D10 -> 44652
F39: Signature of the Contractor with Seal

Sheet Fines
A1: FORM XVII- REGISTER OF FINES
A3: (Vide Rule 78(1) (a) (i) of Contract Labour (Regulation and Abolition) Maharashtra Rules 1971
A4: Name and address of Contractor: | D4: ='0422Master'!F5 -> Burgeon IT Services Pvt.Ltd. | E4: Name and address of the establishment in / under which contract is carried on:
B5: ='0422Master'!F6 -> Siri Mansion LIGB 436 Dr.A S Rao Nagar,Hyderabad
B6: ='0422Master'!F7 -> 0
A7: Nature and Location of Work: | D7: ='0422Master'!F8 -> IT SUPPORTIVE SERVICES& PUNE SEZ UNIT-II | E7: Name and address of principal employer:
E8: ='0422Master'!AP10 -> INFOSYS LTD.IL Pune SEZ Unit-II,Plot No. 24/3
E9: ='0422Master'!AP11 -> Rajiv gandhi Info tech park,Village Mann,Pune,Maharashtra 411057
A11: S.No | B11: Name of workman | C11: Father's / Husband's Name | D11: Designation / Nature of employment | E11: Act/Omission for which fine imposed | F11: Date of offence | G11: Whether workman showed cause against fine | H11: Name of person in whose presence employee's explanation was heard | I11: Wage-period and wge payable | J11: Amount of fine Imposed | K11: Date on which fine realised | L11: Remarks
A13: 1 | B13: 2 | C13: 3 | D13: 4 | E13: 5 | F13: 6 | G13: 7 | H13: 8 | I13: 9 | J13: 10 | K13: 11 | L13: 12
B16: NO EMPLOYEE WAS IMPOSED FINESFOR THE MONTH OF | H16: ='0422Master'!D10 -> 44652
F38: Signature of the Contractor with Seal

Sheet Advances
A1: FORM XVIII- REGISTER OF ADVANCES
A3: (Vide Rule 78(1) (a) (i) of Contract Labour (Regulation and Abolition) Maharashtra Rules 1971
A4: Name and address of Contractor: | D4: ='0422Master'!F5 -> Burgeon IT Services Pvt.Ltd. | E4: Name and address of the establishment in / under which contract is carried on:
B5: ='0422Master'!F6 -> Siri Mansion LIGB 436 Dr.A S Rao Nagar,Hyderabad
B6: ='0422Master'!F7 -> 0
A7: Nature and Location of Work: | D7: ='0422Master'!F8 -> IT SUPPORTIVE SERVICES& PUNE SEZ UNIT-II | E7: Name and address of principal employer:
E8: ='0422Master'!AP10 -> INFOSYS LTD.IL Pune SEZ Unit-II,Plot No. 24/3
E9: ='0422Master'!AP11 -> Rajiv gandhi Info tech park,Village Mann,Pune,Maharashtra 411057
A11: S.No | B11: Name of workman | C11: Father's / Husband's Name | D11: Designation / Nature of employment | E11: Wage period and wages payable | F11: Date and amount of advance given | G11: Purpose(s) for which advance made | H11: Number of instalments by which advance to be repaid | I11: Date and amount of each instalment repaid | J11: Date on which last instalment was repaid | K11: Remarks
A13: 1 | B13: 2 | C13: 3 | D13: 4 | E13: 5 | F13: 6 | G13: 7 | H13: 8 | I13: 9 | J13: 10 | K13: 11
B16: NO EMPLOYEE TAKEN ADVANCE FOR THE MONTH OF | F16: ='0422Master'!D10 -> 44652
G39: Signature of the Contractor with Seal

Sheet Overtime
A1: FORM XIX- REGISTER OF OVERTIME
A3: (Vide Rule 78(1) (a) (i) of Contract Labour (Regulation and Abolition) Maharashtra Rules 1971
A4: Name and address of Contractor: GROTECH LANDSCAPE DEVELOPERS PVT.LTD. E-35 GREATER KAILASH ENCLAVE-1 NEW DELHI | D4: ='0422Master'!F5 -> Burgeon IT Services Pvt.Ltd. | F4: Name and address of the establishment in which under contract is carried on:
B5: ='0422Master'!F6 -> Siri Mansion LIGB 436 Dr.A S Rao Nagar,Hyderabad
B6: ='0422Master'!F7 -> 0
A7: Nature and Location of Work: | D7: ='0422Master'!F8 -> IT SUPPORTIVE SERVICES& PUNE SEZ UNIT-II | F7: Name and address of principal employer:
F8: ='0422Master'!AP10 -> INFOSYS LTD.IL Pune SEZ Unit-II,Plot No. 24/3
F9: ='0422Master'!AP11 -> Rajiv gandhi Info tech park,Village Mann,Pune,Maharashtra 411057
A11: S.No | B11: Name of workman | C11: Father's / Husband's Name | D11: Sex | E11: Designation / Nature of employment | F11: Date on which overtime worked | G11: Total overtime worked or production in case of piece-rates | H11: Normal rate of wages | I11: Overtime rate of wages | J11: overtime earnings | K11: Date on which overtime wages paid | L11: Remarks
A13: 1 | B13: 2 | C13: 3 | D13: 4 | E13: 5 | F13: 6 | G13: 7 | H13: 8 | I13: 9 | J13: 10 | K13: 11 | L13: 12
B16: NO EMPLOYEE DONE OVERTIME FOR THE MONTH OF | F16: ='0422Master'!D10 -> 44652
G33: Signature of the Contractor with Seal

Sheet Accident
A1: FORM 11
A3: ACCIDENT BOOK
A4: EMPLOYEE STATE INSURANCE CORPORATION
B5: (Regulation 66)
A7: S.No | B7: Date of Notice | C7: Time of Notice | D7: Name and Address of the Injured Person | E7: Sex | F7: Age | H7: Shift,Department and occupation of employee | I7: Details of Injury | P7: Signature and designation of the person who makes the entry in the accident book | Q7: Name,address and occupation of the two witnesses | R7: Remarks if any
G8: Insurance Number | N8: What exactly was the injured person doing at the time of accident | O8: Name,Occupation,address and signature or the thumb impression of the person(s) giving notice
I9: Cause | J9: Nature | K9: Date | L9: Time | M9: Place
A10: 1 | B10: 2 | C10: 3 | D10: 4 | E10: 5 | F10: 6 | G10: 7 | H10: 8 | I10: 9 | J10: 10 | K10: 11 | L10: 12 | M10: 13 | N10: 14 | O10: 15 | P10: 16 | Q10: 17 | R10: 18
B12: NO ACCIDENT OCCURRED FOR THE MONTH OF | F12: ='0422Master'!D10 -> 44652
M27: Signature of the Contractor with Seal
M32: Signature of the Contractor with Seal

Sheet ESI cards Reg
C1: ='0422Master'!F5 -> Burgeon IT Services Pvt.Ltd. | E1: ESI PAHECHAN CARDS ISSUE REGISTER
B2: S.No | C2: Name of the Employee | D2: ESI Number | E2: Issue Date | F2: Signature | G2: Remarks
B3: 1 | C3: ='0422Master'!#REF! -> #REF! | D3: ='0422Master'!#REF! -> #REF!
B4: 2 | C4: ='0422Master'!#REF! -> #REF! | D4: ='0422Master'!#REF! -> #REF!
B5: 3 | C5: ='0422Master'!#REF! -> #REF! | D5: ='0422Master'!#REF! -> #REF!
B6: 4 | C6: ='0422Master'!#REF! -> #REF! | D6: ='0422Master'!#REF! -> #REF!
B7: 5 | C7: ='0422Master'!#REF! -> #REF! | D7: ='0422Master'!#REF! -> #REF!
B8: 6 | C8: ='0422Master'!#REF! -> #REF! | D8: ='0422Master'!#REF! -> #REF!
B9: 7 | C9: ='0422Master'!#REF! -> #REF! | D9: ='0422Master'!#REF! -> #REF!
B10: 8 | C10: ='0422Master'!#REF! -> #REF! | D10: ='0422Master'!#REF! -> #REF!
B11: 9 | C11: ='0422Master'!#REF! -> #REF! | D11: ='0422Master'!#REF! -> #REF!
B12: 10 | C12: ='0422Master'!#REF! -> #REF! | D12: ='0422Master'!#REF! -> #REF!
B13: 11 | C13: ='0422Master'!#REF! -> #REF! | D13: ='0422Master'!#REF! -> #REF!
B14: 12 | C14: ='0422Master'!#REF! -> #REF! | D14: ='0422Master'!#REF! -> #REF!
... B22: 20 | C22: ='0422Master'!#REF! -> #REF! | D22: ='0422Master'!#REF! -> #REF!

Sheet Form-I
B1: FORM I
B2: NOMINATION AND DECLARATION FORM
B3: (Vide Rule 3 of Payment of wages Act Central & A.P Rules, 1936)
B4: Name and Address of the Contractor | H4: Name and Address of the Establishment in/under which Contract is carried on:
B7: =#REF! -> #REF! | H7: =#REF! -> #REF!
B9: =#REF! -> #REF! | H9: =#REF! -> #REF!
B12: Nature of work and location of work: | H12: Name and address of Principal Employer:
H15: =#REF! -> #REF!
B16: =#REF! -> #REF!
H17: =#REF! -> #REF!
B19: 1. Name of the person making nomination | H19: ='0422Master'!#REF! -> #REF!
B20: 2. Father's/Husband name | H20: ='0422Master'!#REF! -> #REF!
B21: 3. Date of Birth | H21: ='0422Master'!#REF! -> #REF!
B22: 4. Sex | H22: ='0422Master'!#REF! -> #REF!
B23: 5. Marital Status | H23: Un-Married
B24: 6.Address
B25: Permanent | H25: ='0422Master'!#REF! -> #REF!
H26: ='0422Master'!#REF! -> #REF!
H27: ='0422Master'!#REF! -> #REF!
B28: Temporary | H28: ='0422Master'!#REF! -> #REF!
H29: ='0422Master'!#REF! -> #REF!
H30: ='0422Master'!#REF! -> #REF!
B31: I hereby nominate the person(s)/cancel the nomination made by me previously and nominate the person(s) mentioned below to
B32: receive any amount due to me from the employer,in the event to my death.
B33: Name of the Nominee/nominees | E33: Address | G33: Nominee's relationship With the member | I33: Date of Birth | J33: Total amount of Share of accumulations | K33: If the nominee is minor,name,relationship and address of the guardian
B34: 1 | E34: 2 | G34: 3 | I34: 4 | J34: 5 | L34: 6
B35: ='0422Master'!#REF! -> #REF! | E35: Same as permanant address | G35: Father | I35: 54 years | J35: 1 | K35: N/A
B39: 1.Certified that I have no family and should I acquire a family hereafter,the above nomination shall be deemed as cancelled.
B40: 2.Certified that my father/mother is/ are dependent upon me.
B41: 3.Strike out whichever is not applicable.
I43: Signature or the thumb impression of the employed person
F44: CERTIFCATE BY EMPLOYER
A45: Certified that the above declaration and nomination has been signed/thumb impressed before me by Shri/Smt/Kum | K45: ='0422Master'!#REF! -> #REF!
A46: employed in my establishment after he/she has read the entry/entries have been read over to him/her by me and got confirmed by him/her.
F49: Signature or the employer or other authorized officer of the establiment and Designation
A50: Place | B50: Hyderabad | F50: ='0422Master'!AP5 -> Burgeon IT Services Pvt.Ltd.
A51: Date | B51: ='0422Master'!#REF! -> #REF! | F51: ='0422Master'!AP6 -> Siri Mansion LIGB 436 Dr.A S Rao Nagar,Hyderabad
B53: FORM I
B54: NOMINATION AND DECLARATION FORM
B55: (Vide Rule 3 of Payment of wages Act Central & A.P Rules, 1936)
B56: Name and Address of the Contractor | H56: Name and Address of the Establishment in/under which Contract is carried on:
B59: ='0422Master'!F5 -> Burgeon IT Services Pvt.Ltd. | H59: ='0422Master'!AP5 -> Burgeon IT Services Pvt.Ltd.
B61: ='0422Master'!F6 -> Siri Mansion LIGB 436 Dr.A S Rao Nagar,Hyderabad | H61: ='0422Master'!AP6 -> Siri Mansion LIGB 436 Dr.A S Rao Nagar,Hyderabad
B64: Nature of work and location of work: | H64: Name and address of Principal Employer:
H67: ='0422Master'!AP10 -> INFOSYS LTD.IL Pune SEZ Unit-II,Plot No. 24/3
B68: ='0422Master'!F8 -> IT SUPPORTIVE SERVICES& PUNE SEZ UNIT-II
H69: ='0422Master'!AP11 -> Rajiv gandhi Info tech park,Village Mann,Pune,Maharashtra 411057
B71: 1. Name of the person making nomination | H71: ='0422Master'!#REF! -> #REF!
B72: 2. Father's/Husband name | H72: ='0422Master'!#REF! -> #REF!
B73: 3. Date of Birth | H73: ='0422Master'!#REF! -> #REF!
B74: 4. Sex | H74: ='0422Master'!#REF! -> #REF!
B75: 5. Marital Status | H75: Un-Married
B76: 6.Address
B77: Permanent | H77: ='0422Master'!#REF! -> #REF!
H78: ='0422Master'!#REF! -> #REF!
H79: ='0422Master'!#REF! -> #REF!
B80: Temporary | H80: ='0422Master'!#REF! -> #REF!
H81: ='0422Master'!#REF! -> #REF!
H82: ='0422Master'!#REF! -> #REF!
B83: I hereby nominate the person(s)/cancel the nomination made by me previously and nominate the person(s) mentioned below to
B84: receive any amount due to me from the employer,in the event to my death.
B85: Name of the Nominee/nominees | E85: Address | G85: Nominee's relationship With the member | I85: Date of Birth | J85: Total amount of Share of accumulations | K85: If the nominee is minor,name,relationship and address of the guardian
B86: 1 | E86: 2 | G86: 3 | I86: 4 | J86: 5 | L86: 6
B87: ='0422Master'!#REF! -> #REF! | E87: Same as permanant address | G87: Father | I87: 54 years | J87: 1 | K87: N/A
B91: 1.Certified that I have no family and should I acquire a family hereafter,the above nomination shall be deemed as cancelled.
B92: 2.Certified that my father/mother is/ are dependent upon me.
B93: 3.Strike out whichever is not applicable.
I95: Signature or the thumb impression of the employed person
F96: CERTIFCATE BY EMPLOYER
A97: Certified that the above declaration and nomination has been signed/thumb impressed before me by Shri/Smt/Kum | K97: ='0422Master'!#REF! -> #REF!
A98: employed in my establishment after he/she has read the entry/entries have been read over to him/her by me and got confirmed by him/her.
F101: Signature or the employer or other authorized officer of the establiment and Designation
A102: Place | B102: Hyderabad | F102: ='0422Master'!F5 -> Burgeon IT Services Pvt.Ltd.
A103: Date | B103: ='0422Master'!#REF! -> #REF! | F103: ='0422Master'!F6 -> Siri Mansion LIGB 436 Dr.A S Rao Nagar,Hyderabad
B107: FORM I
B108: NOMINATION AND DECLARATION FORM
B109: (Vide Rule 3 of Payment of wages Act Central & A.P Rules, 1936)
B110: Name and Address of the Contractor | H110: Name and Address of the Establishment in/under which Contract is carried on:
B113: ='0422Master'!F5 -> Burgeon IT Services Pvt.Ltd. | H113: ='0422Master'!AP5 -> Burgeon IT Services Pvt.Ltd.
B115: ='0422Master'!F6 -> Siri Mansion LIGB 436 Dr.A S Rao Nagar,Hyderabad | H115: ='0422Master'!AP6 -> Siri Mansion LIGB 436 Dr.A S Rao Nagar,Hyderabad
B118: Nature of work and location of work: | H118: Name and address of Principal Employer:
H121: ='0422Master'!AP10 -> INFOSYS LTD.IL Pune SEZ Unit-II,Plot No. 24/3
B122: ='0422Master'!F8 -> IT SUPPORTIVE SERVICES& PUNE SEZ UNIT-II
H123: ='0422Master'!AP11 -> Rajiv gandhi Info tech park,Village Mann,Pune,Maharashtra 411057
B125: 1. Name of the person making nomination | H125: ='0422Master'!#REF! -> #REF!
B126: 2. Father's/Husband name | H126: ='0422Master'!#REF! -> #REF!
B127: 3. Date of Birth | H127: ='0422Master'!#REF! -> #REF!
B128: 4. Sex | H128: ='0422Master'!#REF! -> #REF!
B129: 5. Marital Status | H129: Un-Married
B130: 6.Address
B131: Permanent | H131: ='0422Master'!#REF! -> #REF!
H132: ='0422Master'!#REF! -> #REF!
H133: ='0422Master'!#REF! -> #REF!
B134: Temporary | H134: ='0422Master'!#REF! -> #REF!
H135: ='0422Master'!#REF! -> #REF!
H136: ='0422Master'!#REF! -> #REF!
B137: I hereby nominate the person(s)/cancel the nomination made by me previously and nominate the person(s) mentioned below to
B138: receive any amount due to me from the employer,in the event to my death.
B139: Name of the Nominee/nominees | E139: Address | G139: Nominee's relationship With the member | I139: Date of Birth | J139: Total amount of Share of accumulations | K139: If the nominee is minor,name,relationship and address of the guardian
B140: 1 | E140: 2 | G140: 3 | I140: 4 | J140: 5 | L140: 6
...

Sheet Form-2
K1: (FORM 2 REVISED)
B2: NOMINATION AND DECLARATION FORM FOR UNEXEMPTED/EXEMPTED ESTABLISHMENTS
B3: Declaration and Nomination Form under the Employees Provident Funds and Employees Pension Schemes
B4: (Paragraph 33 and 61(1) of the Employees Provident Fund Scheme 1952 and Paragraph 18 of the Employees Pension Scheme 1995)
B6: 1. Name of the person making nomination | H6: ='0422Master'!#REF! -> #REF!
B7: 2. Father's/Husband name | H7: ='0422Master'!#REF! -> #REF!
B8: 3. Date of Birth | H8: ='0422Master'!#REF! -> #REF!
B9: 4. Sex | H9: ='0422Master'!#REF! -> #REF!
B10: 5. Marital Status | H10: Un-Married
B11: 6.Address
B12: Permanent | H12: ='0422Master'!#REF! -> #REF!
H13: ='0422Master'!#REF! -> #REF!
H14: ='0422Master'!#REF! -> #REF!
G15: PART-A(EPF)
B16: I hereby nominate the person(s)/cancel the nomination made by me previously and nominate the person(s) mentioned below to
B17: receive any amount due to me from the employer,in the event to my death.
B18: Name of the Nominee/nominees | E18: Address | G18: Nominee's relationship With the member | I18: Date of Birth | J18: Total amount of Share of accumulations | K18: If the nominee is minor,name,relationship and address of the guardian
B19: 1 | E19: 2 | G19: 3 | I19: 4 | J19: 5 | L19: 6
B20: ='0422Master'!#REF! -> #REF! | E20: Same as Permanant Address | G20: Father | I20: 55 Years | J20: 1 | K20: N/A
B24: 1.Certified that I have no family and should I acquire a family hereafter,the above nomination shall be deemed as cancelled.
B25: 2.Certified that my father/mother is/ are dependent upon me.
B26: Strike out whichever is not applicable | J26: Signature/or thumb impression of the subscriber
G27: PART (EPS)
G28: Para 18
B29: I hereby furnish below particulars of the members of my family who would be eligible to receive Widow/Children Pension in the event of
B30: my premature death in service
B31: S.No | C31: Name & Address of the Family Member | I31: Age | J31: Relationship with the member
B32: 1 | E32: 2 | I32: 3 | K32: 4
B37: Certified that I have no family as defined in para 2 (vii) of the Employees's Family Pension Scheme 1995 and should I acquire a family hereafter
B38: I shall furnish Particulars there on in the above form.
B39: I hereby nominate the following person for receiving the monthly widow pension (admissible under para 16 2 (a) (1) & (ii) in the even of my death
B40: without leaving any eligible member for receiving pension.
B41: Name and Address of the nominee | G41: Date of Birth | I41: Relationship with member
B47: Date | C47: ='0422Master'!#REF! -> #REF! | I47: Signature or thumb impression of the subscriber
F48: CERTIFCATE BY EMPLOYER
A49: Certified that the above declaration and nomination has been signed/thumb impressed before me by Shri/Smt/Kum | K49: ='0422Master'!#REF! -> #REF!
A50: employed in my establishment after he/she has read the entry/entries have been read over to him/her by me and got confirmed by him/her.
F52: Signature or the employer or other authorized officer of the establiment and Designation
A53: Place | B53: Hyderabad | F53: ='0422Master'!F5 -> Burgeon IT Services Pvt.Ltd.
A54: Date | B54: ='0422Master'!#REF! -> #REF! | F54: ='0422Master'!F6 -> Siri Mansion LIGB 436 Dr.A S Rao Nagar,Hyderabad
K55: (FORM 2 REVISED)
B56: NOMINATION AND DECLARATION FORM FOR UNEXEMPTED/EXEMPTED ESTABLISHMENTS
B57: Declaration and Nomination Form under the Employees Provident Funds and Employees Pension Schemes
B58: (Paragraph 33 and 61(1) of the Employees Provident Fund Scheme 1952 and Paragraph 18 of the Employees Pension Scheme 1995)
B60: 1. Name of the person making nomination | H60: ='0422Master'!#REF! -> #REF!
B61: 2. Father's/Husband name | H61: ='0422Master'!#REF! -> #REF!
B62: 3. Date of Birth | H62: ='0422Master'!#REF! -> #REF!
B63: 4. Sex | H63: ='0422Master'!#REF! -> #REF!
B64: 5. Marital Status | H64: Un-Married
B65: 6.Address
B66: Permanent | H66: ='0422Master'!#REF! -> #REF!
H67: ='0422Master'!#REF! -> #REF!
H68: ='0422Master'!#REF! -> #REF!
G69: PART-A(EPF)
B70: I hereby nominate the person(s)/cancel the nomination made by me previously and nominate the person(s) mentioned below to
B71: receive any amount due to me from the employer,in the event to my death.
B72: Name of the Nominee/nominees | E72: Address | G72: Nominee's relationship With the member | I72: Date of Birth | J72: Total amount of Share of accumulations | K72: If the nominee is minor,name,relationship and address of the guardian
B73: 1 | E73: 2 | G73: 3 | I73: 4 | J73: 5 | L73: 6
B74: ='0422Master'!#REF! -> #REF! | E74: Same as Permanant Address | G74: Father | I74: 55 Years | J74: 1 | K74: N/A
B78: 1.Certified that I have no family and should I acquire a family hereafter,the above nomination shall be deemed as cancelled.
B79: 2.Certified that my father/mother is/ are dependent upon me.
B80: Strike out whichever is not applicable | J80: Signature/or thumb impression of the subscriber
G81: PART (EPS)
G82: Para 18
B83: I hereby furnish below particulars of the members of my family who would be eligible to receive Widow/Children Pension in the event of
B84: my premature death in service
B85: S.No | C85: Name & Address of the Family Member | I85: Age | J85: Relationship with the member
B86: 1 | E86: 2 | I86: 3 | K86: 4
B91: Certified that I have no family as defined in para 2 (vii) of the Employees's Family Pension Scheme 1995 and should I acquire a family hereafter
B92: I shall furnish Particulars there on in the above form.
B93: I hereby nominate the following person for receiving the monthly widow pension (admissible under para 16 2 (a) (1) & (ii) in the even of my death
B94: without leaving any eligible member for receiving pension.
B95: Name and Address of the nominee | G95: Date of Birth | I95: Relationship with member
B101: Date | C101: ='0422Master'!#REF! -> #REF! | I101: Signature or thumb impression of the subscriber
F102: CERTIFCATE BY EMPLOYER
A103: Certified that the above declaration and nomination has been signed/thumb impressed before me by Shri/Smt/Kum | K103: ='0422Master'!#REF! -> #REF!
A104: employed in my establishment after he/she has read the entry/entries have been read over to him/her by me and got confirmed by him/her.
F106: Signature or the employer or other authorized officer of the establiment and Designation
A107: Place | B107: Hyderabad | F107: ='0422Master'!F5 -> Burgeon IT Services Pvt.Ltd.
A108: Date | B108: ='0422Master'!#REF! -> #REF! | F108: ='0422Master'!F6 -> Siri Mansion LIGB 436 Dr.A S Rao Nagar,Hyderabad
K109: (FORM 2 REVISED)
B110: NOMINATION AND DECLARATION FORM FOR UNEXEMPTED/EXEMPTED ESTABLISHMENTS
B111: Declaration and Nomination Form under the Employees Provident Funds and Employees Pension Schemes
B112: (Paragraph 33 and 61(1) of the Employees Provident Fund Scheme 1952 and Paragraph 18 of the Employees Pension Scheme 1995)
B114: 1. Name of the person making nomination | H114: ='0422Master'!#REF! -> #REF!
B115: 2. Father's/Husband name | H115: ='0422Master'!#REF! -> #REF!
B116: 3. Date of Birth | H116: ='0422Master'!#REF! -> #REF!
B117: 4. Sex | H117: ='0422Master'!#REF! -> #REF!
B118: 5. Marital Status | H118: Un-Married
B119: 6.Address
B120: Permanent | H120: ='0422Master'!#REF! -> #REF!
H121: ='0422Master'!#REF! -> #REF!
H122: ='0422Master'!#REF! -> #REF!
G123: PART-A(EPF)
B124: I hereby nominate the person(s)/cancel the nomination made by me previously and nominate the person(s) mentioned below to
B125: receive any amount due to me from the employer,in the event to my death.
B126: Name of the Nominee/nominees | E126: Address | G126: Nominee's relationship With the member | I126: Date of Birth | J126: Total amount of Share of accumulations | K126: If the nominee is minor,name,relationship and address of the guardian
B127: 1 | E127: 2 | G127: 3 | I127: 4 | J127: 5 | L127: 6
B128: ='0422Master'!#REF! -> #REF! | E128: Same as Permanant Address | G128: Father | I128: 55 Years | J128: 1 | K128: N/A
B132: 1.Certified that I have no family and should I acquire a family hereafter,the above nomination shall be deemed as cancelled.
...

Sheet Form 11
I1: New Form No. 11 - Declaration Form
B2: (To be retained by t he employer for future reference)
D3: EMPLOYEES' PROVIDENT FUND ORGANIZATION | I3: Emp Code: | K3: ='0422Master'!#REF! -> #REF!
C4: Employees' Provident Funds Scheme, 1952 (Paragraph 34 & 57) & | I4: Company | J4: ='0422Master'!F5 -> Burgeon IT Services Pvt.Ltd.
C5: The Employees' Pension Scheme, 1995 (Paragraph 24) | I5: ='0422Master'!F6 -> Siri Mansion LIGB 436 Dr.A S Rao Nagar,Hyderabad
A8: 1 | B8: Name of the Member | H8: ='0422Master'!#REF! -> #REF!
A9: 2 | B9: Fathers' Name | F9: Husband's Name | H9: ='0422Master'!#REF! -> #REF!
B10: (Please tick whichever is applicable)
A11: 3 | B11: Date of Birth (DD/MM/YYYY) | H11: ='0422Master'!#REF! -> #REF!
A12: 4 | B12: Gender (Male/Female/Transgender) | H12: ='0422Master'!#REF! -> #REF!
A13: 5 | B13: Marital Status(married / Unmarried / Widow/divorce) | H13: UNMARRIED
A14: 6 | B14: (a) | C14: Email Id
B15: (b) | C15: Mobile No.
A16: 7 | B16: Whether earlier a member of the Employees' Provident Fund Scheme, 1952 ? | H16: Yes | K16: No
A17: 8 | B17: Whether earlier a member of the Employees' Pension Scheme, 1995? | H17: Yes | K17: No
F18: Previous employment details [if Yes to 7 &/or 8 above]
A19: 9 | B19: a) | C19: Universal Account Number
B20: b) | C20: Previous PF Account Number
B21: C) | C21: Date of exit from previous employment (DD/MM/YYYY)
B22: d) | C22: Scheme Certificate No. (if issued)
B23: e) | C23: Pension Payment Order (PPO) No. (if issued)
A24: 10 | B24: a) | C24: International Worker | H24: Yes | K24: No
B25: b) | C25: If yes, state country of origin(India/Name of other country)
B26: C) | C26: Passport No.
B27: d) | C27: Validity of passport [(DD/MM/YYYY) to (DD/MM/YYYY)]
E28: KYC Details (attach self attested copies of following KYCs)
A29: 11 | B29: a) | C29: Bank Account No. & IFS Code
B30: b) | C30: AADHAR No.
B31: c) | C31: Permanent Account No. (PAN), if available
F32: UNDERTAKING
B33: 1) | C33: Certified that the particulars are true to the best of my knowledge.
B34: 2) | C34: I authorize EPFO to use my Aadhar for verification/authentication/eKYC purpose for service delivery.
B35: 3) | C35: Kindly transfer the funds and service details, if applicable from the previous PF account as declared above to the present P.F. Account (The Transfer would be possible only if the identified KYC details approved by previous employer has been verified by present employer
B36: 4) | C36: In case of changes in above details, the same will be intimated to employer at the earliest.
C37: Date : | D37: ='0422Master'!#REF! -> #REF!
C38: Place: | D38: Hyderabad | J38: Signature of Member
F40: DECLARATION BY PRESENT EMPLOYER
A41: A) | B41: The member Mr./Ms./Mrs. | E41: ='0422Master'!#REF! -> #REF! | H41: has joined on | J41: ='0422Master'!#REF! -> #REF! | K41: and has been allotted PF Number
B42: ='0422Master'!#REF! -> #REF!
A43: B) | B43: In case the person was earlier not a member of EPF Scheme, 1952 and EPS, 1995:
B44: (Post allotment of UAN) The UAN allotted for the member is
B45: Please Tick the Appropriate Option:
B46: The KYC details of the above member in the UAN database
B47: Have not been uploaded
B48: Have been uploaded but not approved
B49: Have been uploaded and approved with DSC
A50: C) | B50: In case the person was earlier a member of EPF Scheme, 1952 and EPS, 1995:
B51: The above PF Account Number/ UAN of the member as mentioned in (A) above has been tagged with his/her UAN/Previous Member ID as declared by member.
B52: Please Tick the Appropriate Option:
B53: The KYC details of the above member in the UAN database have been approved with DSC and transfer request has been generated on portal.
B54: As the DSC of establishment are not registered with EPFO, the member has been informed to file physical claim (Form 13) for transfer of funds
B55: from his previous establishment.
B56: Date | C56: =D37 -> #REF! | I56: Signature of Employer with seal of Establishment
I59: New Form No. 11 - Declaration Form
B60: (To be retained by t he employer for future reference)
D61: EMPLOYEES' PROVIDENT FUND ORGANIZATION | I61: Emp Code: | K61: ='0422Master'!#REF! -> #REF!
C62: Employees' Provident Funds Scheme, 1952 (Paragraph 34 & 57) & | I62: Company | J62: ='0422Master'!F5 -> Burgeon IT Services Pvt.Ltd.
C63: The Employees' Pension Scheme, 1995 (Paragraph 24) | I63: ='0422Master'!F6 -> Siri Mansion LIGB 436 Dr.A S Rao Nagar,Hyderabad
A65: 1 | B65: Name of the Member | H65: ='0422Master'!#REF! -> #REF!
A66: 2 | B66: Fathers' Name | F66: Husband's Name | H66: ='0422Master'!#REF! -> #REF!
B67: (Please tick whichever is applicable)
A68: 3 | B68: Date of Birth (DD/MM/YYYY) | H68: ='0422Master'!#REF! -> #REF!
A69: 4 | B69: Gender (Male/Female/Transgender) | H69: ='0422Master'!#REF! -> #REF!
A70: 5 | B70: Marital Status(married / Unmarried / Widow/divorce) | H70: Unmarried
A71: 6 | B71: (a) | C71: Email Id
B72: (b) | C72: Mobile No.
A73: 7 | B73: Whether earlier a member of the Employees' Provident Fund Scheme, 1952 ? | H73: Yes | K73: No
A74: 8 | B74: Whether earlier a member of the Employees' Pension Scheme, 1995? | H74: Yes | K74: No
F75: Previous employment details [if Yes to 7 &/or 8 above]
A76: 9 | B76: a) | C76: Universal Account Number
B77: b) | C77: Previous PF Account Number
B78: C) | C78: Date of exit from previous employment (DD/MM/YYYY)
B79: d) | C79: Scheme Certificate No. (if issued)
B80: e) | C80: Pension Payment Order (PPO) No. (if issued)
A81: 10 | B81: a) | C81: International Worker | H81: Yes | K81: No
B82: b) | C82: If yes, state country of origin(India/Name of other country)
B83: C) | C83: Passport No.
B84: d) | C84: Validity of passport [(DD/MM/YYYY) to (DD/MM/YYYY)]
E85: KYC Details (attach self attested copies of following KYCs)
A86: 11 | B86: a) | C86: Bank Account No. & IFS Code
B87: b) | C87: AADHAR No.
B88: c) | C88: Permanent Account No. (PAN), if available
F89: UNDERTAKING
B90: 1) | C90: Certified that the particulars are true to the best of my knowledge.
B91: 2) | C91: I authorize EPFO to use my Aadhar for verification/authentication/eKYC purpose for service delivery.
B92: 3) | C92: Kindly transfer the funds and service details, if applicable from the previous PF account as declared above to the present P.F. Account (The Transfer would be possible only if the identified KYC details approved by previous employer has been verified by present employer
B93: 4) | C93: In case of changes in above details, the same will be intimated to employer at the earliest.
C94: Date : | D94: ='0422Master'!#REF! -> #REF!
C95: Place: | D95: Hyderabad | J95: Signature of Member
F97: DECLARATION BY PRESENT EMPLOYER
A98: A) | B98: The member Mr./Ms./Mrs. | E98: ='0422Master'!#REF! -> #REF! | H98: has joined on | J98: ='0422Master'!#REF! -> #REF! | K98: and has been allotted PF Number
B99: ='0422Master'!#REF! -> #REF!
A100: B) | B100: In case the person was earlier not a member of EPF Scheme, 1952 and EPS, 1995:
B101: (Post allotment of UAN) The UAN allotted for the member is
B102: Please Tick the Appropriate Option:
B103: The KYC details of the above member in the UAN database
B104: Have not been uploaded
B105: Have been uploaded but not approved
B106: Have been uploaded and approved with DSC
A107: C) | B107: In case the person was earlier a member of EPF Scheme, 1952 and EPS, 1995:
...

Sheet Form-F
A1: F O R M – F
A2: [See sub-Rule (1) of Rule 6] The Payment of Gratuity Rules, 1973:
A3: NOMINATION
A4: To
A5: ='0422Master'!F5 -> Burgeon IT Services Pvt.Ltd.
A6: ='0422Master'!F6 -> Siri Mansion LIGB 436 Dr.A S Rao Nagar,Hyderabad
A8: 1. I, Shri / Shrimati / Kumari | C8: ='0422Master'!#REF! -> #REF!
A9: whose particulars are given in the statement below, hereby nominate the person(s) mentioned below to receive the gratuity payable after my death as also the gratuity standing to my credit in the event of my death before that amount has become payable, or having become payable has not been paid and direct that the said amount of gratuity shall be paid in proportion indicated against the name(s) of the nominee(s).
A11: 2. I hereby certify that the person(s) mentioned is a /are member(s) of my family within the meaning of clause (h) of Section 2 of the Payment of Gratuity Act, 1972.
A13: 3. I hereby declare that I have no family within the meaning of clause (h) of Section 2 of the said Act.
A15: 4. (a) My father/mother/parents is/are not dependent on me
A16: (b) My husband’s father/mother/parents is/are not dependent on my husband.
A18: 5. I have excluded my husband from my family by a notice dated the ……………. to the Controlling Authority in terms of the proviso to clause (h) of Section 2 of the said Act.
A20: 6. Nomination made herein invalidates my previous nomination.
A22: NOMINEE(S)
A23: Name in full with full address of nominee(s): | B23: Relationship with the empliyee | C23: Age of nominee: | D23: Proportion by which the gratuity will be shared:
A24: 1 | B24: 2 | C24: 3 | D24: 4
A25: ='0422Master'!#REF! -> #REF! | B25: Father | C25: 54 Years | D25: 1
A29: STATEMENT
A31: 1. Name of employee in full: | C31: ='0422Master'!#REF! -> #REF!
A32: 2. Sex: | C32: ='0422Master'!#REF! -> #REF!
A33: 3. Religion: | C33: Muslim
A34: 4. Whether unmarried/married/widow/widower: | C34: Un married
A35: 5. Department/Branch/Section where employed: | C35: ='0422Master'!#REF! -> #REF!
A36: 6. Post held with Ticket No. or Serial No. if any: | C36: ='0422Master'!#REF! -> #REF!
A37: 7. Date of appointment: | C37: ='0422Master'!#REF! -> #REF!
A38: 8. Permanent address:
C39: ='0422Master'!#REF! -> #REF!
C40: ='0422Master'!#REF! -> #REF!
C41: ='0422Master'!#REF! -> #REF!
A42: Place: | B42: Hyderabad
A43: Date: | B43: ='0422Master'!#REF! -> #REF! | C43: Signature/Thumb impression of the employee
A45: Declaration by witnesses:
A46: Nomination signed/thumb impressed before me:
A48: Name in full and full address of witnesses: | C48: Signature of witnesses:
A49: 1 | C49: 1
A50: 2 | C50: 2
C51: Certificate by the Employer
A52: Certified that the particulars of the above nomination have been verified and recorded in t his establishment
A53: Employer's reference No, if any
C55: Signature of the employer/Officer authorized
C56: Designation
C57: Name address of the establishment or rubber stamp there of
C58: ='0422Master'!F5 -> Burgeon IT Services Pvt.Ltd.
A59: Place: | B59: =B42 -> Hyderabad | C59: ='0422Master'!F6 -> Siri Mansion LIGB 436 Dr.A S Rao Nagar,Hyderabad
A60: Date: | B60: =B43 -> #REF!
B61: Acknowledgment by the Employee
A62: Received the duplicate of the nomination in Form 'F'Filled by me and duly certified by the employer
A63: Date: | B63: =B60 -> #REF!
A64: Note: Strike out words/paragraph not applicable | D64: Signature of the Employee
A69: F O R M – F
A70: [See sub-Rule (1) of Rule 6] The Payment of Gratuity Rules, 1973:
A71: NOMINATION
A72: To
A73: ='0422Master'!F5 -> Burgeon IT Services Pvt.Ltd.
A74: ='0422Master'!F6 -> Siri Mansion LIGB 436 Dr.A S Rao Nagar,Hyderabad
A76: 1. I, Shri / Shrimati / Kumari | C76: ='0422Master'!#REF! -> #REF!
A77: whose particulars are given in the statement below, hereby nominate the person(s) mentioned below to receive the gratuity payable after my death as also the gratuity standing to my credit in the event of my death before that amount has become payable, or having become payable has not been paid and direct that the said amount of gratuity shall be paid in proportion indicated against the name(s) of the nominee(s).
A79: 2. I hereby certify that the person(s) mentioned is a /are member(s) of my family within the meaning of clause (h) of Section 2 of the Payment of Gratuity Act, 1972.
A81: 3. I hereby declare that I have no family within the meaning of clause (h) of Section 2 of the said Act.
A83: 4. (a) My father/mother/parents is/are not dependent on me
A84: (b) My husband’s father/mother/parents is/are not dependent on my husband.
A86: 5. I have excluded my husband from my family by a notice dated the ……………. to the Controlling Authority in terms of the proviso to clause (h) of Section 2 of the said Act.
A88: 6. Nomination made herein invalidates my previous nomination.
A90: NOMINEE(S)
A91: Name in full with full address of nominee(s): | B91: Relationship with the empliyee | C91: Age of nominee: | D91: Proportion by which the gratuity will be shared:
A92: 1 | B92: 2 | C92: 3 | D92: 4
A93: ='0422Master'!#REF! -> #REF! | B93: Father | C93: 54 Years | D93: 1
A97: STATEMENT
A99: 1. Name of employee in full: | C99: ='0422Master'!#REF! -> #REF!
A100: 2. Sex: | C100: ='0422Master'!#REF! -> #REF!
A101: 3. Religion: | C101: Hindu
A102: 4. Whether unmarried/married/widow/widower: | C102: Un married
A103: 5. Department/Branch/Section where employed: | C103: ='0422Master'!#REF! -> #REF!
A104: 6. Post held with Ticket No. or Serial No. if any: | C104: ='0422Master'!#REF! -> #REF!
A105: 7. Date of appointment: | C105: ='0422Master'!#REF! -> #REF!
A106: 8. Permanent address:
C107: ='0422Master'!#REF! -> #REF!
C108: ='0422Master'!#REF! -> #REF!
C109: ='0422Master'!#REF! -> #REF!
A110: Place: | B110: Hyderabad
A111: Date: | B111: ='0422Master'!#REF! -> #REF! | C111: Signature/Thumb impression of the employee
A113: Declaration by witnesses:
A114: Nomination signed/thumb impressed before me:
A116: Name in full and full address of witnesses: | C116: Signature of witnesses:
A117: 1 | C117: 1
A118: 2 | C118: 2
C119: Certificate by the Employer
A120: Certified that the particulars of the above nomination have been verified and recorded in t his establishment
A121: Employer's reference No, if any
C123: Signature of the employer/Officer authorized
C124: Designation
C125: Name address of the establishment or rubber stamp there of
C126: ='0422Master'!F5 -> Burgeon IT Services Pvt.Ltd.
A127: Place: | B127: =B110 -> Hyderabad | C127: ='0422Master'!F6 -> Siri Mansion LIGB 436 Dr.A S Rao Nagar,Hyderabad
A128: Date: | B128: =B111 -> #REF!
B129: Acknowledgment by the Employee
A130: Received the duplicate of the nomination in Form 'F'Filled by me and duly certified by the employer
A131: Date: | B131: =B128 -> #REF!
A132: Note: Strike out words/paragraph not applicable | D132: Signature of the Employee
...

Sheet Sheet1
