Workbook

Sheet BGLR STP APRIL 22-WM Reg
B1: 44531
A2: FORM - XIII REGISTER OF WORKMEN EMPLOYED BY CONTRACTOR
A4: Name and address of Contractor: | F4: ='04-22Master'!F5 -> Burgeon IT Services Pvt.Ltd. | I4: Name and address of Establishemnt in/ under which conctract is carried on: | L4: ='04-22Master'!AK5 -> Burgeon IT Services Pvt.Ltd.
F5: ='04-22Master'!F6 -> Siri Mansion LIGB 436 Dr.A S Rao Nagar,Hyderabad | L5: ='04-22Master'!AK6 -> Siri Mansion LIGB 436 Dr.A S Rao Nagar,Hyderabad
A6: Nature and location of work: | F6: ='04-22Master'!F8 -> IT SUPPORTIVE SERVICES & BANGALORE STP
I8: Name and address of Principal Employer: | L8: ='04-22Master'!AK10 -> INFOSYS LTD.IL Bangalore STP Park - I
L9: ='04-22Master'!AK11 -> No.45&46,3rd Cross,Electronic City,BANGALORE,KARNATAKA
A12: Serial No. in the Register of Workmen | B12: Name of Workman | C12: Age | D12: Sex | E12: Father's /Husband Name | F12: Designation / Nature of Work Done | G12: Permanent Address | H12: Local Address | I12: Date of Commencement of Employment | J12: Signature or thumb impression of Workman | K12: Date of termination of Employment | L12: Reasons for termination | M12: Remarks | N12: TOTAL EMPLOYESIN JULY 21
A14: =[1]Master!A16 -> 1 | B14: =[1]Master!B16 -> Kameswara Rao .M | C14: =[1]Master!C16 -> 03.07.1981 | D14: =[1]Master!D16 -> M | E14: =[1]Master!E16 -> Joga Rao | F14: =[1]Master!F16 -> TECHNICAL CONSULTATNT | G14: VENKATA SAI NILAYAM,OPP:LIG-1-39,APHB COLONY,SRIKAKULAM,A.P. 582001 | H14: GROUND FLOOR,NAGAPA ROY ,BLOCK NO 3 THUMBALA HALDI, BANGALORE, KARNATAKA STATE | I14: =[1]Master!N16 -> 11.04.2018 | K14: 30.01.2019 | L14: RESIGNED
A15: 2 | B15: Yogesh Rao | C15: 09.05.1983 | D15: M | E15: Bhaskar Rao | F15: TECHNICAL CONSULTATNT | G15: 874, 2ND C MAIN 8TH BLOCK,KORAMANGALA,BANGALORE | H15: 204, 2ND FLOOR,JPARVATHI BLK,SHRI TIRUMALA APPTS.SINGA SANDRA,BANGALAORE,KARNATAKA STATE | I15: 21.05.2018 | K15: 17.05.2019 | L15: RESIGNED
A16: =[2]Master!A16 -> 3 | B16: =[2]Master!B16 -> Rahul Balachandran | C16: =[2]Master!C16 -> 15.04.1983 | D16: =[2]Master!D16 -> M | E16: =[2]Master!E16 -> Balachandran S P | F16: =[2]Master!F16 -> TECHNICAL CONSULTATNT | G16: KARTHIKA KB NAGAR,72 WEST ADIKADU TEMPLE ERAVIPURAM POST KOLLAM,KERALA 691011 | H16: SHANTHI APPRTS.PLOT NO 25/4 KUMARAN STREET,SELAIVUR ,CHENNAI,TAMILNADU | I16: =[2]Master!I16 -> 06.09.2018 | K16: 04.09.2019 | L16: RESIGNED
A17: =[3]Master!A19 -> 4 | B17: =[3]Master!B19 -> Satyaprasanna Das | C17: =[3]Master!C19 -> 05.05.1981 | D17: =[3]Master!D19 -> M | E17: =[3]Master!E19 -> Bhajan Kumar Das | F17: =[3]Master!F19 -> TECHNICAL CONSULTATNT | G17: Meena Glory B 5/A , Dasadrone, Kolkata 700136 | H17: 123 PVR Building 5th Cross KEB road Vittal Nagar Bangalore 560078 | I17: =[3]Master!N19 -> 10.09.2018 | K17: 14.12.2018 | L17: RESIGNED
A18: 5 | B18: Avishek Singh Rathaur | C18: 01.04.1991 | D18: M | E18: Rama Shankar Singh | F18: TECHNICAL CONSULTATNT | G18: VICE- PACHRUKHIYA,POHS-EKHA,DIST CHAPARA,BIHAR 841208 | H18: RZH -745,Flat no -102,Street-14,H Block RajnagarII,Palam colony,Bangalore Karnataka | I18: 25.03.2019 | K18: 13.05.2019 | L18: RESIGNED
A19: 6 | B19: =[2]Master!B17 -> ELLALACHERUVU MOHAMMAD IMRAN | C19: 10.07.1991 | D19: =[2]Master!D17 -> M | E19: Mubarak Ali | F19: TECHNICAL CONSULTATNT | G19: 6-106, small mosque street, Rompicherla, Chittoor, AP 517192 | H19: Meenasri PG Electronic city Bangalore | I19: =[2]Master!I17 -> 01.06.2019 | K19: 31.12.2019 | L19: RESIGNED
A20: 7 | B20: Anil Kumar.B | C20: 29392 | D20: M | E20: Pitchaiah | F20: Senior Associate | G20: 2-194, Machavaram, Ponnur(MD), Guntur(DT), AP - 522315 | H20: #28, Deccon Flats, Flat no.G11,LIC Colony, East Tambaram, Chennai-59 | I20: 02.13.2020 | L20: RESIGNED
A21: 8 | B21: Yateesh Kumar | C21: 17.06.1989 | D21: M | E21: K. Amaranatha Reddy | F21: Senior Consultant | G21: No 36a, Chokkanathan Nagar, 3rd Street, Maduravoyal,Ch-95 | H21: No 36a, Chokkanathan Nagar, 3rd Street, Maduravoyal,Ch-95 | I21: 43950 | L21: RESIGNED
A22: 9 | B22: Nagarjuna Animireddy | C22: 33241 | D22: M | E22: SRILATHA P | F22: Support Lead | G22: H.No 2-40,Ravigunta Palli Village, Pamuru Mandal, Prakasam District, Andhra Pradesh Pin -523230 | H22: H.NO 2209,Vaddarapet, doddaballapur, Bangalore Rural, Karnataka PIN-561203 | I22: 43957 | K22: 29.05.2020 | L22: RESIGNED
A23: 10 | B23: Aswartha Narayana Guptha | C23: 21-03-1984 | D23: MALE | E23: Nagaraju J | F23: Associate Manager | G23: H.No-14/405, kamalanagar, S.L.V garments, Anantapur - 515001 | H23: F.No-101, Mayura E-city Apartment, Doddathogur, Electronic city Ph-1, Opp. Four Points Super market, Bangalore - 560100 | I23: 44126 | K23: 44403 | L23: RESIGNED
A24: 11 | B24: RAMESH DHAYALAN | C24: 31799 | D24: M | E24: Dhayalan. D | F24: Senior Windows Administration | G24: No 180, 3rd Cross st, MGR St, Bharathi Nagar, Mettuthandalam, Thiruporur, Chengalpattu District Pincode=603110 | H24: No 180, 3rd Cross st, MGR St, Bharathi Nagar, Mettuthandalam, Thiruporur, Chengalpattu District Pincode=603110 | I24: 44117 | K24: 44187 | L24: RESIGNED
A25: 12 | B25: AKASH DEEP CHUNAP | C25: 33695 | D25: MALE | E25: Priyanka Chunap | F25: Network security engineer | G25: H.No 4-3-216/2A,Narasimha Nagar, Bhainsa, Nirmal District, 504 103 | H25: Selene Court, Sree Vensai Projects, Flat 404, Kompally, 500014 | I25: 44105 | K25: ACTIVE | L25: ACTIVE | N25: 1
A26: 13 | B26: Kotravel Balasubramaniam | C26: 30142 | D26: MALE | E26: Balasubramaniam K | F26: Senior Technical Specialist | G26: 3/442,Vasantha Nagar,Nathakadaiyur,Kangeyam(TK),Tirupur(DT),TamilNadu | H26: #195 TRC Paradise, 6stage,5th mainBEML Layout ,Bangalore | I26: 44139 | J26: OOOO | K26: 44440 | L26: RESIGNED
A27: 14 | B27: SUDALAI KANNAN M | C27: 31571 | D27: MALE | E27: Mohandass T | F27: Sr Solaris Administrator | G27: 449/6 Selva Nagar Main Road, LRG Nagar backside, Vadivel Nagar, Karur -639008. Tamilnadu | H27: 83. 8th Cross, 2nd Main Road, Manjunath Nagar, Chikkalsandra, Uttarahalli - 560061, Bangalore - Karnataka | I27: 44147 | J27: OOOO | K27: 44359 | L27: RESIGNED
A28: 15 | B28: Parteek Arora | C28: 32111 | D28: MALE | E28: Lovejeet Kour | F28: Active Directory Architect | G28: A-207, Sainik Colony, Sector 49, Faridabad, Haryana, 121001 | H28: A-207, Sainik Colony, Sector 49, Faridabad, Haryana, 121001 | I28: 44159 | J28: OOOO | K28: ACTIVE | L28: ACTIVE
A29: 16 | B29: Gudipati Ravi Teja | C29: 29048 | D29: M | E29: G Abdul Hameed | F29: Senior Software Engineer | G29: Flat 311,Hyder Chand Plaza,Vadeegeri,Kurnool.A.P | H29: H.No.12-2-790/11,Flat G2,Span Nest Appartments,Ayodha Nagar Colony,Mehdipatnam,Hyderabad. | I29: 44166 | K29: 44253 | L29: RESIGNED
A30: 17 | B30: Aniket Shankar Bamane | C30: 32826 | D30: MALE | E30: SHANKAR BAMANE | F30: Solution Architect | G30: 101, LAXMI KRUPA SADAN, NEAR GAONDEVI MANDIR, TALAVALI NAKA, NAVI MUMBAI - 400708 | H30: G-3, MATRUCHAYA BUILDING, NEAR RAM MARATHE BUNGLOW, KOPARI COLONY, THANE (E) - 400603 | I30: 44181 | J30: OOOO | K30: 44412 | L30: RESIGNED
A31: 18 | B31: Roshan Ravinder Vannam | C31: 29/6/1986 | D31: M | E31: Ravinder Vannam | F31: Sales force Business Analyst | G31: 1-8-700/29, Padma Colony,Hydebad- 500044, Telangana | H31: Flat#501, KBR Sai Akshaya Residency,2-2-18/15, DD Colony, Hyderabad-500013,TS | I31: 44210 | K31: 44258 | L31: RESIGNED
A32: 19 | B32: Naveena Kura | C32: 31573 | D32: F | E32: A.Rajesh | F32: Associate Consultant | G32: 2-72,Rompicherls cross,Challavaripalle(p),Rompicherla(M),Chittoor(dt),Andhrapradesh-517192 | H32: 102,1st floor,K.L.Regency,Sai Brindavana Layout,3rd cross,Medahalli,Bangalore-560049 | I32: 44214 | K32: 44253 | L32: RESIGNED
A33: 20 | B33: SantoshKumar KA | C33: 30101 | D33: M | E33: K J Arunachalam | F33: Senior Manager-Projects | G33: No.13, Flat F-1, Kurinji Flats, Mahalakshmi Nagar 2nd Street, Madipakkam, Chennai - 600091 | H33: No.13, Flat F-1, Kurinji Flats, Mahalakshmi Nagar 2nd Street, Madipakkam, Chennai - 600091 | I33: 44214 | K33: 44286 | L33: RESIGNED
A34: 21 | B34: Damodar Medara | C34: 25/7/1990 | D34: MALE | E34: M.Rajgopal | F34: Senior Technial Consultant | G34: s/o Rajgopal medara, 16/21, Mohammediya, cowal Bazar, 1st gate, bellary-583102 | H34: s/o Rajgopal medara, 16/21, Mohammediya, cowal Bazar, 1st gate, bellary-583102 | I34: 44214 | K34: 44439 | L34: RESIGNED
A35: 22 | B35: Shaikmahaboob vali | C35: 33030 | D35: MALE | E35: shaik mahaboob basha | F35: Technical Consultant | G35: 3-16,uppalapdu owk mandal banaganapalli taluk kurnool ap 51812 | H35: 3-16,uppalapdu owk mandal banaganapalli taluk kurnool ap 51812 | I35: 44249 | K35: 44408 | L35: RESIGNED
A36: 23 | B36: Kuldeep Singh | C36: 30/1/1990 | D36: M | E36: Ankita Singh | F36: Client Delievary Manager | G36: Flat no 302, Sai park Phase 1, Keshav nagar, Pune 4110136 | H36: Flat no 302, Sai park Phase 1, Keshav nagar, Pune 4110136 | I36: 44252 | J36: OOOO | K36: 43329 | L36: RESIGNED
A37: 24 | B37: VarunKumar AVS | C37: 29/3/1988 | D37: MALE | E37: Aida Krishna Rao | F37: Windows VMware Engineer | G37: H.No.8-2-310/A/76/1, IbrahimNagar, Banjara Hills Road No.10 Hyderabad 500034 | H37: H.No.8-2-310/A/76/1, IbrahimNagar, Banjara Hills Road No.10 Hyderabad 500034 | I37: 44256 | K37: 44393 | L37: RESIGNED
A38: 25 | B38: Akhila Surineni | C38: 25/6/1990 | D38: MALE | E38: Srinivasa Rao Surineni | G38: Plot no: 149, Road No:7,Plot no: 149, Road No:7,Harivillu township, Patelguda,Ameenpur, Sangareddy- 502319 | H38: Plot no: 149, Road No:7 Harivillu township, Patelguda, Ameenpur, Sangareddy- 502319 | I38: 44256 | J38: OOOO | K38: 44362 | L38: RESIGNED
A39: 26 | B39: Obulreddy Desam | C39: 33978 | D39: MALE | E39: Ramakrishna Reddy | F39: Linux System Administrator | G39: D-NO 1-7, Polepalli post,Durgi mondal,Guntur dist,Andhrapradesh 522612 | H39: D-NO 1-7, Polepalli post,Durgi mondal,Guntur dist,Andhrapradesh 522612 | I39: 44274 | J39: OOOO | K39: ACTIVE | L39: ACTIVE
A40: 27 | B40: Aiesha Nabi | C40: 22/07/1994 | D40: FEMALE | E40: D P Nabirasool | F40: Linux System Administrator | G40: 107, 1st floor, Sri Shravya PG, 6th cross, thulasi theater road, Marathahalli -560037 | H40: 9-246, Hindupur,kirikera, Ananthapur, AP-515211 | I40: 44274 | K40: ACTIVE | L40: ACTIVE
A41: 28 | B41: Nikath Banu | C41: 32785 | D41: FEMALE | E41: ABDUL KADAR | F41: Technical Consultant | G41: 112B Ist Floor, manohar nagar, | H41: 112B Ist Floor, manohar nagar, | I41: 44279 | K41: ACTIVE | L41: ACTIVE
A42: 29 | B42: RAMBABU PYDI | C42: 30804 | D42: MALE | E42: PYDI. DHANA LAKSHMI | F42: Major Incident Manager | G42: H.NO - 20-72/3. GOUTHAM NAGAR, MALKAJGIRI., MEDCHAL - 500047 | H42: H.NO - 20-72/3. GOUTHAM NAGAR, MALKAJGIRI., MEDCHAL - 500047 | I42: 44279 | J42: OOOO | K42: ACTIVE | L42: ACTIVE
A43: 30 | B43: Srinivasulu Boyapati | C43: 32787 | D43: MALE | E43: Subbarayudu | F43: Salesforce Vlocity Consultant | G43: Flat no#301,ss Fecility homes, Berewell Road, White field, Bangloor | H43: Sanjeeva Nagar, Gowraram, anatnthsagaram, TS | I43: 44284 | K43: 44455 | L43: RESIGNED
A44: 31 | B44: Vijay kola | C44: 17-06-1993 | D44: MALE | E44: Kola Sathish babu | F44: Senior Associate | G44: 11-139/6, Yogimallavaram, Tiruchanoor, Tirupati, 517503 | H44: 11-139/6, Yogimallavaram, Tiruchanoor, Tirupati, 517503 | I44: 44287 | J44: OOOO | K44: 44469 | L44: RESIGNED
A45: 32 | B45: Venkadesh Pounraj | C45: 30839 | D45: MALE | E45: Pounraj | F45: Technical Consultant | G45: 1/242A, Perumal Kovil street, Thalai vasal street, Salem,Tamil Nadu 636112 | H45: 1/242A, Perumal Kovil street, Thalai vasal street, Salem,Tamil Nadu 636112 | I45: 44287 | K45: 44333 | L45: RESIGNED
A46: 33 | B46: Aftabuddin Ahmed | C46: 30-06-1992 | D46: MALE | E46: Abdul Latif | F46: Senior Network Security Engineer | G46: Ghilakuri, Barampur,Darrang,Assam,784144 | H46: Ghilakuri, Barampur,Darrang,Assam,784144 | I46: 7th April 2021 | K46: 44469 | L46: RESIGNED
A47: 34 | B47: BadriNarayana Mandla | C47: 32785 | D47: MALE | E47: M.Rukhmangadudu | F47: Windows Admin | G47: 1-112 , Yadawada, Allagadda (M), Kurnool (Dt),Andra Pradesh. PIN : 518543 | H47: 1-112 , Yadawada, Allagadda (M), Kurnool (Dt),Andra Pradesh. PIN : 518543 | I47: 44295 | J47: OOOO | K47: ACTIVE | L47: ACTIVE
A48: 35 | B48: Naresh Jampala | C48: 31858 | D48: MALE | E48: Venkateswarlu | F48: Sr.System Administrator | G48: Flat No 304, Arvind Apts, Manjunatha Layout, Devasandra, Kuvempulayout, Krishnarajapuram, Bengaluru, KA 560036 | H48: 46/682 F3, Budhwarpet, Kurnool, AP 518001 | I48: 44321 | K48: ACTIVE | L48: ACTIVE
A49: 36 | B49: Reddiyappa Shanmugam | C49: 29227 | D49: MALE | E49: Shanmugam | F49: Citrix Administrator | G49: 106 A-block, Garden residency, Kanchanayakanahalli,Bommasandra Ind. area,jigani, Bangalore-560099 | H49: 106 A-block, Garden residency, Kanchanayakanahalli,Bommasandra Ind. area,jigani, Bangalore-560099 | I49: 44321 | K49: 44377 | L49: RESIGNED
A50: 37 | B50: RajasekharReddy KN | C50: 30837 | D50: MALE | E50: Narayana Reddy | F50: Citrix Administrator | G50: 3-48, Boorlapalli, PTM Madalam, Tamballapalli, Boorlapalle, Chittoor, AP 517370 | H50: 3-48, Boorlapalli, PTM Madalam, Tamballapalli, Boorlapalle, Chittoor, AP 517370 | I50: 44326 | K50: ACTIVE | L50: ACTIVE | N50: 2
A51: 38 | B51: Moulika GM | C51: 35558 | D51: Female | E51: Maniganda Charan Kumar | F51: Ansible Developer | G51: 12A/22A,METTU,TIRUTTANI | H51: BANGALORE, ELECTRONIC CITY,PHASE1 | I51: 44327 | K51: ACTIVE | L51: ACTIVE | N51: 3
A52: 39 | B52: AsokKumar J | C52: 32274 | D52: Male | E52: J.Prabhakar Reddt | F52: Senior Middleware Administrator (MQ & Kafka) | G52: #303, Dhanunjaya Apartment, Dasarahalli Main Road, Hebbal,Bangalore-560024. | H52: 2-88, S/o Juturu Prabhakar Reddy, Gunipalli, Bukkapatnam, Anantapur, Andra Pradesh-515154 | I52: 44328 | K52: ACTIVE | L52: ACTIVE | N52: 4
A53: 40 | B53: Yugandhar | C53: 32011 | D53: Male | E53: M SAMBA SIVA RAO | F53: Network Security Consultant | G53: 20-14-38/1,Devabakthuni vaari veedi, Chinnaravuru, Tenali | H53: 20-14-38/1,Devabakthuni vaari veedi, Chinnaravuru, Tenali | I53: 44333 | K53: ACTIVE | L53: ACTIVE
A54: 41 | B54: Srikanth Chodapaneedi | C54: 31-07-1986 | D54: Male | E54: CVN.UMAMAHESWARA RAO | F54: IT Service Manager | G54: FNO-301, PNO-15, ANANTHA SAI RESIDENCY, RAGHAVENDRA SHELTERS, KMR ESTATES, KONDAPUR, HYDERABAD 500084 | H54: FNO-301, PNO-15, ANANTHA SAI RESIDENCY, RAGHAVENDRA SHELTERS, KMR ESTATES, KONDAPUR, HYDERABAD 500084 | I54: 44342 | K54: 44408 | L54: RESIGNED
A55: 42 | B55: Majed Khan | C55: 32203 | D55: Male | E55: Habeeb Khan | F55: Oracle/SAP DBA | G55: H NO 4-11-44/1, Kareem colony, OP, Narsa Hotel,Roshan Gate, Aurangabad, MH 431001 | H55: H NO 4-11-44/1, Kareem colony, OP, Narsa Hotel,Roshan Gate, Aurangabad, MH 431001 | I55: 44344 | K55: ACTIVE | L55: ACTIVE | N55: 5
A56: 43 | B56: Mahesh Kadtan | C56: 33412 | D56: Male | E56: Narayan Gangadhar | F56: Oracle/SAP DBA | G56: 1-7-65, Vimantal Road, Near Hanuman Temple, Sahayog Nagar, Nanded, MH 431605 | H56: 1-7-65, Vimantal Road, Near Hanuman Temple, Sahayog Nagar, Nanded, MH 431605 | I56: 44344 | J56: OOOO | K56: ACTIVE | L56: ACTIVE
A57: 44 | B57: Swetha Moluguru | C57: 34106 | D57: Female | E57: Sampath Kumar | F57: Senior IT Analyst | G57: 1-8-518/16/2/1,Street No 9, Chikkadapalli,Hyderabad Telangana 500020 | H57: 1-8-518/16/2/1,Street No 9, Chikkadapalli,Hyderabad Telangana 500020 | I57: 44344 | K57: ACTIVE | L57: ACTIVE
A58: 45 | B58: Reno Vijayan | C58: 31699 | D58: MALE | E58: Vijayan IR | F58: VMware Administrator | G58: Iyrada House,Anchery post,Trissul,Kerala 680006 | H58: Iyrada House,Anchery post,Trissul,Kerala 680006 | I58: 44348 | K58: ACTIVE | L58: ACTIVE
A59: 46 | B59: SathishKumar V | C59: 32918 | D59: MALE | E59: M Venkatesam | F59: Lead Administrator | G59: #789, Balaji Nager Tirumala, Tirupathi(M), Chittoor(Dist) AP-517504 | H59: #789, Balaji Nager Tirumala, Tirupathi(M), Chittoor(Dist) AP-517504 | I59: 44348 | K59: ACTIVE | L59: ACTIVE
A60: 47 | B60: MADAN DH | C60: 25-05-1988 | D60: MALE | E60: Dayanand H | F60: Principal Storage Consultant | G60: #402, Supreme Sunrise, Wellington Layout, Singasandra, Hosur road, Bangalore-68 | H60: #402, Supreme Sunrise, Wellington Layout, Singasandra, Hosur road, Bangalore-68 | I60: 44362 | K60: ACTIVE | L60: ACTIVE | N60: 6
A61: 48 | B61: Kutagolla Mohazzer | C61: 14/06/1996 | D61: MALE | E61: Khaleel Saheb | F61: Sr. Software Engineer | G61: 2-99,MBT Road,Angallu,Andhra Pradesh -517325 | H61: 2-99,MBT Road,Angallu,Andhra Pradesh -517325 | I61: 44363 | K61: ACTIVE | L61: ACTIVE
A62: 49 | B62: Sachin Ameshram | C62: 21/09/1983 | D62: MALE | E62: POONAM SACHIN MESHRAM | F62: Windows Administrator | G62: T4 KUNAL RESIDENCY 2 BEHIND VITTHAL MANDIR BELTARODI NAGPUR 441108 | H62: 403 BHAKTI HEIGHTS ADHIRAJ CLUSTER 2 BEHIND DAWLAT PETROL PUMP BHUGAON PUNE 411023 | I62: 44368 | K62: ACTIVE | L62: ACTIVE | N62: 7
A63: 50 | B63: Sunny Singh | C63: 32308 | D63: MALE | E63: Mrs. Malti S Singh | F63: SAP Consultant | G63: D13-3, S.G. Barvenager, Ghatkopar West, Mumbai 400084 | H63: 17/7, JPM Co Op Hsg Society, Mulund East, Mumbai 400081 | I63: 44375 | K63: 44469 | L63: RESIGNED
A64: 51 | B64: Santhosh Mandla | C64: 24-05-1992 | D64: MALE | E64: Ramreddy Mandla | F64: Database Administrator | G64: H NO 239, Jalavayuvihar colony, Kukatpally, Hyderabad, Telangana, 500082 | H64: H NO 239, Jalavayuvihar colony, Kukatpally, Hyderabad, Telangana, 500082 | I64: 44390 | K64: ACTIVE | L64: ACTIVE
A65: 52 | B65: Barathiyar A | C65: 03.05.1981 | D65: MALE | E65: Arumugam | F65: VMware & Wintel Admin | G65: 3/148,New Street,Mundiyampakkam & PO,Vikkravandi Taluk,Villupuram Dist,PIN 605601 | H65: 3/148,New Street,Mundiyampakkam & PO,Vikkravandi Taluk,Villupuram Dist,PIN 605601 | I65: 44396 | K65: ACTIVE | L65: ACTIVE | N65: 8
A66: 53 | B66: Kumaravel M | C66: 30142 | D66: MALE | E66: Madhavaraj | F66: Sr. Network Administrator | G66: NO 88, Arvind Nagar, 5th Street, Madambakkam, Chennai, 600126 | H66: NO 88, Arvind Nagar, 5th Street, Madambakkam, Chennai, 600126 | I66: 44396 | K66: ACTIVE | L66: ACTIVE | N66: 9
A67: 54 | B67: Janakiraman C | C67: 29370 | D67: MALE | E67: Chitrao | F67: Sr.Vmware Administrator | G67: No 5, Thaneer Pandhal Colony, Vayalur Village, Kalpakkam, Chengalpattu dist | H67: No 5, Thaneer Pandhal Colony, Vayalur Village, Kalpakkam, Chengalpattu dist | I67: 44396 | K67: ACTIVE | L67: ACTIVE
A68: 55 | B68: CHANDRASEHARAN GERORGE | C68: 27181 | D68: MALE | E68: George | F68: SENIOR TECHNICAL SPECIALIST | G68: PLOT NO.88, KAMALALAYAM 2, M.G.NAGAR 2, URAPAKKAM - 603211 | H68: PLOT NO.88, KAMALALAYAM 2, M.G.NAGAR 2, URAPAKKAM - 603211 | I68: 44396 | K68: ACTIVE | L68: ACTIVE | N68: 10
A69: 56 | B69: Kannan Selvakumar | C69: 22/03/1987 | D69: MALE | E69: SELVA KUMAR.S | F69: Senior Associate consultant | G69: KANNAN. S NO 20C, ROAD ST, NAINAMPATTI, VELLANDIVALASU (PO), EDAPPADI, SALEM (Dt) PIN- 637101 | H69: NO 2 2ND FLOOR, NARAYANAN ST, LORD SRINIVASA COLONY, PALLAVARAM,CHENNAI. PIN : 600043 | I69: 44396 | K69: ACTIVE | L69: ACTIVE
A70: 57 | B70: VISHNUPRASATH T | C70: 33729 | D70: MALE | E70: Thavamani | F70: Sr. Network Engineer | G70: 1/97, Kilmettu st, Villvarani PO, Kalasapakkam taluk, Tiruvannamalai dt, Tamilnadu PIN-606906 | H70: 1/97, Kilmettu st, Villvarani PO, Kalasapakkam taluk, Tiruvannamalai dt, Tamilnadu PIN-606906 | I70: 44396 | K70: ACTIVE | L70: ACTIVE | N70: 11
A71: 58 | B71: Nagaranjan S | C71: 19.06.1981 | D71: MALE | E71: SUBBIAH G | F71: Linux Administrator | G71: 4\122,V.Sundaralingapuram,Pavali(PO),Virudhunagar(DT)-626103 | H71: 5\1, 1st floor,3rd cross street,BalajiNagar,Kolathur,Chennai-600099 | I71: 44396 | K71: ACTIVE | L71: ACTIVE | N71: 12
A72: 59 | B72: ELAMPARITHI SB | C72: 20-02-1986 | D72: MALE | E72: Balasubramanian.S | F72: Senior Network Engineer | G72: 77 - Mela Dhasappa Nayakkan Street , Kanagam Thottam ,East Gate,Thanjavur-613001 | H72: C5 - Orchid Screne Moovendar Nagar Extension, Old Perungalathur , Chennai - 600063 | I72: 44396 | K72: ACTIVE | L72: ACTIVE | N72: 13
A73: 60 | B73: GauriSankara Padhy | C73: 32400 | D73: MALE | E73: HARIHAR PADHY | F73: Linux Administrator | H73: PALURBUNGLOW 1ST LANE, BERHAMPUR,ODISHAPALURBUNGLOW 1ST LANE, BERHAMPUR,ODISHA | I73: 44417 | K73: ACTIVE | L73: ACTIVE
A74: 61 | B74: Karthick G | C74: 32831 | D74: MALE | E74: Ganesan | F74: Senior EUC Analyst | G74: 47A,Vallaneri,Koothandan Post,Melavaniyankudi,Sivaganga,Tamil Nadu-630561 | H74: G-02,Teja Residency-01,Coconut Garden Layout,Kodigehalli Main Road, Ayyappa Nagar,KR Puram, Bangalore-560036 | I74: 44419 | K74: ACTIVE | L74: ACTIVE | N74: 14
A75: 62 | B75: Venkatesham Kamtam | C75: 30627 | D75: MALE | E75: Sadula NIROOPA | F75: EUC Analyst | G75: 2-32/a Rahimkhanpet mdl- Ellanthakunta Dist- Karimnagar | H75: 1-5-426/11 Suryanagar old alwal Hyderabad | I75: 44419 | K75: ACTIVE | L75: ACTIVE
A76: 63 | B76: Ramarao Kongara | C76: 31108 | D76: MALE | E76: Venkateshwarlu kongara | F76: Senior Storage Administrator | G76: 6-472, adigoppula, Guntur, AP 522612 | H76: 6-472, adigoppula, Guntur, AP 522612 | I76: 44426 | K76: ACTIVE | L76: ACTIVE
A77: 64 | B77: Sambasivarao M | C77: 33024 | D77: MALE | E77: Perayya | F77: Sr Devops Engineers | G77: H No 11-7-6/42,Navodaya nagar,narsarao pet,Guntur,AP 522601 | H77: H No 11-7-6/42,Navodaya nagar,narsarao pet,Guntur,AP 522601 | I77: 44445 | K77: ACTIVE | L77: ACTIVE
A78: 65 | B78: K V Kannan | C78: 29774 | D78: MALE | E78: K C Venkata Kumar | F78: Windows and Assure Administrator | G78: New No.1,old no 43/351,Jyothi ramalingam street,Rajajipuram,Thiruvallur,TN 602001 | H78: New No.1,old no 43/351,Jyothi ramalingam street,Rajajipuram,Thiruvallur,TN 602001 | I78: 44446 | K78: ACTIVE | L78: ACTIVE | N78: 15
A79: 66 | B79: Thanigaivel.J | C79: 34698 | D79: MALE | E79: Jayavelu | F79: Network Engineer | G79: No 6,Load man street,varadharajan nagar,changalpet,chengalpattu,kanchipuram,TN 603002 | H79: No 6,Load man street,varadharajan nagar,changalpet,chengalpattu,kanchipuram,TN 603002 | I79: 44446 | K79: ACTIVE | L79: ACTIVE | N79: 16
A80: 67 | B80: Suprity Chandra | C80: 33838 | D80: FEMALE | E80: Subratha chandra | F80: HR Recruiter | G80: near nirsakalimandir,ganbadh,jarkhand 828205 | H80: near nirsakalimandir,ganbadh,jarkhand 828205 | I80: 44453 | K80: ACTIVE | L80: ACTIVE
A81: 68 | B81: Anil kumar Redd kusam | C81: 33181 | D81: MALE | E81: Pullareddy | F81: Associate Consultant | G81: H No 2-36,Jalalapuram,Singanamel mandal,Ananthpur district,AP 515425 | H81: H No 2-36,Jalalapuram,Singanamel mandal,Ananthpur district,AP 515425 | I81: 44459 | K81: ACTIVE | L81: ACTIVE | N81: 17
A82: 69 | B82: Balne Kishore | C82: 31307 | D82: MALE | E82: B Pandurangam | F82: Sr Software Engineer | G82: 24-3/48/A,Street no.8,Vimaladevi nagar,vishnupuri ext,Malkajgiri,Hyderabad,TS 500047 | H82: 24-3/48/A,Street no.8,Vimaladevi nagar,vishnupuri ext,Malkajgiri,Hyderabad,TS 500047 | I82: 44466 | K82: ACTIVE | L82: ACTIVE
A83: 70 | B83: Manzoor Ahamed | C83: 31191 | D83: MALE | E83: Syed Rahim | F83: Lead Devops Engineer | G83: D No 426,Karuppanannan house,T B Road,Sankari,Selam,Tamilnadu 637301 | H83: Ground floor,Padmalayam site No 24,4th cross,Vellinganton paradise layout,singa sandra,Bangalore 560068,Karnataka | I83: 44487 | K83: ACTIVE | L83: ACTIVE | N83: 18
A84: 71 | B84: Ramakrishna J Reddy | C84: 33048 | D84: MALE | E84: Satyanarayana Reddy | F84: SENIOR SAP ABAP CONSULTANT | G84: 7-20-1092/A,28th line,Sarada colony,Guntur 522002,AP | H84: 7-20-1092/A,28th line,Sarada colony,Guntur 522002,AP | I84: 44512 | K84: ACTIVE | L84: ACTIVE | N84: 19
A85: 72 | B85: Praveen Kumar Tandra | C85: 30287 | D85: MALE | E85: Ram reddy Tandra | F85: Sr.Linux Admin | G85: 1-156,Boinapally,Midjil,Mahabubnagar District,Telangan 509357 | H85: 303,CBR Enclave2,Road No.2,Triveni nagar,Balapur cross roads,Hyderabad,Telangana 500097 | I85: 44536 | K85: ACTIVE | L85: ACTIVE | N85: 20
A86: 73 | B86: KAMBADASAN KALIDASAN | C86: 34959 | D86: MALE | E86: Kalidas | F86: NDC Engineer | G86: No.2 Vadakkupet,Ambagaratur,Karaikar,Puducheri 609601 | H86: No.2 Vadakkupet,Ambagaratur,Karaikar,Puducheri 609601 | I86: 44559 | K86: ACTIVE | L86: ACTIVE
A87: 74 | B87: Nagarjun KV | C87: 31644 | D87: MALE | E87: Arpitha R | F87: Technical Consultant | G87: #66\E, 3rd C Main, Raghavendra Layout, Hulimavu, Bangalore - 560076 | H87: #66\E, 3rd C Main, Raghavendra Layout, Hulimavu, Bangalore - 560076 | I87: 44564 | K87: ACTIVE | L87: ACTIVE | N87: 21
A88: 75 | B88: Boopathi Palani | C88: 33749 | D88: MALE | E88: M.Palani | F88: Senior Technology Analyst | G88: kadayapatti village, Thippampatti PO, Dharmapuri Dist 635202 | H88: kadayapatti village, Thippampatti PO, Dharmapuri Dist 635202 | I88: 44564 | K88: ACTIVE | L88: ACTIVE | N88: 22
A89: 76 | B89: JNANESWARARAO G | C89: 31527 | D89: MALE | E89: Subba Rao | F89: SENIOR SOFTWARE ENGINEER- MongoDB DBA | G89: H No 1-57/338,Sreeram nagar,Kondapur,Hyderabad 500084 | H89: H No 1-57/338,Sreeram nagar,Kondapur,Hyderabad 500084 | I89: 44562 | K89: ACTIVE | L89: ACTIVE | N89: 23
A90: 77 | B90: Shridhar Madlur | C90: 33977 | D90: MALE | E90: Hanamantappa Madlur | F90: Network Engineer | G90: Devaraj Aras Colony, Behind Eshwar Park, Koppal - 583231,Bangalore | H90: No. 36, Hari Nivas, 1st Block, 1st Main, BEL L/O, Vidyaranyapura Bengaluru-560097. | I90: 44594 | K90: ACTIVE | L90: ACTIVE | N90: 24
A91: 78 | B91: Samarjit Saha | C91: 09-05-1978 | D91: MALE | E91: Gopal Chandra Saha | F91: Devopers Specialist | G91: 110,Sucheta Nagar-2, Rajmahal Apartment, 3rd floor,P.O:Haltu, Dist: South 24 Paraganas,City:Kolkata. State:West Bengal | H91: 110,Sucheta Nagar-2, Rajmahal Apartment, 3rd floor,P.O:Haltu, Dist: South 24 Paraganas,City:Kolkata. State:West Bengal | I91: 44594 | K91: ACTIVE | L91: ACTIVE | N91: 25
A92: 79 | B92: Narasimha rao Gurazala | C92: 33292 | D92: MALE | E92: G seshaiah | F92: Software Developer | G92: Hno 15-21-237/1,Flat no G2,sattenapally towers,Balaji Nagar,Kukatpally,Hyderabad,500072 | H92: Hno 15-21-237/1,Flat no G2,sattenapally towers,Balaji Nagar,Kukatpally,Hyderabad,500072 | I92: 44602 | K92: ACTIVE | L92: ACTIVE | N92: 26
A93: 80 | B93: Mahanth Devasani | C93: 33301 | D93: MALE | E93: KAILASAM DEVASANI | F93: Information Security Engineer | G93: 103, Sri datta sai residency, Budhha Nagar, Boduppal,Hyderabad | H93: H.no: 4-69/55/5/d/6, Vidyaranyapuri-3, Near apolo reach hospital, Karimnagar | I93: 44606 | K93: ACTIVE | L93: ACTIVE | N93: 27
A94: 81 | B94: YAMUNA S | C94: 25/08/1992 | D94: FEMALE | E94: N VAMSI KRISHNA | F94: Sr Software Engineer | G94: Door no:22-965/6,kameshwar Nagar,Near Moruganipalli Road, Chittoor-517001,Andhrapradesh | H94: Door no:22-965/6,kameshwar Nagar,Near Moruganipalli Road, Chittoor-517001,Andhrapradesh | I94: 44631 | K94: ACTIVE | L94: ACTIVE | N94: 28
A95: 82 | B95: Chetan Madhukar Mundhe | C95: 31430 | D95: MALE | E95: Madhukar kondiran munde | F95: Technical Consultant | G95: B 41, Mahaveer Park, PUNE, satara road, Bibwewadi pune, 411037 | H95: 14 gulmohar colony,Jti Road, Shanupuri, Satara, 415002 | I95: 44635 | K95: ACTIVE | L95: ACTIVE | N95: 29
A96: 83 | B96: Sathish Kumar dhandu | C96: 33257 | D96: MALE | E96: Shiva shankar | F96: Technical Consultant | G96: 1/3A,BC colony,Lachannapally,Ananthapur,AP 515401 | H96: 1/3A,BC colony,Lachannapally,Ananthapur,AP 515401 | I96: 44636 | K96: ACTIVE | L96: ACTIVE | N96: 30
A97: 84 | B97: Praveen Kumar GATTU | C97: 33606 | D97: MALE | E97: G Muniratnam | F97: System Administrator | G97: 30-104, Kalyanapuram,st colony, puttur, Chittoor, AP 517583 | H97: 30-104, Kalyanapuram,st colony, puttur, Chittoor, AP 517583 | I97: 44648 | K97: ACTIVE | L97: ACTIVE | N97: 31
A98: 85 | B98: Vinoth Vairavan | C98: 31514 | D98: MALE | E98: Vairavan | F98: SR, NETWORK ENGINEER | G98: 127/69,Anna nagar,Pattu kottal,Thanjavur district,Tamil nadu,614601 | H98: No.21,Neminathal nagar,Shakthi nagar ext.,Back side Annie School,Mudichur,Chennai-48 | I98: 44657 | K98: ACTIVE | L98: ACTIVE | N98: 32
A99: 86 | B99: Govarthanan TK | C99: 31863 | D99: MALE | E99: Kumaraswamy papaiya | F99: IT Project Manager | G99: 94A,AK Abhinayam Appts,F Block,1st floor,2nd main road,Thankikachalam nagar west,Ponniya manmedeo,chennai,Tamil nadu,600110 | H99: 94A,AK Abhinayam Appts,F Block,1st floor,2nd main road,Thankikachalam nagar west,Ponniya manmedeo,chennai,Tamil nadu,600110 | I99: 44662 | K99: ACTIVE | L99: ACTIVE | N99: 33
A100: 87 | B100: LaxmiSoujanya Mudunuri | C100: 33107 | D100: FEMALE | E100: Venkata Satya narayana Raju | F100: Senior Middleware Consultant | G100: 25-10-20,Fire station opposite road,Beside sai baba temple,NR Pet,W G Dt.,Eluru,AP 534006 | H100: 25-10-20,Fire station opposite road,Beside sai baba temple,NR Pet,W G Dt.,Eluru,AP 534006 | I100: 44671 | K100: ACTIVE | L100: ACTIVE | N100: 34
A118: BITS-575 | B118: Reno Vijayan | C118: 31699 | D118: MALE | E118: Vijayan IR | F118: VMware Administrator | G118: Iyrada House,Anchery post,Trissul,Kerala 680006 | H118: Iyrada House,Anchery post,Trissul,Kerala 680006 | I118: 44348 | N118: 100312757617 | O118: N/A | P118: =B118 -> Reno Vijayan | Q118: 30 | R118: =VLOOKUP(A118,'[4]Pay sheet-MARCH- 2022'!$C$7:$AF$147,10,0) -> 31 | S118: N/A | T118: 61740 | U118: =VLOOKUP(A118,'[4]Pay sheet-MARCH- 2022'!$C$7:$AF$147,11,0) -> 37044 | V118: 0 | W118: 0 | X118: =Y118+Z118+AA118+AB118 -> 24696 | Y118: =VLOOKUP(A118,'[4]Pay sheet-MARCH- 2022'!$C$7:$AF$147,12,0) -> 14817.6 | Z118: =VLOOKUP(A118,'[4]Pay sheet-MARCH- 2022'!$C$7:$AF$147,13,0) -> 2083 | AA118: =VLOOKUP(A118,'[4]Pay sheet-MARCH- 2022'!$C$7:$AF$147,14,0) -> 2083 | AB118: =VLOOKUP(A118,'[4]Pay sheet-MARCH- 2022'!$C$7:$AF$147,15,0) -> 5712.4 | AC118: =U118+X118 -> 61740 | AD118: =VLOOKUP(A118,'[4]Pay sheet-MARCH- 2022'!$C$7:$AF$147,18,0) -> 1441.609 | AE118: =VLOOKUP(A118,'[4]Pay sheet-MARCH- 2022'!$C$7:$AF$147,19,0) -> 1781.8164 | AF118: =VLOOKUP(A118,'[4]Pay sheet-MARCH- 2022'!$C$7:$AF$147,20,0) -> 3087 | AG118: =VLOOKUP(A118,'[4]Pay sheet-MARCH- 2022'!$C$7:$AF$147,22,0) -> 0 | AH118: =AC118+AD118+AE118+AF118+AG118 -> 68050.425 | AI118: 0 | AJ118: =VLOOKUP(A118,'[4]Pay sheet-MARCH- 2022'!$C$7:$AF$147,26,0) -> 1800 | AK118: =VLOOKUP(A118,'[4]Pay sheet-MARCH- 2022'!$C$7:$AF$147,25,0) -> 200 | AL118: =VLOOKUP(A118,'[4]Pay sheet-MARCH- 2022'!$C$7:$AF$147,24,0) -> 0 | AM118: =VLOOKUP(A118,'[4]Pay sheet-MARCH- 2022'!$C$7:$AF$147,27,0) -> 391.78785 | AN118: =AI118+AJ118+AK118+AL118+AM118 -> 2391.7878 | AO118: =AH118-AN118 -> 65658.638 | AP118: 44686 | AQ118: Kotak Mahindra | AR118: 6712401159 | AU118: 15 | AV118: 2
A119: BITS-582 | B119: SathishKumar V | C119: 32918 | D119: MALE | E119: M Venkatesam | F119: Lead Administrator | G119: #789, Balaji Nager Tirumala, Tirupathi(M), Chittoor(Dist) AP-517504 | H119: #789, Balaji Nager Tirumala, Tirupathi(M), Chittoor(Dist) AP-517504 | I119: 44348 | N119: 101130825899 | O119: N/A | P119: =B119 -> SathishKumar V | Q119: 30 | R119: =VLOOKUP(A119,'[4]Pay sheet-MARCH- 2022'!$C$7:$AF$147,10,0) -> 31 | S119: N/A | T119: 117354 | U119: =VLOOKUP(A119,'[4]Pay sheet-MARCH- 2022'!$C$7:$AF$147,11,0) -> 70412.4 | V119: 0 | W119: 0 | X119: =Y119+Z119+AA119+AB119 -> 46941.6 | Y119: =VLOOKUP(A119,'[4]Pay sheet-MARCH- 2022'!$C$7:$AF$147,12,0) -> 28164.96 | Z119: =VLOOKUP(A119,'[4]Pay sheet-MARCH- 2022'!$C$7:$AF$147,13,0) -> 2083 | AA119: =VLOOKUP(A119,'[4]Pay sheet-MARCH- 2022'!$C$7:$AF$147,14,0) -> 2083 | AB119: =VLOOKUP(A119,'[4]Pay sheet-MARCH- 2022'!$C$7:$AF$147,15,0) -> 14610.64 | AC119: =U119+X119 -> 117354 | AD119: =VLOOKUP(A119,'[4]Pay sheet-MARCH- 2022'!$C$7:$AF$147,18,0) -> 1441.609 | AE119: =VLOOKUP(A119,'[4]Pay sheet-MARCH- 2022'!$C$7:$AF$147,19,0) -> 3386.8364 | AF119: =VLOOKUP(A119,'[4]Pay sheet-MARCH- 2022'!$C$7:$AF$147,20,0) -> 5867.7 | AG119: =VLOOKUP(A119,'[4]Pay sheet-MARCH- 2022'!$C$7:$AF$147,22,0) -> 0 | AH119: =AC119+AD119+AE119+AF119+AG119 -> 128050.15 | AI119: 0 | AJ119: =VLOOKUP(A119,'[4]Pay sheet-MARCH- 2022'!$C$7:$AF$147,26,0) -> 1800 | AK119: =VLOOKUP(A119,'[4]Pay sheet-MARCH- 2022'!$C$7:$AF$147,25,0) -> 200 | AL119: =VLOOKUP(A119,'[4]Pay sheet-MARCH- 2022'!$C$7:$AF$147,24,0) -> 0 | AM119: =VLOOKUP(A119,'[4]Pay sheet-MARCH- 2022'!$C$7:$AF$147,27,0) -> 391.78785 | AN119: =AI119+AJ119+AK119+AL119+AM119 -> 2391.7878 | AO119: =AH119-AN119 -> 125658.36 | AP119: 44686 | AQ119: AXIS BANK | AR119: 917010039649735 | AU119: 29 | AV119: 3
A120: BITS-588 | B120: Kutagolla Mohazzer | C120: 14/06/1996 | D120: MALE | E120: Khaleel Saheb | F120: Sr. Software Engineer | G120: 2-99,MBT Road,Angallu,Andhra Pradesh -517325 | H120: 2-99,MBT Road,Angallu,Andhra Pradesh -517325 | I120: 44363 | N120: 101701757176 | O120: N/A | P120: =B120 -> Kutagolla Mohazzer | Q120: 30 | R120: =VLOOKUP(A120,'[4]Pay sheet-MARCH- 2022'!$C$7:$AF$147,10,0) -> 31 | S120: N/A | T120: 66374 | U120: =VLOOKUP(A120,'[4]Pay sheet-MARCH- 2022'!$C$7:$AF$147,11,0) -> 39824.4 | V120: 0 | W120: 0 | X120: =Y120+Z120+AA120+AB120 -> 26549.6 | Y120: =VLOOKUP(A120,'[4]Pay sheet-MARCH- 2022'!$C$7:$AF$147,12,0) -> 15929.76 | Z120: =VLOOKUP(A120,'[4]Pay sheet-MARCH- 2022'!$C$7:$AF$147,13,0) -> 2083 | AA120: =VLOOKUP(A120,'[4]Pay sheet-MARCH- 2022'!$C$7:$AF$147,14,0) -> 2083 | AB120: =VLOOKUP(A120,'[4]Pay sheet-MARCH- 2022'!$C$7:$AF$147,15,0) -> 6453.84 | AC120: =U120+X120 -> 66374 | AD120: =VLOOKUP(A120,'[4]Pay sheet-MARCH- 2022'!$C$7:$AF$147,18,0) -> 1441.609 | AE120: =VLOOKUP(A120,'[4]Pay sheet-MARCH- 2022'!$C$7:$AF$147,19,0) -> 1915.5536 | AF120: =VLOOKUP(A120,'[4]Pay sheet-MARCH- 2022'!$C$7:$AF$147,20,0) -> 3318.7 | AG120: =VLOOKUP(A120,'[4]Pay sheet-MARCH- 2022'!$C$7:$AF$147,22,0) -> 0 | AH120: =AC120+AD120+AE120+AF120+AG120 -> 73049.863 | AI120: 0 | AJ120: =VLOOKUP(A120,'[4]Pay sheet-MARCH- 2022'!$C$7:$AF$147,26,0) -> 1800 | AK120: =VLOOKUP(A120,'[4]Pay sheet-MARCH- 2022'!$C$7:$AF$147,25,0) -> 200 | AL120: =VLOOKUP(A120,'[4]Pay sheet-MARCH- 2022'!$C$7:$AF$147,24,0) -> 0 | AM120: =VLOOKUP(A120,'[4]Pay sheet-MARCH- 2022'!$C$7:$AF$147,27,0) -> 391.78785 | AN120: =AI120+AJ120+AK120+AL120+AM120 -> 2391.7878 | AO120: =AH120-AN120 -> 70658.075 | AP120: 44686 | AQ120: AXIS BANK | AR120: 917010033244147 | AU120: 48 | AV120: 9
A121: BITS-610 | B121: Kannan Selvakumar | C121: 22/03/1987 | D121: MALE | E121: SELVA KUMAR.S | F121: Senior Associate consultant | G121: KANNAN. S NO 20C, ROAD ST, NAINAMPATTI, VELLANDIVALASU (PO), EDAPPADI, SALEM (Dt) PIN- 637101 | H121: NO 2 2ND FLOOR, NARAYANAN ST, LORD SRINIVASA COLONY, PALLAVARAM,CHENNAI. PIN : 600043 | I121: 44396 | N121: 100894069398 | O121: N/A | P121: =B121 -> Kannan Selvakumar | Q121: 30 | R121: =VLOOKUP(A121,'[4]Pay sheet-MARCH- 2022'!$C$7:$AF$147,10,0) -> 31 | S121: N/A | T121: 57105 | U121: =VLOOKUP(A121,'[4]Pay sheet-MARCH- 2022'!$C$7:$AF$147,11,0) -> 34263 | V121: 0 | W121: 0 | X121: =Y121+Z121+AA121+AB121 -> 22842 | Y121: =VLOOKUP(A121,'[4]Pay sheet-MARCH- 2022'!$C$7:$AF$147,12,0) -> 13705.2 | Z121: =VLOOKUP(A121,'[4]Pay sheet-MARCH- 2022'!$C$7:$AF$147,13,0) -> 2083 | AA121: =VLOOKUP(A121,'[4]Pay sheet-MARCH- 2022'!$C$7:$AF$147,14,0) -> 2083 | AB121: =VLOOKUP(A121,'[4]Pay sheet-MARCH- 2022'!$C$7:$AF$147,15,0) -> 4970.8 | AC121: =U121+X121 -> 57105 | AD121: =VLOOKUP(A121,'[4]Pay sheet-MARCH- 2022'!$C$7:$AF$147,18,0) -> 1441.609 | AE121: =VLOOKUP(A121,'[4]Pay sheet-MARCH- 2022'!$C$7:$AF$147,19,0) -> 1648.0503 | AF121: =VLOOKUP(A121,'[4]Pay sheet-MARCH- 2022'!$C$7:$AF$147,20,0) -> 2855.25 | AG121: =VLOOKUP(A121,'[4]Pay sheet-MARCH- 2022'!$C$7:$AF$147,22,0) -> 0 | AH121: =AC121+AD121+AE121+AF121+AG121 -> 63049.909 | AI121: 0 | AJ121: =VLOOKUP(A121,'[4]Pay sheet-MARCH- 2022'!$C$7:$AF$147,26,0) -> 1800 | AK121: =VLOOKUP(A121,'[4]Pay sheet-MARCH- 2022'!$C$7:$AF$147,25,0) -> 200 | AL121: =VLOOKUP(A121,'[4]Pay sheet-MARCH- 2022'!$C$7:$AF$147,24,0) -> 0 | AM121: =VLOOKUP(A121,'[4]Pay sheet-MARCH- 2022'!$C$7:$AF$147,27,0) -> 335 | AN121: =AI121+AJ121+AK121+AL121+AM121 -> 2335 | AO121: =AH121-AN121 -> 60714.909 | AP121: 44686 | AQ121: HDFC BANK | AR121: 50100173957961 | AU121: 56 | AV121: 14
A122: BITS-637 | B122: Sambasivarao M | C122: 33024 | D122: MALE | E122: Perayya | F122: Sr Devops Engineers | G122: H No 11-7-6/42,Navodaya nagar,narsarao pet,Guntur,AP 522601 | H122: H No 11-7-6/42,Navodaya nagar,narsarao pet,Guntur,AP 522601 | I122: 44445 | N122: 101380564421 | O122: N/A | P122: Sambasivarao M | Q122: 30 | R122: =VLOOKUP(A122,'[4]Pay sheet-MARCH- 2022'!$C$7:$AF$147,10,0) -> 31 | S122: N/A | T122: 94181 | U122: =VLOOKUP(A122,'[4]Pay sheet-MARCH- 2022'!$C$7:$AF$147,11,0) -> 56508.6 | V122: 0 | W122: 0 | X122: =Y122+Z122+AA122+AB122 -> 37672.4 | Y122: =VLOOKUP(A122,'[4]Pay sheet-MARCH- 2022'!$C$7:$AF$147,12,0) -> 22603.44 | Z122: =VLOOKUP(A122,'[4]Pay sheet-MARCH- 2022'!$C$7:$AF$147,13,0) -> 2083 | AA122: =VLOOKUP(A122,'[4]Pay sheet-MARCH- 2022'!$C$7:$AF$147,14,0) -> 2083 | AB122: =VLOOKUP(A122,'[4]Pay sheet-MARCH- 2022'!$C$7:$AF$147,15,0) -> 10902.96 | AC122: =U122+X122 -> 94181 | AD122: =VLOOKUP(A122,'[4]Pay sheet-MARCH- 2022'!$C$7:$AF$147,18,0) -> 1441.609 | AE122: =VLOOKUP(A122,'[4]Pay sheet-MARCH- 2022'!$C$7:$AF$147,19,0) -> 2718.0637 | AF122: =VLOOKUP(A122,'[4]Pay sheet-MARCH- 2022'!$C$7:$AF$147,20,0) -> 4709.05 | AG122: =VLOOKUP(A122,'[4]Pay sheet-MARCH- 2022'!$C$7:$AF$147,22,0) -> 0 | AH122: =AC122+AD122+AE122+AF122+AG122 -> 103049.72 | AI122: 0 | AJ122: =VLOOKUP(A122,'[4]Pay sheet-MARCH- 2022'!$C$7:$AF$147,26,0) -> 1800 | AK122: =VLOOKUP(A122,'[4]Pay sheet-MARCH- 2022'!$C$7:$AF$147,25,0) -> 200 | AL122: =VLOOKUP(A122,'[4]Pay sheet-MARCH- 2022'!$C$7:$AF$147,24,0) -> 0 | AM122: =VLOOKUP(A122,'[4]Pay sheet-MARCH- 2022'!$C$7:$AF$147,27,0) -> 224 | AN122: =AI122+AJ122+AK122+AL122+AM122 -> 2224 | AO122: =AH122-AN122 -> 100825.72 | AP122: 44686 | AQ122: HDFC BANK | AR122: 50100302195870 | AU122: 64 | AV122: 19

Sheet 04-22Master
A3: FORM - XIII REGISTER OF WORKMEN EMPLOYED BY CONTRACTOR
B4: (Vide Rule 75 of Contract Labour (Regulation and Abolition) Central/Karnataka Rules 1974)
A5: Name and address of Contractor: | F5: Burgeon IT Services Pvt.Ltd. | W5: Name and address of Establishemnt in/ under which contract is carried on: | AK5: =F5 -> Burgeon IT Services Pvt.Ltd.
F6: Siri Mansion LIGB 436 Dr.A S Rao Nagar,Hyderabad | AK6: =F6 -> Siri Mansion LIGB 436 Dr.A S Rao Nagar,Hyderabad
AK7: =F7 -> 0
A8: Nature and location of work: | F8: IT SUPPORTIVE SERVICES & BANGALORE STP | AU8: to paste on left side in "A" column.
A10: Wage period: Monthly | D10: 44652 | AF10: Name and address of Principal Employer: | AK10: INFOSYS LTD.IL Bangalore STP Park - I
AK11: No.45&46,3rd Cross,Electronic City,BANGALORE,KARNATAKA
A13: 1 | B13: 2 | C13: 3 | D13: 4 | E13: 5 | F13: 6 | G13: 7 | H13: 8 | I13: 9 | J13: 10 | K13: 11 | L13: 12 | M13: 13 | N13: 14 | O13: 15 | P13: 16 | Q13: 17 | R13: 18 | S13: 19 | T13: 20 | U13: 21 | V13: 22 | W13: 23 | X13: 24 | Y13: 25 | Z13: 26 | AA13: 27 | AB13: 28 | AC13: 29 | AD13: 30 | AE13: 31 | AF13: 32 | AG13: 33 | AH13: 34 | AI13: 35 | AJ13: 36 | AK13: 37 | AL13: 38 | AM13: 39 | AN13: 40 | AO13: 41 | AP13: 42 | AQ13: 43 | AR13: 44 | AS13: 45
B14: Name of Workman | C14: Age | D14: Sex | E14: Father's /Husband Name | F14: Designation / Nature of Work Done | G14: Permanent Address | H14: Local Address | I14: Date of Commencement of Employment | J14: Signature or thumb impression of Workman | K14: Date of termination of Employment | L14: Reasons for termination | M14: Remarks | N14: EPF Number | O14: ESI Number | P14: Name of Workman | Q14: NO.OF DAYS | R14: NO OF DAYS PAYABLE | S14: Unit of work done | T14: Monthly rate of wages/ piece rate | U14: Basic wages | V14: Dearness Allowances | W14: Over time | X14: Other cash payments (Nature of payments to be indicated) | Y14: HRA | Z14: CONVEYANCE | AA14: MEDICAL ALLOWANCES | AB14: SPECIAL ALLOWNANCES | AC14: Total | AD14: BONUS | AE14: GRATUITY | AF14: LTA/L.E | AG14: ARREAR AMOUNT | AH14: TOTAL AMOUNT | AI14: Deductions, if any, (Indicate nature) | AO14: Net Amount paid | AP14: Time and Date of Payment | AQ14: Place of Payment | AR14: Signature/Thumb Impression of workman | AS14: Initial of Contractor or his representative | AU14: Serial No. in the Register of Workmen
AI15: ESI | AJ15: PF | AK15: PT | AL15: TDS | AM15: MED | AN15: Total Deductions
A16: BITS-485 | B16: AKASH DEEP CHUNAP | C16: 33695 | D16: MALE | E16: Priyanka Chunap | F16: Network security engineer | G16: H.No 4-3-216/2A,Narasimha Nagar, Bhainsa, Nirmal District, 504 103 | H16: Selene Court, Sree Vensai Projects, Flat 404, Kompally, 500014 | I16: 44105 | N16: 101629256413 | O16: N/A | P16: =B16 -> AKASH DEEP CHUNAP | Q16: 30 | R16: =VLOOKUP(A16,'[5]Pay sheet-APRIL- 2022'!$C$7:$AF$137,10,0) -> 30 | S16: N/A | T16: 135892 | U16: =VLOOKUP(A16,'[5]Pay sheet-APRIL- 2022'!$C$7:$AF$137,11,0) -> 81535.2 | V16: 0 | W16: 0 | X16: =Y16+Z16+AA16+AB16 -> 54469.8 | Y16: =VLOOKUP(A16,'[5]Pay sheet-APRIL- 2022'!$C$7:$AF$137,12,0) -> 32614.08 | Z16: =VLOOKUP(A16,'[5]Pay sheet-APRIL- 2022'!$C$7:$AF$137,13,0) -> 2083 | AA16: =VLOOKUP(A16,'[5]Pay sheet-APRIL- 2022'!$C$7:$AF$137,14,0) -> 2083 | AB16: =VLOOKUP(A16,'[5]Pay sheet-APRIL- 2022'!$C$7:$AF$137,15,0) -> 17689.72 | AC16: =U16+X16 -> 136005 | AD16: =VLOOKUP(A16,'[5]Pay sheet-APRIL- 2022'!$C$7:$AF$137,18,0) -> 1554.609 | AE16: =VLOOKUP(A16,'[5]Pay sheet-APRIL- 2022'!$C$7:$AF$137,19,0) -> 3921.8431 | AF16: =VLOOKUP(A16,'[5]Pay sheet-APRIL- 2022'!$C$7:$AF$137,20,0) -> 6794.6 | AG16: =VLOOKUP(A16,'[5]Pay sheet-APRIL- 2022'!$C$7:$AF$137,22,0) -> 0 | AH16: =AC16+AD16+AE16+AF16+AG16 -> 148276.05 | AJ16: =VLOOKUP(A16,'[4]Pay sheet-MARCH- 2022'!$C$7:$AF$147,26,0) -> 1800 | AK16: =VLOOKUP(A16,'[4]Pay sheet-MARCH- 2022'!$C$7:$AF$147,25,0) -> 200 | AL16: =VLOOKUP(A16,'[5]Pay sheet-APRIL- 2022'!$C$7:$AF$137,24,0) -> 0 | AM16: =VLOOKUP(A16,'[4]Pay sheet-MARCH- 2022'!$C$7:$AF$147,27,0) -> 0 | AN16: =AI16+AJ16+AK16+AL16+AM16 -> 2000 | AO16: =AH16-AN16 -> 146276.05 | AP16: 44686 | AQ16: SBIN | AR16: A/C 621 732 836 92 | AU16: 12 | AV16: 1
A17: BITS-565 | B17: RajasekharReddy KN | C17: 30837 | D17: MALE | E17: Narayana Reddy | F17: Citrix Administrator | G17: 3-48, Boorlapalli, PTM Madalam, Tamballapalli, Boorlapalle, Chittoor, AP 517370 | H17: 3-48, Boorlapalli, PTM Madalam, Tamballapalli, Boorlapalle, Chittoor, AP 517370 | I17: 44326 | N17: 100432313742 | O17: N/A | P17: =B17 -> RajasekharReddy KN | Q17: 30 | R17: =VLOOKUP(A17,'[5]Pay sheet-APRIL- 2022'!$C$7:$AF$137,10,0) -> 30 | S17: N/A | T17: 66374 | U17: =VLOOKUP(A17,'[5]Pay sheet-APRIL- 2022'!$C$7:$AF$137,11,0) -> 39824.4 | V17: 0 | W17: 0 | X17: =Y17+Z17+AA17+AB17 -> 26662.6 | Y17: =VLOOKUP(A17,'[5]Pay sheet-APRIL- 2022'!$C$7:$AF$137,12,0) -> 15929.76 | Z17: =VLOOKUP(A17,'[5]Pay sheet-APRIL- 2022'!$C$7:$AF$137,13,0) -> 2083 | AA17: =VLOOKUP(A17,'[5]Pay sheet-APRIL- 2022'!$C$7:$AF$137,14,0) -> 2083 | AB17: =VLOOKUP(A17,'[5]Pay sheet-APRIL- 2022'!$C$7:$AF$137,15,0) -> 6566.84 | AC17: =U17+X17 -> 66487 | AD17: =VLOOKUP(A17,'[5]Pay sheet-APRIL- 2022'!$C$7:$AF$137,18,0) -> 1554.609 | AE17: =VLOOKUP(A17,'[5]Pay sheet-APRIL- 2022'!$C$7:$AF$137,19,0) -> 1915.5536 | AF17: =VLOOKUP(A17,'[5]Pay sheet-APRIL- 2022'!$C$7:$AF$137,20,0) -> 3318.7 | AG17: =VLOOKUP(A17,'[5]Pay sheet-APRIL- 2022'!$C$7:$AF$137,22,0) -> 0 | AH17: =AC17+AD17+AE17+AF17+AG17 -> 73275.863 | AI17: 0 | AJ17: =VLOOKUP(A17,'[4]Pay sheet-MARCH- 2022'!$C$7:$AF$147,26,0) -> 1800 | AK17: =VLOOKUP(A17,'[4]Pay sheet-MARCH- 2022'!$C$7:$AF$147,25,0) -> 200 | AL17: =VLOOKUP(A17,'[5]Pay sheet-APRIL- 2022'!$C$7:$AF$137,24,0) -> 0 | AM17: =VLOOKUP(A17,'[4]Pay sheet-MARCH- 2022'!$C$7:$AF$147,27,0) -> 391.78785 | AN17: =AI17+AJ17+AK17+AL17+AM17 -> 2391.7878 | AO17: =AH17-AN17 -> 70884.075 | AP17: 44686 | AQ17: ICICI | AR17: 272601504387 | AU17: 37 | AV17: 2
A18: BITS-566 | B18: Moulika GM | C18: 35558 | D18: FEMALE | E18: Maniganda Charan Kumar | F18: Ansible Developer | G18: 12A/22A,METTU,TIRUTTANI | H18: BANGALORE, ELECTRONIC CITY,PHASE1 | I18: 44327 | N18: 101695261774 | O18: N/A | P18: =B18 -> Moulika GM | Q18: 30 | R18: =VLOOKUP(A18,'[5]Pay sheet-APRIL- 2022'!$C$7:$AF$137,10,0) -> 30 | S18: N/A | T18: 20029 | U18: =VLOOKUP(A18,'[5]Pay sheet-APRIL- 2022'!$C$7:$AF$137,11,0) -> 12017.4 | V18: 0 | W18: 0 | X18: =Y18+Z18+AA18+AB18 -> 8124.6 | Y18: =VLOOKUP(A18,'[5]Pay sheet-APRIL- 2022'!$C$7:$AF$137,12,0) -> 4806.96 | Z18: =VLOOKUP(A18,'[5]Pay sheet-APRIL- 2022'!$C$7:$AF$137,13,0) -> 2083 | AA18: =VLOOKUP(A18,'[5]Pay sheet-APRIL- 2022'!$C$7:$AF$137,14,0) -> 2083 | AB18: =VLOOKUP(A18,'[5]Pay sheet-APRIL- 2022'!$C$7:$AF$137,15,0) -> -848.36 | AC18: =U18+X18 -> 20142 | AD18: =VLOOKUP(A18,'[5]Pay sheet-APRIL- 2022'!$C$7:$AF$137,18,0) -> 1554.609 | AE18: =VLOOKUP(A18,'[5]Pay sheet-APRIL- 2022'!$C$7:$AF$137,19,0) -> 578.03694 | AF18: =VLOOKUP(A18,'[5]Pay sheet-APRIL- 2022'!$C$7:$AF$137,20,0) -> 1001.45 | AG18: =VLOOKUP(A18,'[5]Pay sheet-APRIL- 2022'!$C$7:$AF$137,22,0) -> 0 | AH18: =AC18+AD18+AE18+AF18+AG18 -> 23276.096 | AI18: 0 | AJ18: =VLOOKUP(A18,'[4]Pay sheet-MARCH- 2022'!$C$7:$AF$147,26,0) -> 1442 | AK18: =VLOOKUP(A18,'[4]Pay sheet-MARCH- 2022'!$C$7:$AF$147,25,0) -> 200 | AL18: =VLOOKUP(A18,'[5]Pay sheet-APRIL- 2022'!$C$7:$AF$137,24,0) -> 0 | AM18: =VLOOKUP(A18,'[4]Pay sheet-MARCH- 2022'!$C$7:$AF$147,27,0) -> 391.78785 | AN18: =AI18+AJ18+AK18+AL18+AM18 -> 2033.7878 | AO18: =AH18-AN18 -> 21242.308 | AP18: 44686 | AQ18: Indian Bank | AR18: 6685853376 | AU18: 38 | AV18: 3
A19: BITS-567 | B19: AsokKumar J | C19: 32274 | D19: MALE | E19: J.Prabhakar Reddt | F19: Senior Middleware Administrator (MQ & Kafka) | G19: #303, Dhanunjaya Apartment, Dasarahalli Main Road, Hebbal,Bangalore-560024. | H19: 2-88, S/o Juturu Prabhakar Reddy, Gunipalli, Bukkapatnam, Anantapur, Andra Pradesh-515154 | I19: 44328 | N19: 101695261742 | O19: N/A | P19: =B19 -> AsokKumar J | Q19: 30 | R19: =VLOOKUP(A19,'[5]Pay sheet-APRIL- 2022'!$C$7:$AF$137,10,0) -> 28 | S19: N/A | T19: 121988 | U19: =VLOOKUP(A19,'[5]Pay sheet-APRIL- 2022'!$C$7:$AF$137,11,0) -> 68313.28 | V19: 0 | W19: 0 | X19: =Y19+Z19+AA19+AB19 -> 45655.187 | Y19: =VLOOKUP(A19,'[5]Pay sheet-APRIL- 2022'!$C$7:$AF$137,12,0) -> 27325.312 | Z19: =VLOOKUP(A19,'[5]Pay sheet-APRIL- 2022'!$C$7:$AF$137,13,0) -> 1944 | AA19: =VLOOKUP(A19,'[5]Pay sheet-APRIL- 2022'!$C$7:$AF$137,14,0) -> 1944 | AB19: =VLOOKUP(A19,'[5]Pay sheet-APRIL- 2022'!$C$7:$AF$137,15,0) -> 14441.875 | AC19: =U19+X19 -> 113968.47 | AD19: =VLOOKUP(A19,'[5]Pay sheet-APRIL- 2022'!$C$7:$AF$137,18,0) -> 1554.609 | AE19: =VLOOKUP(A19,'[5]Pay sheet-APRIL- 2022'!$C$7:$AF$137,19,0) -> 3285.8688 | AF19: =VLOOKUP(A19,'[5]Pay sheet-APRIL- 2022'!$C$7:$AF$137,20,0) -> 5692.7733 | AG19: =VLOOKUP(A19,'[5]Pay sheet-APRIL- 2022'!$C$7:$AF$137,22,0) -> 0 | AH19: =AC19+AD19+AE19+AF19+AG19 -> 124501.72 | AI19: 0 | AJ19: =VLOOKUP(A19,'[4]Pay sheet-MARCH- 2022'!$C$7:$AF$147,26,0) -> 1800 | AK19: =VLOOKUP(A19,'[4]Pay sheet-MARCH- 2022'!$C$7:$AF$147,25,0) -> 200 | AL19: =VLOOKUP(A19,'[5]Pay sheet-APRIL- 2022'!$C$7:$AF$137,24,0) -> 0 | AM19: =VLOOKUP(A19,'[4]Pay sheet-MARCH- 2022'!$C$7:$AF$147,27,0) -> 391.78785 | AN19: =AI19+AJ19+AK19+AL19+AM19 -> 2391.7878 | AO19: =AH19-AN19 -> 122109.93 | AP19: 44686 | AQ19: HDFC | AR19: 50100397382442 | AU19: 39 | AV19: 4
A20: BITS-577 | B20: Majed Khan | C20: 32203 | D20: MALE | E20: Habeeb Khan | F20: Oracle/SAP DBA | G20: H NO 4-11-44/1, Kareem colony, OP, Narsa Hotel,Roshan Gate, Aurangabad, MH 431001 | H20: H NO 4-11-44/1, Kareem colony, OP, Narsa Hotel,Roshan Gate, Aurangabad, MH 431001 | I20: 44344 | N20: 100240675169 | O20: N/A | P20: =B20 -> Majed Khan | Q20: 30 | R20: =VLOOKUP(A20,'[5]Pay sheet-APRIL- 2022'!$C$7:$AF$137,10,0) -> 30 | S20: N/A | T20: 135892 | U20: =VLOOKUP(A20,'[5]Pay sheet-APRIL- 2022'!$C$7:$AF$137,11,0) -> 81535.2 | V20: 0 | W20: 0 | X20: =Y20+Z20+AA20+AB20 -> 54469.8 | Y20: =VLOOKUP(A20,'[5]Pay sheet-APRIL- 2022'!$C$7:$AF$137,12,0) -> 32614.08 | Z20: =VLOOKUP(A20,'[5]Pay sheet-APRIL- 2022'!$C$7:$AF$137,13,0) -> 2083 | AA20: =VLOOKUP(A20,'[5]Pay sheet-APRIL- 2022'!$C$7:$AF$137,14,0) -> 2083 | AB20: =VLOOKUP(A20,'[5]Pay sheet-APRIL- 2022'!$C$7:$AF$137,15,0) -> 17689.72 | AC20: =U20+X20 -> 136005 | AD20: =VLOOKUP(A20,'[5]Pay sheet-APRIL- 2022'!$C$7:$AF$137,18,0) -> 1554.609 | AE20: =VLOOKUP(A20,'[5]Pay sheet-APRIL- 2022'!$C$7:$AF$137,19,0) -> 3921.8431 | AF20: =VLOOKUP(A20,'[5]Pay sheet-APRIL- 2022'!$C$7:$AF$137,20,0) -> 6794.6 | AG20: =VLOOKUP(A20,'[5]Pay sheet-APRIL- 2022'!$C$7:$AF$137,22,0) -> 0 | AH20: =AC20+AD20+AE20+AF20+AG20 -> 148276.05 | AI20: 0 | AJ20: =VLOOKUP(A20,'[4]Pay sheet-MARCH- 2022'!$C$7:$AF$147,26,0) -> 1800 | AK20: =VLOOKUP(A20,'[4]Pay sheet-MARCH- 2022'!$C$7:$AF$147,25,0) -> 200 | AL20: =VLOOKUP(A20,'[5]Pay sheet-APRIL- 2022'!$C$7:$AF$137,24,0) -> 0 | AM20: =VLOOKUP(A20,'[4]Pay sheet-MARCH- 2022'!$C$7:$AF$147,27,0) -> 391.78785 | AN20: =AI20+AJ20+AK20+AL20+AM20 -> 2391.7878 | AO20: =AH20-AN20 -> 145884.26 | AP20: 44686 | AQ20: HDFC | AR20: 07941610141597 | AU20: 42 | AV20: 5
A21: BITS-587 | B21: MADAN DH | C21: 25-05-1988 | D21: MALE | E21: Dayanand H | F21: Principal Storage Consultant | G21: #402, Supreme Sunrise, Wellington Layout, Singasandra, Hosur road, Bangalore-68 | H21: #402, Supreme Sunrise, Wellington Layout, Singasandra, Hosur road, Bangalore-68 | I21: 44362 | N21: 100632443174 | O21: N/A | P21: =B21 -> MADAN DH | Q21: 30 | R21: =VLOOKUP(A21,'[5]Pay sheet-APRIL- 2022'!$C$7:$AF$137,10,0) -> 30 | S21: N/A | T21: 94181 | U21: =VLOOKUP(A21,'[5]Pay sheet-APRIL- 2022'!$C$7:$AF$137,11,0) -> 56508.6 | V21: 0 | W21: 0 | X21: =Y21+Z21+AA21+AB21 -> 37785.4 | Y21: =VLOOKUP(A21,'[5]Pay sheet-APRIL- 2022'!$C$7:$AF$137,12,0) -> 22603.44 | Z21: =VLOOKUP(A21,'[5]Pay sheet-APRIL- 2022'!$C$7:$AF$137,13,0) -> 2083 | AA21: =VLOOKUP(A21,'[5]Pay sheet-APRIL- 2022'!$C$7:$AF$137,14,0) -> 2083 | AB21: =VLOOKUP(A21,'[5]Pay sheet-APRIL- 2022'!$C$7:$AF$137,15,0) -> 11015.96 | AC21: =U21+X21 -> 94294 | AD21: =VLOOKUP(A21,'[5]Pay sheet-APRIL- 2022'!$C$7:$AF$137,18,0) -> 1554.609 | AE21: =VLOOKUP(A21,'[5]Pay sheet-APRIL- 2022'!$C$7:$AF$137,19,0) -> 2718.0637 | AF21: =VLOOKUP(A21,'[5]Pay sheet-APRIL- 2022'!$C$7:$AF$137,20,0) -> 4709.05 | AG21: =VLOOKUP(A21,'[5]Pay sheet-APRIL- 2022'!$C$7:$AF$137,22,0) -> 0 | AH21: =AC21+AD21+AE21+AF21+AG21 -> 103275.72 | AI21: 0 | AJ21: =VLOOKUP(A21,'[4]Pay sheet-MARCH- 2022'!$C$7:$AF$147,26,0) -> 1800 | AK21: =VLOOKUP(A21,'[4]Pay sheet-MARCH- 2022'!$C$7:$AF$147,25,0) -> 200 | AL21: =VLOOKUP(A21,'[5]Pay sheet-APRIL- 2022'!$C$7:$AF$137,24,0) -> 0 | AM21: =VLOOKUP(A21,'[4]Pay sheet-MARCH- 2022'!$C$7:$AF$147,27,0) -> 391.78785 | AN21: =AI21+AJ21+AK21+AL21+AM21 -> 2391.7878 | AO21: =AH21-AN21 -> 100883.93 | AP21: 44686 | AQ21: HDFC Bank | AR21: 50100122835737 | AU21: 47 | AV21: 6
A22: BITS-592 | B22: Sachin | C22: 21/09/1983 | D22: MALE | E22: POONAM SACHIN MESHRAM | F22: Windows Administrator | G22: T4 KUNAL RESIDENCY 2 BEHIND VITTHAL MANDIR BELTARODI NAGPUR 441108 | H22: 403 BHAKTI HEIGHTS ADHIRAJ CLUSTER 2 BEHIND DAWLAT PETROL PUMP BHUGAON PUNE 411023 | I22: 44368 | N22: 101090261210 | O22: N/A | P22: =B22 -> Sachin | Q22: 30 | R22: =VLOOKUP(A22,'[5]Pay sheet-APRIL- 2022'!$C$7:$AF$137,10,0) -> 13 | S22: N/A | T22: 84912 | U22: =VLOOKUP(A22,'[5]Pay sheet-APRIL- 2022'!$C$7:$AF$137,11,0) -> 22077.12 | V22: 0 | W22: 0 | X22: =Y22+Z22+AA22+AB22 -> 14831.08 | Y22: =VLOOKUP(A22,'[5]Pay sheet-APRIL- 2022'!$C$7:$AF$137,12,0) -> 8830.848 | Z22: =VLOOKUP(A22,'[5]Pay sheet-APRIL- 2022'!$C$7:$AF$137,13,0) -> 903 | AA22: =VLOOKUP(A22,'[5]Pay sheet-APRIL- 2022'!$C$7:$AF$137,14,0) -> 903 | AB22: =VLOOKUP(A22,'[5]Pay sheet-APRIL- 2022'!$C$7:$AF$137,15,0) -> 4194.232 | AC22: =U22+X22 -> 36908.2 | AD22: =VLOOKUP(A22,'[5]Pay sheet-APRIL- 2022'!$C$7:$AF$137,18,0) -> 1554.609 | AE22: =VLOOKUP(A22,'[5]Pay sheet-APRIL- 2022'!$C$7:$AF$137,19,0) -> 1061.9095 | AF22: =VLOOKUP(A22,'[5]Pay sheet-APRIL- 2022'!$C$7:$AF$137,20,0) -> 1839.76 | AG22: =VLOOKUP(A22,'[5]Pay sheet-APRIL- 2022'!$C$7:$AF$137,22,0) -> 0 | AH22: =AC22+AD22+AE22+AF22+AG22 -> 41364.478 | AI22: 0 | AJ22: =VLOOKUP(A22,'[4]Pay sheet-MARCH- 2022'!$C$7:$AF$147,26,0) -> 1800 | AK22: =VLOOKUP(A22,'[4]Pay sheet-MARCH- 2022'!$C$7:$AF$147,25,0) -> 200 | AL22: =VLOOKUP(A22,'[5]Pay sheet-APRIL- 2022'!$C$7:$AF$137,24,0) -> 0 | AM22: =VLOOKUP(A22,'[4]Pay sheet-MARCH- 2022'!$C$7:$AF$147,27,0) -> 391.78785 | AN22: =AI22+AJ22+AK22+AL22+AM22 -> 2391.7878 | AO22: =AH22-AN22 -> 38972.691 | AP22: 44686 | AQ22: STATE BANK OF INDIA | AR22: 20079696052 | AU22: 49 | AV22: 7
A23: BITS-606 | B23: Barathiyar A | C23: 03.05.1981 | D23: MALE | E23: Arumugam | F23: VMware & Wintel Admin | G23: 3/148,New Street,Mundiyampakkam & PO,Vikkravandi Taluk,Villupuram Dist,PIN 605601 | H23: 3/148,New Street,Mundiyampakkam & PO,Vikkravandi Taluk,Villupuram Dist,PIN 605601 | I23: 44396 | N23: 100583941709 | O23: N/A | P23: =B23 -> Barathiyar A | Q23: 30 | R23: =VLOOKUP(A23,'[5]Pay sheet-APRIL- 2022'!$C$7:$AF$137,10,0) -> 13 | S23: N/A | T23: 58959 | U23: =VLOOKUP(A23,'[5]Pay sheet-APRIL- 2022'!$C$7:$AF$137,11,0) -> 15329.34 | V23: 0 | W23: 0 | X23: =Y23+Z23+AA23+AB23 -> 10332.56 | Y23: =VLOOKUP(A23,'[5]Pay sheet-APRIL- 2022'!$C$7:$AF$137,12,0) -> 6131.736 | Z23: =VLOOKUP(A23,'[5]Pay sheet-APRIL- 2022'!$C$7:$AF$137,13,0) -> 903 | AA23: =VLOOKUP(A23,'[5]Pay sheet-APRIL- 2022'!$C$7:$AF$137,14,0) -> 903 | AB23: =VLOOKUP(A23,'[5]Pay sheet-APRIL- 2022'!$C$7:$AF$137,15,0) -> 2394.824 | AC23: =U23+X23 -> 25661.9 | AD23: =VLOOKUP(A23,'[5]Pay sheet-APRIL- 2022'!$C$7:$AF$137,18,0) -> 1554.609 | AE23: =VLOOKUP(A23,'[5]Pay sheet-APRIL- 2022'!$C$7:$AF$137,19,0) -> 737.34125 | AF23: =VLOOKUP(A23,'[5]Pay sheet-APRIL- 2022'!$C$7:$AF$137,20,0) -> 1277.445 | AG23: =VLOOKUP(A23,'[5]Pay sheet-APRIL- 2022'!$C$7:$AF$137,22,0) -> 0 | AH23: =AC23+AD23+AE23+AF23+AG23 -> 29231.295 | AI23: 0 | AJ23: =VLOOKUP(A23,'[4]Pay sheet-MARCH- 2022'!$C$7:$AF$147,26,0) -> 1800 | AK23: =VLOOKUP(A23,'[4]Pay sheet-MARCH- 2022'!$C$7:$AF$147,25,0) -> 200 | AL23: =VLOOKUP(A23,'[5]Pay sheet-APRIL- 2022'!$C$7:$AF$137,24,0) -> 0 | AM23: =VLOOKUP(A23,'[4]Pay sheet-MARCH- 2022'!$C$7:$AF$147,27,0) -> 335 | AN23: =AI23+AJ23+AK23+AL23+AM23 -> 2335 | AO23: =AH23-AN23 -> 26896.295 | AP23: 44686 | AQ23: ICICI BANK | AR23: 602601522530 | AU23: 52 | AV23: 8
A24: BITS-607 | B24: Kumaravel M | C24: 30142 | D24: MALE | E24: Madhavaraj | F24: Sr. Network Administrator | G24: NO 88, Arvind Nagar, 5th Street, Madambakkam, Chennai, 600126 | H24: NO 88, Arvind Nagar, 5th Street, Madambakkam, Chennai, 600126 | I24: 44396 | N24: 101273936714 | O24: N/A | P24: =B24 -> Kumaravel M | Q24: 30 | R24: =VLOOKUP(A24,'[5]Pay sheet-APRIL- 2022'!$C$7:$AF$137,10,0) -> 30 | S24: N/A | T24: 47836 | U24: =VLOOKUP(A24,'[5]Pay sheet-APRIL- 2022'!$C$7:$AF$137,11,0) -> 28701.6 | V24: 0 | W24: 0 | X24: =Y24+Z24+AA24+AB24 -> 19247.4 | Y24: =VLOOKUP(A24,'[5]Pay sheet-APRIL- 2022'!$C$7:$AF$137,12,0) -> 11480.64 | Z24: =VLOOKUP(A24,'[5]Pay sheet-APRIL- 2022'!$C$7:$AF$137,13,0) -> 2083 | AA24: =VLOOKUP(A24,'[5]Pay sheet-APRIL- 2022'!$C$7:$AF$137,14,0) -> 2083 | AB24: =VLOOKUP(A24,'[5]Pay sheet-APRIL- 2022'!$C$7:$AF$137,15,0) -> 3600.76 | AC24: =U24+X24 -> 47949 | AD24: =VLOOKUP(A24,'[5]Pay sheet-APRIL- 2022'!$C$7:$AF$137,18,0) -> 1554.609 | AE24: =VLOOKUP(A24,'[5]Pay sheet-APRIL- 2022'!$C$7:$AF$137,19,0) -> 1380.547 | AF24: =VLOOKUP(A24,'[5]Pay sheet-APRIL- 2022'!$C$7:$AF$137,20,0) -> 2391.8 | AG24: =VLOOKUP(A24,'[5]Pay sheet-APRIL- 2022'!$C$7:$AF$137,22,0) -> 0 | AH24: =AC24+AD24+AE24+AF24+AG24 -> 53275.956 | AI24: 0 | AJ24: =VLOOKUP(A24,'[4]Pay sheet-MARCH- 2022'!$C$7:$AF$147,26,0) -> 1800 | AK24: =VLOOKUP(A24,'[4]Pay sheet-MARCH- 2022'!$C$7:$AF$147,25,0) -> 200 | AL24: =VLOOKUP(A24,'[5]Pay sheet-APRIL- 2022'!$C$7:$AF$137,24,0) -> 0 | AM24: =VLOOKUP(A24,'[4]Pay sheet-MARCH- 2022'!$C$7:$AF$147,27,0) -> 335 | AN24: =AI24+AJ24+AK24+AL24+AM24 -> 2335 | AO24: =AH24-AN24 -> 50940.956 | AP24: 44686 | AQ24: Indian Bank | AR24: 443843855 | AU24: 53 | AV24: 9
A25: BITS-609 | B25: CHANDRASEHARAN GERORGE | C25: 27181 | D25: MALE | E25: George | F25: SENIOR TECHNICAL SPECIALIST | G25: PLOT NO.88, KAMALALAYAM 2, M.G.NAGAR 2, URAPAKKAM - 603211 | H25: PLOT NO.88, KAMALALAYAM 2, M.G.NAGAR 2, URAPAKKAM - 603211 | I25: 44396 | N25: 100123005976 | O25: N/A | P25: =B25 -> CHANDRASEHARAN GERORGE | Q25: 30 | R25: =VLOOKUP(A25,'[5]Pay sheet-APRIL- 2022'!$C$7:$AF$137,10,0) -> 15 | S25: N/A | T25: 50617 | U25: =VLOOKUP(A25,'[5]Pay sheet-APRIL- 2022'!$C$7:$AF$137,11,0) -> 15185.1 | V25: 0 | W25: 0 | X25: =Y25+Z25+AA25+AB25 -> 10236.4 | Y25: =VLOOKUP(A25,'[5]Pay sheet-APRIL- 2022'!$C$7:$AF$137,12,0) -> 6074.04 | Z25: =VLOOKUP(A25,'[5]Pay sheet-APRIL- 2022'!$C$7:$AF$137,13,0) -> 1042 | AA25: =VLOOKUP(A25,'[5]Pay sheet-APRIL- 2022'!$C$7:$AF$137,14,0) -> 1042 | AB25: =VLOOKUP(A25,'[5]Pay sheet-APRIL- 2022'!$C$7:$AF$137,15,0) -> 2078.36 | AC25: =U25+X25 -> 25421.5 | AD25: =VLOOKUP(A25,'[5]Pay sheet-APRIL- 2022'!$C$7:$AF$137,18,0) -> 1554.609 | AE25: =VLOOKUP(A25,'[5]Pay sheet-APRIL- 2022'!$C$7:$AF$137,19,0) -> 730.40331 | AF25: =VLOOKUP(A25,'[5]Pay sheet-APRIL- 2022'!$C$7:$AF$137,20,0) -> 1265.425 | AG25: =VLOOKUP(A25,'[5]Pay sheet-APRIL- 2022'!$C$7:$AF$137,22,0) -> 0 | AH25: =AC25+AD25+AE25+AF25+AG25 -> 28971.937 | AI25: 0 | AJ25: =VLOOKUP(A25,'[4]Pay sheet-MARCH- 2022'!$C$7:$AF$147,26,0) -> 1800 | AK25: =VLOOKUP(A25,'[4]Pay sheet-MARCH- 2022'!$C$7:$AF$147,25,0) -> 200 | AL25: =VLOOKUP(A25,'[5]Pay sheet-APRIL- 2022'!$C$7:$AF$137,24,0) -> 0 | AM25: =VLOOKUP(A25,'[4]Pay sheet-MARCH- 2022'!$C$7:$AF$147,27,0) -> 335 | AN25: =AI25+AJ25+AK25+AL25+AM25 -> 2335 | AO25: =AH25-AN25 -> 26636.937 | AP25: 44686 | AQ25: Standard Charter Bank | AR25: 42610387037 | AU25: 55 | AV25: 10
A26: BITS-611 | B26: VISHNUPRASATH T | C26: 33729 | D26: MALE | E26: Thavamani | F26: Sr. Network Engineer | G26: 1/97, Kilmettu st, Villvarani PO, Kalasapakkam taluk, Tiruvannamalai dt, Tamilnadu PIN-606906 | H26: 1/97, Kilmettu st, Villvarani PO, Kalasapakkam taluk, Tiruvannamalai dt, Tamilnadu PIN-606906 | I26: 44396 | N26: 100910953478 | O26: N/A | P26: =B26 -> VISHNUPRASATH T | Q26: 30 | R26: =VLOOKUP(A26,'[5]Pay sheet-APRIL- 2022'!$C$7:$AF$137,10,0) -> 30 | S26: N/A | T26: 47836 | U26: =VLOOKUP(A26,'[5]Pay sheet-APRIL- 2022'!$C$7:$AF$137,11,0) -> 28701.6 | V26: 0 | W26: 0 | X26: =Y26+Z26+AA26+AB26 -> 19247.4 | Y26: =VLOOKUP(A26,'[5]Pay sheet-APRIL- 2022'!$C$7:$AF$137,12,0) -> 11480.64 | Z26: =VLOOKUP(A26,'[5]Pay sheet-APRIL- 2022'!$C$7:$AF$137,13,0) -> 2083 | AA26: =VLOOKUP(A26,'[5]Pay sheet-APRIL- 2022'!$C$7:$AF$137,14,0) -> 2083 | AB26: =VLOOKUP(A26,'[5]Pay sheet-APRIL- 2022'!$C$7:$AF$137,15,0) -> 3600.76 | AC26: =U26+X26 -> 47949 | AD26: =VLOOKUP(A26,'[5]Pay sheet-APRIL- 2022'!$C$7:$AF$137,18,0) -> 1554.609 | AE26: =VLOOKUP(A26,'[5]Pay sheet-APRIL- 2022'!$C$7:$AF$137,19,0) -> 1380.547 | AF26: =VLOOKUP(A26,'[5]Pay sheet-APRIL- 2022'!$C$7:$AF$137,20,0) -> 2391.8 | AG26: =VLOOKUP(A26,'[5]Pay sheet-APRIL- 2022'!$C$7:$AF$137,22,0) -> 0 | AH26: =AC26+AD26+AE26+AF26+AG26 -> 53275.956 | AI26: 0 | AJ26: =VLOOKUP(A26,'[4]Pay sheet-MARCH- 2022'!$C$7:$AF$147,26,0) -> 1800 | AK26: =VLOOKUP(A26,'[4]Pay sheet-MARCH- 2022'!$C$7:$AF$147,25,0) -> 200 | AL26: =VLOOKUP(A26,'[5]Pay sheet-APRIL- 2022'!$C$7:$AF$137,24,0) -> 0 | AM26: =VLOOKUP(A26,'[4]Pay sheet-MARCH- 2022'!$C$7:$AF$147,27,0) -> 335 | AN26: =AI26+AJ26+AK26+AL26+AM26 -> 2335 | AO26: =AH26-AN26 -> 50940.956 | AP26: 44686 | AQ26: ICICI BANK | AR26: 270401504431 | AU26: 57 | AV26: 11
A27: BITS-612 | B27: Nagaranjan S | C27: 19.06.1981 | D27: MALE | E27: SUBBIAH G | F27: Linux Administrator | G27: 4\122,V.Sundaralingapuram,Pavali(PO),Virudhunagar(DT)-626103 | H27: 5\1, 1st floor,3rd cross street,BalajiNagar,Kolathur,Chennai-600099 | I27: 44396 | N27: 100363582963 | O27: N/A | P27: =B27 -> Nagaranjan S | Q27: 30 | R27: =VLOOKUP(A27,'[5]Pay sheet-APRIL- 2022'!$C$7:$AF$137,10,0) -> 30 | S27: N/A | T27: 47836 | U27: =VLOOKUP(A27,'[5]Pay sheet-APRIL- 2022'!$C$7:$AF$137,11,0) -> 28701.6 | V27: 0 | W27: 0 | X27: =Y27+Z27+AA27+AB27 -> 19247.4 | Y27: =VLOOKUP(A27,'[5]Pay sheet-APRIL- 2022'!$C$7:$AF$137,12,0) -> 11480.64 | Z27: =VLOOKUP(A27,'[5]Pay sheet-APRIL- 2022'!$C$7:$AF$137,13,0) -> 2083 | AA27: =VLOOKUP(A27,'[5]Pay sheet-APRIL- 2022'!$C$7:$AF$137,14,0) -> 2083 | AB27: =VLOOKUP(A27,'[5]Pay sheet-APRIL- 2022'!$C$7:$AF$137,15,0) -> 3600.76 | AC27: =U27+X27 -> 47949 | AD27: =VLOOKUP(A27,'[5]Pay sheet-APRIL- 2022'!$C$7:$AF$137,18,0) -> 1554.609 | AE27: =VLOOKUP(A27,'[5]Pay sheet-APRIL- 2022'!$C$7:$AF$137,19,0) -> 1380.547 | AF27: =VLOOKUP(A27,'[5]Pay sheet-APRIL- 2022'!$C$7:$AF$137,20,0) -> 2391.8 | AG27: =VLOOKUP(A27,'[5]Pay sheet-APRIL- 2022'!$C$7:$AF$137,22,0) -> 0 | AH27: =AC27+AD27+AE27+AF27+AG27 -> 53275.956 | AI27: 0 | AJ27: =VLOOKUP(A27,'[4]Pay sheet-MARCH- 2022'!$C$7:$AF$147,26,0) -> 1800 | AK27: =VLOOKUP(A27,'[4]Pay sheet-MARCH- 2022'!$C$7:$AF$147,25,0) -> 200 | AL27: =VLOOKUP(A27,'[5]Pay sheet-APRIL- 2022'!$C$7:$AF$137,24,0) -> 0 | AM27: =VLOOKUP(A27,'[4]Pay sheet-MARCH- 2022'!$C$7:$AF$147,27,0) -> 335 | AN27: =AI27+AJ27+AK27+AL27+AM27 -> 2335 | AO27: =AH27-AN27 -> 50940.956 | AP27: 44686 | AQ27: IDBI BANK | AR27: 005104000198752 | AU27: 58 | AV27: 12
A28: BITS-613 | B28: ELAMPARITHI SB | C28: 20-02-1986 | D28: MALE | E28: Balasubramanian.S | F28: Senior Network Engineer | G28: 77 - Mela Dhasappa Nayakkan Street , Kanagam Thottam ,East Gate,Thanjavur-613001 | H28: C5 - Orchid Screne Moovendar Nagar Extension, Old Perungalathur , Chennai - 600063 | I28: 44396 | N28: 100500123608 | O28: N/A | P28: =B28 -> ELAMPARITHI SB | Q28: 30 | R28: =VLOOKUP(A28,'[5]Pay sheet-APRIL- 2022'!$C$7:$AF$137,10,0) -> 20 | S28: N/A | T28: 47836 | U28: =VLOOKUP(A28,'[5]Pay sheet-APRIL- 2022'!$C$7:$AF$137,11,0) -> 19134.4 | V28: 0 | W28: 0 | X28: =Y28+Z28+AA28+AB28 -> 12869.267 | Y28: =VLOOKUP(A28,'[5]Pay sheet-APRIL- 2022'!$C$7:$AF$137,12,0) -> 7653.76 | Z28: =VLOOKUP(A28,'[5]Pay sheet-APRIL- 2022'!$C$7:$AF$137,13,0) -> 1389 | AA28: =VLOOKUP(A28,'[5]Pay sheet-APRIL- 2022'!$C$7:$AF$137,14,0) -> 1389 | AB28: =VLOOKUP(A28,'[5]Pay sheet-APRIL- 2022'!$C$7:$AF$137,15,0) -> 2437.5067 | AC28: =U28+X28 -> 32003.667 | AD28: =VLOOKUP(A28,'[5]Pay sheet-APRIL- 2022'!$C$7:$AF$137,18,0) -> 1554.609 | AE28: =VLOOKUP(A28,'[5]Pay sheet-APRIL- 2022'!$C$7:$AF$137,19,0) -> 920.36464 | AF28: =VLOOKUP(A28,'[5]Pay sheet-APRIL- 2022'!$C$7:$AF$137,20,0) -> 1594.5333 | AG28: =VLOOKUP(A28,'[5]Pay sheet-APRIL- 2022'!$C$7:$AF$137,22,0) -> 0 | AH28: =AC28+AD28+AE28+AF28+AG28 -> 36073.174 | AI28: 0 | AJ28: =VLOOKUP(A28,'[4]Pay sheet-MARCH- 2022'!$C$7:$AF$147,26,0) -> 1800 | AK28: =VLOOKUP(A28,'[4]Pay sheet-MARCH- 2022'!$C$7:$AF$147,25,0) -> 200 | AL28: =VLOOKUP(A28,'[5]Pay sheet-APRIL- 2022'!$C$7:$AF$137,24,0) -> 0 | AM28: =VLOOKUP(A28,'[4]Pay sheet-MARCH- 2022'!$C$7:$AF$147,27,0) -> 335 | AN28: =AI28+AJ28+AK28+AL28+AM28 -> 2335 | AO28: =AH28-AN28 -> 33738.174 | AP28: 44686 | AQ28: ICICI | AR28: 060701514623 | AU28: 59 | AV28: 13
A29: BITS-624 | B29: Karthick G | C29: 32831 | D29: MALE | E29: Ganesan | F29: Senior EUC Analyst | G29: 47A,Vallaneri,Koothandan Post,Melavaniyankudi,Sivaganga,Tamil Nadu-630561 | H29: G-02,Teja Residency-01,Coconut Garden Layout,Kodigehalli Main Road, Ayyappa Nagar,KR Puram, Bangalore-560036 | I29: 44419 | N29: 100874601152 | O29: N/A | P29: =B29 -> Karthick G | Q29: 30 | R29: =VLOOKUP(A29,'[5]Pay sheet-APRIL- 2022'!$C$7:$AF$137,10,0) -> 30 | S29: N/A | T29: 89547 | U29: =VLOOKUP(A29,'[5]Pay sheet-APRIL- 2022'!$C$7:$AF$137,11,0) -> 53728.2 | V29: 0 | W29: 0 | X29: =Y29+Z29+AA29+AB29 -> 35931.8 | Y29: =VLOOKUP(A29,'[5]Pay sheet-APRIL- 2022'!$C$7:$AF$137,12,0) -> 21491.28 | Z29: =VLOOKUP(A29,'[5]Pay sheet-APRIL- 2022'!$C$7:$AF$137,13,0) -> 2083 | AA29: =VLOOKUP(A29,'[5]Pay sheet-APRIL- 2022'!$C$7:$AF$137,14,0) -> 2083 | AB29: =VLOOKUP(A29,'[5]Pay sheet-APRIL- 2022'!$C$7:$AF$137,15,0) -> 10274.52 | AC29: =U29+X29 -> 89660 | AD29: =VLOOKUP(A29,'[5]Pay sheet-APRIL- 2022'!$C$7:$AF$137,18,0) -> 1554.609 | AE29: =VLOOKUP(A29,'[5]Pay sheet-APRIL- 2022'!$C$7:$AF$137,19,0) -> 2584.3264 | AF29: =VLOOKUP(A29,'[5]Pay sheet-APRIL- 2022'!$C$7:$AF$137,20,0) -> 4477.35 | AG29: =VLOOKUP(A29,'[5]Pay sheet-APRIL- 2022'!$C$7:$AF$137,22,0) -> 0 | AH29: =AC29+AD29+AE29+AF29+AG29 -> 98276.285 | AI29: 0 | AJ29: =VLOOKUP(A29,'[4]Pay sheet-MARCH- 2022'!$C$7:$AF$147,26,0) -> 1800 | AK29: =VLOOKUP(A29,'[4]Pay sheet-MARCH- 2022'!$C$7:$AF$147,25,0) -> 200 | AL29: =VLOOKUP(A29,'[5]Pay sheet-APRIL- 2022'!$C$7:$AF$137,24,0) -> 0 | AM29: =VLOOKUP(A29,'[4]Pay sheet-MARCH- 2022'!$C$7:$AF$147,27,0) -> 336 | AN29: =AI29+AJ29+AK29+AL29+AM29 -> 2336 | AO29: =AH29-AN29 -> 95940.285 | AP29: 44686 | AQ29: HDFC BANK | AR29: 50100072083437 | AU29: 61 | AV29: 14
A30: BITS-640 | B30: K V Kannan | C30: 29774 | D30: MALE | E30: K C Venkata Kumar | F30: Windows and Assure Administrator | G30: New No.1,old no 43/351,Jyothi ramalingam street,Rajajipuram,Thiruvallur,TN 602001 | H30: New No.1,old no 43/351,Jyothi ramalingam street,Rajajipuram,Thiruvallur,TN 602001 | I30: 44446 | N30: 101275235803 | O30: N/A | P30: K V Kannan | Q30: 30 | R30: =VLOOKUP(A30,'[5]Pay sheet-APRIL- 2022'!$C$7:$AF$137,10,0) -> 30 | S30: N/A | T30: 36713 | U30: =VLOOKUP(A30,'[5]Pay sheet-APRIL- 2022'!$C$7:$AF$137,11,0) -> 22027.8 | V30: 0 | W30: 0 | X30: =Y30+Z30+AA30+AB30 -> 14798.2 | Y30: =VLOOKUP(A30,'[5]Pay sheet-APRIL- 2022'!$C$7:$AF$137,12,0) -> 8811.12 | Z30: =VLOOKUP(A30,'[5]Pay sheet-APRIL- 2022'!$C$7:$AF$137,13,0) -> 2083 | AA30: =VLOOKUP(A30,'[5]Pay sheet-APRIL- 2022'!$C$7:$AF$137,14,0) -> 2083 | AB30: =VLOOKUP(A30,'[5]Pay sheet-APRIL- 2022'!$C$7:$AF$137,15,0) -> 1821.08 | AC30: =U30+X30 -> 36826 | AD30: =VLOOKUP(A30,'[5]Pay sheet-APRIL- 2022'!$C$7:$AF$137,18,0) -> 1554.609 | AE30: =VLOOKUP(A30,'[5]Pay sheet-APRIL- 2022'!$C$7:$AF$137,19,0) -> 1059.5372 | AF30: =VLOOKUP(A30,'[5]Pay sheet-APRIL- 2022'!$C$7:$AF$137,20,0) -> 1835.65 | AG30: =VLOOKUP(A30,'[5]Pay sheet-APRIL- 2022'!$C$7:$AF$137,22,0) -> 0 | AH30: =AC30+AD30+AE30+AF30+AG30 -> 41275.796 | AI30: 0 | AJ30: =VLOOKUP(A30,'[4]Pay sheet-MARCH- 2022'!$C$7:$AF$147,26,0) -> 1800 | AK30: =VLOOKUP(A30,'[4]Pay sheet-MARCH- 2022'!$C$7:$AF$147,25,0) -> 200 | AL30: =VLOOKUP(A30,'[5]Pay sheet-APRIL- 2022'!$C$7:$AF$137,24,0) -> 0 | AM30: =VLOOKUP(A30,'[4]Pay sheet-MARCH- 2022'!$C$7:$AF$147,27,0) -> 252 | AN30: =AI30+AJ30+AK30+AL30+AM30 -> 2252 | AO30: =AH30-AN30 -> 39023.796 | AP30: 44686 | AQ30: INDUSIND BANK | AR30: 100062052877 | AU30: 65 | AV30: 15
A31: BITS-641 | B31: Thanigaivel.J | C31: 34698 | D31: MALE | E31: Jayavelu | F31: Network Engineer | G31: No 6,Load man street,varadharajan nagar,changalpet,chengalpattu,kanchipuram,TN 603002 | H31: No 6,Load man street,varadharajan nagar,changalpet,chengalpattu,kanchipuram,TN 603002 | I31: 44446 | N31: 101131863380 | O31: N/A | P31: Thanigaivel.J | Q31: 30 | R31: =VLOOKUP(A31,'[5]Pay sheet-APRIL- 2022'!$C$7:$AF$137,10,0) -> 30 | S31: N/A | T31: 36713 | U31: =VLOOKUP(A31,'[5]Pay sheet-APRIL- 2022'!$C$7:$AF$137,11,0) -> 22027.8 | V31: 0 | W31: 0 | X31: =Y31+Z31+AA31+AB31 -> 14798.2 | Y31: =VLOOKUP(A31,'[5]Pay sheet-APRIL- 2022'!$C$7:$AF$137,12,0) -> 8811.12 | Z31: =VLOOKUP(A31,'[5]Pay sheet-APRIL- 2022'!$C$7:$AF$137,13,0) -> 2083 | AA31: =VLOOKUP(A31,'[5]Pay sheet-APRIL- 2022'!$C$7:$AF$137,14,0) -> 2083 | AB31: =VLOOKUP(A31,'[5]Pay sheet-APRIL- 2022'!$C$7:$AF$137,15,0) -> 1821.08 | AC31: =U31+X31 -> 36826 | AD31: =VLOOKUP(A31,'[5]Pay sheet-APRIL- 2022'!$C$7:$AF$137,18,0) -> 1554.609 | AE31: =VLOOKUP(A31,'[5]Pay sheet-APRIL- 2022'!$C$7:$AF$137,19,0) -> 1059.5372 | AF31: =VLOOKUP(A31,'[5]Pay sheet-APRIL- 2022'!$C$7:$AF$137,20,0) -> 1835.65 | AG31: =VLOOKUP(A31,'[5]Pay sheet-APRIL- 2022'!$C$7:$AF$137,22,0) -> 0 | AH31: =AC31+AD31+AE31+AF31+AG31 -> 41275.796 | AI31: 0 | AJ31: =VLOOKUP(A31,'[5]Pay sheet-APRIL- 2022'!$C$7:$AF$137,26,0) -> 1800 | AK31: =VLOOKUP(A31,'[5]Pay sheet-APRIL- 2022'!$C$7:$AF$137,25,0) -> 200 | AL31: =VLOOKUP(A31,'[5]Pay sheet-APRIL- 2022'!$C$7:$AF$137,24,0) -> 0 | AM31: =VLOOKUP(A31,'[5]Pay sheet-APRIL- 2022'!$C$7:$AF$137,27,0) -> 224 | AN31: =AI31+AJ31+AK31+AL31+AM31 -> 2224 | AO31: =AH31-AN31 -> 39051.796 | AP31: 44686 | AQ31: AXIS BANK | AR31: 917010045864654 | AU31: 66 | AV31: 16
A32: BITS-659 | B32: Manzoor Ahamed | C32: 31191 | D32: MALE | E32: Syed Rahim | F32: Lead Devops Engineer | G32: D No 426,Karuppanannan house,T B Road,Sankari,Selam,Tamilnadu 637301 | H32: Ground floor,Padmalayam site No 24,4th cross,Vellinganton paradise layout,singa sandra,Bangalore 560068,Karnataka | I32: 44487 | N32: 100551348435 | O32: N/A | P32: =B32 -> Manzoor Ahamed | Q32: 30 | R32: =VLOOKUP(A32,'[5]Pay sheet-APRIL- 2022'!$C$7:$AF$137,10,0) -> 30 | S32: N/A | T32: 223948 | U32: =VLOOKUP(A32,'[5]Pay sheet-APRIL- 2022'!$C$7:$AF$137,11,0) -> 134368.8 | V32: 0 | W32: 0 | X32: =Y32+Z32+AA32+AB32 -> 89692.2 | Y32: =VLOOKUP(A32,'[5]Pay sheet-APRIL- 2022'!$C$7:$AF$137,12,0) -> 53747.52 | Z32: =VLOOKUP(A32,'[5]Pay sheet-APRIL- 2022'!$C$7:$AF$137,13,0) -> 2083 | AA32: =VLOOKUP(A32,'[5]Pay sheet-APRIL- 2022'!$C$7:$AF$137,14,0) -> 2083 | AB32: =VLOOKUP(A32,'[5]Pay sheet-APRIL- 2022'!$C$7:$AF$137,15,0) -> 31778.68 | AC32: =U32+X32 -> 224061 | AD32: =VLOOKUP(A32,'[5]Pay sheet-APRIL- 2022'!$C$7:$AF$137,18,0) -> 1554.609 | AE32: =VLOOKUP(A32,'[5]Pay sheet-APRIL- 2022'!$C$7:$AF$137,19,0) -> 6463.1393 | AF32: =VLOOKUP(A32,'[5]Pay sheet-APRIL- 2022'!$C$7:$AF$137,20,0) -> 11197.4 | AG32: =VLOOKUP(A32,'[5]Pay sheet-APRIL- 2022'!$C$7:$AF$137,22,0) -> 0 | AH32: =AC32+AD32+AE32+AF32+AG32 -> 243276.15 | AI32: 0 | AJ32: =VLOOKUP(A32,'[5]Pay sheet-APRIL- 2022'!$C$7:$AF$137,26,0) -> 1800 | AK32: =VLOOKUP(A32,'[5]Pay sheet-APRIL- 2022'!$C$7:$AF$137,25,0) -> 200 | AL32: =VLOOKUP(A32,'[5]Pay sheet-APRIL- 2022'!$C$7:$AF$137,24,0) -> 0 | AM32: =VLOOKUP(A32,'[5]Pay sheet-APRIL- 2022'!$C$7:$AF$137,27,0) -> 286 | AN32: =AI32+AJ32+AK32+AL32+AM32 -> 2286 | AO32: =AH32-AN32 -> 240990.15 | AP32: 44686 | AQ32: CITI Bank | AR32: 5153635813 | AU32: 70 | AV32: 17
A33: BITS-671 | B33: Ramakrishna J Reddy | C33: 33048 | D33: MALE | E33: Satyanarayana Reddy | F33: SENIOR SAP ABAP CONSULTANT | G33: 7-20-1092/A,28th line,Sarada colony,Guntur 522002,AP | H33: 7-20-1092/A,28th line,Sarada colony,Guntur 522002,AP | I33: 44512 | N33: 100453787600 | O33: N/A | P33: =B33 -> Ramakrishna J Reddy | Q33: 30 | R33: =VLOOKUP(A33,'[5]Pay sheet-APRIL- 2022'!$C$7:$AF$137,10,0) -> 28 | S33: N/A | T33: 191506 | U33: =VLOOKUP(A33,'[5]Pay sheet-APRIL- 2022'!$C$7:$AF$137,11,0) -> 107243.36 | V33: 0 | W33: 0 | X33: =Y33+Z33+AA33+AB33 -> 71608.573 | Y33: =VLOOKUP(A33,'[5]Pay sheet-APRIL- 2022'!$C$7:$AF$137,12,0) -> 42897.344 | Z33: =VLOOKUP(A33,'[5]Pay sheet-APRIL- 2022'!$C$7:$AF$137,13,0) -> 1944 | AA33: =VLOOKUP(A33,'[5]Pay sheet-APRIL- 2022'!$C$7:$AF$137,14,0) -> 1944 | AB33: =VLOOKUP(A33,'[5]Pay sheet-APRIL- 2022'!$C$7:$AF$137,15,0) -> 24823.229 | AC33: =U33+X33 -> 178851.93 | AD33: =VLOOKUP(A33,'[5]Pay sheet-APRIL- 2022'!$C$7:$AF$137,18,0) -> 1554.609 | AE33: =VLOOKUP(A33,'[5]Pay sheet-APRIL- 2022'!$C$7:$AF$137,19,0) -> 5158.4056 | AF33: =VLOOKUP(A33,'[5]Pay sheet-APRIL- 2022'!$C$7:$AF$137,20,0) -> 8936.9467 | AG33: =VLOOKUP(A33,'[5]Pay sheet-APRIL- 2022'!$C$7:$AF$137,22,0) -> 0 | AH33: =AC33+AD33+AE33+AF33+AG33 -> 194501.89 | AI33: 0 | AJ33: =VLOOKUP(A33,'[5]Pay sheet-APRIL- 2022'!$C$7:$AF$137,26,0) -> 1800 | AK33: =VLOOKUP(A33,'[5]Pay sheet-APRIL- 2022'!$C$7:$AF$137,25,0) -> 200 | AL33: =VLOOKUP(A33,'[5]Pay sheet-APRIL- 2022'!$C$7:$AF$137,24,0) -> 0 | AM33: =VLOOKUP(A33,'[5]Pay sheet-APRIL- 2022'!$C$7:$AF$137,27,0) -> 252 | AN33: =AI33+AJ33+AK33+AL33+AM33 -> 2252 | AO33: =AH33-AN33 -> 192249.89 | AP33: 44686 | AQ33: HDFC BANK | AR33: 50100216035976 | AU33: 71 | AV33: 18
A34: BITS-645 | B34: Anil kumar Reddy kusam | C34: 32974 | D34: MALE | E34: Pulla Reddy | F34: Associate Consultant | G34: 2-36,B.Jwalapuram,Singamavula Mandal,Ananthapur,AP 515435 | H34: 2-36,B.Jwalapuram,Singamavula Mandal,Ananthapur,AP 515435 | I34: 44459 | N34: 101182432317 | O34: N/A | P34: =B34 -> Anil kumar Reddy kusam | Q34: 30 | R34: =VLOOKUP(A34,'[5]Pay sheet-APRIL- 2022'!$C$7:$AF$137,10,0) -> 30 | S34: N/A | T34: 80278 | U34: 48167 | V34: 0 | W34: 0 | X34: =Y34+Z34+AA34+AB34 -> 32224 | Y34: 19267 | Z34: =VLOOKUP(A34,'[5]Pay sheet-APRIL- 2022'!$C$7:$AF$137,13,0) -> 2083 | AA34: =VLOOKUP(A34,'[5]Pay sheet-APRIL- 2022'!$C$7:$AF$137,14,0) -> 2083 | AB34: 8791 | AC34: =U34+X34 -> 80391 | AD34: =VLOOKUP(A34,'[5]Pay sheet-APRIL- 2022'!$C$7:$AF$137,18,0) -> 1554.609 | AE34: 2317 | AF34: 4014 | AG34: =VLOOKUP(A34,'[5]Pay sheet-APRIL- 2022'!$C$7:$AF$137,22,0) -> 0 | AH34: =AC34+AD34+AE34+AF34+AG34 -> 88276.609 | AI34: 0 | AJ34: =VLOOKUP(A34,'[5]Pay sheet-APRIL- 2022'!$C$7:$AF$137,26,0) -> 1800 | AK34: =VLOOKUP(A34,'[5]Pay sheet-APRIL- 2022'!$C$7:$AF$137,25,0) -> 200 | AL34: =VLOOKUP(A34,'[5]Pay sheet-APRIL- 2022'!$C$7:$AF$137,24,0) -> 0 | AM34: 224 | AN34: =AI34+AJ34+AK34+AL34+AM34 -> 2224 | AO34: =AH34-AN34 -> 86052.609 | AP34: 44686 | AQ34: ICICI BANK | AR34: 020201566128 | AU34: 68 | AV34: 19 | AW34: v-lookkup troubling
A35: BITS-679 | B35: Praveen Kumar Tandra | C35: 30287 | D35: MALE | E35: Ram reddy Tandra | F35: Sr.Linux Admin | G35: 1-156,Boinapally,Midjil,Mahabubnagar District,Telangan 509357 | H35: 303,CBR Enclave2,Road No.2,Triveni nagar,Balapur cross roads,Hyderabad,Telangana 500097 | I35: 44536 | J35: OOOO | K35: OOOO | L35: OOOO | M35: OOOO | N35: 100279367972 | O35: N/A | P35: Praveen Kumar Tandra | Q35: 30 | R35: =VLOOKUP(A35,'[5]Pay sheet-APRIL- 2022'!$C$7:$AF$137,10,0) -> 30 | S35: N/A | T35: 98816 | U35: =VLOOKUP(A35,'[5]Pay sheet-APRIL- 2022'!$C$7:$AF$137,11,0) -> 59289.6 | V35: 0 | W35: 0 | X35: =Y35+Z35+AA35+AB35 -> 39639.4 | Y35: =VLOOKUP(A35,'[5]Pay sheet-APRIL- 2022'!$C$7:$AF$137,12,0) -> 23715.84 | Z35: =VLOOKUP(A35,'[5]Pay sheet-APRIL- 2022'!$C$7:$AF$137,13,0) -> 2083 | AA35: =VLOOKUP(A35,'[5]Pay sheet-APRIL- 2022'!$C$7:$AF$137,14,0) -> 2083 | AB35: =VLOOKUP(A35,'[5]Pay sheet-APRIL- 2022'!$C$7:$AF$137,15,0) -> 11757.56 | AC35: =U35+X35 -> 98929 | AD35: =VLOOKUP(A35,'[5]Pay sheet-APRIL- 2022'!$C$7:$AF$137,18,0) -> 1554.609 | AE35: =VLOOKUP(A35,'[5]Pay sheet-APRIL- 2022'!$C$7:$AF$137,19,0) -> 2851.8298 | AF35: =VLOOKUP(A35,'[5]Pay sheet-APRIL- 2022'!$C$7:$AF$137,20,0) -> 4940.8 | AG35: =VLOOKUP(A35,'[5]Pay sheet-APRIL- 2022'!$C$7:$AF$137,22,0) -> 0 | AH35: =AC35+AD35+AE35+AF35+AG35 -> 108276.24 | AI35: 0 | AJ35: =VLOOKUP(A35,'[5]Pay sheet-APRIL- 2022'!$C$7:$AF$137,26,0) -> 1800 | AK35: =VLOOKUP(A35,'[5]Pay sheet-APRIL- 2022'!$C$7:$AF$137,25,0) -> 200 | AL35: =VLOOKUP(A35,'[5]Pay sheet-APRIL- 2022'!$C$7:$AF$137,24,0) -> 0 | AM35: =VLOOKUP(A35,'[5]Pay sheet-APRIL- 2022'!$C$7:$AF$137,27,0) -> 283 | AN35: =AI35+AJ35+AK35+AL35+AM35 -> 2283 | AO35: =AH35-AN35 -> 105993.24 | AP35: 44686 | AQ35: HDFC BANK | AR35: 00008099320 | AU35: 72 | AV35: 20
A36: BITS-689 | B36: Nagarjun KV | C36: 31644 | D36: MALE | E36: Arpitha R | F36: Technical Consultant | G36: #66\E, 3rd C Main, Raghavendra Layout, Hulimavu, Bangalore - 560076 | H36: #66\E, 3rd C Main, Raghavendra Layout, Hulimavu, Bangalore - 560076 | I36: 44564 | J36: OOOO | K36: OOOO | L36: OOOO | M36: OOOO | N36: 100247870639 | O36: N/A | P36: Nagarjun KV | Q36: 30 | R36: =VLOOKUP(A36,'[5]Pay sheet-APRIL- 2022'!$C$7:$AF$137,10,0) -> 30 | S36: N/A | T36: 75643 | U36: =VLOOKUP(A36,'[5]Pay sheet-APRIL- 2022'!$C$7:$AF$137,11,0) -> 45385.8 | V36: 0 | W36: 0 | X36: =Y36+Z36+AA36+AB36 -> 30370.2 | Y36: =VLOOKUP(A36,'[5]Pay sheet-APRIL- 2022'!$C$7:$AF$137,12,0) -> 18154.32 | Z36: =VLOOKUP(A36,'[5]Pay sheet-APRIL- 2022'!$C$7:$AF$137,13,0) -> 2083 | AA36: =VLOOKUP(A36,'[5]Pay sheet-APRIL- 2022'!$C$7:$AF$137,14,0) -> 2083 | AB36: =VLOOKUP(A36,'[5]Pay sheet-APRIL- 2022'!$C$7:$AF$137,15,0) -> 8049.88 | AC36: =U36+X36 -> 75756 | AD36: =VLOOKUP(A36,'[5]Pay sheet-APRIL- 2022'!$C$7:$AF$137,18,0) -> 1554.609 | AE36: =VLOOKUP(A36,'[5]Pay sheet-APRIL- 2022'!$C$7:$AF$137,19,0) -> 2183.057 | AF36: =VLOOKUP(A36,'[5]Pay sheet-APRIL- 2022'!$C$7:$AF$137,20,0) -> 3782.15 | AG36: =VLOOKUP(A36,'[5]Pay sheet-APRIL- 2022'!$C$7:$AF$137,22,0) -> 0 | AH36: =AC36+AD36+AE36+AF36+AG36 -> 83275.816 | AI36: 0 | AJ36: =VLOOKUP(A36,'[5]Pay sheet-APRIL- 2022'!$C$7:$AF$137,26,0) -> 1800 | AK36: =VLOOKUP(A36,'[5]Pay sheet-APRIL- 2022'!$C$7:$AF$137,25,0) -> 200 | AL36: =VLOOKUP(A36,'[5]Pay sheet-APRIL- 2022'!$C$7:$AF$137,24,0) -> 0 | AM36: =VLOOKUP(A36,'[5]Pay sheet-APRIL- 2022'!$C$7:$AF$137,27,0) -> 283 | AN36: =AI36+AJ36+AK36+AL36+AM36 -> 2283 | AO36: =AH36-AN36 -> 80992.816 | AP36: 44686 | AQ36: STATE BANK OF INDIA | AR36: 20174267977 | AU36: 74 | AV36: 21
A37: BITS-691 | B37: Boopathi Palani | C37: 33749 | D37: MALE | E37: M.Palani | F37: Senior Technology Analyst | G37: kadayapatti village, Thippampatti PO, Dharmapuri Dist 635202 | H37: kadayapatti village, Thippampatti PO, Dharmapuri Dist 635202 | I37: 44564 | J37: OOOO | K37: OOOO | L37: OOOO | M37: OOOO | N37: 101153836004 | O37: N/A | P37: Boopathi Palani | Q37: 30 | R37: =VLOOKUP(A37,'[5]Pay sheet-APRIL- 2022'!$C$7:$AF$137,10,0) -> 30 | S37: N/A | T37: 75643 | U37: =VLOOKUP(A37,'[5]Pay sheet-APRIL- 2022'!$C$7:$AF$137,11,0) -> 45385.8 | V37: 0 | W37: 0 | X37: =Y37+Z37+AA37+AB37 -> 30370.2 | Y37: =VLOOKUP(A37,'[5]Pay sheet-APRIL- 2022'!$C$7:$AF$137,12,0) -> 18154.32 | Z37: =VLOOKUP(A37,'[5]Pay sheet-APRIL- 2022'!$C$7:$AF$137,13,0) -> 2083 | AA37: =VLOOKUP(A37,'[5]Pay sheet-APRIL- 2022'!$C$7:$AF$137,14,0) -> 2083 | AB37: =VLOOKUP(A37,'[5]Pay sheet-APRIL- 2022'!$C$7:$AF$137,15,0) -> 8049.88 | AC37: =U37+X37 -> 75756 | AD37: =VLOOKUP(A37,'[5]Pay sheet-APRIL- 2022'!$C$7:$AF$137,18,0) -> 1554.609 | AE37: =VLOOKUP(A37,'[5]Pay sheet-APRIL- 2022'!$C$7:$AF$137,19,0) -> 2183.057 | AF37: =VLOOKUP(A37,'[5]Pay sheet-APRIL- 2022'!$C$7:$AF$137,20,0) -> 3782.15 | AG37: =VLOOKUP(A37,'[5]Pay sheet-APRIL- 2022'!$C$7:$AF$137,22,0) -> 0 | AH37: =AC37+AD37+AE37+AF37+AG37 -> 83275.816 | AI37: 0 | AJ37: =VLOOKUP(A37,'[5]Pay sheet-APRIL- 2022'!$C$7:$AF$137,26,0) -> 1800 | AK37: =VLOOKUP(A37,'[5]Pay sheet-APRIL- 2022'!$C$7:$AF$137,25,0) -> 200 | AL37: =VLOOKUP(A37,'[5]Pay sheet-APRIL- 2022'!$C$7:$AF$137,24,0) -> 0 | AM37: =VLOOKUP(A37,'[5]Pay sheet-APRIL- 2022'!$C$7:$AF$137,27,0) -> 283 | AN37: =AI37+AJ37+AK37+AL37+AM37 -> 2283 | AO37: =AH37-AN37 -> 80992.816 | AP37: 44686 | AQ37: ICICI BANK | AR37: 603601537940 | AU37: 75 | AV37: 22
A38: BITS-693 | B38: JNANESWARARAO G | C38: 31527 | D38: MALE | E38: Subba Rao | F38: SENIOR SOFTWARE ENGINEER- MongoDB DBA | G38: H No 1-57/338,Sreeram nagar,Kondapur,Hyderabad 500084 | H38: H No 1-57/338,Sreeram nagar,Kondapur,Hyderabad 500084 | I38: 44562 | J38: OOOO | K38: OOOO | L38: OOOO | M38: OOOO | N38: 100848702184 | O38: N/A | P38: JNANESWARARAO G | Q38: 30 | R38: =VLOOKUP(A38,'[5]Pay sheet-APRIL- 2022'!$C$7:$AF$137,10,0) -> 30 | S38: N/A | T38: 96962 | U38: =VLOOKUP(A38,'[5]Pay sheet-APRIL- 2022'!$C$7:$AF$137,11,0) -> 58177.2 | V38: 0 | W38: 0 | X38: =Y38+Z38+AA38+AB38 -> 38897.8 | Y38: =VLOOKUP(A38,'[5]Pay sheet-APRIL- 2022'!$C$7:$AF$137,12,0) -> 23270.88 | Z38: =VLOOKUP(A38,'[5]Pay sheet-APRIL- 2022'!$C$7:$AF$137,13,0) -> 2083 | AA38: =VLOOKUP(A38,'[5]Pay sheet-APRIL- 2022'!$C$7:$AF$137,14,0) -> 2083 | AB38: =VLOOKUP(A38,'[5]Pay sheet-APRIL- 2022'!$C$7:$AF$137,15,0) -> 11460.92 | AC38: =U38+X38 -> 97075 | AD38: =VLOOKUP(A38,'[5]Pay sheet-APRIL- 2022'!$C$7:$AF$137,18,0) -> 1554.609 | AE38: =VLOOKUP(A38,'[5]Pay sheet-APRIL- 2022'!$C$7:$AF$137,19,0) -> 2798.3233 | AF38: =VLOOKUP(A38,'[5]Pay sheet-APRIL- 2022'!$C$7:$AF$137,20,0) -> 4848.1 | AG38: =VLOOKUP(A38,'[5]Pay sheet-APRIL- 2022'!$C$7:$AF$137,22,0) -> 14400 | AH38: =AC38+AD38+AE38+AF38+AG38 -> 120676.03 | AI38: 0 | AJ38: =VLOOKUP(A38,'[5]Pay sheet-APRIL- 2022'!$C$7:$AF$137,26,0) -> 1800 | AK38: =VLOOKUP(A38,'[5]Pay sheet-APRIL- 2022'!$C$7:$AF$137,25,0) -> 200 | AL38: =VLOOKUP(A38,'[5]Pay sheet-APRIL- 2022'!$C$7:$AF$137,24,0) -> 0 | AM38: =VLOOKUP(A38,'[5]Pay sheet-APRIL- 2022'!$C$7:$AF$137,27,0) -> 283 | AN38: =AI38+AJ38+AK38+AL38+AM38 -> 2283 | AO38: =AH38-AN38 -> 118393.03 | AP38: 44686 | AQ38: STATE BANK OF INDIA | AR38: 62404945568 | AU38: 76 | AV38: 23
A39: BITS-701 | B39: Shridhar Madlur | C39: 33977 | D39: MALE | E39: Hanamantappa Madlur | F39: Network Engineer | G39: Devaraj Aras Colony, Behind Eshwar Park, Koppal - 583231,Bangalore | H39: No. 36, Hari Nivas, 1st Block, 1st Main, BEL L/O, Vidyaranyapura Bengaluru-560097. | I39: 44594 | J39: OOOO | K39: OOOO | L39: OOOO | M39: OOOO | N39: 101364625395 | O39: N/A | P39: Shridhar Madlur | Q39: 30 | R39: =VLOOKUP(A39,'[5]Pay sheet-APRIL- 2022'!$C$7:$AF$137,10,0) -> 30 | S39: N/A | T39: 50617 | U39: =VLOOKUP(A39,'[5]Pay sheet-APRIL- 2022'!$C$7:$AF$137,11,0) -> 30370.2 | V39: 0 | W39: 0 | X39: =Y39+Z39+AA39+AB39 -> 20359.8 | Y39: =VLOOKUP(A39,'[5]Pay sheet-APRIL- 2022'!$C$7:$AF$137,12,0) -> 12148.08 | Z39: =VLOOKUP(A39,'[5]Pay sheet-APRIL- 2022'!$C$7:$AF$137,13,0) -> 2083 | AA39: =VLOOKUP(A39,'[5]Pay sheet-APRIL- 2022'!$C$7:$AF$137,14,0) -> 2083 | AB39: =VLOOKUP(A39,'[5]Pay sheet-APRIL- 2022'!$C$7:$AF$137,15,0) -> 4045.72 | AC39: =U39+X39 -> 50730 | AD39: =VLOOKUP(A39,'[5]Pay sheet-APRIL- 2022'!$C$7:$AF$137,18,0) -> 1554.609 | AE39: =VLOOKUP(A39,'[5]Pay sheet-APRIL- 2022'!$C$7:$AF$137,19,0) -> 1460.8066 | AF39: =VLOOKUP(A39,'[5]Pay sheet-APRIL- 2022'!$C$7:$AF$137,20,0) -> 2530.85 | AG39: =VLOOKUP(A39,'[5]Pay sheet-APRIL- 2022'!$C$7:$AF$137,22,0) -> 0 | AH39: =AC39+AD39+AE39+AF39+AG39 -> 56276.266 | AI39: 0 | AJ39: =VLOOKUP(A39,'[5]Pay sheet-APRIL- 2022'!$C$7:$AF$137,26,0) -> 1800 | AK39: =VLOOKUP(A39,'[5]Pay sheet-APRIL- 2022'!$C$7:$AF$137,25,0) -> 200 | AL39: =VLOOKUP(A39,'[5]Pay sheet-APRIL- 2022'!$C$7:$AF$137,24,0) -> 0 | AM39: =VLOOKUP(A39,'[5]Pay sheet-APRIL- 2022'!$C$7:$AF$137,27,0) -> 283 | AN39: =AI39+AJ39+AK39+AL39+AM39 -> 2283 | AO39: =AH39-AN39 -> 53993.266 | AP39: 44686 | AQ39: ICICI Bank | AR39: 93701529580 | AU39: 77 | AV39: 24
A40: BITS-702 | B40: Samarjit Saha | C40: 09-05-1978 | D40: MALE | E40: Gopal Chandra Saha | F40: Devopers Specialist | G40: 110,Sucheta Nagar-2, Rajmahal Apartment, 3rd floor,P.O:Haltu, Dist: South 24 Paraganas,City:Kolkata. State:West Bengal | H40: 110,Sucheta Nagar-2, Rajmahal Apartment, 3rd floor,P.O:Haltu, Dist: South 24 Paraganas,City:Kolkata. State:West Bengal | I40: 44594 | J40: OOOO | K40: OOOO | L40: OOOO | M40: OOOO | N40: 100329306766 | O40: N/A | P40: Samarjit Saha | Q40: 30 | R40: =VLOOKUP(A40,'[5]Pay sheet-APRIL- 2022'!$C$7:$AF$137,10,0) -> 30 | S40: N/A | T40: 126623 | U40: =VLOOKUP(A40,'[5]Pay sheet-APRIL- 2022'!$C$7:$AF$137,11,0) -> 75973.8 | V40: 0 | W40: 0 | X40: =Y40+Z40+AA40+AB40 -> 50762.2 | Y40: =VLOOKUP(A40,'[5]Pay sheet-APRIL- 2022'!$C$7:$AF$137,12,0) -> 30389.52 | Z40: =VLOOKUP(A40,'[5]Pay sheet-APRIL- 2022'!$C$7:$AF$137,13,0) -> 2083 | AA40: =VLOOKUP(A40,'[5]Pay sheet-APRIL- 2022'!$C$7:$AF$137,14,0) -> 2083 | AB40: =VLOOKUP(A40,'[5]Pay sheet-APRIL- 2022'!$C$7:$AF$137,15,0) -> 16206.68 | AC40: =U40+X40 -> 126736 | AD40: =VLOOKUP(A40,'[5]Pay sheet-APRIL- 2022'!$C$7:$AF$137,18,0) -> 1554.609 | AE40: =VLOOKUP(A40,'[5]Pay sheet-APRIL- 2022'!$C$7:$AF$137,19,0) -> 3654.3398 | AF40: =VLOOKUP(A40,'[5]Pay sheet-APRIL- 2022'!$C$7:$AF$137,20,0) -> 6331.15 | AG40: =VLOOKUP(A40,'[5]Pay sheet-APRIL- 2022'!$C$7:$AF$137,22,0) -> 0 | AH40: =AC40+AD40+AE40+AF40+AG40 -> 138276.1 | AI40: 0 | AJ40: =VLOOKUP(A40,'[5]Pay sheet-APRIL- 2022'!$C$7:$AF$137,26,0) -> 1800 | AK40: =VLOOKUP(A40,'[5]Pay sheet-APRIL- 2022'!$C$7:$AF$137,25,0) -> 200 | AL40: =VLOOKUP(A40,'[5]Pay sheet-APRIL- 2022'!$C$7:$AF$137,24,0) -> 0 | AM40: =VLOOKUP(A40,'[5]Pay sheet-APRIL- 2022'!$C$7:$AF$137,27,0) -> 283 | AN40: =AI40+AJ40+AK40+AL40+AM40 -> 2283 | AO40: =AH40-AN40 -> 135993.1 | AP40: 44686 | AQ40: HDFC | AR40: 5161140000905 | AU40: 78 | AV40: 25
A41: BITS-705 | B41: Narasimha rao Gurazala | C41: 33292 | D41: MALE | E41: G seshaiah | F41: Software Developer | G41: Hno 15-21-237/1,Flat no G2,sattenapally towers,Balaji Nagar,Kukatpally,Hyderabad,500072 | H41: Hno 15-21-237/1,Flat no G2,sattenapally towers,Balaji Nagar,Kukatpally,Hyderabad,500072 | I41: 44602 | J41: OOOO | K41: OOOO | L41: OOOO | M41: OOOO | N41: 100250029678 | O41: N/A | P41: Narasimha rao Gurazala | Q41: 30 | R41: =VLOOKUP(A41,'[5]Pay sheet-APRIL- 2022'!$C$7:$AF$137,10,0) -> 30 | S41: N/A | T41: 89547 | U41: =VLOOKUP(A41,'[5]Pay sheet-APRIL- 2022'!$C$7:$AF$137,11,0) -> 53728.2 | V41: 0 | W41: 0 | X41: =Y41+Z41+AA41+AB41 -> 35931.8 | Y41: =VLOOKUP(A41,'[5]Pay sheet-APRIL- 2022'!$C$7:$AF$137,12,0) -> 21491.28 | Z41: =VLOOKUP(A41,'[5]Pay sheet-APRIL- 2022'!$C$7:$AF$137,13,0) -> 2083 | AA41: =VLOOKUP(A41,'[5]Pay sheet-APRIL- 2022'!$C$7:$AF$137,14,0) -> 2083 | AB41: =VLOOKUP(A41,'[5]Pay sheet-APRIL- 2022'!$C$7:$AF$137,15,0) -> 10274.52 | AC41: =U41+X41 -> 89660 | AD41: =VLOOKUP(A41,'[5]Pay sheet-APRIL- 2022'!$C$7:$AF$137,18,0) -> 1554.609 | AE41: =VLOOKUP(A41,'[5]Pay sheet-APRIL- 2022'!$C$7:$AF$137,19,0) -> 2584.3264 | AF41: =VLOOKUP(A41,'[5]Pay sheet-APRIL- 2022'!$C$7:$AF$137,20,0) -> 4477.35 | AG41: =VLOOKUP(A41,'[5]Pay sheet-APRIL- 2022'!$C$7:$AF$137,22,0) -> 0 | AH41: =AC41+AD41+AE41+AF41+AG41 -> 98276.285 | AI41: 0 | AJ41: =VLOOKUP(A41,'[5]Pay sheet-APRIL- 2022'!$C$7:$AF$137,26,0) -> 1800 | AK41: =VLOOKUP(A41,'[5]Pay sheet-APRIL- 2022'!$C$7:$AF$137,25,0) -> 200 | AL41: =VLOOKUP(A41,'[5]Pay sheet-APRIL- 2022'!$C$7:$AF$137,24,0) -> 0 | AM41: =VLOOKUP(A41,'[5]Pay sheet-APRIL- 2022'!$C$7:$AF$137,27,0) -> 283 | AN41: =AI41+AJ41+AK41+AL41+AM41 -> 2283 | AO41: =AH41-AN41 -> 95993.285 | AP41: 44686 | AQ41: SBI | AR41: 33272355244 | AU41: 79 | AV41: 26
A42: BITS-718 | B42: Mahanth Devasani | C42: 33301 | D42: MALE | E42: KAILASAM DEVASANI | F42: Information Security Engineer | G42: 103, Sri datta sai residency, Budhha Nagar, Boduppal,Hyderabad | H42: H.no: 4-69/55/5/d/6, Vidyaranyapuri-3, Near apolo reach hospital, Karimnagar | I42: 44606 | J42: OOOO | K42: OOOO | L42: OOOO | M42: OOOO | N42: 100783978333 | O42: N/A | P42: Mahanth Devasani | Q42: 30 | R42: =VLOOKUP(A42,'[5]Pay sheet-APRIL- 2022'!$C$7:$AF$137,10,0) -> 30 | S42: N/A | T42: 145161 | U42: =VLOOKUP(A42,'[5]Pay sheet-APRIL- 2022'!$C$7:$AF$137,11,0) -> 87096.6 | V42: 0 | W42: 0 | X42: =Y42+Z42+AA42+AB42 -> 58177.4 | Y42: =VLOOKUP(A42,'[5]Pay sheet-APRIL- 2022'!$C$7:$AF$137,12,0) -> 34838.64 | Z42: =VLOOKUP(A42,'[5]Pay sheet-APRIL- 2022'!$C$7:$AF$137,13,0) -> 2083 | AA42: =VLOOKUP(A42,'[5]Pay sheet-APRIL- 2022'!$C$7:$AF$137,14,0) -> 2083 | AB42: =VLOOKUP(A42,'[5]Pay sheet-APRIL- 2022'!$C$7:$AF$137,15,0) -> 19172.76 | AC42: =U42+X42 -> 145274 | AD42: =VLOOKUP(A42,'[5]Pay sheet-APRIL- 2022'!$C$7:$AF$137,18,0) -> 1554.609 | AE42: =VLOOKUP(A42,'[5]Pay sheet-APRIL- 2022'!$C$7:$AF$137,19,0) -> 4189.3465 | AF42: =VLOOKUP(A42,'[5]Pay sheet-APRIL- 2022'!$C$7:$AF$137,20,0) -> 7258.05 | AG42: =VLOOKUP(A42,'[5]Pay sheet-APRIL- 2022'!$C$7:$AF$137,22,0) -> 0 | AH42: =AC42+AD42+AE42+AF42+AG42 -> 158276.01 | AI42: 0 | AJ42: =VLOOKUP(A42,'[5]Pay sheet-APRIL- 2022'!$C$7:$AF$137,26,0) -> 1800 | AK42: =VLOOKUP(A42,'[5]Pay sheet-APRIL- 2022'!$C$7:$AF$137,25,0) -> 200 | AL42: =VLOOKUP(A42,'[5]Pay sheet-APRIL- 2022'!$C$7:$AF$137,24,0) -> 0 | AM42: =VLOOKUP(A42,'[5]Pay sheet-APRIL- 2022'!$C$7:$AF$137,27,0) -> 283 | AN42: =AI42+AJ42+AK42+AL42+AM42 -> 2283 | AO42: =AH42-AN42 -> 155993.01 | AP42: 44686 | AQ42: SBI | AR42: 20165946904, | AU42: 80 | AV42: 27
A43: BITS-731 | B43: YAMUNA S | C43: 25/08/1992 | D43: FEMALE | E43: N VAMSI KRISHNA | F43: Sr Software Engineer | G43: Door no:22-965/6,kameshwar Nagar,Near Moruganipalli Road, Chittoor-517001,Andhrapradesh | H43: Door no:22-965/6,kameshwar Nagar,Near Moruganipalli Road, Chittoor-517001,Andhrapradesh | I43: 44631 | J43: OOOO | K43: OOOO | L43: OOOO | M43: OOOO | N43: QQQQ | O43: N/A | P43: YAMUNA S | Q43: 30 | R43: =VLOOKUP(A43,'[5]Pay sheet-APRIL- 2022'!$C$7:$AF$137,10,0) -> 30 | S43: N/A | T43: 121988 | U43: =VLOOKUP(A43,'[5]Pay sheet-APRIL- 2022'!$C$7:$AF$137,11,0) -> 73192.8 | V43: 0 | W43: 0 | X43: =Y43+Z43+AA43+AB43 -> 48908.2 | Y43: =VLOOKUP(A43,'[5]Pay sheet-APRIL- 2022'!$C$7:$AF$137,12,0) -> 29277.12 | Z43: =VLOOKUP(A43,'[5]Pay sheet-APRIL- 2022'!$C$7:$AF$137,13,0) -> 2083 | AA43: =VLOOKUP(A43,'[5]Pay sheet-APRIL- 2022'!$C$7:$AF$137,14,0) -> 2083 | AB43: =VLOOKUP(A43,'[5]Pay sheet-APRIL- 2022'!$C$7:$AF$137,15,0) -> 15465.08 | AC43: =U43+X43 -> 122101 | AD43: =VLOOKUP(A43,'[5]Pay sheet-APRIL- 2022'!$C$7:$AF$137,18,0) -> 1554.609 | AE43: =VLOOKUP(A43,'[5]Pay sheet-APRIL- 2022'!$C$7:$AF$137,19,0) -> 3520.5737 | AF43: =VLOOKUP(A43,'[5]Pay sheet-APRIL- 2022'!$C$7:$AF$137,20,0) -> 6099.4 | AG43: =VLOOKUP(A43,'[5]Pay sheet-APRIL- 2022'!$C$7:$AF$137,22,0) -> 0 | AH43: =AC43+AD43+AE43+AF43+AG43 -> 133275.58 | AI43: 0 | AJ43: =VLOOKUP(A43,'[5]Pay sheet-APRIL- 2022'!$C$7:$AF$137,26,0) -> 1800 | AK43: =VLOOKUP(A43,'[5]Pay sheet-APRIL- 2022'!$C$7:$AF$137,25,0) -> 200 | AL43: =VLOOKUP(A43,'[5]Pay sheet-APRIL- 2022'!$C$7:$AF$137,24,0) -> 0 | AM43: =VLOOKUP(A43,'[5]Pay sheet-APRIL- 2022'!$C$7:$AF$137,27,0) -> 283 | AN43: =AI43+AJ43+AK43+AL43+AM43 -> 2283 | AO43: =AH43-AN43 -> 130992.58 | AP43: 44686 | AQ43: Axis Bank | AR43: 922010002162775 | AU43: 81 | AV43: 28
A44: BITS-732 | B44: Chetan Madhukar Mundhe | C44: 31430 | D44: MALE | E44: Madhukar kondiran munde | F44: Technical Consultant | G44: B 41, Mahaveer Park, PUNE, satara road, Bibwewadi pune, 411037 | H44: 14 gulmohar colony,Jti Road, Shanupuri, Satara, 415002 | I44: 44635 | J44: OOOO | K44: OOOO | L44: OOOO | M44: OOOO | N44: 100770453041 | O44: N/A | P44: Chetan Madhukar Mundhe | Q44: 30 | R44: =VLOOKUP(A44,'[5]Pay sheet-APRIL- 2022'!$C$7:$AF$137,10,0) -> 30 | S44: N/A | T44: 112719 | U44: =VLOOKUP(A44,'[5]Pay sheet-APRIL- 2022'!$C$7:$AF$137,11,0) -> 67631.4 | V44: 0 | W44: 0 | X44: =Y44+Z44+AA44+AB44 -> 45200.6 | Y44: =VLOOKUP(A44,'[5]Pay sheet-APRIL- 2022'!$C$7:$AF$137,12,0) -> 27052.56 | Z44: =VLOOKUP(A44,'[5]Pay sheet-APRIL- 2022'!$C$7:$AF$137,13,0) -> 2083 | AA44: =VLOOKUP(A44,'[5]Pay sheet-APRIL- 2022'!$C$7:$AF$137,14,0) -> 2083 | AB44: =VLOOKUP(A44,'[5]Pay sheet-APRIL- 2022'!$C$7:$AF$137,15,0) -> 13982.04 | AC44: =U44+X44 -> 112832 | AD44: =VLOOKUP(A44,'[5]Pay sheet-APRIL- 2022'!$C$7:$AF$137,18,0) -> 1554.609 | AE44: =VLOOKUP(A44,'[5]Pay sheet-APRIL- 2022'!$C$7:$AF$137,19,0) -> 3253.0703 | AF44: =VLOOKUP(A44,'[5]Pay sheet-APRIL- 2022'!$C$7:$AF$137,20,0) -> 5635.95 | AG44: =VLOOKUP(A44,'[5]Pay sheet-APRIL- 2022'!$C$7:$AF$137,22,0) -> 0 | AH44: =AC44+AD44+AE44+AF44+AG44 -> 123275.63 | AI44: 0 | AJ44: =VLOOKUP(A44,'[5]Pay sheet-APRIL- 2022'!$C$7:$AF$137,26,0) -> 1800 | AK44: =VLOOKUP(A44,'[5]Pay sheet-APRIL- 2022'!$C$7:$AF$137,25,0) -> 200 | AL44: =VLOOKUP(A44,'[5]Pay sheet-APRIL- 2022'!$C$7:$AF$137,24,0) -> 0 | AM44: =VLOOKUP(A44,'[5]Pay sheet-APRIL- 2022'!$C$7:$AF$137,27,0) -> 283 | AN44: =AI44+AJ44+AK44+AL44+AM44 -> 2283 | AO44: =AH44-AN44 -> 120992.63 | AP44: 44686 | AQ44: SBI | AR44: 62339873786 | AU44: 82 | AV44: 29
A45: BITS-734 | B45: Sathish Kumar dhandu | C45: 33257 | D45: MALE | E45: Shiva shankar | F45: Technical Consultant | G45: 1/3A,BC colony,Lachannapally,Ananthapur,AP 515401 | H45: 1/3A,BC colony,Lachannapally,Ananthapur,AP 515401 | I45: 44636 | J45: OOOO | K45: OOOO | L45: OOOO | M45: OOOO | N45: QQQQ | O45: N/A | P45: Sathish Kumar dhandu | Q45: 30 | R45: =VLOOKUP(A45,'[5]Pay sheet-APRIL- 2022'!$C$7:$AF$137,10,0) -> 30 | S45: N/A | T45: 84812.825 | U45: =VLOOKUP(A45,'[5]Pay sheet-APRIL- 2022'!$C$122:$AH$122,11,0) -> 50887.2 | V45: 0 | W45: 0 | X45: =Y45+Z45+AA45+AB45 -> 34038 | Y45: 20355 | Z45: =VLOOKUP(A45,'[5]Pay sheet-APRIL- 2022'!$C$7:$AF$137,13,0) -> 2083 | AA45: =VLOOKUP(A45,'[5]Pay sheet-APRIL- 2022'!$C$7:$AF$137,14,0) -> 2083 | AB45: 9517 | AC45: =U45+X45 -> 84925.2 | AD45: =VLOOKUP(A45,'[5]Pay sheet-APRIL- 2022'!$C$7:$AF$137,18,0) -> 1554.609 | AE45: 2448 | AF45: 4241 | AG45: =VLOOKUP(A45,'[5]Pay sheet-APRIL- 2022'!$C$7:$AF$137,22,0) -> 0 | AH45: =AC45+AD45+AE45+AF45+AG45 -> 93168.809 | AI45: 0 | AJ45: 0 | AK45: =VLOOKUP(A45,'[5]Pay sheet-APRIL- 2022'!$C$7:$AF$137,25,0) -> 200 | AL45: 0 | AM45: =VLOOKUP(A45,'[5]Pay sheet-APRIL- 2022'!$C$7:$AF$137,27,0) -> 283 | AN45: =AI45+AJ45+AK45+AL45+AM45 -> 483 | AO45: =AH45-AN45 -> 92685.809 | AP45: 44686 | AQ45: SBI | AR45: 32442653960 | AU45: 83 | AV45: 30
A46: BITS-739 | B46: Praveen Kumar GATTU | C46: 33606 | D46: MALE | E46: G Muniratnam | F46: System Administrator | G46: 30-104, Kalyanapuram,st colony, puttur, Chittoor, AP 517583 | H46: 30-104, Kalyanapuram,st colony, puttur, Chittoor, AP 517583 | I46: 44648 | J46: OOOO | K46: OOOO | L46: OOOO | M46: OOOO | N46: 100515794652 | O46: N/A | P46: Praveen Kumar GATTU | Q46: 30 | R46: =VLOOKUP(A46,'[5]Pay sheet-APRIL- 2022'!$C$7:$AF$137,10,0) -> 30 | S46: N/A | T46: 80278 | U46: =VLOOKUP(A46,'[5]Pay sheet-APRIL- 2022'!$C$7:$AF$137,11,0) -> 48166.8 | V46: 0 | W46: 0 | X46: =Y46+Z46+AA46+AB46 -> 32224.2 | Y46: =VLOOKUP(A46,'[5]Pay sheet-APRIL- 2022'!$C$7:$AF$137,12,0) -> 19266.72 | Z46: =VLOOKUP(A46,'[5]Pay sheet-APRIL- 2022'!$C$7:$AF$137,13,0) -> 2083 | AA46: =VLOOKUP(A46,'[5]Pay sheet-APRIL- 2022'!$C$7:$AF$137,14,0) -> 2083 | AB46: =VLOOKUP(A46,'[5]Pay sheet-APRIL- 2022'!$C$7:$AF$137,15,0) -> 8791.48 | AC46: =U46+X46 -> 80391 | AD46: =VLOOKUP(A46,'[5]Pay sheet-APRIL- 2022'!$C$7:$AF$137,18,0) -> 1554.609 | AE46: =VLOOKUP(A46,'[5]Pay sheet-APRIL- 2022'!$C$7:$AF$137,19,0) -> 2316.8231 | AF46: =VLOOKUP(A46,'[5]Pay sheet-APRIL- 2022'!$C$7:$AF$137,20,0) -> 4013.9 | AG46: =VLOOKUP(A46,'[5]Pay sheet-APRIL- 2022'!$C$7:$AF$137,22,0) -> 0 | AH46: =AC46+AD46+AE46+AF46+AG46 -> 88276.332 | AI46: 0 | AJ46: =VLOOKUP(A46,'[5]Pay sheet-APRIL- 2022'!$C$7:$AF$137,26,0) -> 1800 | AK46: =VLOOKUP(A46,'[5]Pay sheet-APRIL- 2022'!$C$7:$AF$137,25,0) -> 200 | AL46: =VLOOKUP(A46,'[5]Pay sheet-APRIL- 2022'!$C$7:$AF$137,24,0) -> 0 | AM46: =VLOOKUP(A46,'[5]Pay sheet-APRIL- 2022'!$C$7:$AF$137,27,0) -> 283 | AN46: =AI46+AJ46+AK46+AL46+AM46 -> 2283 | AO46: =AH46-AN46 -> 85993.332 | AP46: 44686 | AQ46: Axis Bank | AR46: 915010017171911 | AU46: 84 | AV46: 31
A47: BITS-743 | B47: Vinoth Vairavan | C47: 31514 | D47: MALE | E47: Vairavan | F47: SR, NETWORK ENGINEER | G47: 127/69,Anna nagar,Pattu kottal,Thanjavur district,Tamil nadu,614601 | H47: No.21,Neminathal nagar,Shakthi nagar ext.,Back side Annie School,Mudichur,Chennai-48 | I47: 44657 | J47: OOOO | K47: OOOO | L47: OOOO | M47: OOOO | N47: 100766312722 | O47: N/A | P47: Vinoth Vairavan | Q47: 30 | R47: =VLOOKUP(A47,'[5]Pay sheet-APRIL- 2022'!$C$7:$AF$137,10,0) -> 25 | S47: N/A | T47: 135892 | U47: =VLOOKUP(A47,'[5]Pay sheet-APRIL- 2022'!$C$7:$AF$137,11,0) -> 67946 | V47: 0 | W47: 0 | X47: =Y47+Z47+AA47+AB47 -> 45410.333 | Y47: =VLOOKUP(A47,'[5]Pay sheet-APRIL- 2022'!$C$7:$AF$137,12,0) -> 27178.4 | Z47: =VLOOKUP(A47,'[5]Pay sheet-APRIL- 2022'!$C$7:$AF$137,13,0) -> 1736 | AA47: =VLOOKUP(A47,'[5]Pay sheet-APRIL- 2022'!$C$7:$AF$137,14,0) -> 1736 | AB47: =VLOOKUP(A47,'[5]Pay sheet-APRIL- 2022'!$C$7:$AF$137,15,0) -> 14759.933 | AC47: =U47+X47 -> 113356.33 | AD47: =VLOOKUP(A47,'[5]Pay sheet-APRIL- 2022'!$C$7:$AF$137,18,0) -> 1554.609 | AE47: =VLOOKUP(A47,'[5]Pay sheet-APRIL- 2022'!$C$7:$AF$137,19,0) -> 3268.2026 | AF47: =VLOOKUP(A47,'[5]Pay sheet-APRIL- 2022'!$C$7:$AF$137,20,0) -> 5662.1667 | AG47: =VLOOKUP(A47,'[5]Pay sheet-APRIL- 2022'!$C$7:$AF$137,22,0) -> 0 | AH47: =AC47+AD47+AE47+AF47+AG47 -> 123841.31 | AI47: 0 | AJ47: =VLOOKUP(A47,'[5]Pay sheet-APRIL- 2022'!$C$7:$AF$137,26,0) -> 1800 | AK47: =VLOOKUP(A47,'[5]Pay sheet-APRIL- 2022'!$C$7:$AF$137,25,0) -> 200 | AL47: =VLOOKUP(A47,'[5]Pay sheet-APRIL- 2022'!$C$7:$AF$137,24,0) -> 0 | AM47: =VLOOKUP(A47,'[5]Pay sheet-APRIL- 2022'!$C$7:$AF$137,27,0) -> 0 | AN47: =AI47+AJ47+AK47+AL47+AM47 -> 2000 | AO47: =AH47-AN47 -> 121841.31 | AP47: 44686 | AQ47: AXIS Bank | AR47: 916010024710764 | AU47: 85 | AV47: 32
A48: BITS-747 | B48: Govarthanan TK | C48: 31863 | D48: MALE | E48: Kumaraswamy papaiya | F48: IT Project Manager | G48: 94A,AK Abhinayam Appts,F Block,1st floor,2nd main road,Thankikachalam nagar west,Ponniya manmedeo,chennai,Tamil nadu,600110 | H48: 94A,AK Abhinayam Appts,F Block,1st floor,2nd main road,Thankikachalam nagar west,Ponniya manmedeo,chennai,Tamil nadu,600110 | I48: 44662 | J48: OOOO | K48: OOOO | L48: OOOO | M48: OOOO | N48: 100159339504 | O48: N/A | P48: Govarthanan TK | Q48: 30 | R48: =VLOOKUP(A48,'[5]Pay sheet-APRIL- 2022'!$C$7:$AF$137,10,0) -> 20 | S48: N/A | T48: 121988 | U48: =VLOOKUP(A48,'[5]Pay sheet-APRIL- 2022'!$C$7:$AF$137,11,0) -> 48795.2 | V48: 0 | W48: 0 | X48: =Y48+Z48+AA48+AB48 -> 32643.133 | Y48: =VLOOKUP(A48,'[5]Pay sheet-APRIL- 2022'!$C$7:$AF$137,12,0) -> 19518.08 | Z48: =VLOOKUP(A48,'[5]Pay sheet-APRIL- 2022'!$C$7:$AF$137,13,0) -> 1389 | AA48: =VLOOKUP(A48,'[5]Pay sheet-APRIL- 2022'!$C$7:$AF$137,14,0) -> 1389 | AB48: =VLOOKUP(A48,'[5]Pay sheet-APRIL- 2022'!$C$7:$AF$137,15,0) -> 10347.053 | AC48: =U48+X48 -> 81438.333 | AD48: =VLOOKUP(A48,'[5]Pay sheet-APRIL- 2022'!$C$7:$AF$137,18,0) -> 1554.609 | AE48: =VLOOKUP(A48,'[5]Pay sheet-APRIL- 2022'!$C$7:$AF$137,19,0) -> 2347.0491 | AF48: =VLOOKUP(A48,'[5]Pay sheet-APRIL- 2022'!$C$7:$AF$137,20,0) -> 4066.2667 | AG48: =VLOOKUP(A48,'[5]Pay sheet-APRIL- 2022'!$C$7:$AF$137,22,0) -> 0 | AH48: =AC48+AD48+AE48+AF48+AG48 -> 89406.258 | AI48: 0 | AJ48: =VLOOKUP(A48,'[5]Pay sheet-APRIL- 2022'!$C$7:$AF$137,26,0) -> 1800 | AK48: =VLOOKUP(A48,'[5]Pay sheet-APRIL- 2022'!$C$7:$AF$137,25,0) -> 200 | AL48: =VLOOKUP(A48,'[5]Pay sheet-APRIL- 2022'!$C$7:$AF$137,24,0) -> 0 | AM48: =VLOOKUP(A48,'[5]Pay sheet-APRIL- 2022'!$C$7:$AF$137,27,0) -> 0 | AN48: =AI48+AJ48+AK48+AL48+AM48 -> 2000 | AO48: =AH48-AN48 -> 87406.258 | AP48: 44686 | AQ48: CITI Bank | AR48: 5708925554 | AU48: 86 | AV48: 33
A49: BITS-749 | B49: Laxmi Soujanya Mudunuri | C49: 33107 | D49: FEMALE | E49: Venkata Satya narayana Raju | F49: Senior Middleware Consultant | G49: 25-10-20,Fire station opposite road,Beside sai baba temple,NR Pet,W G Dt.,Eluru,AP 534006 | H49: 25-10-20,Fire station opposite road,Beside sai baba temple,NR Pet,W G Dt.,Eluru,AP 534006 | I49: 44671 | J49: OOOO | K49: OOOO | L49: OOOO | M49: OOOO | N49: 100619683716 | O49: N/A | P49: Laxmi Soujanya Mudunuri | Q49: 30 | R49: =VLOOKUP(A49,'[5]Pay sheet-APRIL- 2022'!$C$7:$AF$137,10,0) -> 11 | S49: N/A | T49: 159065 | U49: =VLOOKUP(A49,'[5]Pay sheet-APRIL- 2022'!$C$7:$AF$137,11,0) -> 34994.3 | V49: 0 | W49: 0 | X49: =Y49+Z49+AA49+AB49 -> 23442.533 | Y49: =VLOOKUP(A49,'[5]Pay sheet-APRIL- 2022'!$C$7:$AF$137,12,0) -> 13997.72 | Z49: =VLOOKUP(A49,'[5]Pay sheet-APRIL- 2022'!$C$7:$AF$137,13,0) -> 764 | AA49: =VLOOKUP(A49,'[5]Pay sheet-APRIL- 2022'!$C$7:$AF$137,14,0) -> 764 | AB49: =VLOOKUP(A49,'[5]Pay sheet-APRIL- 2022'!$C$7:$AF$137,15,0) -> 7916.8133 | AC49: =U49+X49 -> 58436.833 | AD49: =VLOOKUP(A49,'[5]Pay sheet-APRIL- 2022'!$C$7:$AF$137,18,0) -> 1554.609 | AE49: =VLOOKUP(A49,'[5]Pay sheet-APRIL- 2022'!$C$7:$AF$137,19,0) -> 1683.2258 | AF49: =VLOOKUP(A49,'[5]Pay sheet-APRIL- 2022'!$C$7:$AF$137,20,0) -> 2916.1917 | AG49: =VLOOKUP(A49,'[5]Pay sheet-APRIL- 2022'!$C$7:$AF$137,22,0) -> 0 | AH49: =AC49+AD49+AE49+AF49+AG49 -> 64590.86 | AI49: 0 | AJ49: =VLOOKUP(A49,'[5]Pay sheet-APRIL- 2022'!$C$7:$AF$137,26,0) -> 1800 | AK49: =VLOOKUP(A49,'[5]Pay sheet-APRIL- 2022'!$C$7:$AF$137,25,0) -> 200 | AL49: =VLOOKUP(A49,'[5]Pay sheet-APRIL- 2022'!$C$7:$AF$137,24,0) -> 0 | AM49: =VLOOKUP(A49,'[5]Pay sheet-APRIL- 2022'!$C$7:$AF$137,27,0) -> 0 | AN49: =AI49+AJ49+AK49+AL49+AM49 -> 2000 | AO49: =AH49-AN49 -> 62590.86 | AP49: 44686 | AQ49: Axis Bank | AR49: 915010032166004 | AU49: 87 | AV49: 34
R50: =SUM(R16:R49) -> 923 | S50: =SUM(S16:S49) -> 0 | T50: =SUM(T16:T49) -> 3194647.8 | U50: =SUM(U16:U49) -> 1732148.7 | V50: =SUM(V16:V49) -> 0 | W50: =SUM(W16:W49) -> 0 | X50: =SUM(X16:X49) -> 1158607.7 | Y50: =SUM(Y16:Y49) -> 692859.8 | ... AO50: =SUM(AO16:AO49) -> 3110503.4

Sheet 04-22Eql rem
A1: Form D
A2: (See rule 6)
A4: Register to be maintained by the employer under rule 6 of the Equal Remuneration Rules, 1976
D6: ='04-22Master'!D10 -> 44652
A8: Name and address of Contractor : | F8: ='04-22Master'!F5 -> Burgeon IT Services Pvt.Ltd.
A10: Name and address of establishment in/under which contract is carried on : | F10: ='04-22Master'!AK5 -> Burgeon IT Services Pvt.Ltd.
F11: ='04-22Master'!AK6 -> Siri Mansion LIGB 436 Dr.A S Rao Nagar,Hyderabad
A12: Name and address of Principal Employer : | F12: ='04-22Master'!AK10 -> INFOSYS LTD.IL Bangalore STP Park - I
F13: ='04-22Master'!AK11 -> No.45&46,3rd Cross,Electronic City,BANGALORE,KARNATAKA
A14: Total number of men workers employed | C14: =D54 -> 31
A16: Total number of women workers employed | C16: =C54 -> 3
C18: Components of remuneration
A19: Category of workers | B19: Brief Description of work | C19: No of women employed | D19: No. of men employed | E19: Rate or remuneration paid | F19: Basic wage & Dearness Allowance | G19: House Rent allowance | H19: Other allowances | I19: Cash value of concessional supply of essential commodities | J19: Name of the Client | K19: Primary Work Place/ Location
A20: ='04-22Master'!F16 -> Network security engineer | B20: IT SUPPORTIVE SERVICES | C20: 0 | D20: 1 | E20: ='04-22Master'!T16 -> 135892 | F20: ='04-22Master'!U16 -> 81535.2 | G20: ='04-22Master'!Y16 -> 32614.08 | H20: =E20-(F20+G20) -> 21742.72 | I20: 0
A21: ='04-22Master'!F17 -> Citrix Administrator | B21: IT SUPPORTIVE SERVICES | C21: 0 | D21: 1 | E21: ='04-22Master'!T17 -> 66374 | F21: ='04-22Master'!U17 -> 39824.4 | G21: ='04-22Master'!Y17 -> 15929.76 | H21: =E21-(F21+G21) -> 10619.84 | I21: 0
A22: ='04-22Master'!F18 -> Ansible Developer | B22: IT SUPPORTIVE SERVICES | C22: 1 | D22: 0 | E22: ='04-22Master'!T18 -> 20029 | F22: ='04-22Master'!U18 -> 12017.4 | G22: ='04-22Master'!Y18 -> 4806.96 | H22: =E22-(F22+G22) -> 3204.64 | I22: 0
A23: ='04-22Master'!F19 -> Senior Middleware Administrator (MQ & Kafka) | B23: IT SUPPORTIVE SERVICES | C23: 0 | D23: 1 | E23: ='04-22Master'!T19 -> 121988 | F23: ='04-22Master'!U19 -> 68313.28 | G23: ='04-22Master'!Y19 -> 27325.312 | H23: =E23-(F23+G23) -> 26349.408 | I23: 0
A24: ='04-22Master'!F20 -> Oracle/SAP DBA | B24: IT SUPPORTIVE SERVICES | C24: 0 | D24: 1 | E24: ='04-22Master'!T20 -> 135892 | F24: ='04-22Master'!U20 -> 81535.2 | G24: ='04-22Master'!Y20 -> 32614.08 | H24: =E24-(F24+G24) -> 21742.72 | I24: 0
A25: ='04-22Master'!F21 -> Principal Storage Consultant | B25: IT SUPPORTIVE SERVICES | C25: 0 | D25: 1 | E25: ='04-22Master'!T21 -> 94181 | F25: ='04-22Master'!U21 -> 56508.6 | G25: ='04-22Master'!Y21 -> 22603.44 | H25: =E25-(F25+G25) -> 15068.96 | I25: 0
A26: ='04-22Master'!F22 -> Windows Administrator | B26: IT SUPPORTIVE SERVICES | C26: 0 | D26: 1 | E26: ='04-22Master'!T22 -> 84912 | F26: ='04-22Master'!U22 -> 22077.12 | G26: ='04-22Master'!Y22 -> 8830.848 | H26: =E26-(F26+G26) -> 54004.032 | I26: 0
A27: ='04-22Master'!F23 -> VMware & Wintel Admin | B27: IT SUPPORTIVE SERVICES | C27: 0 | D27: 1 | E27: ='04-22Master'!T23 -> 58959 | F27: ='04-22Master'!U23 -> 15329.34 | G27: ='04-22Master'!Y23 -> 6131.736 | H27: =E27-(F27+G27) -> 37497.924 | I27: 0
A28: ='04-22Master'!F24 -> Sr. Network Administrator | B28: IT SUPPORTIVE SERVICES | C28: 0 | D28: 1 | E28: ='04-22Master'!T24 -> 47836 | F28: ='04-22Master'!U24 -> 28701.6 | G28: ='04-22Master'!Y24 -> 11480.64 | H28: =E28-(F28+G28) -> 7653.76 | I28: 0
A29: ='04-22Master'!F25 -> SENIOR TECHNICAL SPECIALIST | B29: IT SUPPORTIVE SERVICES | C29: 0 | D29: 1 | E29: ='04-22Master'!T25 -> 50617 | F29: ='04-22Master'!U25 -> 15185.1 | G29: ='04-22Master'!Y25 -> 6074.04 | H29: =E29-(F29+G29) -> 29357.86 | I29: 0
A30: ='04-22Master'!F27 -> Linux Administrator | B30: IT SUPPORTIVE SERVICES | C30: 0 | D30: 1 | E30: ='04-22Master'!T27 -> 47836 | F30: ='04-22Master'!U27 -> 28701.6 | G30: ='04-22Master'!Y27 -> 11480.64 | H30: =E30-(F30+G30) -> 7653.76 | I30: 0
A31: ='04-22Master'!F28 -> Senior Network Engineer | B31: IT SUPPORTIVE SERVICES | C31: 0 | D31: 1 | E31: ='04-22Master'!T28 -> 47836 | F31: ='04-22Master'!U28 -> 19134.4 | G31: ='04-22Master'!Y28 -> 7653.76 | H31: =E31-(F31+G31) -> 21047.84 | I31: 0
A32: ='04-22Master'!F29 -> Senior EUC Analyst | B32: IT SUPPORTIVE SERVICES | C32: 0 | D32: 1 | E32: ='04-22Master'!T29 -> 89547 | F32: ='04-22Master'!U29 -> 53728.2 | G32: ='04-22Master'!Y29 -> 21491.28 | H32: =E32-(F32+G32) -> 14327.52 | I32: 0
A33: ='BGLR STP APRIL 22-WM Reg'!F122 -> Sr Devops Engineers | B33: IT SUPPORTIVE SERVICES | C33: 0 | D33: 1 | E33: ='BGLR STP APRIL 22-WM Reg'!T122 -> 94181 | F33: ='BGLR STP APRIL 22-WM Reg'!U122 -> 56508.6 | G33: ='BGLR STP APRIL 22-WM Reg'!Y122 -> 22603.44 | H33: =E33-(F33+G33) -> 15068.96 | I33: 0
A34: ='04-22Master'!F30 -> Windows and Assure Administrator | B34: IT SUPPORTIVE SERVICES | C34: 0 | D34: 1 | E34: ='04-22Master'!T30 -> 36713 | F34: ='04-22Master'!U30 -> 22027.8 | G34: ='04-22Master'!Y30 -> 8811.12 | H34: =E34-(F34+G34) -> 5874.08 | I34: 0
A35: ='04-22Master'!F31 -> Network Engineer | B35: IT SUPPORTIVE SERVICES | C35: 0 | D35: 1 | E35: ='04-22Master'!T31 -> 36713 | F35: ='04-22Master'!U31 -> 22027.8 | G35: ='04-22Master'!Y31 -> 8811.12 | H35: =E35-(F35+G35) -> 5874.08 | I35: 0
A36: ='04-22Master'!F32 -> Lead Devops Engineer | B36: IT SUPPORTIVE SERVICES | C36: 0 | D36: 1 | E36: ='04-22Master'!T32 -> 223948 | F36: ='04-22Master'!U32 -> 134368.8 | G36: ='04-22Master'!Y32 -> 53747.52 | H36: =E36-(F36+G36) -> 35831.68 | I36: 0
A37: ='04-22Master'!F33 -> SENIOR SAP ABAP CONSULTANT | B37: IT SUPPORTIVE SERVICES | C37: 0 | D37: 1 | E37: ='04-22Master'!T33 -> 191506 | F37: ='04-22Master'!U33 -> 107243.36 | G37: ='04-22Master'!Y33 -> 42897.344 | H37: =E37-(F37+G37) -> 41365.296 | I37: 0
A38: ='04-22Master'!F34 -> Associate Consultant | B38: IT SUPPORTIVE SERVICES | C38: 0 | D38: 1 | E38: ='04-22Master'!T34 -> 80278 | F38: ='04-22Master'!U34 -> 48167 | G38: ='04-22Master'!Y34 -> 19267 | H38: =E38-(F38+G38) -> 12844 | I38: 0
A39: ='04-22Master'!F35 -> Sr.Linux Admin | B39: IT SUPPORTIVE SERVICES | C39: 0 | D39: 1 | E39: ='04-22Master'!T35 -> 98816 | F39: ='04-22Master'!U35 -> 59289.6 | G39: ='04-22Master'!Y35 -> 23715.84 | H39: =E39-(F39+G39) -> 15810.56 | I39: 0
A40: ='04-22Master'!F36 -> Technical Consultant | B40: IT SUPPORTIVE SERVICES | C40: 0 | D40: 1 | E40: ='04-22Master'!T36 -> 75643 | F40: ='04-22Master'!U36 -> 45385.8 | G40: ='04-22Master'!Y36 -> 18154.32 | H40: =E40-(F40+G40) -> 12102.88 | I40: 0
A41: ='04-22Master'!F37 -> Senior Technology Analyst | B41: IT SUPPORTIVE SERVICES | C41: 0 | D41: 1 | E41: ='04-22Master'!T37 -> 75643 | F41: ='04-22Master'!U37 -> 45385.8 | G41: ='04-22Master'!Y37 -> 18154.32 | H41: =E41-(F41+G41) -> 12102.88 | I41: 0
A42: ='04-22Master'!F38 -> SENIOR SOFTWARE ENGINEER- MongoDB DBA | B42: IT SUPPORTIVE SERVICES | C42: 0 | D42: 1 | E42: ='04-22Master'!T38 -> 96962 | F42: ='04-22Master'!U38 -> 58177.2 | G42: ='04-22Master'!Y38 -> 23270.88 | H42: =E42-(F42+G42) -> 15513.92 | I42: 0
A43: ='04-22Master'!F39 -> Network Engineer | B43: IT SUPPORTIVE SERVICES | C43: 0 | D43: 1 | E43: ='04-22Master'!T39 -> 50617 | F43: ='04-22Master'!U39 -> 30370.2 | G43: ='04-22Master'!Y39 -> 12148.08 | H43: =E43-(F43+G43) -> 8098.72 | I43: 0
A44: ='04-22Master'!F40 -> Devopers Specialist | B44: IT SUPPORTIVE SERVICES | C44: 0 | D44: 1 | E44: ='04-22Master'!T40 -> 126623 | F44: ='04-22Master'!U40 -> 75973.8 | G44: ='04-22Master'!Y40 -> 30389.52 | H44: =E44-(F44+G44) -> 20259.68 | I44: 0
A45: ='04-22Master'!F41 -> Software Developer | B45: IT SUPPORTIVE SERVICES | C45: 0 | D45: 1 | E45: ='04-22Master'!T41 -> 89547 | F45: ='04-22Master'!U41 -> 53728.2 | G45: ='04-22Master'!Y41 -> 21491.28 | H45: =E45-(F45+G45) -> 14327.52 | I45: 0
... A53: ='04-22Master'!F49 -> Senior Middleware Consultant | B53: IT SUPPORTIVE SERVICES | C53: 1 | D53: 0 | E53: ='04-22Master'!T49 -> 159065 | F53: ='04-22Master'!U49 -> 34994.3 | G53: ='04-22Master'!Y49 -> 13997.72 | H53: =E53-(F53+G53) -> 110072.98 | I53: 0
C54: =SUM(C20:C53) -> 3 | D54: =SUM(D20:D53) -> 31
H63: Signature of the Contractor with Seal

Sheet 04-22F-T ATTEN
A1: FORM T
A2: [See Rule 24(9-B)]
A3: Combined Muster Roll-cum-Register of Wages in lieu of
A4: 1. Forms I and II of Rule 22(4); Form IV of Rule 2R(2) and Forms V and VII of Rule 29(1) and (5) of Minimum Wages (Karnataka) Rules, 1958.
A5: 2. Form I of Rule 3(1) of Payment of Wages (Karnataka) Rules, 1963.
A6: 3. Form XIII of Rule 75 and Forms XV, XVII,.XX, XXI, XXII and XXIII of Rule 78(1)(a)(i), (ii) and (iii) of Contract Labour (Regulation and Abolition) (Karnataka) Rules, 1974.
A7: 4. Form XIII of Rule 43 and Forms XVII, XVIII, XIX, XX, XXI and XXII of Rule 46(2)(a), (c) and (d) of Inter-State Migrant Workmen (Regulation of Employment and Conditions of Service) (Karnataka) Rules, 1981.
A8: Name & address of the Establishment: | AA8: Name and Address of Principal employer:
A9: ='04-22Master'!F5 -> Burgeon IT Services Pvt.Ltd. | Q9: Month & Year | AA9: ='04-22Master'!AK10 -> INFOSYS LTD.IL Bangalore STP Park - I
A10: ='04-22Master'!F6 -> Siri Mansion LIGB 436 Dr.A S Rao Nagar,Hyderabad | P10: ='04-22Master'!D10 -> 44652 | AA10: ='04-22Master'!AK11 -> No.45&46,3rd Cross,Electronic City,BANGALORE,KARNATAKA
A11: ='04-22Master'!F7 -> 0
A12: Sl. No. | B12: Name of the Employee Father/Husband Name | C12: Father/Husband Name | D12: Male / Female | E12: Designation | F12: Department | G12: Site Address | H12: Date of joining | I12: ESI No. | J12: PF No. | K12: Wages fixed including VDA | L12: (9) Attendance | AQ12: No. of Payable Days | AR12: Total OT hours worked | BF12: Month / Year | BJ12: ='04-22Master'!D10 -> 44652 | BN12: Deductions | BQ12: Net Payable | BR12: Mode of payment Cash/Cheque No | BS12: Employee Signature
A13: -1 | B13: (2) | C13: (2A) | D13: (3) | E13: (4A) | F13: (4B) | G13: (4C) | H13: (5) | I13: (6) | J13: (7) | K13: (8) | L13: 1 | M13: 2 | N13: 3 | O13: 4 | P13: 5 | Q13: 6 | R13: 7 | S13: 8 | T13: 9 | U13: 10 | V13: 11 | W13: 12 | X13: 13 | Y13: 14 | Z13: 15 | AA13: 16 | AB13: 17 | AC13: 18 | AD13: 19 | AE13: 20 | AF13: 21 | AG13: 22 | AH13: 23 | AI13: 24 | AJ13: 25 | AK13: 26 | AL13: 27 | AM13: 28 | AN13: 29 | AO13: 30 | AP13: please mention the date of suspension of the employees if any | AQ13: (10) | AR13: (11) | AS13: Basic(12) | AT13: DA / VDA (13) | AU13: HRA (15) | AV13: Conv (15) | AW13: Med. Allow (16) | AX13: Attendance Bonus (17) | AY13: Special Allow (18) | AZ13: OT (19) | BA13: NFH (20) | BB13: Maternity Benefit (21) | BC13: Others (22) | BD13: Subsistence allowance, if any (23) | BE13: Total (24) | BF13: ESI (25) | BG13: PF (26) | BH13: PT (27) | BI13: TOS (28) | BJ13: Society (29) | BK13: Insurance (30) | BL13: Salary Adv (31) | BM13: Fines (32) | BN13: Damages / Loss (33) | BO13: Others (34) | BP13: Total | BQ13: (36) | BR13: (37) | BS13: (38)
A14: 1 | B14: ='04-22Master'!B16 -> AKASH DEEP CHUNAP | C14: ='04-22Master'!E16 -> Priyanka Chunap | D14: ='04-22Master'!D16 -> MALE | E14: ='04-22Master'!F16 -> Network security engineer | F14: IT Supportive | G14: BNG.STP | H14: ='04-22Master'!I16 -> 44105 | I14: ='04-22Master'!O16 -> N/A | J14: ='04-22Master'!N16 -> 101629256413 | K14: ='04-22Master'!T16 -> 135892 | L14: P | M14: WO | N14: WO | O14: P | P14: P | Q14: P | R14: P | S14: P | T14: WO | U14: WO | V14: P | W14: P | X14: P | Y14: P | Z14: H | AA14: WO | AB14: WO | AC14: P | AD14: P | AE14: P | AF14: P | AG14: P | AH14: WO | AI14: WO | AJ14: P | AK14: P | AL14: P | AM14: P | AN14: P | AO14: WO | AQ14: ='04-22Master'!R16 -> 30 | AR14: 0 | AS14: ='04-22Master'!U16 -> 81535.2 | AT14: ='04-22Master'!V16 -> 0 | AU14: ='04-22Master'!Y16 -> 32614.08 | AV14: ='04-22Master'!Z16 -> 2083 | AW14: ='04-22Master'!AA16 -> 2083 | AX14: ='04-22Master'!AD16 -> 1554.609 | AY14: ='04-22Master'!AB16 -> 17689.72 | AZ14: 0 | BA14: 0 | BB14: 0 | BC14: 0 | BD14: 0 | BE14: ='04-22Master'!AH16 -> 148276.05 | BF14: ='04-22Master'!AI16 -> 0 | BG14: ='04-22Master'!AJ16 -> 1800 | BH14: ='04-22Master'!AK16 -> 200 | BI14: ='04-22Master'!AL16 -> 0 | BJ14: 0 | BK14: 0 | BL14: 0 | BM14: 0 | BN14: 0 | BO14: 0 | BP14: ='04-22Master'!AN16 -> 2000 | BQ14: ='04-22Master'!AO16 -> 146276.05 | BR14: ='04-22Master'!AQ16 -> SBIN | BS14: ='04-22Master'!AR16 -> A/C 621 732 836 92
A15: 2 | B15: ='04-22Master'!B17 -> RajasekharReddy KN | C15: ='04-22Master'!E17 -> Narayana Reddy | D15: ='04-22Master'!D17 -> MALE | E15: ='04-22Master'!F17 -> Citrix Administrator | F15: IT Supportive | G15: BNG.STP | H15: ='04-22Master'!I17 -> 44326 | I15: ='04-22Master'!O17 -> N/A | J15: ='04-22Master'!N17 -> 100432313742 | K15: ='04-22Master'!T17 -> 66374 | L15: P | M15: WO | N15: WO | O15: P | P15: P | Q15: P | R15: P | S15: P | T15: WO | U15: WO | V15: P | W15: P | X15: P | Y15: P | Z15: H | AA15: WO | AB15: WO | AC15: EL | AD15: P | AE15: P | AF15: P | AG15: P | AH15: WO | AI15: WO | AJ15: P | AK15: P | AL15: P | AM15: P | AN15: P | AO15: WO | AQ15: ='04-22Master'!R17 -> 30 | AR15: 0 | AS15: ='04-22Master'!U17 -> 39824.4 | AT15: ='04-22Master'!V17 -> 0 | AU15: ='04-22Master'!Y17 -> 15929.76 | AV15: ='04-22Master'!Z17 -> 2083 | AW15: ='04-22Master'!AA17 -> 2083 | AX15: ='04-22Master'!AD17 -> 1554.609 | AY15: ='04-22Master'!AB17 -> 6566.84 | AZ15: 0 | BA15: 0 | BB15: 0 | BC15: 0 | BD15: 0 | BE15: ='04-22Master'!AH17 -> 73275.863 | BF15: ='04-22Master'!AI17 -> 0 | BG15: ='04-22Master'!AJ17 -> 1800 | BH15: ='04-22Master'!AK17 -> 200 | BI15: ='04-22Master'!AL17 -> 0 | BJ15: 0 | BK15: 0 | BL15: 0 | BM15: 0 | BN15: 0 | BO15: 0 | BP15: ='04-22Master'!AN17 -> 2391.7878 | BQ15: ='04-22Master'!AO17 -> 70884.075 | BR15: ='04-22Master'!AQ17 -> ICICI | BS15: ='04-22Master'!AR17 -> 272601504387
A16: 3 | B16: ='04-22Master'!B18 -> Moulika GM | C16: ='04-22Master'!E18 -> Maniganda Charan Kumar | D16: ='04-22Master'!D18 -> FEMALE | E16: ='04-22Master'!F18 -> Ansible Developer | F16: IT Supportive | G16: BNG.STP | H16: ='04-22Master'!I18 -> 44327 | I16: ='04-22Master'!O18 -> N/A | J16: ='04-22Master'!N18 -> 101695261774 | K16: ='04-22Master'!T18 -> 20029 | L16: P | M16: WO | N16: WO | O16: P | P16: P | Q16: P | R16: P | S16: P | T16: WO | U16: WO | V16: P | W16: P | X16: P | Y16: P | Z16: H | AA16: WO | AB16: WO | AC16: P | AD16: P | AE16: P | AF16: P | AG16: P | AH16: WO | AI16: WO | AJ16: P | AK16: P | AL16: P | AM16: P | AN16: P | AO16: WO | AQ16: ='04-22Master'!R18 -> 30 | AR16: 0 | AS16: ='04-22Master'!U18 -> 12017.4 | AT16: ='04-22Master'!V18 -> 0 | AU16: ='04-22Master'!Y18 -> 4806.96 | AV16: ='04-22Master'!Z18 -> 2083 | AW16: ='04-22Master'!AA18 -> 2083 | AX16: ='04-22Master'!AD18 -> 1554.609 | AY16: ='04-22Master'!AB18 -> -848.36 | AZ16: 0 | BA16: 0 | BB16: 0 | BC16: 0 | BD16: 0 | BE16: ='04-22Master'!AH18 -> 23276.096 | BF16: ='04-22Master'!AI18 -> 0 | BG16: ='04-22Master'!AJ18 -> 1442 | BH16: ='04-22Master'!AK18 -> 200 | BI16: ='04-22Master'!AL18 -> 0 | BJ16: 0 | BK16: 0 | BL16: 0 | BM16: 0 | BN16: 0 | BO16: 0 | BP16: ='04-22Master'!AN18 -> 2033.7878 | BQ16: ='04-22Master'!AO18 -> 21242.308 | BR16: ='04-22Master'!AQ18 -> Indian Bank | BS16: ='04-22Master'!AR18 -> 6685853376
A17: 4 | B17: ='04-22Master'!B19 -> AsokKumar J | C17: ='04-22Master'!E19 -> J.Prabhakar Reddt | D17: ='04-22Master'!D19 -> MALE | E17: ='04-22Master'!F19 -> Senior Middleware Administrator (MQ & Kafka) | F17: IT Supportive | G17: BNG.STP | H17: ='04-22Master'!I19 -> 44328 | I17: ='04-22Master'!O19 -> N/A | J17: ='04-22Master'!N19 -> 101695261742 | K17: ='04-22Master'!T19 -> 121988 | L17: P | M17: WO | N17: WO | O17: P | P17: P | Q17: P | R17: P | S17: P | T17: WO | U17: WO | V17: P | W17: P | X17: P | Y17: P | Z17: H | AA17: WO | AB17: WO | AC17: P | AD17: P | AE17: P | AF17: P | AG17: EL | AH17: WO | AI17: WO | AJ17: A | AK17: A | AL17: P | AM17: P | AN17: P | AO17: WO | AQ17: ='04-22Master'!R19 -> 28 | AR17: 0 | AS17: ='04-22Master'!U19 -> 68313.28 | AT17: ='04-22Master'!V19 -> 0 | AU17: ='04-22Master'!Y19 -> 27325.312 | AV17: ='04-22Master'!Z19 -> 1944 | AW17: ='04-22Master'!AA19 -> 1944 | AX17: ='04-22Master'!AD19 -> 1554.609 | AY17: ='04-22Master'!AB19 -> 14441.875 | AZ17: 0 | BA17: 0 | BB17: 0 | BC17: 0 | BD17: 0 | BE17: ='04-22Master'!AH19 -> 124501.72 | BF17: ='04-22Master'!AI19 -> 0 | BG17: ='04-22Master'!AJ19 -> 1800 | BH17: ='04-22Master'!AK19 -> 200 | BI17: ='04-22Master'!AL19 -> 0 | BJ17: 0 | BK17: 0 | BL17: 0 | BM17: 0 | BN17: 0 | BO17: 0 | BP17: ='04-22Master'!AN19 -> 2391.7878 | BQ17: ='04-22Master'!AO19 -> 122109.93 | BR17: ='04-22Master'!AQ19 -> HDFC | BS17: ='04-22Master'!AR19 -> 50100397382442
A18: 5 | B18: ='04-22Master'!B20 -> Majed Khan | C18: ='04-22Master'!E20 -> Habeeb Khan | D18: ='04-22Master'!D20 -> MALE | E18: ='04-22Master'!F20 -> Oracle/SAP DBA | F18: IT Supportive | G18: BNG.STP | H18: ='04-22Master'!I20 -> 44344 | I18: ='04-22Master'!O20 -> N/A | J18: ='04-22Master'!N20 -> 100240675169 | K18: ='04-22Master'!T20 -> 135892 | L18: P | M18: WO | N18: WO | O18: P | P18: P | Q18: P | R18: P | S18: EL | T18: WO | U18: WO | V18: P | W18: P | X18: P | Y18: P | Z18: H | AA18: WO | AB18: WO | AC18: P | AD18: P | AE18: P | AF18: P | AG18: P | AH18: WO | AI18: WO | AJ18: P | AK18: P | AL18: P | AM18: P | AN18: P | AO18: WO | AQ18: ='04-22Master'!R20 -> 30 | AR18: 0 | AS18: ='04-22Master'!U20 -> 81535.2 | AT18: ='04-22Master'!V20 -> 0 | AU18: ='04-22Master'!Y20 -> 32614.08 | AV18: ='04-22Master'!Z20 -> 2083 | AW18: ='04-22Master'!AA20 -> 2083 | AX18: ='04-22Master'!AD20 -> 1554.609 | AY18: ='04-22Master'!AB20 -> 17689.72 | AZ18: 0 | BA18: 0 | BB18: 0 | BC18: 0 | BD18: 0 | BE18: ='04-22Master'!AH20 -> 148276.05 | BF18: ='04-22Master'!AI20 -> 0 | BG18: ='04-22Master'!AJ20 -> 1800 | BH18: ='04-22Master'!AK20 -> 200 | BI18: ='04-22Master'!AL20 -> 0 | BJ18: 0 | BK18: 0 | BL18: 0 | BM18: 0 | BN18: 0 | BO18: 0 | BP18: ='04-22Master'!AN20 -> 2391.7878 | BQ18: ='04-22Master'!AO20 -> 145884.26 | BR18: ='04-22Master'!AQ20 -> HDFC | BS18: ='04-22Master'!AR20 -> 07941610141597
A19: 6 | B19: ='04-22Master'!B21 -> MADAN DH | C19: ='04-22Master'!E21 -> Dayanand H | D19: ='04-22Master'!D21 -> MALE | E19: ='04-22Master'!F21 -> Principal Storage Consultant | F19: IT Supportive | G19: BNG.STP | H19: ='04-22Master'!I21 -> 44362 | I19: ='04-22Master'!O21 -> N/A | J19: ='04-22Master'!N21 -> 100632443174 | K19: ='04-22Master'!T21 -> 94181 | L19: P | M19: WO | N19: WO | O19: P | P19: P | Q19: P | R19: P | S19: P | T19: WO | U19: WO | V19: P | W19: P | X19: P | Y19: P | Z19: H | AA19: WO | AB19: WO | AC19: P | AD19: P | AE19: P | AF19: P | AG19: P | AH19: WO | AI19: WO | AJ19: P | AK19: P | AL19: P | AM19: P | AN19: P | AO19: WO | AQ19: ='04-22Master'!R21 -> 30 | AR19: 0 | AS19: ='04-22Master'!U21 -> 56508.6 | AT19: ='04-22Master'!V21 -> 0 | AU19: ='04-22Master'!Y21 -> 22603.44 | AV19: ='04-22Master'!Z21 -> 2083 | AW19: ='04-22Master'!AA21 -> 2083 | AX19: ='04-22Master'!AD21 -> 1554.609 | AY19: ='04-22Master'!AB21 -> 11015.96 | AZ19: 0 | BA19: 0 | BB19: 0 | BC19: 0 | BD19: 0 | BE19: ='04-22Master'!AH21 -> 103275.72 | BF19: ='04-22Master'!AI21 -> 0 | BG19: ='04-22Master'!AJ21 -> 1800 | BH19: ='04-22Master'!AK21 -> 200 | BI19: ='04-22Master'!AL21 -> 0 | BJ19: 0 | BK19: 0 | BL19: 0 | BM19: 0 | BN19: 0 | BO19: 0 | BP19: ='04-22Master'!AN21 -> 2391.7878 | BQ19: ='04-22Master'!AO21 -> 100883.93 | BR19: ='04-22Master'!AQ21 -> HDFC Bank | BS19: ='04-22Master'!AR21 -> 50100122835737
A20: 7 | B20: ='04-22Master'!B22 -> Sachin | C20: ='04-22Master'!E22 -> POONAM SACHIN MESHRAM | D20: ='04-22Master'!D22 -> MALE | E20: ='04-22Master'!F22 -> Windows Administrator | F20: IT Supportive | G20: BNG.STP | H20: ='04-22Master'!I22 -> 44368 | I20: ='04-22Master'!O22 -> N/A | J20: ='04-22Master'!N22 -> 101090261210 | K20: ='04-22Master'!T22 -> 84912 | L20: P | M20: WO | N20: WO | O20: P | P20: P | Q20: P | R20: P | S20: P | T20: WO | U20: WO | V20: P | W20: P | X20: P | AQ20: ='04-22Master'!R22 -> 13 | AR20: 0 | AS20: ='04-22Master'!U22 -> 22077.12 | AT20: ='04-22Master'!V22 -> 0 | AU20: ='04-22Master'!Y22 -> 8830.848 | AV20: ='04-22Master'!Z22 -> 903 | AW20: ='04-22Master'!AA22 -> 903 | AX20: ='04-22Master'!AD22 -> 1554.609 | AY20: ='04-22Master'!AB22 -> 4194.232 | AZ20: 0 | BA20: 0 | BB20: 0 | BC20: 0 | BD20: 0 | BE20: ='04-22Master'!AH22 -> 41364.478 | BF20: ='04-22Master'!AI22 -> 0 | BG20: ='04-22Master'!AJ22 -> 1800 | BH20: ='04-22Master'!AK22 -> 200 | BI20: ='04-22Master'!AL22 -> 0 | BJ20: 0 | BK20: 0 | BL20: 0 | BM20: 0 | BN20: 0 | BO20: 0 | BP20: ='04-22Master'!AN22 -> 2391.7878 | BQ20: ='04-22Master'!AO22 -> 38972.691 | BR20: ='04-22Master'!AQ22 -> STATE BANK OF INDIA | BS20: ='04-22Master'!AR22 -> 20079696052
A21: 8 | B21: ='04-22Master'!B23 -> Barathiyar A | C21: ='04-22Master'!E23 -> Arumugam | D21: ='04-22Master'!D23 -> MALE | E21: ='04-22Master'!F23 -> VMware & Wintel Admin | F21: IT Supportive | G21: BNG.STP | H21: ='04-22Master'!I23 -> 44396 | I21: ='04-22Master'!O23 -> N/A | J21: ='04-22Master'!N23 -> 100583941709 | K21: ='04-22Master'!T23 -> 58959 | L21: P | M21: WO | N21: WO | O21: P | P21: P | Q21: P | R21: P | S21: P | T21: WO | U21: WO | V21: P | W21: P | X21: EL | AQ21: ='04-22Master'!R23 -> 13 | AR21: 0 | AS21: ='04-22Master'!U23 -> 15329.34 | AT21: ='04-22Master'!V23 -> 0 | AU21: ='04-22Master'!Y23 -> 6131.736 | AV21: ='04-22Master'!Z23 -> 903 | AW21: ='04-22Master'!AA23 -> 903 | AX21: ='04-22Master'!AD23 -> 1554.609 | AY21: ='04-22Master'!AB23 -> 2394.824 | AZ21: 0 | BA21: 0 | BB21: 0 | BC21: 0 | BD21: 0 | BE21: ='04-22Master'!AH23 -> 29231.295 | BF21: ='04-22Master'!AI23 -> 0 | BG21: ='04-22Master'!AJ23 -> 1800 | BH21: ='04-22Master'!AK23 -> 200 | BI21: ='04-22Master'!AL23 -> 0 | BJ21: 0 | BK21: 0 | BL21: 0 | BM21: 0 | BN21: 0 | BO21: 0 | BP21: ='04-22Master'!AN23 -> 2335 | BQ21: ='04-22Master'!AO23 -> 26896.295 | BR21: ='04-22Master'!AQ23 -> ICICI BANK | BS21: ='04-22Master'!AR23 -> 602601522530
A22: 9 | B22: ='04-22Master'!B24 -> Kumaravel M | C22: ='04-22Master'!E24 -> Madhavaraj | D22: ='04-22Master'!D24 -> MALE | E22: ='04-22Master'!F24 -> Sr. Network Administrator | F22: IT Supportive | G22: BNG.STP | H22: ='04-22Master'!I24 -> 44396 | I22: ='04-22Master'!O24 -> N/A | J22: ='04-22Master'!N24 -> 101273936714 | K22: ='04-22Master'!T24 -> 47836 | L22: P | M22: WO | N22: WO | O22: P | P22: P | Q22: P | R22: P | S22: P | T22: WO | U22: WO | V22: P | W22: P | X22: P | Y22: P | Z22: H | AA22: WO | AB22: WO | AC22: EL | AD22: P | AE22: P | AF22: P | AG22: P | AH22: WO | AI22: WO | AJ22: P | AK22: P | AL22: P | AM22: P | AN22: P | AO22: WO | AQ22: ='04-22Master'!R24 -> 30 | AR22: 0 | AS22: ='04-22Master'!U24 -> 28701.6 | AT22: ='04-22Master'!V24 -> 0 | AU22: ='04-22Master'!Y24 -> 11480.64 | AV22: ='04-22Master'!Z24 -> 2083 | AW22: ='04-22Master'!AA24 -> 2083 | AX22: ='04-22Master'!AD24 -> 1554.609 | AY22: ='04-22Master'!AB24 -> 3600.76 | AZ22: 0 | BA22: 0 | BB22: 0 | BC22: 0 | BD22: 0 | BE22: ='04-22Master'!AH24 -> 53275.956 | BF22: ='04-22Master'!AI24 -> 0 | BG22: ='04-22Master'!AJ24 -> 1800 | BH22: ='04-22Master'!AK24 -> 200 | BI22: ='04-22Master'!AL24 -> 0 | BJ22: 0 | BK22: 0 | BL22: 0 | BM22: 0 | BN22: 0 | BO22: 0 | BP22: ='04-22Master'!AN24 -> 2335 | BQ22: ='04-22Master'!AO24 -> 50940.956 | BR22: ='04-22Master'!AQ24 -> Indian Bank | BS22: ='04-22Master'!AR24 -> 443843855
A23: 10 | B23: ='04-22Master'!B25 -> CHANDRASEHARAN GERORGE | C23: ='04-22Master'!E25 -> George | D23: ='04-22Master'!D25 -> MALE | E23: ='04-22Master'!F25 -> SENIOR TECHNICAL SPECIALIST | F23: IT Supportive | G23: BNG.STP | H23: ='04-22Master'!I25 -> 44396 | I23: ='04-22Master'!O25 -> N/A | J23: ='04-22Master'!N25 -> 100123005976 | K23: ='04-22Master'!T25 -> 50617 | L23: P | M23: WO | N23: WO | O23: P | P23: P | Q23: P | R23: P | S23: P | T23: WO | U23: WO | V23: P | W23: P | X23: P | Y23: P | Z23: H | AQ23: ='04-22Master'!R25 -> 15 | AR23: 0 | AS23: ='04-22Master'!U25 -> 15185.1 | AT23: ='04-22Master'!V25 -> 0 | AU23: ='04-22Master'!Y25 -> 6074.04 | AV23: ='04-22Master'!Z25 -> 1042 | AW23: ='04-22Master'!AA25 -> 1042 | AX23: ='04-22Master'!AD25 -> 1554.609 | AY23: ='04-22Master'!AB25 -> 2078.36 | AZ23: 0 | BA23: 0 | BB23: 0 | BC23: 0 | BD23: 0 | BE23: ='04-22Master'!AH25 -> 28971.937 | BF23: ='04-22Master'!AI25 -> 0 | BG23: ='04-22Master'!AJ25 -> 1800 | BH23: ='04-22Master'!AK25 -> 200 | BI23: ='04-22Master'!AL25 -> 0 | BJ23: 0 | BK23: 0 | BL23: 0 | BM23: 0 | BN23: 0 | BO23: 0 | BP23: ='04-22Master'!AN25 -> 2335 | BQ23: ='04-22Master'!AO25 -> 26636.937 | BR23: ='04-22Master'!AQ25 -> Standard Charter Bank | BS23: ='04-22Master'!AR25 -> 42610387037
A24: 11 | B24: ='04-22Master'!B26 -> VISHNUPRASATH T | C24: ='04-22Master'!E26 -> Thavamani | D24: ='04-22Master'!D26 -> MALE | E24: ='04-22Master'!F26 -> Sr. Network Engineer | F24: IT Supportive | G24: BNG.STP | H24: ='04-22Master'!I26 -> 44396 | I24: ='04-22Master'!O26 -> N/A | J24: ='04-22Master'!N26 -> 100910953478 | K24: ='04-22Master'!T26 -> 47836 | L24: P | M24: WO | N24: WO | O24: P | P24: P | Q24: P | R24: P | S24: P | T24: WO | U24: WO | V24: P | W24: P | X24: P | Y24: P | Z24: H | AA24: WO | AB24: WO | AC24: P | AD24: P | AE24: P | AF24: P | AG24: P | AH24: WO | AI24: WO | AJ24: EL | AK24: P | AL24: P | AM24: P | AN24: P | AO24: WO | AQ24: ='04-22Master'!R26 -> 30 | AR24: 0 | AS24: ='04-22Master'!U26 -> 28701.6 | AT24: ='04-22Master'!V26 -> 0 | AU24: ='04-22Master'!Y26 -> 11480.64 | AV24: ='04-22Master'!Z26 -> 2083 | AW24: ='04-22Master'!AA26 -> 2083 | AX24: ='04-22Master'!AD26 -> 1554.609 | AY24: ='04-22Master'!AB26 -> 3600.76 | AZ24: 0 | BA24: 0 | BB24: 0 | BC24: 0 | BD24: 0 | BE24: ='04-22Master'!AH26 -> 53275.956 | BF24: ='04-22Master'!AI26 -> 0 | BG24: ='04-22Master'!AJ26 -> 1800 | BH24: ='04-22Master'!AK26 -> 200 | BI24: ='04-22Master'!AL26 -> 0 | BJ24: 0 | BK24: 0 | BL24: 0 | BM24: 0 | BN24: 0 | BO24: 0 | BP24: ='04-22Master'!AN26 -> 2335 | BQ24: ='04-22Master'!AO26 -> 50940.956 | BR24: ='04-22Master'!AQ26 -> ICICI BANK | BS24: ='04-22Master'!AR26 -> 270401504431
A25: 12 | B25: ='04-22Master'!B27 -> Nagaranjan S | C25: ='04-22Master'!E27 -> SUBBIAH G | D25: ='04-22Master'!D27 -> MALE | E25: ='04-22Master'!F27 -> Linux Administrator | F25: IT Supportive | G25: BNG.STP | H25: ='04-22Master'!I27 -> 44396 | I25: ='04-22Master'!O27 -> N/A | J25: ='04-22Master'!N27 -> 100363582963 | K25: ='04-22Master'!T27 -> 47836 | L25: P | M25: WO | N25: WO | O25: P | P25: P | Q25: P | R25: P | S25: P | T25: WO | U25: WO | V25: P | W25: P | X25: P | Y25: P | Z25: H | AA25: WO | AB25: WO | AC25: P | AD25: P | AE25: P | AF25: P | AG25: P | AH25: WO | AI25: WO | AJ25: P | AK25: P | AL25: P | AM25: P | AN25: P | AO25: WO | AQ25: ='04-22Master'!R27 -> 30 | AR25: 0 | AS25: ='04-22Master'!U27 -> 28701.6 | AT25: ='04-22Master'!V27 -> 0 | AU25: ='04-22Master'!Y27 -> 11480.64 | AV25: ='04-22Master'!Z27 -> 2083 | AW25: ='04-22Master'!AA27 -> 2083 | AX25: ='04-22Master'!AD27 -> 1554.609 | AY25: ='04-22Master'!AB27 -> 3600.76 | AZ25: 0 | BA25: 0 | BB25: 0 | BC25: 0 | BD25: 0 | BE25: ='04-22Master'!AH27 -> 53275.956 | BF25: ='04-22Master'!AI27 -> 0 | BG25: ='04-22Master'!AJ27 -> 1800 | BH25: ='04-22Master'!AK27 -> 200 | BI25: ='04-22Master'!AL27 -> 0 | BJ25: 0 | BK25: 0 | BL25: 0 | BM25: 0 | BN25: 0 | BO25: 0 | BP25: ='04-22Master'!AN27 -> 2335 | BQ25: ='04-22Master'!AO27 -> 50940.956 | BR25: ='04-22Master'!AQ27 -> IDBI BANK | BS25: ='04-22Master'!AR27 -> 005104000198752
A26: 13 | B26: ='04-22Master'!B28 -> ELAMPARITHI SB | C26: ='04-22Master'!E28 -> Balasubramanian.S | D26: ='04-22Master'!D28 -> MALE | E26: ='04-22Master'!F28 -> Senior Network Engineer | F26: IT Supportive | G26: BNG.STP | H26: ='04-22Master'!I28 -> 44396 | I26: ='04-22Master'!O28 -> N/A | J26: ='04-22Master'!N28 -> 100500123608 | K26: ='04-22Master'!T28 -> 47836 | L26: P | M26: WO | N26: WO | O26: P | P26: P | Q26: P | R26: P | S26: P | T26: WO | U26: WO | V26: P | W26: P | X26: P | Y26: P | Z26: H | AA26: WO | AB26: WO | AC26: P | AD26: P | AE26: P | AQ26: ='04-22Master'!R28 -> 20 | AR26: 0 | AS26: ='04-22Master'!U28 -> 19134.4 | AT26: ='04-22Master'!V28 -> 0 | AU26: ='04-22Master'!Y28 -> 7653.76 | AV26: ='04-22Master'!Z28 -> 1389 | AW26: ='04-22Master'!AA28 -> 1389 | AX26: ='04-22Master'!AD28 -> 1554.609 | AY26: ='04-22Master'!AB28 -> 2437.5067 | AZ26: 0 | BA26: 0 | BB26: 0 | BC26: 0 | BD26: 0 | BE26: ='04-22Master'!AH28 -> 36073.174 | BF26: ='04-22Master'!AI28 -> 0 | BG26: ='04-22Master'!AJ28 -> 1800 | BH26: ='04-22Master'!AK28 -> 200 | BI26: ='04-22Master'!AL28 -> 0 | BJ26: 0 | BK26: 0 | BL26: 0 | BM26: 0 | BN26: 0 | BO26: 0 | BP26: ='04-22Master'!AN28 -> 2335 | BQ26: ='04-22Master'!AO28 -> 33738.174 | BR26: ='04-22Master'!AQ28 -> ICICI | BS26: ='04-22Master'!AR28 -> 060701514623
A27: 14 | B27: ='04-22Master'!B29 -> Karthick G | C27: ='04-22Master'!E29 -> Ganesan | D27: ='04-22Master'!D29 -> MALE | E27: ='04-22Master'!F29 -> Senior EUC Analyst | F27: IT Supportive | G27: BNG.STP | H27: ='04-22Master'!I29 -> 44419 | I27: ='04-22Master'!O29 -> N/A | J27: ='04-22Master'!N29 -> 100874601152 | K27: ='04-22Master'!T29 -> 89547 | L27: P | M27: WO | N27: WO | O27: P | P27: P | Q27: P | R27: P | S27: P | T27: WO | U27: WO | V27: P | W27: P | X27: P | Y27: P | Z27: H | AA27: WO | AB27: WO | AC27: P | AD27: P | AE27: P | AF27: P | AG27: P | AH27: WO | AI27: WO | AJ27: P | AK27: P | AL27: P | AM27: P | AN27: P | AO27: WO | AQ27: ='04-22Master'!R29 -> 30 | AR27: 0 | AS27: ='04-22Master'!U29 -> 53728.2 | AT27: ='04-22Master'!V29 -> 0 | AU27: ='04-22Master'!Y29 -> 21491.28 | AV27: ='04-22Master'!Z29 -> 2083 | AW27: ='04-22Master'!AA29 -> 2083 | AX27: ='04-22Master'!AD29 -> 1554.609 | AY27: ='04-22Master'!AB29 -> 10274.52 | AZ27: 0 | BA27: 0 | BB27: 0 | BC27: 0 | BD27: 0 | BE27: ='04-22Master'!AH29 -> 98276.285 | BF27: ='04-22Master'!AI29 -> 0 | BG27: ='04-22Master'!AJ29 -> 1800 | BH27: ='04-22Master'!AK29 -> 200 | BI27: ='04-22Master'!AL29 -> 0 | BJ27: 0 | BK27: 0 | BL27: 0 | BM27: 0 | BN27: 0 | BO27: 0 | BP27: ='04-22Master'!AN29 -> 2336 | BQ27: ='04-22Master'!AO29 -> 95940.285 | BR27: ='04-22Master'!AQ29 -> HDFC BANK | BS27: ='04-22Master'!AR29 -> 50100072083437
A28: 15 | B28: ='04-22Master'!B30 -> K V Kannan | C28: ='04-22Master'!E30 -> K C Venkata Kumar | D28: ='04-22Master'!D30 -> MALE | E28: ='04-22Master'!F30 -> Windows and Assure Administrator | F28: IT Supportive | G28: BNG.STP | H28: ='04-22Master'!I30 -> 44446 | I28: ='04-22Master'!O30 -> N/A | J28: ='04-22Master'!N30 -> 101275235803 | K28: ='04-22Master'!T30 -> 36713 | L28: P | M28: WO | N28: WO | O28: P | P28: P | Q28: P | R28: P | S28: P | T28: WO | U28: WO | V28: P | W28: P | X28: P | Y28: P | Z28: H | AA28: WO | AB28: WO | AC28: P | AD28: P | AE28: P | AF28: P | AG28: P | AH28: WO | AI28: WO | AJ28: P | AK28: P | AL28: P | AM28: P | AN28: EL | AO28: WO | AQ28: ='04-22Master'!R30 -> 30 | AR28: 0 | AS28: ='04-22Master'!U30 -> 22027.8 | AT28: ='04-22Master'!V30 -> 0 | AU28: ='04-22Master'!Y30 -> 8811.12 | AV28: ='04-22Master'!Z30 -> 2083 | AW28: ='04-22Master'!AA30 -> 2083 | AX28: ='04-22Master'!AD30 -> 1554.609 | AY28: ='04-22Master'!AB30 -> 1821.08 | AZ28: 0 | BA28: 0 | BB28: 0 | BC28: 0 | BD28: 0 | BE28: ='04-22Master'!AH30 -> 41275.796 | BF28: ='04-22Master'!AI30 -> 0 | BG28: ='04-22Master'!AJ30 -> 1800 | BH28: ='04-22Master'!AK30 -> 200 | BI28: ='04-22Master'!AL30 -> 0 | BJ28: 0 | BK28: 0 | BL28: 0 | BM28: 0 | BN28: 0 | BO28: 0 | BP28: ='04-22Master'!AN30 -> 2252 | BQ28: ='04-22Master'!AO30 -> 39023.796 | BR28: ='04-22Master'!AQ30 -> INDUSIND BANK | BS28: ='04-22Master'!AR30 -> 100062052877
A29: 16 | B29: ='04-22Master'!B31 -> Thanigaivel.J | C29: ='04-22Master'!E31 -> Jayavelu | D29: ='04-22Master'!D31 -> MALE | E29: ='04-22Master'!F31 -> Network Engineer | F29: IT Supportive | G29: BNG.STP | H29: ='04-22Master'!I31 -> 44446 | I29: ='04-22Master'!O31 -> N/A | J29: ='04-22Master'!N31 -> 101131863380 | K29: ='04-22Master'!T31 -> 36713 | L29: P | M29: WO | N29: WO | O29: P | P29: P | Q29: P | R29: P | S29: P | T29: WO | U29: WO | V29: P | W29: P | X29: P | Y29: P | Z29: H | AA29: WO | AB29: WO | AC29: P | AD29: P | AE29: P | AF29: P | AG29: P | AH29: WO | AI29: WO | AJ29: P | AK29: P | AL29: P | AM29: P | AN29: P | AO29: WO | AQ29: ='04-22Master'!R31 -> 30 | AR29: 0 | AS29: ='04-22Master'!U31 -> 22027.8 | AT29: ='04-22Master'!V31 -> 0 | AU29: ='04-22Master'!Y31 -> 8811.12 | AV29: ='04-22Master'!Z31 -> 2083 | AW29: ='04-22Master'!AA31 -> 2083 | AX29: ='04-22Master'!AD31 -> 1554.609 | AY29: ='04-22Master'!AB31 -> 1821.08 | AZ29: 0 | BA29: 0 | BB29: 0 | BC29: 0 | BD29: 0 | BE29: ='04-22Master'!AH31 -> 41275.796 | BF29: ='04-22Master'!AI31 -> 0 | BG29: ='04-22Master'!AJ31 -> 1800 | BH29: ='04-22Master'!AK31 -> 200 | BI29: ='04-22Master'!AL31 -> 0 | BJ29: 0 | BK29: 0 | BL29: 0 | BM29: 0 | BN29: 0 | BO29: 0 | BP29: ='04-22Master'!AN31 -> 2224 | BQ29: ='04-22Master'!AO31 -> 39051.796 | BR29: ='04-22Master'!AQ31 -> AXIS BANK | BS29: ='04-22Master'!AR31 -> 917010045864654
A30: 17 | B30: ='04-22Master'!B32 -> Manzoor Ahamed | C30: ='04-22Master'!E32 -> Syed Rahim | D30: ='04-22Master'!D32 -> MALE | E30: ='04-22Master'!F32 -> Lead Devops Engineer | F30: IT Supportive | G30: BNG.STP | H30: ='04-22Master'!I32 -> 44487 | I30: ='04-22Master'!O32 -> N/A | J30: ='04-22Master'!N32 -> 100551348435 | K30: ='04-22Master'!T32 -> 223948 | L30: P | M30: WO | N30: WO | O30: P | P30: P | Q30: P | R30: P | S30: P | T30: WO | U30: WO | V30: P | W30: P | X30: P | Y30: P | Z30: H | AA30: WO | AB30: WO | AC30: P | AD30: P | AE30: P | AF30: P | AG30: P | AH30: WO | AI30: WO | AJ30: P | AK30: P | AL30: P | AM30: P | AN30: P | AO30: WO | AQ30: ='04-22Master'!R32 -> 30 | AR30: 0 | AS30: ='04-22Master'!U32 -> 134368.8 | AT30: ='04-22Master'!V32 -> 0 | AU30: ='04-22Master'!Y32 -> 53747.52 | AV30: ='04-22Master'!Z32 -> 2083 | AW30: ='04-22Master'!AA32 -> 2083 | AX30: ='04-22Master'!AD32 -> 1554.609 | AY30: ='04-22Master'!AB32 -> 31778.68 | AZ30: 0 | BA30: 0 | BB30: 0 | BC30: 0 | BD30: 0 | BE30: ='04-22Master'!AH32 -> 243276.15 | BF30: ='04-22Master'!AI32 -> 0 | BG30: ='04-22Master'!AJ32 -> 1800 | BH30: ='04-22Master'!AK32 -> 200 | BI30: ='04-22Master'!AL32 -> 0 | BJ30: 0 | BK30: 0 | BL30: 0 | BM30: 0 | BN30: 0 | BO30: 0 | BP30: ='04-22Master'!AN32 -> 2286 | BQ30: ='04-22Master'!AO32 -> 240990.15 | BR30: ='04-22Master'!AQ32 -> CITI Bank | BS30: ='04-22Master'!AR32 -> 5153635813
A31: 18 | B31: ='04-22Master'!B33 -> Ramakrishna J Reddy | C31: ='04-22Master'!E33 -> Satyanarayana Reddy | D31: ='04-22Master'!D33 -> MALE | E31: ='04-22Master'!F33 -> SENIOR SAP ABAP CONSULTANT | F31: IT Supportive | G31: BNG.STP | H31: ='04-22Master'!I33 -> 44512 | I31: ='04-22Master'!O33 -> N/A | J31: ='04-22Master'!N33 -> 100453787600 | K31: ='04-22Master'!T33 -> 191506 | L31: P | M31: WO | N31: WO | O31: P | P31: P | Q31: P | R31: P | S31: P | T31: WO | U31: WO | V31: P | W31: P | X31: P | Y31: P | Z31: H | AA31: WO | AB31: WO | AC31: P | AD31: P | AE31: P | AF31: P | AG31: P | AH31: WO | AI31: WO | AJ31: EL | AK31: A | AL31: A | AM31: P | AN31: P | AO31: WO | AQ31: ='04-22Master'!R33 -> 28 | AR31: 0 | AS31: ='04-22Master'!U33 -> 107243.36 | AT31: ='04-22Master'!V33 -> 0 | AU31: ='04-22Master'!Y33 -> 42897.344 | AV31: ='04-22Master'!Z33 -> 1944 | AW31: ='04-22Master'!AA33 -> 1944 | AX31: ='04-22Master'!AD33 -> 1554.609 | AY31: ='04-22Master'!AB33 -> 24823.229 | AZ31: 0 | BA31: 0 | BB31: 0 | BC31: 0 | BD31: 0 | BE31: ='04-22Master'!AH33 -> 194501.89 | BF31: ='04-22Master'!AI33 -> 0 | BG31: ='04-22Master'!AJ33 -> 1800 | BH31: ='04-22Master'!AK33 -> 200 | BI31: ='04-22Master'!AL33 -> 0 | BJ31: 0 | BK31: 0 | BL31: 0 | BM31: 0 | BN31: 0 | BO31: 0 | BP31: ='04-22Master'!AN33 -> 2252 | BQ31: ='04-22Master'!AO33 -> 192249.89 | BR31: ='04-22Master'!AQ33 -> HDFC BANK | BS31: ='04-22Master'!AR33 -> 50100216035976
A32: 19 | B32: ='04-22Master'!B34 -> Anil kumar Reddy kusam | C32: ='04-22Master'!E34 -> Pulla Reddy | D32: ='04-22Master'!D34 -> MALE | E32: ='04-22Master'!F34 -> Associate Consultant | F32: IT Supportive | G32: BNG.STP | H32: ='04-22Master'!I34 -> 44459 | I32: ='04-22Master'!O34 -> N/A | J32: ='04-22Master'!N34 -> 101182432317 | K32: ='04-22Master'!T34 -> 80278 | L32: P | M32: WO | N32: WO | O32: P | P32: P | Q32: P | R32: P | S32: P | T32: WO | U32: WO | V32: P | W32: P | X32: P | Y32: P | Z32: H | AA32: WO | AB32: WO | AC32: P | AD32: P | AE32: P | AF32: P | AG32: P | AH32: WO | AI32: WO | AJ32: P | AK32: P | AL32: P | AM32: P | AN32: P | AO32: WO | AQ32: ='04-22Master'!R34 -> 30 | AR32: 0 | AS32: ='04-22Master'!U34 -> 48167 | AT32: ='04-22Master'!V34 -> 0 | AU32: ='04-22Master'!Y34 -> 19267 | AV32: ='04-22Master'!Z34 -> 2083 | AW32: ='04-22Master'!AA34 -> 2083 | AX32: ='04-22Master'!AD34 -> 1554.609 | AY32: ='04-22Master'!AB34 -> 8791 | AZ32: 0 | BA32: 0 | BB32: 0 | BC32: 0 | BD32: 0 | BE32: ='04-22Master'!AH34 -> 88276.609 | BF32: ='04-22Master'!AI34 -> 0 | BG32: ='04-22Master'!AJ34 -> 1800 | BH32: ='04-22Master'!AK34 -> 200 | BI32: ='04-22Master'!AL34 -> 0 | BJ32: 0 | BK32: 0 | BL32: 0 | BM32: 0 | BN32: 0 | BO32: 0 | BP32: ='04-22Master'!AN34 -> 2224 | BQ32: ='04-22Master'!AO34 -> 86052.609 | BR32: ='04-22Master'!AQ34 -> ICICI BANK | BS32: ='04-22Master'!AR34 -> 020201566128
A33: 20 | B33: ='04-22Master'!B35 -> Praveen Kumar Tandra | C33: ='04-22Master'!E35 -> Ram reddy Tandra | D33: ='04-22Master'!D35 -> MALE | E33: ='04-22Master'!F35 -> Sr.Linux Admin | F33: IT Supportive | G33: BNG.STP | H33: ='04-22Master'!I35 -> 44536 | I33: ='04-22Master'!O35 -> N/A | J33: ='04-22Master'!N35 -> 100279367972 | K33: ='04-22Master'!T35 -> 98816 | L33: P | M33: WO | N33: WO | O33: P | P33: P | Q33: P | R33: P | S33: P | T33: WO | U33: WO | V33: P | W33: P | X33: P | Y33: P | Z33: H | AA33: WO | AB33: WO | AC33: P | AD33: P | AE33: P | AF33: P | AG33: P | AH33: WO | AI33: WO | AJ33: P | AK33: P | AL33: P | AM33: P | AN33: P | AO33: WO | AQ33: ='04-22Master'!R35 -> 30 | AR33: 0 | AS33: ='04-22Master'!U35 -> 59289.6 | AT33: ='04-22Master'!V35 -> 0 | AU33: ='04-22Master'!Y35 -> 23715.84 | AV33: ='04-22Master'!Z35 -> 2083 | AW33: ='04-22Master'!AA35 -> 2083 | AX33: ='04-22Master'!AD35 -> 1554.609 | AY33: ='04-22Master'!AB35 -> 11757.56 | AZ33: 0 | BA33: 0 | BB33: 0 | BC33: 0 | BD33: 0 | BE33: ='04-22Master'!AH35 -> 108276.24 | BF33: ='04-22Master'!AI35 -> 0 | BG33: ='04-22Master'!AJ35 -> 1800 | BH33: ='04-22Master'!AK35 -> 200 | BI33: ='04-22Master'!AL35 -> 0 | BJ33: 0 | BK33: 0 | BL33: 0 | BM33: 0 | BN33: 0 | BO33: 0 | BP33: ='04-22Master'!AN35 -> 2283 | BQ33: ='04-22Master'!AO35 -> 105993.24 | BR33: ='04-22Master'!AQ35 -> HDFC BANK | BS33: ='04-22Master'!AR35 -> 00008099320
A34: 21 | B34: ='04-22Master'!B36 -> Nagarjun KV | C34: ='04-22Master'!E36 -> Arpitha R | D34: ='04-22Master'!D36 -> MALE | E34: ='04-22Master'!F36 -> Technical Consultant | F34: IT Supportive | G34: BNG.STP | H34: ='04-22Master'!I36 -> 44564 | I34: ='04-22Master'!O36 -> N/A | J34: ='04-22Master'!N36 -> 100247870639 | K34: ='04-22Master'!T36 -> 75643 | L34: P | M34: WO | N34: WO | O34: P | P34: P | Q34: P | R34: P | S34: P | T34: WO | U34: WO | V34: P | W34: P | X34: P | Y34: P | Z34: H | AA34: WO | AB34: WO | AC34: P | AD34: P | AE34: P | AF34: P | AG34: P | AH34: WO | AI34: WO | AJ34: P | AK34: P | AL34: P | AM34: P | AN34: P | AO34: WO | AQ34: ='04-22Master'!R36 -> 30 | AR34: 0 | AS34: ='04-22Master'!U36 -> 45385.8 | AT34: ='04-22Master'!V36 -> 0 | AU34: ='04-22Master'!Y36 -> 18154.32 | AV34: ='04-22Master'!Z36 -> 2083 | AW34: ='04-22Master'!AA36 -> 2083 | AX34: ='04-22Master'!AD36 -> 1554.609 | AY34: ='04-22Master'!AB36 -> 8049.88 | AZ34: 0 | BA34: 0 | BB34: 0 | BC34: 0 | BD34: 0 | BE34: ='04-22Master'!AH36 -> 83275.816 | BF34: ='04-22Master'!AI36 -> 0 | BG34: ='04-22Master'!AJ36 -> 1800 | BH34: ='04-22Master'!AK36 -> 200 | BI34: ='04-22Master'!AL36 -> 0 | BJ34: 0 | BK34: 0 | BL34: 0 | BM34: 0 | BN34: 0 | BO34: 0 | BP34: ='04-22Master'!AN36 -> 2283 | BQ34: ='04-22Master'!AO36 -> 80992.816 | BR34: ='04-22Master'!AQ36 -> STATE BANK OF INDIA | BS34: ='04-22Master'!AR36 -> 20174267977
A35: 22 | B35: ='04-22Master'!B37 -> Boopathi Palani | C35: ='04-22Master'!E37 -> M.Palani | D35: ='04-22Master'!D37 -> MALE | E35: ='04-22Master'!F37 -> Senior Technology Analyst | F35: IT Supportive | G35: BNG.STP | H35: ='04-22Master'!I37 -> 44564 | I35: ='04-22Master'!O37 -> N/A | J35: ='04-22Master'!N37 -> 101153836004 | K35: ='04-22Master'!T37 -> 75643 | L35: P | M35: WO | N35: WO | O35: P | P35: P | Q35: P | R35: P | S35: P | T35: WO | U35: WO | V35: P | W35: P | X35: P | Y35: EL | Z35: H | AA35: WO | AB35: WO | AC35: P | AD35: P | AE35: P | AF35: P | AG35: P | AH35: WO | AI35: WO | AJ35: P | AK35: P | AL35: P | AM35: P | AN35: P | AO35: WO | AQ35: ='04-22Master'!R37 -> 30 | AR35: 0 | AS35: ='04-22Master'!U37 -> 45385.8 | AT35: ='04-22Master'!V37 -> 0 | AU35: ='04-22Master'!Y37 -> 18154.32 | AV35: ='04-22Master'!Z37 -> 2083 | AW35: ='04-22Master'!AA37 -> 2083 | AX35: ='04-22Master'!AD37 -> 1554.609 | AY35: ='04-22Master'!AB37 -> 8049.88 | AZ35: 0 | BA35: 0 | BB35: 0 | BC35: 0 | BD35: 0 | BE35: ='04-22Master'!AH37 -> 83275.816 | BF35: ='04-22Master'!AI37 -> 0 | BG35: ='04-22Master'!AJ37 -> 1800 | BH35: ='04-22Master'!AK37 -> 200 | BI35: ='04-22Master'!AL37 -> 0 | BJ35: 0 | BK35: 0 | BL35: 0 | BM35: 0 | BN35: 0 | BO35: 0 | BP35: ='04-22Master'!AN37 -> 2283 | BQ35: ='04-22Master'!AO37 -> 80992.816 | BR35: ='04-22Master'!AQ37 -> ICICI BANK | BS35: ='04-22Master'!AR37 -> 603601537940
A36: 23 | B36: ='04-22Master'!B38 -> JNANESWARARAO G | C36: ='04-22Master'!E38 -> Subba Rao | D36: ='04-22Master'!D38 -> MALE | E36: ='04-22Master'!F38 -> SENIOR SOFTWARE ENGINEER- MongoDB DBA | F36: IT Supportive | G36: BNG.STP | H36: ='04-22Master'!I38 -> 44562 | I36: ='04-22Master'!O38 -> N/A | J36: ='04-22Master'!N38 -> 100848702184 | K36: ='04-22Master'!T38 -> 96962 | L36: P | M36: WO | N36: WO | O36: P | P36: P | Q36: P | R36: P | S36: P | T36: WO | U36: WO | V36: P | W36: P | X36: P | Y36: P | Z36: H | AA36: WO | AB36: WO | AC36: P | AD36: P | AE36: P | AF36: P | AG36: P | AH36: WO | AI36: WO | AJ36: P | AK36: P | AL36: P | AM36: P | AN36: P | AO36: WO | AQ36: ='04-22Master'!R38 -> 30 | AR36: 0 | AS36: ='04-22Master'!U38 -> 58177.2 | AT36: ='04-22Master'!V38 -> 0 | AU36: ='04-22Master'!Y38 -> 23270.88 | AV36: ='04-22Master'!Z38 -> 2083 | AW36: ='04-22Master'!AA38 -> 2083 | AX36: ='04-22Master'!AD38 -> 1554.609 | AY36: ='04-22Master'!AB38 -> 11460.92 | AZ36: 0 | BA36: 0 | BB36: 0 | BC36: 0 | BD36: 0 | BE36: ='04-22Master'!AH38 -> 120676.03 | BF36: ='04-22Master'!AI38 -> 0 | BG36: ='04-22Master'!AJ38 -> 1800 | BH36: ='04-22Master'!AK38 -> 200 | BI36: ='04-22Master'!AL38 -> 0 | BJ36: 0 | BK36: 0 | BL36: 0 | BM36: 0 | BN36: 0 | BO36: 0 | BP36: ='04-22Master'!AN38 -> 2283 | BQ36: ='04-22Master'!AO38 -> 118393.03 | BR36: ='04-22Master'!AQ38 -> STATE BANK OF INDIA | BS36: ='04-22Master'!AR38 -> 62404945568
A37: 24 | B37: ='04-22Master'!B39 -> Shridhar Madlur | C37: ='04-22Master'!E39 -> Hanamantappa Madlur | D37: ='04-22Master'!D39 -> MALE | E37: ='04-22Master'!F39 -> Network Engineer | F37: IT Supportive | G37: BNG.STP | H37: ='04-22Master'!I39 -> 44594 | I37: ='04-22Master'!O39 -> N/A | J37: ='04-22Master'!N39 -> 101364625395 | K37: ='04-22Master'!T39 -> 50617 | L37: P | M37: WO | N37: WO | O37: P | P37: P | Q37: P | R37: P | S37: P | T37: WO | U37: WO | V37: P | W37: P | X37: P | Y37: P | Z37: H | AA37: WO | AB37: WO | AC37: P | AD37: P | AE37: P | AF37: P | AG37: P | AH37: WO | AI37: WO | AJ37: P | AK37: P | AL37: P | AM37: P | AN37: EL | AO37: WO | AQ37: ='04-22Master'!R39 -> 30 | AR37: 0 | AS37: ='04-22Master'!U39 -> 30370.2 | AT37: ='04-22Master'!V39 -> 0 | AU37: ='04-22Master'!Y39 -> 12148.08 | AV37: ='04-22Master'!Z39 -> 2083 | AW37: ='04-22Master'!AA39 -> 2083 | AX37: ='04-22Master'!AD39 -> 1554.609 | AY37: ='04-22Master'!AB39 -> 4045.72 | AZ37: 0 | BA37: 0 | BB37: 0 | BC37: 0 | BD37: 0 | BE37: ='04-22Master'!AH39 -> 56276.266 | BF37: ='04-22Master'!AI39 -> 0 | BG37: ='04-22Master'!AJ39 -> 1800 | BH37: ='04-22Master'!AK39 -> 200 | BI37: ='04-22Master'!AL39 -> 0 | BJ37: 0 | BK37: 0 | BL37: 0 | BM37: 0 | BN37: 0 | BO37: 0 | BP37: ='04-22Master'!AN39 -> 2283 | BQ37: ='04-22Master'!AO39 -> 53993.266 | BR37: ='04-22Master'!AQ39 -> ICICI Bank | BS37: ='04-22Master'!AR39 -> 93701529580
A38: 25 | B38: ='04-22Master'!B40 -> Samarjit Saha | C38: ='04-22Master'!E40 -> Gopal Chandra Saha | D38: ='04-22Master'!D40 -> MALE | E38: ='04-22Master'!F40 -> Devopers Specialist | F38: IT Supportive | G38: BNG.STP | H38: ='04-22Master'!I40 -> 44594 | I38: ='04-22Master'!O40 -> N/A | J38: ='04-22Master'!N40 -> 100329306766 | K38: ='04-22Master'!T40 -> 126623 | L38: P | M38: WO | N38: WO | O38: P | P38: P | Q38: P | R38: P | S38: P | T38: WO | U38: WO | V38: P | W38: P | X38: P | Y38: P | Z38: H | AA38: WO | AB38: WO | AC38: P | AD38: P | AE38: P | AF38: P | AG38: P | AH38: WO | AI38: WO | AJ38: P | AK38: P | AL38: P | AM38: P | AN38: P | AO38: WO | AQ38: ='04-22Master'!R40 -> 30 | AR38: 0 | AS38: ='04-22Master'!U40 -> 75973.8 | AT38: ='04-22Master'!V40 -> 0 | AU38: ='04-22Master'!Y40 -> 30389.52 | AV38: ='04-22Master'!Z40 -> 2083 | AW38: ='04-22Master'!AA40 -> 2083 | AX38: ='04-22Master'!AD40 -> 1554.609 | AY38: ='04-22Master'!AB40 -> 16206.68 | AZ38: 0 | BA38: 0 | BB38: 0 | BC38: 0 | BD38: 0 | BE38: ='04-22Master'!AH40 -> 138276.1 | BF38: ='04-22Master'!AI40 -> 0 | BG38: ='04-22Master'!AJ40 -> 1800 | BH38: ='04-22Master'!AK40 -> 200 | BI38: ='04-22Master'!AL40 -> 0 | BJ38: 0 | BK38: 0 | BL38: 0 | BM38: 0 | BN38: 0 | BO38: 0 | BP38: ='04-22Master'!AN40 -> 2283 | BQ38: ='04-22Master'!AO40 -> 135993.1 | BR38: ='04-22Master'!AQ40 -> HDFC | BS38: ='04-22Master'!AR40 -> 5161140000905
... A44: 31 | B44: ='04-22Master'!B46 -> Praveen Kumar GATTU | C44: ='04-22Master'!E46 -> G Muniratnam | D44: ='04-22Master'!D46 -> MALE | E44: ='04-22Master'!F46 -> System Administrator | F44: IT Supportive | G44: BNG.STP | H44: ='04-22Master'!I46 -> 44648 | I44: ='04-22Master'!O46 -> N/A | J44: ='04-22Master'!N46 -> 100515794652 | K44: ='04-22Master'!T46 -> 80278 | L44: P | M44: WO | N44: WO | O44: P | P44: P | Q44: P | R44: P | S44: P | T44: WO | U44: WO | V44: P | W44: P | X44: P | Y44: P | Z44: H | AA44: WO | AB44: WO | AC44: P | AD44: P | AE44: P | AF44: P | AG44: P | AH44: WO | AI44: WO | AJ44: P | AK44: P | AL44: P | AM44: P | AN44: P | AO44: WO | AQ44: ='04-22Master'!R46 -> 30 | AR44: 0 | AS44: ='04-22Master'!U46 -> 48166.8 | AT44: ='04-22Master'!V46 -> 0 | AU44: ='04-22Master'!Y46 -> 19266.72 | AV44: ='04-22Master'!Z46 -> 2083 | AW44: ='04-22Master'!AA46 -> 2083 | AX44: ='04-22Master'!AD46 -> 1554.609 | AY44: ='04-22Master'!AB46 -> 8791.48 | AZ44: 0 | BA44: 0 | BB44: 0 | BC44: 0 | BD44: 0 | BE44: ='04-22Master'!AH46 -> 88276.332 | BF44: ='04-22Master'!AI46 -> 0 | BG44: ='04-22Master'!AJ46 -> 1800 | BH44: ='04-22Master'!AK46 -> 200 | BI44: ='04-22Master'!AL46 -> 0 | BJ44: 0 | BK44: 0 | BL44: 0 | BM44: 0 | BN44: 0 | BO44: 0 | BP44: ='04-22Master'!AN46 -> 2283 | BQ44: ='04-22Master'!AO46 -> 85993.332 | BR44: ='04-22Master'!AQ46 -> Axis Bank | BS44: ='04-22Master'!AR46 -> 915010017171911
A45: 32 | B45: ='04-22Master'!B47 -> Vinoth Vairavan | C45: ='04-22Master'!E47 -> Vairavan | D45: ='04-22Master'!D47 -> MALE | E45: ='04-22Master'!F47 -> SR, NETWORK ENGINEER | F45: IT Supportive | G45: BNG.STP | H45: ='04-22Master'!I47 -> 44657 | I45: ='04-22Master'!O47 -> N/A | J45: ='04-22Master'!N47 -> 100766312722 | K45: ='04-22Master'!T47 -> 135892 | Q45: P | R45: P | S45: P | T45: WO | U45: WO | V45: P | W45: P | X45: P | Y45: P | Z45: H | AA45: WO | AB45: WO | AC45: P | AD45: P | AE45: P | AF45: P | AG45: P | AH45: WO | AI45: WO | AJ45: P | AK45: P | AL45: P | AM45: P | AN45: P | AO45: WO | AQ45: ='04-22Master'!R47 -> 25 | AR45: 0 | AS45: ='04-22Master'!U47 -> 67946 | AT45: ='04-22Master'!V47 -> 0 | AU45: ='04-22Master'!Y47 -> 27178.4 | AV45: ='04-22Master'!Z47 -> 1736 | AW45: ='04-22Master'!AA47 -> 1736 | AX45: ='04-22Master'!AD47 -> 1554.609 | AY45: ='04-22Master'!AB47 -> 14759.933 | AZ45: 0 | BA45: 0 | BB45: 0 | BC45: 0 | BD45: 0 | BE45: ='04-22Master'!AH47 -> 123841.31 | BF45: ='04-22Master'!AI47 -> 0 | BG45: ='04-22Master'!AJ47 -> 1800 | BH45: ='04-22Master'!AK47 -> 200 | BI45: ='04-22Master'!AL47 -> 0 | BJ45: 0 | BK45: 0 | BL45: 0 | BM45: 0 | BN45: 0 | BO45: 0 | BP45: ='04-22Master'!AN47 -> 2000 | BQ45: ='04-22Master'!AO47 -> 121841.31 | BR45: ='04-22Master'!AQ47 -> AXIS Bank | BS45: ='04-22Master'!AR47 -> 916010024710764
A46: 33 | B46: ='04-22Master'!B48 -> Govarthanan TK | C46: ='04-22Master'!E48 -> Kumaraswamy papaiya | D46: ='04-22Master'!D48 -> MALE | E46: ='04-22Master'!F48 -> IT Project Manager | F46: IT Supportive | G46: BNG.STP | H46: ='04-22Master'!I48 -> 44662 | I46: ='04-22Master'!O48 -> N/A | J46: ='04-22Master'!N48 -> 100159339504 | K46: ='04-22Master'!T48 -> 121988 | V46: P | W46: P | X46: P | Y46: P | Z46: H | AA46: WO | AB46: WO | AC46: P | AD46: P | AE46: P | AF46: P | AG46: P | AH46: WO | AI46: WO | AJ46: P | AK46: P | AL46: P | AM46: P | AN46: P | AO46: WO | AQ46: ='04-22Master'!R48 -> 20 | AR46: 0 | AS46: ='04-22Master'!U48 -> 48795.2 | AT46: ='04-22Master'!V48 -> 0 | AU46: ='04-22Master'!Y48 -> 19518.08 | AV46: ='04-22Master'!Z48 -> 1389 | AW46: ='04-22Master'!AA48 -> 1389 | AX46: ='04-22Master'!AD48 -> 1554.609 | AY46: ='04-22Master'!AB48 -> 10347.053 | AZ46: 0 | BA46: 0 | BB46: 0 | BC46: 0 | BD46: 0 | BE46: ='04-22Master'!AH48 -> 89406.258 | BF46: ='04-22Master'!AI48 -> 0 | BG46: ='04-22Master'!AJ48 -> 1800 | BH46: ='04-22Master'!AK48 -> 200 | BI46: ='04-22Master'!AL48 -> 0 | BJ46: 0 | BK46: 0 | BL46: 0 | BM46: 0 | BN46: 0 | BO46: 0 | BP46: ='04-22Master'!AN48 -> 2000 | BQ46: ='04-22Master'!AO48 -> 87406.258 | BR46: ='04-22Master'!AQ48 -> CITI Bank | BS46: ='04-22Master'!AR48 -> 5708925554
A47: 34 | B47: ='04-22Master'!B49 -> Laxmi Soujanya Mudunuri | C47: ='04-22Master'!E49 -> Venkata Satya narayana Raju | D47: ='04-22Master'!D49 -> FEMALE | E47: ='04-22Master'!F49 -> Senior Middleware Consultant | F47: IT Supportive | G47: BNG.STP | H47: ='04-22Master'!I49 -> 44671 | I47: ='04-22Master'!O49 -> N/A | J47: ='04-22Master'!N49 -> 100619683716 | K47: ='04-22Master'!T49 -> 159065 | AE47: P | AF47: P | AG47: P | AH47: WO | AI47: WO | AJ47: P | AK47: P | AL47: P | AM47: P | AN47: P | AO47: WO | AQ47: ='04-22Master'!R49 -> 11 | AR47: 0 | AS47: ='04-22Master'!U49 -> 34994.3 | AT47: ='04-22Master'!V49 -> 0 | AU47: ='04-22Master'!Y49 -> 13997.72 | AV47: ='04-22Master'!Z49 -> 764 | AW47: ='04-22Master'!AA49 -> 764 | AX47: ='04-22Master'!AD49 -> 1554.609 | AY47: ='04-22Master'!AB49 -> 7916.8133 | AZ47: 0 | BA47: 0 | BB47: 0 | BC47: 0 | BD47: 0 | BE47: ='04-22Master'!AH49 -> 64590.86 | BF47: ='04-22Master'!AI49 -> 0 | BG47: ='04-22Master'!AJ49 -> 1800 | BH47: ='04-22Master'!AK49 -> 200 | BI47: ='04-22Master'!AL49 -> 0 | BJ47: 0 | BK47: 0 | BL47: 0 | BM47: 0 | BN47: 0 | BO47: 0 | BP47: ='04-22Master'!AN49 -> 2000 | BQ47: ='04-22Master'!AO49 -> 62590.86 | BR47: ='04-22Master'!AQ49 -> Axis Bank | BS47: ='04-22Master'!AR49 -> 915010032166004
AP48: =SUM(AQ14:AQ47) -> 923 | AS48: ='04-22Master'!U50 -> 1732148.7 | AT48: ='04-22Master'!V50 -> 0 | AU48: ='04-22Master'!Y50 -> 692859.8 | AV48: ='04-22Master'!Z50 -> 64089 | AW48: ='04-22Master'!AA50 -> 64089 | AX48: ='04-22Master'!AD50 -> 52856.706 | AY48: ='04-22Master'!AB50 -> 337569.87 | AZ48: 0 | BA48: 0 | BB48: 0 | BC48: 0 | BD48: 0 | BE48: ='04-22Master'!AH50 -> 3185676.1 | BF48: ='04-22Master'!AI50 -> 0 | BG48: ='04-22Master'!AJ50 -> 59042 | BH48: ='04-22Master'!AK50 -> 6800 | BI48: ='04-22Master'!AL50 -> 0 | BJ48: 0 | BK48: 0 | BL48: 0 | BM48: 0 | BN48: 0 | BO48: 0 | BP48: ='04-22Master'!AN50 -> 75172.727 | BQ48: ='04-22Master'!AO50 -> 3110503.4 | BR48: ='04-22Master'!AQ50 -> 0 | BS48: ='04-22Master'!AR50 -> 0

Sheet F F Leave
A1: FORM F
A2: (SEE RULE 8 under Shops& Establishment Karnataka Rules 1974)
A3: REGISTER OF LEAVE WITH WAGES
A5: 1 | B5: Sl No in the Register of Adult/young person: | F5: ='04-22Master'!A16 -> BITS-485 | G5: 2 | H5: Date of entry into service: | K5: ='04-22Master'!I16 -> 44105
A7: 3 | B7: Name of the person : | D7: ='04-22Master'!B16 -> AKASH DEEP CHUNAP | G7: 4 | H7: Father's Name : | J7: ='04-22Master'!E16 -> Priyanka Chunap
A9: PART I EARNED LEAVE
B11: No of Days worked | E11: Leave earned | F11: Leave at credit (incl balance if any, on return from leave on last occasion) | G11: leave availed | J11: Balance on return from leave | K11: Date on which wages for leave paid and amount paid | L11: Remarks
B12: From | C12: To | D12: Total days worked | G12: From | H12: To | I12: No. of days
B13: 1 | C13: 2 | D13: 3 | E13: 4 | F13: 5 | G13: 6 | H13: 7 | I13: 8 | J13: 9 | K13: 10 | L13: 11
B15: 44562 | C15: 44592 | D15: 31 | E15: 1.5 | F15: 23 | G15: 0 | H15: 0 | I15: 0 | J15: 23
B16: 44593 | C16: 44620 | D16: 28 | E16: 1.5 | G16: 0 | H16: 0 | I16: 0 | J16: =J15+E16-H16 -> 24.5
B17: 44621 | C17: 44651 | D17: 31 | E17: 1.5 | G17: 0 | H17: 0 | I17: 0 | J17: =J16+E17-H17 -> 26
B18: 44652 | C18: 44681 | D18: 30 | E18: 1.5 | G18: 0 | H18: 0 | I18: 0 | J18: =J17+E18-H18 -> 27.5 | M18: 1
A35: PART II - Sick/Accident Leave (with pay)
B37: Year | D37: Sick/Accident leave | J37: Balance at the end of the year
D38: of credit | G38: Availed
B39: 1 | D39: 2 | G39: 3 | J39: 4
J40: =D40-G40 -> 0
A43: FORM F
A44: (SEE RULE 8 under Shops& Establishment Karnataka Rules 1974)
A45: REGISTER OF LEAVE WITH WAGES
A47: 1 | B47: Sl No in the Register of Adult/young person: | F47: ='BGLR STP APRIL 22-WM Reg'!A50 -> 37 | G47: 2 | H47: Date of entry into service: | K47: ='BGLR STP APRIL 22-WM Reg'!I50 -> 44326
A49: 3 | B49: Name of the person : | D49: ='BGLR STP APRIL 22-WM Reg'!B50 -> RajasekharReddy KN | G49: 4 | H49: Father's Name : | J49: ='BGLR STP APRIL 22-WM Reg'!E50 -> Narayana Reddy
A51: PART I EARNED LEAVE
B53: No of Days worked | E53: Leave earned | F53: Leave at credit (incl balance if any, on return from leave on last occasion) | G53: leave availed | J53: Balance on return from leave | K53: Date on which wages for leave paid and amount paid | L53: Remarks
B54: From | C54: To | D54: Total days worked | G54: From | H54: To | I54: No. of days
B55: 1 | C55: 2 | D55: 3 | E55: 4 | F55: 01.12.20 | G55: 30.12.20 | H55: 7 | I55: 8 | J55: 9 | K55: 10 | L55: 11
B57: 44562 | C57: 44592 | D57: 31 | E57: 1.5 | F57: 10.5 | G57: 0 | H57: 0 | I57: 0 | J57: 10.5
B58: 44593 | C58: 44620 | D58: 28 | E58: 1.5 | F58: 0 | G58: 44620 | H58: 44620 | I58: 1 | J58: =J57+E58-I58 -> 11
B59: 44621 | C59: 44651 | D59: 31 | E59: 1.5 | G59: 44623 | H59: 44623 | I59: 1 | J59: =J58+E59-I59 -> 11.5
B60: 44652 | C60: 44681 | D60: 30 | E60: 1.5 | G60: 37364 | H60: 44669 | I60: 1 | J60: =J59+E60-I60 -> 12 | M60: 2
A71: PART II - Sick/Accident Leave (with pay)
B73: Year | D73: Sick/Accident leave | J73: Balance at the end of the year
D74: of credit | G74: Availed
B75: 1 | D75: 2 | G75: 3 | J75: 4
J76: =D76-G76 -> 0
A81: FORM F
A82: (SEE RULE 8 under Shops& Establishment Karnataka Rules 1974)
A83: REGISTER OF LEAVE WITH WAGES
A85: 1 | B85: Sl No in the Register of Adult/young person: | F85: ='BGLR STP APRIL 22-WM Reg'!A51 -> 38 | G85: 2 | H85: Date of entry into service: | K85: ='BGLR STP APRIL 22-WM Reg'!I51 -> 44327
A87: 3 | B87: Name of the person : | D87: ='BGLR STP APRIL 22-WM Reg'!B51 -> Moulika GM | G87: 4 | H87: Father's Name : | J87: ='BGLR STP APRIL 22-WM Reg'!E51 -> Maniganda Charan Kumar
A89: PART I EARNED LEAVE
B91: No of Days worked | E91: Leave earned | F91: Leave at credit (incl balance if any, on return from leave on last occasion) | G91: leave availed | J91: Balance on return from leave | K91: Date on which wages for leave paid and amount paid | L91: Remarks
B92: From | C92: To | D92: Total days worked | G92: From | H92: To | I92: No. of days
B93: 1 | C93: 2 | D93: 3 | E93: 4 | F93: 5 | G93: 6 | H93: 7 | I93: 8 | J93: 9 | K93: 10 | L93: 11
B95: 44562 | C95: 44592 | D95: 31 | E95: 1.5 | F95: 11.5 | G95: 44585 | H95: 44585 | I95: 1 | J95: 10.5
B96: 44593 | C96: 44620 | D96: 28 | E96: 1.5 | J96: =J95+E96-I96 -> 12
B97: 44621 | C97: 44651 | D97: 31 | E97: 1.5 | G97: 0 | H97: 0 | I97: 0 | J97: =J96+E97-I97 -> 13.5
B98: 44652 | C98: 44681 | D98: 30 | E98: 1.5 | G98: 0 | H98: 0 | I98: 0 | J98: =J97+E98-H98 -> 15 | M98: 3
A107: PART II - Sick/Accident Leave (with pay)
B109: Year | D109: Sick/Accident leave | J109: Balance at the end of the year
D110: of credit | G110: Availed
B111: 1 | D111: 2 | G111: 3 | J111: 4
J112: =D112-G112 -> 0
A117: FORM F
A118: (SEE RULE 8 under Shops& Establishment Karnataka Rules 1974)
A119: REGISTER OF LEAVE WITH WAGES
A121: 1 | B121: Sl No in the Register of Adult/young person: | F121: ='BGLR STP APRIL 22-WM Reg'!A52 -> 39 | G121: 2 | H121: Date of entry into service: | K121: ='BGLR STP APRIL 22-WM Reg'!I52 -> 44328
A123: 3 | B123: Name of the person : | D123: ='BGLR STP APRIL 22-WM Reg'!B52 -> AsokKumar J | G123: 4 | H123: Father's Name : | J123: ='BGLR STP APRIL 22-WM Reg'!E52 -> J.Prabhakar Reddt
A125: PART I EARNED LEAVE
B127: No of Days worked | E127: Leave earned | F127: Leave at credit (incl balance if any, on return from leave on last occasion) | G127: leave availed | J127: Balance on return from leave | K127: Date on which wages for leave paid and amount paid | L127: Remarks
B128: From | C128: To | D128: Total days worked | G128: From | H128: To | I128: No. of days
B129: 1 | C129: 2 | D129: 3 | E129: 4 | F129: 5 | G129: 6 | H129: 7 | I129: 8 | J129: 9 | K129: 10 | L129: 11
B131: 44562 | C131: 44592 | D131: 31 | E131: 1.5 | F131: 8.5 | G131: 44589 | H131: 44589 | I131: 1 | J131: 7.5
B132: 44593 | C132: 44620 | D132: 28 | E132: 1.5 | J132: =J131+E132-I132 -> 9
B133: 44621 | C133: 44651 | D133: 31 | E133: 1.5 | G133: 44631 | H133: 44631 | I133: 1 | J133: =J132+E133-I133 -> 9.5
B134: 44652 | C134: 44681 | D134: 30 | E134: 1.5 | G134: 44673 | H134: 44673 | I134: 1 | J134: =J133+E134-I134 -> 10 | M134: 4
A143: PART II - Sick/Accident Leave (with pay)
B145: Year | D145: Sick/Accident leave | J145: Balance at the end of the year
D146: of credit | G146: Availed
B147: 1 | D147: 2 | G147: 3 | J147: 4
J148: =D148-G148 -> 0
A153: FORM F
A154: (SEE RULE 8 under Shops& Establishment Karnataka Rules 1974)
A155: REGISTER OF LEAVE WITH WAGES
A157: 1 | B157: Sl No in the Register of Adult/young person: | F157: ='BGLR STP APRIL 22-WM Reg'!A55 -> 42 | G157: 2 | H157: Date of entry into service: | K157: ='BGLR STP APRIL 22-WM Reg'!I55 -> 44344
A159: 3 | B159: Name of the person : | D159: ='BGLR STP APRIL 22-WM Reg'!B55 -> Majed Khan | G159: 4 | H159: Father's Name : | J159: ='BGLR STP APRIL 22-WM Reg'!E55 -> Habeeb Khan
A161: PART I EARNED LEAVE
B163: No of Days worked | E163: Leave earned | F163: Leave at credit (incl balance if any, on return from leave on last occasion) | G163: leave availed | J163: Balance on return from leave | K163: Date on which wages for leave paid and amount paid | L163: Remarks
B164: From | C164: To | D164: Total days worked | G164: From | H164: To | I164: No. of days
B165: 1 | C165: 2 | D165: 3 | E165: 4 | F165: 5 | G165: 6 | H165: 7 | I165: 8 | J165: 9 | K165: 10 | L165: 11
B167: 44562 | C167: 44592 | D167: 31 | E167: 1.5 | F167: 7.5 | G167: 44571 | H167: 44571 | I167: 1 | J167: 6.5
B168: 44593 | C168: 44620 | D168: 28 | E168: 1.5 | F168: 8 | J168: =J167+E168-I168 -> 8
B169: 44621 | C169: 44651 | D169: 31 | E169: 1.5 | F169: 9.5 | G169: 0 | H169: 0 | I169: 0 | J169: =J168+E169-I169 -> 9.5
B170: 44652 | C170: 44681 | D170: 30 | E170: 1.5 | F170: 11 | G170: 44659 | H170: 44659 | I170: 1 | J170: =J169+E170-I170 -> 10 | M170: 5
A174: 9
A179: PART II - Sick/Accident Leave (with pay)
B181: Year | D181: Sick/Accident leave | J181: Balance at the end of the year
D182: of credit | G182: Availed
B183: 1 | D183: 2 | G183: 3 | J183: 4
J184: =D184-G184 -> 0
A189: FORM F
A190: (SEE RULE 8 under Shops& Establishment Karnataka Rules 1974)
A191: REGISTER OF LEAVE WITH WAGES
A193: 1 | B193: Sl No in the Register of Adult/young person: | F193: ='04-22Master'!A21 -> BITS-587 | G193: 2 | H193: Date of entry into service: | K193: ='04-22Master'!I21 -> 44362
A195: 3 | B195: Name of the person : | D195: ='04-22Master'!B21 -> MADAN DH | G195: 4 | H195: Father's Name : | J195: ='04-22Master'!E21 -> Dayanand H
A197: PART I EARNED LEAVE
B199: No of Days worked | E199: Leave earned | F199: Leave at credit (incl balance if any, on return from leave on last occasion) | J199: Balance on return from leave | K199: Date on which wages for leave paid and amount paid | L199: Remarks
B200: From | C200: To | D200: Total days worked | G200: From | H200: To | I200: No. of days
B201: 1 | C201: 2 | D201: 3 | E201: 4 | F201: 5 | G201: 6 | H201: 7 | I201: 8 | J201: 9 | K201: 10 | L201: 11
...

Sheet Emp Cards
B1: FORM XIV
B2: EMPLOYMENT CUM WAGE CARD
B3: (Vide Rule 76 of Contract Labour (R&A) Central & Karnataka Rules, 1974)
B4: Name and Address of the Contractor | H4: Name and Address of the Establishment in/under which Contract is carried on:
B7: ='04-22Master'!F5 -> Burgeon IT Services Pvt.Ltd. | H7: ='04-22Master'!AK5 -> Burgeon IT Services Pvt.Ltd.
B9: ='04-22Master'!F6 -> Siri Mansion LIGB 436 Dr.A S Rao Nagar,Hyderabad | H9: ='04-22Master'!AK6 -> Siri Mansion LIGB 436 Dr.A S Rao Nagar,Hyderabad
B12: Nature of work and location of work: | H12: Name and address of Principal Employer:
H15: ='04-22Master'!AK10 -> INFOSYS LTD.IL Bangalore STP Park - I
B16: ='04-22Master'!F8 -> IT SUPPORTIVE SERVICES & BANGALORE STP
H17: ='04-22Master'!AK11 -> No.45&46,3rd Cross,Electronic City,BANGALORE,KARNATAKA
B19: 1. Name of the Workman and address | H19: ='04-22Master'!B16 -> AKASH DEEP CHUNAP
H20: ='04-22Master'!G16 -> H.No 4-3-216/2A,Narasimha Nagar, Bhainsa, Nirmal District, 504 103
B21: 2. S.No. in the Register of Workmen Employed | H21: ='04-22Master'!A16 -> BITS-485
B22: 3. Nature of Employment /Designation | H22: ='04-22Master'!F16 -> Network security engineer
B23: 4. Date of entry into service | H23: ='04-22Master'!I16 -> 44105
B24: 5. ESI No. | J24: ='04-22Master'!O16 -> N/A
B25: 6.PF No. | J25: ='04-22Master'!N16 -> 101629256413
B26: 7. Wage rate (With particulars of unit in case of piece - work) | H26: ='04-22Master'!T16 -> 135892
B27: 8. Wage period | H27: ='04-22Master'!D10 -> 44652
B28: 9. Tenure of Employment | H28: AS PER CONTRACT
B29: 10.No. of days worked in a month | J29: ='04-22Master'!R16 -> 30
B30: 11. No. of units worked in case of piece rate workers | J30: N/A
B31: 12. Rate of daily wages / piece rate | J31: 0
B32: 13. Amount of overtime wages | J32: 0
B33: 14. Gross wages payable | J33: ='04-22Master'!AH16 -> 148276.05 | L33: MED
B34: 15. Deductions, if any, | D34: PF | E34: ='04-22Master'!AJ16 -> 1800 | F34: ESI | G34: ='04-22Master'!AI16 -> 0 | H34: PT | I34: ='04-22Master'!AK16 -> 200 | J34: TDS | K34: ='04-22Master'!AL16 -> 0 | L34: ='04-22Master'!AM16 -> 0
B35: 16. Net amount of wages paid | J35: =J33-(E34+G34+I34+K34+L34) -> 146276.05
B36: Signature of the Representative
B37: of Contractor
B47: FORM XIV
B48: EMPLOYMENT CUM WAGE CARD
B49: (Vide Rule 76 of Contract Labour (R&A) Central & Karnataka Rules, 1974)
B50: Name and Address of the Contractor | H50: Name and Address of the Establishment in/under which Contract is carried on:
B53: ='04-22Master'!F5 -> Burgeon IT Services Pvt.Ltd. | H53: ='04-22Master'!AK5 -> Burgeon IT Services Pvt.Ltd.
B55: ='04-22Master'!F6 -> Siri Mansion LIGB 436 Dr.A S Rao Nagar,Hyderabad | H55: ='04-22Master'!AK6 -> Siri Mansion LIGB 436 Dr.A S Rao Nagar,Hyderabad
B58: Nature of work and location of work: | H58: Name and address of Principal Employer:
H61: ='04-22Master'!AK10 -> INFOSYS LTD.IL Bangalore STP Park - I
B62: ='04-22Master'!F8 -> IT SUPPORTIVE SERVICES & BANGALORE STP
H63: ='04-22Master'!AK11 -> No.45&46,3rd Cross,Electronic City,BANGALORE,KARNATAKA
B65: 1. Name of the Workman and address | H65: ='04-22Master'!B17 -> RajasekharReddy KN
H66: ='04-22Master'!G17 -> 3-48, Boorlapalli, PTM Madalam, Tamballapalli, Boorlapalle, Chittoor, AP 517370
B67: 2. S.No. in the Register of Workmen Employed | H67: ='04-22Master'!A17 -> BITS-565
B68: 3. Nature of Employment /Designation | H68: ='04-22Master'!F17 -> Citrix Administrator
B69: 4. Date of entry into service | H69: ='04-22Master'!I17 -> 44326
B70: 5. ESI No. | J70: ='04-22Master'!O17 -> N/A
B71: 6.PF No. | J71: ='04-22Master'!N17 -> 100432313742
B72: 7. Wage rate (With particulars of unit in case of piece - work) | H72: ='04-22Master'!T17 -> 66374
B73: 8. Wage period | H73: ='04-22Master'!D10 -> 44652
B74: 9. Tenure of Employment | H74: AS PER CONTRACT
B75: 10.No. of days worked in a month | J75: ='04-22Master'!R17 -> 30
B76: 11. No. of units worked in case of piece rate workers | J76: N/A
B77: 12. Rate of daily wages / piece rate | J77: 0
B78: 13. Amount of overtime wages | J78: 0
B79: 14. Gross wages payable | J79: ='04-22Master'!AH17 -> 73275.863 | L79: MED
B80: 15. Deductions, if any, | D80: PF | E80: 1800 | F80: ESI | G80: ='04-22Master'!AI678 -> 0 | H80: PT | I80: 200 | J80: TDS | K80: ='04-22Master'!AL17 -> 0 | L80: ='04-22Master'!AM17 -> 391.78785
B81: 16. Net amount of wages paid | J81: =J79-(E80+G80+I80+K80+L80) -> 70884.075
B82: Signature of the Representative
B83: of Contractor
B99: FORM XIV
B100: EMPLOYMENT CUM WAGE CARD
B101: (Vide Rule 76 of Contract Labour (R&A) Central & Karnataka Rules, 1974)
B102: Name and Address of the Contractor | H102: Name and Address of the Establishment in/under which Contract is carried on:
B105: ='04-22Master'!F5 -> Burgeon IT Services Pvt.Ltd. | H105: ='04-22Master'!AK5 -> Burgeon IT Services Pvt.Ltd.
B107: ='04-22Master'!F6 -> Siri Mansion LIGB 436 Dr.A S Rao Nagar,Hyderabad | H107: ='04-22Master'!AK6 -> Siri Mansion LIGB 436 Dr.A S Rao Nagar,Hyderabad
B110: Nature of work and location of work: | H110: Name and address of Principal Employer:
H113: ='04-22Master'!AK10 -> INFOSYS LTD.IL Bangalore STP Park - I
B114: ='04-22Master'!F8 -> IT SUPPORTIVE SERVICES & BANGALORE STP
H115: ='04-22Master'!AK11 -> No.45&46,3rd Cross,Electronic City,BANGALORE,KARNATAKA
B117: 1. Name of the Workman and address | H117: ='04-22Master'!B18 -> Moulika GM
H118: ='04-22Master'!G18 -> 12A/22A,METTU,TIRUTTANI
B119: 2. S.No. in the Register of Workmen Employed | H119: ='04-22Master'!A18 -> BITS-566
B120: 3. Nature of Employment /Designation | H120: ='04-22Master'!F18 -> Ansible Developer
B121: 4. Date of entry into service | H121: ='04-22Master'!I18 -> 44327
B122: 5. ESI No. | J122: ='04-22Master'!O18 -> N/A
B123: 6.PF No. | J123: ='04-22Master'!N18 -> 101695261774
B124: 7. Wage rate (With particulars of unit in case of piece - work) | H124: ='04-22Master'!AH18 -> 23276.096
B125: 8. Wage period | H125: ='04-22Master'!D10 -> 44652
B126: 9. Tenure of Employment | H126: AS PER CONTRACT
B127: 10.No. of days worked in a month | J127: ='04-22Master'!R18 -> 30
B128: 11. No. of units worked in case of piece rate workers | J128: N/A
B129: 12. Rate of daily wages / piece rate | J129: 0
B130: 13. Amount of overtime wages | J130: 0
B131: 14. Gross wages payable | J131: ='04-22Master'!AH18 -> 23276.096 | L131: MED
B132: 15. Deductions, if any, | D132: PF | E132: ='04-22Master'!AJ18 -> 1442 | F132: ESI | G132: ='04-22Master'!AI725 -> 0 | H132: PT | I132: ='04-22Master'!AK18 -> 200 | J132: TDS | K132: ='04-22Master'!AL18 -> 0 | L132: ='04-22Master'!AM18 -> 391.78785
B133: 16. Net amount of wages paid | J133: =J131-(E132+G132+I132+K132+L132) -> 21242.308
B134: Signature of the Representative
B135: of Contractor
B151: FORM XIV
B152: EMPLOYMENT CUM WAGE CARD
B153: (Vide Rule 76 of Contract Labour (R&A) Central & Karnataka Rules, 1974)
B154: Name and Address of the Contractor | H154: Name and Address of the Establishment in/under which Contract is carried on:
B157: ='04-22Master'!F5 -> Burgeon IT Services Pvt.Ltd. | H157: ='04-22Master'!AK5 -> Burgeon IT Services Pvt.Ltd.
B159: ='04-22Master'!F6 -> Siri Mansion LIGB 436 Dr.A S Rao Nagar,Hyderabad | H159: ='04-22Master'!AK6 -> Siri Mansion LIGB 436 Dr.A S Rao Nagar,Hyderabad
B162: Nature of work and location of work: | H162: Name and address of Principal Employer:
H165: ='04-22Master'!AK10 -> INFOSYS LTD.IL Bangalore STP Park - I
B166: ='04-22Master'!F8 -> IT SUPPORTIVE SERVICES & BANGALORE STP
H167: ='04-22Master'!AK11 -> No.45&46,3rd Cross,Electronic City,BANGALORE,KARNATAKA
B169: 1. Name of the Workman and address | H169: ='04-22Master'!B19 -> AsokKumar J
H170: ='04-22Master'!G19 -> #303, Dhanunjaya Apartment, Dasarahalli Main Road, Hebbal,Bangalore-560024.
B171: 2. S.No. in the Register of Workmen Employed | H171: ='04-22Master'!A19 -> BITS-567
...

Sheet wage sllips
A2: Form XIX - WAGE SLIP | K2: Form XIX - WAGE SLIP
A3: [Vide rule 78 (1) (b) of the Contract Labour (Regulation and Abolition) Central and A.P Rules, 1971] | K3: [Vide rule 78 (1) (b) of the Contract Labour (Regulation and Abolition) Central and A.P Rules, 1971]
A5: Name and address of Contractor | D5: ='04-22Master'!F5 -> Burgeon IT Services Pvt.Ltd. | K5: Name and address of Contractor | N5: =D5 -> Burgeon IT Services Pvt.Ltd.
B6: ='04-22Master'!F6 -> Siri Mansion LIGB 436 Dr.A S Rao Nagar,Hyderabad | L6: =B6 -> Siri Mansion LIGB 436 Dr.A S Rao Nagar,Hyderabad
B7: ='04-22Master'!F597 -> 0 | L7: =B7 -> 0
A8: Name and Father's / Husband's name of the workman | K8: Name and Father's / Husband's name of the workman
E9: ='04-22Master'!B16 -> AKASH DEEP CHUNAP | H9: ='04-22Master'!E16 -> Priyanka Chunap | O9: =E9 -> AKASH DEEP CHUNAP | R9: =H9 -> Priyanka Chunap
A11: Nature and location of work | E11: ='04-22Master'!F8 -> IT SUPPORTIVE SERVICES & BANGALORE STP | K11: Nature and location of work | O11: =E11 -> IT SUPPORTIVE SERVICES & BANGALORE STP
A13: For the Week / Fortnight / Month ending | E13: ='04-22Master'!D10 -> 44652 | K13: For the Week / Fortnight / Month ending | O13: =E13 -> 44652
A15: 1 | B15: No. of days worked | E15: ='04-22Master'!R16 -> 30 | K15: 1 | L15: No. of days worked | O15: =E15 -> 30
A17: 2 | B17: No. of units worked in case of piece rate workers : | K17: 2 | L17: No. of units worked in case of piece rate workers :
E18: N/A | O18: N/A
A20: 3 | B20: Rate of daily wages / piece rate | E20: N/A | K20: 3 | L20: Rate of daily wages / piece rate | O20: =E20 -> N/A
A22: 4 | B22: Amount of overtime wages | E22: Nil | K22: 4 | L22: Amount of overtime wages | O22: Nil
A24: 5 | B24: Gross wages payble | E24: ='04-22Master'!AH16 -> 148276.05 | K24: 5 | L24: Gross wages payble | O24: =E24 -> 148276.05
D25: EPF | E25: ESI | F25: PT | G25: TDS | H25: MEDICAL | I25: TOTAL | N25: EPF | O25: ESI | P25: PT | Q25: TDS | R25: MEDICAL | S25: TOTAL
A26: 6 | B26: Deductions, if any | D26: ='04-22Master'!AJ16 -> 1800 | E26: ='04-22Master'!AI16 -> 0 | F26: ='04-22Master'!AK16 -> 200 | G26: ='04-22Master'!AL16 -> 0 | H26: ='04-22Master'!AM16 -> 0 | I26: ='04-22Master'!AN16 -> 2000 | K26: 6 | L26: Deductions, if any | N26: =D26 -> 1800 | O26: =E26 -> 0 | P26: =F26 -> 200 | Q26: =G26 -> 0 | R26: =H26 -> 0 | S26: =I26 -> 2000
A28: 7 | B28: Net amount of wages paid | E28: =E24-I26 -> 146276.05 | K28: 7 | L28: Net amount of wages paid | O28: =E28 -> 146276.05
F32: Initial of the Contractor or his representative | P32: Initial of the Contractor or his representative
A49: Form XIX - WAGE SLIP | K49: Form XIX - WAGE SLIP
A50: [Vide rule 78 (1) (b) of the Contract Labour (Regulation and Abolition) Central and A.P Rules, 1971] | K50: [Vide rule 78 (1) (b) of the Contract Labour (Regulation and Abolition) Central and A.P Rules, 1971]
A52: Name and address of Contractor | D52: ='04-22Master'!F5 -> Burgeon IT Services Pvt.Ltd. | K52: Name and address of Contractor | N52: =D52 -> Burgeon IT Services Pvt.Ltd.
B53: ='04-22Master'!F6 -> Siri Mansion LIGB 436 Dr.A S Rao Nagar,Hyderabad | L53: =B53 -> Siri Mansion LIGB 436 Dr.A S Rao Nagar,Hyderabad
B54: ='04-22Master'!F1714 -> 0 | L54: =B54 -> 0
A55: Name and Father's / Husband's name of the workman | K55: Name and Father's / Husband's name of the workman
E56: ='04-22Master'!B17 -> RajasekharReddy KN | H56: ='04-22Master'!E17 -> Narayana Reddy | O56: =E56 -> RajasekharReddy KN | R56: =H56 -> Narayana Reddy
A58: Nature and location of work | E58: ='04-22Master'!F8 -> IT SUPPORTIVE SERVICES & BANGALORE STP | K58: Nature and location of work | O58: =E58 -> IT SUPPORTIVE SERVICES & BANGALORE STP
A60: For the Week / Fortnight / Month ending | E60: ='04-22Master'!D10 -> 44652 | K60: For the Week / Fortnight / Month ending | O60: =E60 -> 44652
A62: 1 | B62: No. of days worked | E62: ='04-22Master'!R17 -> 30 | K62: 1 | L62: No. of days worked | O62: =E62 -> 30
A64: 2 | B64: No. of units worked in case of piece rate workers : | K64: 2 | L64: No. of units worked in case of piece rate workers :
E65: N/A | O65: N/A
A67: 3 | B67: Rate of daily wages / piece rate | E67: N/A | K67: 3 | L67: Rate of daily wages / piece rate | O67: =E67 -> N/A
A69: 4 | B69: Amount of overtime wages | E69: Nil | K69: 4 | L69: Amount of overtime wages | O69: Nil
A71: 5 | B71: Gross wages payble | E71: ='04-22Master'!AH17 -> 73275.863 | K71: 5 | L71: Gross wages payble | O71: =E71 -> 73275.863
D72: EPF | E72: ESI | F72: PT | G72: TDS | H72: MEDICAL | I72: TOTAL | N72: EPF | O72: ESI | P72: PT | Q72: TDS | R72: MEDICAL | S72: TOTAL
A73: 6 | B73: Deductions, if any | D73: ='04-22Master'!AJ17 -> 1800 | E73: ='04-22Master'!AI17 -> 0 | F73: ='04-22Master'!AK17 -> 200 | G73: ='04-22Master'!AL17 -> 0 | H73: ='04-22Master'!AM17 -> 391.78785 | I73: =SUM(D73:H73) -> 2391.7878 | K73: 6 | L73: Deductions, if any | N73: =D73 -> 1800 | O73: =E73 -> 0 | P73: =F73 -> 200 | Q73: =G73 -> 0 | R73: =H73 -> 391.78785 | S73: =I73 -> 2391.7878
A75: 7 | B75: Net amount of wages paid | E75: =E71-I73 -> 70884.075 | K75: 7 | L75: Net amount of wages paid | O75: =E75 -> 70884.075
F79: Initial of the Contractor or his representative | P79: Initial of the Contractor or his representative
A95: Form XIX - WAGE SLIP | K95: Form XIX - WAGE SLIP
A96: [Vide rule 78 (1) (b) of the Contract Labour (Regulation and Abolition) Central and A.P Rules, 1971] | K96: [Vide rule 78 (1) (b) of the Contract Labour (Regulation and Abolition) Central and A.P Rules, 1971]
A98: Name and address of Contractor | D98: ='04-22Master'!F5 -> Burgeon IT Services Pvt.Ltd. | K98: Name and address of Contractor | N98: =D98 -> Burgeon IT Services Pvt.Ltd.
B99: ='04-22Master'!F6 -> Siri Mansion LIGB 436 Dr.A S Rao Nagar,Hyderabad | L99: =B99 -> Siri Mansion LIGB 436 Dr.A S Rao Nagar,Hyderabad
B100: ='04-22Master'!F1755 -> 0 | L100: =B100 -> 0
A101: Name and Father's / Husband's name of the workman | K101: Name and Father's / Husband's name of the workman
E102: ='04-22Master'!B18 -> Moulika GM | H102: ='04-22Master'!E18 -> Maniganda Charan Kumar | O102: =E102 -> Moulika GM | R102: =H102 -> Maniganda Charan Kumar
A104: Nature and location of work | E104: ='04-22Master'!F8 -> IT SUPPORTIVE SERVICES & BANGALORE STP | K104: Nature and location of work | O104: =E104 -> IT SUPPORTIVE SERVICES & BANGALORE STP
A106: For the Week / Fortnight / Month ending | E106: ='04-22Master'!D10 -> 44652 | K106: For the Week / Fortnight / Month ending | O106: =E106 -> 44652
A108: 1 | B108: No. of days worked | E108: ='04-22Master'!R18 -> 30 | K108: 1 | L108: No. of days worked | O108: =E108 -> 30
A110: 2 | B110: No. of units worked in case of piece rate workers : | K110: 2 | L110: No. of units worked in case of piece rate workers :
E111: N/A | O111: N/A
A113: 3 | B113: Rate of daily wages / piece rate | E113: N/A | K113: 3 | L113: Rate of daily wages / piece rate | O113: =E113 -> N/A
A115: 4 | B115: Amount of overtime wages | E115: Nil | K115: 4 | L115: Amount of overtime wages | O115: Nil
A117: 5 | B117: Gross wages payble | E117: ='04-22Master'!AH18 -> 23276.096 | K117: 5 | L117: Gross wages payble | O117: =E117 -> 23276.096
D118: EPF | E118: ESI | F118: PT | G118: TDS | H118: MEDICAL | I118: TOTAL | N118: EPF | O118: ESI | P118: PT | Q118: TDS | R118: MEDICAL | S118: TOTAL
A119: 6 | B119: Deductions, if any | D119: ='04-22Master'!AJ18 -> 1442 | E119: ='04-22Master'!AI686 -> 0 | F119: ='04-22Master'!AK18 -> 200 | G119: ='04-22Master'!AL18 -> 0 | H119: ='04-22Master'!AM18 -> 391.78785 | I119: =SUM(D119:H119) -> 2033.7878 | K119: 6 | L119: Deductions, if any | N119: =D119 -> 1442 | O119: =E119 -> 0 | P119: =F119 -> 200 | Q119: =G119 -> 0 | R119: =H119 -> 391.78785 | S119: =I119 -> 2033.7878
A121: 7 | B121: Net amount of wages paid | E121: =E117-I119 -> 21242.308 | K121: 7 | L121: Net amount of wages paid | O121: =E121 -> 21242.308
F125: Initial of the Contractor or his representative | P125: Initial of the Contractor or his representative
A141: Form XIX - WAGE SLIP | K141: Form XIX - WAGE SLIP
A142: [Vide rule 78 (1) (b) of the Contract Labour (Regulation and Abolition) Central and A.P Rules, 1971] | K142: [Vide rule 78 (1) (b) of the Contract Labour (Regulation and Abolition) Central and A.P Rules, 1971]
A144: Name and address of Contractor | D144: ='04-22Master'!F5 -> Burgeon IT Services Pvt.Ltd. | K144: Name and address of Contractor | N144: =D144 -> Burgeon IT Services Pvt.Ltd.
B145: ='04-22Master'!F6 -> Siri Mansion LIGB 436 Dr.A S Rao Nagar,Hyderabad | L145: =B145 -> Siri Mansion LIGB 436 Dr.A S Rao Nagar,Hyderabad
B146: ='04-22Master'!F1794 -> 0 | L146: =B146 -> 0
A147: Name and Father's / Husband's name of the workman | K147: Name and Father's / Husband's name of the workman
E148: ='04-22Master'!B19 -> AsokKumar J | H148: ='04-22Master'!E19 -> J.Prabhakar Reddt | O148: =E148 -> AsokKumar J | R148: =H148 -> J.Prabhakar Reddt
A150: Nature and location of work | E150: ='04-22Master'!F8 -> IT SUPPORTIVE SERVICES & BANGALORE STP | K150: Nature and location of work | O150: =E150 -> IT SUPPORTIVE SERVICES & BANGALORE STP
A152: For the Week / Fortnight / Month ending | E152: ='04-22Master'!D10 -> 44652 | K152: For the Week / Fortnight / Month ending | O152: =E152 -> 44652
A154: 1 | B154: No. of days worked | E154: ='04-22Master'!R19 -> 28 | K154: 1 | L154: No. of days worked | O154: =E154 -> 28
A156: 2 | B156: No. of units worked in case of piece rate workers : | K156: 2 | L156: No. of units worked in case of piece rate workers :
E157: N/A | O157: N/A
A159: 3 | B159: Rate of daily wages / piece rate | E159: N/A | K159: 3 | L159: Rate of daily wages / piece rate | O159: =E159 -> N/A
A161: 4 | B161: Amount of overtime wages | E161: Nil | K161: 4 | L161: Amount of overtime wages | O161: Nil
A163: 5 | B163: Gross wages payble | E163: ='04-22Master'!AH19 -> 124501.72 | K163: 5 | L163: Gross wages payble | O163: =E163 -> 124501.72
D164: EPF | E164: ESI | F164: PT | G164: TDS | H164: MEDICAL | I164: TOTAL | N164: EPF | O164: ESI | P164: PT | Q164: TDS | R164: MEDICAL | S164: TOTAL
A165: 6 | B165: Deductions, if any | D165: ='04-22Master'!AJ19 -> 1800 | E165: ='04-22Master'!AI725 -> 0 | F165: ='04-22Master'!AK19 -> 200 | G165: ='04-22Master'!AL19 -> 0 | H165: ='04-22Master'!AM19 -> 391.78785 | I165: =SUM(D165:H165) -> 2391.7878 | K165: 6 | L165: Deductions, if any | N165: =D165 -> 1800 | O165: =E165 -> 0 | P165: =F165 -> 200 | Q165: =G165 -> 0 | R165: =H165 -> 391.78785 | S165: =I165 -> 2391.7878
A167: 7 | B167: Net amount of wages paid | E167: =E163-I165 -> 122109.93 | K167: 7 | L167: Net amount of wages paid | O167: =E167 -> 122109.93
F171: Initial of the Contractor or his representative | P171: Initial of the Contractor or his representative
A187: Form XIX - WAGE SLIP | K187: Form XIX - WAGE SLIP
A188: [Vide rule 78 (1) (b) of the Contract Labour (Regulation and Abolition) Central and A.P Rules, 1971] | K188: [Vide rule 78 (1) (b) of the Contract Labour (Regulation and Abolition) Central and A.P Rules, 1971]
A190: Name and address of Contractor | D190: ='04-22Master'!F5 -> Burgeon IT Services Pvt.Ltd. | K190: Name and address of Contractor | N190: =D190 -> Burgeon IT Services Pvt.Ltd.
B191: ='04-22Master'!F6 -> Siri Mansion LIGB 436 Dr.A S Rao Nagar,Hyderabad | L191: =B191 -> Siri Mansion LIGB 436 Dr.A S Rao Nagar,Hyderabad
B192: ='04-22Master'!F1917 -> 0 | L192: =B192 -> 0
A193: Name and Father's / Husband's name of the workman | K193: Name and Father's / Husband's name of the workman
E194: ='04-22Master'!B20 -> Majed Khan | H194: ='04-22Master'!E20 -> Habeeb Khan | O194: =E194 -> Majed Khan | R194: =H194 -> Habeeb Khan
A196: Nature and location of work | E196: ='04-22Master'!F8 -> IT SUPPORTIVE SERVICES & BANGALORE STP | K196: Nature and location of work | O196: =E196 -> IT SUPPORTIVE SERVICES & BANGALORE STP
A198: For the Week / Fortnight / Month ending | E198: ='04-22Master'!D10 -> 44652 | K198: For the Week / Fortnight / Month ending | O198: =E198 -> 44652
A200: 1 | B200: No. of days worked | E200: ='04-22Master'!R20 -> 30 | K200: 1 | L200: No. of days worked | O200: =E200 -> 30
A202: 2 | B202: No. of units worked in case of piece rate workers : | K202: 2 | L202: No. of units worked in case of piece rate workers :
E203: N/A | O203: N/A
A205: 3 | B205: Rate of daily wages / piece rate | E205: N/A | K205: 3 | L205: Rate of daily wages / piece rate | O205: =E205 -> N/A
A207: 4 | B207: Amount of overtime wages | E207: Nil | K207: 4 | L207: Amount of overtime wages | O207: Nil
A209: 5 | B209: Gross wages payble | E209: ='04-22Master'!AH20 -> 148276.05 | K209: 5 | L209: Gross wages payble | O209: =E209 -> 148276.05
D210: EPF | E210: ESI | F210: PT | G210: TDS | H210: MEDICAL | I210: TOTAL | N210: EPF | O210: ESI | P210: PT | Q210: TDS | R210: MEDICAL | S210: TOTAL
A211: 6 | B211: Deductions, if any | D211: ='04-22Master'!AJ20 -> 1800 | E211: ='04-22Master'!AI848 -> 0 | F211: ='04-22Master'!AK20 -> 200 | G211: ='04-22Master'!AL20 -> 0 | H211: ='04-22Master'!AM20 -> 391.78785 | I211: =SUM(D211:H211) -> 2391.7878 | K211: 6 | L211: Deductions, if any | N211: =D211 -> 1800 | O211: =E211 -> 0 | P211: =F211 -> 200 | Q211: =G211 -> 0 | R211: =H211 -> 391.78785 | S211: =I211 -> 2391.7878
A213: 7 | B213: Net amount of wages paid | E213: =E209-I211 -> 145884.26 | K213: 7 | L213: Net amount of wages paid | O213: =E213 -> 145884.26
F217: Initial of the Contractor or his representative | P217: Initial of the Contractor or his representative
A233: Form XIX - WAGE SLIP | K233: Form XIX - WAGE SLIP
A234: [Vide rule 78 (1) (b) of the Contract Labour (Regulation and Abolition) Central and A.P Rules, 1971] | K234: [Vide rule 78 (1) (b) of the Contract Labour (Regulation and Abolition) Central and A.P Rules, 1971]
A236: Name and address of Contractor | D236: ='04-22Master'!F5 -> Burgeon IT Services Pvt.Ltd. | K236: Name and address of Contractor | N236: =D236 -> Burgeon IT Services Pvt.Ltd.
D237: ='04-22Master'!F6 -> Siri Mansion LIGB 436 Dr.A S Rao Nagar,Hyderabad | N237: =D237 -> Siri Mansion LIGB 436 Dr.A S Rao Nagar,Hyderabad
A239: Name and Father's / Husband's name of the workman | K239: Name and Father's / Husband's name of the workman
...

Sheet 4-22Bonus
A1: BONUS REGISTER
A3: FORM "c" ( See rule 4 [c] )
K4: Wage Period | L4: ='04-22Master'!D10 -> 44652
A5: Name of the Establishment : _____________________________ | D5: ='04-22Master'!F5 -> Burgeon IT Services Pvt.Ltd. | K5: Financial year _____ | M5: 2022-2023
A6: ='04-22Master'!F6 -> Siri Mansion LIGB 436 Dr.A S Rao Nagar,Hyderabad
A7: Sr. No | B7: Name of the Employee | C7: Father's Name / Husband's Name | D7: Whether he has completed 15 yrs of age at the beginning of the accounting year | E7: Designation | F7: No. of days worked in the year | G7: Total Salary or wages in the year | H7: Amt. of bonus payable under section 10 or section 11 as the case may be Ex gratia | I7: DEDUCTIONS | L7: Total Sum Deducted (Col. 9,10 and 11) | M7: Net Amount payable (Col. 8 minus Col. 12) | N7: Amount Actually paid | O7: Date on which paid | P7: Signature / Thumb impression of the employee
I8: Puja Bonus or other customary bonus paid during the accounting year | J8: Interim Bonus or bonus paid in advance | K8: Deduction on account of financial loss if any caused by misconduct of the employee | Q8: Account Number
A9: 1 | B9: 2 | C9: 3 | D9: 4 | E9: 5 | F9: 6 | H9: 8 | I9: 9 | J9: 10 | K9: 11 | L9: 12 | M9: 13 | N9: 14 | O9: 15 | P9: 16
A10: 1 | B10: ='04-22Master'!B16 -> AKASH DEEP CHUNAP | C10: ='04-22Master'!E16 -> Priyanka Chunap | D10: YES | E10: ='04-22Master'!F16 -> Network security engineer | F10: ='04-22Master'!R16 -> 30 | G10: ='04-22Master'!AH16 -> 148276.05 | H10: ='04-22Master'!AD16 -> 1554.609 | I10: N/A | J10: N/A | K10: N/A | L10: N/A | M10: =H10 -> 1554.609 | N10: =H10 -> 1554.609 | O10: ='04-22Master'!AP16 -> 44686 | P10: ='04-22Master'!AQ16 -> SBIN | Q10: ='04-22Master'!AR16 -> A/C 621 732 836 92
A11: 2 | B11: ='04-22Master'!B17 -> RajasekharReddy KN | C11: ='04-22Master'!E17 -> Narayana Reddy | D11: YES | E11: ='04-22Master'!F17 -> Citrix Administrator | F11: ='04-22Master'!R17 -> 30 | G11: ='04-22Master'!AH17 -> 73275.863 | H11: ='04-22Master'!AD17 -> 1554.609 | I11: N/A | J11: N/A | K11: N/A | L11: N/A | M11: =H11 -> 1554.609 | N11: =H11 -> 1554.609 | O11: ='04-22Master'!AP17 -> 44686 | P11: ='04-22Master'!AQ17 -> ICICI | Q11: ='04-22Master'!AR17 -> 272601504387
A12: 3 | B12: ='04-22Master'!B18 -> Moulika GM | C12: ='04-22Master'!E18 -> Maniganda Charan Kumar | D12: YES | E12: ='04-22Master'!F18 -> Ansible Developer | F12: ='04-22Master'!R18 -> 30 | G12: ='04-22Master'!AH18 -> 23276.096 | H12: ='04-22Master'!AD18 -> 1554.609 | I12: N/A | J12: N/A | K12: N/A | L12: N/A | M12: =H12 -> 1554.609 | N12: =H12 -> 1554.609 | O12: ='04-22Master'!AP18 -> 44686 | P12: ='04-22Master'!AQ18 -> Indian Bank | Q12: ='04-22Master'!AR18 -> 6685853376
A13: 4 | B13: ='04-22Master'!B19 -> AsokKumar J | C13: ='04-22Master'!E19 -> J.Prabhakar Reddt | D13: YES | E13: ='04-22Master'!F19 -> Senior Middleware Administrator (MQ & Kafka) | F13: ='04-22Master'!R19 -> 28 | G13: ='04-22Master'!AH19 -> 124501.72 | H13: ='04-22Master'!AD19 -> 1554.609 | I13: N/A | J13: N/A | K13: N/A | L13: N/A | M13: =H13 -> 1554.609 | N13: =H13 -> 1554.609 | O13: ='04-22Master'!AP19 -> 44686 | P13: ='04-22Master'!AQ19 -> HDFC | Q13: ='04-22Master'!AR19 -> 50100397382442
A14: 5 | B14: ='04-22Master'!B20 -> Majed Khan | C14: ='04-22Master'!E20 -> Habeeb Khan | D14: YES | E14: ='04-22Master'!F20 -> Oracle/SAP DBA | F14: ='04-22Master'!R20 -> 30 | G14: ='04-22Master'!AH20 -> 148276.05 | H14: ='04-22Master'!AD20 -> 1554.609 | I14: N/A | J14: N/A | K14: N/A | L14: N/A | M14: =H14 -> 1554.609 | N14: =H14 -> 1554.609 | O14: ='04-22Master'!AP20 -> 44686 | P14: ='04-22Master'!AQ20 -> HDFC | Q14: ='04-22Master'!AR20 -> 07941610141597
A15: 6 | B15: ='04-22Master'!B21 -> MADAN DH | C15: ='04-22Master'!E21 -> Dayanand H | D15: YES | E15: ='04-22Master'!F21 -> Principal Storage Consultant | F15: ='04-22Master'!R21 -> 30 | G15: ='04-22Master'!AH21 -> 103275.72 | H15: ='04-22Master'!AD21 -> 1554.609 | I15: N/A | J15: N/A | K15: N/A | L15: N/A | M15: =H15 -> 1554.609 | N15: =H15 -> 1554.609 | O15: ='04-22Master'!AP21 -> 44686 | P15: ='04-22Master'!AQ21 -> HDFC Bank | Q15: ='04-22Master'!AR21 -> 50100122835737
A16: 7 | B16: ='04-22Master'!B22 -> Sachin | C16: ='04-22Master'!E22 -> POONAM SACHIN MESHRAM | D16: YES | E16: ='04-22Master'!F22 -> Windows Administrator | F16: ='04-22Master'!R22 -> 13 | G16: ='04-22Master'!AH22 -> 41364.478 | H16: ='04-22Master'!AD22 -> 1554.609 | I16: N/A | J16: N/A | K16: N/A | L16: N/A | M16: =H16 -> 1554.609 | N16: =H16 -> 1554.609 | O16: ='04-22Master'!AP22 -> 44686 | P16: ='04-22Master'!AQ22 -> STATE BANK OF INDIA | Q16: ='04-22Master'!AR22 -> 20079696052
A17: 8 | B17: ='04-22Master'!B23 -> Barathiyar A | C17: ='04-22Master'!E23 -> Arumugam | D17: YES | E17: ='04-22Master'!F23 -> VMware & Wintel Admin | F17: ='04-22Master'!R23 -> 13 | G17: ='04-22Master'!AH23 -> 29231.295 | H17: ='04-22Master'!AD23 -> 1554.609 | I17: N/A | J17: N/A | K17: N/A | L17: N/A | M17: =H17 -> 1554.609 | N17: =H17 -> 1554.609 | O17: ='04-22Master'!AP23 -> 44686 | P17: ='04-22Master'!AQ23 -> ICICI BANK | Q17: ='04-22Master'!AR23 -> 602601522530
A18: 9 | B18: ='04-22Master'!B24 -> Kumaravel M | C18: ='04-22Master'!E24 -> Madhavaraj | D18: YES | E18: ='04-22Master'!F24 -> Sr. Network Administrator | F18: ='04-22Master'!R24 -> 30 | G18: ='04-22Master'!AH24 -> 53275.956 | H18: ='04-22Master'!AD24 -> 1554.609 | I18: N/A | J18: N/A | K18: N/A | L18: N/A | M18: =H18 -> 1554.609 | N18: =H18 -> 1554.609 | O18: ='04-22Master'!AP24 -> 44686 | P18: ='04-22Master'!AQ24 -> Indian Bank | Q18: ='04-22Master'!AR24 -> 443843855
A19: 10 | B19: ='04-22Master'!B25 -> CHANDRASEHARAN GERORGE | C19: ='04-22Master'!E25 -> George | D19: YES | E19: ='04-22Master'!F25 -> SENIOR TECHNICAL SPECIALIST | F19: ='04-22Master'!R25 -> 15 | G19: ='04-22Master'!AH25 -> 28971.937 | H19: ='04-22Master'!AD25 -> 1554.609 | I19: N/A | J19: N/A | K19: N/A | L19: N/A | M19: =H19 -> 1554.609 | N19: =H19 -> 1554.609 | O19: ='04-22Master'!AP25 -> 44686 | P19: ='04-22Master'!AQ25 -> Standard Charter Bank | Q19: ='04-22Master'!AR25 -> 42610387037
A20: 11 | B20: ='04-22Master'!B26 -> VISHNUPRASATH T | C20: ='04-22Master'!E26 -> Thavamani | D20: YES | E20: ='04-22Master'!F26 -> Sr. Network Engineer | F20: ='04-22Master'!R26 -> 30 | G20: ='04-22Master'!AH26 -> 53275.956 | H20: ='04-22Master'!AD26 -> 1554.609 | I20: N/A | J20: N/A | K20: N/A | L20: N/A | M20: =H20 -> 1554.609 | N20: =H20 -> 1554.609 | O20: ='04-22Master'!AP26 -> 44686 | P20: ='04-22Master'!AQ26 -> ICICI BANK | Q20: ='04-22Master'!AR26 -> 270401504431
A21: 12 | B21: ='04-22Master'!B27 -> Nagaranjan S | C21: ='04-22Master'!E27 -> SUBBIAH G | D21: YES | E21: ='04-22Master'!F27 -> Linux Administrator | F21: ='04-22Master'!R27 -> 30 | G21: ='04-22Master'!AH27 -> 53275.956 | H21: ='04-22Master'!AD27 -> 1554.609 | I21: N/A | J21: N/A | K21: N/A | L21: N/A | M21: =H21 -> 1554.609 | N21: =H21 -> 1554.609 | O21: ='04-22Master'!AP27 -> 44686 | P21: ='04-22Master'!AQ27 -> IDBI BANK | Q21: ='04-22Master'!AR27 -> 005104000198752
... A43: 34 | B43: ='04-22Master'!B49 -> Laxmi Soujanya Mudunuri | C43: ='04-22Master'!E49 -> Venkata Satya narayana Raju | D43: YES | E43: ='04-22Master'!F49 -> Senior Middleware Consultant | F43: ='04-22Master'!R49 -> 11 | G43: ='04-22Master'!AH49 -> 64590.86 | H43: ='04-22Master'!AD49 -> 1554.609 | I43: N/A | J43: N/A | K43: N/A | L43: N/A | M43: =H43 -> 1554.609 | N43: =H43 -> 1554.609 | O43: ='04-22Master'!AP49 -> 44686 | P43: ='04-22Master'!AQ49 -> Axis Bank | Q43: ='04-22Master'!AR49 -> 915010032166004
H44: =SUM(H10:H43) -> 52856.706
M47: Signature of the Contractor with Seal

Sheet Ded
A1: FORM XX- REGISTER OF DEDUCTIONS FOR DAMAGE OR LOSS
A3: (Vide Rule 78(1) (a) (i) of Contract Labour (Regulation and Abolition) Central /Karnataka Rules 1974.
A4: Name and address of Contractor: GROTECH LANDSCAPE DEVELOPERS PVT.LTD. | D4: ='04-22Master'!F5 -> Burgeon IT Services Pvt.Ltd. | E4: Name and address of the establishment in / under which contract is carried on:
B5: ='04-22Master'!F6 -> Siri Mansion LIGB 436 Dr.A S Rao Nagar,Hyderabad | E5: ='04-22Master'!AK5 -> Burgeon IT Services Pvt.Ltd.
E6: ='04-22Master'!AK6 -> Siri Mansion LIGB 436 Dr.A S Rao Nagar,Hyderabad
A7: Nature and Location of Work: | D7: ='04-22Master'!F8 -> IT SUPPORTIVE SERVICES & BANGALORE STP | E7: Name and address of principal employer:
E8: ='04-22Master'!AK10 -> INFOSYS LTD.IL Bangalore STP Park - I
E9: ='04-22Master'!AK11 -> No.45&46,3rd Cross,Electronic City,BANGALORE,KARNATAKA
A11: S.No | B11: Name of workman | C11: Father's / Husband's Name | D11: Designation / Nature of employment | E11: Particulars of damage or loss | F11: Date of Damage or loss | G11: Whether workman showed cause against deduction | H11: Name of person in whose presence employee's explanation was heard | I11: Amount of deduction impossed | J11: Date of recovery | M11: Remarks
J12: No.of Instalments | K12: First Instalment | L12: Last instalment
A13: 1 | B13: 2 | C13: 3 | D13: 4 | E13: 5 | F13: 6 | G13: 7 | H13: 8 | I13: 9 | J13: 10 | K13: 11 | L13: 12 | M13: 13
B16: NO EMPLOYEE WAS IMPOSED DEDUCTIONS FOR DAMAGE OR LOSS FOR THE MONTH OF | H16: ='04-22Master'!D10 -> 44652
F37: Signature of the Contractor with Seal

Sheet Fines
A1: FORM XXI- REGISTER OF FINES
A3: (Vide Rule 78(1) (a) (i) of Contract Labour (Regulation and Abolition) Central /Karnataka Rules 1974
A4: Name and address of Contractor: | D4: ='04-22Master'!F5 -> Burgeon IT Services Pvt.Ltd. | E4: Name and address of the establishment in / under which contract is carried on:
B5: ='04-22Master'!F6 -> Siri Mansion LIGB 436 Dr.A S Rao Nagar,Hyderabad | E5: ='04-22Master'!AK5 -> Burgeon IT Services Pvt.Ltd.
B6: ='04-22Master'!F7 -> 0 | E6: ='04-22Master'!AK6 -> Siri Mansion LIGB 436 Dr.A S Rao Nagar,Hyderabad
A7: Nature and Location of Work: | D7: ='04-22Master'!F8 -> IT SUPPORTIVE SERVICES & BANGALORE STP | E7: Name and address of principal employer:
E8: ='04-22Master'!AK10 -> INFOSYS LTD.IL Bangalore STP Park - I
E9: ='04-22Master'!AK11 -> No.45&46,3rd Cross,Electronic City,BANGALORE,KARNATAKA
A11: S.No | B11: Name of workman | C11: Father's / Husband's Name | D11: Designation / Nature of employment | E11: Act/Omission for which fine imposed | F11: Date of offence | G11: Whether workman showed cause against fine | H11: Name of person in whose presence employee's explanation was heard | I11: Wage-period and wge payable | J11: Amount of fine Imposed | K11: Date on which fine realised | L11: Remarks
A13: 1 | B13: 2 | C13: 3 | D13: 4 | E13: 5 | F13: 6 | G13: 7 | H13: 8 | I13: 9 | J13: 10 | K13: 11 | L13: 12
B16: NO EMPLOYEE WAS IMPOSED FINESFOR THE MONTH OF | H16: ='04-22Master'!D10 -> 44652
F37: Signature of the Contractor with Seal

Sheet Advances
A1: FORM XXII- REGISTER OF ADVANCES
A3: (Vide Rule 78(1) (a) (i) of Contract Labour (Regulation and Abolition) Central /Karnataka Rules 1974
A4: Name and address of Contractor: | D4: ='04-22Master'!F5 -> Burgeon IT Services Pvt.Ltd. | E4: Name and address of the establishment in / under which contract is carried on:
B5: ='04-22Master'!F6 -> Siri Mansion LIGB 436 Dr.A S Rao Nagar,Hyderabad | E5: ='04-22Master'!AK5 -> Burgeon IT Services Pvt.Ltd.
B6: ='04-22Master'!F7 -> 0 | E6: ='04-22Master'!AK6 -> Siri Mansion LIGB 436 Dr.A S Rao Nagar,Hyderabad
A7: Nature and Location of Work: | D7: ='04-22Master'!F8 -> IT SUPPORTIVE SERVICES & BANGALORE STP | E7: Name and address of principal employer:
E8: ='04-22Master'!AK10 -> INFOSYS LTD.IL Bangalore STP Park - I
E9: ='04-22Master'!AK11 -> No.45&46,3rd Cross,Electronic City,BANGALORE,KARNATAKA
A11: S.No | B11: Name of workman | C11: Father's / Husband's Name | D11: Designation / Nature of employment | E11: Wage period and wages payable | F11: Date and amount of advance given | G11: Purpose(s) for which advance made | H11: Number of instalments by which advance to be repaid | I11: Date and amount of each instalment repaid | J11: Date on which last instalment was repaid | K11: Remarks
A13: 1 | B13: 2 | C13: 3 | D13: 4 | E13: 5 | F13: 6 | G13: 7 | H13: 8 | I13: 9 | J13: 10 | K13: 11
B16: NO EMPLOYEE TAKEN ADVANCE FOR THE MONTH OF | F16: ='04-22Master'!D10 -> 44652
G41: Signature of the Contractor with Seal

Sheet Overtime
A1: FORM XXIII- REGISTER OF OVERTIME
A3: (Vide Rule 78(1) (a) (i) of Contract Labour (Regulation and Abolition) Central /Karnataka Rules 1974
A4: Name and address of Contractor: GROTECH LANDSCAPE DEVELOPERS PVT.LTD. E-35 GREATER KAILASH ENCLAVE-1 NEW DELHI | D4: ='04-22Master'!F5 -> Burgeon IT Services Pvt.Ltd. | F4: Name and address of the establishment in which under contract is carried on:
B5: ='04-22Master'!F6 -> Siri Mansion LIGB 436 Dr.A S Rao Nagar,Hyderabad | F5: ='04-22Master'!AK5 -> Burgeon IT Services Pvt.Ltd.
B6: ='04-22Master'!F7 -> 0 | F6: ='04-22Master'!AK6 -> Siri Mansion LIGB 436 Dr.A S Rao Nagar,Hyderabad
A7: Nature and Location of Work: | D7: ='04-22Master'!F8 -> IT SUPPORTIVE SERVICES & BANGALORE STP | F7: Name and address of principal employer:
F8: ='04-22Master'!AK10 -> INFOSYS LTD.IL Bangalore STP Park - I
F9: ='04-22Master'!AK11 -> No.45&46,3rd Cross,Electronic City,BANGALORE,KARNATAKA
A11: S.No | B11: Name of workman | C11: Father's / Husband's Name | D11: Sex | E11: Designation / Nature of employment | F11: Date on which overtime worked | G11: Total overtime worked or production in case of piece-rates | H11: Normal rate of wages | I11: Overtime rate of wages | J11: overtime earnings | K11: Date on which overtime wages paid | L11: Remarks
A13: 1 | B13: 2 | C13: 3 | D13: 4 | E13: 5 | F13: 6 | G13: 7 | H13: 8 | I13: 9 | J13: 10 | K13: 11 | L13: 12
B16: NO EMPLOYEE DONE OVERTIME FOR THE MONTH OF | F16: ='04-22Master'!D10 -> 44652
H38: Signature of the Contractor with Seal

Sheet Accident
A1: FORM 11
A3: ACCIDENT BOOK
A4: EMPLOYEE STATE INSURANCE CORPORATION
B5: (Regulation 66)
A7: S.No | B7: Date of Notice | C7: Time of Notice | D7: Name and Address of the Injured Person | E7: Sex | F7: Age | H7: Shift,Department and occupation of employee | I7: Details of Injury | P7: Signature and designation of the person who makes the entry in the accident book | Q7: Name,address and occupation of the two witnesses | R7: Remarks if any
G8: Insurance Number | N8: What exactly was the injured person doing at the time of accident | O8: Name,Occupation,address and signature or the thumb impression of the person(s) giving notice
I9: Cause | J9: Nature | K9: Date | L9: Time | M9: Place
A10: 1 | B10: 2 | C10: 3 | D10: 4 | E10: 5 | F10: 6 | G10: 7 | H10: 8 | I10: 9 | J10: 10 | K10: 11 | L10: 12 | M10: 13 | N10: 14 | O10: 15 | P10: 16 | Q10: 17 | R10: 18
B12: NO ACCIDENT OCCURRED FOR THE MONTH OF | F12: ='04-22Master'!D10 -> 44652
J27: Signature of the Contractor with Seal

Sheet FORM A
B1: FORM A
B2: [See Rule 3 of Maternity Act Rules, 1965]
B3: MUSTER ROLL
B4: Name of [mine or circus]: | D4: ='04-22Master'!F5 -> Burgeon IT Services Pvt.Ltd. | E4: ='04-22Master'!F6 -> Siri Mansion LIGB 436 Dr.A S Rao Nagar,Hyderabad
B5: 1 | C5: Serial Number.
B6: 2 | C6: Name of woman and her father's (or, if married, husband's) name.
B7: 3 | C7: Date of appointment.
B8: 4 | C8: Nature of work.
B9: 5 | C9: Dates with month and year in which she is employed, laid off and not employed.
C10: Month | D10: No.of days employed | E10: No.of days laid off | F10: No.of days not employed | G10: Remarks
B17: 6 | C17: Date on which the woman gives notice under section 6.
B18: 7 | C18: Date of discharge/dismissal, if any.
B19: 8 | C19: Date of production of proof of pregnancy under section 6.
B20: 9 | C20: Date of birth of child.
B21: 10 | C21: Date of production of proof of delivery/miscarriage/ 1[Medical Termination of pregnancy/ tubectomy operation/death.]
B22: 11 | C22: Date of production of proof of illness referred to in section 10.
B23: 12 | C23: Date with the amount of maternity benefit paid in advance of expected delivery.
B24: 13 | C24: Date with the amount of subsequent payment of maternity benefit.
B25: 14 | C25: Date with the amount of bonus, if paid, under section 8.
B26: 15 | C26: Date with the amount of wages paid on account of leave under section 9.
B27: 15A | C27: Date with the amount of wages paid on account of leave under section 9A
B28: 16 | C28: Date with the amount of wages paid on account of leave under section 10 and period of leave granted
B29: 17 | C29: Name of the person nominated by the woman under section 6.
B30: 18 | C30: If the woman dies, the date of her death, the name of the person to whom maternity benefit and/or other amount was paid, the amount thereof, and the date of payment.
B31: 19 | C31: If the woman dies and the child survives, the name of the person to whom the amount of maternity benefit was paid on behalf of the child and the period for which it was paid.
B32: 20 | C32: Signature of the employer of 3[the mine or circus] authenticating the entries in the muster-roll.
B33: 21 | C33: Remarks column for the use of the Inspector.
B34: Certifited that no pregnant employee worked for the month of | G34: =[6]Master!F10 -> 44287
E36: For | F36: ='04-22Master'!F5 -> Burgeon IT Services Pvt.Ltd.
F38: Authorized Signatory

Sheet FORM B
B1: FORM B
B2: [See Rule 4(1) of Maternity Act Rules, 1965]
B3: Name of [mine or circus]: | D3: ='04-22Master'!F5 -> Burgeon IT Services Pvt.Ltd. | E3: ='04-22Master'!F6 -> Siri Mansion LIGB 436 Dr.A S Rao Nagar,Hyderabad
B6: This is to certify that I examined…. wife /daughter of ….. a woman employee in name of Mine or Circus on (Date)
D7: and found/ cannot discover that she is pregnant and is expected to be delivered of a child within (month/days) from the above
B8: mentioned date date/has undergone miscarriage/[Medical termination of pregnancy or tubectomy operation]/has been delivered
B9: of a child on….. (date) or is suffering from…..(date) from illness arising out of pregnancy/delivery/premature birth of a child or miscarriage/
B10: [Medical termination of pregnancy or tubectomy operation ].
